{
  "type": "Feature",
  "properties": {
    "gn:admin1_code":"8.0",
    "gn:admin2_code":"11049284.0",
    "gn:asciiname":"Blazani",
    "gn:country_code":"HR",
    "gn:dem":460,
    "gn:feature_class":"P",
    "gn:feature_code":"PPL",
    "gn:name":"Bla\u017eani",
    "gn:population":0,
    "gn:timezone":"Europe/Zagreb",
    "iso:country":"HR",
    "wof:name":"Blazani",
    "wof:placetype":"locality"
},
  "geometry": {"coordinates":[15.10611,44.98806],"type":"Point"}
}