{
  "type": "Feature",
  "properties": {
    "gn:admin1_code":"19.0",
    "gn:asciiname":"Tulic",
    "gn:cc2":"HR",
    "gn:country_code":"HR",
    "gn:dem":831,
    "gn:feature_class":"P",
    "gn:feature_code":"PPLL",
    "gn:name":"Tuli\u0107",
    "gn:population":0,
    "gn:timezone":"Europe/Zagreb",
    "iso:country":"HR",
    "name:und_x_variant":[
        "Tuli\u0107i",
        "Tuli\u0107"
    ],
    "wof:name":"Tulic",
    "wof:placetype":"locality"
},
  "geometry": {"coordinates":[15.94139,44.46389],"type":"Point"}
}