{
  "type": "Feature",
  "properties": {
    "gn:admin1_code":"7.0",
    "gn:admin2_code":"11049191.0",
    "gn:asciiname":"Lobor",
    "gn:country_code":"HR",
    "gn:dem":271,
    "gn:feature_class":"P",
    "gn:feature_code":"PPL",
    "gn:name":"Lobor",
    "gn:population":521,
    "gn:timezone":"Europe/Zagreb",
    "iso:country":"HR",
    "name:bos_x_preferred":[
        "Lobor"
    ],
    "name:deu_x_preferred":[
        "Lobor"
    ],
    "name:fra_x_preferred":[
        "Lobor"
    ],
    "name:hrv_x_preferred":[
        "Lobor"
    ],
    "name:hun_x_preferred":[
        "Lobor"
    ],
    "name:ita_x_preferred":[
        "Lobor"
    ],
    "name:nld_x_preferred":[
        "Lobor"
    ],
    "name:pol_x_preferred":[
        "Gmina Lobor"
    ],
    "name:ron_x_preferred":[
        "Comuna Lobor"
    ],
    "name:rus_x_preferred":[
        "\u041b\u043e\u0431\u043e\u0440"
    ],
    "name:slv_x_preferred":[
        "Lobor"
    ],
    "name:spa_x_preferred":[
        "Lobor"
    ],
    "name:srp_x_preferred":[
        "\u041b\u043e\u0431\u043e\u0440"
    ],
    "name:ukr_x_preferred":[
        "\u041b\u043e\u0431\u043e\u0440"
    ],
    "name:war_x_preferred":[
        "Lobor"
    ],
    "wof:name":"Lobor",
    "wof:placetype":"locality",
    "wof:population":521
},
  "geometry": {"coordinates":[16.05889,46.14861],"type":"Point"}
}