{
  "type": "Feature",
  "properties": {
    "gn:admin1_code":"7.0",
    "gn:admin2_code":"11049191.0",
    "gn:asciiname":"Lobor",
    "gn:country_code":"HR",
    "gn:dem":271,
    "gn:feature_class":"P",
    "gn:feature_code":"PPL",
    "gn:name":"Lobor",
    "gn:population":521,
    "gn:timezone":"Europe/Zagreb",
    "iso:country":"HR",
    "wof:name":"Lobor",
    "wof:placetype":"locality",
    "wof:population":521
},
  "geometry": {"coordinates":[16.05889,46.14861],"type":"Point"}
}