{
  "type": "Feature",
  "properties": {
    "gn:admin1_code":"19.0",
    "gn:asciiname":"Obradovici",
    "gn:country_code":"HR",
    "gn:dem":738,
    "gn:feature_class":"P",
    "gn:feature_code":"PPL",
    "gn:name":"Obradovi\u0107i",
    "gn:population":0,
    "gn:timezone":"Europe/Zagreb",
    "iso:country":"HR",
    "wof:name":"Obradovici",
    "wof:placetype":"locality"
},
  "geometry": {"coordinates":[15.85222,44.4325],"type":"Point"}
}