{
  "type": "Feature",
  "properties": {
    "gn:admin1_code":"7.0",
    "gn:admin2_code":"11049222.0",
    "gn:asciiname":"Zlatar bistrica",
    "gn:country_code":"HR",
    "gn:dem":164,
    "gn:feature_class":"P",
    "gn:feature_code":"PPL",
    "gn:name":"Zlatar bistrica",
    "gn:population":0,
    "gn:timezone":"Europe/Zagreb",
    "iso:country":"HR",
    "wof:name":"Zlatar bistrica",
    "wof:placetype":"locality"
},
  "geometry": {"coordinates":[16.08611,46.04972],"type":"Point"}
}