{
  "type": "Feature",
  "properties": {
    "gn:admin1_code":"3.0",
    "gn:admin2_code":"11054972.0",
    "gn:asciiname":"Pende",
    "gn:country_code":"HR",
    "gn:dem":166,
    "gn:feature_class":"P",
    "gn:feature_code":"PPL",
    "gn:name":"Pende",
    "gn:population":0,
    "gn:timezone":"Europe/Zagreb",
    "iso:country":"HR",
    "name:ceb_x_preferred":[
        "Pend\u00e9"
    ],
    "name:deu_x_preferred":[
        "Pend\u00e9"
    ],
    "name:fra_x_preferred":[
        "Pend\u00e9"
    ],
    "name:ita_x_preferred":[
        "Pend\u00e9"
    ],
    "name:nds_x_preferred":[
        "Pende"
    ],
    "name:nld_x_preferred":[
        "Pende"
    ],
    "name:swe_x_preferred":[
        "Pende"
    ],
    "wof:name":"Pende",
    "wof:placetype":"locality"
},
  "geometry": {"coordinates":[18.24167000000001,42.56778],"type":"Point"}
}