{
  "type": "Feature",
  "properties": {
    "gn:admin1_code":"14",
    "gn:admin2_code":"3193419.0",
    "gn:asciiname":"Gornja Bacuga",
    "gn:country_code":"HR",
    "gn:dem":273,
    "gn:feature_class":"P",
    "gn:feature_code":"PPL",
    "gn:name":"Gornja Ba\u010duga",
    "gn:population":79,
    "gn:timezone":"Europe/Zagreb",
    "iso:country":"HR",
    "wof:name":"Gornja Bacuga",
    "wof:placetype":"locality",
    "wof:population":79
},
  "geometry": {"coordinates":[16.26492,45.37711],"type":"Point"}
}