{
  "type": "Feature",
  "properties": {
    "gn:admin1_code":"12.0",
    "gn:asciiname":"Grmani",
    "gn:cc2":"HR",
    "gn:country_code":"HR",
    "gn:dem":163,
    "gn:feature_class":"P",
    "gn:feature_code":"PPL",
    "gn:name":"Grmani",
    "gn:population":0,
    "gn:timezone":"Europe/Zagreb",
    "iso:country":"HR",
    "name:und_x_variant":[
        "Germanska",
        "Grmani"
    ],
    "wof:name":"Grmani",
    "wof:placetype":"locality"
},
  "geometry": {"coordinates":[14.60972,45.24389],"type":"Point"}
}