{
  "type": "Feature",
  "properties": {
    "gn:admin1_code":"13.0",
    "gn:asciiname":"Polje",
    "gn:country_code":"HR",
    "gn:dem":248,
    "gn:feature_class":"P",
    "gn:feature_code":"PPL",
    "gn:name":"Polje",
    "gn:population":0,
    "gn:timezone":"Europe/Zagreb",
    "iso:country":"HR",
    "wof:name":"Polje",
    "wof:placetype":"locality"
},
  "geometry": {"coordinates":[16.20222,44.00194000000001],"type":"Point"}
}