{
  "type": "Feature",
  "properties": {
    "gn:admin1_code":"11",
    "gn:admin2_code":"11049473.0",
    "gn:asciiname":"Stojcinovac",
    "gn:country_code":"HR",
    "gn:dem":214,
    "gn:feature_class":"P",
    "gn:feature_code":"PPL",
    "gn:name":"Stoj\u010dinovac",
    "gn:population":4,
    "gn:timezone":"Europe/Zagreb",
    "iso:country":"HR",
    "wof:name":"Stojcinovac",
    "wof:placetype":"locality",
    "wof:population":4
},
  "geometry": {"coordinates":[18.08278,45.39167],"type":"Point"}
}