{
  "type": "Feature",
  "properties": {
    "gn:admin1_code":"11",
    "gn:admin2_code":"11049478.0",
    "gn:asciiname":"Buk",
    "gn:country_code":"HR",
    "gn:dem":162,
    "gn:feature_class":"P",
    "gn:feature_code":"PPL",
    "gn:name":"Buk",
    "gn:population":192,
    "gn:timezone":"Europe/Zagreb",
    "iso:country":"HR",
    "name:bel_x_preferred":[
        "\u0411\u0443\u043a"
    ],
    "name:ceb_x_preferred":[
        "Buk"
    ],
    "name:deu_x_preferred":[
        "Buk"
    ],
    "name:epo_x_preferred":[
        "Buk"
    ],
    "name:est_x_preferred":[
        "Buk"
    ],
    "name:fra_x_preferred":[
        "Buk"
    ],
    "name:jav_x_preferred":[
        "Buk"
    ],
    "name:lav_x_preferred":[
        "Buka"
    ],
    "name:msa_x_preferred":[
        "Buk"
    ],
    "name:nld_x_preferred":[
        "Buk"
    ],
    "name:pol_x_preferred":[
        "Buk"
    ],
    "name:por_x_preferred":[
        "Buk"
    ],
    "name:ron_x_preferred":[
        "Buk"
    ],
    "name:rus_x_preferred":[
        "\u0411\u0443\u043a"
    ],
    "name:srp_x_preferred":[
        "\u0411\u0443\u043a"
    ],
    "name:szl_x_preferred":[
        "Buk"
    ],
    "name:ukr_x_preferred":[
        "\u0411\u0443\u043a"
    ],
    "name:vie_x_preferred":[
        "Buk"
    ],
    "wof:name":"Buk",
    "wof:placetype":"locality",
    "wof:population":192
},
  "geometry": {"coordinates":[17.86111,45.29972],"type":"Point"}
}