{
  "type": "Feature",
  "properties": {
    "gn:admin1_code":"20",
    "gn:admin2_code":"11048994.0",
    "gn:asciiname":"Gornji Prnjarovec",
    "gn:cc2":"HR",
    "gn:country_code":"HR",
    "gn:dem":108,
    "gn:feature_class":"P",
    "gn:feature_code":"PPL",
    "gn:name":"Gornji Prnjarovec",
    "gn:population":369,
    "gn:timezone":"Europe/Zagreb",
    "iso:country":"HR",
    "name:und_x_variant":[
        "Gornji Prnjarovac",
        "Gornji Prnjarovec"
    ],
    "wof:name":"Gornji Prnjarovec",
    "wof:placetype":"locality",
    "wof:population":369
},
  "geometry": {"coordinates":[16.53333,45.68333],"type":"Point"}
}