{
  "type": "Feature",
  "properties": {
    "gn:admin1_code":"20",
    "gn:asciiname":"Novaki Ravenski",
    "gn:cc2":"HR",
    "gn:country_code":"HR",
    "gn:dem":127,
    "gn:feature_class":"P",
    "gn:feature_code":"PPL",
    "gn:name":"Novaki Ravenski",
    "gn:population":0,
    "gn:timezone":"Europe/Zagreb",
    "iso:country":"HR",
    "name:und_x_variant":[
        "Ravenski Novaki",
        "Novaki",
        "Novaki Ravenski"
    ],
    "wof:name":"Novaki Ravenski",
    "wof:placetype":"locality"
},
  "geometry": {"coordinates":[16.48333,45.95],"type":"Point"}
}