{
  "type": "Feature",
  "properties": {
    "gn:admin1_code":"17",
    "gn:admin2_code":"11049468.0",
    "gn:asciiname":"Oresac",
    "gn:country_code":"HR",
    "gn:dem":102,
    "gn:feature_class":"P",
    "gn:feature_code":"PPL",
    "gn:name":"Ore\u0161ac",
    "gn:population":389,
    "gn:timezone":"Europe/Zagreb",
    "iso:country":"HR",
    "wof:name":"Oresac",
    "wof:placetype":"locality",
    "wof:population":389
},
  "geometry": {"coordinates":[17.58111,45.81361],"type":"Point"}
}