{
  "type": "Feature",
  "properties": {
    "gn:admin1_code":"8.0",
    "gn:admin2_code":"11049287.0",
    "gn:asciiname":"Marasi",
    "gn:country_code":"HR",
    "gn:dem":712,
    "gn:feature_class":"P",
    "gn:feature_code":"PPL",
    "gn:name":"Marasi",
    "gn:population":0,
    "gn:timezone":"Europe/Zagreb",
    "iso:country":"HR",
    "wof:name":"Marasi",
    "wof:placetype":"locality"
},
  "geometry": {"coordinates":[15.28944,44.39722],"type":"Point"}
}