{
  "type": "Feature",
  "properties": {
    "gn:admin1_code":"14.0",
    "gn:admin2_code":"3200915.0",
    "gn:asciiname":"Rijecani Bujinjski",
    "gn:country_code":"HR",
    "gn:dem":221,
    "gn:feature_class":"P",
    "gn:feature_code":"PPL",
    "gn:name":"Rije\u010dani Bujinjski",
    "gn:population":0,
    "gn:timezone":"Europe/Zagreb",
    "iso:country":"HR",
    "wof:name":"Rijecani Bujinjski",
    "wof:placetype":"locality"
},
  "geometry": {"coordinates":[16.40694,45.18667],"type":"Point"}
}