{
  "type": "Feature",
  "properties": {
    "gn:admin1_code":"19.0",
    "gn:asciiname":"Bukarica",
    "gn:country_code":"HR",
    "gn:dem":87,
    "gn:feature_class":"P",
    "gn:feature_code":"PPL",
    "gn:name":"Bukarica",
    "gn:population":0,
    "gn:timezone":"Europe/Zagreb",
    "iso:country":"HR",
    "wof:name":"Bukarica",
    "wof:placetype":"locality"
},
  "geometry": {"coordinates":[15.36111,44.18972],"type":"Point"}
}