{
  "type": "Feature",
  "properties": {
    "gn:admin1_code":"13.0",
    "gn:asciiname":"Validzici",
    "gn:country_code":"HR",
    "gn:dem":254,
    "gn:feature_class":"P",
    "gn:feature_code":"PPL",
    "gn:name":"Valid\u017ei\u0107i",
    "gn:population":0,
    "gn:timezone":"Europe/Zagreb",
    "iso:country":"HR",
    "wof:name":"Validzici",
    "wof:placetype":"locality"
},
  "geometry": {"coordinates":[16.04583,43.92389],"type":"Point"}
}