{
  "type": "Feature",
  "properties": {
    "gn:admin1_code":"14",
    "gn:admin2_code":"3200597.0",
    "gn:asciiname":"Gornje Seliste",
    "gn:country_code":"HR",
    "gn:dem":131,
    "gn:feature_class":"P",
    "gn:feature_code":"PPL",
    "gn:name":"Gornje Seli\u0161te",
    "gn:population":55,
    "gn:timezone":"Europe/Zagreb",
    "iso:country":"HR",
    "wof:name":"Gornje Seliste",
    "wof:placetype":"locality",
    "wof:population":55
},
  "geometry": {"coordinates":[16.06222,45.31806],"type":"Point"}
}