{
  "type": "Feature",
  "properties": {
    "gn:admin1_code":"19.0",
    "gn:asciiname":"Medic",
    "gn:country_code":"HR",
    "gn:dem":344,
    "gn:feature_class":"P",
    "gn:feature_code":"PPL",
    "gn:name":"Medi\u0107",
    "gn:population":0,
    "gn:timezone":"Europe/Zagreb",
    "iso:country":"HR",
    "wof:name":"Medic",
    "wof:placetype":"locality"
},
  "geometry": {"coordinates":[15.81917,44.05833],"type":"Point"}
}