{
  "type": "Feature",
  "properties": {
    "gn:admin1_code":"19.0",
    "gn:asciiname":"Medic",
    "gn:country_code":"HR",
    "gn:dem":344,
    "gn:feature_class":"P",
    "gn:feature_code":"PPL",
    "gn:name":"Medi\u0107",
    "gn:population":0,
    "gn:timezone":"Europe/Zagreb",
    "iso:country":"HR",
    "name:ces_x_preferred":[
        "Medik"
    ],
    "name:jpn_x_preferred":[
        "\u30e1\u30c7\u30a3\u30c3\u30af"
    ],
    "name:mkd_x_preferred":[
        "\u041c\u0435\u0434\u0438\u0446\u0438\u043d\u0430\u0440"
    ],
    "name:swe_x_preferred":[
        "Sjukv\u00e5rdare"
    ],
    "wof:name":"Medic",
    "wof:placetype":"locality"
},
  "geometry": {"coordinates":[15.81917,44.05833],"type":"Point"}
}