{
  "type": "Feature",
  "properties": {
    "gn:admin1_code":"18.0",
    "gn:asciiname":"Zivacine",
    "gn:country_code":"HR",
    "gn:dem":79,
    "gn:feature_class":"P",
    "gn:feature_code":"PPL",
    "gn:name":"\u017diva\u010dine",
    "gn:population":0,
    "gn:timezone":"Europe/Zagreb",
    "iso:country":"HR",
    "wof:name":"Zivacine",
    "wof:placetype":"locality"
},
  "geometry": {"coordinates":[18.84722,45.095],"type":"Point"}
}