{
  "type": "Feature",
  "properties": {
    "gn:admin1_code":"05",
    "gn:admin2_code":"11049275.0",
    "gn:asciiname":"Lasinja",
    "gn:country_code":"HR",
    "gn:dem":140,
    "gn:feature_class":"P",
    "gn:feature_code":"PPLA2",
    "gn:name":"Lasinja",
    "gn:population":0,
    "gn:timezone":"Europe/Zagreb",
    "iso:country":"HR",
    "name:bos_x_preferred":[
        "Lasinja"
    ],
    "name:cat_x_preferred":[
        "Lasinja"
    ],
    "name:deu_x_preferred":[
        "Lasinja"
    ],
    "name:fra_x_preferred":[
        "Lasinja"
    ],
    "name:hrv_x_preferred":[
        "Lasinja"
    ],
    "name:hun_x_preferred":[
        "Lasinja"
    ],
    "name:ita_x_preferred":[
        "Lasinja"
    ],
    "name:nld_x_preferred":[
        "Lasinja"
    ],
    "name:pol_x_preferred":[
        "Gmina Lasinja"
    ],
    "name:ron_x_preferred":[
        "Comuna Lasinja"
    ],
    "name:slv_x_preferred":[
        "Lasinja"
    ],
    "name:spa_x_preferred":[
        "Lasinja"
    ],
    "name:srp_x_preferred":[
        "\u041b\u0430\u0441\u0438\u045a\u0430"
    ],
    "name:ukr_x_preferred":[
        "\u041b\u0430\u0441\u0438\u043d\u044f"
    ],
    "name:war_x_preferred":[
        "Lasinja"
    ],
    "wof:name":"Lasinja",
    "wof:placetype":"locality"
},
  "geometry": {"coordinates":[15.85911,45.52806],"type":"Point"}
}