{
  "type": "Feature",
  "properties": {
    "gn:admin1_code":"05",
    "gn:admin2_code":"11049275.0",
    "gn:asciiname":"Lasinja",
    "gn:country_code":"HR",
    "gn:dem":140,
    "gn:feature_class":"P",
    "gn:feature_code":"PPLA2",
    "gn:name":"Lasinja",
    "gn:population":0,
    "gn:timezone":"Europe/Zagreb",
    "iso:country":"HR",
    "wof:name":"Lasinja",
    "wof:placetype":"locality"
},
  "geometry": {"coordinates":[15.85911,45.52806],"type":"Point"}
}