{
  "type": "Feature",
  "properties": {
    "gn:admin1_code":"15.0",
    "gn:asciiname":"Polje",
    "gn:cc2":"HR",
    "gn:country_code":"HR",
    "gn:dem":103,
    "gn:feature_class":"P",
    "gn:feature_code":"PPL",
    "gn:name":"Polje",
    "gn:population":0,
    "gn:timezone":"Europe/Zagreb",
    "iso:country":"HR",
    "name:und_x_variant":[
        "Potok",
        "Polje"
    ],
    "wof:name":"Polje",
    "wof:placetype":"locality"
},
  "geometry": {"coordinates":[16.00944,42.97222],"type":"Point"}
}