{
  "type": "Feature",
  "properties": {
    "gn:admin1_code":"15.0",
    "gn:asciiname":"Setka",
    "gn:country_code":"HR",
    "gn:dem":524,
    "gn:feature_class":"P",
    "gn:feature_code":"PPL",
    "gn:name":"\u0160etka",
    "gn:population":0,
    "gn:timezone":"Europe/Zagreb",
    "iso:country":"HR",
    "wof:name":"Setka",
    "wof:placetype":"locality"
},
  "geometry": {"coordinates":[16.87083,43.54083],"type":"Point"}
}