{
  "type": "Feature",
  "properties": {
    "gn:admin1_code":"15.0",
    "gn:asciiname":"Jerkovic",
    "gn:country_code":"HR",
    "gn:dem":365,
    "gn:feature_class":"P",
    "gn:feature_code":"PPL",
    "gn:name":"Jerkovi\u0107",
    "gn:population":0,
    "gn:timezone":"Europe/Zagreb",
    "iso:country":"HR",
    "wof:name":"Jerkovic",
    "wof:placetype":"locality"
},
  "geometry": {"coordinates":[16.71027999999999,43.60361],"type":"Point"}
}