{
  "type": "Feature",
  "properties": {
    "gn:admin1_code":"11",
    "gn:admin2_code":"11049473.0",
    "gn:asciiname":"Mokres",
    "gn:country_code":"HR",
    "gn:dem":154,
    "gn:feature_class":"P",
    "gn:feature_code":"PPL",
    "gn:name":"Mokre\u0161",
    "gn:population":20,
    "gn:timezone":"Europe/Zagreb",
    "iso:country":"HR",
    "wof:name":"Mokres",
    "wof:placetype":"locality",
    "wof:population":20
},
  "geometry": {"coordinates":[18.08833,45.3775],"type":"Point"}
}