{
  "type": "Feature",
  "properties": {
    "gn:admin1_code":"04",
    "gn:admin2_code":"11129787.0",
    "gn:asciiname":"Raspor",
    "gn:cc2":"HR",
    "gn:country_code":"HR",
    "gn:dem":673,
    "gn:feature_class":"P",
    "gn:feature_code":"PPL",
    "gn:name":"Ra\u0161por",
    "gn:population":3,
    "gn:timezone":"Europe/Zagreb",
    "iso:country":"HR",
    "name:und_x_variant":[
        "Raspo",
        "Ra\u0161por"
    ],
    "wof:name":"Raspor",
    "wof:placetype":"locality",
    "wof:population":3
},
  "geometry": {"coordinates":[14.07694,45.43944000000001],"type":"Point"}
}