{
  "type": "Feature",
  "properties": {
    "gn:admin1_code":"12",
    "gn:admin2_code":"11049446.0",
    "gn:asciiname":"Brestova Draga",
    "gn:country_code":"HR",
    "gn:dem":964,
    "gn:feature_class":"P",
    "gn:feature_code":"PPL",
    "gn:name":"Brestova Draga",
    "gn:population":53,
    "gn:timezone":"Europe/Zagreb",
    "iso:country":"HR",
    "wof:name":"Brestova Draga",
    "wof:placetype":"locality",
    "wof:population":53
},
  "geometry": {"coordinates":[14.79444,45.32056],"type":"Point"}
}