{
  "type": "Feature",
  "properties": {
    "gn:admin1_code":"14.0",
    "gn:admin2_code":"3196862.0",
    "gn:asciiname":"Banova Jaruga",
    "gn:country_code":"HR",
    "gn:dem":110,
    "gn:feature_class":"P",
    "gn:feature_code":"PPL",
    "gn:name":"Banova Jaruga",
    "gn:population":665,
    "gn:timezone":"Europe/Zagreb",
    "iso:country":"HR",
    "name:bos_x_preferred":[
        "Banova Jaruga"
    ],
    "name:ceb_x_preferred":[
        "Banova Jaruga"
    ],
    "name:fra_x_preferred":[
        "Banova Jaruga"
    ],
    "name:hrv_x_preferred":[
        "Banova Jaruga"
    ],
    "name:hun_x_preferred":[
        "Banova Jaruga"
    ],
    "name:nld_x_preferred":[
        "Banova Jaruga"
    ],
    "name:slv_x_preferred":[
        "Banova Jaruga"
    ],
    "name:spa_x_preferred":[
        "Banova Jaruga"
    ],
    "name:srp_x_preferred":[
        "\u0411\u0430\u043d\u043e\u0432\u0430 \u0408\u0430\u0440\u0443\u0433\u0430"
    ],
    "name:swe_x_preferred":[
        "Banova Jaruga"
    ],
    "name:ukr_x_preferred":[
        "\u0411\u0430\u043d\u043e\u0432\u0430 \u042f\u0440\u0443\u0433\u0430"
    ],
    "wof:name":"Banova Jaruga",
    "wof:placetype":"locality",
    "wof:population":665
},
  "geometry": {"coordinates":[16.905,45.44167],"type":"Point"}
}