{
  "type": "Feature",
  "properties": {
    "gn:admin1_code":"14.0",
    "gn:admin2_code":"3196862.0",
    "gn:asciiname":"Banova Jaruga",
    "gn:country_code":"HR",
    "gn:dem":110,
    "gn:feature_class":"P",
    "gn:feature_code":"PPL",
    "gn:name":"Banova Jaruga",
    "gn:population":665,
    "gn:timezone":"Europe/Zagreb",
    "iso:country":"HR",
    "wof:name":"Banova Jaruga",
    "wof:placetype":"locality",
    "wof:population":665
},
  "geometry": {"coordinates":[16.905,45.44167],"type":"Point"}
}