{
  "type": "Feature",
  "properties": {
    "gn:admin1_code":"5.0",
    "gn:asciiname":"Mikinovac",
    "gn:country_code":"HR",
    "gn:dem":193,
    "gn:feature_class":"P",
    "gn:feature_code":"PPL",
    "gn:name":"Mikinovac",
    "gn:population":0,
    "gn:timezone":"Europe/Zagreb",
    "iso:country":"HR",
    "wof:name":"Mikinovac",
    "wof:placetype":"locality"
},
  "geometry": {"coordinates":[15.7925,45.16139],"type":"Point"}
}