{
  "type": "Feature",
  "properties": {
    "gn:admin1_code":"11.0",
    "gn:asciiname":"Blacko-Jaksic",
    "gn:country_code":"HR",
    "gn:dem":129,
    "gn:feature_class":"P",
    "gn:feature_code":"PPL",
    "gn:name":"Blacko-Jak\u0161i\u0107",
    "gn:population":0,
    "gn:timezone":"Europe/Zagreb",
    "iso:country":"HR",
    "wof:name":"Blacko-Jaksic",
    "wof:placetype":"locality"
},
  "geometry": {"coordinates":[17.75889,45.33417],"type":"Point"}
}