{
  "type": "Feature",
  "properties": {
    "gn:admin1_code":"15.0",
    "gn:asciiname":"Veroci",
    "gn:country_code":"HR",
    "gn:dem":654,
    "gn:feature_class":"P",
    "gn:feature_code":"PPL",
    "gn:name":"Vero\u0107i",
    "gn:population":0,
    "gn:timezone":"Europe/Zagreb",
    "iso:country":"HR",
    "wof:name":"Veroci",
    "wof:placetype":"locality"
},
  "geometry": {"coordinates":[16.88722000000001,43.59083],"type":"Point"}
}