{
  "type": "Feature",
  "properties": {
    "gn:admin1_code":"19",
    "gn:asciiname":"Premuda",
    "gn:country_code":"HR",
    "gn:dem":50,
    "gn:feature_class":"P",
    "gn:feature_code":"PPL",
    "gn:name":"Premuda",
    "gn:population":64,
    "gn:timezone":"Europe/Zagreb",
    "iso:country":"HR",
    "name:deu_x_preferred":[
        "Premuda"
    ],
    "name:ell_x_preferred":[
        "\u03a0\u03c1\u03ad\u03bc\u03bf\u03c5\u03bd\u03c4\u03b1"
    ],
    "name:epo_x_preferred":[
        "Premuda"
    ],
    "name:fra_x_preferred":[
        "Premuda"
    ],
    "name:hrv_x_preferred":[
        "Premuda"
    ],
    "name:ind_x_preferred":[
        "Premuda"
    ],
    "name:ita_x_preferred":[
        "Premuda"
    ],
    "name:kor_x_preferred":[
        "\ud504\ub808\ubb34\ub2e4\uc12c"
    ],
    "name:nld_x_preferred":[
        "Premuda"
    ],
    "name:nno_x_preferred":[
        "Premuda"
    ],
    "name:nor_x_preferred":[
        "Premuda"
    ],
    "name:pol_x_preferred":[
        "Premuda"
    ],
    "name:rus_x_preferred":[
        "\u041f\u0440\u0435\u043c\u0443\u0434\u0430"
    ],
    "name:slv_x_preferred":[
        "Premuda"
    ],
    "name:spa_x_preferred":[
        "Premuda"
    ],
    "name:srp_x_preferred":[
        "\u041f\u0440\u0435\u043c\u0443\u0434\u0430"
    ],
    "name:tur_x_preferred":[
        "Premuda"
    ],
    "name:ukr_x_preferred":[
        "\u041f\u0440\u0435\u043c\u0443\u0434\u0430"
    ],
    "name:zho_x_preferred":[
        "\u666e\u96f7\u7a46\u9054\u5cf6"
    ],
    "wof:name":"Premuda",
    "wof:placetype":"locality",
    "wof:population":64
},
  "geometry": {"coordinates":[14.60139,44.3425],"type":"Point"}
}