{
  "type": "Feature",
  "properties": {
    "gn:admin1_code":"19",
    "gn:asciiname":"Premuda",
    "gn:country_code":"HR",
    "gn:dem":50,
    "gn:feature_class":"P",
    "gn:feature_code":"PPL",
    "gn:name":"Premuda",
    "gn:population":64,
    "gn:timezone":"Europe/Zagreb",
    "iso:country":"HR",
    "wof:name":"Premuda",
    "wof:placetype":"locality",
    "wof:population":64
},
  "geometry": {"coordinates":[14.60139,44.3425],"type":"Point"}
}