{
  "type": "Feature",
  "properties": {
    "gn:admin1_code":"8.0",
    "gn:asciiname":"Kolaci",
    "gn:country_code":"HR",
    "gn:dem":451,
    "gn:feature_class":"P",
    "gn:feature_code":"PPL",
    "gn:name":"Kolaci",
    "gn:population":0,
    "gn:timezone":"Europe/Zagreb",
    "iso:country":"HR",
    "wof:name":"Kolaci",
    "wof:placetype":"locality"
},
  "geometry": {"coordinates":[15.33472,44.80139000000001],"type":"Point"}
}