{
  "type": "Feature",
  "properties": {
    "gn:admin1_code":"15.0",
    "gn:asciiname":"Vukovici",
    "gn:country_code":"HR",
    "gn:dem":321,
    "gn:feature_class":"P",
    "gn:feature_code":"PPL",
    "gn:name":"Vukovi\u0107i",
    "gn:population":0,
    "gn:timezone":"Europe/Zagreb",
    "iso:country":"HR",
    "wof:name":"Vukovici",
    "wof:placetype":"locality"
},
  "geometry": {"coordinates":[16.66611,43.58306],"type":"Point"}
}