{
  "type": "Feature",
  "properties": {
    "gn:admin1_code":"8.0",
    "gn:asciiname":"Krizajica",
    "gn:country_code":"HR",
    "gn:dem":584,
    "gn:feature_class":"P",
    "gn:feature_code":"PPL",
    "gn:name":"Kri\u017eajica",
    "gn:population":0,
    "gn:timezone":"Europe/Zagreb",
    "iso:country":"HR",
    "wof:name":"Krizajica",
    "wof:placetype":"locality"
},
  "geometry": {"coordinates":[15.53306,44.41556],"type":"Point"}
}