{
  "type": "Feature",
  "properties": {
    "gn:country":"HR",
    "gn:fcode":"PPL",
    "gn:population":5866,
    "iso:country":"HR",
    "name:bos_x_preferred":[
        "Stobre\u010d"
    ],
    "name:ceb_x_preferred":[
        "Stobre\u010d"
    ],
    "name:deu_x_preferred":[
        "Stobre\u010d"
    ],
    "name:eng_x_preferred":[
        "Stobre\u010d"
    ],
    "name:fra_x_preferred":[
        "Stobre\u010d"
    ],
    "name:hrv_x_preferred":[
        "Stobre\u010d"
    ],
    "name:hun_x_preferred":[
        "Stobre\u010d"
    ],
    "name:jpn_x_preferred":[
        "\u30b9\u30c8\u30d6\u30ec\u30c1"
    ],
    "name:lit_x_preferred":[
        "Stobre\u010das"
    ],
    "name:nld_x_preferred":[
        "Stobre\u010d"
    ],
    "name:por_x_preferred":[
        "Stobre\u010d"
    ],
    "name:sco_x_preferred":[
        "Stobre\u010d"
    ],
    "name:slv_x_preferred":[
        "Stobre\u010d"
    ],
    "name:spa_x_preferred":[
        "Stobre\u010d"
    ],
    "name:sqi_x_preferred":[
        "Stobre\u010d"
    ],
    "name:srp_x_preferred":[
        "\u0421\u0442\u043e\u0431\u0440\u0435\u0447"
    ],
    "name:swe_x_preferred":[
        "Stobre\u010d"
    ],
    "name:ukr_x_preferred":[
        "\u0421\u0442\u043e\u0431\u0440\u0435\u0447"
    ],
    "qs_pg:aaroncc":"HR",
    "qs_pg:gn_country":"HR",
    "qs_pg:gn_fcode":"PPL",
    "qs_pg:gn_pop":5866,
    "qs_pg:name":"Stobre\u0107",
    "qs_pg:name_adm0":"Hrvatska",
    "qs_pg:name_adm1":"Splitsko-Dalmatinska",
    "qs_pg:photos":218,
    "qs_pg:photos_1k":44,
    "qs_pg:photos_9k":1,
    "qs_pg:photos_9r":4,
    "qs_pg:photos_all":218,
    "qs_pg:photos_sr":4,
    "qs_pg:pop_sr":5,
    "qs_pg:qs_pg_placetype":"locality",
    "qs_pg:qs_pg_placetype_gp":"Town",
    "qs_pg:woe_adm0":23424843,
    "woe:adm0_id":23424843,
    "woe:name_adm0":"Hrvatska",
    "woe:name_adm1":"Splitsko-Dalmatinska",
    "woe:placetype":"Town",
    "wof:name":"Stobre\u0107",
    "wof:placetype":"locality",
    "wof:population":2978
},
  "geometry": {"coordinates":[16.52222,43.5025],"type":"Point"}
}