{
  "type": "Feature",
  "properties": {
    "gn:admin1_code":"3.0",
    "gn:asciiname":"Mlini",
    "gn:country_code":"HR",
    "gn:dem":33,
    "gn:feature_class":"P",
    "gn:feature_code":"PPL",
    "gn:name":"Mlini",
    "gn:population":0,
    "gn:timezone":"Europe/Zagreb",
    "iso:country":"HR",
    "wof:name":"Mlini",
    "wof:placetype":"locality"
},
  "geometry": {"coordinates":[18.13833,42.675],"type":"Point"}
}