{
  "type": "Feature",
  "properties": {
    "gn:admin1_code":"3.0",
    "gn:asciiname":"Mlini",
    "gn:country_code":"HR",
    "gn:dem":33,
    "gn:feature_class":"P",
    "gn:feature_code":"PPL",
    "gn:name":"Mlini",
    "gn:population":0,
    "gn:timezone":"Europe/Zagreb",
    "iso:country":"HR",
    "name:bos_x_preferred":[
        "Mlini"
    ],
    "name:ceb_x_preferred":[
        "Mlini"
    ],
    "name:fra_x_preferred":[
        "Mlini"
    ],
    "name:hrv_x_preferred":[
        "Mlini"
    ],
    "name:hun_x_preferred":[
        "Mlini"
    ],
    "name:slv_x_preferred":[
        "Mlini"
    ],
    "name:srp_x_preferred":[
        "\u041c\u043b\u0438\u043d\u0438"
    ],
    "name:swe_x_preferred":[
        "Mlini"
    ],
    "name:ukr_x_preferred":[
        "\u041c\u043b\u0438\u043d\u0438"
    ],
    "wof:name":"Mlini",
    "wof:placetype":"locality"
},
  "geometry": {"coordinates":[18.13833,42.675],"type":"Point"}
}