{
  "type": "Feature",
  "properties": {
    "gn:admin1_code":"5.0",
    "gn:admin2_code":"3190522.0",
    "gn:asciiname":"Stojmeric",
    "gn:country_code":"HR",
    "gn:dem":266,
    "gn:feature_class":"P",
    "gn:feature_code":"PPL",
    "gn:name":"Stojmeri\u0107",
    "gn:population":3,
    "gn:timezone":"Europe/Zagreb",
    "iso:country":"HR",
    "wof:name":"Stojmeric",
    "wof:placetype":"locality",
    "wof:population":3
},
  "geometry": {"coordinates":[15.60889,45.20278],"type":"Point"}
}