{
  "type": "Feature",
  "properties": {
    "gn:admin1_code":"8.0",
    "gn:asciiname":"Gavran",
    "gn:country_code":"HR",
    "gn:dem":214,
    "gn:feature_class":"P",
    "gn:feature_code":"PPL",
    "gn:name":"Gavran",
    "gn:population":0,
    "gn:timezone":"Europe/Zagreb",
    "iso:country":"HR",
    "name:azb_x_preferred":[
        "\u06af\u0627\u0631\u0648\u0627\u0646\u062e"
    ],
    "name:aze_x_preferred":[
        "Garvank\u0259"
    ],
    "name:ceb_x_preferred":[
        "Gavran"
    ],
    "name:fas_x_preferred":[
        "\u06af\u0627\u0648\u0631\u0627\u0646"
    ],
    "name:ita_x_preferred":[
        "Gavran"
    ],
    "name:kat_x_preferred":[
        "\u10d2\u10d0\u10e0\u10d5\u10d0\u10dc\u10e5\u10d0"
    ],
    "name:msa_x_preferred":[
        "Gavran"
    ],
    "name:swe_x_preferred":[
        "Gavran"
    ],
    "name:tur_x_preferred":[
        "Garvanke"
    ],
    "wof:name":"Gavran",
    "wof:placetype":"locality"
},
  "geometry": {"coordinates":[14.93806,44.65944],"type":"Point"}
}