{
  "type": "Feature",
  "properties": {
    "gn:admin1_code":"8.0",
    "gn:asciiname":"Gavran",
    "gn:country_code":"HR",
    "gn:dem":214,
    "gn:feature_class":"P",
    "gn:feature_code":"PPL",
    "gn:name":"Gavran",
    "gn:population":0,
    "gn:timezone":"Europe/Zagreb",
    "iso:country":"HR",
    "wof:name":"Gavran",
    "wof:placetype":"locality"
},
  "geometry": {"coordinates":[14.93806,44.65944],"type":"Point"}
}