{
  "type": "Feature",
  "properties": {
    "gn:admin1_code":"6.0",
    "gn:admin2_code":"11049378.0",
    "gn:asciiname":"Vlaistav",
    "gn:country_code":"HR",
    "gn:dem":136,
    "gn:feature_class":"P",
    "gn:feature_code":"PPL",
    "gn:name":"Vlaistav",
    "gn:population":0,
    "gn:timezone":"Europe/Zagreb",
    "iso:country":"HR",
    "wof:name":"Vlaistav",
    "wof:placetype":"locality"
},
  "geometry": {"coordinates":[16.90806,46.10861],"type":"Point"}
}