{
  "type": "Feature",
  "properties": {
    "gn:admin1_code":"14.0",
    "gn:asciiname":"Studena",
    "gn:country_code":"HR",
    "gn:dem":291,
    "gn:feature_class":"P",
    "gn:feature_code":"PPL",
    "gn:name":"Studena",
    "gn:population":0,
    "gn:timezone":"Europe/Zagreb",
    "iso:country":"HR",
    "name:bos_x_preferred":[
        "Studena"
    ],
    "name:ceb_x_preferred":[
        "Studena"
    ],
    "name:eus_x_preferred":[
        "Studena"
    ],
    "name:fra_x_preferred":[
        "Studena"
    ],
    "name:hrv_x_preferred":[
        "Studena"
    ],
    "name:slv_x_preferred":[
        "Studena"
    ],
    "name:swe_x_preferred":[
        "Studena"
    ],
    "wof:name":"Studena",
    "wof:placetype":"locality"
},
  "geometry": {"coordinates":[16.04083,45.24833],"type":"Point"}
}