{
  "type": "Feature",
  "properties": {
    "gn:admin1_code":"13",
    "gn:admin2_code":"11054521.0",
    "gn:asciiname":"Rupe",
    "gn:country_code":"HR",
    "gn:dem":165,
    "gn:feature_class":"P",
    "gn:feature_code":"PPL",
    "gn:name":"Rupe",
    "gn:population":470,
    "gn:timezone":"Europe/Zagreb",
    "iso:country":"HR",
    "name:bos_x_preferred":[
        "Rupe"
    ],
    "name:ceb_x_preferred":[
        "Rupe"
    ],
    "name:deu_x_preferred":[
        "Rupe"
    ],
    "name:nld_x_preferred":[
        "Rupe"
    ],
    "name:pol_x_preferred":[
        "Rupe"
    ],
    "name:slv_x_preferred":[
        "Rupe"
    ],
    "name:srp_x_preferred":[
        "\u0420\u0443\u043f\u0435"
    ],
    "name:swe_x_preferred":[
        "Rupe"
    ],
    "wof:name":"Rupe",
    "wof:placetype":"locality",
    "wof:population":470
},
  "geometry": {"coordinates":[15.945,43.89528],"type":"Point"}
}