{
  "type": "Feature",
  "properties": {
    "gn:gn_country":"HR",
    "gn:gn_fcode":"PPL",
    "gn:gn_pop":0,
    "gn:population":330,
    "iso:country":"HR",
    "name:bos_x_preferred":[
        "Zaostrog"
    ],
    "name:bul_x_preferred":[
        "\u0417\u0430\u043e\u0441\u0442\u0440\u043e\u0433"
    ],
    "name:cze_x_preferred":[
        "Zaostrog"
    ],
    "name:dut_x_preferred":[
        "Zaostrog"
    ],
    "name:eng_x_preferred":[
        "Zaostrog"
    ],
    "name:fre_x_preferred":[
        "Zaostrog"
    ],
    "name:ger_x_preferred":[
        "Zaostrog"
    ],
    "name:hrv_x_preferred":[
        "Zaostrog"
    ],
    "name:hun_x_preferred":[
        "Zaostrog"
    ],
    "name:slv_x_preferred":[
        "Zaostrog"
    ],
    "name:srp_x_preferred":[
        "\u0417\u0430\u043e\u0441\u0442\u0440\u043e\u0433"
    ],
    "name:swe_x_preferred":[
        "Zaostrog"
    ],
    "name:unk_x_variant":[
        "Rastozza"
    ],
    "qs_pg:aaroncc":"HR",
    "qs_pg:gn_country":"HR",
    "qs_pg:gn_fcode":"PPL",
    "qs_pg:gn_pop":0,
    "qs_pg:name":"Zaostrog",
    "qs_pg:name_adm0":"Hrvatska",
    "qs_pg:name_adm1":"Splitsko-Dalmatinska",
    "qs_pg:photos":219,
    "qs_pg:photos_1k":44,
    "qs_pg:photos_9k":1,
    "qs_pg:photos_9r":4,
    "qs_pg:photos_all":219,
    "qs_pg:photos_sr":4,
    "qs_pg:pop_sr":0,
    "qs_pg:qs_pg_placetype":"locality",
    "qs_pg:qs_pg_placetype_gp":"Town",
    "qs_pg:woe_adm0":23424843,
    "woe:adm0_id":23424843,
    "woe:name_adm0":"Hrvatska",
    "woe:name_adm1":"Splitsko-Dalmatinska",
    "woe:placetype":"Town",
    "wof:name":"Zaostrog",
    "wof:placetype":"locality",
    "wof:population":330
},
  "geometry": {"coordinates":[17.28222,43.1425],"type":"Point"}
}