{
  "type": "Feature",
  "properties": {
    "gn:admin1_code":"15.0",
    "gn:asciiname":"Visak",
    "gn:country_code":"HR",
    "gn:dem":323,
    "gn:feature_class":"P",
    "gn:feature_code":"PPL",
    "gn:name":"Visak",
    "gn:population":0,
    "gn:timezone":"Europe/Zagreb",
    "iso:country":"HR",
    "wof:name":"Visak",
    "wof:placetype":"locality"
},
  "geometry": {"coordinates":[16.60139,43.50222],"type":"Point"}
}