{
  "type": "Feature",
  "properties": {
    "gn:admin1_code":"16",
    "gn:admin2_code":"11055013.0",
    "gn:asciiname":"Karlovec Ludbreski",
    "gn:cc2":"HR",
    "gn:country_code":"HR",
    "gn:dem":145,
    "gn:feature_class":"P",
    "gn:feature_code":"PPL",
    "gn:name":"Karlovec Ludbre\u0161ki",
    "gn:population":591,
    "gn:timezone":"Europe/Zagreb",
    "iso:country":"HR",
    "name:und_x_variant":[
        "Ludbre\u0161ki Karlovac",
        "Karlovec",
        "Karlovec Ludbre\u0161ki"
    ],
    "wof:name":"Karlovec Ludbreski",
    "wof:placetype":"locality",
    "wof:population":591
},
  "geometry": {"coordinates":[16.62944,46.29194],"type":"Point"}
}