{
  "type": "Feature",
  "properties": {
    "gn:admin1_code":"2.0",
    "gn:asciiname":"Pavlovci",
    "gn:country_code":"HR",
    "gn:dem":175,
    "gn:feature_class":"P",
    "gn:feature_code":"PPL",
    "gn:name":"Pavlovci",
    "gn:population":40,
    "gn:timezone":"Europe/Zagreb",
    "iso:country":"HR",
    "name:bos_x_preferred":[
        "Pavlovci"
    ],
    "name:fra_x_preferred":[
        "Pavlovci"
    ],
    "name:hrv_x_preferred":[
        "Pavlovci"
    ],
    "name:nld_x_preferred":[
        "Pavlovci"
    ],
    "name:srp_x_preferred":[
        "\u041f\u0430\u0432\u043b\u043e\u0432\u0446\u0438"
    ],
    "wof:name":"Pavlovci",
    "wof:placetype":"locality",
    "wof:population":40
},
  "geometry": {"coordinates":[17.68472000000001,45.24861],"type":"Point"}
}