{
  "type": "Feature",
  "properties": {
    "gn:admin1_code":"14.0",
    "gn:admin2_code":"11049230.0",
    "gn:asciiname":"Grabostani",
    "gn:country_code":"HR",
    "gn:dem":146,
    "gn:feature_class":"P",
    "gn:feature_code":"PPL",
    "gn:name":"Grabo\u0161tani",
    "gn:population":134,
    "gn:timezone":"Europe/Zagreb",
    "iso:country":"HR",
    "name:bos_x_preferred":[
        "Grabo\u0161tani"
    ],
    "name:ceb_x_preferred":[
        "Grabo\u0161tani"
    ],
    "name:fra_x_preferred":[
        "Grabo\u0161tani"
    ],
    "name:hrv_x_preferred":[
        "Grabo\u0161tani"
    ],
    "name:hun_x_preferred":[
        "Grabo\u0161tani"
    ],
    "name:nld_x_preferred":[
        "Grabo\u0161tani"
    ],
    "name:slv_x_preferred":[
        "Grabo\u0161tani"
    ],
    "name:spa_x_preferred":[
        "Grabo\u0161tani"
    ],
    "name:srp_x_preferred":[
        "\u0413\u0440\u0430\u0431\u043e\u0448\u0442\u0430\u043d\u0438"
    ],
    "name:swe_x_preferred":[
        "Grabo\u0161tani"
    ],
    "name:ukr_x_preferred":[
        "\u0413\u0440\u0430\u0431\u043e\u0449\u0430\u043d\u0438"
    ],
    "wof:name":"Grabostani",
    "wof:placetype":"locality",
    "wof:population":134
},
  "geometry": {"coordinates":[16.54722000000001,45.28111],"type":"Point"}
}