{
  "type": "Feature",
  "properties": {
    "gn:admin1_code":"15",
    "gn:admin2_code":"11054618.0",
    "gn:asciiname":"Gornje Igrane",
    "gn:cc2":"HR",
    "gn:country_code":"HR",
    "gn:dem":545,
    "gn:feature_class":"P",
    "gn:feature_code":"PPLL",
    "gn:name":"Gornje Igrane",
    "gn:population":0,
    "gn:timezone":"Europe/Zagreb",
    "iso:country":"HR",
    "name:und_x_variant":[
        "Igrane Gornje",
        "Gornje Igrane"
    ],
    "wof:name":"Gornje Igrane",
    "wof:placetype":"locality"
},
  "geometry": {"coordinates":[17.1567,43.23514],"type":"Point"}
}