{
  "type": "Feature",
  "properties": {
    "gn:admin1_code":"15.0",
    "gn:asciiname":"Saranac",
    "gn:country_code":"HR",
    "gn:dem":735,
    "gn:feature_class":"P",
    "gn:feature_code":"PPL",
    "gn:name":"Sarana\u010d",
    "gn:population":0,
    "gn:timezone":"Europe/Zagreb",
    "iso:country":"HR",
    "name:ceb_x_preferred":[
        "Saranac"
    ],
    "name:deu_x_preferred":[
        "Saranac"
    ],
    "name:fra_x_preferred":[
        "Saranac"
    ],
    "name:ita_x_preferred":[
        "Saranac"
    ],
    "name:pol_x_preferred":[
        "Saranac"
    ],
    "name:swe_x_preferred":[
        "Saranac"
    ],
    "wof:name":"Saranac",
    "wof:placetype":"locality"
},
  "geometry": {"coordinates":[17.17694,43.24861],"type":"Point"}
}