{
  "type": "Feature",
  "properties": {
    "gn:admin1_code":"10",
    "gn:admin2_code":"11054471.0",
    "gn:asciiname":"Milinac",
    "gn:cc2":"HR",
    "gn:country_code":"HR",
    "gn:dem":190,
    "gn:feature_class":"P",
    "gn:feature_code":"PPL",
    "gn:name":"Milinac",
    "gn:population":28,
    "gn:timezone":"Europe/Zagreb",
    "iso:country":"HR",
    "name:und_x_variant":[
        "Milinci",
        "Milinac"
    ],
    "wof:name":"Milinac",
    "wof:placetype":"locality",
    "wof:population":28
},
  "geometry": {"coordinates":[18.12389,45.34],"type":"Point"}
}