{
  "type": "Feature",
  "properties": {
    "gn:admin1_code":"19",
    "gn:asciiname":"Kukljica",
    "gn:cc2":"HR",
    "gn:country_code":"HR",
    "gn:dem":-1,
    "gn:feature_class":"P",
    "gn:feature_code":"PPL",
    "gn:name":"Kukljica",
    "gn:population":714,
    "gn:timezone":"Europe/Zagreb",
    "iso:country":"HR",
    "name:bos_x_preferred":[
        "Kukljica"
    ],
    "name:deu_x_preferred":[
        "Kukljica"
    ],
    "name:fra_x_preferred":[
        "Kukljica"
    ],
    "name:hrv_x_preferred":[
        "Kukljica"
    ],
    "name:hun_x_preferred":[
        "Kukljica"
    ],
    "name:ita_x_preferred":[
        "Cuclizza"
    ],
    "name:nld_x_preferred":[
        "Kukljica"
    ],
    "name:pol_x_preferred":[
        "Gmina Kukljica"
    ],
    "name:por_x_preferred":[
        "Kukljica"
    ],
    "name:ron_x_preferred":[
        "Comuna Kukljica"
    ],
    "name:slv_x_preferred":[
        "Kukljica"
    ],
    "name:srp_x_preferred":[
        "\u041a\u0443\u043a\u0459\u0438\u0446\u0430"
    ],
    "name:ukr_x_preferred":[
        "\u041a\u0443\u043a\u043b\u0456\u0446\u044f"
    ],
    "name:und_x_variant":[
        "Kuklica",
        "Kukljica"
    ],
    "name:war_x_preferred":[
        "Kukljica"
    ],
    "wof:name":"Kukljica",
    "wof:placetype":"locality",
    "wof:population":714
},
  "geometry": {"coordinates":[15.25,44.03333],"type":"Point"}
}