{
  "type": "Feature",
  "properties": {
    "gn:admin1_code":"19",
    "gn:asciiname":"Kukljica",
    "gn:cc2":"HR",
    "gn:country_code":"HR",
    "gn:dem":-1,
    "gn:feature_class":"P",
    "gn:feature_code":"PPL",
    "gn:name":"Kukljica",
    "gn:population":714,
    "gn:timezone":"Europe/Zagreb",
    "iso:country":"HR",
    "name:und_x_variant":[
        "Kuklica",
        "Kukljica"
    ],
    "wof:name":"Kukljica",
    "wof:placetype":"locality",
    "wof:population":714
},
  "geometry": {"coordinates":[15.25,44.03333],"type":"Point"}
}