{
  "type": "Feature",
  "properties": {
    "gn:admin1_code":"10.0",
    "gn:asciiname":"Samar Surduk",
    "gn:country_code":"HR",
    "gn:dem":168,
    "gn:feature_class":"P",
    "gn:feature_code":"PPL",
    "gn:name":"Samar Surduk",
    "gn:population":0,
    "gn:timezone":"Europe/Zagreb",
    "iso:country":"HR",
    "wof:name":"Samar Surduk",
    "wof:placetype":"locality"
},
  "geometry": {"coordinates":[18.77111,45.81667],"type":"Point"}
}