{
  "type": "Feature",
  "properties": {
    "gn:admin1_code":"06",
    "gn:admin2_code":"3197228.0",
    "gn:asciiname":"Glogovnica",
    "gn:country_code":"HR",
    "gn:dem":159,
    "gn:feature_class":"P",
    "gn:feature_code":"PPL",
    "gn:name":"Glogovnica",
    "gn:population":0,
    "gn:timezone":"Europe/Zagreb",
    "iso:country":"HR",
    "name:hrv_x_preferred":[
        "Glogovnica"
    ],
    "name:srp_x_preferred":[
        "\u0413\u043b\u043e\u0433\u043e\u0432\u043d\u0438\u0446\u0430"
    ],
    "name:zho_x_preferred":[
        "\u683c\u6d1b\u6208\u592b\u5c3c\u5bdf\u6cb3"
    ],
    "wof:name":"Glogovnica",
    "wof:placetype":"locality"
},
  "geometry": {"coordinates":[16.55806,46.10306],"type":"Point"}
}