{
  "type": "Feature",
  "properties": {
    "gn:admin1_code":"19",
    "gn:admin2_code":"11054377.0",
    "gn:asciiname":"Savar",
    "gn:country_code":"HR",
    "gn:dem":42,
    "gn:feature_class":"P",
    "gn:feature_code":"PPL",
    "gn:name":"Savar",
    "gn:population":53,
    "gn:timezone":"Europe/Zagreb",
    "iso:country":"HR",
    "wof:name":"Savar",
    "wof:placetype":"locality",
    "wof:population":53
},
  "geometry": {"coordinates":[15.01806,44.06083],"type":"Point"}
}