{
  "type": "Feature",
  "properties": {
    "gn:admin1_code":"15.0",
    "gn:asciiname":"Malenice",
    "gn:country_code":"HR",
    "gn:dem":688,
    "gn:feature_class":"P",
    "gn:feature_code":"PPL",
    "gn:name":"Malenice",
    "gn:population":0,
    "gn:timezone":"Europe/Zagreb",
    "iso:country":"HR",
    "wof:name":"Malenice",
    "wof:placetype":"locality"
},
  "geometry": {"coordinates":[17.08806,43.53083],"type":"Point"}
}