{
  "type": "Feature",
  "properties": {
    "gn:admin1_code":"15.0",
    "gn:asciiname":"Malenice",
    "gn:country_code":"HR",
    "gn:dem":688,
    "gn:feature_class":"P",
    "gn:feature_code":"PPL",
    "gn:name":"Malenice",
    "gn:population":0,
    "gn:timezone":"Europe/Zagreb",
    "iso:country":"HR",
    "name:azb_x_preferred":[
        "\u0645\u0627\u0644\u0646\u06cc\u062a\u0633\u0647"
    ],
    "name:ceb_x_preferred":[
        "Malenice"
    ],
    "name:ces_x_preferred":[
        "Malenice"
    ],
    "name:deu_x_preferred":[
        "Malenice"
    ],
    "name:eus_x_preferred":[
        "Malenice"
    ],
    "name:fas_x_preferred":[
        "\u0645\u0627\u0644\u0646\u06cc\u062a\u0633\u0647"
    ],
    "name:fra_x_preferred":[
        "Malenice"
    ],
    "name:hun_x_preferred":[
        "Malenice"
    ],
    "name:ita_x_preferred":[
        "Malenice"
    ],
    "name:msa_x_preferred":[
        "Malenice"
    ],
    "name:nld_x_preferred":[
        "Malenice"
    ],
    "name:por_x_preferred":[
        "Malenice"
    ],
    "name:slk_x_preferred":[
        "Malenice"
    ],
    "name:spa_x_preferred":[
        "Malenice"
    ],
    "name:srp_x_preferred":[
        "\u041c\u0430\u043b\u0435\u045a\u0438\u0446\u0435"
    ],
    "name:swe_x_preferred":[
        "Malenice"
    ],
    "name:vie_x_preferred":[
        "Malenice"
    ],
    "wof:name":"Malenice",
    "wof:placetype":"locality"
},
  "geometry": {"coordinates":[17.08806,43.53083],"type":"Point"}
}