{
  "type": "Feature",
  "properties": {
    "gn:admin1_code":"01",
    "gn:admin2_code":"11049398.0",
    "gn:asciiname":"Podgaric",
    "gn:cc2":"HR",
    "gn:country_code":"HR",
    "gn:dem":172,
    "gn:feature_class":"P",
    "gn:feature_code":"PPL",
    "gn:name":"Podgari\u0107",
    "gn:population":47,
    "gn:timezone":"Europe/Zagreb",
    "iso:country":"HR",
    "name:und_x_variant":[
        "Podgori\u0107",
        "Podgari\u0107"
    ],
    "wof:name":"Podgaric",
    "wof:placetype":"locality",
    "wof:population":47
},
  "geometry": {"coordinates":[16.77528,45.64],"type":"Point"}
}