{
  "type": "Feature",
  "properties": {
    "gn:country":"HR",
    "iso:country":"HR",
    "name:ces_x_preferred":[
        "Barbariga"
    ],
    "name:eng_x_preferred":[
        "Barbariga"
    ],
    "qs_pg:aaroncc":"HR",
    "qs_pg:gn_country":"HR",
    "qs_pg:name":"Barbariga",
    "qs_pg:name_adm0":"Hrvatska",
    "qs_pg:name_adm1":"Istarska",
    "qs_pg:photos":69,
    "qs_pg:photos_1k":14,
    "qs_pg:photos_9k":1,
    "qs_pg:photos_9r":2,
    "qs_pg:photos_all":69,
    "qs_pg:photos_sr":2,
    "qs_pg:pop_sr":0,
    "qs_pg:qs_pg_placetype":"locality",
    "qs_pg:qs_pg_placetype_gp":"Town",
    "qs_pg:woe_adm0":23424843,
    "woe:adm0_id":23424843,
    "woe:name_adm0":"Hrvatska",
    "woe:name_adm1":"Istarska",
    "woe:placetype":"Town",
    "wof:name":"Barbariga",
    "wof:placetype":"locality"
},
  "geometry": {"coordinates":[13.724155,45.001197],"type":"Point"}
}