{
  "type": "Feature",
  "properties": {
    "gn:admin1_code":"5.0",
    "gn:admin2_code":"3193753.0",
    "gn:asciiname":"Badovinci",
    "gn:country_code":"HR",
    "gn:dem":646,
    "gn:feature_class":"P",
    "gn:feature_code":"PPL",
    "gn:name":"Badovinci",
    "gn:population":23,
    "gn:timezone":"Europe/Zagreb",
    "iso:country":"HR",
    "wof:name":"Badovinci",
    "wof:placetype":"locality",
    "wof:population":23
},
  "geometry": {"coordinates":[15.36667,45.71667],"type":"Point"}
}