{
  "type": "Feature",
  "properties": {
    "gn:admin1_code":"10.0",
    "gn:admin2_code":"11054454.0",
    "gn:asciiname":"Bezdan",
    "gn:country_code":"HR",
    "gn:dem":82,
    "gn:feature_class":"P",
    "gn:feature_code":"PPL",
    "gn:name":"Bezdan",
    "gn:population":0,
    "gn:timezone":"Europe/Zagreb",
    "iso:country":"HR",
    "wof:name":"Bezdan",
    "wof:placetype":"locality"
},
  "geometry": {"coordinates":[18.61639,45.62583],"type":"Point"}
}