{
  "type": "Feature",
  "properties": {
    "gn:admin1_code":"10.0",
    "gn:admin2_code":"11054454.0",
    "gn:asciiname":"Bezdan",
    "gn:country_code":"HR",
    "gn:dem":82,
    "gn:feature_class":"P",
    "gn:feature_code":"PPL",
    "gn:name":"Bezdan",
    "gn:population":0,
    "gn:timezone":"Europe/Zagreb",
    "iso:country":"HR",
    "name:ara_x_preferred":[
        "\u0628\u064a\u0632\u062f\u0627\u0646"
    ],
    "name:ceb_x_preferred":[
        "Bezdan"
    ],
    "name:deu_x_preferred":[
        "Bezdan"
    ],
    "name:epo_x_preferred":[
        "Bezdan"
    ],
    "name:fra_x_preferred":[
        "Bezdan"
    ],
    "name:heb_x_preferred":[
        "\u05d1\u05d6\u05d3\u05d0\u05df"
    ],
    "name:hrv_x_preferred":[
        "Bezdan"
    ],
    "name:hun_x_preferred":[
        "Bezd\u00e1n"
    ],
    "name:msa_x_preferred":[
        "Bezdan"
    ],
    "name:slv_x_preferred":[
        "Bezdan"
    ],
    "name:spa_x_preferred":[
        "Bezdan"
    ],
    "name:srp_x_preferred":[
        "\u0411\u0435\u0437\u0434\u0430\u043d"
    ],
    "name:tur_x_preferred":[
        "Bezdan"
    ],
    "name:ukr_x_preferred":[
        "\u0411\u0435\u0437\u0434\u0430\u043d"
    ],
    "wof:name":"Bezdan",
    "wof:placetype":"locality"
},
  "geometry": {"coordinates":[18.61639,45.62583],"type":"Point"}
}