{
  "type": "Feature",
  "properties": {
    "gn:admin1_code":"5.0",
    "gn:admin2_code":"11049280.0",
    "gn:asciiname":"Donje Biljevina",
    "gn:cc2":"HR",
    "gn:country_code":"HR",
    "gn:dem":689,
    "gn:feature_class":"P",
    "gn:feature_code":"PPL",
    "gn:name":"Donje Biljevina",
    "gn:population":0,
    "gn:timezone":"Europe/Zagreb",
    "iso:country":"HR",
    "name:und_x_variant":[
        "Biljevina",
        "Donje Biljevina"
    ],
    "wof:name":"Donje Biljevina",
    "wof:placetype":"locality"
},
  "geometry": {"coordinates":[15.5175,44.96778],"type":"Point"}
}