{
  "type": "Feature",
  "properties": {
    "gn:admin1_code":"15.0",
    "gn:asciiname":"Dujmovici",
    "gn:country_code":"HR",
    "gn:dem":682,
    "gn:feature_class":"P",
    "gn:feature_code":"PPL",
    "gn:name":"Dujmovi\u0107i",
    "gn:population":0,
    "gn:timezone":"Europe/Zagreb",
    "iso:country":"HR",
    "wof:name":"Dujmovici",
    "wof:placetype":"locality"
},
  "geometry": {"coordinates":[17.06444,43.51861],"type":"Point"}
}