{
  "type": "Feature",
  "properties": {
    "gn:admin1_code":"5.0",
    "gn:admin2_code":"3190522.0",
    "gn:asciiname":"Dubrave",
    "gn:country_code":"HR",
    "gn:dem":297,
    "gn:feature_class":"P",
    "gn:feature_code":"PPLL",
    "gn:name":"Dubrave",
    "gn:population":0,
    "gn:timezone":"Europe/Zagreb",
    "iso:country":"HR",
    "wof:name":"Dubrave",
    "wof:placetype":"locality"
},
  "geometry": {"coordinates":[15.68639,45.10389],"type":"Point"}
}