{
  "type": "Feature",
  "properties": {
    "gn:admin1_code":"5.0",
    "gn:admin2_code":"3190522.0",
    "gn:asciiname":"Dubrave",
    "gn:country_code":"HR",
    "gn:dem":297,
    "gn:feature_class":"P",
    "gn:feature_code":"PPLL",
    "gn:name":"Dubrave",
    "gn:population":0,
    "gn:timezone":"Europe/Zagreb",
    "iso:country":"HR",
    "name:bos_x_preferred":[
        "Dubrave"
    ],
    "name:ceb_x_preferred":[
        "Dubrave"
    ],
    "name:fra_x_preferred":[
        "Dubrave"
    ],
    "name:hrv_x_preferred":[
        "Dubrave"
    ],
    "name:hun_x_preferred":[
        "Dubrave"
    ],
    "name:nld_x_preferred":[
        "Dubrave"
    ],
    "name:rus_x_preferred":[
        "\u0414\u0443\u0431\u0440\u0430\u0432\u0435"
    ],
    "name:slv_x_preferred":[
        "Dubrave"
    ],
    "name:srp_x_preferred":[
        "\u0414\u0443\u0431\u0440\u0430\u0432\u0435"
    ],
    "name:swe_x_preferred":[
        "Dubrave"
    ],
    "name:ukr_x_preferred":[
        "\u0414\u0443\u0431\u0440\u0430\u0432\u0435"
    ],
    "wof:name":"Dubrave",
    "wof:placetype":"locality"
},
  "geometry": {"coordinates":[15.68639,45.10389],"type":"Point"}
}