{
  "type": "Feature",
  "properties": {
    "gn:admin1_code":"8.0",
    "gn:admin2_code":"11049284.0",
    "gn:asciiname":"Susnjari",
    "gn:cc2":"HR",
    "gn:country_code":"HR",
    "gn:dem":652,
    "gn:feature_class":"P",
    "gn:feature_code":"PPL",
    "gn:name":"\u0160u\u0161njari",
    "gn:population":0,
    "gn:timezone":"Europe/Zagreb",
    "iso:country":"HR",
    "name:und_x_variant":[
        "\u0160u\u0161njavi",
        "\u0160u\u0161njari"
    ],
    "wof:name":"Susnjari",
    "wof:placetype":"locality"
},
  "geometry": {"coordinates":[15.075,45.05556],"type":"Point"}
}