{
  "type": "Feature",
  "properties": {
    "gn:admin1_code":"11",
    "gn:asciiname":"Dezevci",
    "gn:country_code":"HR",
    "gn:dem":192,
    "gn:feature_class":"P",
    "gn:feature_code":"PPL",
    "gn:name":"De\u017eevci",
    "gn:population":157,
    "gn:timezone":"Europe/Zagreb",
    "iso:country":"HR",
    "name:bos_x_preferred":[
        "De\u017eevci"
    ],
    "name:ceb_x_preferred":[
        "De\u017eevci"
    ],
    "name:hrv_x_preferred":[
        "De\u017eevci"
    ],
    "name:hun_x_preferred":[
        "De\u017eevci"
    ],
    "name:nld_x_preferred":[
        "De\u017eevci"
    ],
    "name:slv_x_preferred":[
        "De\u017eevci"
    ],
    "name:srp_x_preferred":[
        "\u0414\u0435\u0436\u0435\u0432\u0446\u0438"
    ],
    "name:swe_x_preferred":[
        "De\u017eevci"
    ],
    "name:ukr_x_preferred":[
        "\u0414\u0435\u0436\u0435\u0432\u0446\u0456"
    ],
    "name:und_x_variant":[
        "De\u017eevci"
    ],
    "wof:name":"Dezevci",
    "wof:placetype":"locality",
    "wof:population":157
},
  "geometry": {"coordinates":[17.51833,45.37361],"type":"Point"}
}