{
  "type": "Feature",
  "properties": {
    "gn:gn_country":"HR",
    "gn:gn_fcode":"PPL",
    "gn:gn_pop":0,
    "gn:population":192,
    "iso:country":"HR",
    "name:bos_x_preferred":[
        "Porat"
    ],
    "name:eng_x_preferred":[
        "Porat"
    ],
    "name:fra_x_preferred":[
        "Porat"
    ],
    "name:hrv_x_preferred":[
        "Porat"
    ],
    "name:hun_x_preferred":[
        "Porat"
    ],
    "name:nld_x_preferred":[
        "Porat"
    ],
    "name:slv_x_preferred":[
        "Porat"
    ],
    "name:spa_x_preferred":[
        "Porat"
    ],
    "name:ukr_x_preferred":[
        "\u041f\u043e\u0440\u0430\u0442"
    ],
    "qs_pg:aaroncc":"HR",
    "qs_pg:gn_country":"HR",
    "qs_pg:gn_fcode":"PPL",
    "qs_pg:gn_pop":0,
    "qs_pg:name":"Porat",
    "qs_pg:name_adm0":"Hrvatska",
    "qs_pg:name_adm1":"Primorsko-Goranska",
    "qs_pg:photos":21,
    "qs_pg:photos_1k":4,
    "qs_pg:photos_9k":1,
    "qs_pg:photos_9r":1,
    "qs_pg:photos_all":21,
    "qs_pg:photos_sr":1,
    "qs_pg:pop_sr":0,
    "qs_pg:qs_pg_placetype":"locality",
    "qs_pg:qs_pg_placetype_gp":"Town",
    "qs_pg:woe_adm0":23424843,
    "woe:adm0_id":23424843,
    "woe:name_adm0":"Hrvatska",
    "woe:name_adm1":"Primorsko-Goranska",
    "woe:placetype":"Town",
    "wof:name":"Porat",
    "wof:placetype":"locality",
    "wof:population":192
},
  "geometry": {"coordinates":[14.49401,45.1219],"type":"Point"}
}