{
  "type": "Feature",
  "properties": {
    "gn:admin1_code":"17.0",
    "gn:asciiname":"Bankovci",
    "gn:country_code":"HR",
    "gn:dem":107,
    "gn:feature_class":"P",
    "gn:feature_code":"PPL",
    "gn:name":"Bankovci",
    "gn:population":124,
    "gn:timezone":"Europe/Zagreb",
    "iso:country":"HR",
    "name:bos_x_preferred":[
        "Bankovci"
    ],
    "name:fra_x_preferred":[
        "Bankovci"
    ],
    "name:hrv_x_preferred":[
        "Bankovci"
    ],
    "name:nld_x_preferred":[
        "Bankovci"
    ],
    "name:slv_x_preferred":[
        "Bankovci"
    ],
    "name:srp_x_preferred":[
        "\u0411\u0430\u043d\u043a\u043e\u0432\u0446\u0438"
    ],
    "wof:name":"Bankovci",
    "wof:placetype":"locality",
    "wof:population":124
},
  "geometry": {"coordinates":[17.96667,45.56667],"type":"Point"}
}