{
  "type": "Feature",
  "properties": {
    "gn:admin1_code":"15",
    "gn:admin2_code":"11054617.0",
    "gn:asciiname":"Poljica",
    "gn:country_code":"HR",
    "gn:dem":458,
    "gn:feature_class":"P",
    "gn:feature_code":"PPLL",
    "gn:name":"Poljica",
    "gn:population":0,
    "gn:timezone":"Europe/Zagreb",
    "iso:country":"HR",
    "name:bos_x_preferred":[
        "Poljica"
    ],
    "name:ceb_x_preferred":[
        "Poljica"
    ],
    "name:deu_x_preferred":[
        "Poljica"
    ],
    "name:fra_x_preferred":[
        "Poljica"
    ],
    "name:hrv_x_preferred":[
        "Poljica"
    ],
    "name:hun_x_preferred":[
        "Poljica"
    ],
    "name:nld_x_preferred":[
        "Poljica"
    ],
    "name:slv_x_preferred":[
        "Poljica"
    ],
    "name:srp_x_preferred":[
        "\u041f\u043e\u0459\u0438\u0446\u0430"
    ],
    "name:swe_x_preferred":[
        "Poljica"
    ],
    "name:ukr_x_preferred":[
        "\u041f\u043e\u043b\u0456\u0446\u044f"
    ],
    "wof:name":"Poljica",
    "wof:placetype":"locality"
},
  "geometry": {"coordinates":[17.11481,43.42042],"type":"Point"}
}