{
  "type": "Feature",
  "properties": {
    "gn:admin1_code":"15",
    "gn:admin2_code":"11054617.0",
    "gn:asciiname":"Poljica",
    "gn:country_code":"HR",
    "gn:dem":458,
    "gn:feature_class":"P",
    "gn:feature_code":"PPLL",
    "gn:name":"Poljica",
    "gn:population":0,
    "gn:timezone":"Europe/Zagreb",
    "iso:country":"HR",
    "wof:name":"Poljica",
    "wof:placetype":"locality"
},
  "geometry": {"coordinates":[17.11481,43.42042],"type":"Point"}
}