{
  "type": "Feature",
  "properties": {
    "gn:admin1_code":"05",
    "gn:asciiname":"Veselici",
    "gn:country_code":"HR",
    "gn:dem":166,
    "gn:feature_class":"P",
    "gn:feature_code":"PPL",
    "gn:name":"Veseli\u0107i",
    "gn:population":49,
    "gn:timezone":"Europe/Zagreb",
    "iso:country":"HR",
    "wof:name":"Veselici",
    "wof:placetype":"locality",
    "wof:population":49
},
  "geometry": {"coordinates":[15.36667,45.55],"type":"Point"}
}