{
  "type": "Feature",
  "properties": {
    "gn:admin1_code":"8.0",
    "gn:admin2_code":"11049294.0",
    "gn:asciiname":"Lainici",
    "gn:country_code":"HR",
    "gn:dem":782,
    "gn:feature_class":"P",
    "gn:feature_code":"PPL",
    "gn:name":"Laini\u0107i",
    "gn:population":0,
    "gn:timezone":"Europe/Zagreb",
    "iso:country":"HR",
    "wof:name":"Lainici",
    "wof:placetype":"locality"
},
  "geometry": {"coordinates":[15.63361,44.56028],"type":"Point"}
}