{
  "type": "Feature",
  "properties": {
    "gn:admin1_code":"15.0",
    "gn:asciiname":"Marovici",
    "gn:country_code":"HR",
    "gn:dem":833,
    "gn:feature_class":"P",
    "gn:feature_code":"PPL",
    "gn:name":"Marovi\u0107i",
    "gn:population":0,
    "gn:timezone":"Europe/Zagreb",
    "iso:country":"HR",
    "wof:name":"Marovici",
    "wof:placetype":"locality"
},
  "geometry": {"coordinates":[16.55472,43.74083],"type":"Point"}
}