{
  "type": "Feature",
  "properties": {
    "gn:admin1_code":"15.0",
    "gn:asciiname":"Parlovi",
    "gn:country_code":"HR",
    "gn:dem":395,
    "gn:feature_class":"P",
    "gn:feature_code":"PPL",
    "gn:name":"Parlovi",
    "gn:population":0,
    "gn:timezone":"Europe/Zagreb",
    "iso:country":"HR",
    "wof:name":"Parlovi",
    "wof:placetype":"locality"
},
  "geometry": {"coordinates":[17.12611,43.50722],"type":"Point"}
}