{
  "type": "Feature",
  "properties": {
    "gn:admin1_code":"4.0",
    "gn:admin2_code":"3202941.0",
    "gn:asciiname":"Juradi",
    "gn:country_code":"HR",
    "gn:dem":171,
    "gn:feature_class":"P",
    "gn:feature_code":"PPL",
    "gn:name":"Juradi",
    "gn:population":75,
    "gn:timezone":"Europe/Zagreb",
    "iso:country":"HR",
    "wof:name":"Juradi",
    "wof:placetype":"locality",
    "wof:population":75
},
  "geometry": {"coordinates":[13.96278,45.33722],"type":"Point"}
}