{
  "type": "Feature",
  "properties": {
    "gn:admin1_code":"11",
    "gn:asciiname":"Sazije",
    "gn:country_code":"HR",
    "gn:dem":243,
    "gn:feature_class":"P",
    "gn:feature_code":"PPL",
    "gn:name":"Sa\u017eije",
    "gn:population":15,
    "gn:timezone":"Europe/Zagreb",
    "iso:country":"HR",
    "wof:name":"Sazije",
    "wof:placetype":"locality",
    "wof:population":15
},
  "geometry": {"coordinates":[17.48333,45.45],"type":"Point"}
}