{
  "type": "Feature",
  "properties": {
    "gn:country":"HR",
    "gn:fcode":"PPL",
    "gn:population":851,
    "iso:country":"HR",
    "name:bos_x_preferred":[
        "Vidovec"
    ],
    "name:ceb_x_preferred":[
        "Vidovec"
    ],
    "name:eng_x_preferred":[
        "Vidovec"
    ],
    "name:fra_x_preferred":[
        "Vidovec"
    ],
    "name:hrv_x_preferred":[
        "Vidovec"
    ],
    "name:hun_x_preferred":[
        "Zamlacsszentvid"
    ],
    "name:ita_x_preferred":[
        "Vidovec"
    ],
    "name:nld_x_preferred":[
        "Vidovec"
    ],
    "name:pol_x_preferred":[
        "Gmina Vidovec"
    ],
    "name:ron_x_preferred":[
        "Comuna Vidovec"
    ],
    "name:rus_x_preferred":[
        "\u0412\u0438\u0434\u043e\u0432\u0435\u0446"
    ],
    "name:slv_x_preferred":[
        "Vidovec"
    ],
    "name:spa_x_preferred":[
        "Vidovec"
    ],
    "name:srp_x_preferred":[
        "\u0412\u0438\u0434\u043e\u0432\u0435\u0446"
    ],
    "name:swe_x_preferred":[
        "Vidovec"
    ],
    "name:ukr_x_preferred":[
        "\u0412\u0438\u0434\u043e\u0432\u0435\u0446\u044c"
    ],
    "name:war_x_preferred":[
        "Vidovec"
    ],
    "qs_pg:aaroncc":"HR",
    "qs_pg:gn_country":"HR",
    "qs_pg:gn_fcode":"PPL",
    "qs_pg:gn_pop":851,
    "qs_pg:name":"Vitovec",
    "qs_pg:name_adm0":"Slovenija",
    "qs_pg:name_adm1":"Brezice",
    "qs_pg:photos_9r":0,
    "qs_pg:photos_sr":0,
    "qs_pg:pop_sr":2,
    "qs_pg:qs_pg_placetype":"locality",
    "qs_pg:qs_pg_placetype_gp":"Town",
    "qs_pg:woe_adm0":23424945,
    "woe:adm0_id":23424945,
    "woe:name_adm0":"Slovenija",
    "woe:name_adm1":"Brezice",
    "woe:placetype":"Town",
    "wof:name":"Vitovec",
    "wof:placetype":"locality",
    "wof:population":851
},
  "geometry": {"coordinates":[16.24111,46.28333],"type":"Point"}
}