{
  "type": "Feature",
  "properties": {
    "gn:admin1_code":"15.0",
    "gn:asciiname":"Gornji Alebici",
    "gn:country_code":"HR",
    "gn:dem":397,
    "gn:feature_class":"P",
    "gn:feature_code":"PPL",
    "gn:name":"Gornji Alebi\u0107i",
    "gn:population":0,
    "gn:timezone":"Europe/Zagreb",
    "iso:country":"HR",
    "wof:name":"Gornji Alebici",
    "wof:placetype":"locality"
},
  "geometry": {"coordinates":[16.60694,43.77472],"type":"Point"}
}