{
  "type": "Feature",
  "properties": {
    "gn:admin1_code":"14",
    "gn:admin2_code":"3196862.0",
    "gn:asciiname":"Brinjani",
    "gn:country_code":"HR",
    "gn:dem":129,
    "gn:feature_class":"P",
    "gn:feature_code":"PPL",
    "gn:name":"Brinjani",
    "gn:population":253,
    "gn:timezone":"Europe/Zagreb",
    "iso:country":"HR",
    "wof:name":"Brinjani",
    "wof:placetype":"locality",
    "wof:population":253
},
  "geometry": {"coordinates":[16.83333,45.53333],"type":"Point"}
}