{
  "type": "Feature",
  "properties": {
    "gn:admin1_code":"14.0",
    "gn:asciiname":"Javnik",
    "gn:country_code":"HR",
    "gn:dem":298,
    "gn:feature_class":"P",
    "gn:feature_code":"PPL",
    "gn:name":"Javnik",
    "gn:population":0,
    "gn:timezone":"Europe/Zagreb",
    "iso:country":"HR",
    "name:bos_x_preferred":[
        "Javnik"
    ],
    "name:ceb_x_preferred":[
        "Javnik"
    ],
    "name:nld_x_preferred":[
        "Javnik"
    ],
    "name:pol_x_preferred":[
        "Javnik"
    ],
    "name:ron_x_preferred":[
        "Javnik"
    ],
    "name:slv_x_preferred":[
        "Javnik"
    ],
    "name:ukr_x_preferred":[
        "\u042f\u0432\u043d\u0438\u043a"
    ],
    "wof:name":"Javnik",
    "wof:placetype":"locality"
},
  "geometry": {"coordinates":[16.19278,45.04306],"type":"Point"}
}