{
  "type": "Feature",
  "properties": {
    "gn:admin1_code":"06",
    "gn:admin2_code":"11049395.0",
    "gn:asciiname":"Fodrovec Rijecki",
    "gn:cc2":"HR",
    "gn:country_code":"HR",
    "gn:dem":152,
    "gn:feature_class":"P",
    "gn:feature_code":"PPL",
    "gn:name":"Fodrovec Rije\u010dki",
    "gn:population":61,
    "gn:timezone":"Europe/Zagreb",
    "iso:country":"HR",
    "name:und_x_variant":[
        "Rije\u010dki Fodrovec",
        "Fodrovec",
        "Fodrovec Rije\u010dki"
    ],
    "wof:name":"Fodrovec Rijecki",
    "wof:placetype":"locality",
    "wof:population":61
},
  "geometry": {"coordinates":[16.37972,46.06028],"type":"Point"}
}