{
  "type": "Feature",
  "properties": {
    "gn:country":"HR",
    "gn:fcode":"PPL",
    "gn:population":4,
    "iso:country":"HR",
    "name:bos_x_preferred":[
        "\u0110ur\u0111enovac"
    ],
    "name:deu_x_preferred":[
        "\u0110ur\u0111enovac"
    ],
    "name:eng_x_preferred":[
        "\u0110ur\u0111enovac"
    ],
    "name:fra_x_preferred":[
        "\u0110ur\u0111enovac"
    ],
    "name:hrv_x_preferred":[
        "\u0110ur\u0111enovac"
    ],
    "name:hun_x_preferred":[
        "Gjurgjenovac"
    ],
    "name:ita_x_preferred":[
        "\u0110ur\u0111enovac"
    ],
    "name:nld_x_preferred":[
        "\u0110ur\u0111enovac"
    ],
    "name:pol_x_preferred":[
        "\u0110ur\u0111enovac"
    ],
    "name:ron_x_preferred":[
        "Comuna \u0110ur\u0111enovac"
    ],
    "name:slv_x_preferred":[
        "\u0110ur\u0111enovac"
    ],
    "name:spa_x_preferred":[
        "\u0110ur\u0111enovac"
    ],
    "name:sqi_x_preferred":[
        "\u0110ur\u0111enovac"
    ],
    "name:srp_x_preferred":[
        "\u0402\u0443\u0440\u0452\u0435\u043d\u043e\u0432\u0430\u0446"
    ],
    "name:ukr_x_preferred":[
        "\u0414\u0436\u0443\u0440\u0434\u0436\u0435\u043d\u043e\u0432\u0430\u0446\u044c"
    ],
    "name:war_x_preferred":[
        "\u0110ur\u0111enovac"
    ],
    "qs_pg:aaroncc":"HR",
    "qs_pg:gn_country":"HR",
    "qs_pg:gn_fcode":"PPL",
    "qs_pg:gn_pop":4,
    "qs_pg:name":"\u00d0ur\u0111enovac",
    "qs_pg:name_adm0":"Hrvatska",
    "qs_pg:name_adm1":"Osje\u010dko-baranjska",
    "qs_pg:photos_9k":1,
    "qs_pg:photos_9r":1,
    "qs_pg:photos_all":1,
    "qs_pg:photos_sr":0,
    "qs_pg:pop_sr":1,
    "qs_pg:qs_pg_placetype":"locality",
    "qs_pg:qs_pg_placetype_gp":"Town",
    "qs_pg:woe_adm0":23424843,
    "woe:adm0_id":23424843,
    "woe:name_adm0":"Hrvatska",
    "woe:name_adm1":"Osje\u010dko-baranjska",
    "woe:placetype":"Town",
    "wof:name":"\u00d0ur\u0111enovac",
    "wof:placetype":"locality",
    "wof:population":4
},
  "geometry": {"coordinates":[18.04583,45.54333],"type":"Point"}
}