{
  "type": "Feature",
  "properties": {
    "gn:admin1_code":"14.0",
    "gn:asciiname":"Rajsici",
    "gn:country_code":"HR",
    "gn:dem":160,
    "gn:feature_class":"P",
    "gn:feature_code":"PPL",
    "gn:name":"Raj\u0161i\u0107i",
    "gn:population":0,
    "gn:timezone":"Europe/Zagreb",
    "iso:country":"HR",
    "wof:name":"Rajsici",
    "wof:placetype":"locality"
},
  "geometry": {"coordinates":[15.96472,45.24722],"type":"Point"}
}