{
  "type": "Feature",
  "properties": {
    "gn:admin1_code":"19.0",
    "gn:asciiname":"Mededak",
    "gn:country_code":"HR",
    "gn:dem":610,
    "gn:feature_class":"P",
    "gn:feature_code":"PPL",
    "gn:name":"Me\u0111e\u0111ak",
    "gn:population":0,
    "gn:timezone":"Europe/Zagreb",
    "iso:country":"HR",
    "wof:name":"Mededak",
    "wof:placetype":"locality"
},
  "geometry": {"coordinates":[16.11889,44.4275],"type":"Point"}
}