{
  "type": "Feature",
  "properties": {
    "gn:admin1_code":"05",
    "gn:admin2_code":"3187450.0",
    "gn:asciiname":"Krstinja",
    "gn:country_code":"HR",
    "gn:dem":175,
    "gn:feature_class":"P",
    "gn:feature_code":"PPL",
    "gn:name":"Krstinja",
    "gn:population":82,
    "gn:timezone":"Europe/Zagreb",
    "iso:country":"HR",
    "name:bos_x_preferred":[
        "Krstinja"
    ],
    "name:cat_x_preferred":[
        "Krstinja"
    ],
    "name:hrv_x_preferred":[
        "Krstinja"
    ],
    "name:hun_x_preferred":[
        "Krstinja"
    ],
    "name:nld_x_preferred":[
        "Krstinja"
    ],
    "name:slv_x_preferred":[
        "Krstinja"
    ],
    "name:spa_x_preferred":[
        "Krstinja"
    ],
    "name:srp_x_preferred":[
        "\u041a\u0440\u0441\u0442\u0438\u045a\u0430"
    ],
    "name:ukr_x_preferred":[
        "\u041a\u0440\u0441\u0442\u0438\u043d\u044f"
    ],
    "wof:name":"Krstinja",
    "wof:placetype":"locality",
    "wof:population":82
},
  "geometry": {"coordinates":[15.73,45.24417],"type":"Point"}
}