{
  "type": "Feature",
  "properties": {
    "gn:admin1_code":"05",
    "gn:admin2_code":"3187450.0",
    "gn:asciiname":"Krstinja",
    "gn:country_code":"HR",
    "gn:dem":175,
    "gn:feature_class":"P",
    "gn:feature_code":"PPL",
    "gn:name":"Krstinja",
    "gn:population":82,
    "gn:timezone":"Europe/Zagreb",
    "iso:country":"HR",
    "wof:name":"Krstinja",
    "wof:placetype":"locality",
    "wof:population":82
},
  "geometry": {"coordinates":[15.73,45.24417],"type":"Point"}
}