{
  "type": "Feature",
  "properties": {
    "gn:admin1_code":"02",
    "gn:admin2_code":"11049481.0",
    "gn:asciiname":"Krajacici",
    "gn:country_code":"HR",
    "gn:dem":126,
    "gn:feature_class":"P",
    "gn:feature_code":"PPL",
    "gn:name":"Kraja\u010di\u0107i",
    "gn:population":118,
    "gn:timezone":"Europe/Zagreb",
    "iso:country":"HR",
    "wof:name":"Krajacici",
    "wof:placetype":"locality",
    "wof:population":118
},
  "geometry": {"coordinates":[17.84528,45.20583],"type":"Point"}
}