{
  "type": "Feature",
  "properties": {
    "gn:admin1_code":"04",
    "gn:asciiname":"Mali Mlun",
    "gn:country_code":"HR",
    "gn:dem":216,
    "gn:feature_class":"P",
    "gn:feature_code":"PPL",
    "gn:name":"Mali Mlun",
    "gn:population":64,
    "gn:timezone":"Europe/Zagreb",
    "iso:country":"HR",
    "wof:name":"Mali Mlun",
    "wof:placetype":"locality",
    "wof:population":64
},
  "geometry": {"coordinates":[13.90917,45.4025],"type":"Point"}
}