{
  "type": "Feature",
  "properties": {
    "gn:admin1_code":"8.0",
    "gn:admin2_code":"11049291.0",
    "gn:asciiname":"Donji Lulici",
    "gn:country_code":"HR",
    "gn:dem":729,
    "gn:feature_class":"P",
    "gn:feature_code":"PPL",
    "gn:name":"Donji Luli\u0107i",
    "gn:population":0,
    "gn:timezone":"Europe/Zagreb",
    "iso:country":"HR",
    "wof:name":"Donji Lulici",
    "wof:placetype":"locality"
},
  "geometry": {"coordinates":[15.48361,44.68528],"type":"Point"}
}