{
  "type": "Feature",
  "properties": {
    "gn:admin1_code":"14",
    "gn:admin2_code":"3200597.0",
    "gn:asciiname":"Vlahovic",
    "gn:cc2":"HR",
    "gn:country_code":"HR",
    "gn:dem":158,
    "gn:feature_class":"P",
    "gn:feature_code":"PPL",
    "gn:name":"Vlahovi\u0107",
    "gn:population":73,
    "gn:timezone":"Europe/Zagreb",
    "iso:country":"HR",
    "name:und_x_variant":[
        "Vlaovi\u0107",
        "Vlahovi\u0107"
    ],
    "wof:name":"Vlahovic",
    "wof:placetype":"locality",
    "wof:population":73
},
  "geometry": {"coordinates":[16.19625,45.31449],"type":"Point"}
}