{
  "type": "Feature",
  "properties": {
    "gn:admin1_code":"19",
    "gn:asciiname":"Ladvic",
    "gn:country_code":"HR",
    "gn:dem":-9999,
    "gn:feature_class":"P",
    "gn:feature_code":"PPL",
    "gn:name":"Ladvi\u0107",
    "gn:population":0,
    "gn:timezone":"Europe/Zagreb",
    "iso:country":"HR",
    "wof:name":"Ladvic",
    "wof:placetype":"locality"
},
  "geometry": {"coordinates":[14.71667,44.16667],"type":"Point"}
}