{
  "type": "Feature",
  "properties": {
    "gn:admin1_code":"15.0",
    "gn:asciiname":"Gornji Galici",
    "gn:country_code":"HR",
    "gn:dem":632,
    "gn:feature_class":"P",
    "gn:feature_code":"PPL",
    "gn:name":"Gornji Gali\u0107i",
    "gn:population":0,
    "gn:timezone":"Europe/Zagreb",
    "iso:country":"HR",
    "wof:name":"Gornji Galici",
    "wof:placetype":"locality"
},
  "geometry": {"coordinates":[16.94389,43.55],"type":"Point"}
}