{
  "type": "Feature",
  "properties": {
    "gn:admin1_code":"11.0",
    "gn:admin2_code":"11049478.0",
    "gn:asciiname":"Mihaljevici",
    "gn:country_code":"HR",
    "gn:dem":209,
    "gn:feature_class":"P",
    "gn:feature_code":"PPL",
    "gn:name":"Mihaljevi\u0107i",
    "gn:population":2,
    "gn:timezone":"Europe/Zagreb",
    "iso:country":"HR",
    "wof:name":"Mihaljevici",
    "wof:placetype":"locality",
    "wof:population":2
},
  "geometry": {"coordinates":[17.86444,45.25194000000001],"type":"Point"}
}