{
  "type": "Feature",
  "properties": {
    "gn:admin1_code":"04",
    "gn:admin2_code":"11072413.0",
    "gn:asciiname":"Vabriga",
    "gn:cc2":"HR",
    "gn:country_code":"HR",
    "gn:dem":52,
    "gn:feature_class":"P",
    "gn:feature_code":"PPL",
    "gn:name":"Vabriga",
    "gn:population":0,
    "gn:timezone":"Europe/Zagreb",
    "iso:country":"HR",
    "name:bos_x_preferred":[
        "Vabriga"
    ],
    "name:fra_x_preferred":[
        "Vabriga"
    ],
    "name:hrv_x_preferred":[
        "Vabriga"
    ],
    "name:hun_x_preferred":[
        "Vabriga"
    ],
    "name:nld_x_preferred":[
        "Vabriga"
    ],
    "name:slv_x_preferred":[
        "Vabriga"
    ],
    "name:srp_x_preferred":[
        "\u0412\u0430\u0431\u0440\u0438\u0433\u0430"
    ],
    "name:ukr_x_preferred":[
        "\u0412\u0430\u0431\u0440\u0438\u0433\u0430"
    ],
    "name:und_x_variant":[
        "Abrega"
    ],
    "wof:name":"Vabriga",
    "wof:placetype":"locality"
},
  "geometry": {"coordinates":[13.61333,45.29167],"type":"Point"}
}