{
  "type": "Feature",
  "properties": {
    "gn:admin1_code":"10",
    "gn:admin2_code":"11054393.0",
    "gn:asciiname":"Habjanovci",
    "gn:country_code":"HR",
    "gn:dem":90,
    "gn:feature_class":"P",
    "gn:feature_code":"PPL",
    "gn:name":"Habjanovci",
    "gn:population":460,
    "gn:timezone":"Europe/Zagreb",
    "iso:country":"HR",
    "wof:name":"Habjanovci",
    "wof:placetype":"locality",
    "wof:population":460
},
  "geometry": {"coordinates":[18.43,45.54306],"type":"Point"}
}