{
  "type": "Feature",
  "properties": {
    "gn:admin1_code":"19.0",
    "gn:asciiname":"Klancovac",
    "gn:country_code":"HR",
    "gn:dem":342,
    "gn:feature_class":"P",
    "gn:feature_code":"PPL",
    "gn:name":"Klan\u010dovac",
    "gn:population":0,
    "gn:timezone":"Europe/Zagreb",
    "iso:country":"HR",
    "wof:name":"Klancovac",
    "wof:placetype":"locality"
},
  "geometry": {"coordinates":[15.67889,44.17111],"type":"Point"}
}