{
  "type": "Feature",
  "properties": {
    "gn:admin1_code":"12",
    "gn:admin2_code":"11072235.0",
    "gn:asciiname":"Susik",
    "gn:country_code":"HR",
    "gn:dem":54,
    "gn:feature_class":"P",
    "gn:feature_code":"PPL",
    "gn:name":"Su\u0161ik",
    "gn:population":0,
    "gn:timezone":"Europe/Zagreb",
    "iso:country":"HR",
    "wof:name":"Susik",
    "wof:placetype":"locality"
},
  "geometry": {"coordinates":[14.675,45.22583],"type":"Point"}
}