{
  "type": "Feature",
  "properties": {
    "gn:admin1_code":"3.0",
    "gn:admin2_code":"11054961.0",
    "gn:asciiname":"Pozirine",
    "gn:country_code":"HR",
    "gn:dem":50,
    "gn:feature_class":"P",
    "gn:feature_code":"PPL",
    "gn:name":"Pozirine",
    "gn:population":0,
    "gn:timezone":"Europe/Zagreb",
    "iso:country":"HR",
    "wof:name":"Pozirine",
    "wof:placetype":"locality"
},
  "geometry": {"coordinates":[17.46694,42.88222],"type":"Point"}
}