{
  "type": "Feature",
  "properties": {
    "gn:admin1_code":"01",
    "gn:admin2_code":"11049413.0",
    "gn:asciiname":"Donji Mosti",
    "gn:cc2":"HR",
    "gn:country_code":"HR",
    "gn:dem":177,
    "gn:feature_class":"P",
    "gn:feature_code":"PPL",
    "gn:name":"Donji Mosti",
    "gn:population":210,
    "gn:timezone":"Europe/Zagreb",
    "iso:country":"HR",
    "name:bos_x_preferred":[
        "Donji Mosti"
    ],
    "name:hrv_x_preferred":[
        "Donji Mosti"
    ],
    "name:hun_x_preferred":[
        "Donji Mosti"
    ],
    "name:nld_x_preferred":[
        "Donji Mosti"
    ],
    "name:slv_x_preferred":[
        "Donji Mosti"
    ],
    "name:spa_x_preferred":[
        "Donji Mosti"
    ],
    "name:srp_x_preferred":[
        "\u0414\u043e\u045a\u0438 \u041c\u043e\u0441\u0442\u0438"
    ],
    "name:ukr_x_preferred":[
        "\u0414\u043e\u043d\u0456 \u041c\u043e\u0441\u0442\u0438"
    ],
    "name:und_x_variant":[
        "Mosti-dolnji",
        "Donje Mosti"
    ],
    "wof:name":"Donji Mosti",
    "wof:placetype":"locality",
    "wof:population":210
},
  "geometry": {"coordinates":[16.86917,46.04639],"type":"Point"}
}