{
  "type": "Feature",
  "properties": {
    "gn:admin1_code":"01",
    "gn:admin2_code":"11049413.0",
    "gn:asciiname":"Donji Mosti",
    "gn:cc2":"HR",
    "gn:country_code":"HR",
    "gn:dem":177,
    "gn:feature_class":"P",
    "gn:feature_code":"PPL",
    "gn:name":"Donji Mosti",
    "gn:population":210,
    "gn:timezone":"Europe/Zagreb",
    "iso:country":"HR",
    "name:und_x_variant":[
        "Mosti-dolnji",
        "Donje Mosti",
        "Donji Mosti"
    ],
    "wof:name":"Donji Mosti",
    "wof:placetype":"locality",
    "wof:population":210
},
  "geometry": {"coordinates":[16.86917,46.04639],"type":"Point"}
}