{
  "type": "Feature",
  "properties": {
    "gn:admin1_code":"15.0",
    "gn:asciiname":"Sekulovici",
    "gn:country_code":"HR",
    "gn:dem":294,
    "gn:feature_class":"P",
    "gn:feature_code":"PPL",
    "gn:name":"Sekulovi\u0107i",
    "gn:population":0,
    "gn:timezone":"Europe/Zagreb",
    "iso:country":"HR",
    "wof:name":"Sekulovici",
    "wof:placetype":"locality"
},
  "geometry": {"coordinates":[17.15972,43.46667],"type":"Point"}
}