{
  "type": "Feature",
  "properties": {
    "gn:admin1_code":"19.0",
    "gn:asciiname":"Brig",
    "gn:country_code":"HR",
    "gn:dem":41,
    "gn:feature_class":"P",
    "gn:feature_code":"PPL",
    "gn:name":"Brig",
    "gn:population":0,
    "gn:timezone":"Europe/Zagreb",
    "iso:country":"HR",
    "name:afr_x_preferred":[
        "Brik"
    ],
    "name:aze_x_preferred":[
        "Briq"
    ],
    "name:bel_x_preferred":[
        "\u0411\u0440\u044b\u0433"
    ],
    "name:bul_x_preferred":[
        "\u0411\u0440\u0438\u0433"
    ],
    "name:cat_x_preferred":[
        "Bergant\u00ed"
    ],
    "name:ces_x_preferred":[
        "Briga"
    ],
    "name:chv_x_preferred":[
        "\u0411\u0440\u0438\u0433"
    ],
    "name:cym_x_preferred":[
        "Brig"
    ],
    "name:dan_x_preferred":[
        "Brig"
    ],
    "name:deu_x_preferred":[
        "Brigg"
    ],
    "name:ell_x_preferred":[
        "\u0392\u03c1\u03af\u03ba\u03b9\u03bf\u03bd"
    ],
    "name:epo_x_preferred":[
        "Brigo"
    ],
    "name:est_x_preferred":[
        "Prikk"
    ],
    "name:fin_x_preferred":[
        "Priki"
    ],
    "name:fra_x_preferred":[
        "Brick"
    ],
    "name:gle_x_preferred":[
        "Bruig"
    ],
    "name:heb_x_preferred":[
        "\u05d1\u05e8\u05d9\u05d2"
    ],
    "name:hrv_x_preferred":[
        "Brik"
    ],
    "name:hun_x_preferred":[
        "Brigg"
    ],
    "name:ido_x_preferred":[
        "Brigo"
    ],
    "name:ind_x_preferred":[
        "Brig"
    ],
    "name:isl_x_preferred":[
        "Briggskip"
    ],
    "name:ita_x_preferred":[
        "Bricco"
    ],
    "name:jpn_x_preferred":[
        "\u30d6\u30ea\u30c3\u30b0"
    ],
    "name:kat_x_preferred":[
        "\u10d1\u10e0\u10d8\u10d2\u10d8"
    ],
    "name:kaz_x_preferred":[
        "\u0411\u0440\u0438\u0433"
    ],
    "name:kor_x_preferred":[
        "\ube0c\ub9ac\uadf8"
    ],
    "name:lav_x_preferred":[
        "Briga"
    ],
    "name:lit_x_preferred":[
        "Brigas"
    ],
    "name:mkd_x_preferred":[
        "\u0411\u0440\u0438\u043a"
    ],
    "name:nld_x_preferred":[
        "Brik"
    ],
    "name:nno_x_preferred":[
        "Brigg"
    ],
    "name:nor_x_preferred":[
        "Brigg"
    ],
    "name:pol_x_preferred":[
        "Bryg"
    ],
    "name:por_x_preferred":[
        "Brigue"
    ],
    "name:ron_x_preferred":[
        "Bric"
    ],
    "name:rus_x_preferred":[
        "\u0411\u0440\u0438\u0433"
    ],
    "name:slk_x_preferred":[
        "Briga"
    ],
    "name:slv_x_preferred":[
        "Brig"
    ],
    "name:srp_x_preferred":[
        "\u0411\u0440\u0438\u043a"
    ],
    "name:swe_x_preferred":[
        "Brigg"
    ],
    "name:tur_x_preferred":[
        "Brik"
    ],
    "name:ukr_x_preferred":[
        "\u0411\u0440\u0438\u0433"
    ],
    "name:zho_x_preferred":[
        "\u96d9\u6845\u6a6b\u5e06\u8239"
    ],
    "wof:name":"Brig",
    "wof:placetype":"locality"
},
  "geometry": {"coordinates":[15.2875,44.20472],"type":"Point"}
}