{
  "type": "Feature",
  "properties": {
    "gn:admin1_code":"19.0",
    "gn:asciiname":"Brig",
    "gn:country_code":"HR",
    "gn:dem":41,
    "gn:feature_class":"P",
    "gn:feature_code":"PPL",
    "gn:name":"Brig",
    "gn:population":0,
    "gn:timezone":"Europe/Zagreb",
    "iso:country":"HR",
    "wof:name":"Brig",
    "wof:placetype":"locality"
},
  "geometry": {"coordinates":[15.2875,44.20472],"type":"Point"}
}