{
  "type": "Feature",
  "properties": {
    "gn:admin1_code":"12",
    "gn:admin2_code":"11049443.0",
    "gn:asciiname":"Male Mune",
    "gn:country_code":"HR",
    "gn:dem":636,
    "gn:feature_class":"P",
    "gn:feature_code":"PPL",
    "gn:name":"Male Mune",
    "gn:population":103,
    "gn:timezone":"Europe/Zagreb",
    "iso:country":"HR",
    "wof:name":"Male Mune",
    "wof:placetype":"locality",
    "wof:population":103
},
  "geometry": {"coordinates":[14.16444,45.45639],"type":"Point"}
}