{
  "type": "Feature",
  "properties": {
    "gn:admin1_code":"3.0",
    "gn:asciiname":"Muzine",
    "gn:country_code":"HR",
    "gn:dem":221,
    "gn:feature_class":"P",
    "gn:feature_code":"PPL",
    "gn:name":"Mu\u017eine",
    "gn:population":0,
    "gn:timezone":"Europe/Zagreb",
    "iso:country":"HR",
    "wof:name":"Muzine",
    "wof:placetype":"locality"
},
  "geometry": {"coordinates":[18.07056,42.67694],"type":"Point"}
}