{
  "type": "Feature",
  "properties": {
    "gn:admin1_code":"15.0",
    "gn:asciiname":"Donji Bilandzici",
    "gn:country_code":"HR",
    "gn:dem":391,
    "gn:feature_class":"P",
    "gn:feature_code":"PPL",
    "gn:name":"Donji Biland\u017ei\u0107i",
    "gn:population":0,
    "gn:timezone":"Europe/Zagreb",
    "iso:country":"HR",
    "wof:name":"Donji Bilandzici",
    "wof:placetype":"locality"
},
  "geometry": {"coordinates":[16.52083,43.81889],"type":"Point"}
}