{
  "type": "Feature",
  "properties": {
    "gn:admin1_code":"19.0",
    "gn:asciiname":"Bijanko",
    "gn:country_code":"HR",
    "gn:dem":524,
    "gn:feature_class":"P",
    "gn:feature_code":"PPL",
    "gn:name":"Bijanko",
    "gn:population":0,
    "gn:timezone":"Europe/Zagreb",
    "iso:country":"HR",
    "wof:name":"Bijanko",
    "wof:placetype":"locality"
},
  "geometry": {"coordinates":[15.90167,44.22889],"type":"Point"}
}