{
  "type": "Feature",
  "properties": {
    "gn:admin1_code":"20.0",
    "gn:admin2_code":"11054889.0",
    "gn:asciiname":"Mala Gorica",
    "gn:country_code":"HR",
    "gn:dem":150,
    "gn:feature_class":"P",
    "gn:feature_code":"PPL",
    "gn:name":"Mala Gorica",
    "gn:population":623,
    "gn:timezone":"Europe/Zagreb",
    "iso:country":"HR",
    "name:bos_x_preferred":[
        "Mala Gorica"
    ],
    "name:ceb_x_preferred":[
        "Mala Gorica"
    ],
    "name:hrv_x_preferred":[
        "Mala Gorica"
    ],
    "name:hun_x_preferred":[
        "Mala Gorica"
    ],
    "name:nld_x_preferred":[
        "Mala Gorica"
    ],
    "name:slv_x_preferred":[
        "Mala Gorica"
    ],
    "name:srp_x_preferred":[
        "\u041c\u0430\u043b\u0430 \u0413\u043e\u0440\u0438\u0446\u0430"
    ],
    "name:swe_x_preferred":[
        "Mala Gorica"
    ],
    "wof:name":"Mala Gorica",
    "wof:placetype":"locality",
    "wof:population":623
},
  "geometry": {"coordinates":[15.78333,45.76667],"type":"Point"}
}