{
  "type": "Feature",
  "properties": {
    "gn:admin1_code":"04",
    "gn:asciiname":"Gedici",
    "gn:cc2":"HR",
    "gn:country_code":"HR",
    "gn:dem":93,
    "gn:feature_class":"P",
    "gn:feature_code":"PPL",
    "gn:name":"Gedi\u0107i",
    "gn:population":97,
    "gn:timezone":"Europe/Zagreb",
    "iso:country":"HR",
    "name:und_x_variant":[
        "Ghedda",
        "Gedi",
        "Gedi\u0107i"
    ],
    "wof:name":"Gedici",
    "wof:placetype":"locality",
    "wof:population":97
},
  "geometry": {"coordinates":[13.65417,45.27361],"type":"Point"}
}