{
  "type": "Feature",
  "properties": {
    "gn:admin1_code":"16.0",
    "gn:admin2_code":"11049296.0",
    "gn:asciiname":"Cvetlin",
    "gn:country_code":"HR",
    "gn:dem":260,
    "gn:feature_class":"P",
    "gn:feature_code":"PPL",
    "gn:name":"Cvetlin",
    "gn:population":283,
    "gn:timezone":"Europe/Zagreb",
    "iso:country":"HR",
    "wof:name":"Cvetlin",
    "wof:placetype":"locality",
    "wof:population":283
},
  "geometry": {"coordinates":[15.96361,46.28111],"type":"Point"}
}