{
  "type": "Feature",
  "properties": {
    "gn:admin1_code":"12",
    "gn:asciiname":"Guce Selo",
    "gn:country_code":"HR",
    "gn:dem":245,
    "gn:feature_class":"P",
    "gn:feature_code":"PPL",
    "gn:name":"Gu\u010de Selo",
    "gn:population":27,
    "gn:timezone":"Europe/Zagreb",
    "iso:country":"HR",
    "wof:name":"Guce Selo",
    "wof:placetype":"locality",
    "wof:population":27
},
  "geometry": {"coordinates":[14.81361,45.46389],"type":"Point"}
}