{
  "type": "Feature",
  "properties": {
    "gn:admin1_code":"14",
    "gn:admin2_code":"11049234.0",
    "gn:asciiname":"Vorkapic",
    "gn:country_code":"HR",
    "gn:dem":167,
    "gn:feature_class":"P",
    "gn:feature_code":"PPL",
    "gn:name":"Vorkapi\u0107",
    "gn:population":26,
    "gn:timezone":"Europe/Zagreb",
    "iso:country":"HR",
    "wof:name":"Vorkapic",
    "wof:placetype":"locality",
    "wof:population":26
},
  "geometry": {"coordinates":[15.92786,45.26933],"type":"Point"}
}