{
  "type": "Feature",
  "properties": {
    "gn:admin1_code":"8.0",
    "gn:asciiname":"Stampari",
    "gn:country_code":"HR",
    "gn:dem":700,
    "gn:feature_class":"P",
    "gn:feature_code":"PPL",
    "gn:name":"\u0160tampari",
    "gn:population":0,
    "gn:timezone":"Europe/Zagreb",
    "iso:country":"HR",
    "wof:name":"Stampari",
    "wof:placetype":"locality"
},
  "geometry": {"coordinates":[15.51361,44.73611],"type":"Point"}
}