{
  "type": "Feature",
  "properties": {
    "gn:admin1_code":"15.0",
    "gn:asciiname":"Capini",
    "gn:country_code":"HR",
    "gn:dem":451,
    "gn:feature_class":"P",
    "gn:feature_code":"PPL",
    "gn:name":"\u010capini",
    "gn:population":0,
    "gn:timezone":"Europe/Zagreb",
    "iso:country":"HR",
    "wof:name":"Capini",
    "wof:placetype":"locality"
},
  "geometry": {"coordinates":[17.17583,43.39944000000001],"type":"Point"}
}