{
  "type": "Feature",
  "properties": {
    "gn:admin1_code":"05",
    "gn:admin2_code":"11049276.0",
    "gn:asciiname":"Mracin",
    "gn:country_code":"HR",
    "gn:dem":208,
    "gn:feature_class":"P",
    "gn:feature_code":"PPL",
    "gn:name":"Mra\u010din",
    "gn:population":263,
    "gn:timezone":"Europe/Zagreb",
    "iso:country":"HR",
    "wof:name":"Mracin",
    "wof:placetype":"locality",
    "wof:population":263
},
  "geometry": {"coordinates":[15.40901,45.43629],"type":"Point"}
}