{
  "type": "Feature",
  "properties": {
    "gn:admin1_code":"10",
    "gn:admin2_code":"11054391.0",
    "gn:asciiname":"Veliskovci",
    "gn:country_code":"HR",
    "gn:dem":90,
    "gn:feature_class":"P",
    "gn:feature_code":"PPL",
    "gn:name":"Veli\u0161kovci",
    "gn:population":685,
    "gn:timezone":"Europe/Zagreb",
    "iso:country":"HR",
    "name:bos_x_preferred":[
        "Veli\u0161kovci"
    ],
    "name:ceb_x_preferred":[
        "Veli\u0161kovci"
    ],
    "name:fas_x_preferred":[
        "\u0648\u0644\u06cc\u0634\u06a9\u0648\u06a9\u06cc"
    ],
    "name:fra_x_preferred":[
        "Veli\u0161kovci"
    ],
    "name:hrv_x_preferred":[
        "Veli\u0161kovci"
    ],
    "name:slv_x_preferred":[
        "Veli\u0161kovci"
    ],
    "name:srp_x_preferred":[
        "\u0412\u0435\u043b\u0438\u0448\u043a\u043e\u0432\u0446\u0438"
    ],
    "name:swe_x_preferred":[
        "Veli\u0161kovci"
    ],
    "name:ukr_x_preferred":[
        "\u0412\u0435\u043b\u0438\u0448\u043a\u043e\u0432\u0446\u0456"
    ],
    "name:und_x_variant":[
        "Veli\u0161kovci"
    ],
    "wof:name":"Veliskovci",
    "wof:placetype":"locality",
    "wof:population":685
},
  "geometry": {"coordinates":[18.32167,45.69111],"type":"Point"}
}