{
  "type": "Feature",
  "properties": {
    "gn:admin1_code":"10",
    "gn:admin2_code":"11054391.0",
    "gn:asciiname":"Veliskovci",
    "gn:country_code":"HR",
    "gn:dem":90,
    "gn:feature_class":"P",
    "gn:feature_code":"PPL",
    "gn:name":"Veli\u0161kovci",
    "gn:population":685,
    "gn:timezone":"Europe/Zagreb",
    "iso:country":"HR",
    "name:und_x_variant":[
        "Veli\u0161kovci"
    ],
    "wof:name":"Veliskovci",
    "wof:placetype":"locality",
    "wof:population":685
},
  "geometry": {"coordinates":[18.32167,45.69111],"type":"Point"}
}