{
  "type": "Feature",
  "properties": {
    "gn:country":"HR",
    "gn:fcode":"PPL",
    "gn:population":5,
    "iso:country":"HR",
    "name:bos_x_preferred":[
        "Plavno"
    ],
    "name:eng_x_preferred":[
        "Plavno"
    ],
    "name:hrv_x_preferred":[
        "Plavno"
    ],
    "name:hun_x_preferred":[
        "Plavno"
    ],
    "name:nld_x_preferred":[
        "Plavno"
    ],
    "name:slv_x_preferred":[
        "Plavno"
    ],
    "name:srp_x_preferred":[
        "\u041f\u043b\u0430\u0432\u043d\u043e"
    ],
    "name:ukr_x_preferred":[
        "\u041f\u043b\u0430\u0432\u043d\u043e"
    ],
    "qs_pg:aaroncc":"HR",
    "qs_pg:gn_country":"HR",
    "qs_pg:gn_fcode":"PPL",
    "qs_pg:gn_pop":5,
    "qs_pg:name":"Plavno",
    "qs_pg:name_adm0":"Hrvatska",
    "qs_pg:name_adm1":"Sibenska",
    "qs_pg:photos_9k":1,
    "qs_pg:photos_9r":1,
    "qs_pg:photos_all":1,
    "qs_pg:photos_sr":0,
    "qs_pg:pop_sr":1,
    "qs_pg:qs_pg_placetype":"locality",
    "qs_pg:qs_pg_placetype_gp":"Town",
    "qs_pg:woe_adm0":23424843,
    "woe:adm0_id":23424843,
    "woe:name_adm0":"Hrvatska",
    "woe:name_adm1":"Sibenska",
    "woe:placetype":"Town",
    "wof:name":"Plavno",
    "wof:placetype":"locality",
    "wof:population":253
},
  "geometry": {"coordinates":[16.18361,44.14556],"type":"Point"}
}