{
  "type": "Feature",
  "properties": {
    "gn:admin1_code":"3.0",
    "gn:asciiname":"Govedari",
    "gn:cc2":"HR",
    "gn:country_code":"HR",
    "gn:dem":131,
    "gn:feature_class":"P",
    "gn:feature_code":"PPL",
    "gn:name":"Govedari",
    "gn:population":0,
    "gn:timezone":"Europe/Zagreb",
    "iso:country":"HR",
    "name:und_x_variant":[
        "Govedar",
        "Govedari"
    ],
    "wof:name":"Govedari",
    "wof:placetype":"locality"
},
  "geometry": {"coordinates":[17.86167,42.73667],"type":"Point"}
}