{
  "type": "Feature",
  "properties": {
    "gn:admin1_code":"8.0",
    "gn:admin2_code":"11049294.0",
    "gn:asciiname":"Matici",
    "gn:cc2":"HR",
    "gn:country_code":"HR",
    "gn:dem":753,
    "gn:feature_class":"P",
    "gn:feature_code":"PPL",
    "gn:name":"Mati\u0107i",
    "gn:population":0,
    "gn:timezone":"Europe/Zagreb",
    "iso:country":"HR",
    "name:und_x_variant":[
        "Mati\u0107",
        "Mati\u0107i"
    ],
    "wof:name":"Matici",
    "wof:placetype":"locality"
},
  "geometry": {"coordinates":[15.73056,44.50556],"type":"Point"}
}