{
  "type": "Feature",
  "properties": {
    "gn:admin1_code":"19.0",
    "gn:asciiname":"Poljak",
    "gn:country_code":"HR",
    "gn:dem":26,
    "gn:feature_class":"P",
    "gn:feature_code":"PPL",
    "gn:name":"Poljak",
    "gn:population":0,
    "gn:timezone":"Europe/Zagreb",
    "iso:country":"HR",
    "wof:name":"Poljak",
    "wof:placetype":"locality"
},
  "geometry": {"coordinates":[15.27028,44.19056],"type":"Point"}
}