{
  "type": "Feature",
  "properties": {
    "gn:admin1_code":"15",
    "gn:admin2_code":"11054954.0",
    "gn:asciiname":"Ovrlje",
    "gn:cc2":"HR",
    "gn:country_code":"HR",
    "gn:dem":399,
    "gn:feature_class":"P",
    "gn:feature_code":"PPL",
    "gn:name":"Ovrlje",
    "gn:population":190,
    "gn:timezone":"Europe/Zagreb",
    "iso:country":"HR",
    "name:und_x_variant":[
        "Ovrlja",
        "Ovrlje"
    ],
    "wof:name":"Ovrlje",
    "wof:placetype":"locality",
    "wof:population":190
},
  "geometry": {"coordinates":[16.74833,43.68611],"type":"Point"}
}