{
  "type": "Feature",
  "properties": {
    "gn:admin1_code":"14",
    "gn:admin2_code":"11049229.0",
    "gn:asciiname":"Kraljeva Velika",
    "gn:cc2":"HR",
    "gn:country_code":"HR",
    "gn:dem":99,
    "gn:feature_class":"P",
    "gn:feature_code":"PPL",
    "gn:name":"Kraljeva Velika",
    "gn:population":471,
    "gn:timezone":"Europe/Zagreb",
    "iso:country":"HR",
    "name:und_x_variant":[
        "Velika Kraljeva",
        "Kraljeva Velika"
    ],
    "wof:name":"Kraljeva Velika",
    "wof:placetype":"locality",
    "wof:population":471
},
  "geometry": {"coordinates":[16.84694,45.39194000000001],"type":"Point"}
}