{
  "type": "Feature",
  "properties": {
    "gn:admin1_code":"15.0",
    "gn:asciiname":"Kastel Kamblelovac",
    "gn:country_code":"HR",
    "gn:dem":21,
    "gn:feature_class":"P",
    "gn:feature_code":"PPL",
    "gn:name":"Ka\u0161tel Kamblelovac",
    "gn:population":0,
    "gn:timezone":"Europe/Zagreb",
    "iso:country":"HR",
    "wof:name":"Kastel Kamblelovac",
    "wof:placetype":"locality"
},
  "geometry": {"coordinates":[16.40056,43.55056],"type":"Point"}
}