{
  "type": "Feature",
  "properties": {
    "gn:admin1_code":"19.0",
    "gn:asciiname":"Veselinovic",
    "gn:country_code":"HR",
    "gn:dem":377,
    "gn:feature_class":"P",
    "gn:feature_code":"PPL",
    "gn:name":"Veselinovi\u0107",
    "gn:population":0,
    "gn:timezone":"Europe/Zagreb",
    "iso:country":"HR",
    "wof:name":"Veselinovic",
    "wof:placetype":"locality"
},
  "geometry": {"coordinates":[15.825,44.21556],"type":"Point"}
}