{
  "type": "Feature",
  "properties": {
    "gn:admin1_code":"13.0",
    "gn:asciiname":"Vukovici",
    "gn:cc2":"HR",
    "gn:country_code":"HR",
    "gn:dem":315,
    "gn:feature_class":"P",
    "gn:feature_code":"PPL",
    "gn:name":"Vukovi\u0107i",
    "gn:population":0,
    "gn:timezone":"Europe/Zagreb",
    "iso:country":"HR",
    "name:und_x_variant":[
        "Vojnovi\u0107i",
        "Vukovi\u0107i"
    ],
    "wof:name":"Vukovici",
    "wof:placetype":"locality"
},
  "geometry": {"coordinates":[16.24417,44.12694000000001],"type":"Point"}
}