{
  "type": "Feature",
  "properties": {
    "gn:admin1_code":"20.0",
    "gn:asciiname":"Jamnicka Kiselica",
    "gn:country_code":"HR",
    "gn:dem":106,
    "gn:feature_class":"P",
    "gn:feature_code":"PPL",
    "gn:name":"Jamni\u010dka Kiselica",
    "gn:population":0,
    "gn:timezone":"Europe/Zagreb",
    "iso:country":"HR",
    "wof:name":"Jamnicka Kiselica",
    "wof:placetype":"locality"
},
  "geometry": {"coordinates":[15.85944,45.55278],"type":"Point"}
}