{
  "type": "Feature",
  "properties": {
    "gn:admin1_code":"09",
    "gn:admin2_code":"11054853.0",
    "gn:asciiname":"Praporcan",
    "gn:country_code":"HR",
    "gn:dem":240,
    "gn:feature_class":"P",
    "gn:feature_code":"PPL",
    "gn:name":"Prapor\u010dan",
    "gn:population":182,
    "gn:timezone":"Europe/Zagreb",
    "iso:country":"HR",
    "wof:name":"Praporcan",
    "wof:placetype":"locality",
    "wof:population":182
},
  "geometry": {"coordinates":[16.36667000000001,46.46667],"type":"Point"}
}