{
  "type": "Feature",
  "properties": {
    "gn:admin1_code":"8.0",
    "gn:asciiname":"Skladiste Gavrilovic",
    "gn:country_code":"HR",
    "gn:dem":562,
    "gn:feature_class":"P",
    "gn:feature_code":"PPL",
    "gn:name":"Skladi\u0161te Gavrilovi\u0107",
    "gn:population":0,
    "gn:timezone":"Europe/Zagreb",
    "iso:country":"HR",
    "wof:name":"Skladiste Gavrilovic",
    "wof:placetype":"locality"
},
  "geometry": {"coordinates":[15.27889,44.54389000000001],"type":"Point"}
}