{
  "type": "Feature",
  "properties": {
    "gn:gn_country":"HR",
    "gn:gn_fcode":"PPL",
    "gn:gn_pop":901,
    "gn:population":787,
    "iso:country":"HR",
    "name:bos_x_preferred":[
        "Cabuna"
    ],
    "name:ceb_x_preferred":[
        "Cabuna"
    ],
    "name:eng_x_preferred":[
        "Cabuna"
    ],
    "name:fra_x_preferred":[
        "Cabuna"
    ],
    "name:hrv_x_preferred":[
        "Cabuna"
    ],
    "name:hun_x_preferred":[
        "Cabuna"
    ],
    "name:nld_x_preferred":[
        "Cabuna"
    ],
    "name:slv_x_preferred":[
        "Cabuna"
    ],
    "name:spa_x_preferred":[
        "Cabuna"
    ],
    "name:srp_x_preferred":[
        "\u0426\u0430\u0431\u0443\u043d\u0430"
    ],
    "name:swe_x_preferred":[
        "Cabuna"
    ],
    "name:ukr_x_preferred":[
        "\u0426\u0430\u0431\u0443\u043d\u0430"
    ],
    "name:unk_x_variant":[
        "Zabuna"
    ],
    "qs_pg:aaroncc":"HR",
    "qs_pg:gn_country":"HR",
    "qs_pg:gn_fcode":"PPL",
    "qs_pg:gn_pop":901,
    "qs_pg:name":"Cabuna",
    "qs_pg:name_adm0":"Hrvatska",
    "qs_pg:name_adm1":"Viroviti\u010dko-podravska",
    "qs_pg:photos_9r":0,
    "qs_pg:photos_sr":0,
    "qs_pg:pop_sr":2,
    "qs_pg:qs_pg_placetype":"locality",
    "qs_pg:qs_pg_placetype_gp":"Town",
    "qs_pg:woe_adm0":23424843,
    "woe:adm0_id":23424843,
    "woe:name_adm0":"Hrvatska",
    "woe:name_adm1":"Viroviti\u010dko-podravska",
    "woe:placetype":"Town",
    "wof:name":"Cabuna",
    "wof:placetype":"locality",
    "wof:population":787
},
  "geometry": {"coordinates":[17.57806,45.75389],"type":"Point"}
}