{
  "type": "Feature",
  "properties": {
    "gn:admin1_code":"17",
    "gn:admin2_code":"11049455.0",
    "gn:asciiname":"Veliki Rastovac",
    "gn:country_code":"HR",
    "gn:dem":94,
    "gn:feature_class":"P",
    "gn:feature_code":"PPL",
    "gn:name":"Veliki Rastovac",
    "gn:population":238,
    "gn:timezone":"Europe/Zagreb",
    "iso:country":"HR",
    "wof:name":"Veliki Rastovac",
    "wof:placetype":"locality",
    "wof:population":238
},
  "geometry": {"coordinates":[17.98333,45.65],"type":"Point"}
}