{
  "type": "Feature",
  "properties": {
    "gn:admin1_code":"12.0",
    "gn:admin2_code":"3202931.0",
    "gn:asciiname":"Zamost",
    "gn:country_code":"HR",
    "gn:dem":338,
    "gn:feature_class":"P",
    "gn:feature_code":"PPL",
    "gn:name":"Zamost",
    "gn:population":26,
    "gn:timezone":"Europe/Zagreb",
    "iso:country":"HR",
    "name:bos_x_preferred":[
        "Zamost"
    ],
    "name:fra_x_preferred":[
        "Zamost"
    ],
    "name:hrv_x_preferred":[
        "Zamost"
    ],
    "name:hun_x_preferred":[
        "Zamost"
    ],
    "name:slv_x_preferred":[
        "Zamost"
    ],
    "name:spa_x_preferred":[
        "Zamost"
    ],
    "name:ukr_x_preferred":[
        "\u0417\u0430\u043c\u043e\u0441\u0442"
    ],
    "wof:name":"Zamost",
    "wof:placetype":"locality",
    "wof:population":26
},
  "geometry": {"coordinates":[14.68333,45.53028],"type":"Point"}
}