{
  "type": "Feature",
  "properties": {
    "gn:admin1_code":"3.0",
    "gn:admin2_code":"11054964.0",
    "gn:asciiname":"Zidinica",
    "gn:country_code":"HR",
    "gn:dem":151,
    "gn:feature_class":"P",
    "gn:feature_code":"PPL",
    "gn:name":"Zidinica",
    "gn:population":0,
    "gn:timezone":"Europe/Zagreb",
    "iso:country":"HR",
    "wof:name":"Zidinica",
    "wof:placetype":"locality"
},
  "geometry": {"coordinates":[17.49611,43.12528],"type":"Point"}
}