{
  "type": "Feature",
  "properties": {
    "gn:admin1_code":"15.0",
    "gn:asciiname":"Golinjevo",
    "gn:country_code":"HR",
    "gn:dem":409,
    "gn:feature_class":"P",
    "gn:feature_code":"PPL",
    "gn:name":"Golinjevo",
    "gn:population":0,
    "gn:timezone":"Europe/Zagreb",
    "iso:country":"HR",
    "name:bos_x_preferred":[
        "Golinjevo"
    ],
    "name:ceb_x_preferred":[
        "Golinjevo"
    ],
    "name:fra_x_preferred":[
        "Golinjevo"
    ],
    "name:hrv_x_preferred":[
        "Golinjevo"
    ],
    "name:swe_x_preferred":[
        "Golinjevo"
    ],
    "wof:name":"Golinjevo",
    "wof:placetype":"locality"
},
  "geometry": {"coordinates":[16.71417000000001,43.60778],"type":"Point"}
}