{
  "type": "Feature",
  "properties": {
    "gn:admin1_code":"08",
    "gn:admin2_code":"11049286.0",
    "gn:asciiname":"Brusane",
    "gn:cc2":"HR",
    "gn:country_code":"HR",
    "gn:dem":581,
    "gn:feature_class":"P",
    "gn:feature_code":"PPL",
    "gn:name":"Bru\u0161ane",
    "gn:population":134,
    "gn:timezone":"Europe/Zagreb",
    "iso:country":"HR",
    "name:und_x_variant":[
        "Bru\u0161ani",
        "Bru\u0161ane"
    ],
    "wof:name":"Brusane",
    "wof:placetype":"locality",
    "wof:population":134
},
  "geometry": {"coordinates":[15.27861,44.49861],"type":"Point"}
}