{
  "type": "Feature",
  "properties": {
    "gn:admin1_code":"11",
    "gn:admin2_code":"3193705.0",
    "gn:asciiname":"Dragovic",
    "gn:country_code":"HR",
    "gn:dem":216,
    "gn:feature_class":"P",
    "gn:feature_code":"PPL",
    "gn:name":"Dragovi\u0107",
    "gn:population":64,
    "gn:timezone":"Europe/Zagreb",
    "iso:country":"HR",
    "name:und_x_variant":[
        "Dragovi\u0107"
    ],
    "wof:name":"Dragovic",
    "wof:placetype":"locality",
    "wof:population":64
},
  "geometry": {"coordinates":[17.27277999999999,45.47111],"type":"Point"}
}