{
  "type": "Feature",
  "properties": {
    "gn:admin1_code":"15.0",
    "gn:asciiname":"Buljani",
    "gn:country_code":"HR",
    "gn:dem":926,
    "gn:feature_class":"P",
    "gn:feature_code":"PPL",
    "gn:name":"Buljani",
    "gn:population":0,
    "gn:timezone":"Europe/Zagreb",
    "iso:country":"HR",
    "wof:name":"Buljani",
    "wof:placetype":"locality"
},
  "geometry": {"coordinates":[16.63917,43.855],"type":"Point"}
}