{
  "type": "Feature",
  "properties": {
    "gn:population":2167,
    "iso:country":"HR",
    "name:bos_x_preferred":[
        "Rakitje"
    ],
    "name:ceb_x_preferred":[
        "Rakitje"
    ],
    "name:eng_x_preferred":[
        "Rakitje"
    ],
    "name:hbs_x_preferred":[
        "Rakitje"
    ],
    "name:hrv_x_preferred":[
        "Rakitje"
    ],
    "name:hun_x_preferred":[
        "Rakitje"
    ],
    "name:nld_x_preferred":[
        "Rakitje"
    ],
    "name:slv_x_preferred":[
        "Rakitje"
    ],
    "name:sqi_x_preferred":[
        "Rakitje"
    ],
    "name:srp_x_preferred":[
        "\u0420\u0430\u043a\u0438\u0442\u0458\u0435"
    ],
    "name:swe_x_preferred":[
        "Rakitje"
    ],
    "name:ukr_x_preferred":[
        "\u0420\u0430\u043a\u0438\u0442\u0454"
    ],
    "qs:a0":"Republika Hrvatska",
    "qs:a1":"*Zagrebacka \u017eupanija",
    "qs:a1r":"0",
    "qs:adm0":"Republika Hrvatska",
    "qs:la_lc":"*",
    "qs:level":"locality",
    "qs:loc":"Rakitje",
    "qs:loc_alt":"Rakitje",
    "qs:pop":0,
    "qs:type":"buffered point",
    "wd:wordcount":44,
    "wof:name":"Rakitje",
    "wof:placetype":"locality",
    "wof:population":2167
},
  "geometry": {"coordinates":[15.829583,45.793739],"type":"Point"}
}