{
  "type": "Feature",
  "properties": {
    "gn:gn_country":"HR",
    "gn:gn_fcode":"PPL",
    "gn:gn_pop":0,
    "gn:population":392,
    "iso:country":"HR",
    "qs_pg:aaroncc":"HR",
    "qs_pg:gn_country":"HR",
    "qs_pg:gn_fcode":"PPL",
    "qs_pg:gn_pop":0,
    "qs_pg:name":"Gornje Sitno",
    "qs_pg:name_adm0":"Hrvatska",
    "qs_pg:name_adm1":"Splitsko-Dalmatinska",
    "qs_pg:photos":29,
    "qs_pg:photos_1k":6,
    "qs_pg:photos_9k":1,
    "qs_pg:photos_9r":2,
    "qs_pg:photos_all":29,
    "qs_pg:photos_sr":2,
    "qs_pg:pop_sr":0,
    "qs_pg:qs_pg_placetype":"locality",
    "qs_pg:qs_pg_placetype_gp":"Town",
    "qs_pg:woe_adm0":23424843,
    "woe:adm0_id":23424843,
    "woe:name_adm0":"Hrvatska",
    "woe:name_adm1":"Splitsko-Dalmatinska",
    "woe:placetype":"Town",
    "wof:name":"Gornje Sitno",
    "wof:placetype":"locality",
    "wof:population":392
},
  "geometry": {"coordinates":[16.61028,43.51722],"type":"Point"}
}