{
  "type": "Feature",
  "properties": {
    "gn:country":"HR",
    "gn:fcode":"PPL",
    "gn:population":0,
    "iso:country":"HR",
    "name:bos_x_preferred":[
        "Gornje Sitno"
    ],
    "name:hrv_x_preferred":[
        "Gornje Sitno"
    ],
    "name:hun_x_preferred":[
        "Gornje Sitno"
    ],
    "name:slv_x_preferred":[
        "Gornje Sitno"
    ],
    "name:srp_x_preferred":[
        "\u0413\u043e\u0440\u045a\u0435 \u0421\u0438\u0442\u043d\u043e"
    ],
    "name:ukr_x_preferred":[
        "\u0413\u043e\u0440\u043d\u0454 \u0421\u0438\u0442\u043d\u043e"
    ],
    "qs_pg:aaroncc":"HR",
    "qs_pg:gn_country":"HR",
    "qs_pg:gn_fcode":"PPL",
    "qs_pg:gn_pop":0,
    "qs_pg:name":"Gornje Sitno",
    "qs_pg:name_adm0":"Hrvatska",
    "qs_pg:name_adm1":"Splitsko-Dalmatinska",
    "qs_pg:photos":29,
    "qs_pg:photos_1k":6,
    "qs_pg:photos_9k":1,
    "qs_pg:photos_9r":2,
    "qs_pg:photos_all":29,
    "qs_pg:photos_sr":2,
    "qs_pg:pop_sr":0,
    "qs_pg:qs_pg_placetype":"locality",
    "qs_pg:qs_pg_placetype_gp":"Town",
    "qs_pg:woe_adm0":23424843,
    "woe:adm0_id":23424843,
    "woe:name_adm0":"Hrvatska",
    "woe:name_adm1":"Splitsko-Dalmatinska",
    "woe:placetype":"Town",
    "wof:name":"Gornje Sitno",
    "wof:placetype":"locality",
    "wof:population":392
},
  "geometry": {"coordinates":[16.61028,43.51722],"type":"Point"}
}