{
  "type": "Feature",
  "properties": {
    "gn:admin1_code":"04",
    "gn:admin2_code":"11054806.0",
    "gn:asciiname":"Jadreski",
    "gn:cc2":"HR",
    "gn:country_code":"HR",
    "gn:dem":66,
    "gn:feature_class":"P",
    "gn:feature_code":"PPL",
    "gn:name":"Jadre\u0161ki",
    "gn:population":0,
    "gn:timezone":"Europe/Zagreb",
    "iso:country":"HR",
    "name:und_x_variant":[
        "Giadreschi",
        "Jadre\u0161ki"
    ],
    "wof:name":"Jadreski",
    "wof:placetype":"locality"
},
  "geometry": {"coordinates":[13.91611,44.86889],"type":"Point"}
}