{
  "type": "Feature",
  "properties": {
    "gn:admin1_code":"1.0",
    "gn:admin2_code":"11049413.0",
    "gn:asciiname":"Babotok",
    "gn:country_code":"HR",
    "gn:dem":214,
    "gn:feature_class":"P",
    "gn:feature_code":"PPL",
    "gn:name":"Babotok",
    "gn:population":112,
    "gn:timezone":"Europe/Zagreb",
    "iso:country":"HR",
    "wof:name":"Babotok",
    "wof:placetype":"locality",
    "wof:population":112
},
  "geometry": {"coordinates":[16.88332999999999,46.01667],"type":"Point"}
}