{
  "type": "Feature",
  "properties": {
    "gn:admin1_code":"1.0",
    "gn:admin2_code":"11049413.0",
    "gn:asciiname":"Babotok",
    "gn:country_code":"HR",
    "gn:dem":214,
    "gn:feature_class":"P",
    "gn:feature_code":"PPL",
    "gn:name":"Babotok",
    "gn:population":112,
    "gn:timezone":"Europe/Zagreb",
    "iso:country":"HR",
    "name:bos_x_preferred":[
        "Babotok"
    ],
    "name:ceb_x_preferred":[
        "Babotok"
    ],
    "name:hrv_x_preferred":[
        "Babotok"
    ],
    "name:hun_x_preferred":[
        "Babotok"
    ],
    "name:nld_x_preferred":[
        "Babotok"
    ],
    "name:slv_x_preferred":[
        "Babotok"
    ],
    "name:spa_x_preferred":[
        "Babotok"
    ],
    "name:swe_x_preferred":[
        "Babotok"
    ],
    "name:ukr_x_preferred":[
        "\u0411\u0430\u0431\u043e\u0442\u043e\u043a"
    ],
    "wof:name":"Babotok",
    "wof:placetype":"locality",
    "wof:population":112
},
  "geometry": {"coordinates":[16.88332999999999,46.01667],"type":"Point"}
}