{
  "type": "Feature",
  "properties": {
    "gn:admin1_code":"20",
    "gn:admin2_code":"11048999.0",
    "gn:asciiname":"Velika Jamnicka",
    "gn:cc2":"HR",
    "gn:country_code":"HR",
    "gn:dem":139,
    "gn:feature_class":"P",
    "gn:feature_code":"PPL",
    "gn:name":"Velika Jamni\u010dka",
    "gn:population":195,
    "gn:timezone":"Europe/Zagreb",
    "iso:country":"HR",
    "name:und_x_variant":[
        "Velika",
        "Velika Jamni\u010dka"
    ],
    "wof:name":"Velika Jamnicka",
    "wof:placetype":"locality",
    "wof:population":195
},
  "geometry": {"coordinates":[15.84667,45.605],"type":"Point"}
}