{
  "type": "Feature",
  "properties": {
    "gn:admin1_code":"5.0",
    "gn:admin2_code":"3187450.0",
    "gn:asciiname":"Stakorovica",
    "gn:country_code":"HR",
    "gn:dem":183,
    "gn:feature_class":"P",
    "gn:feature_code":"PPLL",
    "gn:name":"\u0160takorovica",
    "gn:population":0,
    "gn:timezone":"Europe/Zagreb",
    "iso:country":"HR",
    "wof:name":"Stakorovica",
    "wof:placetype":"locality"
},
  "geometry": {"coordinates":[15.76341,45.23513],"type":"Point"}
}