{
  "type": "Feature",
  "properties": {
    "gn:admin1_code":"15",
    "gn:admin2_code":"11054733.0",
    "gn:asciiname":"Grabovac",
    "gn:country_code":"HR",
    "gn:dem":327,
    "gn:feature_class":"P",
    "gn:feature_code":"PPL",
    "gn:name":"Grabovac",
    "gn:population":372,
    "gn:timezone":"Europe/Zagreb",
    "iso:country":"HR",
    "wof:name":"Grabovac",
    "wof:placetype":"locality",
    "wof:population":372
},
  "geometry": {"coordinates":[16.98667,43.43083],"type":"Point"}
}