{
  "type": "Feature",
  "properties": {
    "gn:admin1_code":"15",
    "gn:admin2_code":"11054733.0",
    "gn:asciiname":"Grabovac",
    "gn:country_code":"HR",
    "gn:dem":327,
    "gn:feature_class":"P",
    "gn:feature_code":"PPL",
    "gn:name":"Grabovac",
    "gn:population":372,
    "gn:timezone":"Europe/Zagreb",
    "iso:country":"HR",
    "name:bos_x_preferred":[
        "Grabovac"
    ],
    "name:ceb_x_preferred":[
        "Grabovac"
    ],
    "name:deu_x_preferred":[
        "Grabovac"
    ],
    "name:fra_x_preferred":[
        "Grabovac"
    ],
    "name:hrv_x_preferred":[
        "Grabovac"
    ],
    "name:hun_x_preferred":[
        "Grabovac"
    ],
    "name:nld_x_preferred":[
        "Grabovac"
    ],
    "name:rus_x_preferred":[
        "\u0413\u0440\u0430\u0431\u043e\u0432\u0430\u0446"
    ],
    "name:slv_x_preferred":[
        "Grabovac"
    ],
    "name:srp_x_preferred":[
        "\u0413\u0440\u0430\u0431\u043e\u0432\u0430\u0446"
    ],
    "name:swe_x_preferred":[
        "Grabovac"
    ],
    "wof:name":"Grabovac",
    "wof:placetype":"locality",
    "wof:population":372
},
  "geometry": {"coordinates":[16.98667,43.43083],"type":"Point"}
}