{
  "type": "Feature",
  "properties": {
    "gn:admin1_code":"15.0",
    "gn:asciiname":"Bojana",
    "gn:country_code":"HR",
    "gn:dem":404,
    "gn:feature_class":"P",
    "gn:feature_code":"PPL",
    "gn:name":"Bojana",
    "gn:population":0,
    "gn:timezone":"Europe/Zagreb",
    "iso:country":"HR",
    "name:bos_x_preferred":[
        "Bojana"
    ],
    "name:ceb_x_preferred":[
        "Bojana"
    ],
    "name:ces_x_preferred":[
        "Bojana"
    ],
    "name:deu_x_preferred":[
        "Bojana"
    ],
    "name:fra_x_preferred":[
        "Bojana"
    ],
    "name:hun_x_preferred":[
        "Bojana"
    ],
    "name:nld_x_preferred":[
        "Bojana"
    ],
    "name:pol_x_preferred":[
        "Bojana"
    ],
    "name:slv_x_preferred":[
        "Bojana"
    ],
    "name:srp_x_preferred":[
        "\u0411\u043e\u0458\u0430\u043d\u0430"
    ],
    "name:swe_x_preferred":[
        "Bojana"
    ],
    "wof:name":"Bojana",
    "wof:placetype":"locality"
},
  "geometry": {"coordinates":[16.77639,43.52528],"type":"Point"}
}