{
  "type": "Feature",
  "properties": {
    "gn:admin1_code":"14",
    "gn:admin2_code":"3196862.0",
    "gn:asciiname":"Sartovac",
    "gn:country_code":"HR",
    "gn:dem":143,
    "gn:feature_class":"P",
    "gn:feature_code":"PPL",
    "gn:name":"\u0160artovac",
    "gn:population":380,
    "gn:timezone":"Europe/Zagreb",
    "iso:country":"HR",
    "name:bos_x_preferred":[
        "\u0160artovac"
    ],
    "name:ceb_x_preferred":[
        "\u0160artovac"
    ],
    "name:fra_x_preferred":[
        "\u0160artovac"
    ],
    "name:hrv_x_preferred":[
        "\u0160artovac"
    ],
    "name:hun_x_preferred":[
        "\u0160artovac"
    ],
    "name:nld_x_preferred":[
        "\u0160artovac"
    ],
    "name:slv_x_preferred":[
        "\u0160artovac"
    ],
    "name:spa_x_preferred":[
        "\u0160artovac"
    ],
    "name:srp_x_preferred":[
        "\u0428\u0430\u0440\u0442\u043e\u0432\u0430\u0446"
    ],
    "name:swe_x_preferred":[
        "\u0160artovac"
    ],
    "name:ukr_x_preferred":[
        "\u0428\u0430\u0440\u0442\u043e\u0432\u0430\u0446\u044c"
    ],
    "wof:name":"Sartovac",
    "wof:placetype":"locality",
    "wof:population":380
},
  "geometry": {"coordinates":[16.79917,45.51417],"type":"Point"}
}