{
  "type": "Feature",
  "properties": {
    "gn:admin1_code":"8.0",
    "gn:admin2_code":"11049295.0",
    "gn:asciiname":"Bogdanovici",
    "gn:cc2":"HR",
    "gn:country_code":"HR",
    "gn:dem":810,
    "gn:feature_class":"P",
    "gn:feature_code":"PPL",
    "gn:name":"Bogdanovi\u0107i",
    "gn:population":0,
    "gn:timezone":"Europe/Zagreb",
    "iso:country":"HR",
    "name:und_x_variant":[
        "Bogdanovi\u0107",
        "Bogdanovi\u0107i"
    ],
    "wof:name":"Bogdanovici",
    "wof:placetype":"locality"
},
  "geometry": {"coordinates":[15.46833,44.82194000000001],"type":"Point"}
}