{
  "type": "Feature",
  "properties": {
    "gn:admin1_code":"05",
    "gn:admin2_code":"3193753.0",
    "gn:asciiname":"Police-Pirisce",
    "gn:cc2":"HR",
    "gn:country_code":"HR",
    "gn:dem":206,
    "gn:feature_class":"P",
    "gn:feature_code":"PPL",
    "gn:name":"Police-Piri\u0161\u0107e",
    "gn:population":0,
    "gn:timezone":"Europe/Zagreb",
    "iso:country":"HR",
    "name:und_x_variant":[
        "Police",
        "Police-Piri\u0161\u0107e"
    ],
    "wof:name":"Police-Pirisce",
    "wof:placetype":"locality"
},
  "geometry": {"coordinates":[15.43333,45.63333],"type":"Point"}
}