{
  "type": "Feature",
  "properties": {
    "gn:admin1_code":"20",
    "gn:admin2_code":"3186780.0",
    "gn:asciiname":"Ivanec Bistranski",
    "gn:cc2":"HR",
    "gn:country_code":"HR",
    "gn:dem":124,
    "gn:feature_class":"P",
    "gn:feature_code":"PPL",
    "gn:name":"Ivanec Bistranski",
    "gn:population":937,
    "gn:timezone":"Europe/Zagreb",
    "iso:country":"HR",
    "name:und_x_variant":[
        "Bistranski Ivanec",
        "Ivanec Gornji",
        "Ivanec",
        "Ivanec Bistranski"
    ],
    "wof:name":"Ivanec Bistranski",
    "wof:placetype":"locality",
    "wof:population":937
},
  "geometry": {"coordinates":[15.83139,45.84694],"type":"Point"}
}