{
  "type": "Feature",
  "properties": {
    "gn:admin1_code":"19.0",
    "gn:asciiname":"Zavlaka",
    "gn:country_code":"HR",
    "gn:dem":747,
    "gn:feature_class":"P",
    "gn:feature_code":"PPL",
    "gn:name":"Zavlaka",
    "gn:population":0,
    "gn:timezone":"Europe/Zagreb",
    "iso:country":"HR",
    "name:fra_x_preferred":[
        "Zavlaka"
    ],
    "name:msa_x_preferred":[
        "Zavlaka"
    ],
    "name:nld_x_preferred":[
        "Zavlaka"
    ],
    "name:por_x_preferred":[
        "Zavlaka"
    ],
    "name:slv_x_preferred":[
        "Zavlaka"
    ],
    "name:srp_x_preferred":[
        "\u0417\u0430\u0432\u043b\u0430\u043a\u0430"
    ],
    "wof:name":"Zavlaka",
    "wof:placetype":"locality"
},
  "geometry": {"coordinates":[16.17833,44.31778],"type":"Point"}
}