{
  "type": "Feature",
  "properties": {
    "gn:admin1_code":"8.0",
    "gn:asciiname":"Cukovac",
    "gn:country_code":"HR",
    "gn:dem":587,
    "gn:feature_class":"P",
    "gn:feature_code":"PPL",
    "gn:name":"Cukovac",
    "gn:population":0,
    "gn:timezone":"Europe/Zagreb",
    "iso:country":"HR",
    "wof:name":"Cukovac",
    "wof:placetype":"locality"
},
  "geometry": {"coordinates":[15.44806,44.59528],"type":"Point"}
}