{
  "type": "Feature",
  "properties": {
    "gn:admin1_code":"14.0",
    "gn:asciiname":"Januzovici",
    "gn:country_code":"HR",
    "gn:dem":157,
    "gn:feature_class":"P",
    "gn:feature_code":"PPL",
    "gn:name":"Januzovi\u0107i",
    "gn:population":0,
    "gn:timezone":"Europe/Zagreb",
    "iso:country":"HR",
    "wof:name":"Januzovici",
    "wof:placetype":"locality"
},
  "geometry": {"coordinates":[16.3675,45.12333],"type":"Point"}
}