{
  "type": "Feature",
  "properties": {
    "gn:admin1_code":"19",
    "gn:admin2_code":"11054376.0",
    "gn:asciiname":"Miletici",
    "gn:country_code":"HR",
    "gn:dem":34,
    "gn:feature_class":"P",
    "gn:feature_code":"PPL",
    "gn:name":"Mileti\u0107i",
    "gn:population":0,
    "gn:timezone":"Europe/Zagreb",
    "iso:country":"HR",
    "wof:name":"Miletici",
    "wof:placetype":"locality"
},
  "geometry": {"coordinates":[15.27639,44.31194],"type":"Point"}
}