{
  "type": "Feature",
  "properties": {
    "gn:country":"HR",
    "gn:fcode":"PPL",
    "gn:population":898,
    "iso:country":"HR",
    "name:bos_x_preferred":[
        "\u0160mrika"
    ],
    "name:cat_x_preferred":[
        "\u0160mrika"
    ],
    "name:ceb_x_preferred":[
        "\u0160mrika"
    ],
    "name:eng_x_preferred":[
        "\u0160mrika"
    ],
    "name:fra_x_preferred":[
        "\u0160mrika"
    ],
    "name:hrv_x_preferred":[
        "\u0160mrika"
    ],
    "name:hun_x_preferred":[
        "\u0160mrika"
    ],
    "name:ita_x_preferred":[
        "Smericca"
    ],
    "name:nld_x_preferred":[
        "\u0160mrika"
    ],
    "name:pol_x_preferred":[
        "\u0160mrika"
    ],
    "name:slv_x_preferred":[
        "\u0160mrika"
    ],
    "name:spa_x_preferred":[
        "\u0160mrika"
    ],
    "name:srp_x_preferred":[
        "\u0428\u043c\u0440\u0438\u043a\u0430"
    ],
    "name:swe_x_preferred":[
        "\u0160mrika"
    ],
    "name:ukr_x_preferred":[
        "\u0428\u043c\u0440\u0438\u043a\u0430"
    ],
    "name:und_x_variant":[
        "\u0160mrika Burice"
    ],
    "qs_pg:aaroncc":"HR",
    "qs_pg:gn_country":"HR",
    "qs_pg:gn_fcode":"PPL",
    "qs_pg:gn_pop":898,
    "qs_pg:name":"\u0160mrika",
    "qs_pg:photos_9r":0,
    "qs_pg:photos_sr":0,
    "qs_pg:pop_sr":2,
    "qs_pg:qs_pg_placetype":"locality",
    "wof:name":"\u0160mrika",
    "wof:placetype":"locality",
    "wof:population":988
},
  "geometry": {"coordinates":[14.60167,45.24972],"type":"Point"}
}