{
  "type": "Feature",
  "properties": {
    "gn:gn_country":"HR",
    "gn:gn_fcode":"PPL",
    "gn:gn_pop":0,
    "iso:country":"HR",
    "name:bos_x_preferred":[
        "Lo\u017ei\u0161\u0107a"
    ],
    "name:ces_x_preferred":[
        "Lo\u017ei\u0161\u0107a"
    ],
    "name:deu_x_preferred":[
        "Lo\u017ei\u0161\u0107a"
    ],
    "name:eng_x_preferred":[
        "Lo\u017ei\u0161\u0107a"
    ],
    "name:hrv_x_preferred":[
        "Lo\u017ei\u0161\u0107a"
    ],
    "name:hun_x_preferred":[
        "Lo\u017ei\u0161\u0107a"
    ],
    "name:nld_x_preferred":[
        "Lo\u017ei\u0161\u0107a"
    ],
    "name:nno_x_preferred":[
        "Lo\u017ei\u0161\u0107a"
    ],
    "name:nob_x_preferred":[
        "Lo\u017ei\u0161\u0107a"
    ],
    "name:slk_x_preferred":[
        "Lo\u017ei\u0161\u0107a"
    ],
    "name:slv_x_preferred":[
        "Lo\u017ei\u0161\u0107a"
    ],
    "name:sme_x_preferred":[
        "Lo\u017ei\u0161\u0107a"
    ],
    "name:srp_x_preferred":[
        "\u041b\u043e\u0436\u0438\u0448\u045b\u0430"
    ],
    "name:ukr_x_preferred":[
        "\u041b\u043e\u0436\u0438\u0449\u0430"
    ],
    "name:unk_x_variant":[
        "Lo\u017ei\u0161\u0107a"
    ],
    "qs_pg:aaroncc":"HR",
    "qs_pg:gn_country":"HR",
    "qs_pg:gn_fcode":"PPL",
    "qs_pg:gn_pop":0,
    "qs_pg:name":"Lo\u017ei\u0161\u0107e",
    "qs_pg:name_adm0":"Hrvatska",
    "qs_pg:name_adm1":"Splitsko-Dalmatinska",
    "qs_pg:photos":219,
    "qs_pg:photos_1k":44,
    "qs_pg:photos_9k":1,
    "qs_pg:photos_9r":4,
    "qs_pg:photos_all":219,
    "qs_pg:photos_sr":4,
    "qs_pg:pop_sr":0,
    "qs_pg:qs_pg_placetype":"locality",
    "qs_pg:qs_pg_placetype_gp":"Town",
    "qs_pg:woe_adm0":23424843,
    "woe:adm0_id":23424843,
    "woe:name_adm0":"Hrvatska",
    "woe:name_adm1":"Splitsko-Dalmatinska",
    "woe:placetype":"Town",
    "wof:name":"Lo\u017ei\u0161\u0107e",
    "wof:placetype":"locality"
},
  "geometry": {"coordinates":[16.48028,43.34694],"type":"Point"}
}