{
  "type": "Feature",
  "properties": {
    "gn:admin1_code":"19.0",
    "gn:asciiname":"Marinovic",
    "gn:country_code":"HR",
    "gn:dem":109,
    "gn:feature_class":"P",
    "gn:feature_code":"PPL",
    "gn:name":"Marinovi\u0107",
    "gn:population":0,
    "gn:timezone":"Europe/Zagreb",
    "iso:country":"HR",
    "wof:name":"Marinovic",
    "wof:placetype":"locality"
},
  "geometry": {"coordinates":[15.4575,44.08667],"type":"Point"}
}