{
  "type": "Feature",
  "properties": {
    "gn:admin1_code":"4.0",
    "gn:admin2_code":"11054816.0",
    "gn:asciiname":"Barbici",
    "gn:cc2":"HR",
    "gn:country_code":"HR",
    "gn:dem":244,
    "gn:feature_class":"P",
    "gn:feature_code":"PPL",
    "gn:name":"Barbi\u0107i",
    "gn:population":66,
    "gn:timezone":"Europe/Zagreb",
    "iso:country":"HR",
    "name:und_x_variant":[
        "Barbich",
        "Villa Barbi",
        "Barbi\u0107i"
    ],
    "wof:name":"Barbici",
    "wof:placetype":"locality",
    "wof:population":66
},
  "geometry": {"coordinates":[14.05306,45.08694000000001],"type":"Point"}
}