{
  "type": "Feature",
  "properties": {
    "gn:admin1_code":"4.0",
    "gn:admin2_code":"3193560.0",
    "gn:asciiname":"Brajkovici",
    "gn:country_code":"HR",
    "gn:dem":401,
    "gn:feature_class":"P",
    "gn:feature_code":"PPL",
    "gn:name":"Brajkovi\u0107i",
    "gn:population":0,
    "gn:timezone":"Europe/Zagreb",
    "iso:country":"HR",
    "wof:name":"Brajkovici",
    "wof:placetype":"locality"
},
  "geometry": {"coordinates":[13.85944,45.25778],"type":"Point"}
}