{
  "type": "Feature",
  "properties": {
    "gn:admin1_code":"10.0",
    "gn:admin2_code":"11055020.0",
    "gn:asciiname":"Boksic",
    "gn:cc2":"HR",
    "gn:country_code":"HR",
    "gn:dem":99,
    "gn:feature_class":"P",
    "gn:feature_code":"PPL",
    "gn:name":"Bok\u0161i\u0107",
    "gn:population":433,
    "gn:timezone":"Europe/Zagreb",
    "iso:country":"HR",
    "name:und_x_variant":[
        "Boksich",
        "Bok\u0161i\u0107i",
        "Bok\u0161i\u0107"
    ],
    "wof:name":"Boksic",
    "wof:placetype":"locality",
    "wof:population":433
},
  "geometry": {"coordinates":[18.03167,45.58806],"type":"Point"}
}