{
  "type": "Feature",
  "properties": {
    "gn:admin1_code":"16",
    "gn:asciiname":"Crnec Biskupecki",
    "gn:cc2":"HR",
    "gn:country_code":"HR",
    "gn:dem":166,
    "gn:feature_class":"P",
    "gn:feature_code":"PPL",
    "gn:name":"\u010crnec Bi\u0161kupe\u010dki",
    "gn:population":696,
    "gn:timezone":"Europe/Zagreb",
    "iso:country":"HR",
    "name:und_x_variant":[
        "Crnec",
        "Bi\u0161kupe\u010dki \u010crnec",
        "\u010crnec Bi\u0161kupe\u010dki"
    ],
    "wof:name":"Crnec Biskupecki",
    "wof:placetype":"locality",
    "wof:population":696
},
  "geometry": {"coordinates":[16.35,46.26667],"type":"Point"}
}