{
  "type": "Feature",
  "properties": {
    "gn:admin1_code":"08",
    "gn:admin2_code":"11049287.0",
    "gn:asciiname":"Konjsko",
    "gn:country_code":"HR",
    "gn:dem":611,
    "gn:feature_class":"P",
    "gn:feature_code":"PPL",
    "gn:name":"Konjsko",
    "gn:population":0,
    "gn:timezone":"Europe/Zagreb",
    "iso:country":"HR",
    "name:bos_x_preferred":[
        "Konjsko"
    ],
    "name:ceb_x_preferred":[
        "Konjsko"
    ],
    "name:fra_x_preferred":[
        "Konjsko"
    ],
    "name:hrv_x_preferred":[
        "Konjsko"
    ],
    "name:hun_x_preferred":[
        "Konjsko"
    ],
    "name:nld_x_preferred":[
        "Konjsko"
    ],
    "name:slv_x_preferred":[
        "Konjsko"
    ],
    "name:srp_x_preferred":[
        "\u041a\u043e\u045a\u0441\u043a\u043e"
    ],
    "name:swe_x_preferred":[
        "Konjsko"
    ],
    "wof:name":"Konjsko",
    "wof:placetype":"locality"
},
  "geometry": {"coordinates":[15.14444,44.5125],"type":"Point"}
}