{
  "type": "Feature",
  "properties": {
    "gn:admin1_code":"20",
    "gn:admin2_code":"3198798.0",
    "gn:asciiname":"Volavje",
    "gn:country_code":"HR",
    "gn:dem":134,
    "gn:feature_class":"P",
    "gn:feature_code":"PPL",
    "gn:name":"Volavje",
    "gn:population":398,
    "gn:timezone":"Europe/Zagreb",
    "iso:country":"HR",
    "name:bos_x_preferred":[
        "Volavje"
    ],
    "name:hrv_x_preferred":[
        "Volavje"
    ],
    "name:hun_x_preferred":[
        "Volavje"
    ],
    "name:nld_x_preferred":[
        "Volavje"
    ],
    "name:slv_x_preferred":[
        "Volavje"
    ],
    "name:srp_x_preferred":[
        "\u0412\u043e\u043b\u0430\u0432\u0458\u0435"
    ],
    "name:ukr_x_preferred":[
        "\u0412\u043e\u043b\u0430\u0432'\u0454"
    ],
    "wof:name":"Volavje",
    "wof:placetype":"locality",
    "wof:population":398
},
  "geometry": {"coordinates":[15.61083,45.65556],"type":"Point"}
}