{
  "type": "Feature",
  "properties": {
    "gn:admin1_code":"20",
    "gn:admin2_code":"3198798.0",
    "gn:asciiname":"Volavje",
    "gn:country_code":"HR",
    "gn:dem":134,
    "gn:feature_class":"P",
    "gn:feature_code":"PPL",
    "gn:name":"Volavje",
    "gn:population":398,
    "gn:timezone":"Europe/Zagreb",
    "iso:country":"HR",
    "wof:name":"Volavje",
    "wof:placetype":"locality",
    "wof:population":398
},
  "geometry": {"coordinates":[15.61083,45.65556],"type":"Point"}
}