{
  "type": "Feature",
  "properties": {
    "gn:gn_country":"HR",
    "gn:gn_fcode":"PPL",
    "gn:gn_pop":0,
    "iso:country":"HR",
    "name:bos_x_preferred":[
        "Stomorska"
    ],
    "name:bul_x_preferred":[
        "\u0421\u0442\u043e\u043c\u043e\u0440\u0441\u043a\u0430"
    ],
    "name:deu_x_preferred":[
        "Stomorska"
    ],
    "name:eng_x_preferred":[
        "Stomorska"
    ],
    "name:fra_x_preferred":[
        "Stomorska"
    ],
    "name:hrv_x_preferred":[
        "Stomorska"
    ],
    "name:hun_x_preferred":[
        "Stomorska"
    ],
    "name:ita_x_preferred":[
        "Stomorska"
    ],
    "name:nld_x_preferred":[
        "Stomorska"
    ],
    "name:slv_x_preferred":[
        "Stomorska"
    ],
    "name:spa_x_preferred":[
        "Stomorska"
    ],
    "name:srp_x_preferred":[
        "\u0421\u0442\u043e\u043c\u043e\u0440\u0441\u043a\u0430"
    ],
    "name:swe_x_preferred":[
        "Stomorska"
    ],
    "qs_pg:aaroncc":"HR",
    "qs_pg:gn_country":"HR",
    "qs_pg:gn_fcode":"PPL",
    "qs_pg:gn_pop":0,
    "qs_pg:name":"Stomorska",
    "qs_pg:name_adm0":"Hrvatska",
    "qs_pg:name_adm1":"Splitsko-Dalmatinska",
    "qs_pg:photos":918,
    "qs_pg:photos_1k":186,
    "qs_pg:photos_9k":4,
    "qs_pg:photos_9r":6,
    "qs_pg:photos_all":918,
    "qs_pg:photos_sr":10,
    "qs_pg:pop_sr":0,
    "qs_pg:qs_pg_placetype":"locality",
    "qs_pg:qs_pg_placetype_gp":"Town",
    "qs_pg:woe_adm0":23424843,
    "woe:adm0_id":23424843,
    "woe:name_adm0":"Hrvatska",
    "woe:name_adm1":"Splitsko-Dalmatinska",
    "woe:placetype":"Town",
    "wof:name":"Stomorska",
    "wof:placetype":"locality"
},
  "geometry": {"coordinates":[16.35167,43.37],"type":"Point"}
}