{
  "type": "Feature",
  "properties": {
    "gn:admin1_code":"05",
    "gn:admin2_code":"11049279.0",
    "gn:asciiname":"Jasenovica",
    "gn:country_code":"HR",
    "gn:dem":222,
    "gn:feature_class":"P",
    "gn:feature_code":"PPL",
    "gn:name":"Jasenovica",
    "gn:population":25,
    "gn:timezone":"Europe/Zagreb",
    "iso:country":"HR",
    "wof:name":"Jasenovica",
    "wof:placetype":"locality",
    "wof:population":25
},
  "geometry": {"coordinates":[15.36667,45.58333],"type":"Point"}
}