{
  "type": "Feature",
  "properties": {
    "gn:admin1_code":"15.0",
    "gn:asciiname":"Braculji",
    "gn:country_code":"HR",
    "gn:dem":479,
    "gn:feature_class":"P",
    "gn:feature_code":"PPL",
    "gn:name":"Bra\u010dulji",
    "gn:population":0,
    "gn:timezone":"Europe/Zagreb",
    "iso:country":"HR",
    "wof:name":"Braculji",
    "wof:placetype":"locality"
},
  "geometry": {"coordinates":[16.65139,43.80944],"type":"Point"}
}