{
  "type": "Feature",
  "properties": {
    "gn:admin1_code":"12",
    "gn:admin2_code":"11049443.0",
    "gn:asciiname":"Rukavac",
    "gn:cc2":"HR",
    "gn:country_code":"HR",
    "gn:dem":371,
    "gn:feature_class":"P",
    "gn:feature_code":"PPL",
    "gn:name":"Rukavac",
    "gn:population":853,
    "gn:timezone":"Europe/Zagreb",
    "iso:country":"HR",
    "name:und_x_variant":[
        "Ruccavazzo",
        "Rukavac"
    ],
    "wof:name":"Rukavac",
    "wof:placetype":"locality",
    "wof:population":853
},
  "geometry": {"coordinates":[14.29444,45.3625],"type":"Point"}
}