{
  "type": "Feature",
  "properties": {
    "gn:admin1_code":"12",
    "gn:admin2_code":"11049443.0",
    "gn:asciiname":"Rukavac",
    "gn:cc2":"HR",
    "gn:country_code":"HR",
    "gn:dem":371,
    "gn:feature_class":"P",
    "gn:feature_code":"PPL",
    "gn:name":"Rukavac",
    "gn:population":853,
    "gn:timezone":"Europe/Zagreb",
    "iso:country":"HR",
    "name:bos_x_preferred":[
        "Rukavac"
    ],
    "name:ceb_x_preferred":[
        "Rukavac"
    ],
    "name:hrv_x_preferred":[
        "Rukavac"
    ],
    "name:hun_x_preferred":[
        "Rukavac"
    ],
    "name:slv_x_preferred":[
        "Rukavac"
    ],
    "name:srp_x_preferred":[
        "\u0420\u0443\u043a\u0430\u0432\u0430\u0446"
    ],
    "name:swe_x_preferred":[
        "Rukavac"
    ],
    "name:und_x_variant":[
        "Ruccavazzo"
    ],
    "wof:name":"Rukavac",
    "wof:placetype":"locality",
    "wof:population":853
},
  "geometry": {"coordinates":[14.29444,45.3625],"type":"Point"}
}