{
  "type": "Feature",
  "properties": {
    "gn:admin1_code":"04",
    "gn:admin2_code":"11054749.0",
    "gn:asciiname":"Paz",
    "gn:country_code":"HR",
    "gn:dem":320,
    "gn:feature_class":"P",
    "gn:feature_code":"PPL",
    "gn:name":"Paz",
    "gn:population":72,
    "gn:timezone":"Europe/Zagreb",
    "iso:country":"HR",
    "name:bos_x_preferred":[
        "Paz"
    ],
    "name:fra_x_preferred":[
        "Paz"
    ],
    "name:hrv_x_preferred":[
        "Paz"
    ],
    "name:hun_x_preferred":[
        "Paz"
    ],
    "name:pol_x_preferred":[
        "Paz"
    ],
    "name:slv_x_preferred":[
        "Paz"
    ],
    "name:srp_x_preferred":[
        "\u041f\u0430\u0437"
    ],
    "name:ukr_x_preferred":[
        "\u041f\u0430\u0437"
    ],
    "wof:name":"Paz",
    "wof:placetype":"locality",
    "wof:population":72
},
  "geometry": {"coordinates":[14.0925,45.28972],"type":"Point"}
}