{
  "type": "Feature",
  "properties": {
    "gn:admin1_code":"5.0",
    "gn:asciiname":"Drenovac",
    "gn:country_code":"HR",
    "gn:dem":424,
    "gn:feature_class":"P",
    "gn:feature_code":"PPL",
    "gn:name":"Drenovac",
    "gn:population":0,
    "gn:timezone":"Europe/Zagreb",
    "iso:country":"HR",
    "name:bos_x_preferred":[
        "Drenovac"
    ],
    "name:ceb_x_preferred":[
        "Drenovac"
    ],
    "name:fra_x_preferred":[
        "Drenovac"
    ],
    "name:por_x_preferred":[
        "Drenovac"
    ],
    "name:slv_x_preferred":[
        "Drenovac"
    ],
    "name:srp_x_preferred":[
        "\u0414\u0440\u0435\u043d\u043e\u0432\u0430\u0446"
    ],
    "name:swe_x_preferred":[
        "Drenovac"
    ],
    "wof:name":"Drenovac",
    "wof:placetype":"locality"
},
  "geometry": {"coordinates":[15.62194,44.95083],"type":"Point"}
}