{
  "type": "Feature",
  "properties": {
    "gn:admin1_code":"5.0",
    "gn:admin2_code":"11049276.0",
    "gn:asciiname":"Brajakovo Brdo",
    "gn:country_code":"HR",
    "gn:dem":232,
    "gn:feature_class":"P",
    "gn:feature_code":"PPL",
    "gn:name":"Brajakovo Brdo",
    "gn:population":116,
    "gn:timezone":"Europe/Zagreb",
    "iso:country":"HR",
    "name:bos_x_preferred":[
        "Brajakovo Brdo"
    ],
    "name:cat_x_preferred":[
        "Brajakovo Brdo"
    ],
    "name:ceb_x_preferred":[
        "Brajakovo Brdo"
    ],
    "name:hrv_x_preferred":[
        "Brajakovo Brdo"
    ],
    "name:hun_x_preferred":[
        "Brajakovo Brdo"
    ],
    "name:slv_x_preferred":[
        "Brajakovo Brdo"
    ],
    "name:spa_x_preferred":[
        "Brajakovo Brdo"
    ],
    "name:srp_x_preferred":[
        "\u0411\u0440\u0430\u0458\u0430\u043a\u043e\u0432\u043e \u0411\u0440\u0434\u043e"
    ],
    "name:swe_x_preferred":[
        "Brajakovo Brdo"
    ],
    "name:ukr_x_preferred":[
        "\u0411\u0440\u0430\u044f\u043a\u043e\u0432\u043e \u0411\u0440\u0434\u043e"
    ],
    "wof:name":"Brajakovo Brdo",
    "wof:placetype":"locality",
    "wof:population":116
},
  "geometry": {"coordinates":[15.43333,45.51667],"type":"Point"}
}