{
  "type": "Feature",
  "properties": {
    "gn:admin1_code":"5.0",
    "gn:admin2_code":"11049276.0",
    "gn:asciiname":"Brajakovo Brdo",
    "gn:country_code":"HR",
    "gn:dem":232,
    "gn:feature_class":"P",
    "gn:feature_code":"PPL",
    "gn:name":"Brajakovo Brdo",
    "gn:population":116,
    "gn:timezone":"Europe/Zagreb",
    "iso:country":"HR",
    "wof:name":"Brajakovo Brdo",
    "wof:placetype":"locality",
    "wof:population":116
},
  "geometry": {"coordinates":[15.43333,45.51667],"type":"Point"}
}