{
  "type": "Feature",
  "properties": {
    "gn:gn_country":"HR",
    "gn:gn_fcode":"PPL",
    "gn:gn_pop":951,
    "gn:population":897,
    "iso:country":"HR",
    "name:bos_x_preferred":[
        "Hrastelnica"
    ],
    "name:deu_x_preferred":[
        "Hrastelnica"
    ],
    "name:eng_x_preferred":[
        "Hrastelnica"
    ],
    "name:hrv_x_preferred":[
        "Hrastelnica"
    ],
    "name:hun_x_preferred":[
        "Hrastelnica"
    ],
    "name:nld_x_preferred":[
        "Hrastelnica"
    ],
    "name:slv_x_preferred":[
        "Hrastelnica"
    ],
    "name:srp_x_preferred":[
        "\u0425\u0440\u0430\u0441\u0442\u0435\u043b\u043d\u0438\u0446\u0430"
    ],
    "name:swe_x_preferred":[
        "Hrastelnica"
    ],
    "name:tur_x_preferred":[
        "Hrastelnica"
    ],
    "qs_pg:aaroncc":"HR",
    "qs_pg:gn_country":"HR",
    "qs_pg:gn_fcode":"PPL",
    "qs_pg:gn_pop":951,
    "qs_pg:name":"Hrastelnica",
    "qs_pg:name_adm0":"Hrvatska",
    "qs_pg:name_adm1":"Sisa\u010dko-moslava\u010dka",
    "qs_pg:photos_9r":0,
    "qs_pg:photos_sr":0,
    "qs_pg:pop_sr":2,
    "qs_pg:qs_pg_placetype":"locality",
    "qs_pg:qs_pg_placetype_gp":"Town",
    "qs_pg:woe_adm0":23424843,
    "woe:adm0_id":23424843,
    "woe:name_adm0":"Hrvatska",
    "woe:name_adm1":"Sisa\u010dko-moslava\u010dka",
    "woe:placetype":"Town",
    "wof:name":"Hrastelnica",
    "wof:placetype":"locality",
    "wof:population":897
},
  "geometry": {"coordinates":[16.4175,45.50222],"type":"Point"}
}