{
  "type": "Feature",
  "properties": {
    "gn:admin1_code":"05",
    "gn:admin2_code":"3190522.0",
    "gn:asciiname":"Bukovac Perjasicki",
    "gn:cc2":"HR",
    "gn:country_code":"HR",
    "gn:dem":228,
    "gn:feature_class":"P",
    "gn:feature_code":"PPL",
    "gn:name":"Bukovac Perjasi\u010dki",
    "gn:population":3,
    "gn:timezone":"Europe/Zagreb",
    "iso:country":"HR",
    "name:und_x_variant":[
        "Bakovac",
        "Bucovazzo",
        "Bukovac",
        "Bukovac Perjasi\u010dki"
    ],
    "wof:name":"Bukovac Perjasicki",
    "wof:placetype":"locality",
    "wof:population":3
},
  "geometry": {"coordinates":[15.52833,45.24861],"type":"Point"}
}