{
  "type": "Feature",
  "properties": {
    "gn:admin1_code":"8.0",
    "gn:admin2_code":"11049291.0",
    "gn:asciiname":"Zamrsten",
    "gn:country_code":"HR",
    "gn:dem":497,
    "gn:feature_class":"P",
    "gn:feature_code":"PPL",
    "gn:name":"Zamr\u0161ten",
    "gn:population":0,
    "gn:timezone":"Europe/Zagreb",
    "iso:country":"HR",
    "wof:name":"Zamrsten",
    "wof:placetype":"locality"
},
  "geometry": {"coordinates":[15.25861,44.7325],"type":"Point"}
}