{
  "type": "Feature",
  "properties": {
    "gn:admin1_code":"8.0",
    "gn:admin2_code":"11049286.0",
    "gn:asciiname":"Buzim",
    "gn:country_code":"HR",
    "gn:dem":567,
    "gn:feature_class":"P",
    "gn:feature_code":"PPL",
    "gn:name":"Bu\u017eim",
    "gn:population":74,
    "gn:timezone":"Europe/Zagreb",
    "iso:country":"HR",
    "wof:name":"Buzim",
    "wof:placetype":"locality",
    "wof:population":74
},
  "geometry": {"coordinates":[15.24861,44.57278],"type":"Point"}
}