{
  "type": "Feature",
  "properties": {
    "gn:admin1_code":"20",
    "gn:admin2_code":"3198798.0",
    "gn:asciiname":"Malunje",
    "gn:country_code":"HR",
    "gn:dem":165,
    "gn:feature_class":"P",
    "gn:feature_code":"PPL",
    "gn:name":"Malunje",
    "gn:population":211,
    "gn:timezone":"Europe/Zagreb",
    "iso:country":"HR",
    "name:bos_x_preferred":[
        "Malunje"
    ],
    "name:hrv_x_preferred":[
        "Malunje"
    ],
    "name:hun_x_preferred":[
        "Malunje"
    ],
    "name:nld_x_preferred":[
        "Malunje"
    ],
    "name:slv_x_preferred":[
        "Malunje"
    ],
    "name:srp_x_preferred":[
        "\u041c\u0430\u043b\u0443\u045a\u0435"
    ],
    "name:ukr_x_preferred":[
        "\u041c\u0430\u043b\u0443\u043d\u0454"
    ],
    "wof:name":"Malunje",
    "wof:placetype":"locality",
    "wof:population":211
},
  "geometry": {"coordinates":[15.62307,45.69395],"type":"Point"}
}