{
  "type": "Feature",
  "properties": {
    "gn:admin1_code":"19.0",
    "gn:admin2_code":"11054319.0",
    "gn:asciiname":"Dugopolje",
    "gn:country_code":"HR",
    "gn:dem":647,
    "gn:feature_class":"P",
    "gn:feature_code":"PPL",
    "gn:name":"Dugopolje",
    "gn:population":20,
    "gn:timezone":"Europe/Zagreb",
    "iso:country":"HR",
    "wof:name":"Dugopolje",
    "wof:placetype":"locality",
    "wof:population":20
},
  "geometry": {"coordinates":[16.20361,44.3375],"type":"Point"}
}