{
  "type": "Feature",
  "properties": {
    "gn:admin1_code":"19.0",
    "gn:admin2_code":"11054319.0",
    "gn:asciiname":"Dugopolje",
    "gn:country_code":"HR",
    "gn:dem":647,
    "gn:feature_class":"P",
    "gn:feature_code":"PPL",
    "gn:name":"Dugopolje",
    "gn:population":20,
    "gn:timezone":"Europe/Zagreb",
    "iso:country":"HR",
    "name:bos_x_preferred":[
        "Dugopolje"
    ],
    "name:cat_x_preferred":[
        "Dugopolje"
    ],
    "name:ceb_x_preferred":[
        "Dugopolje"
    ],
    "name:ces_x_preferred":[
        "Dugopolje"
    ],
    "name:deu_x_preferred":[
        "Dugopolje"
    ],
    "name:fra_x_preferred":[
        "Dugopolje"
    ],
    "name:hrv_x_preferred":[
        "Dugopolje"
    ],
    "name:hun_x_preferred":[
        "Dugopolje"
    ],
    "name:ita_x_preferred":[
        "Dugopoglie"
    ],
    "name:nld_x_preferred":[
        "Dugopolje"
    ],
    "name:pol_x_preferred":[
        "Gmina Dugopolje"
    ],
    "name:ron_x_preferred":[
        "Comuna Dugopolje"
    ],
    "name:slk_x_preferred":[
        "Dugopolje"
    ],
    "name:slv_x_preferred":[
        "Dugopolje"
    ],
    "name:spa_x_preferred":[
        "Dugopolje"
    ],
    "name:sqi_x_preferred":[
        "Dugopole"
    ],
    "name:srp_x_preferred":[
        "\u0414\u0443\u0433\u043e\u043f\u043e\u0459\u0435"
    ],
    "name:swe_x_preferred":[
        "Dugopolje"
    ],
    "name:ukr_x_preferred":[
        "\u0414\u0443\u0433\u043e\u043f\u043e\u043b\u0454"
    ],
    "name:war_x_preferred":[
        "Dugopolje"
    ],
    "name:zho_x_preferred":[
        "\u675c\u683c\u666e\u5229\u8036"
    ],
    "wof:name":"Dugopolje",
    "wof:placetype":"locality",
    "wof:population":20
},
  "geometry": {"coordinates":[16.20361,44.3375],"type":"Point"}
}