{
  "type": "Feature",
  "properties": {
    "gn:admin1_code":"15.0",
    "gn:asciiname":"Bozinovici",
    "gn:country_code":"HR",
    "gn:dem":395,
    "gn:feature_class":"P",
    "gn:feature_code":"PPL",
    "gn:name":"Bo\u017einovi\u0107i",
    "gn:population":0,
    "gn:timezone":"Europe/Zagreb",
    "iso:country":"HR",
    "wof:name":"Bozinovici",
    "wof:placetype":"locality"
},
  "geometry": {"coordinates":[16.61333,43.75861],"type":"Point"}
}