{
  "type": "Feature",
  "properties": {
    "gn:admin1_code":"17",
    "gn:admin2_code":"11049470.0",
    "gn:asciiname":"Stara Krivaja",
    "gn:country_code":"HR",
    "gn:dem":197,
    "gn:feature_class":"P",
    "gn:feature_code":"PPL",
    "gn:name":"Stara Krivaja",
    "gn:population":0,
    "gn:timezone":"Europe/Zagreb",
    "iso:country":"HR",
    "wof:name":"Stara Krivaja",
    "wof:placetype":"locality"
},
  "geometry": {"coordinates":[17.48333,45.66667],"type":"Point"}
}