{
  "type": "Feature",
  "properties": {
    "gn:admin1_code":"05",
    "gn:admin2_code":"3194182.0",
    "gn:asciiname":"Otok Ostarijski",
    "gn:cc2":"HR",
    "gn:country_code":"HR",
    "gn:dem":315,
    "gn:feature_class":"P",
    "gn:feature_code":"PPL",
    "gn:name":"Otok O\u0161tarijski",
    "gn:population":381,
    "gn:timezone":"Europe/Zagreb",
    "iso:country":"HR",
    "name:und_x_variant":[
        "O\u0161tarski Otok",
        "Otok",
        "Otok O\u0161tarijski"
    ],
    "wof:name":"Otok Ostarijski",
    "wof:placetype":"locality",
    "wof:population":381
},
  "geometry": {"coordinates":[15.25472,45.23861],"type":"Point"}
}