{
  "type": "Feature",
  "properties": {
    "gn:admin1_code":"3.0",
    "gn:admin2_code":"11054961.0",
    "gn:asciiname":"Malo Selo",
    "gn:country_code":"HR",
    "gn:dem":15,
    "gn:feature_class":"P",
    "gn:feature_code":"PPL",
    "gn:name":"Malo Selo",
    "gn:population":0,
    "gn:timezone":"Europe/Zagreb",
    "iso:country":"HR",
    "name:bos_x_preferred":[
        "Malo Selo"
    ],
    "name:fra_x_preferred":[
        "Malo Selo"
    ],
    "name:hrv_x_preferred":[
        "Malo Selo"
    ],
    "name:hun_x_preferred":[
        "Malo Selo"
    ],
    "name:srp_x_preferred":[
        "\u041c\u0430\u043b\u043e \u0421\u0435\u043b\u043e"
    ],
    "wof:name":"Malo Selo",
    "wof:placetype":"locality"
},
  "geometry": {"coordinates":[17.68528,42.85917],"type":"Point"}
}