{
  "type": "Feature",
  "properties": {
    "gn:admin1_code":"15.0",
    "gn:asciiname":"Babici",
    "gn:country_code":"HR",
    "gn:dem":268,
    "gn:feature_class":"P",
    "gn:feature_code":"PPL",
    "gn:name":"Babi\u0107i",
    "gn:population":0,
    "gn:timezone":"Europe/Zagreb",
    "iso:country":"HR",
    "wof:name":"Babici",
    "wof:placetype":"locality"
},
  "geometry": {"coordinates":[17.22917,43.39111],"type":"Point"}
}