{
  "type": "Feature",
  "properties": {
    "gn:admin1_code":"14.0",
    "gn:asciiname":"Cvijica Klanac",
    "gn:country_code":"HR",
    "gn:dem":122,
    "gn:feature_class":"P",
    "gn:feature_code":"PPL",
    "gn:name":"Cviji\u0107a Klanac",
    "gn:population":0,
    "gn:timezone":"Europe/Zagreb",
    "iso:country":"HR",
    "wof:name":"Cvijica Klanac",
    "wof:placetype":"locality"
},
  "geometry": {"coordinates":[16.60611,45.23528],"type":"Point"}
}