{
  "type": "Feature",
  "properties": {
    "gn:admin1_code":"21",
    "gn:asciiname":"Novaki Kraljevecki",
    "gn:cc2":"HR",
    "gn:country_code":"HR",
    "gn:dem":140,
    "gn:feature_class":"P",
    "gn:feature_code":"PPL",
    "gn:name":"Novaki Kraljeve\u010dki",
    "gn:population":0,
    "gn:timezone":"Europe/Zagreb",
    "iso:country":"HR",
    "name:hrv_x_preferred":[
        "Kraljeve\u010dki Novaki"
    ],
    "name:und_x_variant":[
        "Novaki Kraljeva\u010dki",
        "Novaki",
        "Novaki Kraljeve\u010dki"
    ],
    "wof:name":"Novaki Kraljevecki",
    "wof:placetype":"locality"
},
  "geometry": {"coordinates":[16.15,45.83333],"type":"Point"}
}