{
  "type": "Feature",
  "properties": {
    "gn:admin1_code":"8.0",
    "gn:admin2_code":"11049291.0",
    "gn:asciiname":"Petranovic",
    "gn:country_code":"HR",
    "gn:dem":655,
    "gn:feature_class":"P",
    "gn:feature_code":"PPL",
    "gn:name":"Petranovi\u0107",
    "gn:population":0,
    "gn:timezone":"Europe/Zagreb",
    "iso:country":"HR",
    "wof:name":"Petranovic",
    "wof:placetype":"locality"
},
  "geometry": {"coordinates":[15.1575,44.77694],"type":"Point"}
}