{
  "type": "Feature",
  "properties": {
    "gn:admin1_code":"13.0",
    "gn:admin2_code":"3201161.0",
    "gn:asciiname":"Bajici",
    "gn:country_code":"HR",
    "gn:dem":364,
    "gn:feature_class":"P",
    "gn:feature_code":"PPL",
    "gn:name":"Baji\u0107i",
    "gn:population":0,
    "gn:timezone":"Europe/Zagreb",
    "iso:country":"HR",
    "wof:name":"Bajici",
    "wof:placetype":"locality"
},
  "geometry": {"coordinates":[16.23861,44.01889],"type":"Point"}
}