{
  "type": "Feature",
  "properties": {
    "gn:admin1_code":"7.0",
    "gn:admin2_code":"3197366.0",
    "gn:asciiname":"Gornja Pacetina",
    "gn:cc2":"HR",
    "gn:country_code":"HR",
    "gn:dem":178,
    "gn:feature_class":"P",
    "gn:feature_code":"PPL",
    "gn:name":"Gornja Pa\u010detina",
    "gn:population":0,
    "gn:timezone":"Europe/Zagreb",
    "iso:country":"HR",
    "name:bos_x_preferred":[
        "Gornja Pa\u010detina"
    ],
    "name:fra_x_preferred":[
        "Gornja Pa\u010detina"
    ],
    "name:hrv_x_preferred":[
        "Gornja Pa\u010detina"
    ],
    "name:hun_x_preferred":[
        "Gornja Pa\u010detina"
    ],
    "name:nld_x_preferred":[
        "Gornja Pa\u010detina"
    ],
    "name:slv_x_preferred":[
        "Gornja Pa\u010detina"
    ],
    "name:srp_x_preferred":[
        "\u0413\u043e\u0440\u045a\u0430 \u041f\u0430\u0447\u0435\u0442\u0438\u043d\u0430"
    ],
    "name:ukr_x_preferred":[
        "\u0413\u043e\u0440\u043d\u044f \u041f\u0430\u0447\u0435\u0442\u0438\u043d\u0430"
    ],
    "name:und_x_variant":[
        "Zemli\u010devo"
    ],
    "wof:name":"Gornja Pacetina",
    "wof:placetype":"locality",
    "wof:population":404
},
  "geometry": {"coordinates":[15.87667,46.11389],"type":"Point"}
}