{
  "type": "Feature",
  "properties": {
    "gn:admin1_code":"7.0",
    "gn:asciiname":"Gornja Pacetina",
    "gn:cc2":"HR",
    "gn:country_code":"HR",
    "gn:dem":178,
    "gn:feature_class":"P",
    "gn:feature_code":"PPL",
    "gn:name":"Gornja Pa\u010detina",
    "gn:population":0,
    "gn:timezone":"Europe/Zagreb",
    "iso:country":"HR",
    "name:und_x_variant":[
        "Zemli\u010devo",
        "Gornja Pa\u010detina"
    ],
    "wof:name":"Gornja Pacetina",
    "wof:placetype":"locality"
},
  "geometry": {"coordinates":[15.87667,46.11389000000001],"type":"Point"}
}