{
  "type": "Feature",
  "properties": {
    "gn:admin1_code":"4.0",
    "gn:asciiname":"Filipac",
    "gn:cc2":"HR",
    "gn:country_code":"HR",
    "gn:dem":61,
    "gn:feature_class":"P",
    "gn:feature_code":"PPL",
    "gn:name":"Filipac",
    "gn:population":0,
    "gn:timezone":"Europe/Zagreb",
    "iso:country":"HR",
    "name:und_x_variant":[
        "Busit",
        "Filipac"
    ],
    "wof:name":"Filipac",
    "wof:placetype":"locality"
},
  "geometry": {"coordinates":[13.5825,45.33639],"type":"Point"}
}