{
  "type": "Feature",
  "properties": {
    "gn:admin1_code":"14",
    "gn:admin2_code":"3200915.0",
    "gn:asciiname":"Rujevac",
    "gn:country_code":"HR",
    "gn:dem":193,
    "gn:feature_class":"P",
    "gn:feature_code":"PPL",
    "gn:name":"Rujevac",
    "gn:population":254,
    "gn:timezone":"Europe/Zagreb",
    "iso:country":"HR",
    "wof:name":"Rujevac",
    "wof:placetype":"locality",
    "wof:population":254
},
  "geometry": {"coordinates":[16.26222000000001,45.13],"type":"Point"}
}