{
  "type": "Feature",
  "properties": {
    "gn:admin1_code":"14",
    "gn:admin2_code":"3200915.0",
    "gn:asciiname":"Rujevac",
    "gn:country_code":"HR",
    "gn:dem":193,
    "gn:feature_class":"P",
    "gn:feature_code":"PPL",
    "gn:name":"Rujevac",
    "gn:population":254,
    "gn:timezone":"Europe/Zagreb",
    "iso:country":"HR",
    "name:fas_x_preferred":[
        "\u0631\u0648\u06cc\u0648\u0627\u062a\u0633"
    ],
    "name:fra_x_preferred":[
        "Rujevac"
    ],
    "name:msa_x_preferred":[
        "Rujevac"
    ],
    "name:nld_x_preferred":[
        "Rujevac"
    ],
    "name:por_x_preferred":[
        "Rujevac"
    ],
    "name:slv_x_preferred":[
        "Rujevac"
    ],
    "name:srp_x_preferred":[
        "\u0420\u0443\u0458\u0435\u0432\u0430\u0446"
    ],
    "wof:name":"Rujevac",
    "wof:placetype":"locality",
    "wof:population":254
},
  "geometry": {"coordinates":[16.26222000000001,45.13],"type":"Point"}
}