{
  "type": "Feature",
  "properties": {
    "gn:admin1_code":"20",
    "gn:admin2_code":"11048981.0",
    "gn:asciiname":"Stakorovec",
    "gn:country_code":"HR",
    "gn:dem":163,
    "gn:feature_class":"P",
    "gn:feature_code":"PPL",
    "gn:name":"\u0160takorovec",
    "gn:population":315,
    "gn:timezone":"Europe/Zagreb",
    "iso:country":"HR",
    "wof:name":"Stakorovec",
    "wof:placetype":"locality",
    "wof:population":315
},
  "geometry": {"coordinates":[16.28333,45.86667],"type":"Point"}
}