{
  "type": "Feature",
  "properties": {
    "gn:admin1_code":"13.0",
    "gn:asciiname":"Nakici",
    "gn:country_code":"HR",
    "gn:dem":232,
    "gn:feature_class":"P",
    "gn:feature_code":"PPL",
    "gn:name":"Naki\u0107i",
    "gn:population":0,
    "gn:timezone":"Europe/Zagreb",
    "iso:country":"HR",
    "wof:name":"Nakici",
    "wof:placetype":"locality"
},
  "geometry": {"coordinates":[16.0675,43.76111],"type":"Point"}
}