{
  "type": "Feature",
  "properties": {
    "gn:admin1_code":"14",
    "gn:admin2_code":"3200597.0",
    "gn:asciiname":"Novo Selo Glinsko",
    "gn:cc2":"HR",
    "gn:country_code":"HR",
    "gn:dem":148,
    "gn:feature_class":"P",
    "gn:feature_code":"PPL",
    "gn:name":"Novo Selo Glinsko",
    "gn:population":118,
    "gn:timezone":"Europe/Zagreb",
    "iso:country":"HR",
    "name:und_x_variant":[
        "Glinsko Novo Selo",
        "Novo Selo Glinsko"
    ],
    "wof:name":"Novo Selo Glinsko",
    "wof:placetype":"locality",
    "wof:population":118
},
  "geometry": {"coordinates":[16.16944,45.37278],"type":"Point"}
}