{
  "type": "Feature",
  "properties": {
    "gn:admin1_code":"15.0",
    "gn:asciiname":"Kapela",
    "gn:country_code":"HR",
    "gn:dem":318,
    "gn:feature_class":"P",
    "gn:feature_code":"PPL",
    "gn:name":"Kapela",
    "gn:population":0,
    "gn:timezone":"Europe/Zagreb",
    "iso:country":"HR",
    "wof:name":"Kapela",
    "wof:placetype":"locality"
},
  "geometry": {"coordinates":[16.59083,43.59944],"type":"Point"}
}