{
  "type": "Feature",
  "properties": {
    "gn:admin1_code":"15.0",
    "gn:asciiname":"Kapela",
    "gn:country_code":"HR",
    "gn:dem":318,
    "gn:feature_class":"P",
    "gn:feature_code":"PPL",
    "gn:name":"Kapela",
    "gn:population":0,
    "gn:timezone":"Europe/Zagreb",
    "iso:country":"HR",
    "name:bos_x_preferred":[
        "Kapela"
    ],
    "name:bul_x_preferred":[
        "\u041a\u0430\u043f\u0435\u043b\u0430"
    ],
    "name:ceb_x_preferred":[
        "Kapela"
    ],
    "name:hrv_x_preferred":[
        "Kapela"
    ],
    "name:hye_x_preferred":[
        "\u053f\u0561\u057a\u0565\u056c\u0561"
    ],
    "name:pol_x_preferred":[
        "Kapela"
    ],
    "name:rus_x_preferred":[
        "\u041a\u0430\u043f\u0435\u043b\u0430"
    ],
    "name:slv_x_preferred":[
        "Kapela"
    ],
    "name:srp_x_preferred":[
        "\u041a\u0430\u043f\u0435\u043b\u0430"
    ],
    "name:swe_x_preferred":[
        "Kapela"
    ],
    "name:ukr_x_preferred":[
        "\u041a\u0430\u043f\u0435\u043b\u0430"
    ],
    "wof:name":"Kapela",
    "wof:placetype":"locality"
},
  "geometry": {"coordinates":[16.59083,43.59944],"type":"Point"}
}