{
  "type": "Feature",
  "properties": {
    "gn:admin1_code":"15",
    "gn:admin2_code":"11054615.0",
    "gn:asciiname":"Nerezisce",
    "gn:country_code":"HR",
    "gn:dem":391,
    "gn:feature_class":"P",
    "gn:feature_code":"PPLA2",
    "gn:name":"Nere\u017ei\u0161\u0107e",
    "gn:population":0,
    "gn:timezone":"Europe/Zagreb",
    "iso:country":"HR",
    "name:und_x_variant":[
        "Nere\u017ei\u0161\u0107a",
        "Nersi",
        "Nere\u017ei\u0161\u0107e"
    ],
    "wof:name":"Nerezisce",
    "wof:placetype":"locality"
},
  "geometry": {"coordinates":[16.57861,43.33111],"type":"Point"}
}