{
  "type": "Feature",
  "properties": {
    "gn:admin1_code":"15",
    "gn:admin2_code":"11054615.0",
    "gn:asciiname":"Nerezisce",
    "gn:country_code":"HR",
    "gn:dem":391,
    "gn:feature_class":"P",
    "gn:feature_code":"PPLA2",
    "gn:name":"Nere\u017ei\u0161\u0107e",
    "gn:population":0,
    "gn:timezone":"Europe/Zagreb",
    "iso:country":"HR",
    "name:bos_x_preferred":[
        "Nere\u017ei\u0161\u0107a"
    ],
    "name:cat_x_preferred":[
        "Nere\u017ei\u0161\u0107a"
    ],
    "name:ceb_x_preferred":[
        "Nere\u017ei\u0161\u0107e"
    ],
    "name:ces_x_preferred":[
        "Nere\u017ei\u0161\u0107a"
    ],
    "name:fra_x_preferred":[
        "Nere\u017ei\u0161\u0107a"
    ],
    "name:hrv_x_preferred":[
        "Nere\u017ei\u0161\u0107a"
    ],
    "name:hun_x_preferred":[
        "Nere\u017ei\u0161\u0107a"
    ],
    "name:ita_x_preferred":[
        "Neresi"
    ],
    "name:nld_x_preferred":[
        "Nere\u017ei\u0161\u0107a"
    ],
    "name:pol_x_preferred":[
        "Gmina Nere\u017ei\u0161\u0107a"
    ],
    "name:ron_x_preferred":[
        "Comuna Nere\u017ei\u0161\u0107a"
    ],
    "name:slk_x_preferred":[
        "Nere\u017ei\u0161\u0107a"
    ],
    "name:slv_x_preferred":[
        "Nere\u017ei\u0161\u0107a"
    ],
    "name:srp_x_preferred":[
        "\u041d\u0435\u0440\u0435\u0436\u0438\u0448\u045b\u0430"
    ],
    "name:swe_x_preferred":[
        "Nere\u017ei\u0161\u0107e"
    ],
    "name:ukr_x_preferred":[
        "\u041d\u0435\u0440\u0435\u0436\u0438\u0449\u0430"
    ],
    "name:und_x_variant":[
        "Nersi"
    ],
    "name:war_x_preferred":[
        "Nere\u017ei\u0161\u0107a"
    ],
    "name:zho_x_preferred":[
        "\u5167\u52d2\u8332\u5361"
    ],
    "wof:name":"Nerezisce",
    "wof:placetype":"locality"
},
  "geometry": {"coordinates":[16.57861,43.33111],"type":"Point"}
}