{
  "type": "Feature",
  "properties": {
    "gn:admin1_code":"15.0",
    "gn:asciiname":"Donja Zecevina",
    "gn:country_code":"HR",
    "gn:dem":615,
    "gn:feature_class":"P",
    "gn:feature_code":"PPL",
    "gn:name":"Donja Ze\u010devina",
    "gn:population":0,
    "gn:timezone":"Europe/Zagreb",
    "iso:country":"HR",
    "wof:name":"Donja Zecevina",
    "wof:placetype":"locality"
},
  "geometry": {"coordinates":[17.13556,43.38278],"type":"Point"}
}