{
  "type": "Feature",
  "properties": {
    "gn:admin1_code":"5.0",
    "gn:admin2_code":"11049278.0",
    "gn:asciiname":"Seliste",
    "gn:cc2":"HR",
    "gn:country_code":"HR",
    "gn:dem":419,
    "gn:feature_class":"P",
    "gn:feature_code":"PPL",
    "gn:name":"Seli\u0161te",
    "gn:population":0,
    "gn:timezone":"Europe/Zagreb",
    "iso:country":"HR",
    "name:bos_x_preferred":[
        "Seli\u0161te Dre\u017eni\u010dko"
    ],
    "name:cat_x_preferred":[
        "Seli\u0161te Dre\u017eni\u010dko"
    ],
    "name:ceb_x_preferred":[
        "Seliste"
    ],
    "name:est_x_preferred":[
        "Seliste"
    ],
    "name:hrv_x_preferred":[
        "Seli\u0161te Dre\u017eni\u010dko"
    ],
    "name:hun_x_preferred":[
        "Seli\u0161te Dre\u017eni\u010dko"
    ],
    "name:hye_x_preferred":[
        "\u054d\u0565\u056c\u056b\u057d\u057f\u0565"
    ],
    "name:nld_x_preferred":[
        "Seli\u0161te Dre\u017eni\u010dko"
    ],
    "name:pol_x_preferred":[
        "Seliste"
    ],
    "name:slv_x_preferred":[
        "Seli\u0161te Dre\u017eni\u010dko"
    ],
    "name:spa_x_preferred":[
        "Seli\u0161te Dre\u017eni\u010dko"
    ],
    "name:srp_x_preferred":[
        "\u0421\u0435\u043b\u0438\u0448\u0442\u0435 \u0414\u0440\u0435\u0436\u043d\u0438\u0447\u043a\u043e"
    ],
    "name:ukr_x_preferred":[
        "\u0421\u0435\u043b\u0456\u0441\u0442\u0435"
    ],
    "name:und_x_variant":[
        "Seli\u0161\u0107e Dre\u017eni\u010dko",
        "Seli\u0161\u0107e"
    ],
    "name:vol_x_preferred":[
        "Seliste"
    ],
    "wof:name":"Seliste",
    "wof:placetype":"locality"
},
  "geometry": {"coordinates":[15.62889,44.94611],"type":"Point"}
}