{
  "type": "Feature",
  "properties": {
    "gn:admin1_code":"5.0",
    "gn:admin2_code":"11049278.0",
    "gn:asciiname":"Seliste",
    "gn:country_code":"HR",
    "gn:dem":419,
    "gn:feature_class":"P",
    "gn:feature_code":"PPL",
    "gn:name":"Seli\u0161te",
    "gn:population":0,
    "gn:timezone":"Europe/Zagreb",
    "iso:country":"HR",
    "name:ceb_x_preferred":[
        "Seliste"
    ],
    "name:est_x_preferred":[
        "Seliste"
    ],
    "name:hye_x_preferred":[
        "\u054d\u0565\u056c\u056b\u057d\u057f\u0565"
    ],
    "name:pol_x_preferred":[
        "Seliste"
    ],
    "name:ukr_x_preferred":[
        "\u0421\u0435\u043b\u0456\u0441\u0442\u0435"
    ],
    "name:vol_x_preferred":[
        "Seliste"
    ],
    "wof:name":"Seliste",
    "wof:placetype":"locality"
},
  "geometry": {"coordinates":[15.62889,44.94611],"type":"Point"}
}