{
  "type": "Feature",
  "properties": {
    "gn:admin1_code":"20",
    "gn:admin2_code":"3188243.0",
    "gn:asciiname":"Velika Buna",
    "gn:cc2":"HR",
    "gn:country_code":"HR",
    "gn:dem":130,
    "gn:feature_class":"P",
    "gn:feature_code":"PPL",
    "gn:name":"Velika Buna",
    "gn:population":856,
    "gn:timezone":"Europe/Zagreb",
    "iso:country":"HR",
    "name:bos_x_preferred":[
        "Velika Buna"
    ],
    "name:fas_x_preferred":[
        "\u0648\u0644\u06cc\u06a9\u0627 \u0628\u0648\u0646\u0627"
    ],
    "name:hrv_x_preferred":[
        "Velika Buna"
    ],
    "name:hun_x_preferred":[
        "Velika Buna"
    ],
    "name:nld_x_preferred":[
        "Velika Buna"
    ],
    "name:slv_x_preferred":[
        "Velika Buna"
    ],
    "name:srp_x_preferred":[
        "\u0412\u0435\u043b\u0438\u043a\u0430 \u0411\u0443\u043d\u0430"
    ],
    "name:ukr_x_preferred":[
        "\u0412\u0435\u043b\u0438\u043a\u0430 \u0411\u0443\u043d\u0430"
    ],
    "name:und_x_variant":[
        "Buna Velika",
        "Velika Buna"
    ],
    "wof:name":"Velika Buna",
    "wof:placetype":"locality",
    "wof:population":856
},
  "geometry": {"coordinates":[16.06667,45.63333],"type":"Point"}
}