{
  "type": "Feature",
  "properties": {
    "gn:admin1_code":"20",
    "gn:admin2_code":"3188243.0",
    "gn:asciiname":"Velika Buna",
    "gn:cc2":"HR",
    "gn:country_code":"HR",
    "gn:dem":130,
    "gn:feature_class":"P",
    "gn:feature_code":"PPL",
    "gn:name":"Velika Buna",
    "gn:population":856,
    "gn:timezone":"Europe/Zagreb",
    "iso:country":"HR",
    "name:und_x_variant":[
        "Buna Velika",
        "Velika Buna"
    ],
    "wof:name":"Velika Buna",
    "wof:placetype":"locality",
    "wof:population":856
},
  "geometry": {"coordinates":[16.06667,45.63333],"type":"Point"}
}