{
  "type": "Feature",
  "properties": {
    "iso:country":"HR",
    "name:bak_x_preferred":[
        "\u041c\u0435\u0434\u0432\u0435\u0434\u0433\u0440\u0430\u0434"
    ],
    "name:bos_x_preferred":[
        "Medvedgrad"
    ],
    "name:bul_x_preferred":[
        "\u041c\u0435\u0434\u0432\u0435\u0434\u0433\u0440\u0430\u0434"
    ],
    "name:deu_x_preferred":[
        "Burg Medvedgrad"
    ],
    "name:hrv_x_preferred":[
        "Medvedgrad"
    ],
    "name:hun_x_preferred":[
        "Medvev\u00e1r"
    ],
    "name:mkd_x_preferred":[
        "\u041c\u0435\u0434\u0432\u0435\u0434\u0433\u0440\u0430\u0434"
    ],
    "name:rus_x_preferred":[
        "\u041c\u0435\u0434\u0432\u0435\u0434\u0433\u0440\u0430\u0434"
    ],
    "name:slv_x_preferred":[
        "Grad Medvedgrad"
    ],
    "name:srp_x_preferred":[
        "\u041c\u0435\u0434\u0432\u0435\u0434\u0433\u0440\u0430\u0434"
    ],
    "name:swe_x_preferred":[
        "Medvedgrad"
    ],
    "name:ukr_x_preferred":[
        "\u041c\u0435\u0434\u0432\u0435\u0434\u0433\u0440\u0430\u0434"
    ],
    "qs_pg:aaroncc":"HR",
    "qs_pg:name":"Medvedgrad",
    "qs_pg:name_adm0":"Hrvatska",
    "qs_pg:name_adm1":"Grad Zagreb",
    "qs_pg:photos":123,
    "qs_pg:photos_1k":25,
    "qs_pg:photos_9k":1,
    "qs_pg:photos_9r":3,
    "qs_pg:photos_all":123,
    "qs_pg:photos_sr":3,
    "qs_pg:pop_sr":0,
    "qs_pg:qs_pg_placetype":"locality",
    "qs_pg:qs_pg_placetype_gp":"Town",
    "qs_pg:woe_adm0":23424843,
    "woe:adm0_id":23424843,
    "woe:name_adm0":"Hrvatska",
    "woe:name_adm1":"Grad Zagreb",
    "woe:placetype":"Town",
    "wof:name":"Medvedgrad",
    "wof:placetype":"locality"
},
  "geometry": {"coordinates":[15.940657,45.870038],"type":"Point"}
}