{
  "type": "Feature",
  "properties": {
    "gn:admin1_code":"04",
    "gn:asciiname":"Krase",
    "gn:cc2":"HR",
    "gn:country_code":"HR",
    "gn:dem":52,
    "gn:feature_class":"P",
    "gn:feature_code":"PPL",
    "gn:name":"Krase",
    "gn:population":0,
    "gn:timezone":"Europe/Zagreb",
    "iso:country":"HR",
    "name:und_x_variant":[
        "Carse",
        "Kras"
    ],
    "wof:name":"Krase",
    "wof:placetype":"locality"
},
  "geometry": {"coordinates":[13.56667,45.45],"type":"Point"}
}