{
  "type": "Feature",
  "properties": {
    "gn:admin1_code":"03",
    "gn:asciiname":"Ljuta",
    "gn:country_code":"HR",
    "gn:dem":81,
    "gn:feature_class":"P",
    "gn:feature_code":"PPLL",
    "gn:name":"Ljuta",
    "gn:population":0,
    "gn:timezone":"Europe/Zagreb",
    "iso:country":"HR",
    "wof:name":"Ljuta",
    "wof:placetype":"locality"
},
  "geometry": {"coordinates":[18.37806,42.53833],"type":"Point"}
}