{
  "type": "Feature",
  "properties": {
    "gn:admin1_code":"08",
    "gn:admin2_code":"11049287.0",
    "gn:asciiname":"Stanista",
    "gn:cc2":"HR",
    "gn:country_code":"HR",
    "gn:dem":277,
    "gn:feature_class":"P",
    "gn:feature_code":"PPL",
    "gn:name":"Stani\u0161ta",
    "gn:population":6,
    "gn:timezone":"Europe/Zagreb",
    "iso:country":"HR",
    "name:und_x_variant":[
        "Stani\u0161te",
        "Stani\u0161ta"
    ],
    "wof:name":"Stanista",
    "wof:placetype":"locality",
    "wof:population":6
},
  "geometry": {"coordinates":[15.06778,44.54861],"type":"Point"}
}