{
  "type": "Feature",
  "properties": {
    "gn:admin1_code":"5.0",
    "gn:admin2_code":"11049277.0",
    "gn:asciiname":"Budimlje",
    "gn:cc2":"HR",
    "gn:country_code":"HR",
    "gn:dem":397,
    "gn:feature_class":"P",
    "gn:feature_code":"PPL",
    "gn:name":"Budimlje",
    "gn:population":0,
    "gn:timezone":"Europe/Zagreb",
    "iso:country":"HR",
    "name:und_x_variant":[
        "Budimilije",
        "Budimlje"
    ],
    "wof:name":"Budimlje",
    "wof:placetype":"locality"
},
  "geometry": {"coordinates":[15.3625,45.06694],"type":"Point"}
}