{
  "type": "Feature",
  "properties": {
    "gn:admin1_code":"08",
    "gn:admin2_code":"11049288.0",
    "gn:asciiname":"Kik",
    "gn:country_code":"HR",
    "gn:dem":610,
    "gn:feature_class":"P",
    "gn:feature_code":"PPL",
    "gn:name":"Kik",
    "gn:population":4,
    "gn:timezone":"Europe/Zagreb",
    "iso:country":"HR",
    "name:ceb_x_preferred":[
        "Kik"
    ],
    "name:deu_x_preferred":[
        "Kik"
    ],
    "name:nld_x_preferred":[
        "Kik"
    ],
    "name:rus_x_preferred":[
        "\u041a\u0438\u043a"
    ],
    "name:slv_x_preferred":[
        "Kik"
    ],
    "name:srp_x_preferred":[
        "\u041a\u0438\u043a"
    ],
    "name:swe_x_preferred":[
        "Kik"
    ],
    "wof:name":"Kik",
    "wof:placetype":"locality",
    "wof:population":4
},
  "geometry": {"coordinates":[15.63333,44.43444],"type":"Point"}
}