{
  "type": "Feature",
  "properties": {
    "gn:admin1_code":"20",
    "gn:admin2_code":"11049006.0",
    "gn:asciiname":"Kupcina",
    "gn:country_code":"HR",
    "gn:dem":303,
    "gn:feature_class":"P",
    "gn:feature_code":"PPL",
    "gn:name":"Kup\u010dina",
    "gn:population":0,
    "gn:timezone":"Europe/Zagreb",
    "iso:country":"HR",
    "wof:name":"Kupcina",
    "wof:placetype":"locality"
},
  "geometry": {"coordinates":[15.43333,45.73333],"type":"Point"}
}