{
  "type": "Feature",
  "properties": {
    "gn:admin1_code":"13.0",
    "gn:asciiname":"Prokljan",
    "gn:country_code":"HR",
    "gn:dem":8,
    "gn:feature_class":"P",
    "gn:feature_code":"PPL",
    "gn:name":"Prokljan",
    "gn:population":0,
    "gn:timezone":"Europe/Zagreb",
    "iso:country":"HR",
    "wof:name":"Prokljan",
    "wof:placetype":"locality"
},
  "geometry": {"coordinates":[15.85583,43.83833],"type":"Point"}
}