{
  "type": "Feature",
  "properties": {
    "gn:admin1_code":"06",
    "gn:admin2_code":"11049326.0",
    "gn:asciiname":"Gornja Rijeka",
    "gn:country_code":"HR",
    "gn:dem":213,
    "gn:feature_class":"P",
    "gn:feature_code":"PPL",
    "gn:name":"Gornja Rijeka",
    "gn:population":340,
    "gn:timezone":"Europe/Zagreb",
    "iso:country":"HR",
    "name:bos_x_preferred":[
        "Gornja Rijeka"
    ],
    "name:fra_x_preferred":[
        "Gornja Rijeka"
    ],
    "name:hrv_x_preferred":[
        "Gornja Rijeka"
    ],
    "name:hun_x_preferred":[
        "Gornja Rijeka"
    ],
    "name:ita_x_preferred":[
        "Gornja Rijeka"
    ],
    "name:nld_x_preferred":[
        "Gornja Rijeka"
    ],
    "name:pol_x_preferred":[
        "Gmina Gornja Rijeka"
    ],
    "name:ron_x_preferred":[
        "Comuna Gornja Rijeka"
    ],
    "name:rus_x_preferred":[
        "\u0413\u043e\u0440\u043d\u044f-\u0420\u0438\u0435\u043a\u0430"
    ],
    "name:slv_x_preferred":[
        "Gornja Rijeka"
    ],
    "name:spa_x_preferred":[
        "Gornja Rijeka"
    ],
    "name:srp_x_preferred":[
        "\u0413\u043e\u0440\u045a\u0430 \u0420\u0438\u0458\u0435\u043a\u0430"
    ],
    "name:ukr_x_preferred":[
        "\u0413\u043e\u0440\u043d\u044f \u0420\u0456\u0454\u043a\u0430"
    ],
    "name:war_x_preferred":[
        "Gornja Rijeka"
    ],
    "wof:name":"Gornja Rijeka",
    "wof:placetype":"locality",
    "wof:population":340
},
  "geometry": {"coordinates":[16.39229,46.11121],"type":"Point"}
}