{
  "type": "Feature",
  "properties": {
    "gn:admin1_code":"06",
    "gn:admin2_code":"11049326.0",
    "gn:asciiname":"Gornja Rijeka",
    "gn:country_code":"HR",
    "gn:dem":213,
    "gn:feature_class":"P",
    "gn:feature_code":"PPL",
    "gn:name":"Gornja Rijeka",
    "gn:population":340,
    "gn:timezone":"Europe/Zagreb",
    "iso:country":"HR",
    "wof:name":"Gornja Rijeka",
    "wof:placetype":"locality",
    "wof:population":340
},
  "geometry": {"coordinates":[16.39229,46.11121],"type":"Point"}
}