{
  "type": "Feature",
  "properties": {
    "gn:gn_country":"HR",
    "gn:gn_fcode":"PPL",
    "gn:gn_pop":0,
    "gn:population":63,
    "iso:country":"HR",
    "name:bos_x_preferred":[
        "Punta Kri\u017ea"
    ],
    "name:dut_x_preferred":[
        "Punta Kri\u017ea"
    ],
    "name:eng_x_preferred":[
        "Punta Kri\u017ea"
    ],
    "name:fre_x_preferred":[
        "Punta Kri\u017ea"
    ],
    "name:hrv_x_preferred":[
        "Punta Kri\u017ea"
    ],
    "name:hun_x_preferred":[
        "Punta Kri\u017ea"
    ],
    "name:slv_x_preferred":[
        "Punta Kri\u017ea"
    ],
    "name:srp_x_preferred":[
        "\u041f\u0443\u043d\u0442\u0430 \u041a\u0440\u0438\u0436\u0430"
    ],
    "name:unk_x_variant":[
        "Rt Kri\u017e"
    ],
    "qs_pg:aaroncc":"HR",
    "qs_pg:gn_country":"HR",
    "qs_pg:gn_fcode":"PPL",
    "qs_pg:gn_pop":0,
    "qs_pg:name":"Punta Kri\u017ea",
    "qs_pg:name_adm0":"Hrvatska",
    "qs_pg:name_adm1":"Primorsko-Goranska",
    "qs_pg:photos":118,
    "qs_pg:photos_1k":24,
    "qs_pg:photos_9k":1,
    "qs_pg:photos_9r":3,
    "qs_pg:photos_all":118,
    "qs_pg:photos_sr":3,
    "qs_pg:pop_sr":0,
    "qs_pg:qs_pg_placetype":"locality",
    "qs_pg:qs_pg_placetype_gp":"Town",
    "qs_pg:woe_adm0":23424843,
    "woe:adm0_id":23424843,
    "woe:name_adm0":"Hrvatska",
    "woe:name_adm1":"Primorsko-Goranska",
    "woe:placetype":"Town",
    "wof:name":"Punta Kri\u017ea",
    "wof:placetype":"locality",
    "wof:population":63
},
  "geometry": {"coordinates":[14.49583,44.63972],"type":"Point"}
}