{
  "type": "Feature",
  "properties": {
    "gn:admin1_code":"8.0",
    "gn:asciiname":"Sevrlje",
    "gn:country_code":"HR",
    "gn:dem":440,
    "gn:feature_class":"P",
    "gn:feature_code":"PPL",
    "gn:name":"\u0160evrlje",
    "gn:population":0,
    "gn:timezone":"Europe/Zagreb",
    "iso:country":"HR",
    "wof:name":"Sevrlje",
    "wof:placetype":"locality"
},
  "geometry": {"coordinates":[15.13056,44.94139000000001],"type":"Point"}
}