{
  "type": "Feature",
  "properties": {
    "gn:admin1_code":"01",
    "gn:asciiname":"Marcani",
    "gn:country_code":"HR",
    "gn:dem":155,
    "gn:feature_class":"P",
    "gn:feature_code":"PPL",
    "gn:name":"Mar\u010dani",
    "gn:population":103,
    "gn:timezone":"Europe/Zagreb",
    "iso:country":"HR",
    "name:und_x_variant":[
        "Mar\u010dani"
    ],
    "wof:name":"Marcani",
    "wof:placetype":"locality",
    "wof:population":103
},
  "geometry": {"coordinates":[16.51667,45.75],"type":"Point"}
}