{
  "type": "Feature",
  "properties": {
    "gn:admin1_code":"01",
    "gn:asciiname":"Marcani",
    "gn:country_code":"HR",
    "gn:dem":155,
    "gn:feature_class":"P",
    "gn:feature_code":"PPL",
    "gn:name":"Mar\u010dani",
    "gn:population":103,
    "gn:timezone":"Europe/Zagreb",
    "iso:country":"HR",
    "name:bos_x_preferred":[
        "Mar\u010dani"
    ],
    "name:fra_x_preferred":[
        "Mar\u010dani"
    ],
    "name:hrv_x_preferred":[
        "Mar\u010dani"
    ],
    "name:hun_x_preferred":[
        "Mar\u010dani"
    ],
    "name:nld_x_preferred":[
        "Mar\u010dani"
    ],
    "name:slv_x_preferred":[
        "Mar\u010dani"
    ],
    "name:spa_x_preferred":[
        "Mar\u010dani"
    ],
    "name:ukr_x_preferred":[
        "\u041c\u0430\u0440\u0447\u0430\u043d\u0438"
    ],
    "wof:name":"Marcani",
    "wof:placetype":"locality",
    "wof:population":103
},
  "geometry": {"coordinates":[16.51667,45.75],"type":"Point"}
}