{
  "type": "Feature",
  "properties": {
    "gn:admin1_code":"15",
    "gn:asciiname":"Brist",
    "gn:country_code":"HR",
    "gn:dem":21,
    "gn:feature_class":"P",
    "gn:feature_code":"PPL",
    "gn:name":"Brist",
    "gn:population":400,
    "gn:timezone":"Europe/Zagreb",
    "iso:country":"HR",
    "wof:name":"Brist",
    "wof:placetype":"locality",
    "wof:population":400
},
  "geometry": {"coordinates":[17.32472000000001,43.11806],"type":"Point"}
}