{
  "type": "Feature",
  "properties": {
    "gn:admin1_code":"8.0",
    "gn:asciiname":"Zavode",
    "gn:country_code":"HR",
    "gn:dem":586,
    "gn:feature_class":"P",
    "gn:feature_code":"PPL",
    "gn:name":"Zavo\u0111e",
    "gn:population":0,
    "gn:timezone":"Europe/Zagreb",
    "iso:country":"HR",
    "wof:name":"Zavode",
    "wof:placetype":"locality"
},
  "geometry": {"coordinates":[15.51556,44.52306],"type":"Point"}
}