{
  "type": "Feature",
  "properties": {
    "gn:admin1_code":"13.0",
    "gn:asciiname":"Koncarovic",
    "gn:country_code":"HR",
    "gn:dem":182,
    "gn:feature_class":"P",
    "gn:feature_code":"PPL",
    "gn:name":"Kon\u010darovi\u0107",
    "gn:population":0,
    "gn:timezone":"Europe/Zagreb",
    "iso:country":"HR",
    "wof:name":"Koncarovic",
    "wof:placetype":"locality"
},
  "geometry": {"coordinates":[15.94111,44.08611],"type":"Point"}
}