{
  "type": "Feature",
  "properties": {
    "gn:admin1_code":"3.0",
    "gn:admin2_code":"11054972.0",
    "gn:asciiname":"Grusici",
    "gn:country_code":"HR",
    "gn:dem":172,
    "gn:feature_class":"P",
    "gn:feature_code":"PPL",
    "gn:name":"Gru\u0161i\u0107i",
    "gn:population":0,
    "gn:timezone":"Europe/Zagreb",
    "iso:country":"HR",
    "wof:name":"Grusici",
    "wof:placetype":"locality"
},
  "geometry": {"coordinates":[18.30056,42.54222],"type":"Point"}
}