{
  "type": "Feature",
  "properties": {
    "gn:admin1_code":"15.0",
    "gn:asciiname":"Vucici",
    "gn:country_code":"HR",
    "gn:dem":304,
    "gn:feature_class":"P",
    "gn:feature_code":"PPL",
    "gn:name":"Vu\u010di\u0107i",
    "gn:population":0,
    "gn:timezone":"Europe/Zagreb",
    "iso:country":"HR",
    "wof:name":"Vucici",
    "wof:placetype":"locality"
},
  "geometry": {"coordinates":[16.70083,43.71694],"type":"Point"}
}