{
  "type": "Feature",
  "properties": {
    "gn:admin1_code":"10",
    "gn:admin2_code":"11054392.0",
    "gn:asciiname":"Tikves",
    "gn:country_code":"HR",
    "gn:dem":81,
    "gn:feature_class":"P",
    "gn:feature_code":"PPL",
    "gn:name":"Tikve\u0161",
    "gn:population":10,
    "gn:timezone":"Europe/Zagreb",
    "iso:country":"HR",
    "name:und_x_variant":[
        "Tikve\u0161"
    ],
    "wof:name":"Tikves",
    "wof:placetype":"locality",
    "wof:population":10
},
  "geometry": {"coordinates":[18.845,45.67167],"type":"Point"}
}