{
  "type": "Feature",
  "properties": {
    "gn:admin1_code":"12",
    "gn:admin2_code":"3187256.0",
    "gn:asciiname":"Jablan",
    "gn:country_code":"HR",
    "gn:dem":682,
    "gn:feature_class":"P",
    "gn:feature_code":"PPL",
    "gn:name":"Jablan",
    "gn:population":209,
    "gn:timezone":"Europe/Zagreb",
    "iso:country":"HR",
    "name:bos_x_preferred":[
        "Jablan"
    ],
    "name:ceb_x_preferred":[
        "Jablan"
    ],
    "name:fra_x_preferred":[
        "Jablan"
    ],
    "name:hrv_x_preferred":[
        "Jablan"
    ],
    "name:hun_x_preferred":[
        "Jablan"
    ],
    "name:slv_x_preferred":[
        "Jablan"
    ],
    "name:srp_x_preferred":[
        "\u0408\u0430\u0431\u043b\u0430\u043d"
    ],
    "name:swe_x_preferred":[
        "Jablan"
    ],
    "wof:name":"Jablan",
    "wof:placetype":"locality",
    "wof:population":209
},
  "geometry": {"coordinates":[15.02889,45.37778],"type":"Point"}
}