{
  "type": "Feature",
  "properties": {
    "gn:admin1_code":"12",
    "gn:admin2_code":"3187256.0",
    "gn:asciiname":"Jablan",
    "gn:country_code":"HR",
    "gn:dem":682,
    "gn:feature_class":"P",
    "gn:feature_code":"PPL",
    "gn:name":"Jablan",
    "gn:population":209,
    "gn:timezone":"Europe/Zagreb",
    "iso:country":"HR",
    "wof:name":"Jablan",
    "wof:placetype":"locality",
    "wof:population":209
},
  "geometry": {"coordinates":[15.02889,45.37778],"type":"Point"}
}