{
  "type": "Feature",
  "properties": {
    "gn:admin1_code":"13.0",
    "gn:asciiname":"Susa",
    "gn:country_code":"HR",
    "gn:dem":253,
    "gn:feature_class":"P",
    "gn:feature_code":"PPL",
    "gn:name":"\u0160u\u0161a",
    "gn:population":0,
    "gn:timezone":"Europe/Zagreb",
    "iso:country":"HR",
    "wof:name":"Susa",
    "wof:placetype":"locality"
},
  "geometry": {"coordinates":[15.91222,44.02583],"type":"Point"}
}