{
  "type": "Feature",
  "properties": {
    "gn:admin1_code":"15.0",
    "gn:asciiname":"Kolovrati",
    "gn:country_code":"HR",
    "gn:dem":480,
    "gn:feature_class":"P",
    "gn:feature_code":"PPL",
    "gn:name":"Kolovrati",
    "gn:population":0,
    "gn:timezone":"Europe/Zagreb",
    "iso:country":"HR",
    "wof:name":"Kolovrati",
    "wof:placetype":"locality"
},
  "geometry": {"coordinates":[17.1425,43.49611],"type":"Point"}
}