{
  "type": "Feature",
  "properties": {
    "gn:admin1_code":"19.0",
    "gn:asciiname":"Smiric",
    "gn:country_code":"HR",
    "gn:dem":-3,
    "gn:feature_class":"P",
    "gn:feature_code":"PPL",
    "gn:name":"Smiri\u0107",
    "gn:population":0,
    "gn:timezone":"Europe/Zagreb",
    "iso:country":"HR",
    "wof:name":"Smiric",
    "wof:placetype":"locality"
},
  "geometry": {"coordinates":[15.21,44.13306],"type":"Point"}
}