{
  "type": "Feature",
  "properties": {
    "gn:admin1_code":"19.0",
    "gn:asciiname":"Sveti Krijak",
    "gn:country_code":"HR",
    "gn:dem":45,
    "gn:feature_class":"P",
    "gn:feature_code":"PPL",
    "gn:name":"Sveti Krijak",
    "gn:population":0,
    "gn:timezone":"Europe/Zagreb",
    "iso:country":"HR",
    "wof:name":"Sveti Krijak",
    "wof:placetype":"locality"
},
  "geometry": {"coordinates":[14.59889,44.3375],"type":"Point"}
}