{
  "type": "Feature",
  "properties": {
    "gn:gn_country":"HR",
    "gn:gn_fcode":"PPL",
    "gn:gn_pop":0,
    "gn:population":137,
    "iso:country":"HR",
    "name:bos_x_preferred":[
        "Dinji\u0161ka"
    ],
    "name:eng_x_preferred":[
        "Dinji\u0161ka"
    ],
    "name:hrv_x_preferred":[
        "Dinji\u0161ka"
    ],
    "name:hun_x_preferred":[
        "Dinji\u0161ka"
    ],
    "name:nld_x_preferred":[
        "Dinji\u0161ka"
    ],
    "name:slv_x_preferred":[
        "Dinji\u0161ka"
    ],
    "name:srp_x_preferred":[
        "\u0414\u0438\u045a\u0438\u0448\u043a\u0430"
    ],
    "name:swe_x_preferred":[
        "Dinji\u0161ka"
    ],
    "name:unk_x_variant":[
        "Dini\u0161ka"
    ],
    "qs_pg:aaroncc":"HR",
    "qs_pg:gn_country":"HR",
    "qs_pg:gn_fcode":"PPL",
    "qs_pg:gn_pop":0,
    "qs_pg:name":"Dinji\u00b5ka",
    "qs_pg:name_adm0":"Hrvatska",
    "qs_pg:name_adm1":"Zadarsko-Kninska",
    "qs_pg:photos":20,
    "qs_pg:photos_1k":4,
    "qs_pg:photos_9k":1,
    "qs_pg:photos_9r":1,
    "qs_pg:photos_all":20,
    "qs_pg:photos_sr":1,
    "qs_pg:pop_sr":0,
    "qs_pg:qs_pg_placetype":"locality",
    "qs_pg:qs_pg_placetype_gp":"Town",
    "qs_pg:woe_adm0":23424843,
    "woe:adm0_id":23424843,
    "woe:name_adm0":"Hrvatska",
    "woe:name_adm1":"Zadarsko-Kninska",
    "woe:placetype":"Town",
    "wof:name":"Dinji\u00b5ka",
    "wof:placetype":"locality",
    "wof:population":137
},
  "geometry": {"coordinates":[15.18722,44.36167],"type":"Point"}
}