{
  "type": "Feature",
  "properties": {
    "gn:admin1_code":"11",
    "gn:admin2_code":"3193705.0",
    "gn:asciiname":"Kusonje",
    "gn:country_code":"HR",
    "gn:dem":254,
    "gn:feature_class":"P",
    "gn:feature_code":"PPL",
    "gn:name":"Kusonje",
    "gn:population":308,
    "gn:timezone":"Europe/Zagreb",
    "iso:country":"HR",
    "wof:name":"Kusonje",
    "wof:placetype":"locality",
    "wof:population":308
},
  "geometry": {"coordinates":[17.23333,45.46667],"type":"Point"}
}