{
  "type": "Feature",
  "properties": {
    "gn:admin1_code":"11",
    "gn:admin2_code":"3193705.0",
    "gn:asciiname":"Kusonje",
    "gn:country_code":"HR",
    "gn:dem":254,
    "gn:feature_class":"P",
    "gn:feature_code":"PPL",
    "gn:name":"Kusonje",
    "gn:population":308,
    "gn:timezone":"Europe/Zagreb",
    "iso:country":"HR",
    "name:bos_x_preferred":[
        "Kusonje"
    ],
    "name:hrv_x_preferred":[
        "Kusonje"
    ],
    "name:hun_x_preferred":[
        "Kusonje"
    ],
    "name:nld_x_preferred":[
        "Kusonje"
    ],
    "name:slv_x_preferred":[
        "Kusonje"
    ],
    "name:spa_x_preferred":[
        "Kusonje"
    ],
    "name:srp_x_preferred":[
        "\u041a\u0443\u0441\u043e\u045a\u0435"
    ],
    "name:ukr_x_preferred":[
        "\u041a\u0443\u0441\u043e\u043d\u0454"
    ],
    "wof:name":"Kusonje",
    "wof:placetype":"locality",
    "wof:population":308
},
  "geometry": {"coordinates":[17.23333,45.46667],"type":"Point"}
}