{
  "type": "Feature",
  "properties": {
    "gn:admin1_code":"8.0",
    "gn:admin2_code":"11049294.0",
    "gn:asciiname":"Ljubovo",
    "gn:country_code":"HR",
    "gn:dem":881,
    "gn:feature_class":"P",
    "gn:feature_code":"PPLL",
    "gn:name":"Ljubovo",
    "gn:population":0,
    "gn:timezone":"Europe/Zagreb",
    "iso:country":"HR",
    "name:bos_x_preferred":[
        "Ljubovo"
    ],
    "name:fra_x_preferred":[
        "Ljubovo"
    ],
    "name:srp_x_preferred":[
        "\u0409\u0443\u0431\u043e\u0432\u043e"
    ],
    "wof:name":"Ljubovo",
    "wof:placetype":"locality"
},
  "geometry": {"coordinates":[15.53556,44.6525],"type":"Point"}
}