{
  "type": "Feature",
  "properties": {
    "gn:admin1_code":"4.0",
    "gn:admin2_code":"11129785.0",
    "gn:asciiname":"Deklevi",
    "gn:country_code":"HR",
    "gn:dem":288,
    "gn:feature_class":"P",
    "gn:feature_code":"PPL",
    "gn:name":"Deklevi",
    "gn:population":25,
    "gn:timezone":"Europe/Zagreb",
    "iso:country":"HR",
    "name:hrv_x_preferred":[
        "Deklevi"
    ],
    "name:ita_x_preferred":[
        "Declevi"
    ],
    "wof:name":"Deklevi",
    "wof:placetype":"locality",
    "wof:population":25
},
  "geometry": {"coordinates":[13.73508,45.28375],"type":"Point"}
}