{
  "type": "Feature",
  "properties": {
    "gn:admin1_code":"19.0",
    "gn:asciiname":"Malbasa",
    "gn:country_code":"HR",
    "gn:dem":181,
    "gn:feature_class":"P",
    "gn:feature_code":"PPL",
    "gn:name":"Malba\u0161a",
    "gn:population":0,
    "gn:timezone":"Europe/Zagreb",
    "iso:country":"HR",
    "wof:name":"Malbasa",
    "wof:placetype":"locality"
},
  "geometry": {"coordinates":[15.52583,44.0725],"type":"Point"}
}