{
  "type": "Feature",
  "properties": {
    "gn:admin1_code":"8.0",
    "gn:admin2_code":"11049288.0",
    "gn:asciiname":"Rasoja",
    "gn:country_code":"HR",
    "gn:dem":592,
    "gn:feature_class":"P",
    "gn:feature_code":"PPL",
    "gn:name":"Rasoja",
    "gn:population":0,
    "gn:timezone":"Europe/Zagreb",
    "iso:country":"HR",
    "wof:name":"Rasoja",
    "wof:placetype":"locality"
},
  "geometry": {"coordinates":[15.71694,44.37806],"type":"Point"}
}