{
  "type": "Feature",
  "properties": {
    "gn:admin1_code":"15",
    "gn:admin2_code":"11054614.0",
    "gn:asciiname":"Gornje Postinje",
    "gn:cc2":"HR",
    "gn:country_code":"HR",
    "gn:dem":450,
    "gn:feature_class":"P",
    "gn:feature_code":"PPL",
    "gn:name":"Gornje Postinje",
    "gn:population":135,
    "gn:timezone":"Europe/Zagreb",
    "iso:country":"HR",
    "name:und_x_variant":[
        "Postinje Gornje",
        "Gornje Postinje"
    ],
    "wof:name":"Gornje Postinje",
    "wof:placetype":"locality",
    "wof:population":135
},
  "geometry": {"coordinates":[16.42516,43.70275],"type":"Point"}
}