{
  "type": "Feature",
  "properties": {
    "gn:admin1_code":"19.0",
    "gn:asciiname":"Majstrovic",
    "gn:country_code":"HR",
    "gn:dem":177,
    "gn:feature_class":"P",
    "gn:feature_code":"PPL",
    "gn:name":"Majstrovi\u0107",
    "gn:population":0,
    "gn:timezone":"Europe/Zagreb",
    "iso:country":"HR",
    "wof:name":"Majstrovic",
    "wof:placetype":"locality"
},
  "geometry": {"coordinates":[15.74472,44.18361],"type":"Point"}
}