{
  "type": "Feature",
  "properties": {
    "gn:admin1_code":"14",
    "gn:asciiname":"Milisavci",
    "gn:cc2":"HR",
    "gn:country_code":"HR",
    "gn:dem":282,
    "gn:feature_class":"P",
    "gn:feature_code":"PPL",
    "gn:name":"Milisavci",
    "gn:population":0,
    "gn:timezone":"Europe/Zagreb",
    "iso:country":"HR",
    "name:und_x_variant":[
        "Gole\u0161i Milisavci",
        "Milisavci"
    ],
    "wof:name":"Milisavci",
    "wof:placetype":"locality"
},
  "geometry": {"coordinates":[17.16667,45.33333],"type":"Point"}
}