{
  "type": "Feature",
  "properties": {
    "gn:admin1_code":"05",
    "gn:admin2_code":"11049276.0",
    "gn:asciiname":"Maletic",
    "gn:country_code":"HR",
    "gn:dem":149,
    "gn:feature_class":"P",
    "gn:feature_code":"PPL",
    "gn:name":"Maleti\u0107",
    "gn:population":0,
    "gn:timezone":"Europe/Zagreb",
    "iso:country":"HR",
    "wof:name":"Maletic",
    "wof:placetype":"locality"
},
  "geometry": {"coordinates":[15.43333,45.48333],"type":"Point"}
}