{
  "type": "Feature",
  "properties": {
    "gn:admin1_code":"13.0",
    "gn:asciiname":"Marasovine",
    "gn:country_code":"HR",
    "gn:dem":263,
    "gn:feature_class":"P",
    "gn:feature_code":"PPL",
    "gn:name":"Marasovine",
    "gn:population":0,
    "gn:timezone":"Europe/Zagreb",
    "iso:country":"HR",
    "wof:name":"Marasovine",
    "wof:placetype":"locality"
},
  "geometry": {"coordinates":[16.09361,44.00278],"type":"Point"}
}