{
  "type": "Feature",
  "properties": {
    "gn:admin1_code":"3.0",
    "gn:admin2_code":"11054971.0",
    "gn:asciiname":"Iskisli",
    "gn:country_code":"HR",
    "gn:dem":79,
    "gn:feature_class":"P",
    "gn:feature_code":"PPL",
    "gn:name":"Iskisli",
    "gn:population":0,
    "gn:timezone":"Europe/Zagreb",
    "iso:country":"HR",
    "wof:name":"Iskisli",
    "wof:placetype":"locality"
},
  "geometry": {"coordinates":[17.5425,43.12056],"type":"Point"}
}