{
  "type": "Feature",
  "properties": {
    "gn:admin1_code":"12.0",
    "gn:asciiname":"Orehov Hrib",
    "gn:country_code":"HR",
    "gn:dem":842,
    "gn:feature_class":"P",
    "gn:feature_code":"PPL",
    "gn:name":"Orehov Hrib",
    "gn:population":0,
    "gn:timezone":"Europe/Zagreb",
    "iso:country":"HR",
    "wof:name":"Orehov Hrib",
    "wof:placetype":"locality"
},
  "geometry": {"coordinates":[14.58861,45.64167],"type":"Point"}
}