{
  "type": "Feature",
  "properties": {
    "gn:admin1_code":"5.0",
    "gn:asciiname":"Lovrici",
    "gn:country_code":"HR",
    "gn:dem":225,
    "gn:feature_class":"P",
    "gn:feature_code":"PPL",
    "gn:name":"Lovri\u0107i",
    "gn:population":0,
    "gn:timezone":"Europe/Zagreb",
    "iso:country":"HR",
    "wof:name":"Lovrici",
    "wof:placetype":"locality"
},
  "geometry": {"coordinates":[15.6475,45.21028],"type":"Point"}
}