{
  "type": "Feature",
  "properties": {
    "gn:admin1_code":"20",
    "gn:admin2_code":"11048989.0",
    "gn:asciiname":"Stara Marca",
    "gn:country_code":"HR",
    "gn:dem":151,
    "gn:feature_class":"P",
    "gn:feature_code":"PPL",
    "gn:name":"Stara Mar\u010da",
    "gn:population":138,
    "gn:timezone":"Europe/Zagreb",
    "iso:country":"HR",
    "wof:name":"Stara Marca",
    "wof:placetype":"locality",
    "wof:population":138
},
  "geometry": {"coordinates":[16.48267,45.76716],"type":"Point"}
}