{
  "type": "Feature",
  "properties": {
    "gn:admin1_code":"03",
    "gn:admin2_code":"7577034.0",
    "gn:asciiname":"Stikovica",
    "gn:country_code":"HR",
    "gn:dem":37,
    "gn:feature_class":"P",
    "gn:feature_code":"PPL",
    "gn:name":"\u0160tikovica",
    "gn:population":0,
    "gn:timezone":"Europe/Zagreb",
    "iso:country":"HR",
    "wof:name":"Stikovica",
    "wof:placetype":"locality"
},
  "geometry": {"coordinates":[18.05056,42.68694],"type":"Point"}
}