{
  "type": "Feature",
  "properties": {
    "gn:admin1_code":"20",
    "gn:admin2_code":"3188243.0",
    "gn:asciiname":"Petina",
    "gn:country_code":"HR",
    "gn:dem":103,
    "gn:feature_class":"P",
    "gn:feature_code":"PPL",
    "gn:name":"Petina",
    "gn:population":213,
    "gn:timezone":"Europe/Zagreb",
    "iso:country":"HR",
    "name:bos_x_preferred":[
        "Petina"
    ],
    "name:ceb_x_preferred":[
        "Petina"
    ],
    "name:hrv_x_preferred":[
        "Petina"
    ],
    "name:hun_x_preferred":[
        "Petina"
    ],
    "name:nld_x_preferred":[
        "Petina"
    ],
    "name:slv_x_preferred":[
        "Petina"
    ],
    "name:srp_x_preferred":[
        "\u041f\u0435\u0442\u0438\u043d\u0430"
    ],
    "name:swe_x_preferred":[
        "Petina"
    ],
    "name:ukr_x_preferred":[
        "\u041f\u0435\u0442\u0438\u043d\u0430"
    ],
    "wof:name":"Petina",
    "wof:placetype":"locality",
    "wof:population":213
},
  "geometry": {"coordinates":[16.08333,45.75],"type":"Point"}
}