{
  "type": "Feature",
  "properties": {
    "gn:population":2771,
    "iso:country":"HR",
    "name:alb_x_preferred":[
        "Strizivojna"
    ],
    "name:bos_x_preferred":[
        "Strizivojna"
    ],
    "name:dut_x_preferred":[
        "Strizivojna"
    ],
    "name:eng_x_preferred":[
        "Strizivojna"
    ],
    "name:fra_x_preferred":[
        "Strizivojna"
    ],
    "name:fre_x_preferred":[
        "Strizivojna"
    ],
    "name:hbs_x_preferred":[
        "Strizivojna"
    ],
    "name:hrv_x_preferred":[
        "Strizivojna"
    ],
    "name:hun_x_preferred":[
        "Strizivojna"
    ],
    "name:ita_x_preferred":[
        "Strizivojna"
    ],
    "name:nld_x_preferred":[
        "Strizivojna"
    ],
    "name:pol_x_preferred":[
        "Strizivojna"
    ],
    "name:ron_x_preferred":[
        "Comuna Strizivojna"
    ],
    "name:rum_x_preferred":[
        "Comuna Strizivojna"
    ],
    "name:slv_x_preferred":[
        "Strizivojna"
    ],
    "name:spa_x_preferred":[
        "Strizivojna"
    ],
    "name:sqi_x_preferred":[
        "Strizivojna"
    ],
    "name:srp_x_preferred":[
        "\u0421\u0442\u0440\u0438\u0437\u0438\u0432\u043e\u0458\u043d\u0430"
    ],
    "name:swe_x_preferred":[
        "Strizivojna"
    ],
    "name:und_x_preferred":[
        "Strizivojna"
    ],
    "name:war_x_preferred":[
        "Strizivojna"
    ],
    "qs:a0":"Republika Hrvatska",
    "qs:a1":"*Osjecko-baranjska \u017eupanija",
    "qs:a1r":"0",
    "qs:adm0":"Republika Hrvatska",
    "qs:la_lc":"*",
    "qs:level":"locality",
    "qs:loc":"Strizivojna",
    "qs:loc_alt":"Strizivojna",
    "qs:pop":0,
    "qs:type":"buffered point",
    "wd:wordcount":52,
    "wof:lang":[
        "unk"
    ],
    "wof:name":"Strizivojna",
    "wof:placetype":"locality",
    "wof:population":2771
},
  "geometry": {"coordinates":[18.438369,45.221458],"type":"Point"}
}