{
  "type": "Feature",
  "properties": {
    "gn:admin1_code":"13.0",
    "gn:admin2_code":"11055025.0",
    "gn:asciiname":"Lukar",
    "gn:country_code":"HR",
    "gn:dem":339,
    "gn:feature_class":"P",
    "gn:feature_code":"PPL",
    "gn:name":"Lukar",
    "gn:population":78,
    "gn:timezone":"Europe/Zagreb",
    "iso:country":"HR",
    "name:bos_x_preferred":[
        "Lukar"
    ],
    "name:ceb_x_preferred":[
        "Lukar"
    ],
    "name:fra_x_preferred":[
        "Lukar"
    ],
    "name:hun_x_preferred":[
        "Lukar"
    ],
    "name:slv_x_preferred":[
        "Lukar"
    ],
    "name:srp_x_preferred":[
        "\u041b\u0443\u043a\u0430\u0440"
    ],
    "wof:name":"Lukar",
    "wof:placetype":"locality",
    "wof:population":78
},
  "geometry": {"coordinates":[16.12361,43.96194000000001],"type":"Point"}
}