{
  "type": "Feature",
  "properties": {
    "gn:admin1_code":"05",
    "gn:admin2_code":"3187450.0",
    "gn:asciiname":"Prisjeka",
    "gn:country_code":"HR",
    "gn:dem":227,
    "gn:feature_class":"P",
    "gn:feature_code":"PPL",
    "gn:name":"Prisjeka",
    "gn:population":24,
    "gn:timezone":"Europe/Zagreb",
    "iso:country":"HR",
    "wof:name":"Prisjeka",
    "wof:placetype":"locality",
    "wof:population":24
},
  "geometry": {"coordinates":[15.71111,45.24222],"type":"Point"}
}