{
  "type": "Feature",
  "properties": {
    "gn:admin1_code":"15.0",
    "gn:asciiname":"Ronici",
    "gn:country_code":"HR",
    "gn:dem":308,
    "gn:feature_class":"P",
    "gn:feature_code":"PPL",
    "gn:name":"Roni\u0107i",
    "gn:population":0,
    "gn:timezone":"Europe/Zagreb",
    "iso:country":"HR",
    "wof:name":"Ronici",
    "wof:placetype":"locality"
},
  "geometry": {"coordinates":[16.64472,43.7775],"type":"Point"}
}