{
  "type": "Feature",
  "properties": {
    "gn:admin1_code":"20",
    "gn:admin2_code":"3186602.0",
    "gn:asciiname":"Radoisce",
    "gn:cc2":"HR",
    "gn:country_code":"HR",
    "gn:dem":197,
    "gn:feature_class":"P",
    "gn:feature_code":"PPL",
    "gn:name":"Radoi\u0161\u0107e",
    "gn:population":250,
    "gn:timezone":"Europe/Zagreb",
    "iso:country":"HR",
    "name:und_x_variant":[
        "Radoji\u0161\u0107e",
        "Radoi\u0161\u0107e"
    ],
    "wof:name":"Radoisce",
    "wof:placetype":"locality",
    "wof:population":250
},
  "geometry": {"coordinates":[16.33056,46.01861],"type":"Point"}
}