{
  "type": "Feature",
  "properties": {
    "gn:admin1_code":"12",
    "gn:admin2_code":"3194097.0",
    "gn:asciiname":"Icici",
    "gn:cc2":"HR",
    "gn:country_code":"HR",
    "gn:dem":18,
    "gn:feature_class":"P",
    "gn:feature_code":"PPL",
    "gn:name":"I\u010di\u0107i",
    "gn:population":0,
    "gn:timezone":"Europe/Zagreb",
    "iso:country":"HR",
    "name:bos_x_preferred":[
        "I\u010di\u0107i"
    ],
    "name:ceb_x_preferred":[
        "I\u010di\u0107i"
    ],
    "name:deu_x_preferred":[
        "I\u010di\u0107i"
    ],
    "name:fra_x_preferred":[
        "I\u010di\u0107i"
    ],
    "name:hrv_x_preferred":[
        "I\u010di\u0107i"
    ],
    "name:hun_x_preferred":[
        "I\u010di\u0107i"
    ],
    "name:slv_x_preferred":[
        "I\u010di\u0107i"
    ],
    "name:spa_x_preferred":[
        "I\u010di\u0107i"
    ],
    "name:srp_x_preferred":[
        "\u0418\u0447\u0438\u045b\u0438"
    ],
    "name:swe_x_preferred":[
        "I\u010di\u0107i"
    ],
    "name:ukr_x_preferred":[
        "\u0406\u0447\u0438\u0447\u0456"
    ],
    "name:und_x_variant":[
        "Ville d\u2019Icici",
        "I\u010di\u0107i"
    ],
    "wof:name":"Icici",
    "wof:placetype":"locality"
},
  "geometry": {"coordinates":[14.28,45.30722],"type":"Point"}
}