{
  "type": "Feature",
  "properties": {
    "gn:admin1_code":"8.0",
    "gn:asciiname":"Obilje",
    "gn:country_code":"HR",
    "gn:dem":461,
    "gn:feature_class":"P",
    "gn:feature_code":"PPL",
    "gn:name":"Obilje",
    "gn:population":0,
    "gn:timezone":"Europe/Zagreb",
    "iso:country":"HR",
    "wof:name":"Obilje",
    "wof:placetype":"locality"
},
  "geometry": {"coordinates":[15.25139,44.84056],"type":"Point"}
}