{
  "type": "Feature",
  "properties": {
    "gn:admin1_code":"14",
    "gn:asciiname":"Gornji Rajic",
    "gn:country_code":"HR",
    "gn:dem":113,
    "gn:feature_class":"P",
    "gn:feature_code":"PPL",
    "gn:name":"Gornji Raji\u0107",
    "gn:population":0,
    "gn:timezone":"Europe/Zagreb",
    "iso:country":"HR",
    "wof:name":"Gornji Rajic",
    "wof:placetype":"locality"
},
  "geometry": {"coordinates":[17.09667,45.30611],"type":"Point"}
}