{
  "type": "Feature",
  "properties": {
    "gn:admin1_code":"8.0",
    "gn:admin2_code":"11049291.0",
    "gn:asciiname":"Kaniza",
    "gn:country_code":"HR",
    "gn:dem":585,
    "gn:feature_class":"P",
    "gn:feature_code":"PPL",
    "gn:name":"Kani\u017ea",
    "gn:population":0,
    "gn:timezone":"Europe/Zagreb",
    "iso:country":"HR",
    "wof:name":"Kaniza",
    "wof:placetype":"locality"
},
  "geometry": {"coordinates":[15.37028,44.64167],"type":"Point"}
}