{
  "type": "Feature",
  "properties": {
    "gn:admin1_code":"01",
    "gn:asciiname":"Srednji Borki",
    "gn:country_code":"HR",
    "gn:dem":469,
    "gn:feature_class":"P",
    "gn:feature_code":"PPL",
    "gn:name":"Srednji Borki",
    "gn:population":0,
    "gn:timezone":"Europe/Zagreb",
    "iso:country":"HR",
    "wof:name":"Srednji Borki",
    "wof:placetype":"locality"
},
  "geometry": {"coordinates":[17.35,45.56667],"type":"Point"}
}