{
  "type": "Feature",
  "properties": {
    "gn:admin1_code":"20",
    "gn:admin2_code":"3186780.0",
    "gn:asciiname":"Kupljenovo",
    "gn:country_code":"HR",
    "gn:dem":144,
    "gn:feature_class":"P",
    "gn:feature_code":"PPL",
    "gn:name":"Kupljenovo",
    "gn:population":704,
    "gn:timezone":"Europe/Zagreb",
    "iso:country":"HR",
    "wof:name":"Kupljenovo",
    "wof:placetype":"locality",
    "wof:population":704
},
  "geometry": {"coordinates":[15.80589,45.92918],"type":"Point"}
}