{
  "type": "Feature",
  "properties": {
    "gn:admin1_code":"20",
    "gn:admin2_code":"3186780.0",
    "gn:asciiname":"Kupljenovo",
    "gn:country_code":"HR",
    "gn:dem":144,
    "gn:feature_class":"P",
    "gn:feature_code":"PPL",
    "gn:name":"Kupljenovo",
    "gn:population":704,
    "gn:timezone":"Europe/Zagreb",
    "iso:country":"HR",
    "name:bos_x_preferred":[
        "Kupljenovo"
    ],
    "name:hrv_x_preferred":[
        "Kupljenovo"
    ],
    "name:hun_x_preferred":[
        "Kupljenovo"
    ],
    "name:nld_x_preferred":[
        "Kupljenovo"
    ],
    "name:slv_x_preferred":[
        "Kupljenovo"
    ],
    "name:srp_x_preferred":[
        "\u041a\u0443\u043f\u0459\u0435\u043d\u043e\u0432\u043e"
    ],
    "name:ukr_x_preferred":[
        "\u041a\u0443\u043f\u043b\u0454\u043d\u043e\u0432\u043e"
    ],
    "wof:name":"Kupljenovo",
    "wof:placetype":"locality",
    "wof:population":704
},
  "geometry": {"coordinates":[15.80589,45.92918],"type":"Point"}
}