{
  "type": "Feature",
  "properties": {
    "gn:admin1_code":"4.0",
    "gn:asciiname":"Fizela",
    "gn:country_code":"HR",
    "gn:dem":11,
    "gn:feature_class":"P",
    "gn:feature_code":"PPL",
    "gn:name":"Fi\u017eela",
    "gn:population":0,
    "gn:timezone":"Europe/Zagreb",
    "iso:country":"HR",
    "wof:name":"Fizela",
    "wof:placetype":"locality"
},
  "geometry": {"coordinates":[13.80639,44.86917],"type":"Point"}
}