{
  "type": "Feature",
  "properties": {
    "gn:admin1_code":"14.0",
    "gn:asciiname":"Drljace",
    "gn:cc2":"HR",
    "gn:country_code":"HR",
    "gn:dem":241,
    "gn:feature_class":"P",
    "gn:feature_code":"PPL",
    "gn:name":"Drlja\u010de",
    "gn:population":0,
    "gn:timezone":"Europe/Zagreb",
    "iso:country":"HR",
    "name:und_x_variant":[
        "Drlja\u010da",
        "Drlja\u010de"
    ],
    "wof:name":"Drljace",
    "wof:placetype":"locality"
},
  "geometry": {"coordinates":[16.11167,45.12806],"type":"Point"}
}