{
  "type": "Feature",
  "properties": {
    "gn:admin1_code":"8.0",
    "gn:asciiname":"Oreskovici",
    "gn:country_code":"HR",
    "gn:dem":436,
    "gn:feature_class":"P",
    "gn:feature_code":"PPL",
    "gn:name":"Ore\u0161kovi\u0107i",
    "gn:population":0,
    "gn:timezone":"Europe/Zagreb",
    "iso:country":"HR",
    "wof:name":"Oreskovici",
    "wof:placetype":"locality"
},
  "geometry": {"coordinates":[15.16639,44.91278],"type":"Point"}
}