{
  "type": "Feature",
  "properties": {
    "gn:admin1_code":"8.0",
    "gn:admin2_code":"11049285.0",
    "gn:asciiname":"Babin Kraj",
    "gn:country_code":"HR",
    "gn:dem":629,
    "gn:feature_class":"P",
    "gn:feature_code":"PPL",
    "gn:name":"Babin Kraj",
    "gn:population":0,
    "gn:timezone":"Europe/Zagreb",
    "iso:country":"HR",
    "wof:name":"Babin Kraj",
    "wof:placetype":"locality"
},
  "geometry": {"coordinates":[16.04611,44.47639],"type":"Point"}
}