{
  "type": "Feature",
  "properties": {
    "gn:admin1_code":"20",
    "gn:asciiname":"Desni Dubrovcak",
    "gn:cc2":"HR",
    "gn:country_code":"HR",
    "gn:dem":98,
    "gn:feature_class":"P",
    "gn:feature_code":"PPL",
    "gn:name":"Desni Dubrov\u010dak",
    "gn:population":0,
    "gn:timezone":"Europe/Zagreb",
    "iso:country":"HR",
    "name:und_x_variant":[
        "Desni Dubrav\u010dak",
        "Desni Dubrov\u010dak"
    ],
    "wof:name":"Desni Dubrovcak",
    "wof:placetype":"locality"
},
  "geometry": {"coordinates":[16.35,45.65],"type":"Point"}
}