{
  "type": "Feature",
  "properties": {
    "gn:admin1_code":"19.0",
    "gn:asciiname":"Crni Lug",
    "gn:cc2":"HR",
    "gn:country_code":"HR",
    "gn:dem":763,
    "gn:feature_class":"P",
    "gn:feature_code":"PPL",
    "gn:name":"Crni Lug",
    "gn:population":0,
    "gn:timezone":"Europe/Zagreb",
    "iso:country":"HR",
    "name:bul_x_preferred":[
        "\u0426\u044a\u0440\u043d\u0438 \u041b\u0443\u0433"
    ],
    "name:ceb_x_preferred":[
        "Crni Lug"
    ],
    "name:fra_x_preferred":[
        "Crni Lug"
    ],
    "name:msa_x_preferred":[
        "Crni Lug"
    ],
    "name:por_x_preferred":[
        "Crni Lug"
    ],
    "name:slv_x_preferred":[
        "Crni Lug"
    ],
    "name:srp_x_preferred":[
        "\u0426\u0440\u043d\u0438 \u041b\u0443\u0433"
    ],
    "name:und_x_variant":[
        "Radakovi\u0107i",
        "Crni Lug"
    ],
    "wof:name":"Crni Lug",
    "wof:placetype":"locality"
},
  "geometry": {"coordinates":[15.91194,44.41028],"type":"Point"}
}