{
  "type": "Feature",
  "properties": {
    "gn:admin1_code":"15.0",
    "gn:asciiname":"Catrnja",
    "gn:country_code":"HR",
    "gn:dem":932,
    "gn:feature_class":"P",
    "gn:feature_code":"PPL",
    "gn:name":"\u010catrnja",
    "gn:population":0,
    "gn:timezone":"Europe/Zagreb",
    "iso:country":"HR",
    "wof:name":"Catrnja",
    "wof:placetype":"locality"
},
  "geometry": {"coordinates":[16.79167,43.73194],"type":"Point"}
}