{
  "type": "Feature",
  "properties": {
    "gn:admin1_code":"02",
    "gn:admin2_code":"11049492.0",
    "gn:asciiname":"Poljane",
    "gn:country_code":"HR",
    "gn:dem":102,
    "gn:feature_class":"P",
    "gn:feature_code":"PPL",
    "gn:name":"Poljane",
    "gn:population":100,
    "gn:timezone":"Europe/Zagreb",
    "iso:country":"HR",
    "wof:name":"Poljane",
    "wof:placetype":"locality",
    "wof:population":100
},
  "geometry": {"coordinates":[17.31139,45.23889000000001],"type":"Point"}
}