{
  "type": "Feature",
  "properties": {
    "gn:admin1_code":"02",
    "gn:admin2_code":"11049492.0",
    "gn:asciiname":"Poljane",
    "gn:country_code":"HR",
    "gn:dem":102,
    "gn:feature_class":"P",
    "gn:feature_code":"PPL",
    "gn:name":"Poljane",
    "gn:population":100,
    "gn:timezone":"Europe/Zagreb",
    "iso:country":"HR",
    "name:bos_x_preferred":[
        "Poljane"
    ],
    "name:ceb_x_preferred":[
        "Poljane"
    ],
    "name:fra_x_preferred":[
        "Poljane"
    ],
    "name:hrv_x_preferred":[
        "Poljane"
    ],
    "name:hun_x_preferred":[
        "Poljane"
    ],
    "name:nld_x_preferred":[
        "Poljane"
    ],
    "name:sco_x_preferred":[
        "Poljane"
    ],
    "name:slv_x_preferred":[
        "Poljane"
    ],
    "name:srp_x_preferred":[
        "\u041f\u043e\u0459\u0430\u043d\u0435"
    ],
    "name:swe_x_preferred":[
        "Poljane"
    ],
    "wof:name":"Poljane",
    "wof:placetype":"locality",
    "wof:population":100
},
  "geometry": {"coordinates":[17.31139,45.23889000000001],"type":"Point"}
}