{
  "type": "Feature",
  "properties": {
    "gn:admin1_code":"04",
    "gn:asciiname":"Momjan",
    "gn:cc2":"HR",
    "gn:country_code":"HR",
    "gn:dem":286,
    "gn:feature_class":"P",
    "gn:feature_code":"PPL",
    "gn:name":"Momjan",
    "gn:population":0,
    "gn:timezone":"Europe/Zagreb",
    "iso:country":"HR",
    "name:bos_x_preferred":[
        "Momjan"
    ],
    "name:fra_x_preferred":[
        "Momjan"
    ],
    "name:hrv_x_preferred":[
        "Momjan"
    ],
    "name:hun_x_preferred":[
        "Momjan"
    ],
    "name:ita_x_preferred":[
        "Momiano"
    ],
    "name:nld_x_preferred":[
        "Momjan"
    ],
    "name:slv_x_preferred":[
        "Momjan"
    ],
    "name:srp_x_preferred":[
        "\u041c\u043e\u043c\u0458\u0430\u043d"
    ],
    "name:ukr_x_preferred":[
        "\u041c\u043e\u043c'\u044f\u043d"
    ],
    "name:und_x_variant":[
        "Mumjan"
    ],
    "wof:name":"Momjan",
    "wof:placetype":"locality"
},
  "geometry": {"coordinates":[13.71111,45.43861],"type":"Point"}
}