{
  "type": "Feature",
  "properties": {
    "gn:admin1_code":"14.0",
    "gn:asciiname":"Korizme",
    "gn:country_code":"HR",
    "gn:dem":153,
    "gn:feature_class":"P",
    "gn:feature_code":"PPL",
    "gn:name":"Korizme",
    "gn:population":0,
    "gn:timezone":"Europe/Zagreb",
    "iso:country":"HR",
    "wof:name":"Korizme",
    "wof:placetype":"locality"
},
  "geometry": {"coordinates":[16.34806,45.12167],"type":"Point"}
}