{
  "type": "Feature",
  "properties": {
    "gn:admin1_code":"10",
    "gn:admin2_code":"11054477.0",
    "gn:asciiname":"Oresnjak",
    "gn:country_code":"HR",
    "gn:dem":108,
    "gn:feature_class":"P",
    "gn:feature_code":"PPL",
    "gn:name":"Ore\u0161njak",
    "gn:population":0,
    "gn:timezone":"Europe/Zagreb",
    "iso:country":"HR",
    "name:hrv_x_preferred":[
        "Ore\u0161njak"
    ],
    "name:und_x_variant":[
        "Ore\u0161njak Pustara",
        "Ore\u0161njak"
    ],
    "wof:name":"Oresnjak",
    "wof:placetype":"locality"
},
  "geometry": {"coordinates":[17.95,45.76667],"type":"Point"}
}