{
  "type": "Feature",
  "properties": {
    "gn:admin1_code":"3.0",
    "gn:asciiname":"Dardin",
    "gn:country_code":"HR",
    "gn:dem":34,
    "gn:feature_class":"P",
    "gn:feature_code":"PPL",
    "gn:name":"\u00d0ardin",
    "gn:population":0,
    "gn:timezone":"Europe/Zagreb",
    "iso:country":"HR",
    "wof:name":"Dardin",
    "wof:placetype":"locality"
},
  "geometry": {"coordinates":[17.89777999999999,42.71306],"type":"Point"}
}