{
  "type": "Feature",
  "properties": {
    "gn:admin1_code":"14.0",
    "gn:asciiname":"Brdani",
    "gn:country_code":"HR",
    "gn:dem":415,
    "gn:feature_class":"P",
    "gn:feature_code":"PPL",
    "gn:name":"Br\u0111ani",
    "gn:population":0,
    "gn:timezone":"Europe/Zagreb",
    "iso:country":"HR",
    "wof:name":"Brdani",
    "wof:placetype":"locality"
},
  "geometry": {"coordinates":[16.15444,45.16417],"type":"Point"}
}