{
  "type": "Feature",
  "properties": {
    "gn:admin1_code":"8.0",
    "gn:asciiname":"Papicic Selo",
    "gn:country_code":"HR",
    "gn:dem":583,
    "gn:feature_class":"P",
    "gn:feature_code":"PPL",
    "gn:name":"Papi\u010di\u0107 Selo",
    "gn:population":0,
    "gn:timezone":"Europe/Zagreb",
    "iso:country":"HR",
    "wof:name":"Papicic Selo",
    "wof:placetype":"locality"
},
  "geometry": {"coordinates":[15.25111,44.57972],"type":"Point"}
}