{
  "type": "Feature",
  "properties": {
    "gn:admin1_code":"8.0",
    "gn:admin2_code":"11049285.0",
    "gn:asciiname":"Pod Debeljacom",
    "gn:country_code":"HR",
    "gn:dem":575,
    "gn:feature_class":"P",
    "gn:feature_code":"PPL",
    "gn:name":"Pod Debelja\u010dom",
    "gn:population":0,
    "gn:timezone":"Europe/Zagreb",
    "iso:country":"HR",
    "wof:name":"Pod Debeljacom",
    "wof:placetype":"locality"
},
  "geometry": {"coordinates":[16.09972,44.49278],"type":"Point"}
}