{
  "type": "Feature",
  "properties": {
    "gn:admin1_code":"01",
    "gn:admin2_code":"3200709.0",
    "gn:asciiname":"Duhovi",
    "gn:country_code":"HR",
    "gn:dem":114,
    "gn:feature_class":"P",
    "gn:feature_code":"PPL",
    "gn:name":"Duhovi",
    "gn:population":111,
    "gn:timezone":"Europe/Zagreb",
    "iso:country":"HR",
    "wof:name":"Duhovi",
    "wof:placetype":"locality",
    "wof:population":111
},
  "geometry": {"coordinates":[17.00832999999999,45.51944],"type":"Point"}
}