{
  "type": "Feature",
  "properties": {
    "gn:admin1_code":"08",
    "gn:asciiname":"Ponori",
    "gn:cc2":"HR",
    "gn:country_code":"HR",
    "gn:dem":486,
    "gn:feature_class":"P",
    "gn:feature_code":"PPLL",
    "gn:name":"Ponori",
    "gn:population":0,
    "gn:timezone":"Europe/Zagreb",
    "iso:country":"HR",
    "name:bos_x_preferred":[
        "Ponori"
    ],
    "name:hrv_x_preferred":[
        "Ponori"
    ],
    "name:hun_x_preferred":[
        "Ponori"
    ],
    "name:nld_x_preferred":[
        "Ponori"
    ],
    "name:slv_x_preferred":[
        "Ponori"
    ],
    "name:spa_x_preferred":[
        "Ponori"
    ],
    "name:srp_x_preferred":[
        "\u041f\u043e\u043d\u043e\u0440\u0438"
    ],
    "name:ukr_x_preferred":[
        "\u041f\u043e\u043d\u043e\u0440\u0438"
    ],
    "name:und_x_variant":[
        "Ponore",
        "Ponori"
    ],
    "wof:name":"Ponori",
    "wof:placetype":"locality"
},
  "geometry": {"coordinates":[15.13944,44.87111],"type":"Point"}
}