{
  "type": "Feature",
  "properties": {
    "gn:admin1_code":"15.0",
    "gn:asciiname":"Gornja Mala",
    "gn:country_code":"HR",
    "gn:dem":479,
    "gn:feature_class":"P",
    "gn:feature_code":"PPL",
    "gn:name":"Gornja Mala",
    "gn:population":0,
    "gn:timezone":"Europe/Zagreb",
    "iso:country":"HR",
    "name:fra_x_preferred":[
        "Kni\u0107"
    ],
    "name:ita_x_preferred":[
        "Kni\u0107"
    ],
    "name:nld_x_preferred":[
        "Kni\u0107"
    ],
    "name:srp_x_preferred":[
        "\u041a\u043d\u0438\u045b"
    ],
    "wof:name":"Gornja Mala",
    "wof:placetype":"locality"
},
  "geometry": {"coordinates":[16.52111,43.68389000000001],"type":"Point"}
}