{
  "type": "Feature",
  "properties": {
    "gn:admin1_code":"20",
    "gn:admin2_code":"8260123.0",
    "gn:asciiname":"Stara Kapela",
    "gn:cc2":"HR",
    "gn:country_code":"HR",
    "gn:dem":125,
    "gn:feature_class":"P",
    "gn:feature_code":"PPL",
    "gn:name":"Stara Kapela",
    "gn:population":192,
    "gn:timezone":"Europe/Zagreb",
    "iso:country":"HR",
    "name:und_x_variant":[
        "Stara Srpska Kapela",
        "Stara Kapela"
    ],
    "wof:name":"Stara Kapela",
    "wof:placetype":"locality",
    "wof:population":192
},
  "geometry": {"coordinates":[16.59982999999999,45.88786],"type":"Point"}
}