{
  "type": "Feature",
  "properties": {
    "gn:admin1_code":"08",
    "gn:admin2_code":"11049294.0",
    "gn:asciiname":"Josan",
    "gn:cc2":"HR",
    "gn:country_code":"HR",
    "gn:dem":671,
    "gn:feature_class":"P",
    "gn:feature_code":"PPLL",
    "gn:name":"Jo\u0161an",
    "gn:population":0,
    "gn:timezone":"Europe/Zagreb",
    "iso:country":"HR",
    "name:und_x_variant":[
        "Jo\u0161ane",
        "Jo\u0161an"
    ],
    "wof:name":"Josan",
    "wof:placetype":"locality"
},
  "geometry": {"coordinates":[15.74889,44.57583],"type":"Point"}
}