{
  "type": "Feature",
  "properties": {
    "gn:admin1_code":"5.0",
    "gn:admin2_code":"11049267.0",
    "gn:asciiname":"Bosiljevo",
    "gn:country_code":"HR",
    "gn:dem":264,
    "gn:feature_class":"P",
    "gn:feature_code":"PPLA2",
    "gn:name":"Bosiljevo",
    "gn:population":0,
    "gn:timezone":"Europe/Zagreb",
    "iso:country":"HR",
    "name:bos_x_preferred":[
        "Bosiljevo"
    ],
    "name:cat_x_preferred":[
        "Bosiljevo"
    ],
    "name:deu_x_preferred":[
        "Bosiljevo"
    ],
    "name:fra_x_preferred":[
        "Bosiljevo"
    ],
    "name:hrv_x_preferred":[
        "Bosiljevo"
    ],
    "name:hun_x_preferred":[
        "Bosiljevo \u010cazmansko"
    ],
    "name:ita_x_preferred":[
        "Bosiljevo"
    ],
    "name:nld_x_preferred":[
        "Bosiljevo"
    ],
    "name:pol_x_preferred":[
        "Gmina Bosiljevo"
    ],
    "name:ron_x_preferred":[
        "Comuna Bosiljevo"
    ],
    "name:slk_x_preferred":[
        "Bosiljevo"
    ],
    "name:spa_x_preferred":[
        "Bosiljevo"
    ],
    "name:srp_x_preferred":[
        "Bosiljevo"
    ],
    "name:srp_x_variant":[
        "\u0411\u043e\u0441\u0438\u0459\u0435\u0432\u043e"
    ],
    "name:swe_x_preferred":[
        "Bosiljevo"
    ],
    "name:ukr_x_preferred":[
        "\u0411\u043e\u0441\u0438\u043b\u0454\u0432\u043e"
    ],
    "name:war_x_preferred":[
        "Bosiljevo"
    ],
    "wof:name":"Bosiljevo",
    "wof:placetype":"locality"
},
  "geometry": {"coordinates":[15.28833,45.40139],"type":"Point"}
}