{
  "type": "Feature",
  "properties": {
    "gn:admin1_code":"8.0",
    "gn:asciiname":"Ljubovica Poljana",
    "gn:cc2":"HR",
    "gn:country_code":"HR",
    "gn:dem":589,
    "gn:feature_class":"P",
    "gn:feature_code":"PPL",
    "gn:name":"Ljubovi\u0107a Poljana",
    "gn:population":0,
    "gn:timezone":"Europe/Zagreb",
    "iso:country":"HR",
    "name:und_x_variant":[
        "Poljana",
        "Ljubovi\u0107a Poljana"
    ],
    "wof:name":"Ljubovica Poljana",
    "wof:placetype":"locality"
},
  "geometry": {"coordinates":[15.97333,44.64139],"type":"Point"}
}