{
  "type": "Feature",
  "properties": {
    "gn:admin1_code":"20",
    "gn:admin2_code":"11049003.0",
    "gn:asciiname":"Hruskovec",
    "gn:country_code":"HR",
    "gn:dem":136,
    "gn:feature_class":"P",
    "gn:feature_code":"PPL",
    "gn:name":"Hru\u0161kovec",
    "gn:population":80,
    "gn:timezone":"Europe/Zagreb",
    "iso:country":"HR",
    "wof:name":"Hruskovec",
    "wof:placetype":"locality",
    "wof:population":80
},
  "geometry": {"coordinates":[16.33333,45.93333],"type":"Point"}
}