{
  "type": "Feature",
  "properties": {
    "gn:admin1_code":"20",
    "gn:admin2_code":"11049001.0",
    "gn:asciiname":"Slatina Ravenska",
    "gn:cc2":"HR",
    "gn:country_code":"HR",
    "gn:dem":161,
    "gn:feature_class":"P",
    "gn:feature_code":"PPL",
    "gn:name":"Slatina Ravenska",
    "gn:population":0,
    "gn:timezone":"Europe/Zagreb",
    "iso:country":"HR",
    "name:und_x_variant":[
        "Ravenska Slatina",
        "Slatina",
        "Slatina Ravenska"
    ],
    "wof:name":"Slatina Ravenska",
    "wof:placetype":"locality"
},
  "geometry": {"coordinates":[16.38332999999999,45.96667],"type":"Point"}
}