{
  "type": "Feature",
  "properties": {
    "gn:admin1_code":"15.0",
    "gn:asciiname":"Bilosi",
    "gn:country_code":"HR",
    "gn:dem":389,
    "gn:feature_class":"P",
    "gn:feature_code":"PPL",
    "gn:name":"Bilo\u0161i",
    "gn:population":0,
    "gn:timezone":"Europe/Zagreb",
    "iso:country":"HR",
    "wof:name":"Bilosi",
    "wof:placetype":"locality"
},
  "geometry": {"coordinates":[17.14972,43.40528],"type":"Point"}
}