{
  "type": "Feature",
  "properties": {
    "gn:admin1_code":"01",
    "gn:admin2_code":"11049403.0",
    "gn:asciiname":"Velika Trnava",
    "gn:cc2":"HR",
    "gn:country_code":"HR",
    "gn:dem":138,
    "gn:feature_class":"P",
    "gn:feature_code":"PPL",
    "gn:name":"Velika Trnava",
    "gn:population":298,
    "gn:timezone":"Europe/Zagreb",
    "iso:country":"HR",
    "name:und_x_variant":[
        "Trnava",
        "Velika Trnava"
    ],
    "wof:name":"Velika Trnava",
    "wof:placetype":"locality",
    "wof:population":298
},
  "geometry": {"coordinates":[17.03333,45.68333],"type":"Point"}
}