{
  "type": "Feature",
  "properties": {
    "gn:admin1_code":"2.0",
    "gn:admin2_code":"11049508.0",
    "gn:asciiname":"Trnacani",
    "gn:country_code":"HR",
    "gn:dem":138,
    "gn:feature_class":"P",
    "gn:feature_code":"PPL",
    "gn:name":"Trna\u010dani",
    "gn:population":0,
    "gn:timezone":"Europe/Zagreb",
    "iso:country":"HR",
    "wof:name":"Trnacani",
    "wof:placetype":"locality"
},
  "geometry": {"coordinates":[17.5225,45.23722],"type":"Point"}
}