{
  "type": "Feature",
  "properties": {
    "gn:admin1_code":"19",
    "gn:admin2_code":"11054377.0",
    "gn:asciiname":"Zman",
    "gn:cc2":"HR",
    "gn:country_code":"HR",
    "gn:dem":12,
    "gn:feature_class":"P",
    "gn:feature_code":"PPL",
    "gn:name":"\u017dman",
    "gn:population":199,
    "gn:timezone":"Europe/Zagreb",
    "iso:country":"HR",
    "name:bos_x_preferred":[
        "\u017dman"
    ],
    "name:fra_x_preferred":[
        "\u017dman"
    ],
    "name:hrv_x_preferred":[
        "\u017dman"
    ],
    "name:hun_x_preferred":[
        "\u017dman"
    ],
    "name:nld_x_preferred":[
        "\u017dman"
    ],
    "name:slv_x_preferred":[
        "\u017dman"
    ],
    "name:srp_x_preferred":[
        "\u0416\u043c\u0430\u043d"
    ],
    "name:ukr_x_preferred":[
        "\u0416\u043c\u0430\u043d"
    ],
    "name:und_x_variant":[
        "Sman"
    ],
    "wof:name":"Zman",
    "wof:placetype":"locality",
    "wof:population":199
},
  "geometry": {"coordinates":[15.11333,43.97222],"type":"Point"}
}