{
  "type": "Feature",
  "properties": {
    "gn:admin1_code":"10.0",
    "gn:admin2_code":"11054470.0",
    "gn:asciiname":"Albertinovac",
    "gn:country_code":"HR",
    "gn:dem":93,
    "gn:feature_class":"P",
    "gn:feature_code":"PPL",
    "gn:name":"Albertinovac",
    "gn:population":0,
    "gn:timezone":"Europe/Zagreb",
    "iso:country":"HR",
    "name:hrv_x_preferred":[
        "Albertinovac"
    ],
    "wof:name":"Albertinovac",
    "wof:placetype":"locality"
},
  "geometry": {"coordinates":[18.25,45.51667],"type":"Point"}
}