{
  "type": "Feature",
  "properties": {
    "gn:admin1_code":"20",
    "gn:admin2_code":"11049006.0",
    "gn:asciiname":"Restovo Zumberacko",
    "gn:cc2":"HR",
    "gn:country_code":"HR",
    "gn:dem":519,
    "gn:feature_class":"P",
    "gn:feature_code":"PPL",
    "gn:name":"Re\u0161tovo \u017dumbera\u010dko",
    "gn:population":14,
    "gn:timezone":"Europe/Zagreb",
    "iso:country":"HR",
    "name:und_x_variant":[
        "\u017dumbera\u010dko Re\u0161tovo",
        "Re\u0161tovo",
        "Re\u0161tovo \u017dumbera\u010dko"
    ],
    "wof:name":"Restovo Zumberacko",
    "wof:placetype":"locality",
    "wof:population":14
},
  "geometry": {"coordinates":[15.38917,45.74],"type":"Point"}
}