{
  "type": "Feature",
  "properties": {
    "gn:admin1_code":"15.0",
    "gn:asciiname":"Jukici",
    "gn:country_code":"HR",
    "gn:dem":283,
    "gn:feature_class":"P",
    "gn:feature_code":"PPL",
    "gn:name":"Juki\u0107i",
    "gn:population":0,
    "gn:timezone":"Europe/Zagreb",
    "iso:country":"HR",
    "wof:name":"Jukici",
    "wof:placetype":"locality"
},
  "geometry": {"coordinates":[17.15694,43.45],"type":"Point"}
}