{
  "type": "Feature",
  "properties": {
    "gn:admin1_code":"16",
    "gn:admin2_code":"11049320.0",
    "gn:asciiname":"Marcan",
    "gn:country_code":"HR",
    "gn:dem":221,
    "gn:feature_class":"P",
    "gn:feature_code":"PPL",
    "gn:name":"Mar\u010dan",
    "gn:population":598,
    "gn:timezone":"Europe/Zagreb",
    "iso:country":"HR",
    "wof:name":"Marcan",
    "wof:placetype":"locality",
    "wof:population":598
},
  "geometry": {"coordinates":[16.14806,46.32917],"type":"Point"}
}