{
  "type": "Feature",
  "properties": {
    "gn:admin1_code":"19.0",
    "gn:asciiname":"Musapstan",
    "gn:country_code":"HR",
    "gn:dem":66,
    "gn:feature_class":"P",
    "gn:feature_code":"PPL",
    "gn:name":"Musapstan",
    "gn:population":0,
    "gn:timezone":"Europe/Zagreb",
    "iso:country":"HR",
    "wof:name":"Musapstan",
    "wof:placetype":"locality"
},
  "geometry": {"coordinates":[15.28194,44.12444],"type":"Point"}
}