{
  "type": "Feature",
  "properties": {
    "gn:admin1_code":"15.0",
    "gn:asciiname":"Kapuilice",
    "gn:country_code":"HR",
    "gn:dem":508,
    "gn:feature_class":"P",
    "gn:feature_code":"PPL",
    "gn:name":"Kapuilice",
    "gn:population":0,
    "gn:timezone":"Europe/Zagreb",
    "iso:country":"HR",
    "wof:name":"Kapuilice",
    "wof:placetype":"locality"
},
  "geometry": {"coordinates":[16.88056,43.53528],"type":"Point"}
}