{
  "type": "Feature",
  "properties": {
    "gn:admin1_code":"15.0",
    "gn:asciiname":"Privor",
    "gn:country_code":"HR",
    "gn:dem":162,
    "gn:feature_class":"P",
    "gn:feature_code":"PPL",
    "gn:name":"Privor",
    "gn:population":0,
    "gn:timezone":"Europe/Zagreb",
    "iso:country":"HR",
    "wof:name":"Privor",
    "wof:placetype":"locality"
},
  "geometry": {"coordinates":[16.55278,43.52833],"type":"Point"}
}