{
  "type": "Feature",
  "properties": {
    "gn:admin1_code":"3.0",
    "gn:admin2_code":"11054963.0",
    "gn:asciiname":"Dancanje",
    "gn:country_code":"HR",
    "gn:dem":114,
    "gn:feature_class":"P",
    "gn:feature_code":"PPL",
    "gn:name":"Dan\u010danje",
    "gn:population":0,
    "gn:timezone":"Europe/Zagreb",
    "iso:country":"HR",
    "wof:name":"Dancanje",
    "wof:placetype":"locality"
},
  "geometry": {"coordinates":[17.55778,42.99111],"type":"Point"}
}