{
  "type": "Feature",
  "properties": {
    "gn:country":"HR",
    "gn:fcode":"PPL",
    "gn:population":0,
    "iso:country":"HR",
    "name:ara_x_preferred":[
        "\u0644\u0627\u0633\u062a\u0648\u0641\u0648"
    ],
    "name:bre_x_preferred":[
        "Lastovo"
    ],
    "name:bul_x_preferred":[
        "\u041b\u0430\u0441\u0442\u043e\u0432\u043e"
    ],
    "name:ceb_x_preferred":[
        "Otok Lastovo"
    ],
    "name:ces_x_preferred":[
        "Lastovo"
    ],
    "name:deu_x_preferred":[
        "Lastovo"
    ],
    "name:ell_x_preferred":[
        "\u039b\u03ac\u03c3\u03c4\u03bf\u03b2\u03bf"
    ],
    "name:fra_x_preferred":[
        "Lastovo"
    ],
    "name:hrv_x_preferred":[
        "Lastovo"
    ],
    "name:hsb_x_preferred":[
        "Lastovo"
    ],
    "name:ind_x_preferred":[
        "Lastovo"
    ],
    "name:ita_x_preferred":[
        "Lagosta"
    ],
    "name:kor_x_preferred":[
        "\ub77c\uc2a4\ud1a0\ubcf4\uc12c"
    ],
    "name:lat_x_preferred":[
        "Augusta Insula"
    ],
    "name:mkd_x_preferred":[
        "\u041b\u0430\u0441\u0442\u043e\u0432\u043e"
    ],
    "name:nld_x_preferred":[
        "Lastovo"
    ],
    "name:nno_x_preferred":[
        "Lastovo"
    ],
    "name:nor_x_preferred":[
        "Lastovo"
    ],
    "name:pol_x_preferred":[
        "Lastovo"
    ],
    "name:por_x_preferred":[
        "Lastovo"
    ],
    "name:rus_x_preferred":[
        "\u041b\u0430\u0441\u0442\u043e\u0432\u043e"
    ],
    "name:slk_x_preferred":[
        "Lastovo"
    ],
    "name:slv_x_preferred":[
        "Lastovo"
    ],
    "name:spa_x_preferred":[
        "Lastovo"
    ],
    "name:srp_x_preferred":[
        "\u041b\u0430\u0441\u0442\u043e\u0432\u043e"
    ],
    "name:swe_x_preferred":[
        "Lastovo"
    ],
    "name:tur_x_preferred":[
        "Lastovo"
    ],
    "name:ukr_x_preferred":[
        "\u041b\u0430\u0441\u0442\u043e\u0432\u043e"
    ],
    "name:war_x_preferred":[
        "Lastovo"
    ],
    "name:zho_x_preferred":[
        "\u62c9\u65af\u6258\u6c83\u5cf6"
    ],
    "qs_pg:aaroncc":"HR",
    "qs_pg:gn_country":"HR",
    "qs_pg:gn_fcode":"PPL",
    "qs_pg:gn_pop":0,
    "qs_pg:name":"Lastovo",
    "qs_pg:name_adm0":"Hrvatska",
    "qs_pg:name_adm1":"Dubrova\u010dko-neretvanska",
    "qs_pg:photos":279,
    "qs_pg:photos_1k":57,
    "qs_pg:photos_9k":1,
    "qs_pg:photos_9r":4,
    "qs_pg:photos_all":279,
    "qs_pg:photos_sr":5,
    "qs_pg:pop_sr":3,
    "qs_pg:qs_pg_placetype":"locality",
    "qs_pg:qs_pg_placetype_gp":"Town",
    "qs_pg:woe_adm0":23424843,
    "woe:adm0_id":23424843,
    "woe:name_adm0":"Hrvatska",
    "woe:name_adm1":"Dubrova\u010dko-neretvanska",
    "woe:placetype":"Town",
    "wof:name":"Lastovo",
    "wof:placetype":"locality"
},
  "geometry": {"coordinates":[16.90083,42.76806],"type":"Point"}
}