{
  "type": "Feature",
  "properties": {
    "gn:gn_country":"HR",
    "gn:gn_fcode":"PPL",
    "gn:gn_pop":0,
    "iso:country":"HR",
    "name:unk_x_variant":[
        "Lagosta"
    ],
    "qs_pg:aaroncc":"HR",
    "qs_pg:gn_country":"HR",
    "qs_pg:gn_fcode":"PPL",
    "qs_pg:gn_pop":0,
    "qs_pg:name":"Lastovo",
    "qs_pg:name_adm0":"Hrvatska",
    "qs_pg:name_adm1":"Dubrova\u010dko-neretvanska",
    "qs_pg:photos":279,
    "qs_pg:photos_1k":57,
    "qs_pg:photos_9k":1,
    "qs_pg:photos_9r":4,
    "qs_pg:photos_all":279,
    "qs_pg:photos_sr":5,
    "qs_pg:pop_sr":3,
    "qs_pg:qs_pg_placetype":"locality",
    "qs_pg:qs_pg_placetype_gp":"Town",
    "qs_pg:woe_adm0":23424843,
    "woe:adm0_id":23424843,
    "woe:name_adm0":"Hrvatska",
    "woe:name_adm1":"Dubrova\u010dko-neretvanska",
    "woe:placetype":"Town",
    "wof:name":"Lastovo",
    "wof:placetype":"locality"
},
  "geometry": {"coordinates":[16.90083,42.76806],"type":"Point"}
}