{
  "type": "Feature",
  "properties": {
    "gn:admin1_code":"15.0",
    "gn:asciiname":"Tavre",
    "gn:country_code":"HR",
    "gn:dem":555,
    "gn:feature_class":"P",
    "gn:feature_code":"PPL",
    "gn:name":"Tavre",
    "gn:population":0,
    "gn:timezone":"Europe/Zagreb",
    "iso:country":"HR",
    "wof:name":"Tavre",
    "wof:placetype":"locality"
},
  "geometry": {"coordinates":[17.08778,43.51917],"type":"Point"}
}