{
  "type": "Feature",
  "properties": {
    "gn:admin1_code":"14.0",
    "gn:admin2_code":"3193419.0",
    "gn:asciiname":"Blinja",
    "gn:country_code":"HR",
    "gn:dem":167,
    "gn:feature_class":"P",
    "gn:feature_code":"PPL",
    "gn:name":"Blinja",
    "gn:population":78,
    "gn:timezone":"Europe/Zagreb",
    "iso:country":"HR",
    "name:bos_x_preferred":[
        "Blinja"
    ],
    "name:fra_x_preferred":[
        "Blinja"
    ],
    "name:hrv_x_preferred":[
        "Blinja"
    ],
    "name:hun_x_preferred":[
        "Blinja"
    ],
    "name:slv_x_preferred":[
        "Blinja"
    ],
    "name:spa_x_preferred":[
        "Blinja"
    ],
    "name:srp_x_preferred":[
        "\u0411\u043b\u0438\u045a\u0430"
    ],
    "name:ukr_x_preferred":[
        "\u0411\u043b\u0438\u043d\u044f"
    ],
    "wof:name":"Blinja",
    "wof:placetype":"locality",
    "wof:population":78
},
  "geometry": {"coordinates":[16.37194,45.35694],"type":"Point"}
}