{
  "type": "Feature",
  "properties": {
    "gn:admin1_code":"14.0",
    "gn:asciiname":"Mrdenovici",
    "gn:country_code":"HR",
    "gn:dem":258,
    "gn:feature_class":"P",
    "gn:feature_code":"PPL",
    "gn:name":"Mr\u0111enovi\u0107i",
    "gn:population":0,
    "gn:timezone":"Europe/Zagreb",
    "iso:country":"HR",
    "wof:name":"Mrdenovici",
    "wof:placetype":"locality"
},
  "geometry": {"coordinates":[16.28444,45.04222],"type":"Point"}
}