{
  "type": "Feature",
  "properties": {
    "gn:admin1_code":"10",
    "gn:admin2_code":"11054476.0",
    "gn:asciiname":"Ostrosinci",
    "gn:country_code":"HR",
    "gn:dem":161,
    "gn:feature_class":"P",
    "gn:feature_code":"PPL",
    "gn:name":"Ostro\u0161inci",
    "gn:population":95,
    "gn:timezone":"Europe/Zagreb",
    "iso:country":"HR",
    "wof:name":"Ostrosinci",
    "wof:placetype":"locality",
    "wof:population":95
},
  "geometry": {"coordinates":[18.20528,45.43083],"type":"Point"}
}