{
  "type": "Feature",
  "properties": {
    "gn:admin1_code":"20",
    "gn:admin2_code":"11049002.0",
    "gn:asciiname":"Donja Pusca",
    "gn:country_code":"HR",
    "gn:dem":165,
    "gn:feature_class":"P",
    "gn:feature_code":"PPLA2",
    "gn:name":"Donja Pu\u0161\u0107a",
    "gn:population":0,
    "gn:timezone":"Europe/Zagreb",
    "iso:country":"HR",
    "name:und_x_variant":[
        "Pu\u0161\u0107a",
        "Pu\u0161\u0107a Donja",
        "Donja Pu\u0161\u0107a"
    ],
    "wof:name":"Donja Pusca",
    "wof:placetype":"locality"
},
  "geometry": {"coordinates":[15.77778,45.91667],"type":"Point"}
}