{
  "type": "Feature",
  "properties": {
    "gn:admin1_code":"8.0",
    "gn:asciiname":"Donja Dubrava",
    "gn:country_code":"HR",
    "gn:dem":453,
    "gn:feature_class":"P",
    "gn:feature_code":"PPL",
    "gn:name":"Donja Dubrava",
    "gn:population":0,
    "gn:timezone":"Europe/Zagreb",
    "iso:country":"HR",
    "name:bos_x_preferred":[
        "Donja Dubrava"
    ],
    "name:fra_x_preferred":[
        "Donja Dubrava"
    ],
    "name:hrv_x_preferred":[
        "Donja Dubrava"
    ],
    "name:nld_x_preferred":[
        "Donja Dubrava"
    ],
    "name:pol_x_preferred":[
        "Donja Dubrava"
    ],
    "wof:name":"Donja Dubrava",
    "wof:placetype":"locality"
},
  "geometry": {"coordinates":[15.25278,44.88028],"type":"Point"}
}