{
  "type": "Feature",
  "properties": {
    "gn:admin1_code":"8.0",
    "gn:admin2_code":"11049288.0",
    "gn:asciiname":"Parcici",
    "gn:country_code":"HR",
    "gn:dem":594,
    "gn:feature_class":"P",
    "gn:feature_code":"PPL",
    "gn:name":"Par\u010di\u0107i",
    "gn:population":0,
    "gn:timezone":"Europe/Zagreb",
    "iso:country":"HR",
    "wof:name":"Parcici",
    "wof:placetype":"locality"
},
  "geometry": {"coordinates":[15.66361,44.41278],"type":"Point"}
}