{
  "type": "Feature",
  "properties": {
    "gn:admin1_code":"8.0",
    "gn:asciiname":"Pavlice",
    "gn:country_code":"HR",
    "gn:dem":565,
    "gn:feature_class":"P",
    "gn:feature_code":"PPL",
    "gn:name":"Pavlice",
    "gn:population":0,
    "gn:timezone":"Europe/Zagreb",
    "iso:country":"HR",
    "name:ceb_x_preferred":[
        "Pavlice"
    ],
    "name:deu_x_preferred":[
        "Pavlice"
    ],
    "name:epo_x_preferred":[
        "Pavlice"
    ],
    "name:fra_x_preferred":[
        "Pavlice"
    ],
    "name:ita_x_preferred":[
        "Pavlice"
    ],
    "name:nld_x_preferred":[
        "Pavlice"
    ],
    "name:slk_x_preferred":[
        "Pavlice"
    ],
    "name:srp_x_preferred":[
        "\u041f\u0430\u0432\u043b\u0438\u0446\u0435"
    ],
    "wof:name":"Pavlice",
    "wof:placetype":"locality"
},
  "geometry": {"coordinates":[15.43278,44.46056],"type":"Point"}
}