{
  "type": "Feature",
  "properties": {
    "gn:admin1_code":"14",
    "gn:admin2_code":"3193419.0",
    "gn:asciiname":"Hrastovica",
    "gn:country_code":"HR",
    "gn:dem":146,
    "gn:feature_class":"P",
    "gn:feature_code":"PPL",
    "gn:name":"Hrastovica",
    "gn:population":464,
    "gn:timezone":"Europe/Zagreb",
    "iso:country":"HR",
    "wof:name":"Hrastovica",
    "wof:placetype":"locality",
    "wof:population":464
},
  "geometry": {"coordinates":[16.28722,45.40111],"type":"Point"}
}