{
  "type": "Feature",
  "properties": {
    "gn:admin1_code":"15.0",
    "gn:asciiname":"Gulici",
    "gn:country_code":"HR",
    "gn:dem":507,
    "gn:feature_class":"P",
    "gn:feature_code":"PPL",
    "gn:name":"Guli\u0107i",
    "gn:population":0,
    "gn:timezone":"Europe/Zagreb",
    "iso:country":"HR",
    "wof:name":"Gulici",
    "wof:placetype":"locality"
},
  "geometry": {"coordinates":[16.76611,43.73167],"type":"Point"}
}