{
  "type": "Feature",
  "properties": {
    "gn:admin1_code":"4.0",
    "gn:admin2_code":"11129767.0",
    "gn:asciiname":"Babici",
    "gn:country_code":"HR",
    "gn:dem":39,
    "gn:feature_class":"P",
    "gn:feature_code":"PPL",
    "gn:name":"Babi\u0107i",
    "gn:population":0,
    "gn:timezone":"Europe/Zagreb",
    "iso:country":"HR",
    "name:und_x_variant":[
        "Donji Babi\u0107i"
    ],
    "wof:name":"Babici",
    "wof:placetype":"locality"
},
  "geometry": {"coordinates":[13.55822,45.39143],"type":"Point"}
}