{
  "type": "Feature",
  "properties": {
    "gn:admin1_code":"11",
    "gn:admin2_code":"3193705.0",
    "gn:asciiname":"Ozegovci",
    "gn:country_code":"HR",
    "gn:dem":326,
    "gn:feature_class":"P",
    "gn:feature_code":"PPL",
    "gn:name":"O\u017eegovci",
    "gn:population":0,
    "gn:timezone":"Europe/Zagreb",
    "iso:country":"HR",
    "wof:name":"Ozegovci",
    "wof:placetype":"locality"
},
  "geometry": {"coordinates":[17.38332999999999,45.46667],"type":"Point"}
}