{
  "type": "Feature",
  "properties": {
    "gn:admin1_code":"13",
    "gn:admin2_code":"11054521.0",
    "gn:asciiname":"Bribir",
    "gn:country_code":"HR",
    "gn:dem":218,
    "gn:feature_class":"P",
    "gn:feature_code":"PPL",
    "gn:name":"Bribir",
    "gn:population":103,
    "gn:timezone":"Europe/Zagreb",
    "iso:country":"HR",
    "wof:name":"Bribir",
    "wof:placetype":"locality",
    "wof:population":103
},
  "geometry": {"coordinates":[15.85,43.91667],"type":"Point"}
}