{
  "type": "Feature",
  "properties": {
    "gn:admin1_code":"4.0",
    "gn:admin2_code":"11129784.0",
    "gn:asciiname":"Baldasi",
    "gn:cc2":"HR",
    "gn:country_code":"HR",
    "gn:dem":266,
    "gn:feature_class":"P",
    "gn:feature_code":"PPL",
    "gn:name":"Balda\u0161i",
    "gn:population":28,
    "gn:timezone":"Europe/Zagreb",
    "iso:country":"HR",
    "name:und_x_variant":[
        "Baldassi",
        "Balda\u0161i"
    ],
    "wof:name":"Baldasi",
    "wof:placetype":"locality",
    "wof:population":28
},
  "geometry": {"coordinates":[13.71972,45.31667],"type":"Point"}
}