{
  "type": "Feature",
  "properties": {
    "gn:admin1_code":"14",
    "gn:admin2_code":"3193419.0",
    "gn:asciiname":"Novi Farkasic",
    "gn:cc2":"HR",
    "gn:country_code":"HR",
    "gn:dem":115,
    "gn:feature_class":"P",
    "gn:feature_code":"PPL",
    "gn:name":"Novi Farka\u0161i\u0107",
    "gn:population":81,
    "gn:timezone":"Europe/Zagreb",
    "iso:country":"HR",
    "name:bos_x_preferred":[
        "Novi Farka\u0161i\u0107"
    ],
    "name:fra_x_preferred":[
        "Novi Farka\u0161i\u0107"
    ],
    "name:hrv_x_preferred":[
        "Novi Farka\u0161i\u0107"
    ],
    "name:hun_x_preferred":[
        "Novi Farka\u0161i\u0107"
    ],
    "name:nld_x_preferred":[
        "Novi Farka\u0161i\u0107"
    ],
    "name:slv_x_preferred":[
        "Novi Farka\u0161i\u0107"
    ],
    "name:spa_x_preferred":[
        "Novi Farka\u0161i\u0107"
    ],
    "name:srp_x_preferred":[
        "\u041d\u043e\u0432\u0438 \u0424\u0430\u0440\u043a\u0430\u0448\u0438\u045b"
    ],
    "name:ukr_x_preferred":[
        "\u041d\u043e\u0432\u0438\u0439 \u0424\u0430\u0440\u043a\u0430\u0448\u0438\u0447"
    ],
    "name:und_x_variant":[
        "Novi Farka\u0161i\u0107i"
    ],
    "wof:name":"Novi Farkasic",
    "wof:placetype":"locality",
    "wof:population":81
},
  "geometry": {"coordinates":[16.15351,45.47217],"type":"Point"}
}