{
  "type": "Feature",
  "properties": {
    "gn:admin1_code":"14",
    "gn:admin2_code":"3193419.0",
    "gn:asciiname":"Novi Farkasic",
    "gn:cc2":"HR",
    "gn:country_code":"HR",
    "gn:dem":115,
    "gn:feature_class":"P",
    "gn:feature_code":"PPL",
    "gn:name":"Novi Farka\u0161i\u0107",
    "gn:population":81,
    "gn:timezone":"Europe/Zagreb",
    "iso:country":"HR",
    "name:und_x_variant":[
        "Novi Farka\u0161i\u0107i",
        "Novi Farka\u0161i\u0107"
    ],
    "wof:name":"Novi Farkasic",
    "wof:placetype":"locality",
    "wof:population":81
},
  "geometry": {"coordinates":[16.15351,45.47217],"type":"Point"}
}