{
  "type": "Feature",
  "properties": {
    "gn:admin1_code":"14",
    "gn:admin2_code":"3200915.0",
    "gn:asciiname":"Goricka",
    "gn:country_code":"HR",
    "gn:dem":347,
    "gn:feature_class":"P",
    "gn:feature_code":"PPLL",
    "gn:name":"Gori\u010dka",
    "gn:population":0,
    "gn:timezone":"Europe/Zagreb",
    "iso:country":"HR",
    "wof:name":"Goricka",
    "wof:placetype":"locality"
},
  "geometry": {"coordinates":[16.33444,45.15833],"type":"Point"}
}