{
  "type": "Feature",
  "properties": {
    "gn:admin1_code":"01",
    "gn:admin2_code":"11049415.0",
    "gn:asciiname":"Orlovac",
    "gn:country_code":"HR",
    "gn:dem":119,
    "gn:feature_class":"P",
    "gn:feature_code":"PPL",
    "gn:name":"Orlovac",
    "gn:population":199,
    "gn:timezone":"Europe/Zagreb",
    "iso:country":"HR",
    "wof:name":"Orlovac",
    "wof:placetype":"locality",
    "wof:population":199
},
  "geometry": {"coordinates":[16.9642,45.74584],"type":"Point"}
}