{
  "type": "Feature",
  "properties": {
    "gn:admin1_code":"10",
    "gn:asciiname":"Kucanci",
    "gn:country_code":"HR",
    "gn:dem":94,
    "gn:feature_class":"P",
    "gn:feature_code":"PPL",
    "gn:name":"Ku\u0107anci",
    "gn:population":0,
    "gn:timezone":"Europe/Zagreb",
    "iso:country":"HR",
    "wof:name":"Kucanci",
    "wof:placetype":"locality"
},
  "geometry": {"coordinates":[18.13417,45.65722],"type":"Point"}
}