{
  "type": "Feature",
  "properties": {
    "gn:admin1_code":"09",
    "gn:admin2_code":"11054886.0",
    "gn:asciiname":"Jalsovec",
    "gn:country_code":"HR",
    "gn:dem":185,
    "gn:feature_class":"P",
    "gn:feature_code":"PPL",
    "gn:name":"Jal\u0161ovec",
    "gn:population":144,
    "gn:timezone":"Europe/Zagreb",
    "iso:country":"HR",
    "wof:name":"Jalsovec",
    "wof:placetype":"locality",
    "wof:population":144
},
  "geometry": {"coordinates":[16.31361,46.51444],"type":"Point"}
}