{
  "type": "Feature",
  "properties": {
    "gn:admin1_code":"10",
    "gn:admin2_code":"11054474.0",
    "gn:asciiname":"Novi Bezdan",
    "gn:country_code":"HR",
    "gn:dem":86,
    "gn:feature_class":"P",
    "gn:feature_code":"PPL",
    "gn:name":"Novi Bezdan",
    "gn:population":300,
    "gn:timezone":"Europe/Zagreb",
    "iso:country":"HR",
    "name:bos_x_preferred":[
        "Novi Bezdan"
    ],
    "name:ceb_x_preferred":[
        "Novi Bezdan"
    ],
    "name:epo_x_preferred":[
        "Novi Bezdan"
    ],
    "name:fra_x_preferred":[
        "Novi Bezdan"
    ],
    "name:hrv_x_preferred":[
        "Novi Bezdan"
    ],
    "name:hun_x_preferred":[
        "\u00dajbezd\u00e1n"
    ],
    "name:slv_x_preferred":[
        "Novi Bezdan"
    ],
    "name:srp_x_preferred":[
        "\u041d\u043e\u0432\u0438 \u0411\u0435\u0437\u0434\u0430\u043d"
    ],
    "name:swe_x_preferred":[
        "Novi Bezdan"
    ],
    "name:ukr_x_preferred":[
        "\u041d\u043e\u0432\u0438\u0439 \u0411\u0435\u0437\u0434\u0430\u043d"
    ],
    "wof:name":"Novi Bezdan",
    "wof:placetype":"locality",
    "wof:population":300
},
  "geometry": {"coordinates":[18.46472,45.73778],"type":"Point"}
}