{
  "type": "Feature",
  "properties": {
    "gn:admin1_code":"14.0",
    "gn:asciiname":"Maljkovici",
    "gn:country_code":"HR",
    "gn:dem":307,
    "gn:feature_class":"P",
    "gn:feature_code":"PPL",
    "gn:name":"Maljkovi\u0107i",
    "gn:population":0,
    "gn:timezone":"Europe/Zagreb",
    "iso:country":"HR",
    "wof:name":"Maljkovici",
    "wof:placetype":"locality"
},
  "geometry": {"coordinates":[16.28806,45.16056],"type":"Point"}
}