{
  "type": "Feature",
  "properties": {
    "gn:admin1_code":"4.0",
    "gn:asciiname":"Veli Vrh",
    "gn:country_code":"HR",
    "gn:dem":40,
    "gn:feature_class":"P",
    "gn:feature_code":"PPL",
    "gn:name":"Veli Vrh",
    "gn:population":0,
    "gn:timezone":"Europe/Zagreb",
    "iso:country":"HR",
    "wof:name":"Veli Vrh",
    "wof:placetype":"locality"
},
  "geometry": {"coordinates":[13.85028,44.8925],"type":"Point"}
}