{
  "type": "Feature",
  "properties": {
    "gn:admin1_code":"04",
    "gn:admin2_code":"11054821.0",
    "gn:asciiname":"Kringa",
    "gn:cc2":"HR",
    "gn:country_code":"HR",
    "gn:dem":290,
    "gn:feature_class":"P",
    "gn:feature_code":"PPL",
    "gn:name":"Kringa",
    "gn:population":315,
    "gn:timezone":"Europe/Zagreb",
    "iso:country":"HR",
    "name:bos_x_preferred":[
        "Kringa"
    ],
    "name:ceb_x_preferred":[
        "Kringa"
    ],
    "name:fra_x_preferred":[
        "Kringa"
    ],
    "name:hrv_x_preferred":[
        "Kringa"
    ],
    "name:hun_x_preferred":[
        "Kringa"
    ],
    "name:nld_x_preferred":[
        "Kringa"
    ],
    "name:slv_x_preferred":[
        "Kringa"
    ],
    "name:spa_x_preferred":[
        "Kringa"
    ],
    "name:srp_x_preferred":[
        "\u041a\u0440\u0438\u043d\u0433\u0430"
    ],
    "name:ukr_x_preferred":[
        "\u041a\u0440\u0438\u043d\u0433\u0430"
    ],
    "name:und_x_variant":[
        "Corr\u00eddico",
        "Kringa"
    ],
    "wof:name":"Kringa",
    "wof:placetype":"locality",
    "wof:population":315
},
  "geometry": {"coordinates":[13.83333,45.18222],"type":"Point"}
}