{
  "type": "Feature",
  "properties": {
    "gn:asciiname":"Sveti Juraj na Bregu",
    "gn:country_code":"HR",
    "gn:dem":224,
    "gn:feature_class":"P",
    "gn:feature_code":"PPL",
    "gn:name":"Sveti Juraj na Bregu",
    "gn:population":0,
    "gn:timezone":"Europe/Zagreb",
    "iso:country":"HR",
    "wof:name":"Sveti Juraj na Bregu",
    "wof:placetype":"locality"
},
  "geometry": {"coordinates":[16.38497000000001,46.43135],"type":"Point"}
}