{
  "type": "Feature",
  "properties": {
    "gn:asciiname":"Sveti Juraj na Bregu",
    "gn:country_code":"HR",
    "gn:dem":224,
    "gn:feature_class":"P",
    "gn:feature_code":"PPL",
    "gn:name":"Sveti Juraj na Bregu",
    "gn:population":0,
    "gn:timezone":"Europe/Zagreb",
    "iso:country":"HR",
    "name:bos_x_preferred":[
        "Sveti Juraj na Bregu"
    ],
    "name:epo_x_preferred":[
        "Sveti Juraj na Bregu"
    ],
    "name:fra_x_preferred":[
        "Sveti Juraj na Bregu"
    ],
    "name:hrv_x_preferred":[
        "Sveti Juraj na Bregu"
    ],
    "name:ita_x_preferred":[
        "Sveti Juraj na Bregu"
    ],
    "name:nld_x_preferred":[
        "Sveti Juraj na Bregu"
    ],
    "name:pol_x_preferred":[
        "Gmina Sveti Juraj na Bregu"
    ],
    "name:ron_x_preferred":[
        "Comuna Sveti Juraj na Bregu"
    ],
    "name:srp_x_preferred":[
        "\u0421\u0432\u0435\u0442\u0438 \u0408\u0443\u0440\u0430\u0458 \u043d\u0430 \u0411\u0440\u0435\u0433\u0443"
    ],
    "name:ukr_x_preferred":[
        "\u0421\u0432\u0435\u0442\u0438\u0439 \u042e\u0440\u0430\u0439-\u043d\u0430-\u0411\u0440\u0435\u0433\u0443"
    ],
    "name:war_x_preferred":[
        "Sveti Juraj na Bregu"
    ],
    "wof:name":"Sveti Juraj na Bregu",
    "wof:placetype":"locality"
},
  "geometry": {"coordinates":[16.38497000000001,46.43135],"type":"Point"}
}