{
  "type": "Feature",
  "properties": {
    "gn:admin1_code":"11",
    "gn:admin2_code":"11049472.0",
    "gn:asciiname":"Kamenski Vucjak",
    "gn:cc2":"HR",
    "gn:country_code":"HR",
    "gn:dem":313,
    "gn:feature_class":"P",
    "gn:feature_code":"PPL",
    "gn:name":"Kamenski Vu\u010djak",
    "gn:population":6,
    "gn:timezone":"Europe/Zagreb",
    "iso:country":"HR",
    "name:und_x_variant":[
        "Vu\u010djak Kamenski",
        "Kamenski Vu\u010djak"
    ],
    "wof:name":"Kamenski Vucjak",
    "wof:placetype":"locality",
    "wof:population":6
},
  "geometry": {"coordinates":[17.53278,45.49139],"type":"Point"}
}