{
  "type": "Feature",
  "properties": {
    "gn:admin1_code":"05",
    "gn:admin2_code":"11049266.0",
    "gn:asciiname":"Podvozic",
    "gn:country_code":"HR",
    "gn:dem":153,
    "gn:feature_class":"P",
    "gn:feature_code":"PPL",
    "gn:name":"Podvo\u017ei\u0107",
    "gn:population":298,
    "gn:timezone":"Europe/Zagreb",
    "iso:country":"HR",
    "wof:name":"Podvozic",
    "wof:placetype":"locality",
    "wof:population":298
},
  "geometry": {"coordinates":[15.55,45.41667],"type":"Point"}
}