{
  "type": "Feature",
  "properties": {
    "gn:admin1_code":"8.0",
    "gn:asciiname":"Bastasko Selo",
    "gn:country_code":"HR",
    "gn:dem":503,
    "gn:feature_class":"P",
    "gn:feature_code":"PPL",
    "gn:name":"Basta\u0161ko Selo",
    "gn:population":0,
    "gn:timezone":"Europe/Zagreb",
    "iso:country":"HR",
    "wof:name":"Bastasko Selo",
    "wof:placetype":"locality"
},
  "geometry": {"coordinates":[15.21639,44.75111],"type":"Point"}
}