{
  "type": "Feature",
  "properties": {
    "gn:admin1_code":"19.0",
    "gn:asciiname":"Lakic",
    "gn:country_code":"HR",
    "gn:dem":177,
    "gn:feature_class":"P",
    "gn:feature_code":"PPL",
    "gn:name":"Laki\u0107",
    "gn:population":0,
    "gn:timezone":"Europe/Zagreb",
    "iso:country":"HR",
    "wof:name":"Lakic",
    "wof:placetype":"locality"
},
  "geometry": {"coordinates":[15.47361,44.11111],"type":"Point"}
}