{
  "type": "Feature",
  "properties": {
    "gn:admin1_code":"8.0",
    "gn:asciiname":"Diklici",
    "gn:country_code":"HR",
    "gn:dem":509,
    "gn:feature_class":"P",
    "gn:feature_code":"PPL",
    "gn:name":"Dikli\u0107i",
    "gn:population":0,
    "gn:timezone":"Europe/Zagreb",
    "iso:country":"HR",
    "wof:name":"Diklici",
    "wof:placetype":"locality"
},
  "geometry": {"coordinates":[15.315,44.87611],"type":"Point"}
}