{
  "type": "Feature",
  "properties": {
    "gn:admin1_code":"10.0",
    "gn:asciiname":"Bukovac",
    "gn:country_code":"HR",
    "gn:dem":237,
    "gn:feature_class":"P",
    "gn:feature_code":"PPL",
    "gn:name":"Bukovac",
    "gn:population":0,
    "gn:timezone":"Europe/Zagreb",
    "iso:country":"HR",
    "wof:name":"Bukovac",
    "wof:placetype":"locality"
},
  "geometry": {"coordinates":[18.0375,45.40972],"type":"Point"}
}