{
  "type": "Feature",
  "properties": {
    "gn:admin1_code":"10.0",
    "gn:asciiname":"Bukovac",
    "gn:country_code":"HR",
    "gn:dem":237,
    "gn:feature_class":"P",
    "gn:feature_code":"PPL",
    "gn:name":"Bukovac",
    "gn:population":0,
    "gn:timezone":"Europe/Zagreb",
    "iso:country":"HR",
    "name:bos_x_preferred":[
        "Bukovac"
    ],
    "name:ceb_x_preferred":[
        "Bukovac"
    ],
    "name:deu_x_preferred":[
        "Bukovac"
    ],
    "name:fra_x_preferred":[
        "Bukovac"
    ],
    "name:hrv_x_preferred":[
        "Bukovac"
    ],
    "name:slv_x_preferred":[
        "Bukovac"
    ],
    "name:srp_x_preferred":[
        "\u0411\u0443\u043a\u043e\u0432\u0430\u0446"
    ],
    "name:swe_x_preferred":[
        "Bukovac"
    ],
    "name:ukr_x_preferred":[
        "\u0411\u0443\u043a\u043e\u0432\u0430\u0446"
    ],
    "wof:name":"Bukovac",
    "wof:placetype":"locality"
},
  "geometry": {"coordinates":[18.0375,45.40972],"type":"Point"}
}