{
  "type": "Feature",
  "properties": {
    "gn:admin1_code":"20",
    "gn:admin2_code":"3188243.0",
    "gn:asciiname":"Siljakovina",
    "gn:country_code":"HR",
    "gn:dem":152,
    "gn:feature_class":"P",
    "gn:feature_code":"PPL",
    "gn:name":"\u0160iljakovina",
    "gn:population":672,
    "gn:timezone":"Europe/Zagreb",
    "iso:country":"HR",
    "wof:name":"Siljakovina",
    "wof:placetype":"locality",
    "wof:population":672
},
  "geometry": {"coordinates":[16.01667,45.63333],"type":"Point"}
}