{
  "type": "Feature",
  "properties": {
    "gn:admin1_code":"8.0",
    "gn:asciiname":"Marjani",
    "gn:country_code":"HR",
    "gn:dem":467,
    "gn:feature_class":"P",
    "gn:feature_code":"PPL",
    "gn:name":"Marjani",
    "gn:population":0,
    "gn:timezone":"Europe/Zagreb",
    "iso:country":"HR",
    "wof:name":"Marjani",
    "wof:placetype":"locality"
},
  "geometry": {"coordinates":[15.27694,44.87361],"type":"Point"}
}