{
  "type": "Feature",
  "properties": {
    "gn:gn_country":"HR",
    "gn:gn_fcode":"PPL",
    "gn:gn_pop":0,
    "gn:population":177,
    "iso:country":"HR",
    "name:bos_x_preferred":[
        "Medveja"
    ],
    "name:ceb_x_preferred":[
        "Medveja"
    ],
    "name:eng_x_preferred":[
        "Medveja"
    ],
    "name:fra_x_preferred":[
        "Medveja"
    ],
    "name:hrv_x_preferred":[
        "Medveja"
    ],
    "name:hun_x_preferred":[
        "Medveja"
    ],
    "name:nld_x_preferred":[
        "Medveja"
    ],
    "name:slv_x_preferred":[
        "Medveja"
    ],
    "name:spa_x_preferred":[
        "Medveja"
    ],
    "name:srp_x_preferred":[
        "\u041c\u0435\u0434\u0432\u0435\u0458\u0430"
    ],
    "name:swe_x_preferred":[
        "Medveja"
    ],
    "name:ukr_x_preferred":[
        "\u041c\u0435\u0434\u0432\u0435\u044f"
    ],
    "name:unk_x_variant":[
        "Medea"
    ],
    "qs_pg:aaroncc":"HR",
    "qs_pg:gn_country":"HR",
    "qs_pg:gn_fcode":"PPL",
    "qs_pg:gn_pop":0,
    "qs_pg:name":"Medveja",
    "qs_pg:name_adm0":"Hrvatska",
    "qs_pg:name_adm1":"Primorsko-Goranska",
    "qs_pg:photos":79,
    "qs_pg:photos_1k":16,
    "qs_pg:photos_9k":1,
    "qs_pg:photos_9r":3,
    "qs_pg:photos_all":79,
    "qs_pg:photos_sr":3,
    "qs_pg:pop_sr":0,
    "qs_pg:qs_pg_placetype":"locality",
    "qs_pg:qs_pg_placetype_gp":"Town",
    "qs_pg:woe_adm0":23424843,
    "woe:adm0_id":23424843,
    "woe:name_adm0":"Hrvatska",
    "woe:name_adm1":"Primorsko-Goranska",
    "woe:placetype":"Town",
    "wof:name":"Medveja",
    "wof:placetype":"locality",
    "wof:population":177
},
  "geometry": {"coordinates":[14.26667,45.26833],"type":"Point"}
}