{
  "type": "Feature",
  "properties": {
    "gn:admin1_code":"10.0",
    "gn:admin2_code":"11054469.0",
    "gn:asciiname":"Zlatna Greda",
    "gn:country_code":"HR",
    "gn:dem":79,
    "gn:feature_class":"P",
    "gn:feature_code":"PPL",
    "gn:name":"Zlatna Greda",
    "gn:population":5,
    "gn:timezone":"Europe/Zagreb",
    "iso:country":"HR",
    "name:bos_x_preferred":[
        "Zlatna Greda"
    ],
    "name:epo_x_preferred":[
        "Zlatna Greda"
    ],
    "name:fra_x_preferred":[
        "Zlatna Greda"
    ],
    "name:hrv_x_preferred":[
        "Zlatna Greda"
    ],
    "name:slv_x_preferred":[
        "Zlatna Greda"
    ],
    "name:ukr_x_preferred":[
        "\u0417\u043b\u0430\u0442\u043d\u0430 \u0413\u0440\u0435\u0434\u0430"
    ],
    "wof:name":"Zlatna Greda",
    "wof:placetype":"locality",
    "wof:population":5
},
  "geometry": {"coordinates":[18.86556,45.72167],"type":"Point"}
}