{
  "type": "Feature",
  "properties": {
    "gn:admin1_code":"08",
    "gn:admin2_code":"11049288.0",
    "gn:asciiname":"Ricice",
    "gn:country_code":"HR",
    "gn:dem":572,
    "gn:feature_class":"P",
    "gn:feature_code":"PPL",
    "gn:name":"Ri\u010dice",
    "gn:population":76,
    "gn:timezone":"Europe/Zagreb",
    "iso:country":"HR",
    "wof:name":"Ricice",
    "wof:placetype":"locality",
    "wof:population":76
},
  "geometry": {"coordinates":[15.74194,44.33778],"type":"Point"}
}