{
  "type": "Feature",
  "properties": {
    "gn:admin1_code":"8.0",
    "gn:asciiname":"Pavelici",
    "gn:country_code":"HR",
    "gn:dem":572,
    "gn:feature_class":"P",
    "gn:feature_code":"PPL",
    "gn:name":"Paveli\u0107i",
    "gn:population":0,
    "gn:timezone":"Europe/Zagreb",
    "iso:country":"HR",
    "wof:name":"Pavelici",
    "wof:placetype":"locality"
},
  "geometry": {"coordinates":[15.30306,44.53722],"type":"Point"}
}