{
  "type": "Feature",
  "properties": {
    "gn:admin1_code":"3.0",
    "gn:admin2_code":"11054963.0",
    "gn:asciiname":"Duba",
    "gn:country_code":"HR",
    "gn:dem":73,
    "gn:feature_class":"P",
    "gn:feature_code":"PPL",
    "gn:name":"Duba",
    "gn:population":0,
    "gn:timezone":"Europe/Zagreb",
    "iso:country":"HR",
    "name:bos_x_preferred":[
        "Duba"
    ],
    "name:ceb_x_preferred":[
        "Duba"
    ],
    "name:ces_x_preferred":[
        "Duba"
    ],
    "name:deu_x_preferred":[
        "Duba"
    ],
    "name:fra_x_preferred":[
        "Duba"
    ],
    "name:hrv_x_preferred":[
        "Duba"
    ],
    "name:hun_x_preferred":[
        "Duba"
    ],
    "name:jpn_x_preferred":[
        "\u30c9\u30a5\u30d0"
    ],
    "name:nld_x_preferred":[
        "Duba"
    ],
    "name:pol_x_preferred":[
        "Duba"
    ],
    "name:rus_x_preferred":[
        "\u0414\u0443\u0431\u0430"
    ],
    "name:slv_x_preferred":[
        "Duba"
    ],
    "name:srp_x_preferred":[
        "\u0414\u0443\u0431\u0430"
    ],
    "name:swe_x_preferred":[
        "Duba"
    ],
    "name:ukr_x_preferred":[
        "\u0414\u0443\u0431\u0430"
    ],
    "wof:name":"Duba",
    "wof:placetype":"locality"
},
  "geometry": {"coordinates":[17.495,42.97806],"type":"Point"}
}