{
  "type": "Feature",
  "properties": {
    "gn:admin1_code":"15.0",
    "gn:asciiname":"Krusevac",
    "gn:country_code":"HR",
    "gn:dem":687,
    "gn:feature_class":"P",
    "gn:feature_code":"PPL",
    "gn:name":"Kru\u0161evac",
    "gn:population":0,
    "gn:timezone":"Europe/Zagreb",
    "iso:country":"HR",
    "wof:name":"Krusevac",
    "wof:placetype":"locality"
},
  "geometry": {"coordinates":[17.10806,43.37611],"type":"Point"}
}