{
  "type": "Feature",
  "properties": {
    "gn:admin1_code":"11",
    "gn:admin2_code":"3193705.0",
    "gn:asciiname":"Kricke Zabrdske",
    "gn:cc2":"HR",
    "gn:country_code":"HR",
    "gn:dem":339,
    "gn:feature_class":"P",
    "gn:feature_code":"PPL",
    "gn:name":"Kri\u010dke Zabrdske",
    "gn:population":0,
    "gn:timezone":"Europe/Zagreb",
    "iso:country":"HR",
    "name:und_x_variant":[
        "Zabrdske Kri\u010dke",
        "Kri\u010dke Zabrdski",
        "Kri\u010dke",
        "Kri\u010dke Zabrdske"
    ],
    "wof:name":"Kricke Zabrdske",
    "wof:placetype":"locality"
},
  "geometry": {"coordinates":[17.35,45.45],"type":"Point"}
}