{
  "type": "Feature",
  "properties": {
    "gn:admin1_code":"15.0",
    "gn:asciiname":"Klarici",
    "gn:country_code":"HR",
    "gn:dem":378,
    "gn:feature_class":"P",
    "gn:feature_code":"PPL",
    "gn:name":"Klari\u0107i",
    "gn:population":0,
    "gn:timezone":"Europe/Zagreb",
    "iso:country":"HR",
    "wof:name":"Klarici",
    "wof:placetype":"locality"
},
  "geometry": {"coordinates":[16.62972,43.70556],"type":"Point"}
}