{
  "type": "Feature",
  "properties": {
    "gn:admin1_code":"07",
    "gn:admin2_code":"11049010.0",
    "gn:asciiname":"Sagudovec",
    "gn:cc2":"HR",
    "gn:country_code":"HR",
    "gn:dem":318,
    "gn:feature_class":"P",
    "gn:feature_code":"PPL",
    "gn:name":"\u0160agudovec",
    "gn:population":195,
    "gn:timezone":"Europe/Zagreb",
    "iso:country":"HR",
    "name:und_x_variant":[
        "Sudovec",
        "\u0160agudovec"
    ],
    "wof:name":"Sagudovec",
    "wof:placetype":"locality",
    "wof:population":195
},
  "geometry": {"coordinates":[16.06811,45.99195],"type":"Point"}
}