{
  "type": "Feature",
  "properties": {
    "gn:admin1_code":"14",
    "gn:admin2_code":"3200915.0",
    "gn:asciiname":"Uncani",
    "gn:country_code":"HR",
    "gn:dem":130,
    "gn:feature_class":"P",
    "gn:feature_code":"PPL",
    "gn:name":"Un\u010dani",
    "gn:population":189,
    "gn:timezone":"Europe/Zagreb",
    "iso:country":"HR",
    "name:und_x_variant":[
        "Un\u010dani"
    ],
    "wof:name":"Uncani",
    "wof:placetype":"locality",
    "wof:population":189
},
  "geometry": {"coordinates":[16.41028,45.12833],"type":"Point"}
}