{
  "type": "Feature",
  "properties": {
    "gn:admin1_code":"14",
    "gn:admin2_code":"3200915.0",
    "gn:asciiname":"Uncani",
    "gn:country_code":"HR",
    "gn:dem":130,
    "gn:feature_class":"P",
    "gn:feature_code":"PPL",
    "gn:name":"Un\u010dani",
    "gn:population":189,
    "gn:timezone":"Europe/Zagreb",
    "iso:country":"HR",
    "name:bos_x_preferred":[
        "Un\u010dani"
    ],
    "name:ceb_x_preferred":[
        "Un\u010dani"
    ],
    "name:hrv_x_preferred":[
        "Un\u010dani"
    ],
    "name:hun_x_preferred":[
        "Un\u010dani"
    ],
    "name:nld_x_preferred":[
        "Un\u010dani"
    ],
    "name:slv_x_preferred":[
        "Un\u010dani"
    ],
    "name:spa_x_preferred":[
        "Un\u010dani"
    ],
    "name:srp_x_preferred":[
        "\u0423\u043d\u0447\u0430\u043d\u0438"
    ],
    "name:swe_x_preferred":[
        "Un\u010dani"
    ],
    "name:ukr_x_preferred":[
        "\u0423\u043d\u0447\u0430\u043d\u0438"
    ],
    "name:und_x_variant":[
        "Un\u010dani"
    ],
    "wof:name":"Uncani",
    "wof:placetype":"locality",
    "wof:population":189
},
  "geometry": {"coordinates":[16.41028,45.12833],"type":"Point"}
}