{
  "type": "Feature",
  "properties": {
    "gn:admin1_code":"5.0",
    "gn:asciiname":"Orlovac",
    "gn:country_code":"HR",
    "gn:dem":112,
    "gn:feature_class":"P",
    "gn:feature_code":"PPL",
    "gn:name":"Orlovac",
    "gn:population":0,
    "gn:timezone":"Europe/Zagreb",
    "iso:country":"HR",
    "name:bul_x_preferred":[
        "\u041e\u0440\u043b\u043e\u0432\u0430\u0446"
    ],
    "name:fra_x_preferred":[
        "Orlovac"
    ],
    "name:msa_x_preferred":[
        "Orlovac"
    ],
    "name:nld_x_preferred":[
        "Orlovac"
    ],
    "name:por_x_preferred":[
        "Orlovac"
    ],
    "name:slv_x_preferred":[
        "Orlovac"
    ],
    "name:srp_x_preferred":[
        "\u041e\u0440\u043b\u043e\u0432\u0430\u0446"
    ],
    "wof:name":"Orlovac",
    "wof:placetype":"locality"
},
  "geometry": {"coordinates":[15.58167,45.52528],"type":"Point"}
}