{
  "type": "Feature",
  "properties": {
    "gn:admin1_code":"15.0",
    "gn:asciiname":"Ozici",
    "gn:country_code":"HR",
    "gn:dem":348,
    "gn:feature_class":"P",
    "gn:feature_code":"PPL",
    "gn:name":"O\u017ei\u0107i",
    "gn:population":0,
    "gn:timezone":"Europe/Zagreb",
    "iso:country":"HR",
    "wof:name":"Ozici",
    "wof:placetype":"locality"
},
  "geometry": {"coordinates":[17.17111,43.30444],"type":"Point"}
}