{
  "type": "Feature",
  "properties": {
    "gn:admin1_code":"8.0",
    "gn:asciiname":"Buzak",
    "gn:country_code":"HR",
    "gn:dem":530,
    "gn:feature_class":"P",
    "gn:feature_code":"PPL",
    "gn:name":"Bu\u017eak",
    "gn:population":0,
    "gn:timezone":"Europe/Zagreb",
    "iso:country":"HR",
    "wof:name":"Buzak",
    "wof:placetype":"locality"
},
  "geometry": {"coordinates":[15.31278,44.945],"type":"Point"}
}