{
  "type": "Feature",
  "properties": {
    "gn:admin1_code":"8.0",
    "gn:asciiname":"Starcevici",
    "gn:country_code":"HR",
    "gn:dem":671,
    "gn:feature_class":"P",
    "gn:feature_code":"PPL",
    "gn:name":"Star\u010devi\u0107i",
    "gn:population":0,
    "gn:timezone":"Europe/Zagreb",
    "iso:country":"HR",
    "wof:name":"Starcevici",
    "wof:placetype":"locality"
},
  "geometry": {"coordinates":[15.14444,44.66667],"type":"Point"}
}