{
  "type": "Feature",
  "properties": {
    "gn:admin1_code":"20",
    "gn:admin2_code":"3199068.0",
    "gn:asciiname":"Graberje Ivanicko",
    "gn:cc2":"HR",
    "gn:country_code":"HR",
    "gn:dem":117,
    "gn:feature_class":"P",
    "gn:feature_code":"PPL",
    "gn:name":"Graberje Ivani\u0107ko",
    "gn:population":0,
    "gn:timezone":"Europe/Zagreb",
    "iso:country":"HR",
    "name:und_x_variant":[
        "Ivani\u010dko Graberje",
        "Graberje",
        "Graberje Ivani\u0107ko"
    ],
    "wof:name":"Graberje Ivanicko",
    "wof:placetype":"locality"
},
  "geometry": {"coordinates":[16.47383,45.7099],"type":"Point"}
}