{
  "type": "Feature",
  "properties": {
    "gn:admin1_code":"12.0",
    "gn:admin2_code":"3202102.0",
    "gn:asciiname":"Lucice",
    "gn:country_code":"HR",
    "gn:dem":711,
    "gn:feature_class":"P",
    "gn:feature_code":"PPL",
    "gn:name":"Lu\u010dice",
    "gn:population":332,
    "gn:timezone":"Europe/Zagreb",
    "iso:country":"HR",
    "wof:name":"Lucice",
    "wof:placetype":"locality",
    "wof:population":332
},
  "geometry": {"coordinates":[14.79583,45.375],"type":"Point"}
}