{
  "type": "Feature",
  "properties": {
    "gn:admin1_code":"14",
    "gn:admin2_code":"3200597.0",
    "gn:asciiname":"Gornja Bucica",
    "gn:cc2":"HR",
    "gn:country_code":"HR",
    "gn:dem":177,
    "gn:feature_class":"P",
    "gn:feature_code":"PPL",
    "gn:name":"Gornja Bu\u010dica",
    "gn:population":128,
    "gn:timezone":"Europe/Zagreb",
    "iso:country":"HR",
    "name:und_x_variant":[
        "Bu\u010dica",
        "Bu\u010di\u010dka",
        "Gornja Bu\u010dica"
    ],
    "wof:name":"Gornja Bucica",
    "wof:placetype":"locality",
    "wof:population":128
},
  "geometry": {"coordinates":[15.98333,45.46667],"type":"Point"}
}