{
  "type": "Feature",
  "properties": {
    "gn:admin1_code":"03",
    "gn:admin2_code":"7577034.0",
    "gn:asciiname":"Prijevor",
    "gn:cc2":"HR",
    "gn:country_code":"HR",
    "gn:dem":18,
    "gn:feature_class":"P",
    "gn:feature_code":"PPL",
    "gn:name":"Prijevor",
    "gn:population":453,
    "gn:timezone":"Europe/Zagreb",
    "iso:country":"HR",
    "name:und_x_variant":[
        "Prijevop",
        "Prijevor"
    ],
    "wof:name":"Prijevor",
    "wof:placetype":"locality",
    "wof:population":453
},
  "geometry": {"coordinates":[18.12389,42.67306],"type":"Point"}
}