{
  "type": "Feature",
  "properties": {
    "gn:admin1_code":"03",
    "gn:admin2_code":"7577034.0",
    "gn:asciiname":"Prijevor",
    "gn:cc2":"HR",
    "gn:country_code":"HR",
    "gn:dem":18,
    "gn:feature_class":"P",
    "gn:feature_code":"PPL",
    "gn:name":"Prijevor",
    "gn:population":453,
    "gn:timezone":"Europe/Zagreb",
    "iso:country":"HR",
    "name:bos_x_preferred":[
        "Prijevor"
    ],
    "name:ceb_x_preferred":[
        "Prijevor"
    ],
    "name:fra_x_preferred":[
        "Prijevor"
    ],
    "name:hrv_x_preferred":[
        "Prijevor"
    ],
    "name:hun_x_preferred":[
        "Prijevor"
    ],
    "name:rus_x_preferred":[
        "\u041f\u0440\u0438\u0435\u0432\u043e\u0440"
    ],
    "name:slv_x_preferred":[
        "Prijevor"
    ],
    "name:srp_x_preferred":[
        "\u041f\u0440\u0438\u0458\u0435\u0432\u043e\u0440"
    ],
    "name:swe_x_preferred":[
        "Prijevor"
    ],
    "name:und_x_variant":[
        "Prijevop"
    ],
    "wof:name":"Prijevor",
    "wof:placetype":"locality",
    "wof:population":453
},
  "geometry": {"coordinates":[18.12389,42.67306],"type":"Point"}
}