{
  "type": "Feature",
  "properties": {
    "gn:admin1_code":"15.0",
    "gn:asciiname":"Kutlese",
    "gn:country_code":"HR",
    "gn:dem":335,
    "gn:feature_class":"P",
    "gn:feature_code":"PPL",
    "gn:name":"Kutle\u0161e",
    "gn:population":0,
    "gn:timezone":"Europe/Zagreb",
    "iso:country":"HR",
    "wof:name":"Kutlese",
    "wof:placetype":"locality"
},
  "geometry": {"coordinates":[16.72194,43.57806],"type":"Point"}
}