{
  "type": "Feature",
  "properties": {
    "gn:admin1_code":"5.0",
    "gn:asciiname":"Matijevici",
    "gn:country_code":"HR",
    "gn:dem":227,
    "gn:feature_class":"P",
    "gn:feature_code":"PPL",
    "gn:name":"Matijevi\u0107i",
    "gn:population":0,
    "gn:timezone":"Europe/Zagreb",
    "iso:country":"HR",
    "wof:name":"Matijevici",
    "wof:placetype":"locality"
},
  "geometry": {"coordinates":[15.64167,45.26528],"type":"Point"}
}