{
  "type": "Feature",
  "properties": {
    "gn:admin1_code":"15",
    "gn:admin2_code":"11054614.0",
    "gn:asciiname":"Donji Muc",
    "gn:cc2":"HR",
    "gn:country_code":"HR",
    "gn:dem":451,
    "gn:feature_class":"P",
    "gn:feature_code":"PPLL",
    "gn:name":"Donji Mu\u0107",
    "gn:population":0,
    "gn:timezone":"Europe/Zagreb",
    "iso:country":"HR",
    "name:und_x_variant":[
        "Mu\u0107 Donji",
        "Mu\u0107 Dolnji",
        "Donji Mu\u0107"
    ],
    "wof:name":"Donji Muc",
    "wof:placetype":"locality"
},
  "geometry": {"coordinates":[16.46224,43.69444],"type":"Point"}
}