{
  "type": "Feature",
  "properties": {
    "gn:admin1_code":"5.0",
    "gn:asciiname":"Jelov Klanac",
    "gn:country_code":"HR",
    "gn:dem":389,
    "gn:feature_class":"P",
    "gn:feature_code":"PPLL",
    "gn:name":"Jelov Klanac",
    "gn:population":0,
    "gn:timezone":"Europe/Zagreb",
    "iso:country":"HR",
    "wof:name":"Jelov Klanac",
    "wof:placetype":"locality"
},
  "geometry": {"coordinates":[15.6025,45.00306],"type":"Point"}
}