{
  "type": "Feature",
  "properties": {
    "gn:admin1_code":"06",
    "gn:admin2_code":"11049393.0",
    "gn:asciiname":"Markovac Krizevacki",
    "gn:cc2":"HR",
    "gn:country_code":"HR",
    "gn:dem":135,
    "gn:feature_class":"P",
    "gn:feature_code":"PPL",
    "gn:name":"Markovac Kri\u017eeva\u010dki",
    "gn:population":147,
    "gn:timezone":"Europe/Zagreb",
    "iso:country":"HR",
    "name:und_x_variant":[
        "Kri\u017eeva\u010dki Markovac",
        "Markovac",
        "Markovac Kri\u017eeva\u010dki"
    ],
    "wof:name":"Markovac Krizevacki",
    "wof:placetype":"locality",
    "wof:population":147
},
  "geometry": {"coordinates":[16.69106,45.95014000000001],"type":"Point"}
}