{
  "type": "Feature",
  "properties": {
    "gn:admin1_code":"06",
    "gn:admin2_code":"11049393.0",
    "gn:asciiname":"Markovac Krizevacki",
    "gn:cc2":"HR",
    "gn:country_code":"HR",
    "gn:dem":135,
    "gn:feature_class":"P",
    "gn:feature_code":"PPL",
    "gn:name":"Markovac Kri\u017eeva\u010dki",
    "gn:population":147,
    "gn:timezone":"Europe/Zagreb",
    "iso:country":"HR",
    "name:bos_x_preferred":[
        "Markovac Kri\u017eeva\u010dki"
    ],
    "name:hrv_x_preferred":[
        "Markovac Kri\u017eeva\u010dki"
    ],
    "name:hun_x_preferred":[
        "Markovac Kri\u017eeva\u010dki"
    ],
    "name:slv_x_preferred":[
        "Markovac Kri\u017eeva\u010dki"
    ],
    "name:spa_x_preferred":[
        "Markovac Kri\u017eeva\u010dki"
    ],
    "name:ukr_x_preferred":[
        "\u041c\u0430\u0440\u043a\u043e\u0432\u0430\u0446\u044c-\u041a\u0440\u0438\u0436\u0435\u0432\u0430\u0446\u044c\u043a\u0438\u0439"
    ],
    "name:und_x_variant":[
        "Kri\u017eeva\u010dki Markovac",
        "Markovac"
    ],
    "wof:name":"Markovac Krizevacki",
    "wof:placetype":"locality",
    "wof:population":147
},
  "geometry": {"coordinates":[16.69106,45.95014000000001],"type":"Point"}
}