{
  "type": "Feature",
  "properties": {
    "gn:admin1_code":"8.0",
    "gn:asciiname":"Lug",
    "gn:country_code":"HR",
    "gn:dem":456,
    "gn:feature_class":"P",
    "gn:feature_code":"PPL",
    "gn:name":"Lug",
    "gn:population":0,
    "gn:timezone":"Europe/Zagreb",
    "iso:country":"HR",
    "wof:name":"Lug",
    "wof:placetype":"locality"
},
  "geometry": {"coordinates":[15.30389,44.83333],"type":"Point"}
}