{
  "type": "Feature",
  "properties": {
    "gn:admin1_code":"20.0",
    "gn:admin2_code":"3191315.0",
    "gn:asciiname":"Beder",
    "gn:country_code":"HR",
    "gn:dem":488,
    "gn:feature_class":"P",
    "gn:feature_code":"PPL",
    "gn:name":"Beder",
    "gn:population":83,
    "gn:timezone":"Europe/Zagreb",
    "iso:country":"HR",
    "wof:name":"Beder",
    "wof:placetype":"locality",
    "wof:population":83
},
  "geometry": {"coordinates":[15.61667,45.81667],"type":"Point"}
}