{
  "type": "Feature",
  "properties": {
    "gn:admin1_code":"15",
    "gn:asciiname":"Kutlesa",
    "gn:country_code":"HR",
    "gn:dem":87,
    "gn:feature_class":"P",
    "gn:feature_code":"PPL",
    "gn:name":"Kutle\u0161a",
    "gn:population":0,
    "gn:timezone":"Europe/Zagreb",
    "iso:country":"HR",
    "wof:name":"Kutlesa",
    "wof:placetype":"locality"
},
  "geometry": {"coordinates":[16.80889,43.40694000000001],"type":"Point"}
}