{
  "type": "Feature",
  "properties": {
    "gn:admin1_code":"8.0",
    "gn:admin2_code":"11049294.0",
    "gn:asciiname":"Potkrcana",
    "gn:cc2":"HR",
    "gn:country_code":"HR",
    "gn:dem":816,
    "gn:feature_class":"P",
    "gn:feature_code":"PPL",
    "gn:name":"Potkr\u010dana",
    "gn:population":0,
    "gn:timezone":"Europe/Zagreb",
    "iso:country":"HR",
    "name:und_x_variant":[
        "Potkr\u010dane",
        "Potkr\u010dana"
    ],
    "wof:name":"Potkrcana",
    "wof:placetype":"locality"
},
  "geometry": {"coordinates":[15.80944,44.51056],"type":"Point"}
}