{
  "type": "Feature",
  "properties": {
    "gn:admin1_code":"19.0",
    "gn:asciiname":"Kruskovac",
    "gn:country_code":"HR",
    "gn:dem":78,
    "gn:feature_class":"P",
    "gn:feature_code":"PPL",
    "gn:name":"Kru\u0161kovac",
    "gn:population":0,
    "gn:timezone":"Europe/Zagreb",
    "iso:country":"HR",
    "wof:name":"Kruskovac",
    "wof:placetype":"locality"
},
  "geometry": {"coordinates":[15.43694,44.30222],"type":"Point"}
}