{
  "type": "Feature",
  "properties": {
    "gn:admin1_code":"15.0",
    "gn:asciiname":"Vidosi",
    "gn:country_code":"HR",
    "gn:dem":656,
    "gn:feature_class":"P",
    "gn:feature_code":"PPL",
    "gn:name":"Vido\u0161i",
    "gn:population":0,
    "gn:timezone":"Europe/Zagreb",
    "iso:country":"HR",
    "wof:name":"Vidosi",
    "wof:placetype":"locality"
},
  "geometry": {"coordinates":[17.275,43.46806],"type":"Point"}
}