{
  "type": "Feature",
  "properties": {
    "gn:admin1_code":"05",
    "gn:admin2_code":"11049272.0",
    "gn:asciiname":"Kamanje",
    "gn:country_code":"HR",
    "gn:dem":167,
    "gn:feature_class":"P",
    "gn:feature_code":"PPLA2",
    "gn:name":"Kamanje",
    "gn:population":0,
    "gn:timezone":"Europe/Zagreb",
    "iso:country":"HR",
    "name:bos_x_preferred":[
        "Kamanje"
    ],
    "name:cat_x_preferred":[
        "Kamanje"
    ],
    "name:deu_x_preferred":[
        "Kamanje"
    ],
    "name:hrv_x_preferred":[
        "Kamanje"
    ],
    "name:hun_x_preferred":[
        "Kamanje"
    ],
    "name:ita_x_preferred":[
        "Kamanje"
    ],
    "name:nld_x_preferred":[
        "Kamanje"
    ],
    "name:ron_x_preferred":[
        "Comuna Kamanje"
    ],
    "name:rus_x_preferred":[
        "\u041a\u0430\u043c\u0430\u043d\u044c\u0435"
    ],
    "name:slv_x_preferred":[
        "Kamanje"
    ],
    "name:spa_x_preferred":[
        "Kamanje"
    ],
    "name:srp_x_preferred":[
        "\u041a\u0430\u043c\u0430\u045a\u0435"
    ],
    "name:ukr_x_preferred":[
        "\u041a\u0430\u043c\u0430\u043d\u0454"
    ],
    "wof:name":"Kamanje",
    "wof:placetype":"locality"
},
  "geometry": {"coordinates":[15.39583,45.63528],"type":"Point"}
}