{
  "type": "Feature",
  "properties": {
    "gn:admin1_code":"15.0",
    "gn:asciiname":"Crip",
    "gn:country_code":"HR",
    "gn:dem":111,
    "gn:feature_class":"P",
    "gn:feature_code":"PPL",
    "gn:name":"Crip",
    "gn:population":0,
    "gn:timezone":"Europe/Zagreb",
    "iso:country":"HR",
    "wof:name":"Crip",
    "wof:placetype":"locality"
},
  "geometry": {"coordinates":[17.31778,43.20028],"type":"Point"}
}