{
  "type": "Feature",
  "properties": {
    "gn:admin1_code":"01",
    "gn:admin2_code":"11049419.0",
    "gn:asciiname":"Pupelica",
    "gn:country_code":"HR",
    "gn:dem":169,
    "gn:feature_class":"P",
    "gn:feature_code":"PPL",
    "gn:name":"Pupelica",
    "gn:population":171,
    "gn:timezone":"Europe/Zagreb",
    "iso:country":"HR",
    "wof:name":"Pupelica",
    "wof:placetype":"locality",
    "wof:population":171
},
  "geometry": {"coordinates":[17.03615,45.88],"type":"Point"}
}