{
  "type": "Feature",
  "properties": {
    "gn:admin1_code":"15.0",
    "gn:asciiname":"Sebisina",
    "gn:country_code":"HR",
    "gn:dem":377,
    "gn:feature_class":"P",
    "gn:feature_code":"PPLL",
    "gn:name":"Sebi\u0161ina",
    "gn:population":0,
    "gn:timezone":"Europe/Zagreb",
    "iso:country":"HR",
    "wof:name":"Sebisina",
    "wof:placetype":"locality"
},
  "geometry": {"coordinates":[17.25972,43.36444],"type":"Point"}
}