{
  "type": "Feature",
  "properties": {
    "gn:admin1_code":"06",
    "gn:asciiname":"Rusevac",
    "gn:country_code":"HR",
    "gn:dem":151,
    "gn:feature_class":"P",
    "gn:feature_code":"PPL",
    "gn:name":"Ru\u0161evac",
    "gn:population":182,
    "gn:timezone":"Europe/Zagreb",
    "iso:country":"HR",
    "name:und_x_variant":[
        "Ru\u0161evac"
    ],
    "wof:name":"Rusevac",
    "wof:placetype":"locality",
    "wof:population":182
},
  "geometry": {"coordinates":[16.67889,46.02639],"type":"Point"}
}