{
  "type": "Feature",
  "properties": {
    "gn:admin1_code":"04",
    "gn:admin2_code":"11054808.0",
    "gn:asciiname":"Veliki Vareski",
    "gn:cc2":"HR",
    "gn:country_code":"HR",
    "gn:dem":164,
    "gn:feature_class":"P",
    "gn:feature_code":"PPL",
    "gn:name":"Veliki Vare\u0161ki",
    "gn:population":25,
    "gn:timezone":"Europe/Zagreb",
    "iso:country":"HR",
    "name:und_x_variant":[
        "Vareschi",
        "Vareschi Grande",
        "Veliki Vare\u0161ki"
    ],
    "wof:name":"Veliki Vareski",
    "wof:placetype":"locality",
    "wof:population":25
},
  "geometry": {"coordinates":[13.99083,44.93944000000001],"type":"Point"}
}