{
  "type": "Feature",
  "properties": {
    "gn:admin1_code":"3.0",
    "gn:admin2_code":"11054972.0",
    "gn:asciiname":"Bezboge",
    "gn:country_code":"HR",
    "gn:dem":149,
    "gn:feature_class":"P",
    "gn:feature_code":"PPL",
    "gn:name":"Bezboge",
    "gn:population":0,
    "gn:timezone":"Europe/Zagreb",
    "iso:country":"HR",
    "wof:name":"Bezboge",
    "wof:placetype":"locality"
},
  "geometry": {"coordinates":[18.48111,42.44056],"type":"Point"}
}