{
  "type": "Feature",
  "properties": {
    "gn:asciiname":"Slunjski Moravci",
    "gn:country_code":"HR",
    "gn:dem":114,
    "gn:feature_class":"P",
    "gn:feature_code":"PPL",
    "gn:name":"Slunjski Moravci",
    "gn:population":85,
    "gn:timezone":"Europe/Zagreb",
    "iso:country":"HR",
    "wof:name":"Slunjski Moravci",
    "wof:placetype":"locality",
    "wof:population":85
},
  "geometry": {"coordinates":[15.70759,45.45131],"type":"Point"}
}