{
  "type": "Feature",
  "properties": {
    "gn:admin1_code":"5.0",
    "gn:asciiname":"Slivnjak",
    "gn:country_code":"HR",
    "gn:dem":225,
    "gn:feature_class":"P",
    "gn:feature_code":"PPLL",
    "gn:name":"\u0160livnjak",
    "gn:population":0,
    "gn:timezone":"Europe/Zagreb",
    "iso:country":"HR",
    "wof:name":"Slivnjak",
    "wof:placetype":"locality"
},
  "geometry": {"coordinates":[15.62028,45.24111],"type":"Point"}
}