{
  "type": "Feature",
  "properties": {
    "gn:admin1_code":"11.0",
    "gn:admin2_code":"3190588.0",
    "gn:asciiname":"Nova Lipa",
    "gn:country_code":"HR",
    "gn:dem":219,
    "gn:feature_class":"P",
    "gn:feature_code":"PPL",
    "gn:name":"Nova Lipa",
    "gn:population":88,
    "gn:timezone":"Europe/Zagreb",
    "iso:country":"HR",
    "name:bos_x_preferred":[
        "Nova Lipa"
    ],
    "name:hrv_x_preferred":[
        "Nova Lipa"
    ],
    "name:hun_x_preferred":[
        "Nova Lipa"
    ],
    "name:slv_x_preferred":[
        "Nova Lipa"
    ],
    "name:spa_x_preferred":[
        "Nova Lipa"
    ],
    "name:srp_x_preferred":[
        "\u041d\u043e\u0432\u0430 \u041b\u0438\u043f\u0430"
    ],
    "name:swe_x_preferred":[
        "Nova Lipa"
    ],
    "name:ukr_x_preferred":[
        "\u041d\u043e\u0432\u0430 \u041b\u0438\u043f\u0430"
    ],
    "wof:name":"Nova Lipa",
    "wof:placetype":"locality",
    "wof:population":88
},
  "geometry": {"coordinates":[17.61528,45.36083],"type":"Point"}
}