{
  "type": "Feature",
  "properties": {
    "gn:admin1_code":"15.0",
    "gn:asciiname":"Vujevici",
    "gn:country_code":"HR",
    "gn:dem":355,
    "gn:feature_class":"P",
    "gn:feature_code":"PPL",
    "gn:name":"Vujevi\u0107i",
    "gn:population":0,
    "gn:timezone":"Europe/Zagreb",
    "iso:country":"HR",
    "wof:name":"Vujevici",
    "wof:placetype":"locality"
},
  "geometry": {"coordinates":[17.18139,43.41556],"type":"Point"}
}