{
  "type": "Feature",
  "properties": {
    "gn:admin1_code":"05",
    "gn:admin2_code":"3194182.0",
    "gn:asciiname":"Ponikve",
    "gn:country_code":"HR",
    "gn:dem":255,
    "gn:feature_class":"P",
    "gn:feature_code":"PPL",
    "gn:name":"Ponikve",
    "gn:population":98,
    "gn:timezone":"Europe/Zagreb",
    "iso:country":"HR",
    "name:bos_x_preferred":[
        "Ponikve"
    ],
    "name:ceb_x_preferred":[
        "Ponikve"
    ],
    "name:fra_x_preferred":[
        "Ponikve"
    ],
    "name:hrv_x_preferred":[
        "Ponikve"
    ],
    "name:hun_x_preferred":[
        "Ponikve"
    ],
    "name:nld_x_preferred":[
        "Ponikve"
    ],
    "name:rus_x_preferred":[
        "\u041f\u043e\u043d\u0438\u043a\u0432\u0435"
    ],
    "name:sco_x_preferred":[
        "Ponikve"
    ],
    "name:slv_x_preferred":[
        "Ponikve"
    ],
    "name:srp_x_preferred":[
        "\u041f\u043e\u043d\u0438\u043a\u0432\u0435"
    ],
    "wof:name":"Ponikve",
    "wof:placetype":"locality",
    "wof:population":98
},
  "geometry": {"coordinates":[15.23611,45.37806],"type":"Point"}
}