{
  "type": "Feature",
  "properties": {
    "gn:admin1_code":"8.0",
    "gn:asciiname":"Strug",
    "gn:country_code":"HR",
    "gn:dem":501,
    "gn:feature_class":"P",
    "gn:feature_code":"PPL",
    "gn:name":"Strug",
    "gn:population":0,
    "gn:timezone":"Europe/Zagreb",
    "iso:country":"HR",
    "name:bos_x_preferred":[
        "Strug"
    ],
    "name:nld_x_preferred":[
        "Strug"
    ],
    "name:pol_x_preferred":[
        "Strug"
    ],
    "name:ron_x_preferred":[
        "Strug"
    ],
    "name:slv_x_preferred":[
        "Strug"
    ],
    "name:ukr_x_preferred":[
        "\u0421\u0442\u0440\u0443\u0433"
    ],
    "wof:name":"Strug",
    "wof:placetype":"locality"
},
  "geometry": {"coordinates":[14.92111,44.86222],"type":"Point"}
}