{
  "type": "Feature",
  "properties": {
    "gn:admin1_code":"8.0",
    "gn:asciiname":"Strug",
    "gn:country_code":"HR",
    "gn:dem":501,
    "gn:feature_class":"P",
    "gn:feature_code":"PPL",
    "gn:name":"Strug",
    "gn:population":0,
    "gn:timezone":"Europe/Zagreb",
    "iso:country":"HR",
    "wof:name":"Strug",
    "wof:placetype":"locality"
},
  "geometry": {"coordinates":[14.92111,44.86222],"type":"Point"}
}