{
  "type": "Feature",
  "properties": {
    "gn:admin1_code":"13",
    "gn:admin2_code":"11054524.0",
    "gn:asciiname":"Ostrogasica",
    "gn:country_code":"HR",
    "gn:dem":314,
    "gn:feature_class":"P",
    "gn:feature_code":"PPL",
    "gn:name":"Ostroga\u0161ica",
    "gn:population":47,
    "gn:timezone":"Europe/Zagreb",
    "iso:country":"HR",
    "wof:name":"Ostrogasica",
    "wof:placetype":"locality",
    "wof:population":47
},
  "geometry": {"coordinates":[16.13016,43.77035],"type":"Point"}
}