{
  "type": "Feature",
  "properties": {
    "gn:admin1_code":"08",
    "gn:admin2_code":"11049293.0",
    "gn:asciiname":"Starigrad",
    "gn:country_code":"HR",
    "gn:dem":75,
    "gn:feature_class":"P",
    "gn:feature_code":"PPL",
    "gn:name":"Starigrad",
    "gn:population":15,
    "gn:timezone":"Europe/Zagreb",
    "iso:country":"HR",
    "name:bos_x_preferred":[
        "Starigrad"
    ],
    "name:deu_x_preferred":[
        "Starigrad"
    ],
    "name:hrv_x_preferred":[
        "Starigrad"
    ],
    "name:hun_x_preferred":[
        "Starigrad"
    ],
    "name:nld_x_preferred":[
        "Starigrad"
    ],
    "name:slv_x_preferred":[
        "Starigrad"
    ],
    "name:spa_x_preferred":[
        "Starigrad"
    ],
    "name:srp_x_preferred":[
        "\u0421\u0442\u0430\u0440\u0438\u0433\u0440\u0430\u0434"
    ],
    "name:ukr_x_preferred":[
        "\u0421\u0442\u0430\u0440\u0438\u0433\u0440\u0430\u0434"
    ],
    "wof:name":"Starigrad",
    "wof:placetype":"locality",
    "wof:population":15
},
  "geometry": {"coordinates":[14.88333,44.79667],"type":"Point"}
}