{
  "type": "Feature",
  "properties": {
    "gn:admin1_code":"02",
    "gn:admin2_code":"11049499.0",
    "gn:asciiname":"Lagevac",
    "gn:country_code":"HR",
    "gn:dem":112,
    "gn:feature_class":"P",
    "gn:feature_code":"PPL",
    "gn:name":"La\u0111evac",
    "gn:population":269,
    "gn:timezone":"Europe/Zagreb",
    "iso:country":"HR",
    "wof:name":"Lagevac",
    "wof:placetype":"locality",
    "wof:population":269
},
  "geometry": {"coordinates":[17.17306,45.27194],"type":"Point"}
}