{
  "type": "Feature",
  "properties": {
    "gn:admin1_code":"15.0",
    "gn:asciiname":"Culavi",
    "gn:country_code":"HR",
    "gn:dem":321,
    "gn:feature_class":"P",
    "gn:feature_code":"PPL",
    "gn:name":"\u010culavi",
    "gn:population":0,
    "gn:timezone":"Europe/Zagreb",
    "iso:country":"HR",
    "wof:name":"Culavi",
    "wof:placetype":"locality"
},
  "geometry": {"coordinates":[17.26917000000001,43.18917],"type":"Point"}
}