{
  "type": "Feature",
  "properties": {
    "gn:admin1_code":"8.0",
    "gn:asciiname":"Krcevine",
    "gn:country_code":"HR",
    "gn:dem":610,
    "gn:feature_class":"P",
    "gn:feature_code":"PPL",
    "gn:name":"Kr\u010devine",
    "gn:population":0,
    "gn:timezone":"Europe/Zagreb",
    "iso:country":"HR",
    "wof:name":"Krcevine",
    "wof:placetype":"locality"
},
  "geometry": {"coordinates":[15.58444,44.50278],"type":"Point"}
}