{
  "type": "Feature",
  "properties": {
    "gn:admin1_code":"15.0",
    "gn:asciiname":"Luka",
    "gn:country_code":"HR",
    "gn:dem":68,
    "gn:feature_class":"P",
    "gn:feature_code":"PPL",
    "gn:name":"Luka",
    "gn:population":0,
    "gn:timezone":"Europe/Zagreb",
    "iso:country":"HR",
    "name:bel_x_preferred":[
        "\u041b\u0443\u043a\u0430"
    ],
    "name:bos_x_preferred":[
        "Luka"
    ],
    "name:bul_x_preferred":[
        "\u041b\u0443\u043a\u0430"
    ],
    "name:ceb_x_preferred":[
        "Luka"
    ],
    "name:ces_x_preferred":[
        "Luka"
    ],
    "name:deu_x_preferred":[
        "Luka"
    ],
    "name:est_x_preferred":[
        "Luka"
    ],
    "name:fra_x_preferred":[
        "Luka"
    ],
    "name:heb_x_preferred":[
        "\u05dc\u05d5\u05e7\u05d4"
    ],
    "name:hrv_x_preferred":[
        "Luka"
    ],
    "name:hun_x_preferred":[
        "Luka"
    ],
    "name:ita_x_preferred":[
        "Luka"
    ],
    "name:jpn_x_preferred":[
        "\u30eb\u30ab"
    ],
    "name:lit_x_preferred":[
        "Luka"
    ],
    "name:nld_x_preferred":[
        "Luka"
    ],
    "name:pol_x_preferred":[
        "\u0141uka"
    ],
    "name:por_x_preferred":[
        "Luka"
    ],
    "name:rus_x_preferred":[
        "\u041b\u0443\u043a\u0430"
    ],
    "name:slk_x_preferred":[
        "Luka"
    ],
    "name:slv_x_preferred":[
        "Luka"
    ],
    "name:spa_x_preferred":[
        "Luka"
    ],
    "name:srp_x_preferred":[
        "\u041b\u0443\u043a\u0430"
    ],
    "name:swe_x_preferred":[
        "Luka"
    ],
    "name:ukr_x_preferred":[
        "\u041b\u0443\u043a\u0430"
    ],
    "wof:name":"Luka",
    "wof:placetype":"locality"
},
  "geometry": {"coordinates":[17.42111,43.21472],"type":"Point"}
}