{
  "type": "Feature",
  "properties": {
    "gn:admin1_code":"15.0",
    "gn:asciiname":"Luka",
    "gn:country_code":"HR",
    "gn:dem":68,
    "gn:feature_class":"P",
    "gn:feature_code":"PPL",
    "gn:name":"Luka",
    "gn:population":0,
    "gn:timezone":"Europe/Zagreb",
    "iso:country":"HR",
    "wof:name":"Luka",
    "wof:placetype":"locality"
},
  "geometry": {"coordinates":[17.42111,43.21472],"type":"Point"}
}