{
  "type": "Feature",
  "properties": {
    "gn:country":"HR",
    "gn:fcode":"PPL",
    "gn:population":276,
    "iso:country":"HR",
    "name:bos_x_preferred":[
        "Zlarin"
    ],
    "name:eng_x_preferred":[
        "Zlarin"
    ],
    "name:hrv_x_preferred":[
        "Zlarino"
    ],
    "name:hrv_x_variant":[
        "Zlarin"
    ],
    "name:hun_x_preferred":[
        "Zlarin"
    ],
    "name:rus_x_preferred":[
        "\u0417\u043b\u0430\u0440\u0438\u043d"
    ],
    "name:slv_x_preferred":[
        "Zlarin"
    ],
    "name:srp_x_preferred":[
        "\u0417\u043b\u0430\u0440\u0438\u043d"
    ],
    "name:ukr_x_preferred":[
        "\u0417\u043b\u0430\u0440\u0438\u043d"
    ],
    "qs_pg:aaroncc":"HR",
    "qs_pg:gn_country":"HR",
    "qs_pg:gn_fcode":"PPL",
    "qs_pg:gn_pop":276,
    "qs_pg:name":"Zlarin",
    "qs_pg:photos_9r":0,
    "qs_pg:photos_sr":0,
    "qs_pg:pop_sr":2,
    "qs_pg:qs_pg_placetype":"locality",
    "wof:name":"Zlarin",
    "wof:placetype":"locality",
    "wof:population":284
},
  "geometry": {"coordinates":[15.83611,43.6975],"type":"Point"}
}