{
  "type": "Feature",
  "properties": {
    "gn:admin1_code":"15.0",
    "gn:admin2_code":"3194113.0",
    "gn:asciiname":"Tice",
    "gn:country_code":"HR",
    "gn:dem":57,
    "gn:feature_class":"P",
    "gn:feature_code":"PPL",
    "gn:name":"Tice",
    "gn:population":0,
    "gn:timezone":"Europe/Zagreb",
    "iso:country":"HR",
    "name:deu_x_preferred":[
        "Tice"
    ],
    "name:nld_x_preferred":[
        "Tice"
    ],
    "name:rus_x_preferred":[
        "\u0422\u0430\u0439\u0441"
    ],
    "wof:name":"Tice",
    "wof:placetype":"locality"
},
  "geometry": {"coordinates":[16.72679,43.41476],"type":"Point"}
}