{
  "type": "Feature",
  "properties": {
    "gn:admin1_code":"15.0",
    "gn:admin2_code":"3194113.0",
    "gn:asciiname":"Tice",
    "gn:country_code":"HR",
    "gn:dem":57,
    "gn:feature_class":"P",
    "gn:feature_code":"PPL",
    "gn:name":"Tice",
    "gn:population":0,
    "gn:timezone":"Europe/Zagreb",
    "iso:country":"HR",
    "wof:name":"Tice",
    "wof:placetype":"locality"
},
  "geometry": {"coordinates":[16.72679,43.41476],"type":"Point"}
}