{
  "type": "Feature",
  "properties": {
    "gn:admin1_code":"06",
    "gn:admin2_code":"3197228.0",
    "gn:asciiname":"Srednji Dubovec",
    "gn:country_code":"HR",
    "gn:dem":128,
    "gn:feature_class":"P",
    "gn:feature_code":"PPL",
    "gn:name":"Srednji Dubovec",
    "gn:population":93,
    "gn:timezone":"Europe/Zagreb",
    "iso:country":"HR",
    "wof:name":"Srednji Dubovec",
    "wof:placetype":"locality",
    "wof:population":93
},
  "geometry": {"coordinates":[16.46667,46.01667],"type":"Point"}
}