{
  "type": "Feature",
  "properties": {
    "gn:admin1_code":"15",
    "gn:asciiname":"Budimir",
    "gn:country_code":"HR",
    "gn:dem":398,
    "gn:feature_class":"P",
    "gn:feature_code":"PPLL",
    "gn:name":"Budimir",
    "gn:population":0,
    "gn:timezone":"Europe/Zagreb",
    "iso:country":"HR",
    "name:bos_x_preferred":[
        "Budimir"
    ],
    "name:deu_x_preferred":[
        "Budimir"
    ],
    "name:hun_x_preferred":[
        "Budimir"
    ],
    "name:nld_x_preferred":[
        "Budimir"
    ],
    "name:rus_x_preferred":[
        "\u0411\u0443\u0434\u0438\u043c\u0438\u0440"
    ],
    "name:slv_x_preferred":[
        "Budimir"
    ],
    "name:srp_x_preferred":[
        "\u0411\u0443\u0434\u0438\u043c\u0438\u0440"
    ],
    "name:ukr_x_preferred":[
        "\u0411\u0443\u0434\u0438\u043c\u0438\u0440"
    ],
    "wof:name":"Budimir",
    "wof:placetype":"locality"
},
  "geometry": {"coordinates":[16.8125,43.565],"type":"Point"}
}