{
  "type": "Feature",
  "properties": {
    "gn:admin1_code":"21",
    "gn:asciiname":"Jesenovec",
    "gn:country_code":"HR",
    "gn:dem":166,
    "gn:feature_class":"P",
    "gn:feature_code":"PPL",
    "gn:name":"Jesenovec",
    "gn:population":0,
    "gn:timezone":"Europe/Zagreb",
    "iso:country":"HR",
    "name:bos_x_preferred":[
        "Jesenovec"
    ],
    "name:hrv_x_preferred":[
        "Jesenovec"
    ],
    "name:nld_x_preferred":[
        "Jesenovec"
    ],
    "name:slv_x_preferred":[
        "Jesenovec"
    ],
    "name:srp_x_preferred":[
        "\u0408\u0435\u0441\u0435\u043d\u043e\u0432\u0435\u0446"
    ],
    "name:ukr_x_preferred":[
        "\u0404\u0441\u0435\u043d\u043e\u0432\u0435\u0446\u044c"
    ],
    "wof:name":"Jesenovec",
    "wof:placetype":"locality"
},
  "geometry": {"coordinates":[16.16667,45.91667],"type":"Point"}
}