{
  "type": "Feature",
  "properties": {
    "gn:admin1_code":"3.0",
    "gn:admin2_code":"11054958.0",
    "gn:asciiname":"Trojavina",
    "gn:country_code":"HR",
    "gn:dem":21,
    "gn:feature_class":"P",
    "gn:feature_code":"PPL",
    "gn:name":"Trojavina",
    "gn:population":0,
    "gn:timezone":"Europe/Zagreb",
    "iso:country":"HR",
    "wof:name":"Trojavina",
    "wof:placetype":"locality"
},
  "geometry": {"coordinates":[17.61139,42.97056],"type":"Point"}
}