{
  "type": "Feature",
  "properties": {
    "gn:admin1_code":"06",
    "gn:admin2_code":"11049380.0",
    "gn:asciiname":"Pavlanci",
    "gn:cc2":"HR",
    "gn:country_code":"HR",
    "gn:dem":112,
    "gn:feature_class":"P",
    "gn:feature_code":"PPL",
    "gn:name":"Pavlanci",
    "gn:population":0,
    "gn:timezone":"Europe/Zagreb",
    "iso:country":"HR",
    "name:und_x_variant":[
        "Pavlanci \u00d0ur\u0111eva\u010dki",
        "Pavljanci",
        "Pavlanci"
    ],
    "wof:name":"Pavlanci",
    "wof:placetype":"locality"
},
  "geometry": {"coordinates":[17.17722,46.08333],"type":"Point"}
}