{
  "type": "Feature",
  "properties": {
    "gn:admin1_code":"5.0",
    "gn:asciiname":"Zgela",
    "gn:country_code":"HR",
    "gn:dem":349,
    "gn:feature_class":"P",
    "gn:feature_code":"PPL",
    "gn:name":"\u017dgela",
    "gn:population":0,
    "gn:timezone":"Europe/Zagreb",
    "iso:country":"HR",
    "wof:name":"Zgela",
    "wof:placetype":"locality"
},
  "geometry": {"coordinates":[15.75472,45.07083],"type":"Point"}
}