{
  "type": "Feature",
  "properties": {
    "gn:admin1_code":"20",
    "gn:asciiname":"Potocec",
    "gn:country_code":"HR",
    "gn:dem":107,
    "gn:feature_class":"P",
    "gn:feature_code":"PPL",
    "gn:name":"Poto\u010dec",
    "gn:population":88,
    "gn:timezone":"Europe/Zagreb",
    "iso:country":"HR",
    "wof:name":"Potocec",
    "wof:placetype":"locality",
    "wof:population":88
},
  "geometry": {"coordinates":[16.46667,45.88333],"type":"Point"}
}