{
  "type": "Feature",
  "properties": {
    "gn:admin1_code":"8.0",
    "gn:asciiname":"Dragicevica Pod",
    "gn:country_code":"HR",
    "gn:dem":761,
    "gn:feature_class":"P",
    "gn:feature_code":"PPL",
    "gn:name":"Dragi\u010devi\u0107a Pod",
    "gn:population":0,
    "gn:timezone":"Europe/Zagreb",
    "iso:country":"HR",
    "wof:name":"Dragicevica Pod",
    "wof:placetype":"locality"
},
  "geometry": {"coordinates":[14.96111,44.68389000000001],"type":"Point"}
}