{
  "type": "Feature",
  "properties": {
    "gn:admin1_code":"3.0",
    "gn:admin2_code":"7577034.0",
    "gn:asciiname":"Petrovo Selo",
    "gn:country_code":"HR",
    "gn:dem":211,
    "gn:feature_class":"P",
    "gn:feature_code":"PPLL",
    "gn:name":"Petrovo Selo",
    "gn:population":0,
    "gn:timezone":"Europe/Zagreb",
    "iso:country":"HR",
    "wof:name":"Petrovo Selo",
    "wof:placetype":"locality"
},
  "geometry": {"coordinates":[18.08833,42.68278],"type":"Point"}
}