{
  "type": "Feature",
  "properties": {
    "gn:admin1_code":"15",
    "gn:admin2_code":"3187229.0",
    "gn:asciiname":"Kokorici",
    "gn:cc2":"HR",
    "gn:country_code":"HR",
    "gn:dem":79,
    "gn:feature_class":"P",
    "gn:feature_code":"PPLL",
    "gn:name":"Kokori\u0107i",
    "gn:population":0,
    "gn:timezone":"Europe/Zagreb",
    "iso:country":"HR",
    "name:und_x_variant":[
        "Kokori\u0107",
        "Kokori\u0107i"
    ],
    "wof:name":"Kokorici",
    "wof:placetype":"locality"
},
  "geometry": {"coordinates":[17.3225,43.19389],"type":"Point"}
}