{
  "type": "Feature",
  "properties": {
    "gn:admin1_code":"15.0",
    "gn:asciiname":"Cekolici",
    "gn:country_code":"HR",
    "gn:dem":355,
    "gn:feature_class":"P",
    "gn:feature_code":"PPL",
    "gn:name":"\u010cekoli\u0107i",
    "gn:population":0,
    "gn:timezone":"Europe/Zagreb",
    "iso:country":"HR",
    "wof:name":"Cekolici",
    "wof:placetype":"locality"
},
  "geometry": {"coordinates":[16.75778,43.53056],"type":"Point"}
}