{
  "type": "Feature",
  "properties": {
    "gn:admin1_code":"3.0",
    "gn:admin2_code":"11054972.0",
    "gn:asciiname":"Smisljani",
    "gn:country_code":"HR",
    "gn:dem":114,
    "gn:feature_class":"P",
    "gn:feature_code":"PPL",
    "gn:name":"Smi\u0161ljani",
    "gn:population":0,
    "gn:timezone":"Europe/Zagreb",
    "iso:country":"HR",
    "wof:name":"Smisljani",
    "wof:placetype":"locality"
},
  "geometry": {"coordinates":[18.31111,42.52028],"type":"Point"}
}