{
  "type": "Feature",
  "properties": {
    "gn:admin1_code":"14.0",
    "gn:asciiname":"Kotarani",
    "gn:country_code":"HR",
    "gn:dem":269,
    "gn:feature_class":"P",
    "gn:feature_code":"PPLL",
    "gn:name":"Kotarani",
    "gn:population":0,
    "gn:timezone":"Europe/Zagreb",
    "iso:country":"HR",
    "wof:name":"Kotarani",
    "wof:placetype":"locality"
},
  "geometry": {"coordinates":[16.20889,45.03583],"type":"Point"}
}