{
  "type": "Feature",
  "properties": {
    "gn:admin1_code":"15.0",
    "gn:asciiname":"Prolascici",
    "gn:country_code":"HR",
    "gn:dem":391,
    "gn:feature_class":"P",
    "gn:feature_code":"PPL",
    "gn:name":"Prola\u0161\u010di\u0107i",
    "gn:population":0,
    "gn:timezone":"Europe/Zagreb",
    "iso:country":"HR",
    "wof:name":"Prolascici",
    "wof:placetype":"locality"
},
  "geometry": {"coordinates":[16.53306,43.80806],"type":"Point"}
}