{
  "type": "Feature",
  "properties": {
    "gn:admin1_code":"20.0",
    "gn:asciiname":"Radicevici",
    "gn:country_code":"HR",
    "gn:dem":168,
    "gn:feature_class":"P",
    "gn:feature_code":"PPL",
    "gn:name":"Radi\u0107evi\u0107i",
    "gn:population":0,
    "gn:timezone":"Europe/Zagreb",
    "iso:country":"HR",
    "wof:name":"Radicevici",
    "wof:placetype":"locality"
},
  "geometry": {"coordinates":[15.87111,45.64444],"type":"Point"}
}