{
  "type": "Feature",
  "properties": {
    "gn:admin1_code":"8.0",
    "gn:asciiname":"Drazica",
    "gn:country_code":"HR",
    "gn:dem":564,
    "gn:feature_class":"P",
    "gn:feature_code":"PPLL",
    "gn:name":"Dra\u017eica",
    "gn:population":0,
    "gn:timezone":"Europe/Zagreb",
    "iso:country":"HR",
    "wof:name":"Drazica",
    "wof:placetype":"locality"
},
  "geometry": {"coordinates":[15.37639,44.78111],"type":"Point"}
}