{
  "type": "Feature",
  "properties": {
    "gn:admin1_code":"5.0",
    "gn:admin2_code":"3190522.0",
    "gn:asciiname":"Kosijersko Selo",
    "gn:country_code":"HR",
    "gn:dem":212,
    "gn:feature_class":"P",
    "gn:feature_code":"PPL",
    "gn:name":"Kosijersko Selo",
    "gn:population":39,
    "gn:timezone":"Europe/Zagreb",
    "iso:country":"HR",
    "wof:name":"Kosijersko Selo",
    "wof:placetype":"locality",
    "wof:population":39
},
  "geometry": {"coordinates":[15.59472,45.20417],"type":"Point"}
}