{
  "type": "Feature",
  "properties": {
    "gn:gn_country":"HR",
    "gn:gn_fcode":"PPL",
    "gn:gn_pop":0,
    "iso:country":"HR",
    "name:bos_x_preferred":[
        "Barban"
    ],
    "name:ces_x_preferred":[
        "Barban"
    ],
    "name:deu_x_preferred":[
        "Barban"
    ],
    "name:fin_x_preferred":[
        "Barban"
    ],
    "name:fra_x_preferred":[
        "Barban"
    ],
    "name:hrv_x_preferred":[
        "Barban"
    ],
    "name:hun_x_preferred":[
        "Barban"
    ],
    "name:ita_x_preferred":[
        "Barbana"
    ],
    "name:lat_x_preferred":[
        "Barbana"
    ],
    "name:nld_x_preferred":[
        "Barban"
    ],
    "name:pol_x_preferred":[
        "Gmina Barban"
    ],
    "name:ron_x_preferred":[
        "Comuna Barban"
    ],
    "name:rus_x_preferred":[
        "\u0411\u0430\u0440\u0431\u0430\u043d"
    ],
    "name:slv_x_preferred":[
        "Barban"
    ],
    "name:srp_x_preferred":[
        "\u0411\u0430\u0440\u0431\u0430\u043d"
    ],
    "name:ukr_x_preferred":[
        "\u0411\u0430\u0440\u0431\u0430\u043d"
    ],
    "name:unk_x_variant":[
        "Ru\u017ei\u0107i"
    ],
    "name:war_x_preferred":[
        "Barban"
    ],
    "qs_pg:aaroncc":"HR",
    "qs_pg:gn_country":"HR",
    "qs_pg:gn_fcode":"PPL",
    "qs_pg:gn_pop":0,
    "qs_pg:name":"Barban",
    "qs_pg:name_adm0":"Hrvatska",
    "qs_pg:name_adm1":"Istarska",
    "qs_pg:photos":46,
    "qs_pg:photos_1k":9,
    "qs_pg:photos_9k":1,
    "qs_pg:photos_9r":2,
    "qs_pg:photos_all":46,
    "qs_pg:photos_sr":2,
    "qs_pg:pop_sr":0,
    "qs_pg:qs_pg_placetype":"locality",
    "qs_pg:qs_pg_placetype_gp":"Town",
    "qs_pg:woe_adm0":23424843,
    "woe:adm0_id":23424843,
    "woe:name_adm0":"Hrvatska",
    "woe:name_adm1":"Istarska",
    "woe:placetype":"Town",
    "wof:name":"Barban",
    "wof:placetype":"locality"
},
  "geometry": {"coordinates":[14.01361,45.06444],"type":"Point"}
}