{
  "type": "Feature",
  "properties": {
    "gn:admin1_code":"20",
    "gn:admin2_code":"11049004.0",
    "gn:asciiname":"Rugvica",
    "gn:country_code":"HR",
    "gn:dem":98,
    "gn:feature_class":"P",
    "gn:feature_code":"PPLA2",
    "gn:name":"Rugvica",
    "gn:population":0,
    "gn:timezone":"Europe/Zagreb",
    "iso:country":"HR",
    "name:ron_x_preferred":[
        "Comuna Rugvica"
    ],
    "name:rus_x_preferred":[
        "\u0420\u0443\u0433\u0432\u0438\u0446\u0430"
    ],
    "name:srp_x_preferred":[
        "\u0420\u0443\u0433\u0432\u0438\u0446\u0430"
    ],
    "wof:name":"Rugvica",
    "wof:placetype":"locality"
},
  "geometry": {"coordinates":[16.23306,45.73611],"type":"Point"}
}