{
  "type": "Feature",
  "properties": {
    "gn:admin1_code":"15",
    "gn:admin2_code":"3187229.0",
    "gn:asciiname":"Umcani",
    "gn:cc2":"HR",
    "gn:country_code":"HR",
    "gn:dem":62,
    "gn:feature_class":"P",
    "gn:feature_code":"PPL",
    "gn:name":"Um\u010dani",
    "gn:population":227,
    "gn:timezone":"Europe/Zagreb",
    "iso:country":"HR",
    "name:und_x_variant":[
        "Um\u010dane",
        "Um\u010dani"
    ],
    "wof:name":"Umcani",
    "wof:placetype":"locality",
    "wof:population":227
},
  "geometry": {"coordinates":[17.38694,43.16528],"type":"Point"}
}