{
  "type": "Feature",
  "properties": {
    "gn:admin1_code":"12",
    "gn:admin2_code":"11049443.0",
    "gn:asciiname":"Jusici",
    "gn:country_code":"HR",
    "gn:dem":311,
    "gn:feature_class":"P",
    "gn:feature_code":"PPL",
    "gn:name":"Ju\u0161i\u0107i",
    "gn:population":861,
    "gn:timezone":"Europe/Zagreb",
    "iso:country":"HR",
    "wof:name":"Jusici",
    "wof:placetype":"locality",
    "wof:population":861
},
  "geometry": {"coordinates":[14.32194,45.3775],"type":"Point"}
}