{
  "type": "Feature",
  "properties": {
    "gn:admin1_code":"12",
    "gn:asciiname":"Volosko",
    "gn:cc2":"HR",
    "gn:country_code":"HR",
    "gn:dem":55,
    "gn:feature_class":"P",
    "gn:feature_code":"PPL",
    "gn:name":"Volosko",
    "gn:population":0,
    "gn:timezone":"Europe/Zagreb",
    "iso:country":"HR",
    "name:deu_x_preferred":[
        "Volosko"
    ],
    "name:est_x_preferred":[
        "Volosko"
    ],
    "name:hrv_x_preferred":[
        "Volosko"
    ],
    "name:ita_x_preferred":[
        "Volosca"
    ],
    "name:nld_x_preferred":[
        "Volosko"
    ],
    "name:ron_x_preferred":[
        "Volosca"
    ],
    "name:slv_x_preferred":[
        "Volosko"
    ],
    "wof:name":"Volosko",
    "wof:placetype":"locality"
},
  "geometry": {"coordinates":[14.3175,45.34889],"type":"Point"}
}