{
  "type": "Feature",
  "properties": {
    "gn:admin1_code":"03",
    "gn:admin2_code":"11054972.0",
    "gn:asciiname":"Gabrili",
    "gn:cc2":"HR",
    "gn:country_code":"HR",
    "gn:dem":169,
    "gn:feature_class":"P",
    "gn:feature_code":"PPL",
    "gn:name":"Gabrili",
    "gn:population":210,
    "gn:timezone":"Europe/Zagreb",
    "iso:country":"HR",
    "name:und_x_variant":[
        "Gabrile",
        "Gabrili"
    ],
    "wof:name":"Gabrili",
    "wof:placetype":"locality",
    "wof:population":210
},
  "geometry": {"coordinates":[18.29028,42.57417],"type":"Point"}
}