{
  "type": "Feature",
  "properties": {
    "gn:admin1_code":"05",
    "gn:admin2_code":"11049283.0",
    "gn:asciiname":"Jadrici",
    "gn:country_code":"HR",
    "gn:dem":212,
    "gn:feature_class":"P",
    "gn:feature_code":"PPL",
    "gn:name":"Jadri\u0107i",
    "gn:population":7,
    "gn:timezone":"Europe/Zagreb",
    "iso:country":"HR",
    "wof:name":"Jadrici",
    "wof:placetype":"locality",
    "wof:population":7
},
  "geometry": {"coordinates":[15.31667,45.55],"type":"Point"}
}