{
  "type": "Feature",
  "properties": {
    "gn:admin1_code":"01",
    "gn:admin2_code":"3202819.0",
    "gn:asciiname":"Sovari",
    "gn:country_code":"HR",
    "gn:dem":142,
    "gn:feature_class":"P",
    "gn:feature_code":"PPL",
    "gn:name":"Sovari",
    "gn:population":97,
    "gn:timezone":"Europe/Zagreb",
    "iso:country":"HR",
    "name:bos_x_preferred":[
        "Sovari"
    ],
    "name:fra_x_preferred":[
        "Sovari"
    ],
    "name:hrv_x_preferred":[
        "Sovari"
    ],
    "name:hun_x_preferred":[
        "Sovari"
    ],
    "name:nld_x_preferred":[
        "Sovari"
    ],
    "name:slv_x_preferred":[
        "Sovari"
    ],
    "name:spa_x_preferred":[
        "Sovari"
    ],
    "name:ukr_x_preferred":[
        "\u0421\u043e\u0432\u0430\u0440\u0438"
    ],
    "wof:name":"Sovari",
    "wof:placetype":"locality",
    "wof:population":97
},
  "geometry": {"coordinates":[16.53333,45.73333],"type":"Point"}
}