{
  "type": "Feature",
  "properties": {
    "gn:admin1_code":"01",
    "gn:admin2_code":"3202819.0",
    "gn:asciiname":"Sovari",
    "gn:country_code":"HR",
    "gn:dem":142,
    "gn:feature_class":"P",
    "gn:feature_code":"PPL",
    "gn:name":"Sovari",
    "gn:population":97,
    "gn:timezone":"Europe/Zagreb",
    "iso:country":"HR",
    "wof:name":"Sovari",
    "wof:placetype":"locality",
    "wof:population":97
},
  "geometry": {"coordinates":[16.53333,45.73333],"type":"Point"}
}