{
  "type": "Feature",
  "properties": {
    "gn:admin1_code":"10.0",
    "gn:admin2_code":"11054393.0",
    "gn:asciiname":"Selci",
    "gn:cc2":"HR",
    "gn:country_code":"HR",
    "gn:dem":89,
    "gn:feature_class":"P",
    "gn:feature_code":"PPL",
    "gn:name":"Selci",
    "gn:population":0,
    "gn:timezone":"Europe/Zagreb",
    "iso:country":"HR",
    "name:azb_x_preferred":[
        "\u0633\u0644\u0686\u06cc"
    ],
    "name:bcl_x_preferred":[
        "Selci"
    ],
    "name:bel_x_preferred":[
        "\u0421\u0435\u043b\u044c\u0447\u044b"
    ],
    "name:bul_x_preferred":[
        "\u0421\u0435\u043b\u0447\u0438"
    ],
    "name:deu_x_preferred":[
        "Selci"
    ],
    "name:epo_x_preferred":[
        "Selci"
    ],
    "name:est_x_preferred":[
        "Selci"
    ],
    "name:eus_x_preferred":[
        "Selci"
    ],
    "name:fas_x_preferred":[
        "\u0633\u0644\u0686\u06cc"
    ],
    "name:fra_x_preferred":[
        "Selci"
    ],
    "name:hun_x_preferred":[
        "Selci"
    ],
    "name:hye_x_preferred":[
        "\u054d\u0565\u056c\u0579\u056b"
    ],
    "name:ina_x_preferred":[
        "Selci"
    ],
    "name:ita_x_preferred":[
        "Selci"
    ],
    "name:jpn_x_preferred":[
        "\u30bb\u30eb\u30c1"
    ],
    "name:kaz_x_preferred":[
        "\u0421\u0435\u043b\u044c\u0447\u0438"
    ],
    "name:lat_x_preferred":[
        "Selicium"
    ],
    "name:lmo_x_preferred":[
        "Selci"
    ],
    "name:msa_x_preferred":[
        "Selci"
    ],
    "name:nap_x_preferred":[
        "Selci"
    ],
    "name:nld_x_preferred":[
        "Selci"
    ],
    "name:pms_x_preferred":[
        "Selci"
    ],
    "name:pol_x_preferred":[
        "Selci"
    ],
    "name:por_x_preferred":[
        "Selci"
    ],
    "name:ron_x_preferred":[
        "Selci"
    ],
    "name:rus_x_preferred":[
        "\u0421\u0435\u043b\u044c\u0447\u0438"
    ],
    "name:scn_x_preferred":[
        "Selci"
    ],
    "name:spa_x_preferred":[
        "Selci"
    ],
    "name:srp_x_preferred":[
        "\u0421\u0435\u043b\u0447\u0438"
    ],
    "name:ukr_x_preferred":[
        "\u0421\u0435\u043b\u044c\u0447\u0456"
    ],
    "name:und_x_variant":[
        "Selce",
        "Selci"
    ],
    "name:uzb_x_preferred":[
        "Selci"
    ],
    "name:vie_x_preferred":[
        "Selci"
    ],
    "name:vol_x_preferred":[
        "Selci"
    ],
    "name:war_x_preferred":[
        "Selci"
    ],
    "name:zho_x_preferred":[
        "\u585e\u5c14\u5947"
    ],
    "wof:name":"Selci",
    "wof:placetype":"locality"
},
  "geometry": {"coordinates":[18.51361,45.55139000000001],"type":"Point"}
}