{
  "type": "Feature",
  "properties": {
    "gn:admin1_code":"14",
    "gn:admin2_code":"11049234.0",
    "gn:asciiname":"Bukovica Cemernicka",
    "gn:cc2":"HR",
    "gn:country_code":"HR",
    "gn:dem":173,
    "gn:feature_class":"P",
    "gn:feature_code":"PPL",
    "gn:name":"Bukovica \u010cemerni\u010dka",
    "gn:population":0,
    "gn:timezone":"Europe/Zagreb",
    "iso:country":"HR",
    "name:und_x_variant":[
        "Bukovica",
        "\u010cemerni\u010dka Bukovica",
        "Bukovica \u010cemerni\u010dka"
    ],
    "wof:name":"Bukovica Cemernicka",
    "wof:placetype":"locality"
},
  "geometry": {"coordinates":[15.9391,45.3618],"type":"Point"}
}