{
  "type": "Feature",
  "properties": {
    "gn:admin1_code":"10",
    "gn:admin2_code":"11054454.0",
    "gn:asciiname":"Svajcernica",
    "gn:cc2":"HR",
    "gn:country_code":"HR",
    "gn:dem":86,
    "gn:feature_class":"P",
    "gn:feature_code":"PPL",
    "gn:name":"\u0160vajcernica",
    "gn:population":0,
    "gn:timezone":"Europe/Zagreb",
    "iso:country":"HR",
    "name:und_x_variant":[
        "\u0160vajcarnica",
        "\u0160vajcernica"
    ],
    "wof:name":"Svajcernica",
    "wof:placetype":"locality"
},
  "geometry": {"coordinates":[18.68056,45.64861],"type":"Point"}
}