{
  "type": "Feature",
  "properties": {
    "gn:admin1_code":"10",
    "gn:admin2_code":"11054454.0",
    "gn:asciiname":"Svajcernica",
    "gn:cc2":"HR",
    "gn:country_code":"HR",
    "gn:dem":86,
    "gn:feature_class":"P",
    "gn:feature_code":"PPL",
    "gn:name":"\u0160vajcernica",
    "gn:population":0,
    "gn:timezone":"Europe/Zagreb",
    "iso:country":"HR",
    "name:bos_x_preferred":[
        "\u0160vajcarnica"
    ],
    "name:ceb_x_preferred":[
        "\u0160vajcernica"
    ],
    "name:epo_x_preferred":[
        "\u0160vajcarnica"
    ],
    "name:fra_x_preferred":[
        "\u0160vajcarnica"
    ],
    "name:hrv_x_preferred":[
        "\u0160vajcarnica"
    ],
    "name:slv_x_preferred":[
        "\u0160vajcarnica"
    ],
    "name:srp_x_preferred":[
        "\u0428\u0432\u0430\u0458\u0446\u0430\u0440\u043d\u0438\u0446\u0430"
    ],
    "name:swe_x_preferred":[
        "\u0160vajcernica"
    ],
    "name:ukr_x_preferred":[
        "\u0428\u0432\u0430\u0439\u0446\u0430\u0440\u043d\u0438\u0446\u044f"
    ],
    "wof:name":"Svajcernica",
    "wof:placetype":"locality"
},
  "geometry": {"coordinates":[18.68056,45.64861],"type":"Point"}
}