{
  "type": "Feature",
  "properties": {
    "gn:admin1_code":"19",
    "gn:admin2_code":"11054323.0",
    "gn:asciiname":"Mandre",
    "gn:country_code":"HR",
    "gn:dem":17,
    "gn:feature_class":"P",
    "gn:feature_code":"PPL",
    "gn:name":"Mandre",
    "gn:population":395,
    "gn:timezone":"Europe/Zagreb",
    "iso:country":"HR",
    "wof:name":"Mandre",
    "wof:placetype":"locality",
    "wof:population":395
},
  "geometry": {"coordinates":[14.92361,44.47639],"type":"Point"}
}