{
  "type": "Feature",
  "properties": {
    "gn:admin1_code":"19.0",
    "gn:asciiname":"Zmirici",
    "gn:country_code":"HR",
    "gn:dem":326,
    "gn:feature_class":"P",
    "gn:feature_code":"PPL",
    "gn:name":"Zmiri\u0107i",
    "gn:population":0,
    "gn:timezone":"Europe/Zagreb",
    "iso:country":"HR",
    "wof:name":"Zmirici",
    "wof:placetype":"locality"
},
  "geometry": {"coordinates":[15.8475,44.0375],"type":"Point"}
}