{
  "type": "Feature",
  "properties": {
    "gn:admin1_code":"01",
    "gn:admin2_code":"3199514.0",
    "gn:asciiname":"Mali Zdenci",
    "gn:cc2":"HR",
    "gn:country_code":"HR",
    "gn:dem":141,
    "gn:feature_class":"P",
    "gn:feature_code":"PPL",
    "gn:name":"Mali Zdenci",
    "gn:population":0,
    "gn:timezone":"Europe/Zagreb",
    "iso:country":"HR",
    "name:bos_x_preferred":[
        "Mali Zdenci"
    ],
    "name:fra_x_preferred":[
        "Mali Zdenci"
    ],
    "name:hrv_x_preferred":[
        "Mali Zdenci"
    ],
    "name:hun_x_preferred":[
        "Mali Zdenci"
    ],
    "name:nld_x_preferred":[
        "Mali Zdenci"
    ],
    "name:slv_x_preferred":[
        "Mali Zdenci"
    ],
    "name:spa_x_preferred":[
        "Mali Zdenci"
    ],
    "name:srp_x_preferred":[
        "\u041c\u0430\u043b\u0438 \u0417\u0434\u0435\u043d\u0446\u0438"
    ],
    "name:ukr_x_preferred":[
        "\u041c\u0430\u043b\u0456 \u0417\u0434\u0435\u043d\u0446\u0456"
    ],
    "name:und_x_variant":[
        "Izdenc",
        "Zdenczi"
    ],
    "wof:name":"Mali Zdenci",
    "wof:placetype":"locality"
},
  "geometry": {"coordinates":[17.13139,45.68306],"type":"Point"}
}