{
  "type": "Feature",
  "properties": {
    "gn:admin1_code":"14.0",
    "gn:asciiname":"Mracaj",
    "gn:country_code":"HR",
    "gn:dem":233,
    "gn:feature_class":"P",
    "gn:feature_code":"PPL",
    "gn:name":"Mra\u010daj",
    "gn:population":42,
    "gn:timezone":"Europe/Zagreb",
    "iso:country":"HR",
    "wof:name":"Mracaj",
    "wof:placetype":"locality",
    "wof:population":42
},
  "geometry": {"coordinates":[16.13332999999999,45.13667],"type":"Point"}
}