{
  "type": "Feature",
  "properties": {
    "gn:admin1_code":"04",
    "gn:admin2_code":"11072234.0",
    "gn:asciiname":"Strmac",
    "gn:country_code":"HR",
    "gn:dem":302,
    "gn:feature_class":"P",
    "gn:feature_code":"PPL",
    "gn:name":"Strmac",
    "gn:population":0,
    "gn:timezone":"Europe/Zagreb",
    "iso:country":"HR",
    "name:bos_x_preferred":[
        "\u0160trmac"
    ],
    "name:ceb_x_preferred":[
        "Strmac"
    ],
    "name:fra_x_preferred":[
        "\u0160trmac"
    ],
    "name:hrv_x_preferred":[
        "\u0160trmac"
    ],
    "name:hun_x_preferred":[
        "\u0160trmac"
    ],
    "name:nld_x_preferred":[
        "\u0160trmac"
    ],
    "name:slv_x_preferred":[
        "\u0160trmac"
    ],
    "name:srp_x_preferred":[
        "\u0428\u0442\u0440\u043c\u0430\u0446"
    ],
    "name:swe_x_preferred":[
        "Strmac"
    ],
    "name:ukr_x_preferred":[
        "\u0428\u0442\u0440\u043c\u0430\u0446\u044c"
    ],
    "wof:name":"Strmac",
    "wof:placetype":"locality"
},
  "geometry": {"coordinates":[14.13,45.11778],"type":"Point"}
}