{
  "type": "Feature",
  "properties": {
    "gn:admin1_code":"15",
    "gn:admin2_code":"11054627.0",
    "gn:asciiname":"Ljubitovica",
    "gn:country_code":"HR",
    "gn:dem":387,
    "gn:feature_class":"P",
    "gn:feature_code":"PPL",
    "gn:name":"Ljubitovica",
    "gn:population":485,
    "gn:timezone":"Europe/Zagreb",
    "iso:country":"HR",
    "wof:name":"Ljubitovica",
    "wof:placetype":"locality",
    "wof:population":485
},
  "geometry": {"coordinates":[16.13634,43.61563],"type":"Point"}
}