{
  "type": "Feature",
  "properties": {
    "gn:admin1_code":"15.0",
    "gn:asciiname":"Milosici Polje",
    "gn:country_code":"HR",
    "gn:dem":36,
    "gn:feature_class":"P",
    "gn:feature_code":"PPL",
    "gn:name":"Milo\u0161i\u0107i Polje",
    "gn:population":0,
    "gn:timezone":"Europe/Zagreb",
    "iso:country":"HR",
    "wof:name":"Milosici Polje",
    "wof:placetype":"locality"
},
  "geometry": {"coordinates":[17.43667,43.16583],"type":"Point"}
}