{
  "type": "Feature",
  "properties": {
    "gn:admin1_code":"20",
    "gn:asciiname":"Vrhovac",
    "gn:country_code":"HR",
    "gn:dem":187,
    "gn:feature_class":"P",
    "gn:feature_code":"PPL",
    "gn:name":"Vrhovac",
    "gn:population":0,
    "gn:timezone":"Europe/Zagreb",
    "iso:country":"HR",
    "wof:name":"Vrhovac",
    "wof:placetype":"locality"
},
  "geometry": {"coordinates":[15.48489,45.63817],"type":"Point"}
}