{
  "type": "Feature",
  "properties": {
    "gn:admin1_code":"14",
    "gn:asciiname":"Staro Selo",
    "gn:cc2":"HR",
    "gn:country_code":"HR",
    "gn:dem":137,
    "gn:feature_class":"P",
    "gn:feature_code":"PPLL",
    "gn:name":"Staro Selo",
    "gn:population":0,
    "gn:timezone":"Europe/Zagreb",
    "iso:country":"HR",
    "name:und_x_variant":[
        "Topusko Staro Selo",
        "Staro Selo Topusko",
        "Staro Selo"
    ],
    "wof:name":"Staro Selo",
    "wof:placetype":"locality"
},
  "geometry": {"coordinates":[15.94361,45.23639],"type":"Point"}
}