{
  "type": "Feature",
  "properties": {
    "gn:admin1_code":"14",
    "gn:asciiname":"Staro Selo",
    "gn:cc2":"HR",
    "gn:country_code":"HR",
    "gn:dem":137,
    "gn:feature_class":"P",
    "gn:feature_code":"PPLL",
    "gn:name":"Staro Selo",
    "gn:population":0,
    "gn:timezone":"Europe/Zagreb",
    "iso:country":"HR",
    "name:bel_x_preferred":[
        "\u0421\u0442\u0430\u0440\u043e\u0435 \u0421\u044f\u043b\u043e"
    ],
    "name:bos_x_preferred":[
        "Staro Selo"
    ],
    "name:bul_x_preferred":[
        "\u0421\u0442\u0430\u0440\u043e \u0441\u0435\u043b\u043e"
    ],
    "name:ceb_x_preferred":[
        "Staro Selo"
    ],
    "name:deu_x_preferred":[
        "Staro Selo"
    ],
    "name:fra_x_preferred":[
        "Staro selo"
    ],
    "name:hrv_x_preferred":[
        "Staro Selo"
    ],
    "name:hun_x_preferred":[
        "Staro Selo"
    ],
    "name:nld_x_preferred":[
        "Staro Selo"
    ],
    "name:ron_x_preferred":[
        "Staro Selo"
    ],
    "name:rus_x_preferred":[
        "\u0421\u0442\u0430\u0440\u043e\u0435 \u0421\u0435\u043b\u043e"
    ],
    "name:slv_x_preferred":[
        "Staro Selo"
    ],
    "name:srp_x_preferred":[
        "\u0421\u0442\u0430\u0440\u043e \u0421\u0435\u043b\u043e"
    ],
    "name:swe_x_preferred":[
        "Staro Selo"
    ],
    "name:und_x_variant":[
        "Topusko Staro Selo",
        "Staro Selo Topusko"
    ],
    "wof:name":"Staro Selo",
    "wof:placetype":"locality"
},
  "geometry": {"coordinates":[15.94361,45.23639],"type":"Point"}
}