{
  "type": "Feature",
  "properties": {
    "gn:admin1_code":"15",
    "gn:asciiname":"Poljica Kozicka",
    "gn:cc2":"HR",
    "gn:country_code":"HR",
    "gn:dem":582,
    "gn:feature_class":"P",
    "gn:feature_code":"PPLL",
    "gn:name":"Poljica Kozi\u010dka",
    "gn:population":0,
    "gn:timezone":"Europe/Zagreb",
    "iso:country":"HR",
    "name:und_x_variant":[
        "Kozi\u010dka Poljica",
        "Poljica",
        "Poljica Kozi\u010dka"
    ],
    "wof:name":"Poljica Kozicka",
    "wof:placetype":"locality"
},
  "geometry": {"coordinates":[17.2825,43.31],"type":"Point"}
}