{
  "type": "Feature",
  "properties": {
    "gn:admin1_code":"14",
    "gn:admin2_code":"3187231.0",
    "gn:asciiname":"Dugo Selo Lasinjsko",
    "gn:cc2":"HR",
    "gn:country_code":"HR",
    "gn:dem":210,
    "gn:feature_class":"P",
    "gn:feature_code":"PPL",
    "gn:name":"Dugo Selo Lasinjsko",
    "gn:population":46,
    "gn:timezone":"Europe/Zagreb",
    "iso:country":"HR",
    "name:und_x_variant":[
        "Lasinjsko Dugo Selo",
        "Dugo Selo",
        "Dugo Selo Lasinjsko"
    ],
    "wof:name":"Dugo Selo Lasinjsko",
    "wof:placetype":"locality",
    "wof:population":46
},
  "geometry": {"coordinates":[15.88117,45.48132],"type":"Point"}
}