{
  "type": "Feature",
  "properties": {
    "gn:admin1_code":"14",
    "gn:admin2_code":"3187231.0",
    "gn:asciiname":"Dugo Selo Lasinjsko",
    "gn:cc2":"HR",
    "gn:country_code":"HR",
    "gn:dem":210,
    "gn:feature_class":"P",
    "gn:feature_code":"PPL",
    "gn:name":"Dugo Selo Lasinjsko",
    "gn:population":46,
    "gn:timezone":"Europe/Zagreb",
    "iso:country":"HR",
    "name:bos_x_preferred":[
        "Dugo Selo Lasinjsko"
    ],
    "name:fra_x_preferred":[
        "Dugo Selo Lasinjsko"
    ],
    "name:hrv_x_preferred":[
        "Dugo Selo"
    ],
    "name:hun_x_preferred":[
        "Dugo Selo"
    ],
    "name:nld_x_preferred":[
        "Dugo Selo"
    ],
    "name:slv_x_preferred":[
        "Dugo Selo Lasinjsko"
    ],
    "name:spa_x_preferred":[
        "Dugo Selo Lasinjsko"
    ],
    "name:srp_x_preferred":[
        "\u0414\u0443\u0433\u043e \u0421\u0435\u043b\u043e \u041b\u0430\u0441\u0438\u045a\u0441\u043a\u043e"
    ],
    "name:ukr_x_preferred":[
        "\u0414\u0443\u0433\u043e \u0421\u0435\u043b\u043e-\u041b\u0430\u0441\u0438\u043d\u0441\u044c\u043a\u043e"
    ],
    "name:und_x_variant":[
        "Lasinjsko Dugo Selo",
        "Dugo Selo",
        "Dugo Selo Lasinjsko"
    ],
    "wof:name":"Dugo Selo Lasinjsko",
    "wof:placetype":"locality",
    "wof:population":46
},
  "geometry": {"coordinates":[15.88117,45.48132],"type":"Point"}
}