{
  "type": "Feature",
  "properties": {
    "gn:admin1_code":"12.0",
    "gn:admin2_code":"11049442.0",
    "gn:asciiname":"Belej",
    "gn:cc2":"HR",
    "gn:country_code":"HR",
    "gn:dem":127,
    "gn:feature_class":"P",
    "gn:feature_code":"PPL",
    "gn:name":"Belej",
    "gn:population":55,
    "gn:timezone":"Europe/Zagreb",
    "iso:country":"HR",
    "name:und_x_variant":[
        "Bellei",
        "Belej"
    ],
    "wof:name":"Belej",
    "wof:placetype":"locality",
    "wof:population":55
},
  "geometry": {"coordinates":[14.4225,44.77917],"type":"Point"}
}