{
  "type": "Feature",
  "properties": {
    "gn:admin1_code":"07",
    "gn:admin2_code":"3186405.0",
    "gn:asciiname":"Petrusevec",
    "gn:country_code":"HR",
    "gn:dem":245,
    "gn:feature_class":"P",
    "gn:feature_code":"PPL",
    "gn:name":"Petru\u0161evec",
    "gn:population":135,
    "gn:timezone":"Europe/Zagreb",
    "iso:country":"HR",
    "wof:name":"Petrusevec",
    "wof:placetype":"locality",
    "wof:population":135
},
  "geometry": {"coordinates":[16.14175,46.12215],"type":"Point"}
}