{
  "type": "Feature",
  "properties": {
    "gn:admin1_code":"2.0",
    "gn:asciiname":"Marinci",
    "gn:country_code":"HR",
    "gn:dem":140,
    "gn:feature_class":"P",
    "gn:feature_code":"PPL",
    "gn:name":"Marinci",
    "gn:population":0,
    "gn:timezone":"Europe/Zagreb",
    "iso:country":"HR",
    "name:bos_x_preferred":[
        "Marinci"
    ],
    "name:fra_x_preferred":[
        "Marinci"
    ],
    "name:hrv_x_preferred":[
        "Marinci"
    ],
    "name:nld_x_preferred":[
        "Marinci"
    ],
    "name:slv_x_preferred":[
        "Marinci"
    ],
    "name:srp_x_preferred":[
        "\u041c\u0430\u0440\u0438\u043d\u0446\u0438"
    ],
    "wof:name":"Marinci",
    "wof:placetype":"locality"
},
  "geometry": {"coordinates":[17.98556,45.18556],"type":"Point"}
}