{
  "type": "Feature",
  "properties": {
    "gn:admin1_code":"15.0",
    "gn:asciiname":"Bazici",
    "gn:country_code":"HR",
    "gn:dem":299,
    "gn:feature_class":"P",
    "gn:feature_code":"PPL",
    "gn:name":"Bazi\u0107i",
    "gn:population":0,
    "gn:timezone":"Europe/Zagreb",
    "iso:country":"HR",
    "wof:name":"Bazici",
    "wof:placetype":"locality"
},
  "geometry": {"coordinates":[16.75806,43.67],"type":"Point"}
}