{
  "type": "Feature",
  "properties": {
    "gn:admin1_code":"13.0",
    "gn:asciiname":"Lake",
    "gn:country_code":"HR",
    "gn:dem":350,
    "gn:feature_class":"P",
    "gn:feature_code":"PPL",
    "gn:name":"Lake",
    "gn:population":0,
    "gn:timezone":"Europe/Zagreb",
    "iso:country":"HR",
    "wof:name":"Lake",
    "wof:placetype":"locality"
},
  "geometry": {"coordinates":[16.24111,44.01444],"type":"Point"}
}