{
  "type": "Feature",
  "properties": {
    "gn:admin1_code":"16",
    "gn:admin2_code":"11049315.0",
    "gn:asciiname":"Zamlaka",
    "gn:country_code":"HR",
    "gn:dem":158,
    "gn:feature_class":"P",
    "gn:feature_code":"PPL",
    "gn:name":"Zamlaka",
    "gn:population":445,
    "gn:timezone":"Europe/Zagreb",
    "iso:country":"HR",
    "name:bos_x_preferred":[
        "Zamlaka"
    ],
    "name:ceb_x_preferred":[
        "Zamlaka"
    ],
    "name:hrv_x_preferred":[
        "Zamlaka"
    ],
    "name:hun_x_preferred":[
        "Zamlaka"
    ],
    "name:nld_x_preferred":[
        "Zamlaka"
    ],
    "name:slv_x_preferred":[
        "Zamlaka"
    ],
    "name:spa_x_preferred":[
        "Zamlaka"
    ],
    "name:srp_x_preferred":[
        "\u0417\u0430\u043c\u043b\u0430\u043a\u0430"
    ],
    "name:swe_x_preferred":[
        "Zamlaka"
    ],
    "name:ukr_x_preferred":[
        "\u0417\u0430\u043c\u043b\u0430\u043a\u0430"
    ],
    "wof:name":"Zamlaka",
    "wof:placetype":"locality",
    "wof:population":445
},
  "geometry": {"coordinates":[16.49806,46.28917],"type":"Point"}
}