{
  "type": "Feature",
  "properties": {
    "gn:admin1_code":"8.0",
    "gn:asciiname":"Krst",
    "gn:country_code":"HR",
    "gn:dem":653,
    "gn:feature_class":"P",
    "gn:feature_code":"PPL",
    "gn:name":"Krst",
    "gn:population":0,
    "gn:timezone":"Europe/Zagreb",
    "iso:country":"HR",
    "wof:name":"Krst",
    "wof:placetype":"locality"
},
  "geometry": {"coordinates":[15.72611,44.74111],"type":"Point"}
}