{
  "type": "Feature",
  "properties": {
    "gn:admin1_code":"13.0",
    "gn:asciiname":"Citluk",
    "gn:country_code":"HR",
    "gn:dem":393,
    "gn:feature_class":"P",
    "gn:feature_code":"PPL",
    "gn:name":"\u010citluk",
    "gn:population":0,
    "gn:timezone":"Europe/Zagreb",
    "iso:country":"HR",
    "wof:name":"Citluk",
    "wof:placetype":"locality"
},
  "geometry": {"coordinates":[16.40667,43.95972],"type":"Point"}
}