{
  "type": "Feature",
  "properties": {
    "gn:admin1_code":"3.0",
    "gn:asciiname":"Vojnovo Selo",
    "gn:country_code":"HR",
    "gn:dem":84,
    "gn:feature_class":"P",
    "gn:feature_code":"PPL",
    "gn:name":"Vojnovo Selo",
    "gn:population":0,
    "gn:timezone":"Europe/Zagreb",
    "iso:country":"HR",
    "wof:name":"Vojnovo Selo",
    "wof:placetype":"locality"
},
  "geometry": {"coordinates":[17.89528,42.71722000000001],"type":"Point"}
}