{
  "type": "Feature",
  "properties": {
    "gn:admin1_code":"6.0",
    "gn:admin2_code":"11049370.0",
    "gn:asciiname":"Draganci",
    "gn:country_code":"HR",
    "gn:dem":112,
    "gn:feature_class":"P",
    "gn:feature_code":"PPL",
    "gn:name":"Draganci",
    "gn:population":0,
    "gn:timezone":"Europe/Zagreb",
    "iso:country":"HR",
    "wof:name":"Draganci",
    "wof:placetype":"locality"
},
  "geometry": {"coordinates":[17.18167,46.01889],"type":"Point"}
}