{
  "type": "Feature",
  "properties": {
    "gn:asciiname":"Filipini",
    "gn:country_code":"HR",
    "gn:dem":120,
    "gn:elevation":"0.0",
    "gn:feature_class":"P",
    "gn:feature_code":"PPL",
    "gn:name":"Filipini",
    "gn:population":43,
    "gn:timezone":"Europe/Zagreb",
    "iso:country":"HR",
    "wof:name":"Filipini",
    "wof:placetype":"locality",
    "wof:population":43
},
  "geometry": {"coordinates":[13.67121,45.2202],"type":"Point"}
}