{
  "type": "Feature",
  "properties": {
    "gn:admin1_code":"14.0",
    "gn:asciiname":"Kovacevici",
    "gn:country_code":"HR",
    "gn:dem":263,
    "gn:feature_class":"P",
    "gn:feature_code":"PPL",
    "gn:name":"Kova\u010devi\u0107i",
    "gn:population":0,
    "gn:timezone":"Europe/Zagreb",
    "iso:country":"HR",
    "wof:name":"Kovacevici",
    "wof:placetype":"locality"
},
  "geometry": {"coordinates":[16.43528,45.18167],"type":"Point"}
}