{
  "type": "Feature",
  "properties": {
    "gn:admin1_code":"03",
    "gn:admin2_code":"11054957.0",
    "gn:asciiname":"Soline",
    "gn:country_code":"HR",
    "gn:dem":85,
    "gn:feature_class":"P",
    "gn:feature_code":"PPL",
    "gn:name":"Soline",
    "gn:population":268,
    "gn:timezone":"Europe/Zagreb",
    "iso:country":"HR",
    "wof:name":"Soline",
    "wof:placetype":"locality",
    "wof:population":268
},
  "geometry": {"coordinates":[18.22222,42.61472],"type":"Point"}
}