{
  "type": "Feature",
  "properties": {
    "gn:admin1_code":"14",
    "gn:admin2_code":"3193419.0",
    "gn:asciiname":"Jabukovac",
    "gn:cc2":"HR",
    "gn:country_code":"HR",
    "gn:dem":166,
    "gn:feature_class":"P",
    "gn:feature_code":"PPL",
    "gn:name":"Jabukovac",
    "gn:population":141,
    "gn:timezone":"Europe/Zagreb",
    "iso:country":"HR",
    "name:bos_x_preferred":[
        "Jabukovac"
    ],
    "name:ceb_x_preferred":[
        "Jabukovac"
    ],
    "name:fra_x_preferred":[
        "Jabukovac"
    ],
    "name:hrv_x_preferred":[
        "Jabukovac"
    ],
    "name:hun_x_preferred":[
        "Jabukovac"
    ],
    "name:nld_x_preferred":[
        "Jabukovac"
    ],
    "name:slv_x_preferred":[
        "Jabukovac"
    ],
    "name:srp_x_preferred":[
        "\u0408\u0430\u0431\u0443\u043a\u043e\u0432\u0430\u0446"
    ],
    "name:swe_x_preferred":[
        "Jabukovac"
    ],
    "name:und_x_variant":[
        "Gornji Jabukovac",
        "Jabukovac"
    ],
    "wof:name":"Jabukovac",
    "wof:placetype":"locality",
    "wof:population":141
},
  "geometry": {"coordinates":[16.295,45.32861],"type":"Point"}
}