{
  "type": "Feature",
  "properties": {
    "gn:admin1_code":"14",
    "gn:admin2_code":"3193419.0",
    "gn:asciiname":"Jabukovac",
    "gn:cc2":"HR",
    "gn:country_code":"HR",
    "gn:dem":166,
    "gn:feature_class":"P",
    "gn:feature_code":"PPL",
    "gn:name":"Jabukovac",
    "gn:population":141,
    "gn:timezone":"Europe/Zagreb",
    "iso:country":"HR",
    "name:und_x_variant":[
        "Gornji Jabukovac",
        "Jabukovac"
    ],
    "wof:name":"Jabukovac",
    "wof:placetype":"locality",
    "wof:population":141
},
  "geometry": {"coordinates":[16.295,45.32861],"type":"Point"}
}