{
  "type": "Feature",
  "properties": {
    "gn:gn_country":"HR",
    "gn:gn_fcode":"PPL",
    "gn:gn_pop":0,
    "gn:population":716,
    "iso:country":"HR",
    "name:bos_x_preferred":[
        "Poljanec"
    ],
    "name:eng_x_preferred":[
        "Poljanec"
    ],
    "name:hrv_x_preferred":[
        "Poljanec"
    ],
    "name:hun_x_preferred":[
        "Poljanec"
    ],
    "name:nld_x_preferred":[
        "Poljanec"
    ],
    "name:slv_x_preferred":[
        "Poljanec"
    ],
    "name:spa_x_preferred":[
        "Poljanec"
    ],
    "name:srp_x_preferred":[
        "\u041f\u043e\u0459\u0430\u043d\u0435\u0446"
    ],
    "name:ukr_x_preferred":[
        "\u041f\u043e\u043b\u044f\u043d\u0435\u0446\u044c"
    ],
    "name:unk_x_variant":[
        "Poljanec"
    ],
    "qs_pg:aaroncc":"HR",
    "qs_pg:gn_country":"HR",
    "qs_pg:gn_fcode":"PPL",
    "qs_pg:gn_pop":0,
    "qs_pg:name":"Polj\u010dane",
    "qs_pg:name_adm0":"Slovenija",
    "qs_pg:name_adm1":"Slovenska Bistrica",
    "qs_pg:photos":32,
    "qs_pg:photos_1k":6,
    "qs_pg:photos_9k":1,
    "qs_pg:photos_9r":2,
    "qs_pg:photos_all":32,
    "qs_pg:photos_sr":2,
    "qs_pg:pop_sr":0,
    "qs_pg:qs_pg_placetype":"locality",
    "qs_pg:qs_pg_placetype_gp":"Town",
    "qs_pg:woe_adm0":23424945,
    "woe:adm0_id":23424945,
    "woe:name_adm0":"Slovenija",
    "woe:name_adm1":"Slovenska Bistrica",
    "woe:placetype":"Town",
    "wof:name":"Polj\u010dane",
    "wof:placetype":"locality",
    "wof:population":716
},
  "geometry": {"coordinates":[16.57361,46.26667],"type":"Point"}
}