{
  "type": "Feature",
  "properties": {
    "gn:admin1_code":"20",
    "gn:admin2_code":"3187264.0",
    "gn:asciiname":"Peskovec",
    "gn:country_code":"HR",
    "gn:dem":110,
    "gn:feature_class":"P",
    "gn:feature_code":"PPL",
    "gn:name":"Peskovec",
    "gn:population":323,
    "gn:timezone":"Europe/Zagreb",
    "iso:country":"HR",
    "wof:name":"Peskovec",
    "wof:placetype":"locality",
    "wof:population":323
},
  "geometry": {"coordinates":[16.32361,45.87306],"type":"Point"}
}