{
  "type": "Feature",
  "properties": {
    "gn:admin1_code":"03",
    "gn:admin2_code":"11054961.0",
    "gn:asciiname":"Dancanje",
    "gn:country_code":"HR",
    "gn:dem":352,
    "gn:feature_class":"P",
    "gn:feature_code":"PPL",
    "gn:name":"Dan\u010danje",
    "gn:population":27,
    "gn:timezone":"Europe/Zagreb",
    "iso:country":"HR",
    "wof:name":"Dancanje",
    "wof:placetype":"locality",
    "wof:population":27
},
  "geometry": {"coordinates":[17.56361,42.87472],"type":"Point"}
}