{
  "type": "Feature",
  "properties": {
    "gn:admin1_code":"3.0",
    "gn:admin2_code":"11054957.0",
    "gn:asciiname":"Martinovici",
    "gn:country_code":"HR",
    "gn:dem":164,
    "gn:feature_class":"P",
    "gn:feature_code":"PPL",
    "gn:name":"Martinovi\u0107i",
    "gn:population":126,
    "gn:timezone":"Europe/Zagreb",
    "iso:country":"HR",
    "wof:name":"Martinovici",
    "wof:placetype":"locality",
    "wof:population":126
},
  "geometry": {"coordinates":[18.18389,42.65056],"type":"Point"}
}