{
  "type": "Feature",
  "properties": {
    "gn:admin1_code":"03",
    "gn:admin2_code":"11055009.0",
    "gn:asciiname":"Doli",
    "gn:country_code":"HR",
    "gn:dem":5,
    "gn:feature_class":"P",
    "gn:feature_code":"PPL",
    "gn:name":"Doli",
    "gn:population":189,
    "gn:timezone":"Europe/Zagreb",
    "iso:country":"HR",
    "wof:name":"Doli",
    "wof:placetype":"locality",
    "wof:population":189
},
  "geometry": {"coordinates":[17.79389,42.80694],"type":"Point"}
}