{
  "type": "Feature",
  "properties": {
    "gn:admin1_code":"08",
    "gn:admin2_code":"11049290.0",
    "gn:asciiname":"Brlog",
    "gn:country_code":"HR",
    "gn:dem":432,
    "gn:feature_class":"P",
    "gn:feature_code":"PPLL",
    "gn:name":"Brlog",
    "gn:population":0,
    "gn:timezone":"Europe/Zagreb",
    "iso:country":"HR",
    "name:bul_x_preferred":[
        "\u0411\u044a\u0440\u043b\u043e\u0433"
    ],
    "name:fra_x_preferred":[
        "Brlog"
    ],
    "name:msa_x_preferred":[
        "Brlog"
    ],
    "name:por_x_preferred":[
        "Brlog"
    ],
    "name:slv_x_preferred":[
        "Brlog"
    ],
    "name:srp_x_preferred":[
        "\u0411\u0440\u043b\u043e\u0433"
    ],
    "wof:name":"Brlog",
    "wof:placetype":"locality"
},
  "geometry": {"coordinates":[15.13611,44.93361],"type":"Point"}
}