{
  "type": "Feature",
  "properties": {
    "gn:admin1_code":"08",
    "gn:admin2_code":"11049290.0",
    "gn:asciiname":"Brlog",
    "gn:country_code":"HR",
    "gn:dem":432,
    "gn:feature_class":"P",
    "gn:feature_code":"PPLL",
    "gn:name":"Brlog",
    "gn:population":0,
    "gn:timezone":"Europe/Zagreb",
    "iso:country":"HR",
    "wof:name":"Brlog",
    "wof:placetype":"locality"
},
  "geometry": {"coordinates":[15.13611,44.93361],"type":"Point"}
}