{
  "type": "Feature",
  "properties": {
    "gn:admin1_code":"08",
    "gn:admin2_code":"11049284.0",
    "gn:asciiname":"Letinac",
    "gn:country_code":"HR",
    "gn:dem":600,
    "gn:feature_class":"P",
    "gn:feature_code":"PPLL",
    "gn:name":"Letinac",
    "gn:population":0,
    "gn:timezone":"Europe/Zagreb",
    "iso:country":"HR",
    "wof:name":"Letinac",
    "wof:placetype":"locality"
},
  "geometry": {"coordinates":[15.22361,44.98194],"type":"Point"}
}