{
  "type": "Feature",
  "properties": {
    "gn:admin1_code":"8.0",
    "gn:admin2_code":"11049291.0",
    "gn:asciiname":"Kosinj Most",
    "gn:country_code":"HR",
    "gn:dem":510,
    "gn:feature_class":"P",
    "gn:feature_code":"PPL",
    "gn:name":"Kosinj Most",
    "gn:population":0,
    "gn:timezone":"Europe/Zagreb",
    "iso:country":"HR",
    "wof:name":"Kosinj Most",
    "wof:placetype":"locality"
},
  "geometry": {"coordinates":[15.27667,44.73639],"type":"Point"}
}