{
  "type": "Feature",
  "properties": {
    "gn:admin1_code":"19.0",
    "gn:asciiname":"Mali Ledenik",
    "gn:country_code":"HR",
    "gn:dem":227,
    "gn:feature_class":"P",
    "gn:feature_code":"PPL",
    "gn:name":"Mali Ledenik",
    "gn:population":0,
    "gn:timezone":"Europe/Zagreb",
    "iso:country":"HR",
    "wof:name":"Mali Ledenik",
    "wof:placetype":"locality"
},
  "geometry": {"coordinates":[15.4025,44.33194],"type":"Point"}
}