{
  "type": "Feature",
  "properties": {
    "gn:admin1_code":"19.0",
    "gn:asciiname":"Genda Vuckovici",
    "gn:country_code":"HR",
    "gn:dem":439,
    "gn:feature_class":"P",
    "gn:feature_code":"PPL",
    "gn:name":"Genda Vu\u010dkovi\u0107i",
    "gn:population":0,
    "gn:timezone":"Europe/Zagreb",
    "iso:country":"HR",
    "wof:name":"Genda Vuckovici",
    "wof:placetype":"locality"
},
  "geometry": {"coordinates":[15.77028,44.12278],"type":"Point"}
}