{
  "type": "Feature",
  "properties": {
    "gn:admin1_code":"10",
    "gn:admin2_code":"11054476.0",
    "gn:asciiname":"Stipanovci",
    "gn:country_code":"HR",
    "gn:dem":113,
    "gn:feature_class":"P",
    "gn:feature_code":"PPL",
    "gn:name":"Stipanovci",
    "gn:population":398,
    "gn:timezone":"Europe/Zagreb",
    "iso:country":"HR",
    "name:bos_x_preferred":[
        "Stipanovci"
    ],
    "name:ceb_x_preferred":[
        "Stipanovci"
    ],
    "name:hrv_x_preferred":[
        "Stipanovci"
    ],
    "name:slv_x_preferred":[
        "Stipanovci"
    ],
    "name:srp_x_preferred":[
        "\u0421\u0442\u0438\u043f\u0430\u043d\u043e\u0432\u0446\u0438"
    ],
    "name:swe_x_preferred":[
        "Stipanovci"
    ],
    "name:ukr_x_preferred":[
        "\u0421\u0442\u0438\u043f\u0430\u043d\u043e\u0432\u0446\u0456"
    ],
    "wof:name":"Stipanovci",
    "wof:placetype":"locality",
    "wof:population":398
},
  "geometry": {"coordinates":[18.18806,45.47361],"type":"Point"}
}