{
  "type": "Feature",
  "properties": {
    "gn:admin1_code":"10",
    "gn:admin2_code":"11054476.0",
    "gn:asciiname":"Stipanovci",
    "gn:country_code":"HR",
    "gn:dem":113,
    "gn:feature_class":"P",
    "gn:feature_code":"PPL",
    "gn:name":"Stipanovci",
    "gn:population":398,
    "gn:timezone":"Europe/Zagreb",
    "iso:country":"HR",
    "wof:name":"Stipanovci",
    "wof:placetype":"locality",
    "wof:population":398
},
  "geometry": {"coordinates":[18.18806,45.47361],"type":"Point"}
}