{
  "type": "Feature",
  "properties": {
    "gn:admin1_code":"13.0",
    "gn:asciiname":"Banjevacki Stanovi",
    "gn:country_code":"HR",
    "gn:dem":38,
    "gn:feature_class":"P",
    "gn:feature_code":"PPL",
    "gn:name":"Banjevacki Stanovi",
    "gn:population":0,
    "gn:timezone":"Europe/Zagreb",
    "iso:country":"HR",
    "wof:name":"Banjevacki Stanovi",
    "wof:placetype":"locality"
},
  "geometry": {"coordinates":[15.65444,43.8625],"type":"Point"}
}