{
  "type": "Feature",
  "properties": {
    "gn:admin1_code":"19.0",
    "gn:asciiname":"Podvrslje",
    "gn:country_code":"HR",
    "gn:dem":83,
    "gn:feature_class":"P",
    "gn:feature_code":"PPL",
    "gn:name":"Podvr\u0161lje",
    "gn:population":0,
    "gn:timezone":"Europe/Zagreb",
    "iso:country":"HR",
    "wof:name":"Podvrslje",
    "wof:placetype":"locality"
},
  "geometry": {"coordinates":[15.37111,44.03361],"type":"Point"}
}