{
  "type": "Feature",
  "properties": {
    "gn:admin1_code":"07",
    "gn:admin2_code":"11049014.0",
    "gn:asciiname":"Brlekovo",
    "gn:country_code":"HR",
    "gn:dem":186,
    "gn:feature_class":"P",
    "gn:feature_code":"PPL",
    "gn:name":"Brlekovo",
    "gn:population":56,
    "gn:timezone":"Europe/Zagreb",
    "iso:country":"HR",
    "wof:name":"Brlekovo",
    "wof:placetype":"locality",
    "wof:population":56
},
  "geometry": {"coordinates":[16.14333,46.07944000000001],"type":"Point"}
}