{
  "type": "Feature",
  "properties": {
    "gn:admin1_code":"5.0",
    "gn:admin2_code":"11049270.0",
    "gn:asciiname":"Duga Gora",
    "gn:country_code":"HR",
    "gn:dem":204,
    "gn:feature_class":"P",
    "gn:feature_code":"PPL",
    "gn:name":"Duga Gora",
    "gn:population":61,
    "gn:timezone":"Europe/Zagreb",
    "iso:country":"HR",
    "wof:name":"Duga Gora",
    "wof:placetype":"locality",
    "wof:population":61
},
  "geometry": {"coordinates":[15.34194,45.33861],"type":"Point"}
}