{
  "type": "Feature",
  "properties": {
    "gn:admin1_code":"07",
    "gn:admin2_code":"11049189.0",
    "gn:asciiname":"Mala Erpenja",
    "gn:cc2":"HR",
    "gn:country_code":"HR",
    "gn:dem":165,
    "gn:feature_class":"P",
    "gn:feature_code":"PPL",
    "gn:name":"Mala Erpenja",
    "gn:population":606,
    "gn:timezone":"Europe/Zagreb",
    "iso:country":"HR",
    "name:und_x_variant":[
        "Erpenye",
        "Male Erpenye",
        "Erpenyicze",
        "Mala Erpenja"
    ],
    "wof:name":"Mala Erpenja",
    "wof:placetype":"locality",
    "wof:population":606
},
  "geometry": {"coordinates":[15.78516,46.09609],"type":"Point"}
}