{
  "type": "Feature",
  "properties": {
    "gn:admin1_code":"11",
    "gn:admin2_code":"11049473.0",
    "gn:asciiname":"Ivanovci Pozeski",
    "gn:cc2":"HR",
    "gn:country_code":"HR",
    "gn:dem":155,
    "gn:feature_class":"P",
    "gn:feature_code":"PPL",
    "gn:name":"Ivanovci Po\u017ee\u0161ki",
    "gn:population":0,
    "gn:timezone":"Europe/Zagreb",
    "iso:country":"HR",
    "name:und_x_variant":[
        "Ivanovci",
        "Ivanovci Po\u017ee\u0161ki"
    ],
    "wof:name":"Ivanovci Pozeski",
    "wof:placetype":"locality"
},
  "geometry": {"coordinates":[17.96333,45.32694],"type":"Point"}
}