{
  "type": "Feature",
  "properties": {
    "gn:admin1_code":"10.0",
    "gn:admin2_code":"11054474.0",
    "gn:asciiname":"Novo Nevesinje",
    "gn:country_code":"HR",
    "gn:dem":87,
    "gn:feature_class":"P",
    "gn:feature_code":"PPL",
    "gn:name":"Novo Nevesinje",
    "gn:population":63,
    "gn:timezone":"Europe/Zagreb",
    "iso:country":"HR",
    "name:bos_x_preferred":[
        "Novo Nevesinje"
    ],
    "name:epo_x_preferred":[
        "Novo Nevesinje"
    ],
    "name:hrv_x_preferred":[
        "Novo Nevesinje"
    ],
    "name:nld_x_preferred":[
        "Novo Nevesinje"
    ],
    "name:slv_x_preferred":[
        "Novo Nevesinje"
    ],
    "name:srp_x_preferred":[
        "\u041d\u043e\u0432\u043e \u041d\u0435\u0432\u0435\u0441\u0438\u045a\u0435"
    ],
    "name:ukr_x_preferred":[
        "\u041d\u043e\u0432\u043e \u041d\u0435\u0432\u0435\u0441\u0438\u043d\u0454"
    ],
    "wof:name":"Novo Nevesinje",
    "wof:placetype":"locality",
    "wof:population":63
},
  "geometry": {"coordinates":[18.41556,45.73389],"type":"Point"}
}