{
  "type": "Feature",
  "properties": {
    "gn:admin1_code":"3.0",
    "gn:admin2_code":"11054972.0",
    "gn:asciiname":"Zvekovica",
    "gn:country_code":"HR",
    "gn:dem":107,
    "gn:feature_class":"P",
    "gn:feature_code":"PPL",
    "gn:name":"Zvekovica",
    "gn:population":570,
    "gn:timezone":"Europe/Zagreb",
    "iso:country":"HR",
    "name:bos_x_preferred":[
        "Zvekovica"
    ],
    "name:ceb_x_preferred":[
        "Zvekovica"
    ],
    "name:hrv_x_preferred":[
        "Zvekovica"
    ],
    "name:hun_x_preferred":[
        "Zvekovica"
    ],
    "name:slv_x_preferred":[
        "Zvekovica"
    ],
    "name:srp_x_preferred":[
        "\u0417\u0432\u0435\u043a\u043e\u0432\u0438\u0446\u0430"
    ],
    "name:swe_x_preferred":[
        "Zvekovica"
    ],
    "name:ukr_x_preferred":[
        "\u0417\u0432\u0435\u043a\u043e\u0432\u0438\u0446\u044f"
    ],
    "wof:name":"Zvekovica",
    "wof:placetype":"locality",
    "wof:population":570
},
  "geometry": {"coordinates":[18.23917,42.57667],"type":"Point"}
}