{
  "type": "Feature",
  "properties": {
    "gn:admin1_code":"19.0",
    "gn:asciiname":"Kruskovace",
    "gn:country_code":"HR",
    "gn:dem":417,
    "gn:feature_class":"P",
    "gn:feature_code":"PPL",
    "gn:name":"Kru\u0161kova\u010de",
    "gn:population":0,
    "gn:timezone":"Europe/Zagreb",
    "iso:country":"HR",
    "wof:name":"Kruskovace",
    "wof:placetype":"locality"
},
  "geometry": {"coordinates":[16.14027999999999,44.37306],"type":"Point"}
}