{
  "type": "Feature",
  "properties": {
    "gn:admin1_code":"15.0",
    "gn:asciiname":"Novo Naselje",
    "gn:country_code":"HR",
    "gn:dem":12,
    "gn:feature_class":"P",
    "gn:feature_code":"PPL",
    "gn:name":"Novo Naselje",
    "gn:population":0,
    "gn:timezone":"Europe/Zagreb",
    "iso:country":"HR",
    "name:bos_x_preferred":[
        "Novo Naselje"
    ],
    "name:fra_x_preferred":[
        "Novo Naselje"
    ],
    "name:rus_x_preferred":[
        "\u041d\u043e\u0432\u043e-\u041d\u0430\u0441\u0435\u043b\u0435"
    ],
    "name:slv_x_preferred":[
        "Novo Naselje"
    ],
    "name:srp_x_preferred":[
        "\u041d\u043e\u0432\u043e \u041d\u0430\u0441\u0435\u0459\u0435"
    ],
    "wof:name":"Novo Naselje",
    "wof:placetype":"locality"
},
  "geometry": {"coordinates":[17.11167,43.21333],"type":"Point"}
}