{
  "type": "Feature",
  "properties": {
    "gn:admin1_code":"15.0",
    "gn:asciiname":"Novo Naselje",
    "gn:country_code":"HR",
    "gn:dem":12,
    "gn:feature_class":"P",
    "gn:feature_code":"PPL",
    "gn:name":"Novo Naselje",
    "gn:population":0,
    "gn:timezone":"Europe/Zagreb",
    "iso:country":"HR",
    "wof:name":"Novo Naselje",
    "wof:placetype":"locality"
},
  "geometry": {"coordinates":[17.11167,43.21333],"type":"Point"}
}