{
  "type": "Feature",
  "properties": {
    "gn:admin1_code":"8.0",
    "gn:admin2_code":"11049285.0",
    "gn:asciiname":"Bubale",
    "gn:country_code":"HR",
    "gn:dem":587,
    "gn:feature_class":"P",
    "gn:feature_code":"PPL",
    "gn:name":"Bubale",
    "gn:population":0,
    "gn:timezone":"Europe/Zagreb",
    "iso:country":"HR",
    "wof:name":"Bubale",
    "wof:placetype":"locality"
},
  "geometry": {"coordinates":[15.98194,44.62806],"type":"Point"}
}