{
  "type": "Feature",
  "properties": {
    "gn:admin1_code":"14",
    "gn:admin2_code":"11049232.0",
    "gn:asciiname":"Popovaca",
    "gn:country_code":"HR",
    "gn:dem":127,
    "gn:feature_class":"P",
    "gn:feature_code":"PPLA2",
    "gn:name":"Popova\u010da",
    "gn:population":0,
    "gn:timezone":"Europe/Zagreb",
    "iso:country":"HR",
    "name:und_x_variant":[
        "Popovacha",
        "Popova\u010da"
    ],
    "wof:name":"Popovaca",
    "wof:placetype":"locality"
},
  "geometry": {"coordinates":[16.625,45.56972],"type":"Point"}
}