{
  "type": "Feature",
  "properties": {
    "gn:admin1_code":"14",
    "gn:admin2_code":"11049232.0",
    "gn:asciiname":"Popovaca",
    "gn:country_code":"HR",
    "gn:dem":127,
    "gn:feature_class":"P",
    "gn:feature_code":"PPLA2",
    "gn:name":"Popova\u010da",
    "gn:population":0,
    "gn:timezone":"Europe/Zagreb",
    "iso:country":"HR",
    "name:bos_x_preferred":[
        "Popova\u010da"
    ],
    "name:cat_x_preferred":[
        "Popova\u010da"
    ],
    "name:deu_x_preferred":[
        "Popova\u010da"
    ],
    "name:fra_x_preferred":[
        "Popova\u010da"
    ],
    "name:hrv_x_preferred":[
        "Popova\u010da"
    ],
    "name:hun_x_preferred":[
        "Popova\u010da"
    ],
    "name:ita_x_preferred":[
        "Popova\u010da"
    ],
    "name:nld_x_preferred":[
        "Popova\u010da"
    ],
    "name:pol_x_preferred":[
        "Gmina Popova\u010da"
    ],
    "name:ron_x_preferred":[
        "Comuna Popova\u010da"
    ],
    "name:rus_x_preferred":[
        "\u041f\u043e\u043f\u043e\u0432\u0430\u0447\u0430"
    ],
    "name:slv_x_preferred":[
        "Popova\u010da"
    ],
    "name:spa_x_preferred":[
        "Popova\u010da"
    ],
    "name:sqi_x_preferred":[
        "Popova\u00e7a"
    ],
    "name:srp_x_preferred":[
        "\u041f\u043e\u043f\u043e\u0432\u0430\u0447\u0430"
    ],
    "name:ukr_x_preferred":[
        "\u041f\u043e\u043f\u043e\u0432\u0430\u0447\u0430"
    ],
    "name:und_x_variant":[
        "Popovacha"
    ],
    "name:war_x_preferred":[
        "Popova\u010da"
    ],
    "wof:name":"Popovaca",
    "wof:placetype":"locality"
},
  "geometry": {"coordinates":[16.625,45.56972],"type":"Point"}
}