{
  "type": "Feature",
  "properties": {
    "gn:admin1_code":"11.0",
    "gn:admin2_code":"11049472.0",
    "gn:asciiname":"Bolomace",
    "gn:country_code":"HR",
    "gn:dem":219,
    "gn:feature_class":"P",
    "gn:feature_code":"PPL",
    "gn:name":"Boloma\u010de",
    "gn:population":22,
    "gn:timezone":"Europe/Zagreb",
    "iso:country":"HR",
    "wof:name":"Bolomace",
    "wof:placetype":"locality",
    "wof:population":22
},
  "geometry": {"coordinates":[17.52472,45.34556],"type":"Point"}
}