{
  "type": "Feature",
  "properties": {
    "gn:admin1_code":"8.0",
    "gn:asciiname":"Kolakovica",
    "gn:country_code":"HR",
    "gn:dem":558,
    "gn:feature_class":"P",
    "gn:feature_code":"PPL",
    "gn:name":"Kolakovica",
    "gn:population":0,
    "gn:timezone":"Europe/Zagreb",
    "iso:country":"HR",
    "wof:name":"Kolakovica",
    "wof:placetype":"locality"
},
  "geometry": {"coordinates":[15.32389,44.54889],"type":"Point"}
}