{
  "type": "Feature",
  "properties": {
    "gn:admin1_code":"8.0",
    "gn:admin2_code":"11049291.0",
    "gn:asciiname":"Pecani",
    "gn:country_code":"HR",
    "gn:dem":588,
    "gn:feature_class":"P",
    "gn:feature_code":"PPL",
    "gn:name":"Pe\u0107ani",
    "gn:population":0,
    "gn:timezone":"Europe/Zagreb",
    "iso:country":"HR",
    "wof:name":"Pecani",
    "wof:placetype":"locality"
},
  "geometry": {"coordinates":[15.38111,44.68806],"type":"Point"}
}