{
  "type": "Feature",
  "properties": {
    "gn:admin1_code":"20.0",
    "gn:admin2_code":"11049004.0",
    "gn:asciiname":"Otok Svibovski",
    "gn:country_code":"HR",
    "gn:dem":103,
    "gn:feature_class":"P",
    "gn:feature_code":"PPL",
    "gn:name":"Otok Svibovski",
    "gn:population":270,
    "gn:timezone":"Europe/Zagreb",
    "iso:country":"HR",
    "wof:name":"Otok Svibovski",
    "wof:placetype":"locality",
    "wof:population":270
},
  "geometry": {"coordinates":[16.15939,45.7806],"type":"Point"}
}