{
  "type": "Feature",
  "properties": {
    "gn:admin1_code":"3.0",
    "gn:admin2_code":"11054961.0",
    "gn:asciiname":"Gorica",
    "gn:country_code":"HR",
    "gn:dem":4,
    "gn:feature_class":"P",
    "gn:feature_code":"PPL",
    "gn:name":"Gorica",
    "gn:population":0,
    "gn:timezone":"Europe/Zagreb",
    "iso:country":"HR",
    "wof:name":"Gorica",
    "wof:placetype":"locality"
},
  "geometry": {"coordinates":[17.68361,42.83444],"type":"Point"}
}