{
  "type": "Feature",
  "properties": {
    "gn:admin1_code":"05",
    "gn:admin2_code":"11049268.0",
    "gn:asciiname":"Kruskovaca",
    "gn:country_code":"HR",
    "gn:dem":362,
    "gn:feature_class":"P",
    "gn:feature_code":"PPL",
    "gn:name":"Kru\u0161kova\u010da",
    "gn:population":46,
    "gn:timezone":"Europe/Zagreb",
    "iso:country":"HR",
    "wof:name":"Kruskovaca",
    "wof:placetype":"locality",
    "wof:population":46
},
  "geometry": {"coordinates":[15.73556,45.09583],"type":"Point"}
}