{
  "type": "Feature",
  "properties": {
    "gn:admin1_code":"19.0",
    "gn:admin2_code":"11054328.0",
    "gn:asciiname":"Kastel Zegarski",
    "gn:country_code":"HR",
    "gn:dem":86,
    "gn:feature_class":"P",
    "gn:feature_code":"PPL",
    "gn:name":"Ka\u0161tel \u017degarski",
    "gn:population":135,
    "gn:timezone":"Europe/Zagreb",
    "iso:country":"HR",
    "name:bos_x_preferred":[
        "Ka\u0161tel \u017degarski"
    ],
    "name:ceb_x_preferred":[
        "Ka\u0161tel \u017degarski"
    ],
    "name:fra_x_preferred":[
        "Ka\u0161tel \u017degarski"
    ],
    "name:hrv_x_preferred":[
        "Ka\u0161tel \u017degarski"
    ],
    "name:hun_x_preferred":[
        "Ka\u0161tel \u017degarski"
    ],
    "name:ita_x_preferred":[
        "Ka\u0161tel \u017degarski"
    ],
    "name:slv_x_preferred":[
        "Ka\u0161tel \u017degarski"
    ],
    "name:srp_x_preferred":[
        "\u041a\u0430\u0448\u0442\u0435\u043b \u0416\u0435\u0433\u0430\u0440\u0441\u043a\u0438"
    ],
    "name:swe_x_preferred":[
        "Ka\u0161tel \u017degarski"
    ],
    "name:ukr_x_preferred":[
        "\u041a\u0430\u0448\u0442\u0435\u043b-\u0416\u0435\u0433\u0430\u0440\u0441\u044c\u043a\u0438\u0439"
    ],
    "name:und_x_variant":[
        "Ka\u0161tel \u017degarski"
    ],
    "wof:name":"Kastel Zegarski",
    "wof:placetype":"locality",
    "wof:population":135
},
  "geometry": {"coordinates":[15.84806,44.15639],"type":"Point"}
}