{
  "type": "Feature",
  "properties": {
    "gn:admin1_code":"5.0",
    "gn:admin2_code":"11049271.0",
    "gn:asciiname":"Blanka",
    "gn:country_code":"HR",
    "gn:dem":337,
    "gn:feature_class":"P",
    "gn:feature_code":"PPL",
    "gn:name":"Blanka",
    "gn:population":0,
    "gn:timezone":"Europe/Zagreb",
    "iso:country":"HR",
    "wof:name":"Blanka",
    "wof:placetype":"locality"
},
  "geometry": {"coordinates":[15.285,45.19],"type":"Point"}
}