{
  "type": "Feature",
  "properties": {
    "gn:admin1_code":"5.0",
    "gn:admin2_code":"11049271.0",
    "gn:asciiname":"Blanka",
    "gn:country_code":"HR",
    "gn:dem":337,
    "gn:feature_class":"P",
    "gn:feature_code":"PPL",
    "gn:name":"Blanka",
    "gn:population":0,
    "gn:timezone":"Europe/Zagreb",
    "iso:country":"HR",
    "name:ara_x_preferred":[
        "\u0628\u0644\u0627\u0646\u0643\u0627"
    ],
    "name:fra_x_preferred":[
        "Blanka"
    ],
    "name:ita_x_preferred":[
        "Blanka"
    ],
    "name:jpn_x_preferred":[
        "\u30d6\u30e9\u30f3\u30ab"
    ],
    "name:nld_x_preferred":[
        "Blanka"
    ],
    "name:por_x_preferred":[
        "Blanka"
    ],
    "name:rus_x_preferred":[
        "\u0411\u043b\u0430\u043d\u043a\u0430"
    ],
    "name:spa_x_preferred":[
        "Blanka"
    ],
    "name:tha_x_preferred":[
        "\u0e1a\u0e25\u0e31\u0e07\u0e01\u0e49\u0e32"
    ],
    "name:urd_x_preferred":[
        "\u0628\u0644\u0627\u0646\u06a9\u0627"
    ],
    "name:vie_x_preferred":[
        "Blanka"
    ],
    "wof:name":"Blanka",
    "wof:placetype":"locality"
},
  "geometry": {"coordinates":[15.285,45.19],"type":"Point"}
}