{
  "type": "Feature",
  "properties": {
    "gn:admin1_code":"13.0",
    "gn:asciiname":"Jovici",
    "gn:country_code":"HR",
    "gn:dem":238,
    "gn:feature_class":"P",
    "gn:feature_code":"PPL",
    "gn:name":"Jovi\u0107i",
    "gn:population":0,
    "gn:timezone":"Europe/Zagreb",
    "iso:country":"HR",
    "wof:name":"Jovici",
    "wof:placetype":"locality"
},
  "geometry": {"coordinates":[16.24667,43.94611],"type":"Point"}
}