{
  "type": "Feature",
  "properties": {
    "gn:admin1_code":"8.0",
    "gn:admin2_code":"11049285.0",
    "gn:asciiname":"Bijelo Brdo",
    "gn:country_code":"HR",
    "gn:dem":599,
    "gn:feature_class":"P",
    "gn:feature_code":"PPL",
    "gn:name":"Bijelo Brdo",
    "gn:population":0,
    "gn:timezone":"Europe/Zagreb",
    "iso:country":"HR",
    "name:bos_x_preferred":[
        "Bijelo Brdo"
    ],
    "name:ceb_x_preferred":[
        "Bijelo Brdo"
    ],
    "name:fra_x_preferred":[
        "Bijelo Brdo"
    ],
    "name:hrv_x_preferred":[
        "Bijelo Brdo"
    ],
    "name:slv_x_preferred":[
        "Bijelo Brdo"
    ],
    "name:srp_x_preferred":[
        "\u0411\u0438\u0458\u0435\u043b\u043e \u0411\u0440\u0434\u043e"
    ],
    "name:swe_x_preferred":[
        "Bijelo Brdo"
    ],
    "wof:name":"Bijelo Brdo",
    "wof:placetype":"locality"
},
  "geometry": {"coordinates":[16.10778,44.4775],"type":"Point"}
}