{
  "type": "Feature",
  "properties": {
    "gn:admin1_code":"3.0",
    "gn:admin2_code":"11054972.0",
    "gn:asciiname":"Siljesci",
    "gn:country_code":"HR",
    "gn:dem":482,
    "gn:feature_class":"P",
    "gn:feature_code":"PPL",
    "gn:name":"Silje\u0161ci",
    "gn:population":0,
    "gn:timezone":"Europe/Zagreb",
    "iso:country":"HR",
    "wof:name":"Siljesci",
    "wof:placetype":"locality"
},
  "geometry": {"coordinates":[18.31306,42.58139],"type":"Point"}
}