{
  "type": "Feature",
  "properties": {
    "gn:admin1_code":"12.0",
    "gn:asciiname":"Peski",
    "gn:country_code":"HR",
    "gn:dem":40,
    "gn:feature_class":"P",
    "gn:feature_code":"PPL",
    "gn:name":"Peski",
    "gn:population":0,
    "gn:timezone":"Europe/Zagreb",
    "iso:country":"HR",
    "wof:name":"Peski",
    "wof:placetype":"locality"
},
  "geometry": {"coordinates":[14.47944,44.6275],"type":"Point"}
}