{
  "type": "Feature",
  "properties": {
    "gn:admin1_code":"14",
    "gn:admin2_code":"3200597.0",
    "gn:asciiname":"Mali Gradac",
    "gn:cc2":"HR",
    "gn:country_code":"HR",
    "gn:dem":199,
    "gn:feature_class":"P",
    "gn:feature_code":"PPL",
    "gn:name":"Mali Gradac",
    "gn:population":143,
    "gn:timezone":"Europe/Zagreb",
    "iso:country":"HR",
    "name:und_x_variant":[
        "Gradac Mali",
        "Mali Gradac"
    ],
    "wof:name":"Mali Gradac",
    "wof:placetype":"locality",
    "wof:population":143
},
  "geometry": {"coordinates":[16.21968,45.26873],"type":"Point"}
}