{
  "type": "Feature",
  "properties": {
    "gn:admin1_code":"14",
    "gn:admin2_code":"3200597.0",
    "gn:asciiname":"Mali Gradac",
    "gn:cc2":"HR",
    "gn:country_code":"HR",
    "gn:dem":199,
    "gn:feature_class":"P",
    "gn:feature_code":"PPL",
    "gn:name":"Mali Gradac",
    "gn:population":143,
    "gn:timezone":"Europe/Zagreb",
    "iso:country":"HR",
    "name:bos_x_preferred":[
        "Mali Gradac"
    ],
    "name:ceb_x_preferred":[
        "Mali Gradac"
    ],
    "name:fra_x_preferred":[
        "Mali Gradac"
    ],
    "name:hrv_x_preferred":[
        "Mali Gradac"
    ],
    "name:hun_x_preferred":[
        "Mali Gradac"
    ],
    "name:nld_x_preferred":[
        "Mali Gradac"
    ],
    "name:slv_x_preferred":[
        "Mali Gradac"
    ],
    "name:spa_x_preferred":[
        "Mali Gradac"
    ],
    "name:srp_x_preferred":[
        "\u041c\u0430\u043b\u0438 \u0413\u0440\u0430\u0434\u0430\u0446"
    ],
    "name:swe_x_preferred":[
        "Mali Gradac"
    ],
    "name:ukr_x_preferred":[
        "\u041c\u0430\u043b\u0438\u0439 \u0413\u0440\u0430\u0434\u0430\u0446\u044c"
    ],
    "name:und_x_variant":[
        "Gradac Mali"
    ],
    "wof:name":"Mali Gradac",
    "wof:placetype":"locality",
    "wof:population":143
},
  "geometry": {"coordinates":[16.21968,45.26873],"type":"Point"}
}