{
  "type": "Feature",
  "properties": {
    "gn:gn_country":"HR",
    "gn:gn_fcode":"PPL",
    "gn:gn_pop":929,
    "gn:population":288,
    "iso:country":"HR",
    "name:bos_x_preferred":[
        "Lupoglav"
    ],
    "name:ceb_x_preferred":[
        "Lupoglav"
    ],
    "name:deu_x_preferred":[
        "Lupoglav"
    ],
    "name:eng_x_preferred":[
        "Lupoglav"
    ],
    "name:fra_x_preferred":[
        "Lupoglav"
    ],
    "name:hrv_x_preferred":[
        "Lupoglav"
    ],
    "name:hun_x_preferred":[
        "Lupoglav"
    ],
    "name:ita_x_preferred":[
        "Lupogliano"
    ],
    "name:lat_x_preferred":[
        "Lupulianum"
    ],
    "name:nld_x_preferred":[
        "Lupoglav"
    ],
    "name:pol_x_preferred":[
        "Lupoglav"
    ],
    "name:ron_x_preferred":[
        "Comuna Lupoglav"
    ],
    "name:rus_x_preferred":[
        "\u041b\u0443\u043f\u043e\u0433\u043b\u0430\u0432"
    ],
    "name:slv_x_preferred":[
        "Lupoglav"
    ],
    "name:spa_x_preferred":[
        "Lupoglav"
    ],
    "name:srp_x_preferred":[
        "\u041b\u0443\u043f\u043e\u0433\u043b\u0430\u0432"
    ],
    "name:swe_x_preferred":[
        "Lupoglav"
    ],
    "name:ukr_x_preferred":[
        "\u041b\u0443\u043f\u043e\u0433\u043b\u0430\u0432"
    ],
    "name:unk_x_variant":[
        "Castel Lupogliano"
    ],
    "name:war_x_preferred":[
        "Lupoglav"
    ],
    "qs_pg:aaroncc":"HR",
    "qs_pg:gn_country":"HR",
    "qs_pg:gn_fcode":"PPL",
    "qs_pg:gn_pop":929,
    "qs_pg:name":"Lupoglav",
    "qs_pg:name_adm0":"Hrvatska",
    "qs_pg:name_adm1":"Istarska",
    "qs_pg:photos":14,
    "qs_pg:photos_1k":3,
    "qs_pg:photos_9k":1,
    "qs_pg:photos_9r":1,
    "qs_pg:photos_all":14,
    "qs_pg:photos_sr":1,
    "qs_pg:pop_sr":2,
    "qs_pg:qs_pg_placetype":"locality",
    "qs_pg:qs_pg_placetype_gp":"Town",
    "qs_pg:woe_adm0":23424843,
    "woe:adm0_id":23424843,
    "woe:name_adm0":"Hrvatska",
    "woe:name_adm1":"Istarska",
    "woe:placetype":"Town",
    "wof:name":"Lupoglav",
    "wof:placetype":"locality",
    "wof:population":288
},
  "geometry": {"coordinates":[14.10444,45.35111],"type":"Point"}
}