{
  "type": "Feature",
  "properties": {
    "gn:admin1_code":"3.0",
    "gn:admin2_code":"11054960.0",
    "gn:asciiname":"Zenjevka",
    "gn:country_code":"HR",
    "gn:dem":214,
    "gn:feature_class":"P",
    "gn:feature_code":"PPL",
    "gn:name":"\u017denjevka",
    "gn:population":0,
    "gn:timezone":"Europe/Zagreb",
    "iso:country":"HR",
    "wof:name":"Zenjevka",
    "wof:placetype":"locality"
},
  "geometry": {"coordinates":[17.2375,43.00306],"type":"Point"}
}