{
  "type": "Feature",
  "properties": {
    "gn:admin1_code":"16",
    "gn:asciiname":"Strmec Podravski",
    "gn:cc2":"HR",
    "gn:country_code":"HR",
    "gn:dem":184,
    "gn:feature_class":"P",
    "gn:feature_code":"PPL",
    "gn:name":"Strmec Podravski",
    "gn:population":663,
    "gn:timezone":"Europe/Zagreb",
    "iso:country":"HR",
    "name:bos_x_preferred":[
        "Strmec Podravski"
    ],
    "name:hrv_x_preferred":[
        "Strmec Podravski"
    ],
    "name:hun_x_preferred":[
        "Strmec Podravski"
    ],
    "name:nld_x_preferred":[
        "Strmec Podravski"
    ],
    "name:slv_x_preferred":[
        "Strmec Podravski"
    ],
    "name:spa_x_preferred":[
        "Strmec Podravski"
    ],
    "name:srp_x_preferred":[
        "\u0421\u0442\u0440\u043c\u0435\u0446 \u041f\u043e\u0434\u0440\u0430\u0432\u0441\u043a\u0438"
    ],
    "name:ukr_x_preferred":[
        "\u0421\u0442\u0440\u043c\u0435\u0446\u044c-\u041f\u043e\u0434\u0440\u0430\u0432\u0441\u044c\u043a\u0438\u0439"
    ],
    "name:und_x_variant":[
        "Podravski Strmec",
        "Strmec",
        "Strmec Podravski"
    ],
    "wof:name":"Strmec Podravski",
    "wof:placetype":"locality",
    "wof:population":663
},
  "geometry": {"coordinates":[16.21417000000001,46.36444],"type":"Point"}
}