{
  "type": "Feature",
  "properties": {
    "gn:admin1_code":"16",
    "gn:asciiname":"Strmec Podravski",
    "gn:cc2":"HR",
    "gn:country_code":"HR",
    "gn:dem":184,
    "gn:feature_class":"P",
    "gn:feature_code":"PPL",
    "gn:name":"Strmec Podravski",
    "gn:population":663,
    "gn:timezone":"Europe/Zagreb",
    "iso:country":"HR",
    "name:und_x_variant":[
        "Podravski Strmec",
        "Strmec",
        "Strmec Podravski"
    ],
    "wof:name":"Strmec Podravski",
    "wof:placetype":"locality",
    "wof:population":663
},
  "geometry": {"coordinates":[16.21417000000001,46.36444],"type":"Point"}
}