{
  "type": "Feature",
  "properties": {
    "gn:admin1_code":"03",
    "gn:asciiname":"Uskoplje",
    "gn:country_code":"HR",
    "gn:dem":207,
    "gn:feature_class":"P",
    "gn:feature_code":"PPLL",
    "gn:name":"Uskoplje",
    "gn:population":0,
    "gn:timezone":"Europe/Zagreb",
    "iso:country":"HR",
    "name:bos_x_preferred":[
        "Uskoplje"
    ],
    "name:fra_x_preferred":[
        "Uskoplje"
    ],
    "name:hrv_x_preferred":[
        "Uskoplje"
    ],
    "name:hun_x_preferred":[
        "Uskoplje"
    ],
    "name:ita_x_preferred":[
        "Uskoplje"
    ],
    "name:nld_x_preferred":[
        "Uskoplje"
    ],
    "name:srp_x_preferred":[
        "\u0423\u0441\u043a\u043e\u043f\u0459\u0435"
    ],
    "name:ukr_x_preferred":[
        "\u0423\u0441\u043a\u043e\u043f\u043b\u0454"
    ],
    "wof:name":"Uskoplje",
    "wof:placetype":"locality"
},
  "geometry": {"coordinates":[18.25222,42.58056],"type":"Point"}
}