{
  "type": "Feature",
  "properties": {
    "gn:admin1_code":"03",
    "gn:asciiname":"Uskoplje",
    "gn:country_code":"HR",
    "gn:dem":207,
    "gn:feature_class":"P",
    "gn:feature_code":"PPLL",
    "gn:name":"Uskoplje",
    "gn:population":0,
    "gn:timezone":"Europe/Zagreb",
    "iso:country":"HR",
    "wof:name":"Uskoplje",
    "wof:placetype":"locality"
},
  "geometry": {"coordinates":[18.25222,42.58056],"type":"Point"}
}