{
  "type": "Feature",
  "properties": {
    "gn:admin1_code":"01",
    "gn:admin2_code":"3200709.0",
    "gn:asciiname":"Kaniska Iva",
    "gn:country_code":"HR",
    "gn:dem":130,
    "gn:feature_class":"P",
    "gn:feature_code":"PPL",
    "gn:name":"Kani\u0161ka Iva",
    "gn:population":466,
    "gn:timezone":"Europe/Zagreb",
    "iso:country":"HR",
    "name:und_x_variant":[
        "Kani\u0161ka Iva"
    ],
    "wof:name":"Kaniska Iva",
    "wof:placetype":"locality",
    "wof:population":466
},
  "geometry": {"coordinates":[16.92694,45.53778],"type":"Point"}
}