{
  "type": "Feature",
  "properties": {
    "gn:admin1_code":"14.0",
    "gn:asciiname":"Borojevici",
    "gn:country_code":"HR",
    "gn:dem":246,
    "gn:feature_class":"P",
    "gn:feature_code":"PPL",
    "gn:name":"Borojevi\u0107i",
    "gn:population":0,
    "gn:timezone":"Europe/Zagreb",
    "iso:country":"HR",
    "wof:name":"Borojevici",
    "wof:placetype":"locality"
},
  "geometry": {"coordinates":[16.26833,45.06778],"type":"Point"}
}