{
  "type": "Feature",
  "properties": {
    "gn:admin1_code":"04",
    "gn:asciiname":"Gamboci",
    "gn:cc2":"HR",
    "gn:country_code":"HR",
    "gn:dem":101,
    "gn:feature_class":"P",
    "gn:feature_code":"PPL",
    "gn:name":"Gamboci",
    "gn:population":0,
    "gn:timezone":"Europe/Zagreb",
    "iso:country":"HR",
    "name:und_x_variant":[
        "Gambozzi",
        "Gamboc",
        "Gamboc I Dio",
        "Gamboci"
    ],
    "wof:name":"Gamboci",
    "wof:placetype":"locality"
},
  "geometry": {"coordinates":[13.62278,45.42861],"type":"Point"}
}