{
  "type": "Feature",
  "properties": {
    "gn:admin1_code":"05",
    "gn:admin2_code":"11049268.0",
    "gn:asciiname":"Glinica",
    "gn:country_code":"HR",
    "gn:dem":186,
    "gn:feature_class":"P",
    "gn:feature_code":"PPLL",
    "gn:name":"Glinica",
    "gn:population":0,
    "gn:timezone":"Europe/Zagreb",
    "iso:country":"HR",
    "name:bos_x_preferred":[
        "Glinica"
    ],
    "name:ceb_x_preferred":[
        "Glinica"
    ],
    "name:deu_x_preferred":[
        "Glinica"
    ],
    "name:fra_x_preferred":[
        "Glinica"
    ],
    "name:hrv_x_preferred":[
        "Glinica"
    ],
    "name:pol_x_preferred":[
        "Glinica"
    ],
    "name:srp_x_preferred":[
        "\u0413\u043b\u0438\u043d\u0438\u0446\u0430"
    ],
    "name:swe_x_preferred":[
        "Glinica"
    ],
    "name:ukr_x_preferred":[
        "\u0490\u043b\u0456\u043d\u0438\u0446\u044f"
    ],
    "wof:name":"Glinica",
    "wof:placetype":"locality"
},
  "geometry": {"coordinates":[15.65194,45.20556],"type":"Point"}
}