{
  "type": "Feature",
  "properties": {
    "gn:admin1_code":"3.0",
    "gn:asciiname":"Milosevic",
    "gn:country_code":"HR",
    "gn:dem":100,
    "gn:feature_class":"P",
    "gn:feature_code":"PPL",
    "gn:name":"Milo\u0161evi\u0107",
    "gn:population":0,
    "gn:timezone":"Europe/Zagreb",
    "iso:country":"HR",
    "wof:name":"Milosevic",
    "wof:placetype":"locality"
},
  "geometry": {"coordinates":[18.02444,42.69417],"type":"Point"}
}