{
  "type": "Feature",
  "properties": {
    "gn:admin1_code":"5.0",
    "gn:asciiname":"Zorici",
    "gn:country_code":"HR",
    "gn:dem":183,
    "gn:feature_class":"P",
    "gn:feature_code":"PPL",
    "gn:name":"Zori\u0107i",
    "gn:population":0,
    "gn:timezone":"Europe/Zagreb",
    "iso:country":"HR",
    "wof:name":"Zorici",
    "wof:placetype":"locality"
},
  "geometry": {"coordinates":[15.80944,45.22528],"type":"Point"}
}