{
  "type": "Feature",
  "properties": {
    "gn:admin1_code":"12",
    "gn:admin2_code":"11049435.0",
    "gn:asciiname":"Jelenje",
    "gn:country_code":"HR",
    "gn:dem":315,
    "gn:feature_class":"P",
    "gn:feature_code":"PPLA2",
    "gn:name":"Jelenje",
    "gn:population":0,
    "gn:timezone":"Europe/Zagreb",
    "iso:country":"HR",
    "name:und_x_variant":[
        "Gellegne",
        "Jelenje"
    ],
    "wof:name":"Jelenje",
    "wof:placetype":"locality"
},
  "geometry": {"coordinates":[14.45111,45.38611],"type":"Point"}
}