{
  "type": "Feature",
  "properties": {
    "gn:admin1_code":"20.0",
    "gn:admin2_code":"11049004.0",
    "gn:asciiname":"Otok Nartski",
    "gn:country_code":"HR",
    "gn:dem":100,
    "gn:feature_class":"P",
    "gn:feature_code":"PPL",
    "gn:name":"Otok Nartski",
    "gn:population":199,
    "gn:timezone":"Europe/Zagreb",
    "iso:country":"HR",
    "wof:name":"Otok Nartski",
    "wof:placetype":"locality",
    "wof:population":199
},
  "geometry": {"coordinates":[16.16398,45.76917],"type":"Point"}
}