{
  "type": "Feature",
  "properties": {
    "gn:admin1_code":"14",
    "gn:asciiname":"Donji Dobretin",
    "gn:country_code":"HR",
    "gn:dem":167,
    "gn:feature_class":"P",
    "gn:feature_code":"PPLL",
    "gn:name":"Donji Dobretin",
    "gn:population":0,
    "gn:timezone":"Europe/Zagreb",
    "iso:country":"HR",
    "wof:name":"Donji Dobretin",
    "wof:placetype":"locality"
},
  "geometry": {"coordinates":[16.30444,45.00806],"type":"Point"}
}