{
  "type": "Feature",
  "properties": {
    "gn:admin1_code":"08",
    "gn:admin2_code":"11049293.0",
    "gn:asciiname":"Velike Brisnice",
    "gn:cc2":"HR",
    "gn:country_code":"HR",
    "gn:dem":531,
    "gn:feature_class":"P",
    "gn:feature_code":"PPL",
    "gn:name":"Velike Brisnice",
    "gn:population":0,
    "gn:timezone":"Europe/Zagreb",
    "iso:country":"HR",
    "name:und_x_variant":[
        "Brisnice Velike",
        "Velike Brisnice"
    ],
    "wof:name":"Velike Brisnice",
    "wof:placetype":"locality"
},
  "geometry": {"coordinates":[14.92528,44.78306],"type":"Point"}
}