{
  "type": "Feature",
  "properties": {
    "gn:admin1_code":"12",
    "gn:admin2_code":"11049435.0",
    "gn:asciiname":"Podkilavac",
    "gn:cc2":"HR",
    "gn:country_code":"HR",
    "gn:dem":304,
    "gn:feature_class":"P",
    "gn:feature_code":"PPL",
    "gn:name":"Podkilavac",
    "gn:population":332,
    "gn:timezone":"Europe/Zagreb",
    "iso:country":"HR",
    "name:und_x_variant":[
        "Potkilavac",
        "Podkilavac"
    ],
    "wof:name":"Podkilavac",
    "wof:placetype":"locality",
    "wof:population":332
},
  "geometry": {"coordinates":[14.46528,45.39972],"type":"Point"}
}