{
  "type": "Feature",
  "properties": {
    "gn:admin1_code":"20",
    "gn:asciiname":"Gornji Dragonozec",
    "gn:country_code":"HR",
    "gn:dem":185,
    "gn:feature_class":"P",
    "gn:feature_code":"PPL",
    "gn:name":"Gornji Dragono\u017eec",
    "gn:population":0,
    "gn:timezone":"Europe/Zagreb",
    "iso:country":"HR",
    "name:bos_x_preferred":[
        "Gornji Dragono\u017eec"
    ],
    "name:hrv_x_preferred":[
        "Gornji Dragono\u017eec"
    ],
    "name:nld_x_preferred":[
        "Gornji Dragono\u017eec"
    ],
    "name:slv_x_preferred":[
        "Gornji Dragono\u017eec"
    ],
    "name:ukr_x_preferred":[
        "\u0413\u043e\u0440\u043d\u0456\u0439 \u0414\u0440\u0430\u0433\u043e\u043d\u043e\u0436\u0435\u0446\u044c"
    ],
    "wof:name":"Gornji Dragonozec",
    "wof:placetype":"locality"
},
  "geometry": {"coordinates":[15.93498,45.64441],"type":"Point"}
}