{
  "type": "Feature",
  "properties": {
    "gn:admin1_code":"10.0",
    "gn:admin2_code":"11054458.0",
    "gn:asciiname":"Bracevci",
    "gn:country_code":"HR",
    "gn:dem":126,
    "gn:feature_class":"P",
    "gn:feature_code":"PPL",
    "gn:name":"Bra\u010devci",
    "gn:population":209,
    "gn:timezone":"Europe/Zagreb",
    "iso:country":"HR",
    "name:bos_x_preferred":[
        "Bra\u010devci"
    ],
    "name:fra_x_preferred":[
        "Bra\u010devci"
    ],
    "name:hrv_x_preferred":[
        "Bra\u010devci"
    ],
    "name:slv_x_preferred":[
        "Bra\u010devci"
    ],
    "name:srp_x_preferred":[
        "\u0411\u0440\u0430\u0447\u0435\u0432\u0446\u0438"
    ],
    "name:ukr_x_preferred":[
        "\u0411\u0440\u0430\u0447\u0435\u0432\u0446\u0456"
    ],
    "wof:name":"Bracevci",
    "wof:placetype":"locality",
    "wof:population":209
},
  "geometry": {"coordinates":[18.2825,45.42972],"type":"Point"}
}