{
  "type": "Feature",
  "properties": {
    "gn:gn_country":"HR",
    "gn:gn_fcode":"PPL",
    "gn:gn_pop":3871,
    "gn:population":3871,
    "iso:country":"HR",
    "name:bos_x_preferred":[
        "Preko"
    ],
    "name:deu_x_preferred":[
        "Preko"
    ],
    "name:eng_x_preferred":[
        "Preko"
    ],
    "name:fra_x_preferred":[
        "Preko"
    ],
    "name:hrv_x_preferred":[
        "Preko"
    ],
    "name:hun_x_preferred":[
        "Preko"
    ],
    "name:ita_x_preferred":[
        "Oltre"
    ],
    "name:lat_x_preferred":[
        "Ultra"
    ],
    "name:nld_x_preferred":[
        "Preko"
    ],
    "name:por_x_preferred":[
        "Preko"
    ],
    "name:ron_x_preferred":[
        "Comuna Preko"
    ],
    "name:rus_x_preferred":[
        "\u041f\u0440\u0435\u043a\u043e"
    ],
    "name:slv_x_preferred":[
        "Preko"
    ],
    "name:spa_x_preferred":[
        "Preko"
    ],
    "name:srp_x_preferred":[
        "\u041f\u0440\u0435\u043a\u043e"
    ],
    "name:swe_x_preferred":[
        "Preko"
    ],
    "name:unk_x_variant":[
        "Oltre"
    ],
    "name:war_x_preferred":[
        "Preko"
    ],
    "qs_pg:aaroncc":"HR",
    "qs_pg:gn_country":"HR",
    "qs_pg:gn_fcode":"PPL",
    "qs_pg:gn_pop":3871,
    "qs_pg:name":"Preko",
    "qs_pg:name_adm0":"Hrvatska",
    "qs_pg:name_adm1":"Zadarsko-Kninska",
    "qs_pg:photos":186,
    "qs_pg:photos_1k":38,
    "qs_pg:photos_9k":1,
    "qs_pg:photos_9r":4,
    "qs_pg:photos_all":186,
    "qs_pg:photos_sr":4,
    "qs_pg:pop_sr":4,
    "qs_pg:qs_pg_placetype":"locality",
    "qs_pg:qs_pg_placetype_gp":"Town",
    "qs_pg:woe_adm0":23424843,
    "woe:adm0_id":23424843,
    "woe:name_adm0":"Hrvatska",
    "woe:name_adm1":"Zadarsko-Kninska",
    "woe:placetype":"Town",
    "wof:name":"Preko",
    "wof:placetype":"locality",
    "wof:population":3871
},
  "geometry": {"coordinates":[15.1875,44.08111],"type":"Point"}
}