{
  "type": "Feature",
  "properties": {
    "gn:admin1_code":"8.0",
    "gn:admin2_code":"11049291.0",
    "gn:asciiname":"Uremovici",
    "gn:cc2":"HR",
    "gn:country_code":"HR",
    "gn:dem":618,
    "gn:feature_class":"P",
    "gn:feature_code":"PPL",
    "gn:name":"Uremovi\u0107i",
    "gn:population":0,
    "gn:timezone":"Europe/Zagreb",
    "iso:country":"HR",
    "name:und_x_variant":[
        "Uremovi\u0107",
        "Uremovi\u0107i"
    ],
    "wof:name":"Uremovici",
    "wof:placetype":"locality"
},
  "geometry": {"coordinates":[15.40583,44.70278],"type":"Point"}
}