{
  "type": "Feature",
  "properties": {
    "gn:admin1_code":"04",
    "gn:admin2_code":"11129785.0",
    "gn:asciiname":"Prhati",
    "gn:cc2":"HR",
    "gn:country_code":"HR",
    "gn:dem":331,
    "gn:feature_class":"P",
    "gn:feature_code":"PPL",
    "gn:name":"Prhati",
    "gn:population":0,
    "gn:timezone":"Europe/Zagreb",
    "iso:country":"HR",
    "name:und_x_variant":[
        "Perkat",
        "Percati",
        "Prhati"
    ],
    "wof:name":"Prhati",
    "wof:placetype":"locality"
},
  "geometry": {"coordinates":[13.78639,45.28472],"type":"Point"}
}