{
  "type": "Feature",
  "properties": {
    "gn:admin1_code":"15.0",
    "gn:asciiname":"Donji Kunci",
    "gn:country_code":"HR",
    "gn:dem":472,
    "gn:feature_class":"P",
    "gn:feature_code":"PPL",
    "gn:name":"Donji Kunci",
    "gn:population":0,
    "gn:timezone":"Europe/Zagreb",
    "iso:country":"HR",
    "wof:name":"Donji Kunci",
    "wof:placetype":"locality"
},
  "geometry": {"coordinates":[16.54806,43.78806],"type":"Point"}
}