{
  "type": "Feature",
  "properties": {
    "gn:admin1_code":"12",
    "gn:admin2_code":"11072235.0",
    "gn:asciiname":"Grizane",
    "gn:country_code":"HR",
    "gn:dem":288,
    "gn:feature_class":"P",
    "gn:feature_code":"PPL",
    "gn:name":"Gri\u017eane",
    "gn:population":0,
    "gn:timezone":"Europe/Zagreb",
    "iso:country":"HR",
    "name:bos_x_preferred":[
        "Gri\u017eane-Belgrad"
    ],
    "name:deu_x_preferred":[
        "Gri\u017eane"
    ],
    "name:ell_x_preferred":[
        "\u0393\u03ba\u03c1\u03b9\u03b6\u03ac\u03bd\u03b5-\u039c\u03c0\u03b5\u03bb\u03b3\u03ba\u03c1\u03ac\u03bd\u03c4"
    ],
    "name:hrv_x_preferred":[
        "Gri\u017eane-Belgrad"
    ],
    "name:hun_x_preferred":[
        "Gri\u017eane-Belgrad"
    ],
    "name:nld_x_preferred":[
        "Gri\u017eane"
    ],
    "name:slv_x_preferred":[
        "Gri\u017eane-Belgrad"
    ],
    "name:spa_x_preferred":[
        "Gri\u017eane-Belgrad"
    ],
    "name:ukr_x_preferred":[
        "\u0413\u0440\u0438\u0436\u0430\u043d\u0438-\u0411\u0435\u043b\u0433\u0440\u0430\u0434"
    ],
    "wof:name":"Grizane",
    "wof:placetype":"locality"
},
  "geometry": {"coordinates":[14.72167,45.20083],"type":"Point"}
}