{
  "type": "Feature",
  "properties": {
    "gn:admin1_code":"12",
    "gn:admin2_code":"11072235.0",
    "gn:asciiname":"Grizane",
    "gn:country_code":"HR",
    "gn:dem":288,
    "gn:feature_class":"P",
    "gn:feature_code":"PPL",
    "gn:name":"Gri\u017eane",
    "gn:population":0,
    "gn:timezone":"Europe/Zagreb",
    "iso:country":"HR",
    "name:und_x_variant":[
        "Gri\u017eane"
    ],
    "wof:name":"Grizane",
    "wof:placetype":"locality"
},
  "geometry": {"coordinates":[14.72167,45.20083],"type":"Point"}
}