{
  "type": "Feature",
  "properties": {
    "gn:admin1_code":"10",
    "gn:admin2_code":"11054484.0",
    "gn:asciiname":"Glozde",
    "gn:cc2":"HR",
    "gn:country_code":"HR",
    "gn:dem":90,
    "gn:feature_class":"P",
    "gn:feature_code":"PPL",
    "gn:name":"Glo\u017e\u0111e",
    "gn:population":0,
    "gn:timezone":"Europe/Zagreb",
    "iso:country":"HR",
    "name:und_x_variant":[
        "Pu\u0161tara Glo\u017e\u0111e",
        "Glo\u017e\u0111e"
    ],
    "wof:name":"Glozde",
    "wof:placetype":"locality"
},
  "geometry": {"coordinates":[18.10472,45.72917],"type":"Point"}
}