{
  "type": "Feature",
  "properties": {
    "gn:admin1_code":"19",
    "gn:asciiname":"Maun",
    "gn:cc2":"HR",
    "gn:country_code":"HR",
    "gn:dem":20,
    "gn:feature_class":"P",
    "gn:feature_code":"PPL",
    "gn:name":"Maun",
    "gn:population":0,
    "gn:timezone":"Europe/Zagreb",
    "iso:country":"HR",
    "name:bul_x_preferred":[
        "\u041c\u0430\u0443\u043d"
    ],
    "name:ceb_x_preferred":[
        "Maun"
    ],
    "name:hun_x_preferred":[
        "Maun"
    ],
    "name:nld_x_preferred":[
        "Maun"
    ],
    "name:rus_x_preferred":[
        "\u041c\u0430\u0443\u043d"
    ],
    "name:swe_x_preferred":[
        "Maun"
    ],
    "name:ukr_x_preferred":[
        "\u041c\u0430\u0443\u043d"
    ],
    "name:und_x_variant":[
        "Maon"
    ],
    "wof:name":"Maun",
    "wof:placetype":"locality"
},
  "geometry": {"coordinates":[14.91194,44.43722],"type":"Point"}
}