{
  "type": "Feature",
  "properties": {
    "gn:admin1_code":"13.0",
    "gn:asciiname":"Segetin",
    "gn:country_code":"HR",
    "gn:dem":301,
    "gn:feature_class":"P",
    "gn:feature_code":"PPL",
    "gn:name":"Segetin",
    "gn:population":0,
    "gn:timezone":"Europe/Zagreb",
    "iso:country":"HR",
    "wof:name":"Segetin",
    "wof:placetype":"locality"
},
  "geometry": {"coordinates":[16.23722,44.07056],"type":"Point"}
}