{
  "type": "Feature",
  "properties": {
    "gn:admin1_code":"10.0",
    "gn:admin2_code":"11054465.0",
    "gn:asciiname":"Vucjak Fericanacki",
    "gn:cc2":"HR",
    "gn:country_code":"HR",
    "gn:dem":143,
    "gn:feature_class":"P",
    "gn:feature_code":"PPL",
    "gn:name":"Vu\u010djak Feri\u010dana\u010dki",
    "gn:population":270,
    "gn:timezone":"Europe/Zagreb",
    "iso:country":"HR",
    "name:und_x_variant":[
        "Vu\u010djak Feri\u010danski",
        "Vu\u010djak Feri\u010dana\u010dki"
    ],
    "wof:name":"Vucjak Fericanacki",
    "wof:placetype":"locality",
    "wof:population":270
},
  "geometry": {"coordinates":[18.00472000000001,45.52],"type":"Point"}
}