{
  "type": "Feature",
  "properties": {
    "gn:admin1_code":"04",
    "gn:asciiname":"Merisce",
    "gn:cc2":"HR",
    "gn:country_code":"HR",
    "gn:dem":207,
    "gn:feature_class":"P",
    "gn:feature_code":"PPL",
    "gn:name":"Meri\u0161\u0107e",
    "gn:population":0,
    "gn:timezone":"Europe/Zagreb",
    "iso:country":"HR",
    "name:und_x_variant":[
        "Merischie",
        "Meri\u0161\u0107e"
    ],
    "wof:name":"Merisce",
    "wof:placetype":"locality"
},
  "geometry": {"coordinates":[13.6975,45.44722],"type":"Point"}
}