{
  "type": "Feature",
  "properties": {
    "gn:admin1_code":"19",
    "gn:admin2_code":"11049512.0",
    "gn:asciiname":"Bukovic",
    "gn:country_code":"HR",
    "gn:dem":245,
    "gn:feature_class":"P",
    "gn:feature_code":"PPL",
    "gn:name":"Bukovi\u0107",
    "gn:population":526,
    "gn:timezone":"Europe/Zagreb",
    "iso:country":"HR",
    "wof:name":"Bukovic",
    "wof:placetype":"locality",
    "wof:population":526
},
  "geometry": {"coordinates":[15.63333,44.03333],"type":"Point"}
}