{
  "type": "Feature",
  "properties": {
    "gn:admin1_code":"14.0",
    "gn:asciiname":"Gaje",
    "gn:country_code":"HR",
    "gn:dem":141,
    "gn:feature_class":"P",
    "gn:feature_code":"PPL",
    "gn:name":"Gaje",
    "gn:population":0,
    "gn:timezone":"Europe/Zagreb",
    "iso:country":"HR",
    "wof:name":"Gaje",
    "wof:placetype":"locality"
},
  "geometry": {"coordinates":[16.81417,45.19611],"type":"Point"}
}