{
  "type": "Feature",
  "properties": {
    "gn:admin1_code":"5.0",
    "gn:admin2_code":"11049277.0",
    "gn:asciiname":"Dragasi",
    "gn:cc2":"HR",
    "gn:country_code":"HR",
    "gn:dem":397,
    "gn:feature_class":"P",
    "gn:feature_code":"PPL",
    "gn:name":"Draga\u0161i",
    "gn:population":0,
    "gn:timezone":"Europe/Zagreb",
    "iso:country":"HR",
    "name:und_x_variant":[
        "Crkovici",
        "Draga\u0161i"
    ],
    "wof:name":"Dragasi",
    "wof:placetype":"locality"
},
  "geometry": {"coordinates":[15.35972,45.10194],"type":"Point"}
}