{
  "type": "Feature",
  "properties": {
    "gn:admin1_code":"19",
    "gn:asciiname":"Olib",
    "gn:cc2":"HR",
    "gn:country_code":"HR",
    "gn:dem":20,
    "gn:feature_class":"P",
    "gn:feature_code":"PPL",
    "gn:name":"Olib",
    "gn:population":140,
    "gn:timezone":"Europe/Zagreb",
    "iso:country":"HR",
    "name:bul_x_preferred":[
        "\u041e\u043b\u0438\u0431"
    ],
    "name:ces_x_preferred":[
        "Olib"
    ],
    "name:deu_x_preferred":[
        "Olib"
    ],
    "name:ell_x_preferred":[
        "\u038c\u03bb\u03b9\u03bc\u03c0"
    ],
    "name:fin_x_preferred":[
        "Olib"
    ],
    "name:fra_x_preferred":[
        "Olib"
    ],
    "name:hrv_x_preferred":[
        "Olib"
    ],
    "name:ind_x_preferred":[
        "Olib"
    ],
    "name:ita_x_preferred":[
        "Ulbo"
    ],
    "name:jpn_x_preferred":[
        "\u30aa\u30ea\u30d6\u5cf6"
    ],
    "name:kor_x_preferred":[
        "\uc62c\ub9ac\ube0c\uc12c"
    ],
    "name:lat_x_preferred":[
        "Aloepus"
    ],
    "name:nld_x_preferred":[
        "Olib"
    ],
    "name:nno_x_preferred":[
        "Olib"
    ],
    "name:nor_x_preferred":[
        "Olib"
    ],
    "name:pol_x_preferred":[
        "Olib"
    ],
    "name:por_x_preferred":[
        "Olib"
    ],
    "name:rus_x_preferred":[
        "\u041e\u043b\u0438\u0431"
    ],
    "name:slv_x_preferred":[
        "Olib"
    ],
    "name:spa_x_preferred":[
        "Olib"
    ],
    "name:srp_x_preferred":[
        "\u041e\u043b\u0438\u0431"
    ],
    "name:swe_x_preferred":[
        "Olib"
    ],
    "name:tur_x_preferred":[
        "Olib"
    ],
    "name:ukr_x_preferred":[
        "\u041e\u043b\u0438\u0431"
    ],
    "name:zho_x_preferred":[
        "\u5967\u5229\u5e03\u5cf6"
    ],
    "wof:name":"Olib",
    "wof:placetype":"locality",
    "wof:population":140
},
  "geometry": {"coordinates":[14.78194,44.375],"type":"Point"}
}