{
  "type": "Feature",
  "properties": {
    "gn:admin1_code":"19",
    "gn:asciiname":"Olib",
    "gn:cc2":"HR",
    "gn:country_code":"HR",
    "gn:dem":20,
    "gn:feature_class":"P",
    "gn:feature_code":"PPL",
    "gn:name":"Olib",
    "gn:population":140,
    "gn:timezone":"Europe/Zagreb",
    "iso:country":"HR",
    "name:und_x_variant":[
        "Ulbo",
        "Olib"
    ],
    "wof:name":"Olib",
    "wof:placetype":"locality",
    "wof:population":140
},
  "geometry": {"coordinates":[14.78194,44.375],"type":"Point"}
}