{
  "type": "Feature",
  "properties": {
    "gn:admin1_code":"8.0",
    "gn:asciiname":"Fortica",
    "gn:country_code":"HR",
    "gn:dem":460,
    "gn:feature_class":"P",
    "gn:feature_code":"PPL",
    "gn:name":"Fortica",
    "gn:population":0,
    "gn:timezone":"Europe/Zagreb",
    "iso:country":"HR",
    "wof:name":"Fortica",
    "wof:placetype":"locality"
},
  "geometry": {"coordinates":[15.23056,44.87444],"type":"Point"}
}