{
  "type": "Feature",
  "properties": {
    "gn:admin1_code":"11.0",
    "gn:admin2_code":"11049475.0",
    "gn:asciiname":"Golo Brdo",
    "gn:country_code":"HR",
    "gn:dem":262,
    "gn:feature_class":"P",
    "gn:feature_code":"PPL",
    "gn:name":"Golo Brdo",
    "gn:population":325,
    "gn:timezone":"Europe/Zagreb",
    "iso:country":"HR",
    "name:bos_x_preferred":[
        "Golo Brdo"
    ],
    "name:ceb_x_preferred":[
        "Golo Brdo"
    ],
    "name:fra_x_preferred":[
        "Golo Brdo"
    ],
    "name:hrv_x_preferred":[
        "Golo Brdo"
    ],
    "name:hun_x_preferred":[
        "Golo Brdo"
    ],
    "name:nld_x_preferred":[
        "Golo Brdo"
    ],
    "name:rus_x_preferred":[
        "\u0413\u043e\u043b\u043e-\u0411\u0440\u0434\u043e"
    ],
    "name:slv_x_preferred":[
        "Golo Brdo"
    ],
    "name:srp_x_preferred":[
        "\u0413\u043e\u043b\u043e \u0411\u0440\u0434\u043e"
    ],
    "name:swe_x_preferred":[
        "Golo Brdo"
    ],
    "wof:name":"Golo Brdo",
    "wof:placetype":"locality",
    "wof:population":325
},
  "geometry": {"coordinates":[17.70083,45.44056],"type":"Point"}
}