{
  "type": "Feature",
  "properties": {
    "gn:admin1_code":"11.0",
    "gn:admin2_code":"11049475.0",
    "gn:asciiname":"Golo Brdo",
    "gn:country_code":"HR",
    "gn:dem":262,
    "gn:feature_class":"P",
    "gn:feature_code":"PPL",
    "gn:name":"Golo Brdo",
    "gn:population":325,
    "gn:timezone":"Europe/Zagreb",
    "iso:country":"HR",
    "wof:name":"Golo Brdo",
    "wof:placetype":"locality",
    "wof:population":325
},
  "geometry": {"coordinates":[17.70083,45.44056],"type":"Point"}
}