{
  "type": "Feature",
  "properties": {
    "gn:admin1_code":"12",
    "gn:admin2_code":"3202102.0",
    "gn:asciiname":"Malo Selo",
    "gn:country_code":"HR",
    "gn:dem":685,
    "gn:feature_class":"P",
    "gn:feature_code":"PPL",
    "gn:name":"Malo Selo",
    "gn:population":62,
    "gn:timezone":"Europe/Zagreb",
    "iso:country":"HR",
    "name:bos_x_preferred":[
        "Malo Selo"
    ],
    "name:fra_x_preferred":[
        "Malo Selo"
    ],
    "name:hrv_x_preferred":[
        "Malo Selo"
    ],
    "name:hun_x_preferred":[
        "Malo Selo"
    ],
    "name:srp_x_preferred":[
        "\u041c\u0430\u043b\u043e \u0421\u0435\u043b\u043e"
    ],
    "wof:name":"Malo Selo",
    "wof:placetype":"locality",
    "wof:population":62
},
  "geometry": {"coordinates":[14.70611,45.43],"type":"Point"}
}