{
  "type": "Feature",
  "properties": {
    "gn:admin1_code":"14.0",
    "gn:asciiname":"Podunavci",
    "gn:country_code":"HR",
    "gn:dem":258,
    "gn:feature_class":"P",
    "gn:feature_code":"PPL",
    "gn:name":"Podunavci",
    "gn:population":0,
    "gn:timezone":"Europe/Zagreb",
    "iso:country":"HR",
    "name:ceb_x_preferred":[
        "Podunavci"
    ],
    "name:fra_x_preferred":[
        "Podunavci"
    ],
    "name:hun_x_preferred":[
        "Podunavci"
    ],
    "name:msa_x_preferred":[
        "Podunavci"
    ],
    "name:nld_x_preferred":[
        "Podunavci"
    ],
    "name:por_x_preferred":[
        "Podunavci"
    ],
    "name:slv_x_preferred":[
        "Podunavci"
    ],
    "name:srp_x_preferred":[
        "\u041f\u043e\u0434\u0443\u043d\u0430\u0432\u0446\u0438"
    ],
    "wof:name":"Podunavci",
    "wof:placetype":"locality"
},
  "geometry": {"coordinates":[16.13306,45.23556],"type":"Point"}
}