{
  "type": "Feature",
  "properties": {
    "gn:admin1_code":"15.0",
    "gn:asciiname":"Turica Staje",
    "gn:country_code":"HR",
    "gn:dem":820,
    "gn:feature_class":"P",
    "gn:feature_code":"PPL",
    "gn:name":"Turi\u0107a Staje",
    "gn:population":0,
    "gn:timezone":"Europe/Zagreb",
    "iso:country":"HR",
    "wof:name":"Turica Staje",
    "wof:placetype":"locality"
},
  "geometry": {"coordinates":[17.28194,43.2725],"type":"Point"}
}