{
  "type": "Feature",
  "properties": {
    "gn:admin1_code":"19.0",
    "gn:asciiname":"Zekici",
    "gn:country_code":"HR",
    "gn:dem":846,
    "gn:feature_class":"P",
    "gn:feature_code":"PPL",
    "gn:name":"Zeki\u0107i",
    "gn:population":0,
    "gn:timezone":"Europe/Zagreb",
    "iso:country":"HR",
    "wof:name":"Zekici",
    "wof:placetype":"locality"
},
  "geometry": {"coordinates":[15.96722,44.25278],"type":"Point"}
}