{
  "type": "Feature",
  "properties": {
    "gn:admin1_code":"02",
    "gn:admin2_code":"11049480.0",
    "gn:asciiname":"Dubocac",
    "gn:country_code":"HR",
    "gn:dem":84,
    "gn:feature_class":"P",
    "gn:feature_code":"PPL",
    "gn:name":"Dubo\u010dac",
    "gn:population":202,
    "gn:timezone":"Europe/Zagreb",
    "iso:country":"HR",
    "wof:name":"Dubocac",
    "wof:placetype":"locality",
    "wof:population":202
},
  "geometry": {"coordinates":[17.86583,45.0525],"type":"Point"}
}