{
  "type": "Feature",
  "properties": {
    "gn:admin1_code":"10.0",
    "gn:admin2_code":"11054471.0",
    "gn:asciiname":"Borojevci",
    "gn:country_code":"HR",
    "gn:dem":257,
    "gn:feature_class":"P",
    "gn:feature_code":"PPL",
    "gn:name":"Borojevci",
    "gn:population":0,
    "gn:timezone":"Europe/Zagreb",
    "iso:country":"HR",
    "name:bos_x_preferred":[
        "Borojevci"
    ],
    "name:hrv_x_preferred":[
        "Borojevci"
    ],
    "name:slv_x_preferred":[
        "Borojevci"
    ],
    "name:ukr_x_preferred":[
        "\u0411\u043e\u0440\u043e\u0454\u0432\u0446\u0456"
    ],
    "wof:name":"Borojevci",
    "wof:placetype":"locality"
},
  "geometry": {"coordinates":[18.10583,45.28528],"type":"Point"}
}