{
  "type": "Feature",
  "properties": {
    "gn:admin1_code":"16",
    "gn:asciiname":"Cestica",
    "gn:country_code":"HR",
    "gn:dem":193,
    "gn:feature_class":"P",
    "gn:feature_code":"PPLA2",
    "gn:name":"Cestica",
    "gn:population":504,
    "gn:timezone":"Europe/Zagreb",
    "iso:country":"HR",
    "name:bos_x_preferred":[
        "Cestica"
    ],
    "name:fra_x_preferred":[
        "Cestica"
    ],
    "name:hrv_x_preferred":[
        "Cestica"
    ],
    "name:hun_x_preferred":[
        "Cestica"
    ],
    "name:ita_x_preferred":[
        "Cestica"
    ],
    "name:nld_x_preferred":[
        "Cestica"
    ],
    "name:pol_x_preferred":[
        "Gmina Cestica"
    ],
    "name:ron_x_preferred":[
        "Comuna Cestica"
    ],
    "name:rus_x_preferred":[
        "\u0426\u0435\u0441\u0442\u0438\u0446\u0430"
    ],
    "name:slv_x_preferred":[
        "Cestica"
    ],
    "name:spa_x_preferred":[
        "Cestica"
    ],
    "name:srp_x_preferred":[
        "\u0426\u0435\u0441\u0442\u0438\u0446\u0430"
    ],
    "name:ukr_x_preferred":[
        "\u0426\u0435\u0441\u0442\u0438\u0446\u044f"
    ],
    "name:war_x_preferred":[
        "Cestica"
    ],
    "wof:name":"Cestica",
    "wof:placetype":"locality",
    "wof:population":504
},
  "geometry": {"coordinates":[16.12528,46.37167],"type":"Point"}
}