{
  "type": "Feature",
  "properties": {
    "gn:admin1_code":"16",
    "gn:asciiname":"Cestica",
    "gn:country_code":"HR",
    "gn:dem":193,
    "gn:feature_class":"P",
    "gn:feature_code":"PPLA2",
    "gn:name":"Cestica",
    "gn:population":504,
    "gn:timezone":"Europe/Zagreb",
    "iso:country":"HR",
    "wof:name":"Cestica",
    "wof:placetype":"locality",
    "wof:population":504
},
  "geometry": {"coordinates":[16.12528,46.37167],"type":"Point"}
}