{
  "type": "Feature",
  "properties": {
    "gn:admin1_code":"19",
    "gn:admin2_code":"11049512.0",
    "gn:asciiname":"Vuksic",
    "gn:country_code":"HR",
    "gn:dem":149,
    "gn:feature_class":"P",
    "gn:feature_code":"PPL",
    "gn:name":"Vuk\u0161i\u0107",
    "gn:population":513,
    "gn:timezone":"Europe/Zagreb",
    "iso:country":"HR",
    "wof:name":"Vuksic",
    "wof:placetype":"locality",
    "wof:population":513
},
  "geometry": {"coordinates":[15.72528,43.94444],"type":"Point"}
}