{
  "type": "Feature",
  "properties": {
    "gn:admin1_code":"10",
    "gn:admin2_code":"11054458.0",
    "gn:asciiname":"Bucje Gorjansko",
    "gn:cc2":"HR",
    "gn:country_code":"HR",
    "gn:dem":127,
    "gn:feature_class":"P",
    "gn:feature_code":"PPL",
    "gn:name":"Bu\u010dje Gorjansko",
    "gn:population":73,
    "gn:timezone":"Europe/Zagreb",
    "iso:country":"HR",
    "name:und_x_variant":[
        "Bu\u010dje",
        "Bu\u010dje Gorjansko"
    ],
    "wof:name":"Bucje Gorjansko",
    "wof:placetype":"locality",
    "wof:population":73
},
  "geometry": {"coordinates":[18.25139,45.42861],"type":"Point"}
}