{
  "type": "Feature",
  "properties": {
    "gn:admin1_code":"14.0",
    "gn:asciiname":"Drumovi",
    "gn:country_code":"HR",
    "gn:dem":154,
    "gn:feature_class":"P",
    "gn:feature_code":"PPL",
    "gn:name":"Drumovi",
    "gn:population":0,
    "gn:timezone":"Europe/Zagreb",
    "iso:country":"HR",
    "wof:name":"Drumovi",
    "wof:placetype":"locality"
},
  "geometry": {"coordinates":[16.94222,45.39861],"type":"Point"}
}