{
  "type": "Feature",
  "properties": {
    "gn:admin1_code":"04",
    "gn:admin2_code":"11072234.0",
    "gn:asciiname":"Martinski",
    "gn:cc2":"HR",
    "gn:country_code":"HR",
    "gn:dem":335,
    "gn:feature_class":"P",
    "gn:feature_code":"PPL",
    "gn:name":"Martinski",
    "gn:population":0,
    "gn:timezone":"Europe/Zagreb",
    "iso:country":"HR",
    "name:und_x_variant":[
        "Sveti Martin",
        "Sveti Martino",
        "Martinski"
    ],
    "wof:name":"Martinski",
    "wof:placetype":"locality"
},
  "geometry": {"coordinates":[14.05111,45.1275],"type":"Point"}
}