{
  "type": "Feature",
  "properties": {
    "gn:admin1_code":"14.0",
    "gn:asciiname":"Crkvine",
    "gn:country_code":"HR",
    "gn:dem":164,
    "gn:feature_class":"P",
    "gn:feature_code":"PPL",
    "gn:name":"Crkvine",
    "gn:population":0,
    "gn:timezone":"Europe/Zagreb",
    "iso:country":"HR",
    "wof:name":"Crkvine",
    "wof:placetype":"locality"
},
  "geometry": {"coordinates":[15.92889,45.21583],"type":"Point"}
}