{
  "type": "Feature",
  "properties": {
    "gn:admin1_code":"14.0",
    "gn:asciiname":"Crkvine",
    "gn:country_code":"HR",
    "gn:dem":164,
    "gn:feature_class":"P",
    "gn:feature_code":"PPL",
    "gn:name":"Crkvine",
    "gn:population":0,
    "gn:timezone":"Europe/Zagreb",
    "iso:country":"HR",
    "name:ceb_x_preferred":[
        "Crkvine"
    ],
    "name:fra_x_preferred":[
        "Crkvine"
    ],
    "name:hrv_x_preferred":[
        "Crkvine"
    ],
    "name:nld_x_preferred":[
        "Crkvine"
    ],
    "name:slv_x_preferred":[
        "Crkvine"
    ],
    "name:srp_x_preferred":[
        "\u0426\u0440\u043a\u0432\u0438\u043d\u0435"
    ],
    "name:swe_x_preferred":[
        "Crkvine"
    ],
    "wof:name":"Crkvine",
    "wof:placetype":"locality"
},
  "geometry": {"coordinates":[15.92889,45.21583],"type":"Point"}
}