{
  "type": "Feature",
  "properties": {
    "gn:admin1_code":"01",
    "gn:admin2_code":"11049398.0",
    "gn:asciiname":"Kostanjevac",
    "gn:cc2":"HR",
    "gn:country_code":"HR",
    "gn:dem":161,
    "gn:feature_class":"P",
    "gn:feature_code":"PPL",
    "gn:name":"Kostanjevac",
    "gn:population":143,
    "gn:timezone":"Europe/Zagreb",
    "iso:country":"HR",
    "name:und_x_variant":[
        "Bere\u010dki Kostanjevac",
        "Kostanjevac Bere\u010dki",
        "Kostanjevac Bera\u010dki",
        "Kostanjevac"
    ],
    "wof:name":"Kostanjevac",
    "wof:placetype":"locality",
    "wof:population":143
},
  "geometry": {"coordinates":[16.88889,45.66667],"type":"Point"}
}