{
  "type": "Feature",
  "properties": {
    "gn:admin1_code":"8.0",
    "gn:admin2_code":"11049291.0",
    "gn:asciiname":"Gostovaca",
    "gn:country_code":"HR",
    "gn:dem":729,
    "gn:feature_class":"P",
    "gn:feature_code":"PPL",
    "gn:name":"Gostova\u010da",
    "gn:population":0,
    "gn:timezone":"Europe/Zagreb",
    "iso:country":"HR",
    "wof:name":"Gostovaca",
    "wof:placetype":"locality"
},
  "geometry": {"coordinates":[15.4625,44.68472],"type":"Point"}
}