{
  "type": "Feature",
  "properties": {
    "gn:gn_country":"HR",
    "gn:gn_fcode":"PPL",
    "gn:gn_pop":852,
    "gn:population":852,
    "iso:country":"HR",
    "name:bos_x_preferred":[
        "Ivanska"
    ],
    "name:bul_x_preferred":[
        "\u0418\u0432\u0430\u043d\u0441\u043a\u0430"
    ],
    "name:cat_x_preferred":[
        "Ivanska"
    ],
    "name:deu_x_preferred":[
        "Ivanska"
    ],
    "name:eng_x_preferred":[
        "Ivanska"
    ],
    "name:fra_x_preferred":[
        "Ivanska"
    ],
    "name:hrv_x_preferred":[
        "Ivanska"
    ],
    "name:ita_x_preferred":[
        "Ivanska"
    ],
    "name:nld_x_preferred":[
        "Ivanska"
    ],
    "name:pol_x_preferred":[
        "Ivanska"
    ],
    "name:ron_x_preferred":[
        "Comuna Ivanska"
    ],
    "name:rus_x_preferred":[
        "\u0418\u0432\u0430\u043d\u0441\u043a\u0430"
    ],
    "name:slv_x_preferred":[
        "Ivanska"
    ],
    "name:spa_x_preferred":[
        "Ivanska"
    ],
    "name:srp_x_preferred":[
        "\u0418\u0432\u0430\u043d\u0441\u043a\u0430"
    ],
    "name:swe_x_preferred":[
        "Ivanska"
    ],
    "name:war_x_preferred":[
        "Ivanska"
    ],
    "qs_pg:aaroncc":"HR",
    "qs_pg:gn_country":"HR",
    "qs_pg:gn_fcode":"PPL",
    "qs_pg:gn_pop":852,
    "qs_pg:name":"Ivanska",
    "qs_pg:name_adm0":"Hrvatska",
    "qs_pg:name_adm1":"Bjelovarsko-Bilogorska",
    "qs_pg:photos_9r":0,
    "qs_pg:photos_sr":0,
    "qs_pg:pop_sr":2,
    "qs_pg:qs_pg_placetype":"locality",
    "qs_pg:qs_pg_placetype_gp":"Town",
    "qs_pg:woe_adm0":23424843,
    "woe:adm0_id":23424843,
    "woe:name_adm0":"Hrvatska",
    "woe:name_adm1":"Bjelovarsko-Bilogorska",
    "woe:placetype":"Town",
    "wof:name":"Ivanska",
    "wof:placetype":"locality",
    "wof:population":852
},
  "geometry": {"coordinates":[16.81194,45.77889],"type":"Point"}
}