{
  "type": "Feature",
  "properties": {
    "gn:admin1_code":"20",
    "gn:admin2_code":"11048994.0",
    "gn:asciiname":"Vezisce",
    "gn:country_code":"HR",
    "gn:dem":96,
    "gn:feature_class":"P",
    "gn:feature_code":"PPL",
    "gn:name":"Vezi\u0161\u0107e",
    "gn:population":0,
    "gn:timezone":"Europe/Zagreb",
    "iso:country":"HR",
    "wof:name":"Vezisce",
    "wof:placetype":"locality"
},
  "geometry": {"coordinates":[16.53333,45.61667],"type":"Point"}
}