{
  "type": "Feature",
  "properties": {
    "gn:admin1_code":"03",
    "gn:admin2_code":"11055009.0",
    "gn:asciiname":"Tocionik",
    "gn:country_code":"HR",
    "gn:dem":254,
    "gn:feature_class":"P",
    "gn:feature_code":"PPL",
    "gn:name":"To\u010dionik",
    "gn:population":23,
    "gn:timezone":"Europe/Zagreb",
    "iso:country":"HR",
    "wof:name":"Tocionik",
    "wof:placetype":"locality",
    "wof:population":23
},
  "geometry": {"coordinates":[17.81167,42.8725],"type":"Point"}
}