{
  "type": "Feature",
  "properties": {
    "gn:admin1_code":"10",
    "gn:admin2_code":"11054471.0",
    "gn:asciiname":"Cenkovo",
    "gn:country_code":"HR",
    "gn:dem":198,
    "gn:feature_class":"P",
    "gn:feature_code":"PPL",
    "gn:name":"\u010cenkovo",
    "gn:population":0,
    "gn:timezone":"Europe/Zagreb",
    "iso:country":"HR",
    "name:bos_x_preferred":[
        "\u010cenkovo"
    ],
    "name:hrv_x_preferred":[
        "\u010cenkovo"
    ],
    "name:nld_x_preferred":[
        "\u010cenkovo"
    ],
    "name:slv_x_preferred":[
        "\u010cenkovo"
    ],
    "name:ukr_x_preferred":[
        "\u0427\u0435\u043d\u043a\u043e\u0432\u043e"
    ],
    "wof:name":"Cenkovo",
    "wof:placetype":"locality"
},
  "geometry": {"coordinates":[18.11056,45.33889],"type":"Point"}
}