{
  "type": "Feature",
  "properties": {
    "gn:admin1_code":"10",
    "gn:admin2_code":"11054471.0",
    "gn:asciiname":"Cenkovo",
    "gn:country_code":"HR",
    "gn:dem":198,
    "gn:feature_class":"P",
    "gn:feature_code":"PPL",
    "gn:name":"\u010cenkovo",
    "gn:population":0,
    "gn:timezone":"Europe/Zagreb",
    "iso:country":"HR",
    "name:und_x_variant":[
        "\u010cenkovo"
    ],
    "wof:name":"Cenkovo",
    "wof:placetype":"locality"
},
  "geometry": {"coordinates":[18.11056,45.33889],"type":"Point"}
}