{
  "type": "Feature",
  "properties": {
    "gn:admin1_code":"08",
    "gn:admin2_code":"11049292.0",
    "gn:asciiname":"Ponor Korenicki",
    "gn:cc2":"HR",
    "gn:country_code":"HR",
    "gn:dem":662,
    "gn:feature_class":"P",
    "gn:feature_code":"PPL",
    "gn:name":"Ponor Koreni\u010dki",
    "gn:population":3,
    "gn:timezone":"Europe/Zagreb",
    "iso:country":"HR",
    "name:und_x_variant":[
        "Koreni\u010dki Ponor",
        "Ponor",
        "Ponor Koreni\u010dki"
    ],
    "wof:name":"Ponor Korenicki",
    "wof:placetype":"locality",
    "wof:population":3
},
  "geometry": {"coordinates":[15.76472,44.73417],"type":"Point"}
}