{
  "type": "Feature",
  "properties": {
    "gn:admin1_code":"04",
    "gn:admin2_code":"11054800.0",
    "gn:asciiname":"Sterna",
    "gn:cc2":"HR",
    "gn:country_code":"HR",
    "gn:dem":299,
    "gn:feature_class":"P",
    "gn:feature_code":"PPL",
    "gn:name":"\u0160terna",
    "gn:population":0,
    "gn:timezone":"Europe/Zagreb",
    "iso:country":"HR",
    "name:afr_x_preferred":[
        "Sterna"
    ],
    "name:ara_x_preferred":[
        "\u062e\u0631\u0634\u0646\u0629"
    ],
    "name:aze_x_preferred":[
        "Sus\u00fcp\u00fcr\u0259n"
    ],
    "name:bre_x_preferred":[
        "Sterna"
    ],
    "name:cat_x_preferred":[
        "Xatrac"
    ],
    "name:ceb_x_preferred":[
        "Sterna"
    ],
    "name:dan_x_preferred":[
        "Sterna"
    ],
    "name:deu_x_preferred":[
        "Sterna"
    ],
    "name:est_x_preferred":[
        "Tiir"
    ],
    "name:fas_x_preferred":[
        "\u06a9\u0627\u06a9\u0627\u06cc\u06cc\u200c\u0647\u0627"
    ],
    "name:fin_x_preferred":[
        "Tiirat"
    ],
    "name:fra_x_preferred":[
        "Sterna"
    ],
    "name:heb_x_preferred":[
        "\u05e9\u05d7\u05e4\u05d9\u05ea"
    ],
    "name:hun_x_preferred":[
        "Sterna"
    ],
    "name:ita_x_preferred":[
        "Sterna"
    ],
    "name:lav_x_preferred":[
        "Z\u012bri\u0146i"
    ],
    "name:nld_x_preferred":[
        "Sterna"
    ],
    "name:nno_x_preferred":[
        "Sterna"
    ],
    "name:nor_x_preferred":[
        "Havterner"
    ],
    "name:pol_x_preferred":[
        "Sterna"
    ],
    "name:por_x_preferred":[
        "Sterna"
    ],
    "name:rus_x_preferred":[
        "\u041a\u0440\u0430\u0447\u043a\u0438"
    ],
    "name:sah_x_preferred":[
        "\u0422\u044b\u044b\u0440\u0430\u0430\u0445\u044b\u043b\u0430\u0440 \u0443\u0443\u0441\u0442\u0430\u0440\u0430"
    ],
    "name:sco_x_preferred":[
        "Sterna"
    ],
    "name:spa_x_preferred":[
        "Sterna"
    ],
    "name:swe_x_preferred":[
        "Sterna"
    ],
    "name:ukr_x_preferred":[
        "\u041a\u0440\u044f\u0447\u043e\u043a"
    ],
    "name:und_x_variant":[
        "Sterna Filaria",
        "\u0160terna"
    ],
    "name:vie_x_preferred":[
        "Sterna"
    ],
    "name:war_x_preferred":[
        "Sterna"
    ],
    "name:zho_x_preferred":[
        "\u71d5\u9dd7\u5c6c"
    ],
    "wof:name":"Sterna",
    "wof:placetype":"locality"
},
  "geometry": {"coordinates":[13.79361,45.41306],"type":"Point"}
}