{
  "type": "Feature",
  "properties": {
    "gn:admin1_code":"04",
    "gn:admin2_code":"11054800.0",
    "gn:asciiname":"Sterna",
    "gn:cc2":"HR",
    "gn:country_code":"HR",
    "gn:dem":299,
    "gn:feature_class":"P",
    "gn:feature_code":"PPL",
    "gn:name":"\u0160terna",
    "gn:population":0,
    "gn:timezone":"Europe/Zagreb",
    "iso:country":"HR",
    "name:und_x_variant":[
        "Sterna Filaria",
        "\u0160terna"
    ],
    "wof:name":"Sterna",
    "wof:placetype":"locality"
},
  "geometry": {"coordinates":[13.79361,45.41306],"type":"Point"}
}