{
  "type": "Feature",
  "properties": {
    "gn:admin1_code":"07",
    "gn:admin2_code":"11049011.0",
    "gn:asciiname":"Gornji Kraljevec",
    "gn:country_code":"HR",
    "gn:dem":201,
    "gn:feature_class":"P",
    "gn:feature_code":"PPL",
    "gn:name":"Gornji Kraljevec",
    "gn:population":353,
    "gn:timezone":"Europe/Zagreb",
    "iso:country":"HR",
    "wof:name":"Gornji Kraljevec",
    "wof:placetype":"locality",
    "wof:population":353
},
  "geometry": {"coordinates":[16.21852,46.13036],"type":"Point"}
}