{
  "type": "Feature",
  "properties": {
    "gn:admin1_code":"2.0",
    "gn:admin2_code":"11049510.0",
    "gn:asciiname":"Gredica",
    "gn:country_code":"HR",
    "gn:dem":89,
    "gn:feature_class":"P",
    "gn:feature_code":"PPL",
    "gn:name":"Gredica",
    "gn:population":0,
    "gn:timezone":"Europe/Zagreb",
    "iso:country":"HR",
    "wof:name":"Gredica",
    "wof:placetype":"locality"
},
  "geometry": {"coordinates":[17.38,45.14361],"type":"Point"}
}