{
  "type": "Feature",
  "properties": {
    "gn:admin1_code":"09",
    "gn:admin2_code":"11054886.0",
    "gn:asciiname":"Grabrovnik",
    "gn:country_code":"HR",
    "gn:dem":246,
    "gn:feature_class":"P",
    "gn:feature_code":"PPL",
    "gn:name":"Grabrovnik",
    "gn:population":274,
    "gn:timezone":"Europe/Zagreb",
    "iso:country":"HR",
    "wof:name":"Grabrovnik",
    "wof:placetype":"locality",
    "wof:population":274
},
  "geometry": {"coordinates":[16.30199,46.48811],"type":"Point"}
}