{
  "type": "Feature",
  "properties": {
    "gn:admin1_code":"8.0",
    "gn:asciiname":"Bakovac",
    "gn:country_code":"HR",
    "gn:dem":895,
    "gn:feature_class":"P",
    "gn:feature_code":"PPL",
    "gn:name":"Bakovac",
    "gn:population":0,
    "gn:timezone":"Europe/Zagreb",
    "iso:country":"HR",
    "wof:name":"Bakovac",
    "wof:placetype":"locality"
},
  "geometry": {"coordinates":[15.12528,44.68472],"type":"Point"}
}