{
  "type": "Feature",
  "properties": {
    "gn:admin1_code":"8.0",
    "gn:admin2_code":"11049291.0",
    "gn:asciiname":"Bukovac",
    "gn:country_code":"HR",
    "gn:dem":575,
    "gn:feature_class":"P",
    "gn:feature_code":"PPL",
    "gn:name":"Bukovac",
    "gn:population":0,
    "gn:timezone":"Europe/Zagreb",
    "iso:country":"HR",
    "wof:name":"Bukovac",
    "wof:placetype":"locality"
},
  "geometry": {"coordinates":[15.41667,44.65444],"type":"Point"}
}