{
  "type": "Feature",
  "properties": {
    "gn:admin1_code":"15",
    "gn:admin2_code":"11054601.0",
    "gn:asciiname":"Sicane",
    "gn:cc2":"HR",
    "gn:country_code":"HR",
    "gn:dem":383,
    "gn:feature_class":"P",
    "gn:feature_code":"PPLL",
    "gn:name":"Si\u010dane",
    "gn:population":0,
    "gn:timezone":"Europe/Zagreb",
    "iso:country":"HR",
    "name:und_x_variant":[
        "Si\u010dani",
        "Si\u010dane"
    ],
    "wof:name":"Sicane",
    "wof:placetype":"locality"
},
  "geometry": {"coordinates":[16.58917000000001,43.65778],"type":"Point"}
}