{
  "type": "Feature",
  "properties": {
    "gn:admin1_code":"14.0",
    "gn:asciiname":"Durici",
    "gn:country_code":"HR",
    "gn:dem":208,
    "gn:feature_class":"P",
    "gn:feature_code":"PPL",
    "gn:name":"\u00d0uri\u0107i",
    "gn:population":0,
    "gn:timezone":"Europe/Zagreb",
    "iso:country":"HR",
    "wof:name":"Durici",
    "wof:placetype":"locality"
},
  "geometry": {"coordinates":[16.31028,45.11167],"type":"Point"}
}