{
  "type": "Feature",
  "properties": {
    "gn:admin1_code":"8.0",
    "gn:admin2_code":"11049287.0",
    "gn:asciiname":"Dosen-Duliba",
    "gn:country_code":"HR",
    "gn:dem":744,
    "gn:feature_class":"P",
    "gn:feature_code":"PPL",
    "gn:name":"Do\u0161en-Duliba",
    "gn:population":0,
    "gn:timezone":"Europe/Zagreb",
    "iso:country":"HR",
    "wof:name":"Dosen-Duliba",
    "wof:placetype":"locality"
},
  "geometry": {"coordinates":[15.12028,44.575],"type":"Point"}
}