{
  "type": "Feature",
  "properties": {
    "gn:admin1_code":"11",
    "gn:admin2_code":"11049477.0",
    "gn:asciiname":"Kukunjevac",
    "gn:country_code":"HR",
    "gn:dem":156,
    "gn:feature_class":"P",
    "gn:feature_code":"PPLL",
    "gn:name":"Kukunjevac",
    "gn:population":0,
    "gn:timezone":"Europe/Zagreb",
    "iso:country":"HR",
    "name:bos_x_preferred":[
        "Kukunjevac"
    ],
    "name:hrv_x_preferred":[
        "Kukunjevac"
    ],
    "name:hun_x_preferred":[
        "Kukunjevac"
    ],
    "name:nld_x_preferred":[
        "Kukunjevac"
    ],
    "name:slv_x_preferred":[
        "Kukunjevac"
    ],
    "name:spa_x_preferred":[
        "Kukunjevac"
    ],
    "name:srp_x_preferred":[
        "\u041a\u0443\u043a\u0443\u045a\u0435\u0432\u0430\u0446"
    ],
    "name:ukr_x_preferred":[
        "\u041a\u0443\u043a\u0443\u043d\u0454\u0432\u0430\u0446\u044c"
    ],
    "wof:name":"Kukunjevac",
    "wof:placetype":"locality"
},
  "geometry": {"coordinates":[17.09111,45.44972],"type":"Point"}
}