{
  "type": "Feature",
  "properties": {
    "gn:admin1_code":"15.0",
    "gn:asciiname":"Sladoje",
    "gn:country_code":"HR",
    "gn:dem":348,
    "gn:feature_class":"P",
    "gn:feature_code":"PPL",
    "gn:name":"Sladoje",
    "gn:population":0,
    "gn:timezone":"Europe/Zagreb",
    "iso:country":"HR",
    "wof:name":"Sladoje",
    "wof:placetype":"locality"
},
  "geometry": {"coordinates":[16.61611,43.72139],"type":"Point"}
}