{
  "type": "Feature",
  "properties": {
    "gn:admin1_code":"12",
    "gn:admin2_code":"11049431.0",
    "gn:asciiname":"Gornji Sajn",
    "gn:cc2":"HR",
    "gn:country_code":"HR",
    "gn:dem":540,
    "gn:feature_class":"P",
    "gn:feature_code":"PPL",
    "gn:name":"Gornji \u0160ajn",
    "gn:population":12,
    "gn:timezone":"Europe/Zagreb",
    "iso:country":"HR",
    "name:und_x_variant":[
        "Gornji \u0160ain",
        "Gornji \u0160ajn"
    ],
    "wof:name":"Gornji Sajn",
    "wof:placetype":"locality",
    "wof:population":12
},
  "geometry": {"coordinates":[14.96611,45.49694],"type":"Point"}
}