{
  "type": "Feature",
  "properties": {
    "gn:country":"HR",
    "gn:fcode":"PPL",
    "gn:population":0,
    "iso:country":"HR",
    "name:bos_x_preferred":[
        "Zara\u0107e"
    ],
    "name:ces_x_preferred":[
        "Zara\u0107e"
    ],
    "name:deu_x_preferred":[
        "Zara\u0107e"
    ],
    "name:eng_x_preferred":[
        "Zara\u0107e"
    ],
    "name:fra_x_preferred":[
        "Zara\u0107e"
    ],
    "name:hrv_x_preferred":[
        "Zara\u0107e"
    ],
    "name:hun_x_preferred":[
        "Zara\u0107e"
    ],
    "name:nld_x_preferred":[
        "Zara\u0107e"
    ],
    "name:pol_x_preferred":[
        "Zara\u0107e"
    ],
    "name:slk_x_preferred":[
        "Zara\u0107e"
    ],
    "name:slv_x_preferred":[
        "Zara\u0107e"
    ],
    "name:spa_x_preferred":[
        "Zara\u0107e"
    ],
    "name:srp_x_preferred":[
        "\u0417\u0430\u0440\u0430\u045b\u0435"
    ],
    "name:ukr_x_preferred":[
        "\u0417\u0430\u0440\u0430\u0447\u0435"
    ],
    "qs_pg:aaroncc":"HR",
    "qs_pg:gn_country":"HR",
    "qs_pg:gn_fcode":"PPL",
    "qs_pg:gn_pop":0,
    "qs_pg:name":"Zara\u010de",
    "qs_pg:name_adm0":"Hrvatska",
    "qs_pg:name_adm1":"Splitsko-Dalmatinska",
    "qs_pg:photos":116,
    "qs_pg:photos_1k":24,
    "qs_pg:photos_9k":1,
    "qs_pg:photos_9r":3,
    "qs_pg:photos_all":116,
    "qs_pg:photos_sr":3,
    "qs_pg:pop_sr":0,
    "qs_pg:qs_pg_placetype":"locality",
    "qs_pg:qs_pg_placetype_gp":"Town",
    "qs_pg:woe_adm0":23424843,
    "woe:adm0_id":23424843,
    "woe:name_adm0":"Hrvatska",
    "woe:name_adm1":"Splitsko-Dalmatinska",
    "woe:placetype":"Town",
    "wof:name":"Zara\u010de",
    "wof:placetype":"locality"
},
  "geometry": {"coordinates":[16.51667,43.15],"type":"Point"}
}