{
  "type": "Feature",
  "properties": {
    "gn:admin1_code":"11",
    "gn:admin2_code":"11049478.0",
    "gn:asciiname":"Knezci",
    "gn:cc2":"HR",
    "gn:country_code":"HR",
    "gn:dem":129,
    "gn:feature_class":"P",
    "gn:feature_code":"PPL",
    "gn:name":"Kne\u017eci",
    "gn:population":61,
    "gn:timezone":"Europe/Zagreb",
    "iso:country":"HR",
    "name:bos_x_preferred":[
        "Kne\u017eci"
    ],
    "name:hrv_x_preferred":[
        "Kne\u017eci"
    ],
    "name:nld_x_preferred":[
        "Kne\u017eci"
    ],
    "name:slv_x_preferred":[
        "Kne\u017eci"
    ],
    "name:spa_x_preferred":[
        "Kne\u017eci"
    ],
    "name:srp_x_preferred":[
        "\u041a\u043d\u0435\u0436\u0446\u0438"
    ],
    "name:ukr_x_preferred":[
        "\u041a\u043d\u0435\u0436\u0446\u0456"
    ],
    "name:und_x_variant":[
        "Kne\u0161ci",
        "Kne\u017eci"
    ],
    "wof:name":"Knezci",
    "wof:placetype":"locality",
    "wof:population":61
},
  "geometry": {"coordinates":[17.89917,45.33972],"type":"Point"}
}