{
  "type": "Feature",
  "properties": {
    "gn:admin1_code":"8.0",
    "gn:asciiname":"Panjenovici",
    "gn:country_code":"HR",
    "gn:dem":804,
    "gn:feature_class":"P",
    "gn:feature_code":"PPL",
    "gn:name":"Panjenovi\u0107i",
    "gn:population":0,
    "gn:timezone":"Europe/Zagreb",
    "iso:country":"HR",
    "wof:name":"Panjenovici",
    "wof:placetype":"locality"
},
  "geometry": {"coordinates":[15.06028,44.81583],"type":"Point"}
}