{
  "type": "Feature",
  "properties": {
    "gn:admin1_code":"4.0",
    "gn:asciiname":"Kosici",
    "gn:cc2":"HR",
    "gn:country_code":"HR",
    "gn:dem":18,
    "gn:feature_class":"P",
    "gn:feature_code":"PPL",
    "gn:name":"Kosi\u0107i",
    "gn:population":0,
    "gn:timezone":"Europe/Zagreb",
    "iso:country":"HR",
    "name:und_x_variant":[
        "Varela"
    ],
    "wof:name":"Kosici",
    "wof:placetype":"locality"
},
  "geometry": {"coordinates":[13.69667,45.0475],"type":"Point"}
}