{
  "type": "Feature",
  "properties": {
    "gn:admin1_code":"04",
    "gn:admin2_code":"11054816.0",
    "gn:asciiname":"Diminici",
    "gn:cc2":"HR",
    "gn:country_code":"HR",
    "gn:dem":137,
    "gn:feature_class":"P",
    "gn:feature_code":"PPL",
    "gn:name":"Dimini\u0107i",
    "gn:population":0,
    "gn:timezone":"Europe/Zagreb",
    "iso:country":"HR",
    "name:fra_x_preferred":[
        "Dimini\u0107i"
    ],
    "name:hrv_x_preferred":[
        "Dimini\u0107i"
    ],
    "name:und_x_variant":[
        "Villa Diminici",
        "San Lorenzo d\u2019Albona",
        "Sveti Lovre\u010d",
        "Diminic",
        "San Lorenzo"
    ],
    "wof:name":"Diminici",
    "wof:placetype":"locality"
},
  "geometry": {"coordinates":[14.10333,44.99194],"type":"Point"}
}