{
  "type": "Feature",
  "properties": {
    "gn:admin1_code":"20",
    "gn:admin2_code":"3188243.0",
    "gn:asciiname":"Kljucic Brdo",
    "gn:country_code":"HR",
    "gn:dem":167,
    "gn:feature_class":"P",
    "gn:feature_code":"PPL",
    "gn:name":"Klju\u010di\u0107 Brdo",
    "gn:population":214,
    "gn:timezone":"Europe/Zagreb",
    "iso:country":"HR",
    "wof:name":"Kljucic Brdo",
    "wof:placetype":"locality",
    "wof:population":214
},
  "geometry": {"coordinates":[16.04244,45.62064],"type":"Point"}
}