{
  "type": "Feature",
  "properties": {
    "gn:admin1_code":"13",
    "gn:admin2_code":"11054524.0",
    "gn:asciiname":"Gornje Vinovo",
    "gn:country_code":"HR",
    "gn:dem":443,
    "gn:feature_class":"P",
    "gn:feature_code":"PPL",
    "gn:name":"Gornje Vinovo",
    "gn:population":33,
    "gn:timezone":"Europe/Zagreb",
    "iso:country":"HR",
    "wof:name":"Gornje Vinovo",
    "wof:placetype":"locality",
    "wof:population":33
},
  "geometry": {"coordinates":[16.30697,43.73104],"type":"Point"}
}