{
  "type": "Feature",
  "properties": {
    "gn:admin1_code":"14",
    "gn:admin2_code":"11049233.0",
    "gn:asciiname":"Gornja Letina",
    "gn:country_code":"HR",
    "gn:dem":96,
    "gn:feature_class":"P",
    "gn:feature_code":"PPL",
    "gn:name":"Gornja Letina",
    "gn:population":71,
    "gn:timezone":"Europe/Zagreb",
    "iso:country":"HR",
    "name:bos_x_preferred":[
        "Gornja Letina"
    ],
    "name:fra_x_preferred":[
        "Gornja Letina"
    ],
    "name:hrv_x_preferred":[
        "Gornja Letina"
    ],
    "name:hun_x_preferred":[
        "Gornja Letina"
    ],
    "name:nld_x_preferred":[
        "Gornja Letina"
    ],
    "name:slv_x_preferred":[
        "Gornja Letina"
    ],
    "name:spa_x_preferred":[
        "Gornja Letina"
    ],
    "name:srp_x_preferred":[
        "\u0413\u043e\u0440\u045a\u0430 \u041b\u0435\u0442\u0438\u043d\u0430"
    ],
    "name:ukr_x_preferred":[
        "\u0413\u043e\u0440\u043d\u044f \u041b\u0435\u0442\u0438\u043d\u0430"
    ],
    "wof:name":"Gornja Letina",
    "wof:placetype":"locality",
    "wof:population":71
},
  "geometry": {"coordinates":[16.56278,45.40667],"type":"Point"}
}