{
  "type": "Feature",
  "properties": {
    "gn:admin1_code":"18",
    "gn:admin2_code":"11054540.0",
    "gn:asciiname":"Opatovac",
    "gn:country_code":"HR",
    "gn:dem":86,
    "gn:feature_class":"P",
    "gn:feature_code":"PPL",
    "gn:name":"Opatovac",
    "gn:population":345,
    "gn:timezone":"Europe/Zagreb",
    "iso:country":"HR",
    "name:bos_x_preferred":[
        "Opatovac"
    ],
    "name:hrv_x_preferred":[
        "Opatovac"
    ],
    "name:nld_x_preferred":[
        "Opatovac"
    ],
    "name:slv_x_preferred":[
        "Opatovac"
    ],
    "name:srp_x_preferred":[
        "\u041e\u043f\u0430\u0442\u043e\u0432\u0430\u0446"
    ],
    "wof:name":"Opatovac",
    "wof:placetype":"locality",
    "wof:population":345
},
  "geometry": {"coordinates":[19.17083,45.26056],"type":"Point"}
}