{
  "type": "Feature",
  "properties": {
    "gn:admin1_code":"12",
    "gn:admin2_code":"11049443.0",
    "gn:asciiname":"Zejane",
    "gn:cc2":"HR",
    "gn:country_code":"HR",
    "gn:dem":603,
    "gn:feature_class":"P",
    "gn:feature_code":"PPL",
    "gn:name":"\u017dejane",
    "gn:population":130,
    "gn:timezone":"Europe/Zagreb",
    "iso:country":"HR",
    "name:und_x_variant":[
        "Seiane",
        "\u017dejane"
    ],
    "wof:name":"Zejane",
    "wof:placetype":"locality",
    "wof:population":130
},
  "geometry": {"coordinates":[14.19528,45.43944000000001],"type":"Point"}
}