{
  "type": "Feature",
  "properties": {
    "gn:admin1_code":"12",
    "gn:admin2_code":"11049443.0",
    "gn:asciiname":"Zejane",
    "gn:cc2":"HR",
    "gn:country_code":"HR",
    "gn:dem":603,
    "gn:feature_class":"P",
    "gn:feature_code":"PPL",
    "gn:name":"\u017dejane",
    "gn:population":130,
    "gn:timezone":"Europe/Zagreb",
    "iso:country":"HR",
    "name:bos_x_preferred":[
        "\u017dejane"
    ],
    "name:fra_x_preferred":[
        "\u017dejane"
    ],
    "name:hrv_x_preferred":[
        "\u017dejane"
    ],
    "name:hun_x_preferred":[
        "\u017dejane"
    ],
    "name:ita_x_preferred":[
        "Seiane"
    ],
    "name:ron_x_preferred":[
        "Jei\u0103n"
    ],
    "name:slv_x_preferred":[
        "\u017dejane"
    ],
    "name:spa_x_preferred":[
        "\u017dejane"
    ],
    "name:srp_x_preferred":[
        "\u0416\u0435\u0458\u0430\u043d\u0435"
    ],
    "name:ukr_x_preferred":[
        "\u0416\u0435\u044f\u043d\u0435"
    ],
    "wof:name":"Zejane",
    "wof:placetype":"locality",
    "wof:population":130
},
  "geometry": {"coordinates":[14.19528,45.43944000000001],"type":"Point"}
}