{
  "type": "Feature",
  "properties": {
    "gn:admin1_code":"8.0",
    "gn:admin2_code":"11049292.0",
    "gn:asciiname":"Korana",
    "gn:country_code":"HR",
    "gn:dem":517,
    "gn:feature_class":"P",
    "gn:feature_code":"PPL",
    "gn:name":"Korana",
    "gn:population":18,
    "gn:timezone":"Europe/Zagreb",
    "iso:country":"HR",
    "name:hrv_x_preferred":[
        "Selo Korana"
    ],
    "wof:name":"Korana",
    "wof:placetype":"locality",
    "wof:population":18
},
  "geometry": {"coordinates":[15.60954,44.91919],"type":"Point"}
}