{
  "type": "Feature",
  "properties": {
    "gn:admin1_code":"8.0",
    "gn:admin2_code":"11049292.0",
    "gn:asciiname":"Korana",
    "gn:country_code":"HR",
    "gn:dem":517,
    "gn:feature_class":"P",
    "gn:feature_code":"PPL",
    "gn:name":"Korana",
    "gn:population":18,
    "gn:timezone":"Europe/Zagreb",
    "iso:country":"HR",
    "name:ara_x_preferred":[
        "\u0646\u0647\u0631 \u0643\u0648\u0631\u0627\u0646\u0627"
    ],
    "name:bos_x_preferred":[
        "Korana"
    ],
    "name:ces_x_preferred":[
        "Korana"
    ],
    "name:deu_x_preferred":[
        "Korana"
    ],
    "name:fin_x_preferred":[
        "Korana"
    ],
    "name:fra_x_preferred":[
        "Korana"
    ],
    "name:hrv_x_preferred":[
        "Selo Korana"
    ],
    "name:hrv_x_variant":[
        "Korana"
    ],
    "name:hun_x_preferred":[
        "Korana"
    ],
    "name:lit_x_preferred":[
        "Korana"
    ],
    "name:mkd_x_preferred":[
        "\u041a\u043e\u0440\u0430\u043d\u0430"
    ],
    "name:nld_x_preferred":[
        "Korana"
    ],
    "name:nno_x_preferred":[
        "Korana"
    ],
    "name:nor_x_preferred":[
        "Korana"
    ],
    "name:pol_x_preferred":[
        "Korana"
    ],
    "name:rus_x_preferred":[
        "\u041a\u043e\u0440\u0430\u043d\u0430"
    ],
    "name:slk_x_preferred":[
        "Korana"
    ],
    "name:slv_x_preferred":[
        "Korana"
    ],
    "name:srp_x_preferred":[
        "\u041a\u043e\u0440\u0430\u043d\u0430"
    ],
    "name:swe_x_preferred":[
        "Korana"
    ],
    "name:ukr_x_preferred":[
        "\u041a\u043e\u0440\u0430\u043d\u0430"
    ],
    "name:zho_x_preferred":[
        "\u79d1\u62c9\u7d0d\u6cb3"
    ],
    "wof:name":"Korana",
    "wof:placetype":"locality",
    "wof:population":18
},
  "geometry": {"coordinates":[15.60954,44.91919],"type":"Point"}
}