{
  "type": "Feature",
  "properties": {
    "gn:admin1_code":"12",
    "gn:asciiname":"Unije",
    "gn:cc2":"HR",
    "gn:country_code":"HR",
    "gn:dem":0,
    "gn:feature_class":"P",
    "gn:feature_code":"PPL",
    "gn:name":"Unije",
    "gn:population":88,
    "gn:timezone":"Europe/Zagreb",
    "iso:country":"HR",
    "name:bul_x_preferred":[
        "\u0423\u043d\u0438\u0435"
    ],
    "name:deu_x_preferred":[
        "Unije"
    ],
    "name:ell_x_preferred":[
        "\u039f\u03cd\u03bd\u03b9\u03b3\u03b5"
    ],
    "name:fra_x_preferred":[
        "Unije"
    ],
    "name:hrv_x_preferred":[
        "Unije"
    ],
    "name:ind_x_preferred":[
        "Unije"
    ],
    "name:ita_x_preferred":[
        "Unie"
    ],
    "name:kor_x_preferred":[
        "\uc6b0\ub2c8\uc608\uc12c"
    ],
    "name:lat_x_preferred":[
        "Uniae"
    ],
    "name:nld_x_preferred":[
        "Unije"
    ],
    "name:nno_x_preferred":[
        "Unije"
    ],
    "name:nor_x_preferred":[
        "Unije"
    ],
    "name:pol_x_preferred":[
        "Unije"
    ],
    "name:por_x_preferred":[
        "Unije"
    ],
    "name:rus_x_preferred":[
        "\u0423\u043d\u0438\u0435"
    ],
    "name:slv_x_preferred":[
        "Unije"
    ],
    "name:spa_x_preferred":[
        "Unije"
    ],
    "name:srp_x_preferred":[
        "\u0423\u043d\u0438\u0458\u0435"
    ],
    "name:swe_x_preferred":[
        "Unije"
    ],
    "name:tur_x_preferred":[
        "Unije"
    ],
    "name:ukr_x_preferred":[
        "\u0423\u043d\u0456\u0454"
    ],
    "name:und_x_variant":[
        "Unje"
    ],
    "name:zho_x_preferred":[
        "\u70cf\u5c3c\u8036\u5cf6"
    ],
    "wof:name":"Unije",
    "wof:placetype":"locality",
    "wof:population":88
},
  "geometry": {"coordinates":[14.24778,44.63472],"type":"Point"}
}