{
  "type": "Feature",
  "properties": {
    "gn:admin1_code":"12",
    "gn:asciiname":"Unije",
    "gn:cc2":"HR",
    "gn:country_code":"HR",
    "gn:dem":0,
    "gn:feature_class":"P",
    "gn:feature_code":"PPL",
    "gn:name":"Unije",
    "gn:population":88,
    "gn:timezone":"Europe/Zagreb",
    "iso:country":"HR",
    "name:und_x_variant":[
        "Unie",
        "Unje",
        "Unije"
    ],
    "wof:name":"Unije",
    "wof:placetype":"locality",
    "wof:population":88
},
  "geometry": {"coordinates":[14.24778,44.63472],"type":"Point"}
}