{
  "type": "Feature",
  "properties": {
    "gn:admin1_code":"12.0",
    "gn:asciiname":"Luban",
    "gn:country_code":"HR",
    "gn:dem":374,
    "gn:feature_class":"P",
    "gn:feature_code":"PPL",
    "gn:name":"Luban",
    "gn:population":0,
    "gn:timezone":"Europe/Zagreb",
    "iso:country":"HR",
    "wof:name":"Luban",
    "wof:placetype":"locality"
},
  "geometry": {"coordinates":[14.42889,45.36444],"type":"Point"}
}