{
  "type": "Feature",
  "properties": {
    "gn:admin1_code":"8.0",
    "gn:admin2_code":"11049284.0",
    "gn:asciiname":"Bukovje",
    "gn:cc2":"HR",
    "gn:country_code":"HR",
    "gn:dem":602,
    "gn:feature_class":"P",
    "gn:feature_code":"PPL",
    "gn:name":"Bukovje",
    "gn:population":0,
    "gn:timezone":"Europe/Zagreb",
    "iso:country":"HR",
    "name:bos_x_preferred":[
        "Bukovje"
    ],
    "name:ceb_x_preferred":[
        "Bukovje"
    ],
    "name:hrv_x_preferred":[
        "Bukovje"
    ],
    "name:ita_x_preferred":[
        "Bukovje"
    ],
    "name:nld_x_preferred":[
        "Bukovje"
    ],
    "name:slv_x_preferred":[
        "Bukovje"
    ],
    "name:srp_x_preferred":[
        "\u0411\u0443\u043a\u043e\u0432\u0458\u0435"
    ],
    "name:ukr_x_preferred":[
        "\u0411\u0443\u043a\u043e\u0432'\u0454"
    ],
    "name:und_x_variant":[
        "Bukovlje"
    ],
    "wof:name":"Bukovje",
    "wof:placetype":"locality"
},
  "geometry": {"coordinates":[15.11472,45.02722],"type":"Point"}
}