{
  "type": "Feature",
  "properties": {
    "gn:admin1_code":"8.0",
    "gn:admin2_code":"11049284.0",
    "gn:asciiname":"Bukovje",
    "gn:cc2":"HR",
    "gn:country_code":"HR",
    "gn:dem":602,
    "gn:feature_class":"P",
    "gn:feature_code":"PPL",
    "gn:name":"Bukovje",
    "gn:population":0,
    "gn:timezone":"Europe/Zagreb",
    "iso:country":"HR",
    "name:und_x_variant":[
        "Bukovlje",
        "Bukovje"
    ],
    "wof:name":"Bukovje",
    "wof:placetype":"locality"
},
  "geometry": {"coordinates":[15.11472,45.02722],"type":"Point"}
}