{
  "type": "Feature",
  "properties": {
    "gn:admin1_code":"05",
    "gn:admin2_code":"11049278.0",
    "gn:asciiname":"Brocanac",
    "gn:country_code":"HR",
    "gn:dem":326,
    "gn:feature_class":"P",
    "gn:feature_code":"PPLL",
    "gn:name":"Bro\u010danac",
    "gn:population":0,
    "gn:timezone":"Europe/Zagreb",
    "iso:country":"HR",
    "name:bos_x_preferred":[
        "Bro\u0107anac"
    ],
    "name:cat_x_preferred":[
        "Bro\u0107anac"
    ],
    "name:hrv_x_preferred":[
        "Bro\u0107anac"
    ],
    "name:hun_x_preferred":[
        "Bro\u0107anac"
    ],
    "name:nld_x_preferred":[
        "Bro\u0107anac"
    ],
    "name:slv_x_preferred":[
        "Bro\u0107anac"
    ],
    "name:spa_x_preferred":[
        "Bro\u0107anac"
    ],
    "name:srp_x_preferred":[
        "\u0411\u0440\u043e\u045b\u0430\u043d\u0430\u0446"
    ],
    "name:ukr_x_preferred":[
        "\u0411\u0440\u043e\u0447\u0430\u043d\u0430\u0446\u044c"
    ],
    "name:und_x_variant":[
        "Bro\u010danac"
    ],
    "wof:name":"Brocanac",
    "wof:placetype":"locality"
},
  "geometry": {"coordinates":[15.62361,45.05833],"type":"Point"}
}