{
  "type": "Feature",
  "properties": {
    "gn:admin1_code":"19.0",
    "gn:asciiname":"Skarda",
    "gn:country_code":"HR",
    "gn:dem":5,
    "gn:feature_class":"P",
    "gn:feature_code":"PPL",
    "gn:name":"\u0160karda",
    "gn:population":0,
    "gn:timezone":"Europe/Zagreb",
    "iso:country":"HR",
    "wof:name":"Skarda",
    "wof:placetype":"locality"
},
  "geometry": {"coordinates":[14.70139,44.28889],"type":"Point"}
}