{
  "type": "Feature",
  "properties": {
    "gn:admin1_code":"8.0",
    "gn:asciiname":"Skendzici",
    "gn:country_code":"HR",
    "gn:dem":522,
    "gn:feature_class":"P",
    "gn:feature_code":"PPL",
    "gn:name":"Skend\u017ei\u0107i",
    "gn:population":0,
    "gn:timezone":"Europe/Zagreb",
    "iso:country":"HR",
    "wof:name":"Skendzici",
    "wof:placetype":"locality"
},
  "geometry": {"coordinates":[15.31056,44.89889],"type":"Point"}
}