{
  "type": "Feature",
  "properties": {
    "gn:admin1_code":"19",
    "gn:admin2_code":"11054319.0",
    "gn:asciiname":"Nadvrelo",
    "gn:cc2":"HR",
    "gn:country_code":"HR",
    "gn:dem":601,
    "gn:feature_class":"P",
    "gn:feature_code":"PPL",
    "gn:name":"Nadvrelo",
    "gn:population":1,
    "gn:timezone":"Europe/Zagreb",
    "iso:country":"HR",
    "name:und_x_variant":[
        "Nad Vrelom",
        "Nadvrelo"
    ],
    "wof:name":"Nadvrelo",
    "wof:placetype":"locality",
    "wof:population":1
},
  "geometry": {"coordinates":[16.07861,44.21778],"type":"Point"}
}