{
  "type": "Feature",
  "properties": {
    "gn:admin1_code":"8.0",
    "gn:admin2_code":"11049294.0",
    "gn:asciiname":"Mirkovic",
    "gn:country_code":"HR",
    "gn:dem":763,
    "gn:feature_class":"P",
    "gn:feature_code":"PPL",
    "gn:name":"Mirkovi\u0107",
    "gn:population":0,
    "gn:timezone":"Europe/Zagreb",
    "iso:country":"HR",
    "wof:name":"Mirkovic",
    "wof:placetype":"locality"
},
  "geometry": {"coordinates":[15.80306,44.45361],"type":"Point"}
}