{
  "type": "Feature",
  "properties": {
    "gn:admin1_code":"17",
    "gn:asciiname":"Neteca",
    "gn:country_code":"HR",
    "gn:dem":102,
    "gn:feature_class":"P",
    "gn:feature_code":"PPL",
    "gn:name":"Nete\u010da",
    "gn:population":0,
    "gn:timezone":"Europe/Zagreb",
    "iso:country":"HR",
    "wof:name":"Neteca",
    "wof:placetype":"locality"
},
  "geometry": {"coordinates":[17.41667,45.91667],"type":"Point"}
}