{
  "type": "Feature",
  "properties": {
    "gn:admin1_code":"15.0",
    "gn:asciiname":"Jasenak",
    "gn:cc2":"HR",
    "gn:country_code":"HR",
    "gn:dem":623,
    "gn:feature_class":"P",
    "gn:feature_code":"PPL",
    "gn:name":"Jasenak",
    "gn:population":0,
    "gn:timezone":"Europe/Zagreb",
    "iso:country":"HR",
    "name:und_x_variant":[
        "Donji Gali\u0107i",
        "Jasenak"
    ],
    "wof:name":"Jasenak",
    "wof:placetype":"locality"
},
  "geometry": {"coordinates":[16.93194,43.53472],"type":"Point"}
}