{
  "type": "Feature",
  "properties": {
    "gn:admin1_code":"15.0",
    "gn:asciiname":"Ujevici",
    "gn:country_code":"HR",
    "gn:dem":500,
    "gn:feature_class":"P",
    "gn:feature_code":"PPL",
    "gn:name":"Ujevi\u0107i",
    "gn:population":0,
    "gn:timezone":"Europe/Zagreb",
    "iso:country":"HR",
    "wof:name":"Ujevici",
    "wof:placetype":"locality"
},
  "geometry": {"coordinates":[17.11472,43.43472],"type":"Point"}
}