{
  "type": "Feature",
  "properties": {
    "gn:admin1_code":"04",
    "gn:admin2_code":"11054816.0",
    "gn:asciiname":"Koromacno",
    "gn:cc2":"HR",
    "gn:country_code":"HR",
    "gn:dem":155,
    "gn:feature_class":"P",
    "gn:feature_code":"PPL",
    "gn:name":"Koroma\u010dno",
    "gn:population":180,
    "gn:timezone":"Europe/Zagreb",
    "iso:country":"HR",
    "name:und_x_variant":[
        "Karoma\u010dno",
        "Valmazzinghi",
        "Koroma\u010dno"
    ],
    "wof:name":"Koromacno",
    "wof:placetype":"locality",
    "wof:population":180
},
  "geometry": {"coordinates":[14.12222,44.98056],"type":"Point"}
}