{
  "type": "Feature",
  "properties": {
    "gn:admin1_code":"15.0",
    "gn:asciiname":"Marasovac",
    "gn:country_code":"HR",
    "gn:dem":461,
    "gn:feature_class":"P",
    "gn:feature_code":"PPL",
    "gn:name":"Marasovac",
    "gn:population":0,
    "gn:timezone":"Europe/Zagreb",
    "iso:country":"HR",
    "wof:name":"Marasovac",
    "wof:placetype":"locality"
},
  "geometry": {"coordinates":[16.75056,43.73806],"type":"Point"}
}