{
  "type": "Feature",
  "properties": {
    "gn:admin1_code":"15",
    "gn:admin2_code":"11054615.0",
    "gn:asciiname":"Donji Humac",
    "gn:cc2":"HR",
    "gn:country_code":"HR",
    "gn:dem":313,
    "gn:feature_class":"P",
    "gn:feature_code":"PPL",
    "gn:name":"Donji Humac",
    "gn:population":0,
    "gn:timezone":"Europe/Zagreb",
    "iso:country":"HR",
    "name:bos_x_preferred":[
        "Donji Humac"
    ],
    "name:cat_x_preferred":[
        "Donji Humac"
    ],
    "name:deu_x_preferred":[
        "Donji Humac"
    ],
    "name:hrv_x_preferred":[
        "Donji Humac"
    ],
    "name:hun_x_preferred":[
        "Donji Humac"
    ],
    "name:nld_x_preferred":[
        "Donji Humac"
    ],
    "name:slk_x_preferred":[
        "Donji Humac"
    ],
    "name:slv_x_preferred":[
        "Donji Humac"
    ],
    "name:srp_x_preferred":[
        "\u0414\u043e\u045a\u0438 \u0425\u0443\u043c\u0430\u0446"
    ],
    "name:ukr_x_preferred":[
        "\u0414\u043e\u043d\u0456\u0439 \u0425\u0443\u043c\u0430\u0446\u044c"
    ],
    "name:und_x_variant":[
        "Humac Donji",
        "Donji Humac"
    ],
    "wof:name":"Donji Humac",
    "wof:placetype":"locality"
},
  "geometry": {"coordinates":[16.55583,43.34222000000001],"type":"Point"}
}