{
  "type": "Feature",
  "properties": {
    "gn:admin1_code":"8.0",
    "gn:asciiname":"Brdo",
    "gn:country_code":"HR",
    "gn:dem":572,
    "gn:feature_class":"P",
    "gn:feature_code":"PPL",
    "gn:name":"Brdo",
    "gn:population":0,
    "gn:timezone":"Europe/Zagreb",
    "iso:country":"HR",
    "wof:name":"Brdo",
    "wof:placetype":"locality"
},
  "geometry": {"coordinates":[15.45333,44.53278],"type":"Point"}
}