{
  "type": "Feature",
  "properties": {
    "gn:admin1_code":"20",
    "gn:admin2_code":"8260123.0",
    "gn:asciiname":"Graberec",
    "gn:country_code":"HR",
    "gn:dem":117,
    "gn:feature_class":"P",
    "gn:feature_code":"PPL",
    "gn:name":"Graberec",
    "gn:population":0,
    "gn:timezone":"Europe/Zagreb",
    "iso:country":"HR",
    "wof:name":"Graberec",
    "wof:placetype":"locality"
},
  "geometry": {"coordinates":[16.54309,45.80804000000001],"type":"Point"}
}