{
  "type": "Feature",
  "properties": {
    "gn:admin1_code":"12.0",
    "gn:asciiname":"Velilosini",
    "gn:country_code":"HR",
    "gn:dem":15,
    "gn:feature_class":"P",
    "gn:feature_code":"PPL",
    "gn:name":"Velilo\u0161ini",
    "gn:population":0,
    "gn:timezone":"Europe/Zagreb",
    "iso:country":"HR",
    "wof:name":"Velilosini",
    "wof:placetype":"locality"
},
  "geometry": {"coordinates":[14.50111,44.51861],"type":"Point"}
}