{
  "type": "Feature",
  "properties": {
    "gn:admin1_code":"06",
    "gn:admin2_code":"3197228.0",
    "gn:asciiname":"Osijek Vojakovacki",
    "gn:cc2":"HR",
    "gn:country_code":"HR",
    "gn:dem":282,
    "gn:feature_class":"P",
    "gn:feature_code":"PPL",
    "gn:name":"Osijek Vojakova\u010dki",
    "gn:population":205,
    "gn:timezone":"Europe/Zagreb",
    "iso:country":"HR",
    "name:und_x_variant":[
        "Osijek",
        "Osijek Vojakova\u010dki"
    ],
    "wof:name":"Osijek Vojakovacki",
    "wof:placetype":"locality",
    "wof:population":205
},
  "geometry": {"coordinates":[16.55,46.13333],"type":"Point"}
}