{
  "type": "Feature",
  "properties": {
    "gn:admin1_code":"15.0",
    "gn:asciiname":"Bralici",
    "gn:country_code":"HR",
    "gn:dem":369,
    "gn:feature_class":"P",
    "gn:feature_code":"PPL",
    "gn:name":"Brali\u0107i",
    "gn:population":0,
    "gn:timezone":"Europe/Zagreb",
    "iso:country":"HR",
    "wof:name":"Bralici",
    "wof:placetype":"locality"
},
  "geometry": {"coordinates":[16.60944,43.62917],"type":"Point"}
}