{
  "type": "Feature",
  "properties": {
    "gn:admin1_code":"08",
    "gn:admin2_code":"11049294.0",
    "gn:asciiname":"Jagodnje",
    "gn:country_code":"HR",
    "gn:dem":682,
    "gn:feature_class":"P",
    "gn:feature_code":"PPL",
    "gn:name":"Jagodnje",
    "gn:population":32,
    "gn:timezone":"Europe/Zagreb",
    "iso:country":"HR",
    "wof:name":"Jagodnje",
    "wof:placetype":"locality",
    "wof:population":32
},
  "geometry": {"coordinates":[15.59528,44.60694],"type":"Point"}
}