{
  "type": "Feature",
  "properties": {
    "gn:admin1_code":"8.0",
    "gn:asciiname":"Galinka",
    "gn:country_code":"HR",
    "gn:dem":681,
    "gn:feature_class":"P",
    "gn:feature_code":"PPL",
    "gn:name":"Galinka",
    "gn:population":0,
    "gn:timezone":"Europe/Zagreb",
    "iso:country":"HR",
    "wof:name":"Galinka",
    "wof:placetype":"locality"
},
  "geometry": {"coordinates":[15.36056,44.91889000000001],"type":"Point"}
}