{
  "type": "Feature",
  "properties": {
    "gn:admin1_code":"4.0",
    "gn:admin2_code":"11129784.0",
    "gn:asciiname":"Ferenci",
    "gn:country_code":"HR",
    "gn:dem":297,
    "gn:feature_class":"P",
    "gn:feature_code":"PPL",
    "gn:name":"Ferenci",
    "gn:population":69,
    "gn:timezone":"Europe/Zagreb",
    "iso:country":"HR",
    "name:bos_x_preferred":[
        "Ferenci"
    ],
    "name:cat_x_preferred":[
        "Ferenci"
    ],
    "name:hrv_x_preferred":[
        "Ferenci"
    ],
    "name:hun_x_preferred":[
        "Ferenci"
    ],
    "name:nld_x_preferred":[
        "Ferenci"
    ],
    "name:slv_x_preferred":[
        "Ferenci"
    ],
    "name:ukr_x_preferred":[
        "\u0424\u0435\u0440\u0435\u043d\u0446\u0456"
    ],
    "wof:name":"Ferenci",
    "wof:placetype":"locality",
    "wof:population":69
},
  "geometry": {"coordinates":[13.7525,45.31361],"type":"Point"}
}