{
  "type": "Feature",
  "properties": {
    "gn:admin1_code":"8.0",
    "gn:asciiname":"Pilipovici",
    "gn:country_code":"HR",
    "gn:dem":321,
    "gn:feature_class":"P",
    "gn:feature_code":"PPL",
    "gn:name":"Pilipovi\u0107i",
    "gn:population":0,
    "gn:timezone":"Europe/Zagreb",
    "iso:country":"HR",
    "wof:name":"Pilipovici",
    "wof:placetype":"locality"
},
  "geometry": {"coordinates":[16.12528,44.5125],"type":"Point"}
}