{
  "type": "Feature",
  "properties": {
    "gn:admin1_code":"15.0",
    "gn:asciiname":"Kraj",
    "gn:country_code":"HR",
    "gn:dem":20,
    "gn:feature_class":"P",
    "gn:feature_code":"PPL",
    "gn:name":"Kraj",
    "gn:population":0,
    "gn:timezone":"Europe/Zagreb",
    "iso:country":"HR",
    "wof:name":"Kraj",
    "wof:placetype":"locality"
},
  "geometry": {"coordinates":[17.10889,43.21833],"type":"Point"}
}