{
  "type": "Feature",
  "properties": {
    "gn:admin1_code":"19",
    "gn:asciiname":"Vrgada",
    "gn:country_code":"HR",
    "gn:dem":19,
    "gn:feature_class":"P",
    "gn:feature_code":"PPL",
    "gn:name":"Vrgada",
    "gn:population":249,
    "gn:timezone":"Europe/Zagreb",
    "iso:country":"HR",
    "name:deu_x_preferred":[
        "Vrgada"
    ],
    "name:hrv_x_preferred":[
        "Vrgada"
    ],
    "name:ind_x_preferred":[
        "Vrgada"
    ],
    "name:ita_x_preferred":[
        "Vergada"
    ],
    "name:nld_x_preferred":[
        "Vrgada"
    ],
    "name:nor_x_preferred":[
        "Vrgada"
    ],
    "name:pol_x_preferred":[
        "Vrgada"
    ],
    "name:rus_x_preferred":[
        "\u0412\u0440\u0433\u0430\u0434\u0430"
    ],
    "name:slv_x_preferred":[
        "Vrgada"
    ],
    "name:spa_x_preferred":[
        "Vrgada"
    ],
    "name:tur_x_preferred":[
        "Vrgada"
    ],
    "name:ukr_x_preferred":[
        "\u0412\u0440\u0433\u0430\u0434\u0430"
    ],
    "name:vie_x_preferred":[
        "Vrgada"
    ],
    "wof:name":"Vrgada",
    "wof:placetype":"locality",
    "wof:population":249
},
  "geometry": {"coordinates":[15.50306,43.85611],"type":"Point"}
}