{
  "type": "Feature",
  "properties": {
    "gn:admin1_code":"19",
    "gn:asciiname":"Vrgada",
    "gn:country_code":"HR",
    "gn:dem":19,
    "gn:feature_class":"P",
    "gn:feature_code":"PPL",
    "gn:name":"Vrgada",
    "gn:population":249,
    "gn:timezone":"Europe/Zagreb",
    "iso:country":"HR",
    "wof:name":"Vrgada",
    "wof:placetype":"locality",
    "wof:population":249
},
  "geometry": {"coordinates":[15.50306,43.85611],"type":"Point"}
}