{
  "type": "Feature",
  "properties": {
    "gn:admin1_code":"15.0",
    "gn:admin2_code":"11054612.0",
    "gn:asciiname":"Dograde",
    "gn:country_code":"HR",
    "gn:dem":139,
    "gn:feature_class":"P",
    "gn:feature_code":"PPL",
    "gn:name":"Dograde",
    "gn:population":194,
    "gn:timezone":"Europe/Zagreb",
    "iso:country":"HR",
    "wof:name":"Dograde",
    "wof:placetype":"locality",
    "wof:population":194
},
  "geometry": {"coordinates":[16.11444,43.54528],"type":"Point"}
}