{
  "type": "Feature",
  "properties": {
    "gn:admin1_code":"08",
    "gn:admin2_code":"11049293.0",
    "gn:asciiname":"Mrzli Dol",
    "gn:country_code":"HR",
    "gn:dem":765,
    "gn:feature_class":"P",
    "gn:feature_code":"PPL",
    "gn:name":"Mrzli Dol",
    "gn:population":28,
    "gn:timezone":"Europe/Zagreb",
    "iso:country":"HR",
    "wof:name":"Mrzli Dol",
    "wof:placetype":"locality",
    "wof:population":28
},
  "geometry": {"coordinates":[14.97722,45.03417],"type":"Point"}
}