{
  "type": "Feature",
  "properties": {
    "gn:admin1_code":"12",
    "gn:admin2_code":"11049443.0",
    "gn:asciiname":"Vele Mune",
    "gn:cc2":"HR",
    "gn:country_code":"HR",
    "gn:dem":647,
    "gn:feature_class":"P",
    "gn:feature_code":"PPL",
    "gn:name":"Vele Mune",
    "gn:population":122,
    "gn:timezone":"Europe/Zagreb",
    "iso:country":"HR",
    "name:und_x_variant":[
        "Mune Vele",
        "Velje Mune",
        "Mune",
        "Mune Grande",
        "Vele Mune"
    ],
    "wof:name":"Vele Mune",
    "wof:placetype":"locality",
    "wof:population":122
},
  "geometry": {"coordinates":[14.16722,45.45889],"type":"Point"}
}