{
  "type": "Feature",
  "properties": {
    "gn:admin1_code":"03",
    "gn:asciiname":"Istocna Plina",
    "gn:cc2":"HR",
    "gn:country_code":"HR",
    "gn:dem":29,
    "gn:feature_class":"P",
    "gn:feature_code":"PPLL",
    "gn:name":"Isto\u010dna Plina",
    "gn:population":0,
    "gn:timezone":"Europe/Zagreb",
    "iso:country":"HR",
    "name:und_x_variant":[
        "Plina",
        "Isto\u010dna Plina"
    ],
    "wof:name":"Istocna Plina",
    "wof:placetype":"locality"
},
  "geometry": {"coordinates":[17.48056,43.10028],"type":"Point"}
}