{
  "type": "Feature",
  "properties": {
    "gn:admin1_code":"15.0",
    "gn:asciiname":"Luke",
    "gn:country_code":"HR",
    "gn:dem":271,
    "gn:feature_class":"P",
    "gn:feature_code":"PPL",
    "gn:name":"Luke",
    "gn:population":0,
    "gn:timezone":"Europe/Zagreb",
    "iso:country":"HR",
    "name:bos_x_preferred":[
        "Luke"
    ],
    "name:ceb_x_preferred":[
        "Luke"
    ],
    "name:ces_x_preferred":[
        "Luke"
    ],
    "name:deu_x_preferred":[
        "Luke"
    ],
    "name:fra_x_preferred":[
        "Luke"
    ],
    "name:hrv_x_preferred":[
        "Luke"
    ],
    "name:hun_x_preferred":[
        "Luke"
    ],
    "name:hye_x_preferred":[
        "\u053c\u0578\u0582\u056f\u0565"
    ],
    "name:ita_x_preferred":[
        "Luke"
    ],
    "name:nld_x_preferred":[
        "Luke"
    ],
    "name:rus_x_preferred":[
        "\u041b\u0443\u043a\u0435"
    ],
    "name:slv_x_preferred":[
        "Luke"
    ],
    "name:srp_x_preferred":[
        "\u041b\u0443\u043a\u0435"
    ],
    "name:swe_x_preferred":[
        "Luke"
    ],
    "name:ukr_x_preferred":[
        "\u041b\u0443\u043a\u0435"
    ],
    "name:vol_x_preferred":[
        "Luke"
    ],
    "wof:name":"Luke",
    "wof:placetype":"locality"
},
  "geometry": {"coordinates":[16.74806,43.52056],"type":"Point"}
}