{
  "type": "Feature",
  "properties": {
    "gn:admin1_code":"13.0",
    "gn:asciiname":"Krnete",
    "gn:country_code":"HR",
    "gn:dem":395,
    "gn:feature_class":"P",
    "gn:feature_code":"PPL",
    "gn:name":"Krnete",
    "gn:population":0,
    "gn:timezone":"Europe/Zagreb",
    "iso:country":"HR",
    "wof:name":"Krnete",
    "wof:placetype":"locality"
},
  "geometry": {"coordinates":[16.25528,44.17972],"type":"Point"}
}