{
  "type": "Feature",
  "properties": {
    "gn:admin1_code":"15.0",
    "gn:asciiname":"Kuduzi",
    "gn:country_code":"HR",
    "gn:dem":745,
    "gn:feature_class":"P",
    "gn:feature_code":"PPL",
    "gn:name":"Kuduzi",
    "gn:population":0,
    "gn:timezone":"Europe/Zagreb",
    "iso:country":"HR",
    "wof:name":"Kuduzi",
    "wof:placetype":"locality"
},
  "geometry": {"coordinates":[16.51778,43.71306],"type":"Point"}
}