{
  "type": "Feature",
  "properties": {
    "gn:gn_country":"HR",
    "gn:gn_fcode":"PPL",
    "gn:gn_pop":0,
    "gn:population":965,
    "iso:country":"HR",
    "name:bos_x_preferred":[
        "Malinska"
    ],
    "name:bul_x_preferred":[
        "\u041c\u0430\u043b\u0438\u043d\u0441\u043a\u0430"
    ],
    "name:deu_x_preferred":[
        "Malinska"
    ],
    "name:eng_x_preferred":[
        "Malinska"
    ],
    "name:fra_x_preferred":[
        "Malinska"
    ],
    "name:hrv_x_preferred":[
        "Malinska"
    ],
    "name:hun_x_preferred":[
        "Malinska"
    ],
    "name:ita_x_preferred":[
        "Malinska"
    ],
    "name:nld_x_preferred":[
        "Malinska"
    ],
    "name:rus_x_preferred":[
        "\u041c\u0430\u043b\u0438\u043d\u0441\u043a\u0430"
    ],
    "name:slv_x_preferred":[
        "Malinska"
    ],
    "name:srp_x_preferred":[
        "\u041c\u0430\u043b\u0438\u043d\u0441\u043a\u0430"
    ],
    "name:swe_x_preferred":[
        "Malinska"
    ],
    "name:ukr_x_preferred":[
        "\u041c\u0430\u043b\u0456\u043d\u0441\u044c\u043a\u0430"
    ],
    "name:unk_x_variant":[
        "Malinsca"
    ],
    "qs_pg:aaroncc":"HR",
    "qs_pg:gn_country":"HR",
    "qs_pg:gn_fcode":"PPL",
    "qs_pg:gn_pop":0,
    "qs_pg:name":"Malinska",
    "qs_pg:name_adm0":"Hrvatska",
    "qs_pg:name_adm1":"Primorsko-Goranska",
    "qs_pg:photos":473,
    "qs_pg:photos_1k":96,
    "qs_pg:photos_9k":2,
    "qs_pg:photos_9r":5,
    "qs_pg:photos_all":473,
    "qs_pg:photos_sr":7,
    "qs_pg:pop_sr":0,
    "qs_pg:qs_pg_placetype":"locality",
    "qs_pg:qs_pg_placetype_gp":"Town",
    "qs_pg:woe_adm0":23424843,
    "woe:adm0_id":23424843,
    "woe:name_adm0":"Hrvatska",
    "woe:name_adm1":"Primorsko-Goranska",
    "woe:placetype":"Town",
    "wof:name":"Malinska",
    "wof:placetype":"locality",
    "wof:population":965
},
  "geometry": {"coordinates":[14.52828,45.12417],"type":"Point"}
}