{
  "type": "Feature",
  "properties": {
    "gn:admin1_code":"16",
    "gn:admin2_code":"11049308.0",
    "gn:asciiname":"Jazbina Visnjicka",
    "gn:cc2":"HR",
    "gn:country_code":"HR",
    "gn:dem":266,
    "gn:feature_class":"P",
    "gn:feature_code":"PPL",
    "gn:name":"Jazbina Vi\u0161nji\u010dka",
    "gn:population":25,
    "gn:timezone":"Europe/Zagreb",
    "iso:country":"HR",
    "name:und_x_variant":[
        "Vi\u0161nji\u010dka Jazbina",
        "Jazbina",
        "Jazbina Vi\u0161nji\u010dka"
    ],
    "wof:name":"Jazbina Visnjicka",
    "wof:placetype":"locality",
    "wof:population":25
},
  "geometry": {"coordinates":[15.96667,46.28333],"type":"Point"}
}