{
  "type": "Feature",
  "properties": {
    "gn:admin1_code":"10",
    "gn:admin2_code":"11054482.0",
    "gn:asciiname":"Koprivna",
    "gn:country_code":"HR",
    "gn:dem":86,
    "gn:feature_class":"P",
    "gn:feature_code":"PPL",
    "gn:name":"Koprivna",
    "gn:population":113,
    "gn:timezone":"Europe/Zagreb",
    "iso:country":"HR",
    "wof:name":"Koprivna",
    "wof:placetype":"locality",
    "wof:population":113
},
  "geometry": {"coordinates":[18.61389,45.40472000000001],"type":"Point"}
}