{
  "type": "Feature",
  "properties": {
    "gn:admin1_code":"15.0",
    "gn:asciiname":"Mandaci",
    "gn:country_code":"HR",
    "gn:dem":330,
    "gn:feature_class":"P",
    "gn:feature_code":"PPL",
    "gn:name":"Mandaci",
    "gn:population":0,
    "gn:timezone":"Europe/Zagreb",
    "iso:country":"HR",
    "wof:name":"Mandaci",
    "wof:placetype":"locality"
},
  "geometry": {"coordinates":[16.66,43.67667],"type":"Point"}
}