{
  "type": "Feature",
  "properties": {
    "gn:admin1_code":"14.0",
    "gn:asciiname":"Boturi",
    "gn:country_code":"HR",
    "gn:dem":192,
    "gn:feature_class":"P",
    "gn:feature_code":"PPL",
    "gn:name":"Boturi",
    "gn:population":0,
    "gn:timezone":"Europe/Zagreb",
    "iso:country":"HR",
    "wof:name":"Boturi",
    "wof:placetype":"locality"
},
  "geometry": {"coordinates":[15.98583,45.38472],"type":"Point"}
}