{
  "type": "Feature",
  "properties": {
    "gn:admin1_code":"8.0",
    "gn:asciiname":"Zaostra",
    "gn:country_code":"HR",
    "gn:dem":562,
    "gn:feature_class":"P",
    "gn:feature_code":"PPL",
    "gn:name":"Zao\u0161tra",
    "gn:population":0,
    "gn:timezone":"Europe/Zagreb",
    "iso:country":"HR",
    "wof:name":"Zaostra",
    "wof:placetype":"locality"
},
  "geometry": {"coordinates":[15.31861,44.53139],"type":"Point"}
}