{
  "type": "Feature",
  "properties": {
    "gn:admin1_code":"15.0",
    "gn:asciiname":"Pleici",
    "gn:country_code":"HR",
    "gn:dem":419,
    "gn:feature_class":"P",
    "gn:feature_code":"PPL",
    "gn:name":"Plei\u0107i",
    "gn:population":0,
    "gn:timezone":"Europe/Zagreb",
    "iso:country":"HR",
    "wof:name":"Pleici",
    "wof:placetype":"locality"
},
  "geometry": {"coordinates":[16.84944,43.54361],"type":"Point"}
}