{
  "type": "Feature",
  "properties": {
    "gn:admin1_code":"19.0",
    "gn:asciiname":"Vagan Popinski",
    "gn:cc2":"HR",
    "gn:country_code":"HR",
    "gn:dem":643,
    "gn:feature_class":"P",
    "gn:feature_code":"PPL",
    "gn:name":"Vagan Popinski",
    "gn:population":0,
    "gn:timezone":"Europe/Zagreb",
    "iso:country":"HR",
    "name:und_x_variant":[
        "Vagan",
        "Vagan Popinski"
    ],
    "wof:name":"Vagan Popinski",
    "wof:placetype":"locality"
},
  "geometry": {"coordinates":[16.03,44.26611],"type":"Point"}
}