{
  "type": "Feature",
  "properties": {
    "gn:admin1_code":"01",
    "gn:admin2_code":"11049406.0",
    "gn:asciiname":"Samarica",
    "gn:country_code":"HR",
    "gn:dem":136,
    "gn:feature_class":"P",
    "gn:feature_code":"PPL",
    "gn:name":"Samarica",
    "gn:population":195,
    "gn:timezone":"Europe/Zagreb",
    "iso:country":"HR",
    "wof:name":"Samarica",
    "wof:placetype":"locality",
    "wof:population":195
},
  "geometry": {"coordinates":[16.76889,45.69778],"type":"Point"}
}