{
  "type": "Feature",
  "properties": {
    "gn:admin1_code":"8.0",
    "gn:asciiname":"Rukavine",
    "gn:country_code":"HR",
    "gn:dem":425,
    "gn:feature_class":"P",
    "gn:feature_code":"PPL",
    "gn:name":"Rukavine",
    "gn:population":0,
    "gn:timezone":"Europe/Zagreb",
    "iso:country":"HR",
    "wof:name":"Rukavine",
    "wof:placetype":"locality"
},
  "geometry": {"coordinates":[15.125,44.90583],"type":"Point"}
}