{
  "type": "Feature",
  "properties": {
    "gn:admin1_code":"15",
    "gn:admin2_code":"3190864.0",
    "gn:asciiname":"Karakasica",
    "gn:country_code":"HR",
    "gn:dem":315,
    "gn:feature_class":"P",
    "gn:feature_code":"PPL",
    "gn:name":"Karaka\u0161ica",
    "gn:population":665,
    "gn:timezone":"Europe/Zagreb",
    "iso:country":"HR",
    "name:und_x_variant":[
        "Karaka\u0161ica"
    ],
    "wof:name":"Karakasica",
    "wof:placetype":"locality",
    "wof:population":665
},
  "geometry": {"coordinates":[16.63694,43.73472],"type":"Point"}
}