{
  "type": "Feature",
  "properties": {
    "gn:admin1_code":"15",
    "gn:admin2_code":"3190864.0",
    "gn:asciiname":"Karakasica",
    "gn:country_code":"HR",
    "gn:dem":315,
    "gn:feature_class":"P",
    "gn:feature_code":"PPL",
    "gn:name":"Karaka\u0161ica",
    "gn:population":665,
    "gn:timezone":"Europe/Zagreb",
    "iso:country":"HR",
    "name:bos_x_preferred":[
        "Karaka\u0161ica"
    ],
    "name:cat_x_preferred":[
        "Karaka\u0161ica"
    ],
    "name:hrv_x_preferred":[
        "Karaka\u0161ica"
    ],
    "name:hun_x_preferred":[
        "Karaka\u0161ica"
    ],
    "name:slv_x_preferred":[
        "Karaka\u0161ica"
    ],
    "name:srp_x_preferred":[
        "\u041a\u0430\u0440\u0430\u043a\u0430\u0448\u0438\u0446\u0430"
    ],
    "name:ukr_x_preferred":[
        "\u041a\u0430\u0440\u0430\u043a\u0430\u0448\u0438\u0446\u044f"
    ],
    "wof:name":"Karakasica",
    "wof:placetype":"locality",
    "wof:population":665
},
  "geometry": {"coordinates":[16.63694,43.73472],"type":"Point"}
}