{
  "type": "Feature",
  "properties": {
    "gn:admin1_code":"8.0",
    "gn:asciiname":"Oljubine",
    "gn:country_code":"HR",
    "gn:dem":721,
    "gn:feature_class":"P",
    "gn:feature_code":"PPL",
    "gn:name":"Oljubine",
    "gn:population":0,
    "gn:timezone":"Europe/Zagreb",
    "iso:country":"HR",
    "wof:name":"Oljubine",
    "wof:placetype":"locality"
},
  "geometry": {"coordinates":[15.63639,44.72194],"type":"Point"}
}