{
  "type": "Feature",
  "properties": {
    "gn:admin1_code":"14.0",
    "gn:asciiname":"Gornja Lovca",
    "gn:country_code":"HR",
    "gn:dem":344,
    "gn:feature_class":"P",
    "gn:feature_code":"PPL",
    "gn:name":"Gornja Lov\u010da",
    "gn:population":0,
    "gn:timezone":"Europe/Zagreb",
    "iso:country":"HR",
    "wof:name":"Gornja Lovca",
    "wof:placetype":"locality"
},
  "geometry": {"coordinates":[16.34778,45.2375],"type":"Point"}
}