{
  "type": "Feature",
  "properties": {
    "gn:admin1_code":"20",
    "gn:admin2_code":"11054889.0",
    "gn:asciiname":"Kalinovica",
    "gn:country_code":"HR",
    "gn:dem":150,
    "gn:feature_class":"P",
    "gn:feature_code":"PPL",
    "gn:name":"Kalinovica",
    "gn:population":385,
    "gn:timezone":"Europe/Zagreb",
    "iso:country":"HR",
    "name:bos_x_preferred":[
        "Kalinovica"
    ],
    "name:hrv_x_preferred":[
        "Kalinovica"
    ],
    "name:hun_x_preferred":[
        "Kalinovica"
    ],
    "name:nld_x_preferred":[
        "Kalinovica"
    ],
    "name:slv_x_preferred":[
        "Kalinovica"
    ],
    "name:srp_x_preferred":[
        "\u041a\u0430\u043b\u0438\u043d\u043e\u0432\u0438\u0446\u0430"
    ],
    "name:ukr_x_preferred":[
        "\u041a\u0430\u043b\u0438\u043d\u043e\u0432\u0438\u0446\u044f"
    ],
    "wof:name":"Kalinovica",
    "wof:placetype":"locality",
    "wof:population":385
},
  "geometry": {"coordinates":[15.78333,45.76667],"type":"Point"}
}