{
  "type": "Feature",
  "properties": {
    "gn:admin1_code":"12",
    "gn:admin2_code":"11049430.0",
    "gn:asciiname":"Jurandvor",
    "gn:country_code":"HR",
    "gn:dem":77,
    "gn:feature_class":"P",
    "gn:feature_code":"PPL",
    "gn:name":"Jurandvor",
    "gn:population":299,
    "gn:timezone":"Europe/Zagreb",
    "iso:country":"HR",
    "name:bos_x_preferred":[
        "Jurandvor"
    ],
    "name:fra_x_preferred":[
        "Jurandvor"
    ],
    "name:hrv_x_preferred":[
        "Jurandvor"
    ],
    "name:hun_x_preferred":[
        "Jurandvor"
    ],
    "name:slv_x_preferred":[
        "Jurandvor"
    ],
    "name:spa_x_preferred":[
        "Jurandvor"
    ],
    "name:srp_x_preferred":[
        "\u0408\u0443\u0440\u0430\u043d\u0434\u0432\u043e\u0440"
    ],
    "name:ukr_x_preferred":[
        "\u042e\u0440\u0430\u043d\u0434\u0432\u043e\u0440"
    ],
    "wof:name":"Jurandvor",
    "wof:placetype":"locality",
    "wof:population":299
},
  "geometry": {"coordinates":[14.7375,44.98],"type":"Point"}
}