{
  "type": "Feature",
  "properties": {
    "gn:admin1_code":"04",
    "gn:admin2_code":"11054804.0",
    "gn:asciiname":"Rakotule",
    "gn:cc2":"HR",
    "gn:country_code":"HR",
    "gn:dem":282,
    "gn:feature_class":"P",
    "gn:feature_code":"PPL",
    "gn:name":"Rakotule",
    "gn:population":226,
    "gn:timezone":"Europe/Zagreb",
    "iso:country":"HR",
    "name:und_x_variant":[
        "Rakotole",
        "Rakotule"
    ],
    "wof:name":"Rakotule",
    "wof:placetype":"locality",
    "wof:population":226
},
  "geometry": {"coordinates":[13.80694,45.30722],"type":"Point"}
}