{
  "type": "Feature",
  "properties": {
    "gn:admin1_code":"15.0",
    "gn:asciiname":"Cvitkovici",
    "gn:country_code":"HR",
    "gn:dem":716,
    "gn:feature_class":"P",
    "gn:feature_code":"PPL",
    "gn:name":"Cvitkovi\u0107i",
    "gn:population":0,
    "gn:timezone":"Europe/Zagreb",
    "iso:country":"HR",
    "wof:name":"Cvitkovici",
    "wof:placetype":"locality"
},
  "geometry": {"coordinates":[16.55278,43.765],"type":"Point"}
}