{
  "type": "Feature",
  "properties": {
    "gn:admin1_code":"10",
    "gn:admin2_code":"11054482.0",
    "gn:asciiname":"Palaca",
    "gn:country_code":"HR",
    "gn:dem":82,
    "gn:feature_class":"P",
    "gn:feature_code":"PPL",
    "gn:name":"Pala\u010da",
    "gn:population":241,
    "gn:timezone":"Europe/Zagreb",
    "iso:country":"HR",
    "name:bos_x_preferred":[
        "Pala\u010da"
    ],
    "name:ceb_x_preferred":[
        "Pala\u010da"
    ],
    "name:hrv_x_preferred":[
        "Pala\u010da"
    ],
    "name:slv_x_preferred":[
        "Pala\u010da"
    ],
    "name:srp_x_preferred":[
        "\u041f\u0430\u043b\u0430\u0447\u0430"
    ],
    "name:swe_x_preferred":[
        "Pala\u010da"
    ],
    "name:ukr_x_preferred":[
        "\u041f\u0430\u043b\u0430\u0447\u0430"
    ],
    "name:und_x_variant":[
        "Pala\u010da"
    ],
    "wof:name":"Palaca",
    "wof:placetype":"locality",
    "wof:population":241
},
  "geometry": {"coordinates":[18.72,45.41083],"type":"Point"}
}