{
  "type": "Feature",
  "properties": {
    "gn:admin1_code":"17.0",
    "gn:admin2_code":"11049459.0",
    "gn:asciiname":"Bacevac",
    "gn:country_code":"HR",
    "gn:dem":101,
    "gn:feature_class":"P",
    "gn:feature_code":"PPL",
    "gn:name":"Ba\u010devac",
    "gn:population":370,
    "gn:timezone":"Europe/Zagreb",
    "iso:country":"HR",
    "wof:name":"Bacevac",
    "wof:placetype":"locality",
    "wof:population":370
},
  "geometry": {"coordinates":[17.48333,45.86667],"type":"Point"}
}