{
  "type": "Feature",
  "properties": {
    "gn:admin1_code":"10.0",
    "gn:admin2_code":"11054472.0",
    "gn:asciiname":"Benicanci",
    "gn:country_code":"HR",
    "gn:dem":91,
    "gn:feature_class":"P",
    "gn:feature_code":"PPL",
    "gn:name":"Beni\u010danci",
    "gn:population":520,
    "gn:timezone":"Europe/Zagreb",
    "iso:country":"HR",
    "name:bos_x_preferred":[
        "Beni\u010danci"
    ],
    "name:hrv_x_preferred":[
        "Beni\u010danci"
    ],
    "name:slv_x_preferred":[
        "Beni\u010danci"
    ],
    "name:srp_x_preferred":[
        "\u0411\u0435\u043d\u0438\u0447\u0430\u043d\u0446\u0438"
    ],
    "name:ukr_x_preferred":[
        "\u0411\u0435\u043d\u0438\u0447\u0430\u043d\u0446\u0456"
    ],
    "wof:name":"Benicanci",
    "wof:placetype":"locality",
    "wof:population":520
},
  "geometry": {"coordinates":[18.17667,45.63861],"type":"Point"}
}