{
  "type": "Feature",
  "properties": {
    "gn:asciiname":"Salakovci",
    "gn:country_code":"HR",
    "gn:dem":279,
    "gn:elevation":"0.0",
    "gn:feature_class":"P",
    "gn:feature_code":"PPL",
    "gn:name":"Salakovci",
    "gn:population":48,
    "gn:timezone":"Europe/Zagreb",
    "iso:country":"HR",
    "wof:name":"Salakovci",
    "wof:placetype":"locality",
    "wof:population":48
},
  "geometry": {"coordinates":[14.091,45.05638],"type":"Point"}
}