{
  "type": "Feature",
  "properties": {
    "gn:admin1_code":"05",
    "gn:admin2_code":"11049270.0",
    "gn:asciiname":"Donji Zvecaj",
    "gn:cc2":"HR",
    "gn:country_code":"HR",
    "gn:dem":167,
    "gn:feature_class":"P",
    "gn:feature_code":"PPL",
    "gn:name":"Donji Zve\u010daj",
    "gn:population":0,
    "gn:timezone":"Europe/Zagreb",
    "iso:country":"HR",
    "name:und_x_variant":[
        "Zve\u010daj",
        "Donji Zve\u010daj"
    ],
    "wof:name":"Donji Zvecaj",
    "wof:placetype":"locality"
},
  "geometry": {"coordinates":[15.41667,45.36667],"type":"Point"}
}