{
  "type": "Feature",
  "properties": {
    "gn:admin1_code":"12.0",
    "gn:asciiname":"Pogana",
    "gn:country_code":"HR",
    "gn:dem":15,
    "gn:feature_class":"P",
    "gn:feature_code":"PPL",
    "gn:name":"Pogana",
    "gn:population":0,
    "gn:timezone":"Europe/Zagreb",
    "iso:country":"HR",
    "wof:name":"Pogana",
    "wof:placetype":"locality"
},
  "geometry": {"coordinates":[14.50583,44.62028],"type":"Point"}
}