{
  "type": "Feature",
  "properties": {
    "gn:admin1_code":"12.0",
    "gn:asciiname":"Pogana",
    "gn:country_code":"HR",
    "gn:dem":15,
    "gn:feature_class":"P",
    "gn:feature_code":"PPL",
    "gn:name":"Pogana",
    "gn:population":0,
    "gn:timezone":"Europe/Zagreb",
    "iso:country":"HR",
    "name:ceb_x_preferred":[
        "Comuna Pogana"
    ],
    "name:ita_x_preferred":[
        "Pogana"
    ],
    "name:msa_x_preferred":[
        "Pogana"
    ],
    "name:nld_x_preferred":[
        "Pogana"
    ],
    "name:por_x_preferred":[
        "Pogana"
    ],
    "name:ron_x_preferred":[
        "Comuna Pogana"
    ],
    "name:srp_x_preferred":[
        "\u041e\u043f\u0448\u0442\u0438\u043d\u0430 \u041f\u043e\u0433\u0430\u043d\u0430"
    ],
    "name:ukr_x_preferred":[
        "\u041f\u043e\u0433\u0430\u043d\u0430"
    ],
    "name:vie_x_preferred":[
        "Pogana"
    ],
    "name:zho_x_preferred":[
        "\u6ce2\u52a0\u7d0d\u9109"
    ],
    "wof:name":"Pogana",
    "wof:placetype":"locality"
},
  "geometry": {"coordinates":[14.50583,44.62028],"type":"Point"}
}