{
  "type": "Feature",
  "properties": {
    "gn:admin1_code":"16",
    "gn:asciiname":"Krizance",
    "gn:cc2":"HR",
    "gn:country_code":"HR",
    "gn:dem":301,
    "gn:feature_class":"P",
    "gn:feature_code":"PPL",
    "gn:name":"Kri\u017ean\u010de",
    "gn:population":126,
    "gn:timezone":"Europe/Zagreb",
    "iso:country":"HR",
    "name:und_x_variant":[
        "Kri\u017eanci",
        "Kri\u017ean\u010de"
    ],
    "wof:name":"Krizance",
    "wof:placetype":"locality",
    "wof:population":126
},
  "geometry": {"coordinates":[16.09677000000001,46.33697],"type":"Point"}
}