{
  "type": "Feature",
  "properties": {
    "gn:admin1_code":"16",
    "gn:admin2_code":"11049302.0",
    "gn:asciiname":"Donji Kneginec",
    "gn:cc2":"HR",
    "gn:country_code":"HR",
    "gn:dem":169,
    "gn:feature_class":"P",
    "gn:feature_code":"PPL",
    "gn:name":"Donji Kneginec",
    "gn:population":743,
    "gn:timezone":"Europe/Zagreb",
    "iso:country":"HR",
    "name:und_x_variant":[
        "Kneginec-dolnji",
        "Kneginec",
        "Donji Kneginec"
    ],
    "wof:name":"Donji Kneginec",
    "wof:placetype":"locality",
    "wof:population":743
},
  "geometry": {"coordinates":[16.38444,46.25944000000001],"type":"Point"}
}