{
  "type": "Feature",
  "properties": {
    "gn:admin1_code":"14.0",
    "gn:asciiname":"Madnovic",
    "gn:country_code":"HR",
    "gn:dem":263,
    "gn:feature_class":"P",
    "gn:feature_code":"PPL",
    "gn:name":"Madnovic",
    "gn:population":0,
    "gn:timezone":"Europe/Zagreb",
    "iso:country":"HR",
    "wof:name":"Madnovic",
    "wof:placetype":"locality"
},
  "geometry": {"coordinates":[16.04222,45.23361],"type":"Point"}
}