{
  "type": "Feature",
  "properties": {
    "gn:admin1_code":"15.0",
    "gn:asciiname":"Kostrici",
    "gn:country_code":"HR",
    "gn:dem":709,
    "gn:feature_class":"P",
    "gn:feature_code":"PPL",
    "gn:name":"Ko\u0161tri\u0107i",
    "gn:population":0,
    "gn:timezone":"Europe/Zagreb",
    "iso:country":"HR",
    "wof:name":"Kostrici",
    "wof:placetype":"locality"
},
  "geometry": {"coordinates":[17.07917,43.54167],"type":"Point"}
}