{
  "type": "Feature",
  "properties": {
    "gn:gn_country":"HR",
    "gn:gn_fcode":"PPL",
    "gn:gn_pop":0,
    "iso:country":"HR",
    "name:bos_x_preferred":[
        "Lovre\u010dica"
    ],
    "name:eng_x_preferred":[
        "Lovre\u010dica"
    ],
    "name:fra_x_preferred":[
        "Lovre\u010dica"
    ],
    "name:hrv_x_preferred":[
        "Lovre\u010dica"
    ],
    "name:hun_x_preferred":[
        "Lovre\u010dica"
    ],
    "name:nld_x_preferred":[
        "Lovre\u010dica"
    ],
    "name:slv_x_preferred":[
        "Lovre\u010dica"
    ],
    "name:srp_x_preferred":[
        "\u041b\u043e\u0432\u0440\u0435\u0447\u0438\u0446\u0430"
    ],
    "name:swe_x_preferred":[
        "Lovre\u010dica"
    ],
    "name:unk_x_variant":[
        "San Lorenzo in Daila"
    ],
    "qs_pg:aaroncc":"HR",
    "qs_pg:gn_country":"HR",
    "qs_pg:gn_fcode":"PPL",
    "qs_pg:gn_pop":0,
    "qs_pg:name":"Lovre\u010dica",
    "qs_pg:name_adm0":"Hrvatska",
    "qs_pg:name_adm1":"Istarska",
    "qs_pg:photos":143,
    "qs_pg:photos_1k":29,
    "qs_pg:photos_9k":1,
    "qs_pg:photos_9r":3,
    "qs_pg:photos_all":143,
    "qs_pg:photos_sr":3,
    "qs_pg:pop_sr":0,
    "qs_pg:qs_pg_placetype":"locality",
    "qs_pg:qs_pg_placetype_gp":"Town",
    "qs_pg:woe_adm0":23424843,
    "woe:adm0_id":23424843,
    "woe:name_adm0":"Hrvatska",
    "woe:name_adm1":"Istarska",
    "woe:placetype":"Town",
    "wof:name":"Lovre\u010dica",
    "wof:placetype":"locality"
},
  "geometry": {"coordinates":[13.54056,45.38194],"type":"Point"}
}