{
  "type": "Feature",
  "properties": {
    "gn:admin1_code":"14",
    "gn:admin2_code":"3187231.0",
    "gn:asciiname":"Gornja Trstenica",
    "gn:country_code":"HR",
    "gn:dem":190,
    "gn:feature_class":"P",
    "gn:feature_code":"PPL",
    "gn:name":"Gornja Trstenica",
    "gn:population":88,
    "gn:timezone":"Europe/Zagreb",
    "iso:country":"HR",
    "wof:name":"Gornja Trstenica",
    "wof:placetype":"locality",
    "wof:population":88
},
  "geometry": {"coordinates":[15.94694,45.39],"type":"Point"}
}