{
  "type": "Feature",
  "properties": {
    "gn:admin1_code":"14",
    "gn:admin2_code":"3187231.0",
    "gn:asciiname":"Gornja Trstenica",
    "gn:country_code":"HR",
    "gn:dem":190,
    "gn:feature_class":"P",
    "gn:feature_code":"PPL",
    "gn:name":"Gornja Trstenica",
    "gn:population":88,
    "gn:timezone":"Europe/Zagreb",
    "iso:country":"HR",
    "name:bos_x_preferred":[
        "Gornja Trstenica"
    ],
    "name:fra_x_preferred":[
        "Gornja Trstenica"
    ],
    "name:hrv_x_preferred":[
        "Gornja Trstenica"
    ],
    "name:hun_x_preferred":[
        "Gornja Trstenica"
    ],
    "name:nld_x_preferred":[
        "Gornja Trstenica"
    ],
    "name:slv_x_preferred":[
        "Gornja Trstenica"
    ],
    "name:spa_x_preferred":[
        "Gornja Trstenica"
    ],
    "name:srp_x_preferred":[
        "\u0413\u043e\u0440\u045a\u0430 \u0422\u0440\u0441\u0442\u0435\u043d\u0438\u0446\u0430"
    ],
    "name:ukr_x_preferred":[
        "\u0413\u043e\u0440\u043d\u044f \u0422\u0440\u0441\u0442\u0435\u043d\u0438\u0446\u044f"
    ],
    "wof:name":"Gornja Trstenica",
    "wof:placetype":"locality",
    "wof:population":88
},
  "geometry": {"coordinates":[15.94694,45.39],"type":"Point"}
}