{
  "type": "Feature",
  "properties": {
    "gn:admin1_code":"4.0",
    "gn:admin2_code":"11054808.0",
    "gn:asciiname":"Krasa",
    "gn:country_code":"HR",
    "gn:dem":179,
    "gn:feature_class":"P",
    "gn:feature_code":"PPL",
    "gn:name":"Krasa",
    "gn:population":0,
    "gn:timezone":"Europe/Zagreb",
    "iso:country":"HR",
    "wof:name":"Krasa",
    "wof:placetype":"locality"
},
  "geometry": {"coordinates":[14.02889,44.98972],"type":"Point"}
}