{
  "type": "Feature",
  "properties": {
    "gn:admin1_code":"4.0",
    "gn:admin2_code":"11054820.0",
    "gn:asciiname":"Bokordici",
    "gn:cc2":"HR",
    "gn:country_code":"HR",
    "gn:dem":274,
    "gn:feature_class":"P",
    "gn:feature_code":"PPL",
    "gn:name":"Bokordi\u0107i",
    "gn:population":76,
    "gn:timezone":"Europe/Zagreb",
    "iso:country":"HR",
    "name:und_x_variant":[
        "Boccordi",
        "Bokordi\u0107i"
    ],
    "wof:name":"Bokordici",
    "wof:placetype":"locality",
    "wof:population":76
},
  "geometry": {"coordinates":[13.91194,45.06194],"type":"Point"}
}