{
  "type": "Feature",
  "properties": {
    "gn:admin1_code":"11.0",
    "gn:admin2_code":"11049479.0",
    "gn:asciiname":"Doljanci",
    "gn:country_code":"HR",
    "gn:dem":344,
    "gn:feature_class":"P",
    "gn:feature_code":"PPL",
    "gn:name":"Doljanci",
    "gn:population":84,
    "gn:timezone":"Europe/Zagreb",
    "iso:country":"HR",
    "wof:name":"Doljanci",
    "wof:placetype":"locality",
    "wof:population":84
},
  "geometry": {"coordinates":[17.61083,45.45139],"type":"Point"}
}