{
  "type": "Feature",
  "properties": {
    "gn:admin1_code":"19.0",
    "gn:asciiname":"Magas",
    "gn:country_code":"HR",
    "gn:dem":114,
    "gn:feature_class":"P",
    "gn:feature_code":"PPL",
    "gn:name":"Maga\u0161",
    "gn:population":0,
    "gn:timezone":"Europe/Zagreb",
    "iso:country":"HR",
    "wof:name":"Magas",
    "wof:placetype":"locality"
},
  "geometry": {"coordinates":[15.46833,44.24889],"type":"Point"}
}