{
  "type": "Feature",
  "properties": {
    "gn:admin1_code":"12",
    "gn:admin2_code":"11049443.0",
    "gn:asciiname":"Zaluki",
    "gn:cc2":"HR",
    "gn:country_code":"HR",
    "gn:dem":371,
    "gn:feature_class":"P",
    "gn:feature_code":"PPL",
    "gn:name":"Zaluki",
    "gn:population":73,
    "gn:timezone":"Europe/Zagreb",
    "iso:country":"HR",
    "name:und_x_variant":[
        "Zaluche",
        "Zaluki"
    ],
    "wof:name":"Zaluki",
    "wof:placetype":"locality",
    "wof:population":73
},
  "geometry": {"coordinates":[14.28167,45.40361],"type":"Point"}
}