{
  "type": "Feature",
  "properties": {
    "gn:admin1_code":"15.0",
    "gn:asciiname":"Domazeti",
    "gn:country_code":"HR",
    "gn:dem":814,
    "gn:feature_class":"P",
    "gn:feature_code":"PPL",
    "gn:name":"Domazeti",
    "gn:population":0,
    "gn:timezone":"Europe/Zagreb",
    "iso:country":"HR",
    "wof:name":"Domazeti",
    "wof:placetype":"locality"
},
  "geometry": {"coordinates":[16.54917,43.75306],"type":"Point"}
}