{
  "type": "Feature",
  "properties": {
    "gn:admin1_code":"3.0",
    "gn:asciiname":"Poduciji Brig",
    "gn:country_code":"HR",
    "gn:dem":15,
    "gn:feature_class":"P",
    "gn:feature_code":"PPL",
    "gn:name":"Podu\u010diji Brig",
    "gn:population":0,
    "gn:timezone":"Europe/Zagreb",
    "iso:country":"HR",
    "wof:name":"Poduciji Brig",
    "wof:placetype":"locality"
},
  "geometry": {"coordinates":[17.50139,43.05167],"type":"Point"}
}