{
  "type": "Feature",
  "properties": {
    "gn:admin1_code":"19.0",
    "gn:asciiname":"Bokanjac",
    "gn:country_code":"HR",
    "gn:dem":76,
    "gn:feature_class":"P",
    "gn:feature_code":"PPL",
    "gn:name":"Bokanjac",
    "gn:population":0,
    "gn:timezone":"Europe/Zagreb",
    "iso:country":"HR",
    "wof:name":"Bokanjac",
    "wof:placetype":"locality"
},
  "geometry": {"coordinates":[15.24667,44.145],"type":"Point"}
}