{
  "type": "Feature",
  "properties": {
    "gn:admin1_code":"8.0",
    "gn:admin2_code":"11049292.0",
    "gn:asciiname":"Varicaci",
    "gn:country_code":"HR",
    "gn:dem":808,
    "gn:feature_class":"P",
    "gn:feature_code":"PPL",
    "gn:name":"Vari\u010daci",
    "gn:population":0,
    "gn:timezone":"Europe/Zagreb",
    "iso:country":"HR",
    "wof:name":"Varicaci",
    "wof:placetype":"locality"
},
  "geometry": {"coordinates":[15.63917,44.77083],"type":"Point"}
}