{
  "type": "Feature",
  "properties": {
    "gn:admin1_code":"06",
    "gn:admin2_code":"3200960.0",
    "gn:asciiname":"Sirova Katalena",
    "gn:cc2":"HR",
    "gn:country_code":"HR",
    "gn:dem":174,
    "gn:feature_class":"P",
    "gn:feature_code":"PPL",
    "gn:name":"Sirova Katalena",
    "gn:population":281,
    "gn:timezone":"Europe/Zagreb",
    "iso:country":"HR",
    "name:und_x_variant":[
        "Sirava-Katalena",
        "Sirova Katalena"
    ],
    "wof:name":"Sirova Katalena",
    "wof:placetype":"locality",
    "wof:population":281
},
  "geometry": {"coordinates":[17.06028,45.96083],"type":"Point"}
}