{
  "type": "Feature",
  "properties": {
    "gn:admin1_code":"19.0",
    "gn:asciiname":"Podorjak",
    "gn:country_code":"HR",
    "gn:dem":114,
    "gn:feature_class":"P",
    "gn:feature_code":"PPL",
    "gn:name":"Podorjak",
    "gn:population":0,
    "gn:timezone":"Europe/Zagreb",
    "iso:country":"HR",
    "wof:name":"Podorjak",
    "wof:placetype":"locality"
},
  "geometry": {"coordinates":[15.62694,44.16306],"type":"Point"}
}