{
  "type": "Feature",
  "properties": {
    "gn:admin1_code":"2.0",
    "gn:admin2_code":"11049498.0",
    "gn:asciiname":"Bili Brig",
    "gn:country_code":"HR",
    "gn:dem":130,
    "gn:feature_class":"P",
    "gn:feature_code":"PPL",
    "gn:name":"Bili Brig",
    "gn:population":272,
    "gn:timezone":"Europe/Zagreb",
    "iso:country":"HR",
    "wof:name":"Bili Brig",
    "wof:placetype":"locality",
    "wof:population":272
},
  "geometry": {"coordinates":[17.61472000000001,45.21056],"type":"Point"}
}