{
  "type": "Feature",
  "properties": {
    "gn:admin1_code":"01",
    "gn:admin2_code":"11049399.0",
    "gn:asciiname":"Gornji Sregani",
    "gn:country_code":"HR",
    "gn:dem":159,
    "gn:feature_class":"P",
    "gn:feature_code":"PPL",
    "gn:name":"Gornji Sre\u0111ani",
    "gn:population":265,
    "gn:timezone":"Europe/Zagreb",
    "iso:country":"HR",
    "wof:name":"Gornji Sregani",
    "wof:placetype":"locality",
    "wof:population":265
},
  "geometry": {"coordinates":[17.16306,45.52861],"type":"Point"}
}