{
  "type": "Feature",
  "properties": {
    "gn:admin1_code":"1.0",
    "gn:asciiname":"Sabani",
    "gn:country_code":"HR",
    "gn:dem":213,
    "gn:feature_class":"P",
    "gn:feature_code":"PPL",
    "gn:name":"\u0160abani",
    "gn:population":0,
    "gn:timezone":"Europe/Zagreb",
    "iso:country":"HR",
    "wof:name":"Sabani",
    "wof:placetype":"locality"
},
  "geometry": {"coordinates":[15.75009,45.16343],"type":"Point"}
}