{
  "type": "Feature",
  "properties": {
    "gn:admin1_code":"12",
    "gn:admin2_code":"11049431.0",
    "gn:asciiname":"Brod Moravice",
    "gn:country_code":"HR",
    "gn:dem":610,
    "gn:feature_class":"P",
    "gn:feature_code":"PPLA2",
    "gn:name":"Brod Moravice",
    "gn:population":0,
    "gn:timezone":"Europe/Zagreb",
    "iso:country":"HR",
    "name:bos_x_preferred":[
        "Brod Moravice"
    ],
    "name:cat_x_preferred":[
        "Brod Moravice"
    ],
    "name:deu_x_preferred":[
        "Brod Moravice"
    ],
    "name:fra_x_preferred":[
        "Brod Moravice"
    ],
    "name:hrv_x_preferred":[
        "Brod Moravice"
    ],
    "name:hun_x_preferred":[
        "Brod Moravice"
    ],
    "name:ita_x_preferred":[
        "Brod Moravice"
    ],
    "name:nld_x_preferred":[
        "Brod Moravice"
    ],
    "name:pol_x_preferred":[
        "Gmina Brod Moravice"
    ],
    "name:ron_x_preferred":[
        "Comuna Brod Moravice"
    ],
    "name:rus_x_preferred":[
        "\u0411\u0440\u043e\u0434-\u041c\u043e\u0440\u0430\u0432\u0438\u0446\u0435"
    ],
    "name:slv_x_preferred":[
        "Brod Moravice"
    ],
    "name:spa_x_preferred":[
        "Brod Moravice"
    ],
    "name:srp_x_preferred":[
        "\u0411\u0440\u043e\u0434 \u041c\u043e\u0440\u0430\u0432\u0438\u0446\u0435"
    ],
    "name:swe_x_preferred":[
        "Brod Moravice"
    ],
    "name:ukr_x_preferred":[
        "\u0411\u0440\u043e\u0434-\u041c\u043e\u0440\u0430\u0432\u0438\u0446\u0435"
    ],
    "name:war_x_preferred":[
        "Brod Moravice"
    ],
    "wof:name":"Brod Moravice",
    "wof:placetype":"locality"
},
  "geometry": {"coordinates":[14.97444,45.46528],"type":"Point"}
}