{
  "type": "Feature",
  "properties": {
    "gn:admin1_code":"8.0",
    "gn:asciiname":"Loskun",
    "gn:country_code":"HR",
    "gn:dem":246,
    "gn:feature_class":"P",
    "gn:feature_code":"PPL",
    "gn:name":"Loskun",
    "gn:population":0,
    "gn:timezone":"Europe/Zagreb",
    "iso:country":"HR",
    "wof:name":"Loskun",
    "wof:placetype":"locality"
},
  "geometry": {"coordinates":[15.955,44.69583],"type":"Point"}
}