{
  "type": "Feature",
  "properties": {
    "gn:country":"HR",
    "gn:fcode":"PPL",
    "gn:population":2500,
    "iso:country":"HR",
    "name:eng_x_preferred":[
        "Veli Drvenik"
    ],
    "name:rus_x_preferred":[
        "\u0412\u0435\u043b\u0438 \u0414\u0440\u0432\u0435\u043d\u0438\u043a"
    ],
    "name:und_x_variant":[
        "Zirona"
    ],
    "qs_pg:aaroncc":"HR",
    "qs_pg:gn_country":"HR",
    "qs_pg:gn_fcode":"PPL",
    "qs_pg:gn_pop":2500,
    "qs_pg:name":"Veliki Drvenik",
    "qs_pg:name_adm0":"Hrvatska",
    "qs_pg:name_adm1":"Splitsko-Dalmatinska",
    "qs_pg:photos":221,
    "qs_pg:photos_1k":45,
    "qs_pg:photos_9k":1,
    "qs_pg:photos_9r":4,
    "qs_pg:photos_all":221,
    "qs_pg:photos_sr":4,
    "qs_pg:pop_sr":4,
    "qs_pg:qs_pg_placetype":"locality",
    "qs_pg:qs_pg_placetype_gp":"Town",
    "qs_pg:woe_adm0":23424843,
    "woe:adm0_id":23424843,
    "woe:name_adm0":"Hrvatska",
    "woe:name_adm1":"Splitsko-Dalmatinska",
    "woe:placetype":"Town",
    "wof:name":"Veliki Drvenik",
    "wof:placetype":"locality",
    "wof:population":2500
},
  "geometry": {"coordinates":[16.15,43.45],"type":"Point"}
}