{
  "type": "Feature",
  "properties": {
    "gn:admin1_code":"21",
    "gn:asciiname":"Vrapce",
    "gn:country_code":"HR",
    "gn:dem":201,
    "gn:feature_class":"P",
    "gn:feature_code":"PPL",
    "gn:name":"Vrap\u010de",
    "gn:population":0,
    "gn:timezone":"Europe/Zagreb",
    "iso:country":"HR",
    "name:bos_x_preferred":[
        "Vrap\u010de"
    ],
    "name:fra_x_preferred":[
        "Vrapce"
    ],
    "name:hrv_x_preferred":[
        "Vrap\u010de"
    ],
    "name:srp_x_preferred":[
        "\u0412\u0440\u0430\u043f\u0447\u0435"
    ],
    "wof:name":"Vrapce",
    "wof:placetype":"locality"
},
  "geometry": {"coordinates":[15.91667,45.81667],"type":"Point"}
}