{
  "type": "Feature",
  "properties": {
    "gn:admin1_code":"19.0",
    "gn:asciiname":"Zaluzje",
    "gn:country_code":"HR",
    "gn:dem":381,
    "gn:feature_class":"P",
    "gn:feature_code":"PPLL",
    "gn:name":"Zalu\u017eje",
    "gn:population":0,
    "gn:timezone":"Europe/Zagreb",
    "iso:country":"HR",
    "wof:name":"Zaluzje",
    "wof:placetype":"locality"
},
  "geometry": {"coordinates":[16.12528,44.41861],"type":"Point"}
}