{
  "type": "Feature",
  "properties": {
    "gn:admin1_code":"5.0",
    "gn:admin2_code":"3190522.0",
    "gn:asciiname":"Novo Selo",
    "gn:country_code":"HR",
    "gn:dem":288,
    "gn:feature_class":"P",
    "gn:feature_code":"PPL",
    "gn:name":"Novo Selo",
    "gn:population":68,
    "gn:timezone":"Europe/Zagreb",
    "iso:country":"HR",
    "wof:name":"Novo Selo",
    "wof:placetype":"locality",
    "wof:population":68
},
  "geometry": {"coordinates":[15.5925,45.09667],"type":"Point"}
}