{
  "type": "Feature",
  "properties": {
    "gn:admin1_code":"08",
    "gn:admin2_code":"11049284.0",
    "gn:asciiname":"Lipice",
    "gn:cc2":"HR",
    "gn:country_code":"HR",
    "gn:dem":644,
    "gn:feature_class":"P",
    "gn:feature_code":"PPL",
    "gn:name":"Lipice",
    "gn:population":154,
    "gn:timezone":"Europe/Zagreb",
    "iso:country":"HR",
    "name:und_x_variant":[
        "Lipica",
        "Lipice"
    ],
    "wof:name":"Lipice",
    "wof:placetype":"locality",
    "wof:population":154
},
  "geometry": {"coordinates":[15.26667,45.01667],"type":"Point"}
}