{
  "type": "Feature",
  "properties": {
    "gn:admin1_code":"4.0",
    "gn:admin2_code":"11129785.0",
    "gn:asciiname":"Bacva",
    "gn:cc2":"HR",
    "gn:country_code":"HR",
    "gn:dem":198,
    "gn:feature_class":"P",
    "gn:feature_code":"PPL",
    "gn:name":"Ba\u010dva",
    "gn:population":21,
    "gn:timezone":"Europe/Zagreb",
    "iso:country":"HR",
    "name:und_x_variant":[
        "Mondellebotte",
        "Ba\u010dva"
    ],
    "wof:name":"Bacva",
    "wof:placetype":"locality",
    "wof:population":21
},
  "geometry": {"coordinates":[13.715,45.25333],"type":"Point"}
}