{
  "type": "Feature",
  "properties": {
    "gn:admin1_code":"5.0",
    "gn:asciiname":"Kucinic-Selo",
    "gn:country_code":"HR",
    "gn:dem":343,
    "gn:feature_class":"P",
    "gn:feature_code":"PPL",
    "gn:name":"Ku\u010dini\u0107-Selo",
    "gn:population":0,
    "gn:timezone":"Europe/Zagreb",
    "iso:country":"HR",
    "wof:name":"Kucinic-Selo",
    "wof:placetype":"locality"
},
  "geometry": {"coordinates":[15.22694,45.24278],"type":"Point"}
}