{
  "type": "Feature",
  "properties": {
    "gn:admin1_code":"14.0",
    "gn:asciiname":"Stambolije",
    "gn:country_code":"HR",
    "gn:dem":183,
    "gn:feature_class":"P",
    "gn:feature_code":"PPL",
    "gn:name":"Stambolije",
    "gn:population":0,
    "gn:timezone":"Europe/Zagreb",
    "iso:country":"HR",
    "wof:name":"Stambolije",
    "wof:placetype":"locality"
},
  "geometry": {"coordinates":[16.25417,45.085],"type":"Point"}
}