{
  "type": "Feature",
  "properties": {
    "gn:admin1_code":"04",
    "gn:admin2_code":"3193560.0",
    "gn:asciiname":"Trviz",
    "gn:cc2":"HR",
    "gn:country_code":"HR",
    "gn:dem":395,
    "gn:feature_class":"P",
    "gn:feature_code":"PPL",
    "gn:name":"Trvi\u017e",
    "gn:population":409,
    "gn:timezone":"Europe/Zagreb",
    "iso:country":"HR",
    "name:und_x_variant":[
        "Terviso",
        "Villa Treviso",
        "Trvi\u017e"
    ],
    "wof:name":"Trviz",
    "wof:placetype":"locality",
    "wof:population":409
},
  "geometry": {"coordinates":[13.875,45.26472],"type":"Point"}
}