{
  "type": "Feature",
  "properties": {
    "gn:admin1_code":"15.0",
    "gn:asciiname":"Milasi",
    "gn:country_code":"HR",
    "gn:dem":274,
    "gn:feature_class":"P",
    "gn:feature_code":"PPL",
    "gn:name":"Milasi",
    "gn:population":0,
    "gn:timezone":"Europe/Zagreb",
    "iso:country":"HR",
    "wof:name":"Milasi",
    "wof:placetype":"locality"
},
  "geometry": {"coordinates":[17.20639,43.41639],"type":"Point"}
}