{
  "type": "Feature",
  "properties": {
    "gn:admin1_code":"10",
    "gn:admin2_code":"3193934.0",
    "gn:asciiname":"Tvrgavica",
    "gn:country_code":"HR",
    "gn:dem":82,
    "gn:feature_class":"P",
    "gn:feature_code":"PPL",
    "gn:name":"Tvr\u0111avica",
    "gn:population":578,
    "gn:timezone":"Europe/Zagreb",
    "iso:country":"HR",
    "wof:name":"Tvrgavica",
    "wof:placetype":"locality",
    "wof:population":578
},
  "geometry": {"coordinates":[18.67583,45.57139],"type":"Point"}
}