{
  "type": "Feature",
  "properties": {
    "gn:admin1_code":"15",
    "gn:admin2_code":"3194113.0",
    "gn:asciiname":"Cisla",
    "gn:cc2":"HR",
    "gn:country_code":"HR",
    "gn:dem":273,
    "gn:feature_class":"P",
    "gn:feature_code":"PPL",
    "gn:name":"\u010cisla",
    "gn:population":302,
    "gn:timezone":"Europe/Zagreb",
    "iso:country":"HR",
    "name:ara_x_preferred":[
        "\u062b\u064a\u0633\u0644\u0627"
    ],
    "name:ast_x_preferred":[
        "Cisla"
    ],
    "name:cat_x_preferred":[
        "Cisla"
    ],
    "name:ceb_x_preferred":[
        "Cisla"
    ],
    "name:eus_x_preferred":[
        "Cisla"
    ],
    "name:fas_x_preferred":[
        "\u0633\u06cc\u0633\u0644\u0627"
    ],
    "name:fra_x_preferred":[
        "Cisla"
    ],
    "name:hun_x_preferred":[
        "Cisla"
    ],
    "name:ina_x_preferred":[
        "Cisla"
    ],
    "name:ita_x_preferred":[
        "Cisla"
    ],
    "name:kaz_x_preferred":[
        "\u0421\u0438\u0441\u043b\u0430"
    ],
    "name:mkd_x_preferred":[
        "\u041a\u0438\u0441\u043b\u0430"
    ],
    "name:msa_x_preferred":[
        "Cisla"
    ],
    "name:nld_x_preferred":[
        "Cisla"
    ],
    "name:oci_x_preferred":[
        "Cisla"
    ],
    "name:pol_x_preferred":[
        "Cisla"
    ],
    "name:por_x_preferred":[
        "Cisla"
    ],
    "name:rus_x_preferred":[
        "\u0421\u0438\u0441\u043b\u0430"
    ],
    "name:spa_x_preferred":[
        "Cisla"
    ],
    "name:swe_x_preferred":[
        "Cisla"
    ],
    "name:ukr_x_preferred":[
        "\u0421\u0456\u0441\u043b\u0430"
    ],
    "name:und_x_variant":[
        "\u010cista",
        "\u010cisla"
    ],
    "name:uzb_x_preferred":[
        "Cisla"
    ],
    "name:vie_x_preferred":[
        "Cisla"
    ],
    "name:war_x_preferred":[
        "Cisla"
    ],
    "name:zho_x_preferred":[
        "\u897f\u65af\u62c9"
    ],
    "wof:name":"Cisla",
    "wof:placetype":"locality",
    "wof:population":302
},
  "geometry": {"coordinates":[16.73282,43.46155],"type":"Point"}
}