{
  "type": "Feature",
  "properties": {
    "gn:admin1_code":"15",
    "gn:admin2_code":"3194113.0",
    "gn:asciiname":"Cisla",
    "gn:cc2":"HR",
    "gn:country_code":"HR",
    "gn:dem":273,
    "gn:feature_class":"P",
    "gn:feature_code":"PPL",
    "gn:name":"\u010cisla",
    "gn:population":302,
    "gn:timezone":"Europe/Zagreb",
    "iso:country":"HR",
    "name:und_x_variant":[
        "\u010cista",
        "\u010cisla"
    ],
    "wof:name":"Cisla",
    "wof:placetype":"locality",
    "wof:population":302
},
  "geometry": {"coordinates":[16.73282,43.46155],"type":"Point"}
}