{
  "type": "Feature",
  "properties": {
    "gn:admin1_code":"15.0",
    "gn:asciiname":"Milanovici",
    "gn:cc2":"HR",
    "gn:country_code":"HR",
    "gn:dem":314,
    "gn:feature_class":"P",
    "gn:feature_code":"PPL",
    "gn:name":"Milanovi\u0107i",
    "gn:population":0,
    "gn:timezone":"Europe/Zagreb",
    "iso:country":"HR",
    "name:und_x_variant":[
        "Milanovi\u0107",
        "Milanovi\u0107i"
    ],
    "wof:name":"Milanovici",
    "wof:placetype":"locality"
},
  "geometry": {"coordinates":[16.73444,43.70444000000001],"type":"Point"}
}