{
  "type": "Feature",
  "properties": {
    "gn:admin1_code":"15.0",
    "gn:asciiname":"Butina",
    "gn:country_code":"HR",
    "gn:dem":40,
    "gn:feature_class":"P",
    "gn:feature_code":"PPL",
    "gn:name":"Butina",
    "gn:population":0,
    "gn:timezone":"Europe/Zagreb",
    "iso:country":"HR",
    "name:slv_x_preferred":[
        "Butina"
    ],
    "wof:name":"Butina",
    "wof:placetype":"locality"
},
  "geometry": {"coordinates":[17.40444,43.17889],"type":"Point"}
}