{
  "type": "Feature",
  "properties": {
    "gn:admin1_code":"05",
    "gn:admin2_code":"11049279.0",
    "gn:asciiname":"Ribnik",
    "gn:country_code":"HR",
    "gn:dem":151,
    "gn:feature_class":"P",
    "gn:feature_code":"PPLA2",
    "gn:name":"Ribnik",
    "gn:population":0,
    "gn:timezone":"Europe/Zagreb",
    "iso:country":"HR",
    "name:bos_x_preferred":[
        "Ribnik"
    ],
    "name:cat_x_preferred":[
        "Ribnik"
    ],
    "name:deu_x_preferred":[
        "Ribnik"
    ],
    "name:fra_x_preferred":[
        "Ribnik"
    ],
    "name:hrv_x_preferred":[
        "Ribnik"
    ],
    "name:hun_x_preferred":[
        "Ribnik"
    ],
    "name:ita_x_preferred":[
        "Ribnik"
    ],
    "name:nld_x_preferred":[
        "Ribnik"
    ],
    "name:pol_x_preferred":[
        "Gmina Ribnik"
    ],
    "name:ron_x_preferred":[
        "Comuna Ribnik"
    ],
    "name:slv_x_preferred":[
        "Ribnik"
    ],
    "name:spa_x_preferred":[
        "Ribnik"
    ],
    "name:srp_x_preferred":[
        "\u0420\u0438\u0431\u043d\u0438\u043a"
    ],
    "name:ukr_x_preferred":[
        "\u0420\u0438\u0431\u043d\u0438\u043a"
    ],
    "name:war_x_preferred":[
        "Ribnik"
    ],
    "wof:name":"Ribnik",
    "wof:placetype":"locality"
},
  "geometry": {"coordinates":[15.35139,45.57944000000001],"type":"Point"}
}