{
  "type": "Feature",
  "properties": {
    "gn:admin1_code":"13",
    "gn:admin2_code":"3201161.0",
    "gn:asciiname":"Kaocine",
    "gn:country_code":"HR",
    "gn:dem":257,
    "gn:feature_class":"P",
    "gn:feature_code":"PPL",
    "gn:name":"Kao\u010dine",
    "gn:population":203,
    "gn:timezone":"Europe/Zagreb",
    "iso:country":"HR",
    "wof:name":"Kaocine",
    "wof:placetype":"locality",
    "wof:population":203
},
  "geometry": {"coordinates":[16.06667,43.86667],"type":"Point"}
}