{
  "type": "Feature",
  "properties": {
    "gn:admin1_code":"3.0",
    "gn:admin2_code":"11054958.0",
    "gn:asciiname":"Medarovine",
    "gn:country_code":"HR",
    "gn:dem":9,
    "gn:feature_class":"P",
    "gn:feature_code":"PPL",
    "gn:name":"Medarovine",
    "gn:population":0,
    "gn:timezone":"Europe/Zagreb",
    "iso:country":"HR",
    "wof:name":"Medarovine",
    "wof:placetype":"locality"
},
  "geometry": {"coordinates":[17.64027999999999,43.00556],"type":"Point"}
}