{
  "type": "Feature",
  "properties": {
    "gn:admin1_code":"20",
    "gn:admin2_code":"3191315.0",
    "gn:asciiname":"Simraki",
    "gn:country_code":"HR",
    "gn:dem":493,
    "gn:feature_class":"P",
    "gn:feature_code":"PPL",
    "gn:name":"\u0160imraki",
    "gn:population":5,
    "gn:timezone":"Europe/Zagreb",
    "iso:country":"HR",
    "wof:name":"Simraki",
    "wof:placetype":"locality",
    "wof:population":5
},
  "geometry": {"coordinates":[15.53333,45.78333],"type":"Point"}
}