{
  "type": "Feature",
  "properties": {
    "gn:admin1_code":"02",
    "gn:admin2_code":"11049499.0",
    "gn:asciiname":"Gornje Rogolje",
    "gn:cc2":"HR",
    "gn:country_code":"HR",
    "gn:dem":278,
    "gn:feature_class":"P",
    "gn:feature_code":"PPL",
    "gn:name":"Gornje Rogolje",
    "gn:population":0,
    "gn:timezone":"Europe/Zagreb",
    "iso:country":"HR",
    "name:und_x_variant":[
        "Gornji Rogolji",
        "Gornje Rogolje"
    ],
    "wof:name":"Gornje Rogolje",
    "wof:placetype":"locality"
},
  "geometry": {"coordinates":[17.21667,45.36667],"type":"Point"}
}