{
  "type": "Feature",
  "properties": {
    "gn:admin1_code":"8.0",
    "gn:asciiname":"Podastrana",
    "gn:cc2":"HR",
    "gn:country_code":"HR",
    "gn:dem":582,
    "gn:feature_class":"P",
    "gn:feature_code":"PPL",
    "gn:name":"Podastrana",
    "gn:population":51,
    "gn:timezone":"Europe/Zagreb",
    "iso:country":"HR",
    "name:und_x_variant":[
        "Padastrana",
        "Podastrana"
    ],
    "wof:name":"Podastrana",
    "wof:placetype":"locality",
    "wof:population":51
},
  "geometry": {"coordinates":[15.20611,44.65306],"type":"Point"}
}