{
  "type": "Feature",
  "properties": {
    "gn:admin1_code":"04",
    "gn:asciiname":"Veruda",
    "gn:country_code":"HR",
    "gn:dem":-1,
    "gn:feature_class":"P",
    "gn:feature_code":"PPL",
    "gn:name":"Veruda",
    "gn:population":0,
    "gn:timezone":"Europe/Zagreb",
    "iso:country":"HR",
    "wof:name":"Veruda",
    "wof:placetype":"locality"
},
  "geometry": {"coordinates":[13.83333,44.85],"type":"Point"}
}