{
  "type": "Feature",
  "properties": {
    "gn:admin1_code":"8.0",
    "gn:admin2_code":"11049286.0",
    "gn:asciiname":"Smiljansko Polje",
    "gn:country_code":"HR",
    "gn:dem":565,
    "gn:feature_class":"P",
    "gn:feature_code":"PPL",
    "gn:name":"Smiljansko Polje",
    "gn:population":135,
    "gn:timezone":"Europe/Zagreb",
    "iso:country":"HR",
    "wof:name":"Smiljansko Polje",
    "wof:placetype":"locality",
    "wof:population":135
},
  "geometry": {"coordinates":[15.38444,44.58472],"type":"Point"}
}