{
  "type": "Feature",
  "properties": {
    "gn:admin1_code":"15",
    "gn:admin2_code":"11054614.0",
    "gn:asciiname":"Donje Ogorje",
    "gn:cc2":"HR",
    "gn:country_code":"HR",
    "gn:dem":550,
    "gn:feature_class":"P",
    "gn:feature_code":"PPL",
    "gn:name":"Donje Ogorje",
    "gn:population":116,
    "gn:timezone":"Europe/Zagreb",
    "iso:country":"HR",
    "name:und_x_variant":[
        "Ogorje Donje",
        "Donje Ogorje"
    ],
    "wof:name":"Donje Ogorje",
    "wof:placetype":"locality",
    "wof:population":116
},
  "geometry": {"coordinates":[16.435,43.74417],"type":"Point"}
}