{
  "type": "Feature",
  "properties": {
    "gn:admin1_code":"19.0",
    "gn:asciiname":"Knezevic",
    "gn:country_code":"HR",
    "gn:dem":42,
    "gn:feature_class":"P",
    "gn:feature_code":"PPL",
    "gn:name":"Kne\u017eevi\u0107",
    "gn:population":0,
    "gn:timezone":"Europe/Zagreb",
    "iso:country":"HR",
    "wof:name":"Knezevic",
    "wof:placetype":"locality"
},
  "geometry": {"coordinates":[15.4975,44.27889],"type":"Point"}
}