{
  "type": "Feature",
  "properties": {
    "gn:admin1_code":"3.0",
    "gn:asciiname":"Ograd",
    "gn:country_code":"HR",
    "gn:dem":210,
    "gn:feature_class":"P",
    "gn:feature_code":"PPL",
    "gn:name":"Ogra\u0111",
    "gn:population":0,
    "gn:timezone":"Europe/Zagreb",
    "iso:country":"HR",
    "wof:name":"Ograd",
    "wof:placetype":"locality"
},
  "geometry": {"coordinates":[17.605,43.08861],"type":"Point"}
}