{
  "type": "Feature",
  "properties": {
    "gn:country":"HR",
    "gn:fcode":"PPL",
    "gn:population":831,
    "iso:country":"HR",
    "name:bos_x_preferred":[
        "Brtonigla"
    ],
    "name:ceb_x_preferred":[
        "Brtonigla"
    ],
    "name:ces_x_preferred":[
        "Brtonigla"
    ],
    "name:deu_x_preferred":[
        "Brtonigla"
    ],
    "name:eng_x_preferred":[
        "Brtonigla"
    ],
    "name:fra_x_preferred":[
        "Brtonigla"
    ],
    "name:hrv_x_preferred":[
        "Brtonigla"
    ],
    "name:hun_x_preferred":[
        "Brtonigla"
    ],
    "name:ita_x_preferred":[
        "Verteneglio"
    ],
    "name:lat_x_preferred":[
        "Vertex Niger"
    ],
    "name:nld_x_preferred":[
        "Brtonigla"
    ],
    "name:pol_x_preferred":[
        "Brtonigla"
    ],
    "name:ron_x_preferred":[
        "Comuna Brtonigla"
    ],
    "name:rus_x_preferred":[
        "\u0411\u0440\u0442\u043e\u043d\u0438\u0433\u043b\u0430"
    ],
    "name:slk_x_preferred":[
        "Brtonigla"
    ],
    "name:slv_x_preferred":[
        "Brtonigla"
    ],
    "name:spa_x_preferred":[
        "Brtonigla"
    ],
    "name:srp_x_preferred":[
        "\u0411\u0440\u0442\u043e\u043d\u0438\u0433\u043b\u0430"
    ],
    "name:swe_x_preferred":[
        "Brtonigla"
    ],
    "name:ukr_x_preferred":[
        "\u0411\u0440\u0442\u043e\u043d\u0438\u0433\u043b\u0430"
    ],
    "name:war_x_preferred":[
        "Brtonigla"
    ],
    "qs_pg:aaroncc":"HR",
    "qs_pg:gn_country":"HR",
    "qs_pg:gn_fcode":"PPL",
    "qs_pg:gn_pop":831,
    "qs_pg:name":"Brtonigla",
    "qs_pg:name_adm0":"Hrvatska",
    "qs_pg:name_adm1":"Istarska",
    "qs_pg:photos":111,
    "qs_pg:photos_1k":22,
    "qs_pg:photos_9k":1,
    "qs_pg:photos_9r":3,
    "qs_pg:photos_all":111,
    "qs_pg:photos_sr":3,
    "qs_pg:pop_sr":2,
    "qs_pg:qs_pg_placetype":"locality",
    "qs_pg:qs_pg_placetype_gp":"Town",
    "qs_pg:woe_adm0":23424843,
    "woe:adm0_id":23424843,
    "woe:name_adm0":"Hrvatska",
    "woe:name_adm1":"Istarska",
    "woe:placetype":"Town",
    "wof:name":"Brtonigla",
    "wof:placetype":"locality",
    "wof:population":831
},
  "geometry": {"coordinates":[13.62944,45.38139],"type":"Point"}
}