{
  "type": "Feature",
  "properties": {
    "gn:admin1_code":"15.0",
    "gn:asciiname":"Tomici",
    "gn:country_code":"HR",
    "gn:dem":516,
    "gn:feature_class":"P",
    "gn:feature_code":"PPL",
    "gn:name":"Tomi\u0107i",
    "gn:population":0,
    "gn:timezone":"Europe/Zagreb",
    "iso:country":"HR",
    "wof:name":"Tomici",
    "wof:placetype":"locality"
},
  "geometry": {"coordinates":[16.71694,43.50861],"type":"Point"}
}