{
  "type": "Feature",
  "properties": {
    "gn:admin1_code":"8.0",
    "gn:admin2_code":"11049292.0",
    "gn:asciiname":"Svinjar",
    "gn:country_code":"HR",
    "gn:dem":671,
    "gn:feature_class":"P",
    "gn:feature_code":"PPL",
    "gn:name":"Svinjar",
    "gn:population":0,
    "gn:timezone":"Europe/Zagreb",
    "iso:country":"HR",
    "wof:name":"Svinjar",
    "wof:placetype":"locality"
},
  "geometry": {"coordinates":[15.74111,44.70611],"type":"Point"}
}