{
  "type": "Feature",
  "properties": {
    "gn:admin1_code":"19",
    "gn:admin2_code":"11054329.0",
    "gn:asciiname":"Vlasici",
    "gn:cc2":"HR",
    "gn:country_code":"HR",
    "gn:dem":31,
    "gn:feature_class":"P",
    "gn:feature_code":"PPL",
    "gn:name":"Vla\u0161i\u0107i",
    "gn:population":272,
    "gn:timezone":"Europe/Zagreb",
    "iso:country":"HR",
    "name:und_x_variant":[
        "Vla\u0161i\u0107",
        "Vla\u0161i\u0107i"
    ],
    "wof:name":"Vlasici",
    "wof:placetype":"locality",
    "wof:population":272
},
  "geometry": {"coordinates":[15.2075,44.32722],"type":"Point"}
}