{
  "type": "Feature",
  "properties": {
    "gn:admin1_code":"15.0",
    "gn:asciiname":"Ispod Crkve",
    "gn:country_code":"HR",
    "gn:dem":409,
    "gn:feature_class":"P",
    "gn:feature_code":"PPL",
    "gn:name":"Ispod Crkve",
    "gn:population":0,
    "gn:timezone":"Europe/Zagreb",
    "iso:country":"HR",
    "wof:name":"Ispod Crkve",
    "wof:placetype":"locality"
},
  "geometry": {"coordinates":[16.71694,43.61],"type":"Point"}
}