{
  "type": "Feature",
  "properties": {
    "gn:admin1_code":"15.0",
    "gn:asciiname":"Voloderi",
    "gn:country_code":"HR",
    "gn:dem":681,
    "gn:feature_class":"P",
    "gn:feature_code":"PPL",
    "gn:name":"Voloderi",
    "gn:population":0,
    "gn:timezone":"Europe/Zagreb",
    "iso:country":"HR",
    "wof:name":"Voloderi",
    "wof:placetype":"locality"
},
  "geometry": {"coordinates":[16.92417,43.59472],"type":"Point"}
}