{
  "type": "Feature",
  "properties": {
    "gn:admin1_code":"13.0",
    "gn:asciiname":"Radici",
    "gn:country_code":"HR",
    "gn:dem":362,
    "gn:feature_class":"P",
    "gn:feature_code":"PPL",
    "gn:name":"Radi\u0107i",
    "gn:population":0,
    "gn:timezone":"Europe/Zagreb",
    "iso:country":"HR",
    "name:deu_x_preferred":[
        "Radici"
    ],
    "name:ita_x_preferred":[
        "Radici"
    ],
    "wof:name":"Radici",
    "wof:placetype":"locality"
},
  "geometry": {"coordinates":[16.26361,44.16361],"type":"Point"}
}