{
  "type": "Feature",
  "properties": {
    "gn:gn_country":"HR",
    "gn:gn_fcode":"PPL",
    "gn:gn_pop":0,
    "gn:population":18,
    "iso:country":"HR",
    "name:bos_x_preferred":[
        "Trako\u0161\u0107an"
    ],
    "name:cze_x_preferred":[
        "Trako\u0161\u0107an"
    ],
    "name:dut_x_preferred":[
        "Trako\u0161\u0107an"
    ],
    "name:eng_x_preferred":[
        "Trako\u0161\u0107an"
    ],
    "name:hrv_x_preferred":[
        "Trako\u0161\u0107an"
    ],
    "name:hun_x_preferred":[
        "Trakosty\u00e1n"
    ],
    "name:rus_x_preferred":[
        "\u0422\u0440\u0430\u043a\u043e\u0448\u0447\u0430\u043d"
    ],
    "name:slv_x_preferred":[
        "Trako\u0161\u0107an"
    ],
    "name:swe_x_preferred":[
        "Trako\u0161\u0107an"
    ],
    "name:ukr_x_preferred":[
        "\u0422\u0440\u0430\u043a\u043e\u0448\u0447\u0430\u043d"
    ],
    "name:unk_x_variant":[
        "Tako\u0161can"
    ],
    "qs_pg:aaroncc":"HR",
    "qs_pg:gn_country":"HR",
    "qs_pg:gn_fcode":"PPL",
    "qs_pg:gn_pop":0,
    "qs_pg:name":"Trako\u0161\u0107an",
    "qs_pg:name_adm0":"Hrvatska",
    "qs_pg:name_adm1":"Vara\u017edinska",
    "qs_pg:photos":253,
    "qs_pg:photos_1k":51,
    "qs_pg:photos_9k":1,
    "qs_pg:photos_9r":4,
    "qs_pg:photos_all":253,
    "qs_pg:photos_sr":5,
    "qs_pg:pop_sr":0,
    "qs_pg:qs_pg_placetype":"locality",
    "qs_pg:qs_pg_placetype_gp":"Town",
    "qs_pg:woe_adm0":23424843,
    "woe:adm0_id":23424843,
    "woe:name_adm0":"Hrvatska",
    "woe:name_adm1":"Vara\u017edinska",
    "woe:placetype":"Town",
    "wof:name":"Trako\u0161\u0107an",
    "wof:placetype":"locality",
    "wof:population":18
},
  "geometry": {"coordinates":[15.94861,46.25833],"type":"Point"}
}