{
  "type": "Feature",
  "properties": {
    "gn:admin1_code":"8.0",
    "gn:admin2_code":"11049294.0",
    "gn:asciiname":"Jelovci",
    "gn:country_code":"HR",
    "gn:dem":670,
    "gn:feature_class":"P",
    "gn:feature_code":"PPL",
    "gn:name":"Jelovci",
    "gn:population":0,
    "gn:timezone":"Europe/Zagreb",
    "iso:country":"HR",
    "wof:name":"Jelovci",
    "wof:placetype":"locality"
},
  "geometry": {"coordinates":[15.65167,44.6775],"type":"Point"}
}