{
  "type": "Feature",
  "properties": {
    "gn:admin1_code":"04",
    "gn:admin2_code":"11054808.0",
    "gn:asciiname":"Pinezici",
    "gn:cc2":"HR",
    "gn:country_code":"HR",
    "gn:dem":190,
    "gn:feature_class":"P",
    "gn:feature_code":"PPL",
    "gn:name":"Pinezi\u0107i",
    "gn:population":47,
    "gn:timezone":"Europe/Zagreb",
    "iso:country":"HR",
    "name:und_x_variant":[
        "Pinezi",
        "Pinesi",
        "Pinezi\u0107i"
    ],
    "wof:name":"Pinezici",
    "wof:placetype":"locality",
    "wof:population":47
},
  "geometry": {"coordinates":[13.935,44.965],"type":"Point"}
}