{
  "type": "Feature",
  "properties": {
    "gn:admin1_code":"01",
    "gn:admin2_code":"3203981.0",
    "gn:asciiname":"Patkovac",
    "gn:country_code":"HR",
    "gn:dem":123,
    "gn:feature_class":"P",
    "gn:feature_code":"PPL",
    "gn:name":"Patkovac",
    "gn:population":257,
    "gn:timezone":"Europe/Zagreb",
    "iso:country":"HR",
    "wof:name":"Patkovac",
    "wof:placetype":"locality",
    "wof:population":257
},
  "geometry": {"coordinates":[16.93139,45.8525],"type":"Point"}
}