{
  "type": "Feature",
  "properties": {
    "gn:gn_country":"HR",
    "gn:gn_fcode":"PPL",
    "gn:gn_pop":836,
    "gn:population":836,
    "iso:country":"HR",
    "name:bos_x_preferred":[
        "Dekanovec"
    ],
    "name:ceb_x_preferred":[
        "Dekanovec"
    ],
    "name:ces_x_preferred":[
        "Dekanovec"
    ],
    "name:eng_x_preferred":[
        "Dekanovec"
    ],
    "name:epo_x_preferred":[
        "Dekanovec"
    ],
    "name:fra_x_preferred":[
        "Dekanovec"
    ],
    "name:hrv_x_preferred":[
        "Dekanovec"
    ],
    "name:hun_x_preferred":[
        "D\u00e9k\u00e1nfalva"
    ],
    "name:ita_x_preferred":[
        "Dekanovec"
    ],
    "name:nld_x_preferred":[
        "Dekanovec"
    ],
    "name:pol_x_preferred":[
        "Gmina Dekanovec"
    ],
    "name:ron_x_preferred":[
        "Comuna Dekanovec"
    ],
    "name:slv_x_preferred":[
        "Dekanovec"
    ],
    "name:spa_x_preferred":[
        "Dekanovec"
    ],
    "name:srp_x_preferred":[
        "\u0414\u0435\u043a\u0430\u043d\u043e\u0432\u0435\u0446"
    ],
    "name:swe_x_preferred":[
        "Dekanovec"
    ],
    "name:ukr_x_preferred":[
        "\u0414\u0435\u043a\u0430\u043d\u043e\u0432\u0435\u0446\u044c"
    ],
    "name:war_x_preferred":[
        "Dekanovec"
    ],
    "qs_pg:aaroncc":"HR",
    "qs_pg:gn_country":"HR",
    "qs_pg:gn_fcode":"PPL",
    "qs_pg:gn_pop":836,
    "qs_pg:name":"Dekanovec",
    "qs_pg:name_adm0":"Hrvatska",
    "qs_pg:name_adm1":"Medjimurska",
    "qs_pg:photos_9r":0,
    "qs_pg:photos_sr":0,
    "qs_pg:pop_sr":2,
    "qs_pg:qs_pg_placetype":"locality",
    "qs_pg:qs_pg_placetype_gp":"Town",
    "qs_pg:woe_adm0":23424843,
    "woe:adm0_id":23424843,
    "woe:name_adm0":"Hrvatska",
    "woe:name_adm1":"Medjimurska",
    "woe:placetype":"Town",
    "wof:name":"Dekanovec",
    "wof:placetype":"locality",
    "wof:population":836
},
  "geometry": {"coordinates":[16.58472,46.44861],"type":"Point"}
}