{
  "type": "Feature",
  "properties": {
    "gn:admin1_code":"14.0",
    "gn:asciiname":"Kukici",
    "gn:country_code":"HR",
    "gn:dem":361,
    "gn:feature_class":"P",
    "gn:feature_code":"PPL",
    "gn:name":"Kuki\u0107i",
    "gn:population":0,
    "gn:timezone":"Europe/Zagreb",
    "iso:country":"HR",
    "wof:name":"Kukici",
    "wof:placetype":"locality"
},
  "geometry": {"coordinates":[16.31528,45.16278],"type":"Point"}
}