{
  "type": "Feature",
  "properties": {
    "gn:admin1_code":"09",
    "gn:admin2_code":"11054839.0",
    "gn:asciiname":"Gornji Mihaljevec",
    "gn:country_code":"HR",
    "gn:dem":224,
    "gn:feature_class":"P",
    "gn:feature_code":"PPLA2",
    "gn:name":"Gornji Mihaljevec",
    "gn:population":0,
    "gn:timezone":"Europe/Zagreb",
    "iso:country":"HR",
    "name:bos_x_preferred":[
        "Gornji Mihaljevec"
    ],
    "name:ces_x_preferred":[
        "Gornji Mihaljevec"
    ],
    "name:epo_x_preferred":[
        "Gornji Mihaljevec"
    ],
    "name:fra_x_preferred":[
        "Gornji Mihaljevec"
    ],
    "name:hrv_x_preferred":[
        "Gornji Mihaljevec"
    ],
    "name:hun_x_preferred":[
        "Fels\u0151mih\u00e1lyfalva"
    ],
    "name:ita_x_preferred":[
        "Gornji Mihaljevec"
    ],
    "name:nld_x_preferred":[
        "Gornji Mihaljevec"
    ],
    "name:pol_x_preferred":[
        "Gmina Gornji Mihaljevec"
    ],
    "name:ron_x_preferred":[
        "Comuna Gornji Mihaljevec"
    ],
    "name:slv_x_preferred":[
        "Gornji Mihaljevec"
    ],
    "name:srp_x_preferred":[
        "\u0413\u043e\u0440\u045a\u0438 \u041c\u0438\u0445\u0430\u0459\u0435\u0432\u0435\u0446"
    ],
    "name:ukr_x_preferred":[
        "\u0413\u043e\u0440\u043d\u0456\u0439 \u041c\u0438\u0445\u0430\u043b\u0454\u0432\u0435\u0446\u044c"
    ],
    "name:war_x_preferred":[
        "Gornji Mihaljevec"
    ],
    "wof:name":"Gornji Mihaljevec",
    "wof:placetype":"locality"
},
  "geometry": {"coordinates":[16.33328,46.42864],"type":"Point"}
}