{
  "type": "Feature",
  "properties": {
    "gn:admin1_code":"09",
    "gn:admin2_code":"11054839.0",
    "gn:asciiname":"Gornji Mihaljevec",
    "gn:country_code":"HR",
    "gn:dem":224,
    "gn:feature_class":"P",
    "gn:feature_code":"PPLA2",
    "gn:name":"Gornji Mihaljevec",
    "gn:population":0,
    "gn:timezone":"Europe/Zagreb",
    "iso:country":"HR",
    "wof:name":"Gornji Mihaljevec",
    "wof:placetype":"locality"
},
  "geometry": {"coordinates":[16.33328,46.42864],"type":"Point"}
}