{
  "type": "Feature",
  "properties": {
    "gn:admin1_code":"15.0",
    "gn:asciiname":"Ivanovici",
    "gn:country_code":"HR",
    "gn:dem":495,
    "gn:feature_class":"P",
    "gn:feature_code":"PPL",
    "gn:name":"Ivanovi\u0107i",
    "gn:population":0,
    "gn:timezone":"Europe/Zagreb",
    "iso:country":"HR",
    "wof:name":"Ivanovici",
    "wof:placetype":"locality"
},
  "geometry": {"coordinates":[17.15444,43.36972],"type":"Point"}
}