{
  "type": "Feature",
  "properties": {
    "gn:admin1_code":"15.0",
    "gn:asciiname":"Donji Arambasici",
    "gn:country_code":"HR",
    "gn:dem":475,
    "gn:feature_class":"P",
    "gn:feature_code":"PPL",
    "gn:name":"Donji Aramba\u0161i\u0107i",
    "gn:population":0,
    "gn:timezone":"Europe/Zagreb",
    "iso:country":"HR",
    "wof:name":"Donji Arambasici",
    "wof:placetype":"locality"
},
  "geometry": {"coordinates":[17.29833,43.30889000000001],"type":"Point"}
}