{
  "type": "Feature",
  "properties": {
    "gn:admin1_code":"4.0",
    "gn:admin2_code":"11054800.0",
    "gn:asciiname":"Makovci",
    "gn:country_code":"HR",
    "gn:dem":281,
    "gn:feature_class":"P",
    "gn:feature_code":"PPL",
    "gn:name":"Makovci",
    "gn:population":0,
    "gn:timezone":"Europe/Zagreb",
    "iso:country":"HR",
    "wof:name":"Makovci",
    "wof:placetype":"locality"
},
  "geometry": {"coordinates":[13.78028,45.39222],"type":"Point"}
}