{
  "type": "Feature",
  "properties": {
    "gn:admin1_code":"15.0",
    "gn:asciiname":"Perusi",
    "gn:country_code":"HR",
    "gn:dem":457,
    "gn:feature_class":"P",
    "gn:feature_code":"PPL",
    "gn:name":"Peru\u0161i",
    "gn:population":0,
    "gn:timezone":"Europe/Zagreb",
    "iso:country":"HR",
    "wof:name":"Perusi",
    "wof:placetype":"locality"
},
  "geometry": {"coordinates":[16.50444,43.88056],"type":"Point"}
}