{
  "type": "Feature",
  "properties": {
    "gn:admin1_code":"8.0",
    "gn:admin2_code":"11049294.0",
    "gn:asciiname":"Trnava Poljana",
    "gn:country_code":"HR",
    "gn:dem":942,
    "gn:feature_class":"P",
    "gn:feature_code":"PPL",
    "gn:name":"Trnava Poljana",
    "gn:population":0,
    "gn:timezone":"Europe/Zagreb",
    "iso:country":"HR",
    "wof:name":"Trnava Poljana",
    "wof:placetype":"locality"
},
  "geometry": {"coordinates":[15.87056,44.51528],"type":"Point"}
}