{
  "type": "Feature",
  "properties": {
    "gn:admin1_code":"15.0",
    "gn:asciiname":"Nenadici",
    "gn:country_code":"HR",
    "gn:dem":603,
    "gn:feature_class":"P",
    "gn:feature_code":"PPL",
    "gn:name":"Nenadi\u0107i",
    "gn:population":0,
    "gn:timezone":"Europe/Zagreb",
    "iso:country":"HR",
    "wof:name":"Nenadici",
    "wof:placetype":"locality"
},
  "geometry": {"coordinates":[17.24889,43.48306],"type":"Point"}
}