{
  "type": "Feature",
  "properties": {
    "gn:country":"HR",
    "gn:fcode":"PPL",
    "gn:population":526,
    "iso:country":"HR",
    "name:bos_x_preferred":[
        "Vrboska"
    ],
    "name:bul_x_preferred":[
        "\u0412\u0440\u0431\u043e\u0441\u043a\u0430"
    ],
    "name:ceb_x_preferred":[
        "Vrboska"
    ],
    "name:ces_x_preferred":[
        "Vrboska"
    ],
    "name:deu_x_preferred":[
        "Vrboska"
    ],
    "name:eng_x_preferred":[
        "Vrboska"
    ],
    "name:fra_x_preferred":[
        "Vrboska"
    ],
    "name:frc_x_preferred":[
        "Vrboska"
    ],
    "name:hrv_x_preferred":[
        "Vrboska"
    ],
    "name:hun_x_preferred":[
        "Vrboska"
    ],
    "name:ind_x_preferred":[
        "Vrboska"
    ],
    "name:ita_x_preferred":[
        "Verbosca"
    ],
    "name:nld_x_preferred":[
        "Vrboska"
    ],
    "name:pol_x_preferred":[
        "Vrboska"
    ],
    "name:ron_x_preferred":[
        "Vrboska"
    ],
    "name:rus_x_preferred":[
        "\u0412\u0440\u0431\u043e\u0441\u043a\u0430"
    ],
    "name:slv_x_preferred":[
        "Vrboska"
    ],
    "name:srp_x_preferred":[
        "\u0412\u0440\u0431\u043e\u0441\u043a\u0430"
    ],
    "name:swe_x_preferred":[
        "Vrboska"
    ],
    "name:ukr_x_preferred":[
        "\u0412\u0440\u0431\u043e\u0441\u044c\u043a\u0430"
    ],
    "name:und_x_variant":[
        "Vrbovska"
    ],
    "name:zho_x_preferred":[
        "\u7dad\u723e\u535a\u65af\u5361"
    ],
    "qs_pg:aaroncc":"HR",
    "qs_pg:gn_country":"HR",
    "qs_pg:gn_fcode":"PPL",
    "qs_pg:gn_pop":526,
    "qs_pg:name":"Vrboska",
    "qs_pg:name_adm0":"Hrvatska",
    "qs_pg:name_adm1":"Splitsko-Dalmatinska",
    "qs_pg:photos":594,
    "qs_pg:photos_1k":120,
    "qs_pg:photos_9k":3,
    "qs_pg:photos_9r":5,
    "qs_pg:photos_all":594,
    "qs_pg:photos_sr":8,
    "qs_pg:pop_sr":2,
    "qs_pg:qs_pg_placetype":"locality",
    "qs_pg:qs_pg_placetype_gp":"Town",
    "qs_pg:woe_adm0":23424843,
    "woe:adm0_id":23424843,
    "woe:name_adm0":"Hrvatska",
    "woe:name_adm1":"Splitsko-Dalmatinska",
    "woe:placetype":"Town",
    "wof:name":"Vrboska",
    "wof:placetype":"locality",
    "wof:population":548
},
  "geometry": {"coordinates":[16.67083,43.18222],"type":"Point"}
}