{
  "type": "Feature",
  "properties": {
    "gn:admin1_code":"11",
    "gn:admin2_code":"11049476.0",
    "gn:asciiname":"Kula",
    "gn:country_code":"HR",
    "gn:dem":167,
    "gn:feature_class":"P",
    "gn:feature_code":"PPL",
    "gn:name":"Kula",
    "gn:population":331,
    "gn:timezone":"Europe/Zagreb",
    "iso:country":"HR",
    "wof:name":"Kula",
    "wof:placetype":"locality",
    "wof:population":331
},
  "geometry": {"coordinates":[17.89444,45.38611],"type":"Point"}
}