{
  "type": "Feature",
  "properties": {
    "gn:country":"HR",
    "gn:fcode":"PPL",
    "gn:population":822,
    "iso:country":"HR",
    "qs_pg:aaroncc":"HR",
    "qs_pg:gn_country":"HR",
    "qs_pg:gn_fcode":"PPL",
    "qs_pg:gn_pop":822,
    "qs_pg:name":"Trenkovo",
    "qs_pg:name_adm0":"Hrvatska",
    "qs_pg:name_adm1":"Po\u017ee\u0161ko-slavonska",
    "qs_pg:photos_9k":1,
    "qs_pg:photos_9r":1,
    "qs_pg:photos_all":1,
    "qs_pg:photos_sr":0,
    "qs_pg:pop_sr":2,
    "qs_pg:qs_pg_placetype":"locality",
    "qs_pg:qs_pg_placetype_gp":"Town",
    "qs_pg:woe_adm0":23424843,
    "woe:adm0_id":23424843,
    "woe:name_adm0":"Hrvatska",
    "woe:name_adm1":"Po\u017ee\u0161ko-slavonska",
    "woe:placetype":"Town",
    "wof:name":"Trenkovo",
    "wof:placetype":"locality",
    "wof:population":799
},
  "geometry": {"coordinates":[17.66333,45.40278],"type":"Point"}
}