{
  "type": "Feature",
  "properties": {
    "gn:admin1_code":"04",
    "gn:admin2_code":"11054747.0",
    "gn:asciiname":"Fiorini",
    "gn:country_code":"HR",
    "gn:dem":45,
    "gn:feature_class":"P",
    "gn:feature_code":"PPL",
    "gn:name":"Fiorini",
    "gn:population":0,
    "gn:timezone":"Europe/Zagreb",
    "iso:country":"HR",
    "name:bos_x_preferred":[
        "Fiorini"
    ],
    "name:fra_x_preferred":[
        "Fiorini"
    ],
    "name:hrv_x_preferred":[
        "Fiorini"
    ],
    "name:hun_x_preferred":[
        "Fiorini"
    ],
    "name:ita_x_preferred":[
        "Fiorini"
    ],
    "name:nld_x_preferred":[
        "Fiorini"
    ],
    "name:pol_x_preferred":[
        "Fiorini"
    ],
    "name:slv_x_preferred":[
        "Fiorini"
    ],
    "name:srp_x_preferred":[
        "\u0424\u0438\u043e\u0440\u0438\u043d\u0438"
    ],
    "name:ukr_x_preferred":[
        "\u0424\u0456\u043e\u0440\u0438\u043d\u0438"
    ],
    "wof:name":"Fiorini",
    "wof:placetype":"locality"
},
  "geometry": {"coordinates":[13.58778,45.36167],"type":"Point"}
}