{
  "type": "Feature",
  "properties": {
    "gn:admin1_code":"8.0",
    "gn:admin2_code":"11049291.0",
    "gn:asciiname":"Klobucari",
    "gn:cc2":"HR",
    "gn:country_code":"HR",
    "gn:dem":747,
    "gn:feature_class":"P",
    "gn:feature_code":"PPL",
    "gn:name":"Klobu\u010dari",
    "gn:population":0,
    "gn:timezone":"Europe/Zagreb",
    "iso:country":"HR",
    "name:und_x_variant":[
        "Klobu\u010dare",
        "Klobu\u010dari"
    ],
    "wof:name":"Klobucari",
    "wof:placetype":"locality"
},
  "geometry": {"coordinates":[15.14972,44.78028],"type":"Point"}
}