{
  "type": "Feature",
  "properties": {
    "gn:admin1_code":"14.0",
    "gn:asciiname":"Radasnica",
    "gn:country_code":"HR",
    "gn:dem":270,
    "gn:feature_class":"P",
    "gn:feature_code":"PPL",
    "gn:name":"Rada\u0161nica",
    "gn:population":0,
    "gn:timezone":"Europe/Zagreb",
    "iso:country":"HR",
    "wof:name":"Radasnica",
    "wof:placetype":"locality"
},
  "geometry": {"coordinates":[16.11277999999999,45.11806],"type":"Point"}
}