{
  "type": "Feature",
  "properties": {
    "gn:admin1_code":"09",
    "gn:admin2_code":"11054845.0",
    "gn:asciiname":"Kriz Dravski",
    "gn:cc2":"HR",
    "gn:country_code":"HR",
    "gn:dem":153,
    "gn:feature_class":"P",
    "gn:feature_code":"PPL",
    "gn:name":"Kri\u017e Dravski",
    "gn:population":0,
    "gn:timezone":"Europe/Zagreb",
    "iso:country":"HR",
    "name:und_x_variant":[
        "Dravski Sveti Kri\u017e",
        "Kri\u017e Dravski"
    ],
    "wof:name":"Kriz Dravski",
    "wof:placetype":"locality"
},
  "geometry": {"coordinates":[16.53917,46.34306],"type":"Point"}
}