{
  "type": "Feature",
  "properties": {
    "gn:admin1_code":"15.0",
    "gn:asciiname":"Gornji Muslimi",
    "gn:country_code":"HR",
    "gn:dem":861,
    "gn:feature_class":"P",
    "gn:feature_code":"PPL",
    "gn:name":"Gornji Muslimi",
    "gn:population":0,
    "gn:timezone":"Europe/Zagreb",
    "iso:country":"HR",
    "wof:name":"Gornji Muslimi",
    "wof:placetype":"locality"
},
  "geometry": {"coordinates":[16.50944,43.74611],"type":"Point"}
}