{
  "type": "Feature",
  "properties": {
    "gn:admin1_code":"20",
    "gn:admin2_code":"3187264.0",
    "gn:asciiname":"Brcevec",
    "gn:country_code":"HR",
    "gn:dem":110,
    "gn:feature_class":"P",
    "gn:feature_code":"PPL",
    "gn:name":"Br\u010devec",
    "gn:population":546,
    "gn:timezone":"Europe/Zagreb",
    "iso:country":"HR",
    "wof:name":"Brcevec",
    "wof:placetype":"locality",
    "wof:population":546
},
  "geometry": {"coordinates":[16.41667,45.86667],"type":"Point"}
}