{
  "type": "Feature",
  "properties": {
    "gn:admin1_code":"01",
    "gn:admin2_code":"11049426.0",
    "gn:asciiname":"Malo Trojstvo",
    "gn:country_code":"HR",
    "gn:dem":181,
    "gn:feature_class":"P",
    "gn:feature_code":"PPL",
    "gn:name":"Malo Trojstvo",
    "gn:population":158,
    "gn:timezone":"Europe/Zagreb",
    "iso:country":"HR",
    "wof:name":"Malo Trojstvo",
    "wof:placetype":"locality",
    "wof:population":158
},
  "geometry": {"coordinates":[16.94861,45.97278],"type":"Point"}
}