{
  "type": "Feature",
  "properties": {
    "gn:admin1_code":"08",
    "gn:admin2_code":"11049284.0",
    "gn:asciiname":"Zupanjol",
    "gn:cc2":"HR",
    "gn:country_code":"HR",
    "gn:dem":650,
    "gn:feature_class":"P",
    "gn:feature_code":"PPL",
    "gn:name":"\u017dupanjol",
    "gn:population":0,
    "gn:timezone":"Europe/Zagreb",
    "iso:country":"HR",
    "name:und_x_variant":[
        "\u017dupanjel",
        "\u017dupanjol"
    ],
    "wof:name":"Zupanjol",
    "wof:placetype":"locality"
},
  "geometry": {"coordinates":[15.02639,45.005],"type":"Point"}
}