{
  "type": "Feature",
  "properties": {
    "gn:admin1_code":"14.0",
    "gn:admin2_code":"11049230.0",
    "gn:asciiname":"Veliko Krcevo",
    "gn:country_code":"HR",
    "gn:dem":138,
    "gn:feature_class":"P",
    "gn:feature_code":"PPL",
    "gn:name":"Veliko Kr\u010devo",
    "gn:population":79,
    "gn:timezone":"Europe/Zagreb",
    "iso:country":"HR",
    "name:und_x_variant":[
        "Veliko Kr\u010devo"
    ],
    "wof:name":"Veliko Krcevo",
    "wof:placetype":"locality",
    "wof:population":79
},
  "geometry": {"coordinates":[16.51829,45.28678],"type":"Point"}
}