{
  "type": "Feature",
  "properties": {
    "gn:admin1_code":"14.0",
    "gn:admin2_code":"11049230.0",
    "gn:asciiname":"Veliko Krcevo",
    "gn:country_code":"HR",
    "gn:dem":138,
    "gn:feature_class":"P",
    "gn:feature_code":"PPL",
    "gn:name":"Veliko Kr\u010devo",
    "gn:population":79,
    "gn:timezone":"Europe/Zagreb",
    "iso:country":"HR",
    "name:bos_x_preferred":[
        "Veliko Kr\u010devo"
    ],
    "name:fas_x_preferred":[
        "\u0648\u0644\u06cc\u06a9\u0648 \u06a9\u0631\u0686\u0648\u0648"
    ],
    "name:fra_x_preferred":[
        "Veliko Kr\u010devo"
    ],
    "name:hrv_x_preferred":[
        "Veliko Kr\u010devo"
    ],
    "name:hun_x_preferred":[
        "Veliko Kr\u010devo"
    ],
    "name:nld_x_preferred":[
        "Veliko Kr\u010devo"
    ],
    "name:slv_x_preferred":[
        "Veliko Kr\u010devo"
    ],
    "name:spa_x_preferred":[
        "Veliko Kr\u010devo"
    ],
    "name:srp_x_preferred":[
        "\u0412\u0435\u043b\u0438\u043a\u043e \u041a\u0440\u0447\u0435\u0432\u043e"
    ],
    "name:ukr_x_preferred":[
        "\u0412\u0435\u043b\u0438\u043a\u043e \u041a\u0440\u0447\u0435\u0432\u043e"
    ],
    "wof:name":"Veliko Krcevo",
    "wof:placetype":"locality",
    "wof:population":79
},
  "geometry": {"coordinates":[16.51829,45.28678],"type":"Point"}
}