{
  "type": "Feature",
  "properties": {
    "gn:admin1_code":"08",
    "gn:admin2_code":"11049292.0",
    "gn:asciiname":"Plitvicki Ljeskovac",
    "gn:cc2":"HR",
    "gn:country_code":"HR",
    "gn:dem":647,
    "gn:feature_class":"P",
    "gn:feature_code":"PPL",
    "gn:name":"Plitvi\u010dki Ljeskovac",
    "gn:population":0,
    "gn:timezone":"Europe/Zagreb",
    "iso:country":"HR",
    "name:und_x_variant":[
        "Ljeskovac",
        "Plitvi\u010dki Leskovac",
        "Plitvi\u010dki Ljeskovac"
    ],
    "wof:name":"Plitvicki Ljeskovac",
    "wof:placetype":"locality"
},
  "geometry": {"coordinates":[15.60278,44.845],"type":"Point"}
}