{
  "type": "Feature",
  "properties": {
    "gn:admin1_code":"10",
    "gn:admin2_code":"11054455.0",
    "gn:asciiname":"Gornja Moticina",
    "gn:country_code":"HR",
    "gn:dem":193,
    "gn:feature_class":"P",
    "gn:feature_code":"PPL",
    "gn:name":"Gornja Moti\u010dina",
    "gn:population":49,
    "gn:timezone":"Europe/Zagreb",
    "iso:country":"HR",
    "wof:name":"Gornja Moticina",
    "wof:placetype":"locality",
    "wof:population":49
},
  "geometry": {"coordinates":[17.97139,45.47167],"type":"Point"}
}