{
  "type": "Feature",
  "properties": {
    "gn:admin1_code":"15.0",
    "gn:asciiname":"Njivice",
    "gn:country_code":"HR",
    "gn:dem":366,
    "gn:feature_class":"P",
    "gn:feature_code":"PPL",
    "gn:name":"Njivice",
    "gn:population":0,
    "gn:timezone":"Europe/Zagreb",
    "iso:country":"HR",
    "wof:name":"Njivice",
    "wof:placetype":"locality"
},
  "geometry": {"coordinates":[17.15694,43.3075],"type":"Point"}
}