{
  "type": "Feature",
  "properties": {
    "gn:admin1_code":"20",
    "gn:admin2_code":"11048994.0",
    "gn:asciiname":"Recica Kriska",
    "gn:cc2":"HR",
    "gn:country_code":"HR",
    "gn:dem":103,
    "gn:feature_class":"P",
    "gn:feature_code":"PPL",
    "gn:name":"Re\u010dica Kri\u0161ka",
    "gn:population":346,
    "gn:timezone":"Europe/Zagreb",
    "iso:country":"HR",
    "name:bos_x_preferred":[
        "Re\u010dica Kri\u0161ka"
    ],
    "name:ceb_x_preferred":[
        "Re\u010dica Kri\u0161ka"
    ],
    "name:hrv_x_preferred":[
        "Re\u010dica Kri\u0161ka"
    ],
    "name:hun_x_preferred":[
        "Re\u010dica Kri\u0161ka"
    ],
    "name:nld_x_preferred":[
        "Re\u010dica Kri\u0161ka"
    ],
    "name:slv_x_preferred":[
        "Re\u010dica Kri\u0161ka"
    ],
    "name:spa_x_preferred":[
        "Re\u010dica Kri\u0161ka"
    ],
    "name:srp_x_preferred":[
        "\u0420\u0435\u0447\u0438\u0446\u0430 \u041a\u0440\u0438\u0448\u043a\u0430"
    ],
    "name:swe_x_preferred":[
        "Re\u010dica Kri\u0161ka"
    ],
    "name:ukr_x_preferred":[
        "\u0420\u0435\u0447\u0438\u0446\u044f-\u041a\u0440\u0438\u0441\u044c\u043a\u0430"
    ],
    "name:und_x_variant":[
        "Kri\u0161ka Re\u010dica",
        "Re\u010dica Kr\u0161ka",
        "Re\u010dica"
    ],
    "wof:name":"Recica Kriska",
    "wof:placetype":"locality",
    "wof:population":346
},
  "geometry": {"coordinates":[16.58083,45.66167],"type":"Point"}
}