{
  "type": "Feature",
  "properties": {
    "gn:admin1_code":"4.0",
    "gn:asciiname":"Katun Gracanski",
    "gn:cc2":"HR",
    "gn:country_code":"HR",
    "gn:dem":393,
    "gn:feature_class":"P",
    "gn:feature_code":"PPL",
    "gn:name":"Katun Gra\u010danski",
    "gn:population":0,
    "gn:timezone":"Europe/Zagreb",
    "iso:country":"HR",
    "name:und_x_variant":[
        "Ten\u010di\u0107i",
        "Katun Gra\u010danski"
    ],
    "wof:name":"Katun Gracanski",
    "wof:placetype":"locality"
},
  "geometry": {"coordinates":[13.97556,45.20583],"type":"Point"}
}