{
  "type": "Feature",
  "properties": {
    "gn:admin1_code":"14",
    "gn:admin2_code":"11049234.0",
    "gn:asciiname":"Gregani",
    "gn:country_code":"HR",
    "gn:dem":163,
    "gn:feature_class":"P",
    "gn:feature_code":"PPL",
    "gn:name":"Gre\u0111ani",
    "gn:population":341,
    "gn:timezone":"Europe/Zagreb",
    "iso:country":"HR",
    "name:und_x_variant":[
        "Gredjani",
        "Gre\u0111ani"
    ],
    "wof:name":"Gregani",
    "wof:placetype":"locality",
    "wof:population":341
},
  "geometry": {"coordinates":[15.97378,45.31317],"type":"Point"}
}