{
  "type": "Feature",
  "properties": {
    "gn:gn_country":"HR",
    "gn:gn_fcode":"PPL",
    "gn:gn_pop":0,
    "gn:population":153,
    "iso:country":"HR",
    "name:arm_x_preferred":[
        "\u054c\u0578\u0579"
    ],
    "name:bos_x_preferred":[
        "Ro\u010d"
    ],
    "name:dut_x_preferred":[
        "Ro\u010d"
    ],
    "name:eng_x_preferred":[
        "Ro\u010d"
    ],
    "name:fre_x_preferred":[
        "Ro\u010d"
    ],
    "name:ger_x_preferred":[
        "Ro\u010d"
    ],
    "name:hrv_x_preferred":[
        "Ro\u010d"
    ],
    "name:hun_x_preferred":[
        "Ro\u010d"
    ],
    "name:ita_x_preferred":[
        "Rozzo"
    ],
    "name:rus_x_preferred":[
        "\u0420\u043e\u0447"
    ],
    "name:slv_x_preferred":[
        "Ro\u010d"
    ],
    "name:srp_x_preferred":[
        "\u0420\u043e\u0447"
    ],
    "name:swe_x_preferred":[
        "Ro\u010d"
    ],
    "name:unk_x_variant":[
        "Rozzo d\u2019Istria"
    ],
    "qs_pg:aaroncc":"HR",
    "qs_pg:gn_country":"HR",
    "qs_pg:gn_fcode":"PPL",
    "qs_pg:gn_pop":0,
    "qs_pg:name":"Ro\u010d",
    "qs_pg:name_adm0":"Hrvatska",
    "qs_pg:name_adm1":"Istarska",
    "qs_pg:photos":69,
    "qs_pg:photos_1k":14,
    "qs_pg:photos_9k":1,
    "qs_pg:photos_9r":2,
    "qs_pg:photos_all":69,
    "qs_pg:photos_sr":2,
    "qs_pg:pop_sr":0,
    "qs_pg:qs_pg_placetype":"locality",
    "qs_pg:qs_pg_placetype_gp":"Town",
    "qs_pg:woe_adm0":23424843,
    "woe:adm0_id":23424843,
    "woe:name_adm0":"Hrvatska",
    "woe:name_adm1":"Istarska",
    "woe:placetype":"Town",
    "wof:name":"Ro\u010d",
    "wof:placetype":"locality",
    "wof:population":153
},
  "geometry": {"coordinates":[14.04722,45.39222],"type":"Point"}
}