{
  "type": "Feature",
  "properties": {
    "gn:admin1_code":"2.0",
    "gn:admin2_code":"11049480.0",
    "gn:asciiname":"Banovci",
    "gn:country_code":"HR",
    "gn:dem":85,
    "gn:feature_class":"P",
    "gn:feature_code":"PPL",
    "gn:name":"Banovci",
    "gn:population":357,
    "gn:timezone":"Europe/Zagreb",
    "iso:country":"HR",
    "wof:name":"Banovci",
    "wof:placetype":"locality",
    "wof:population":357
},
  "geometry": {"coordinates":[17.83806000000001,45.08222],"type":"Point"}
}