{
  "type": "Feature",
  "properties": {
    "gn:admin1_code":"8.0",
    "gn:admin2_code":"11049295.0",
    "gn:asciiname":"Novakovici",
    "gn:country_code":"HR",
    "gn:dem":519,
    "gn:feature_class":"P",
    "gn:feature_code":"PPL",
    "gn:name":"Novakovi\u0107i",
    "gn:population":0,
    "gn:timezone":"Europe/Zagreb",
    "iso:country":"HR",
    "wof:name":"Novakovici",
    "wof:placetype":"locality"
},
  "geometry": {"coordinates":[15.34833,44.87],"type":"Point"}
}