{
  "type": "Feature",
  "properties": {
    "gn:admin1_code":"15.0",
    "gn:asciiname":"Bajto",
    "gn:country_code":"HR",
    "gn:dem":375,
    "gn:feature_class":"P",
    "gn:feature_code":"PPL",
    "gn:name":"Bajto",
    "gn:population":0,
    "gn:timezone":"Europe/Zagreb",
    "iso:country":"HR",
    "wof:name":"Bajto",
    "wof:placetype":"locality"
},
  "geometry": {"coordinates":[17.26527999999999,43.24167],"type":"Point"}
}