{
  "type": "Feature",
  "properties": {
    "gn:admin1_code":"19.0",
    "gn:admin2_code":"11054319.0",
    "gn:asciiname":"Tiskovac Licki",
    "gn:cc2":"HR",
    "gn:country_code":"HR",
    "gn:dem":608,
    "gn:feature_class":"P",
    "gn:feature_code":"PPLL",
    "gn:name":"Ti\u0161kovac Li\u010dki",
    "gn:population":0,
    "gn:timezone":"Europe/Zagreb",
    "iso:country":"HR",
    "name:und_x_variant":[
        "Ti\u0161kovac",
        "Ti\u0161kovac Li\u010dki"
    ],
    "wof:name":"Tiskovac Licki",
    "wof:placetype":"locality"
},
  "geometry": {"coordinates":[16.18,44.26889],"type":"Point"}
}