{
  "type": "Feature",
  "properties": {
    "gn:admin1_code":"14.0",
    "gn:asciiname":"Ostojici",
    "gn:country_code":"HR",
    "gn:dem":307,
    "gn:feature_class":"P",
    "gn:feature_code":"PPL",
    "gn:name":"Ostoji\u0107i",
    "gn:population":0,
    "gn:timezone":"Europe/Zagreb",
    "iso:country":"HR",
    "wof:name":"Ostojici",
    "wof:placetype":"locality"
},
  "geometry": {"coordinates":[16.07194,45.16917],"type":"Point"}
}