{
  "type": "Feature",
  "properties": {
    "gn:admin1_code":"8.0",
    "gn:asciiname":"Slavkovici",
    "gn:country_code":"HR",
    "gn:dem":492,
    "gn:feature_class":"P",
    "gn:feature_code":"PPL",
    "gn:name":"Slavkovi\u0107i",
    "gn:population":0,
    "gn:timezone":"Europe/Zagreb",
    "iso:country":"HR",
    "wof:name":"Slavkovici",
    "wof:placetype":"locality"
},
  "geometry": {"coordinates":[15.18833,44.92278],"type":"Point"}
}