{
  "type": "Feature",
  "properties": {
    "gn:admin1_code":"8.0",
    "gn:admin2_code":"11049286.0",
    "gn:asciiname":"Musaluk",
    "gn:country_code":"HR",
    "gn:dem":570,
    "gn:feature_class":"P",
    "gn:feature_code":"PPL",
    "gn:name":"Mu\u0161aluk",
    "gn:population":228,
    "gn:timezone":"Europe/Zagreb",
    "iso:country":"HR",
    "wof:name":"Musaluk",
    "wof:placetype":"locality",
    "wof:population":228
},
  "geometry": {"coordinates":[15.38528,44.60917],"type":"Point"}
}