{
  "type": "Feature",
  "properties": {
    "gn:admin1_code":"8.0",
    "gn:asciiname":"Jelici",
    "gn:cc2":"HR",
    "gn:country_code":"HR",
    "gn:dem":580,
    "gn:feature_class":"P",
    "gn:feature_code":"PPL",
    "gn:name":"Jeli\u0107i",
    "gn:population":0,
    "gn:timezone":"Europe/Zagreb",
    "iso:country":"HR",
    "name:und_x_variant":[
        "Jeli\u0107",
        "Jeli\u0107i"
    ],
    "wof:name":"Jelici",
    "wof:placetype":"locality"
},
  "geometry": {"coordinates":[15.26556,44.60833],"type":"Point"}
}