{
  "type": "Feature",
  "properties": {
    "gn:gn_country":"HR",
    "gn:gn_fcode":"PPL",
    "gn:gn_pop":0,
    "gn:population":116,
    "iso:country":"HR",
    "name:unk_x_variant":[
        "Sveta Jana"
    ],
    "qs_pg:aaroncc":"HR",
    "qs_pg:gn_country":"HR",
    "qs_pg:gn_fcode":"PPL",
    "qs_pg:gn_pop":0,
    "qs_pg:name":"Gorica Svetojanska",
    "qs_pg:name_adm0":"Hrvatska",
    "qs_pg:name_adm1":"Zagreba\u010dka",
    "qs_pg:photos":54,
    "qs_pg:photos_1k":11,
    "qs_pg:photos_9k":1,
    "qs_pg:photos_9r":2,
    "qs_pg:photos_all":54,
    "qs_pg:photos_sr":2,
    "qs_pg:pop_sr":0,
    "qs_pg:qs_pg_placetype":"locality",
    "qs_pg:qs_pg_placetype_gp":"Town",
    "qs_pg:woe_adm0":23424843,
    "woe:adm0_id":23424843,
    "woe:name_adm0":"Hrvatska",
    "woe:name_adm1":"Zagreba\u010dka",
    "woe:placetype":"Town",
    "wof:name":"Gorica Svetojanska",
    "wof:placetype":"locality",
    "wof:population":116
},
  "geometry": {"coordinates":[15.59611,45.71889],"type":"Point"}
}