{
  "type": "Feature",
  "properties": {
    "gn:country":"HR",
    "gn:fcode":"PPL",
    "gn:population":0,
    "iso:country":"HR",
    "name:bos_x_preferred":[
        "Gorica Svetojanska"
    ],
    "name:hrv_x_preferred":[
        "Gorica Svetojanska"
    ],
    "name:hun_x_preferred":[
        "Gorica Svetojanska"
    ],
    "name:nld_x_preferred":[
        "Gorica Svetojanska"
    ],
    "name:slv_x_preferred":[
        "Gorica Svetojanska"
    ],
    "name:ukr_x_preferred":[
        "\u0413\u043e\u0440\u0438\u0446\u044f-\u0421\u0432\u0435\u0442\u043e\u044f\u043d\u0441\u044c\u043a\u0430"
    ],
    "name:und_x_variant":[
        "Sveta Jana"
    ],
    "qs_pg:aaroncc":"HR",
    "qs_pg:gn_country":"HR",
    "qs_pg:gn_fcode":"PPL",
    "qs_pg:gn_pop":0,
    "qs_pg:name":"Gorica Svetojanska",
    "qs_pg:name_adm0":"Hrvatska",
    "qs_pg:name_adm1":"Zagreba\u010dka",
    "qs_pg:photos":54,
    "qs_pg:photos_1k":11,
    "qs_pg:photos_9k":1,
    "qs_pg:photos_9r":2,
    "qs_pg:photos_all":54,
    "qs_pg:photos_sr":2,
    "qs_pg:pop_sr":0,
    "qs_pg:qs_pg_placetype":"locality",
    "qs_pg:qs_pg_placetype_gp":"Town",
    "qs_pg:woe_adm0":23424843,
    "woe:adm0_id":23424843,
    "woe:name_adm0":"Hrvatska",
    "woe:name_adm1":"Zagreba\u010dka",
    "woe:placetype":"Town",
    "wof:name":"Gorica Svetojanska",
    "wof:placetype":"locality",
    "wof:population":116
},
  "geometry": {"coordinates":[15.59611,45.71889],"type":"Point"}
}