{
  "type": "Feature",
  "properties": {
    "gn:admin1_code":"4.0",
    "gn:admin2_code":"11054808.0",
    "gn:asciiname":"Pavicini",
    "gn:country_code":"HR",
    "gn:dem":145,
    "gn:feature_class":"P",
    "gn:feature_code":"PPL",
    "gn:name":"Pavicini",
    "gn:population":0,
    "gn:timezone":"Europe/Zagreb",
    "iso:country":"HR",
    "wof:name":"Pavicini",
    "wof:placetype":"locality"
},
  "geometry": {"coordinates":[14.00062,44.92862],"type":"Point"}
}