{
  "type": "Feature",
  "properties": {
    "gn:admin1_code":"3.0",
    "gn:asciiname":"Blato",
    "gn:country_code":"HR",
    "gn:dem":20,
    "gn:feature_class":"P",
    "gn:feature_code":"PPL",
    "gn:name":"Blato",
    "gn:population":0,
    "gn:timezone":"Europe/Zagreb",
    "iso:country":"HR",
    "wof:name":"Blato",
    "wof:placetype":"locality"
},
  "geometry": {"coordinates":[18.17833,42.6225],"type":"Point"}
}