{
  "type": "Feature",
  "properties": {
    "gn:admin1_code":"3.0",
    "gn:asciiname":"Blato",
    "gn:country_code":"HR",
    "gn:dem":20,
    "gn:feature_class":"P",
    "gn:feature_code":"PPL",
    "gn:name":"Blato",
    "gn:population":0,
    "gn:timezone":"Europe/Zagreb",
    "iso:country":"HR",
    "name:bos_x_preferred":[
        "Blato"
    ],
    "name:bul_x_preferred":[
        "\u0411\u043b\u0430\u0442\u043e"
    ],
    "name:ceb_x_preferred":[
        "Blato"
    ],
    "name:ces_x_preferred":[
        "Blato"
    ],
    "name:deu_x_preferred":[
        "Blato"
    ],
    "name:fra_x_preferred":[
        "Blato"
    ],
    "name:hrv_x_preferred":[
        "Blato"
    ],
    "name:hun_x_preferred":[
        "Blato"
    ],
    "name:nld_x_preferred":[
        "Blato"
    ],
    "name:pol_x_preferred":[
        "Blato"
    ],
    "name:por_x_preferred":[
        "Blato"
    ],
    "name:ron_x_preferred":[
        "Blato"
    ],
    "name:rus_x_preferred":[
        "\u0411\u043b\u0430\u0442\u043e"
    ],
    "name:slv_x_preferred":[
        "Blato"
    ],
    "name:srp_x_preferred":[
        "\u0411\u043b\u0430\u0442\u043e"
    ],
    "name:swe_x_preferred":[
        "Blato"
    ],
    "name:ukr_x_preferred":[
        "\u0411\u043b\u0430\u0442\u043e"
    ],
    "wof:name":"Blato",
    "wof:placetype":"locality"
},
  "geometry": {"coordinates":[18.17833,42.6225],"type":"Point"}
}