{
  "type": "Feature",
  "properties": {
    "gn:admin1_code":"12",
    "gn:admin2_code":"11049433.0",
    "gn:asciiname":"Gabonjin",
    "gn:country_code":"HR",
    "gn:dem":225,
    "gn:feature_class":"P",
    "gn:feature_code":"PPL",
    "gn:name":"Gabonjin",
    "gn:population":201,
    "gn:timezone":"Europe/Zagreb",
    "iso:country":"HR",
    "name:bos_x_preferred":[
        "Gabonjin"
    ],
    "name:fra_x_preferred":[
        "Gabonjin"
    ],
    "name:hrv_x_preferred":[
        "Gabonjin"
    ],
    "name:hun_x_preferred":[
        "Gabonjin"
    ],
    "name:slv_x_preferred":[
        "Gabonjin"
    ],
    "name:ukr_x_preferred":[
        "\u0413\u0430\u0431\u043e\u043d\u0456\u043d"
    ],
    "wof:name":"Gabonjin",
    "wof:placetype":"locality",
    "wof:population":201
},
  "geometry": {"coordinates":[14.56628,45.11108],"type":"Point"}
}