{
  "type": "Feature",
  "properties": {
    "gn:admin1_code":"10",
    "gn:asciiname":"Brezovica",
    "gn:cc2":"HR",
    "gn:country_code":"HR",
    "gn:dem":90,
    "gn:feature_class":"P",
    "gn:feature_code":"PPL",
    "gn:name":"Brezovica",
    "gn:population":53,
    "gn:timezone":"Europe/Zagreb",
    "iso:country":"HR",
    "name:bos_x_preferred":[
        "Brezovica"
    ],
    "name:ceb_x_preferred":[
        "Brezovica"
    ],
    "name:ces_x_preferred":[
        "Brezovica"
    ],
    "name:deu_x_preferred":[
        "Brezovica"
    ],
    "name:epo_x_preferred":[
        "Brezovica"
    ],
    "name:fra_x_preferred":[
        "Brezovica"
    ],
    "name:hrv_x_preferred":[
        "Brezovica"
    ],
    "name:hun_x_preferred":[
        "Brezovica"
    ],
    "name:ita_x_preferred":[
        "Brezovica"
    ],
    "name:nld_x_preferred":[
        "Brezovica"
    ],
    "name:pol_x_preferred":[
        "Brezovica"
    ],
    "name:ron_x_preferred":[
        "Brezovica"
    ],
    "name:slk_x_preferred":[
        "Brezovica"
    ],
    "name:slv_x_preferred":[
        "Brezovica"
    ],
    "name:spa_x_preferred":[
        "Brezovica"
    ],
    "name:srp_x_preferred":[
        "\u0411\u0440\u0435\u0437\u043e\u0432\u0438\u0446\u0430"
    ],
    "name:swe_x_preferred":[
        "Brezovica"
    ],
    "name:und_x_variant":[
        "Miholja\u010dka Brezovica",
        "Brezovica Pustara",
        "Brezovica Miholja\u010dka"
    ],
    "name:vie_x_preferred":[
        "Brezovica"
    ],
    "wof:name":"Brezovica",
    "wof:placetype":"locality",
    "wof:population":53
},
  "geometry": {"coordinates":[18.32889,45.64056],"type":"Point"}
}