{
  "type": "Feature",
  "properties": {
    "gn:admin1_code":"10",
    "gn:asciiname":"Brezovica",
    "gn:cc2":"HR",
    "gn:country_code":"HR",
    "gn:dem":90,
    "gn:feature_class":"P",
    "gn:feature_code":"PPL",
    "gn:name":"Brezovica",
    "gn:population":53,
    "gn:timezone":"Europe/Zagreb",
    "iso:country":"HR",
    "name:und_x_variant":[
        "Miholja\u010dka Brezovica",
        "Brezovica Pustara",
        "Brezovica Miholja\u010dka",
        "Brezovica"
    ],
    "wof:name":"Brezovica",
    "wof:placetype":"locality",
    "wof:population":53
},
  "geometry": {"coordinates":[18.32889,45.64056],"type":"Point"}
}