{
  "type": "Feature",
  "properties": {
    "gn:admin1_code":"15.0",
    "gn:asciiname":"Skarici",
    "gn:country_code":"HR",
    "gn:dem":404,
    "gn:feature_class":"P",
    "gn:feature_code":"PPL",
    "gn:name":"\u0160kari\u0107i",
    "gn:population":0,
    "gn:timezone":"Europe/Zagreb",
    "iso:country":"HR",
    "wof:name":"Skarici",
    "wof:placetype":"locality"
},
  "geometry": {"coordinates":[16.82777999999999,43.55028],"type":"Point"}
}