{
  "type": "Feature",
  "properties": {
    "gn:admin1_code":"15.0",
    "gn:asciiname":"Desisevici",
    "gn:country_code":"HR",
    "gn:dem":470,
    "gn:feature_class":"P",
    "gn:feature_code":"PPL",
    "gn:name":"De\u0161i\u0161evi\u0107i",
    "gn:population":0,
    "gn:timezone":"Europe/Zagreb",
    "iso:country":"HR",
    "wof:name":"Desisevici",
    "wof:placetype":"locality"
},
  "geometry": {"coordinates":[16.67722,43.52028],"type":"Point"}
}