{
  "type": "Feature",
  "properties": {
    "gn:gn_country":"HR",
    "gn:gn_fcode":"PPL",
    "gn:gn_pop":13329,
    "gn:population":13329,
    "iso:country":"HR",
    "name:unk_x_variant":[
        "\u00dajgradiska"
    ],
    "qs_pg:aaroncc":"HR",
    "qs_pg:gn_country":"HR",
    "qs_pg:gn_fcode":"PPL",
    "qs_pg:gn_pop":13329,
    "qs_pg:name":"Nova Gradi\u00b5ka",
    "qs_pg:name_adm0":"Hrvatska",
    "qs_pg:name_adm1":"Brodsko-Posavska",
    "qs_pg:photos_9k":1,
    "qs_pg:photos_9r":1,
    "qs_pg:photos_all":8,
    "qs_pg:photos_sr":0,
    "qs_pg:pop_sr":6,
    "qs_pg:qs_pg_placetype":"locality",
    "qs_pg:qs_pg_placetype_gp":"Town",
    "qs_pg:woe_adm0":23424843,
    "woe:adm0_id":23424843,
    "woe:name_adm0":"Hrvatska",
    "woe:name_adm1":"Brodsko-Posavska",
    "woe:placetype":"Town",
    "wof:name":"Nova Gradi\u00b5ka",
    "wof:placetype":"locality",
    "wof:population":13329
},
  "geometry": {"coordinates":[17.38306,45.255],"type":"Point"}
}