{
  "type": "Feature",
  "properties": {
    "gn:admin1_code":"19.0",
    "gn:asciiname":"Loncan",
    "gn:country_code":"HR",
    "gn:dem":392,
    "gn:feature_class":"P",
    "gn:feature_code":"PPL",
    "gn:name":"Lon\u010dan",
    "gn:population":0,
    "gn:timezone":"Europe/Zagreb",
    "iso:country":"HR",
    "wof:name":"Loncan",
    "wof:placetype":"locality"
},
  "geometry": {"coordinates":[15.66417,44.14528],"type":"Point"}
}