{
  "type": "Feature",
  "properties": {
    "gn:admin1_code":"8.0",
    "gn:asciiname":"Opaljene Klade",
    "gn:country_code":"HR",
    "gn:dem":669,
    "gn:feature_class":"P",
    "gn:feature_code":"PPL",
    "gn:name":"Opaljene Klade",
    "gn:population":0,
    "gn:timezone":"Europe/Zagreb",
    "iso:country":"HR",
    "wof:name":"Opaljene Klade",
    "wof:placetype":"locality"
},
  "geometry": {"coordinates":[15.96111,44.64333],"type":"Point"}
}