{
  "type": "Feature",
  "properties": {
    "gn:admin1_code":"5.0",
    "gn:asciiname":"Pod Obale",
    "gn:country_code":"HR",
    "gn:dem":141,
    "gn:feature_class":"P",
    "gn:feature_code":"PPL",
    "gn:name":"Pod Obale",
    "gn:population":0,
    "gn:timezone":"Europe/Zagreb",
    "iso:country":"HR",
    "wof:name":"Pod Obale",
    "wof:placetype":"locality"
},
  "geometry": {"coordinates":[15.81056,45.21111],"type":"Point"}
}