{
  "type": "Feature",
  "properties": {
    "gn:admin1_code":"19.0",
    "gn:asciiname":"Opacici",
    "gn:country_code":"HR",
    "gn:dem":74,
    "gn:feature_class":"P",
    "gn:feature_code":"PPL",
    "gn:name":"Opa\u010di\u0107i",
    "gn:population":0,
    "gn:timezone":"Europe/Zagreb",
    "iso:country":"HR",
    "wof:name":"Opacici",
    "wof:placetype":"locality"
},
  "geometry": {"coordinates":[15.32361,44.14167],"type":"Point"}
}