{
  "type": "Feature",
  "properties": {
    "gn:admin1_code":"14.0",
    "gn:asciiname":"Mali Obljaj",
    "gn:country_code":"HR",
    "gn:dem":239,
    "gn:feature_class":"P",
    "gn:feature_code":"PPLL",
    "gn:name":"Mali Obljaj",
    "gn:population":0,
    "gn:timezone":"Europe/Zagreb",
    "iso:country":"HR",
    "wof:name":"Mali Obljaj",
    "wof:placetype":"locality"
},
  "geometry": {"coordinates":[16.02083,45.23167],"type":"Point"}
}