{
  "type": "Feature",
  "properties": {
    "gn:admin1_code":"15.0",
    "gn:asciiname":"Miljak",
    "gn:country_code":"HR",
    "gn:dem":362,
    "gn:feature_class":"P",
    "gn:feature_code":"PPL",
    "gn:name":"Miljak",
    "gn:population":0,
    "gn:timezone":"Europe/Zagreb",
    "iso:country":"HR",
    "wof:name":"Miljak",
    "wof:placetype":"locality"
},
  "geometry": {"coordinates":[16.76806,43.52306],"type":"Point"}
}