{
  "type": "Feature",
  "properties": {
    "gn:admin1_code":"13.0",
    "gn:asciiname":"Cilasi",
    "gn:country_code":"HR",
    "gn:dem":244,
    "gn:feature_class":"P",
    "gn:feature_code":"PPL",
    "gn:name":"\u010cilasi",
    "gn:population":0,
    "gn:timezone":"Europe/Zagreb",
    "iso:country":"HR",
    "wof:name":"Cilasi",
    "wof:placetype":"locality"
},
  "geometry": {"coordinates":[16.05361,43.96333],"type":"Point"}
}