{
  "type": "Feature",
  "properties": {
    "gn:admin1_code":"8.0",
    "gn:asciiname":"Dunjevac",
    "gn:country_code":"HR",
    "gn:dem":565,
    "gn:feature_class":"P",
    "gn:feature_code":"PPL",
    "gn:name":"Dunjevac",
    "gn:population":0,
    "gn:timezone":"Europe/Zagreb",
    "iso:country":"HR",
    "wof:name":"Dunjevac",
    "wof:placetype":"locality"
},
  "geometry": {"coordinates":[15.33417,44.62556],"type":"Point"}
}