{
  "type": "Feature",
  "properties": {
    "gn:admin1_code":"14.0",
    "gn:asciiname":"Eremije",
    "gn:country_code":"HR",
    "gn:dem":314,
    "gn:feature_class":"P",
    "gn:feature_code":"PPL",
    "gn:name":"Eremije",
    "gn:population":0,
    "gn:timezone":"Europe/Zagreb",
    "iso:country":"HR",
    "wof:name":"Eremije",
    "wof:placetype":"locality"
},
  "geometry": {"coordinates":[16.03694,45.21833],"type":"Point"}
}