{
  "type": "Feature",
  "properties": {
    "gn:admin1_code":"15.0",
    "gn:asciiname":"Maglici",
    "gn:country_code":"HR",
    "gn:dem":514,
    "gn:feature_class":"P",
    "gn:feature_code":"PPL",
    "gn:name":"Magli\u0107i",
    "gn:population":0,
    "gn:timezone":"Europe/Zagreb",
    "iso:country":"HR",
    "wof:name":"Maglici",
    "wof:placetype":"locality"
},
  "geometry": {"coordinates":[16.87806,43.53556],"type":"Point"}
}