{
  "type": "Feature",
  "properties": {
    "gn:gn_country":"HR",
    "gn:gn_fcode":"PPL",
    "gn:gn_pop":0,
    "gn:population":34,
    "iso:country":"HR",
    "name:bos_x_preferred":[
        "Podobu\u010de"
    ],
    "name:ces_x_preferred":[
        "Podobu\u010de"
    ],
    "name:eng_x_preferred":[
        "Podobu\u010de"
    ],
    "name:hrv_x_preferred":[
        "Podobu\u010de"
    ],
    "name:hun_x_preferred":[
        "Podobu\u010de"
    ],
    "name:slv_x_preferred":[
        "Podobu\u010de"
    ],
    "name:srp_x_preferred":[
        "\u041f\u043e\u0434\u043e\u0431\u0443\u0447\u0435"
    ],
    "name:ukr_x_preferred":[
        "\u041f\u043e\u0434\u043e\u0431\u0443\u0447\u0435"
    ],
    "qs_pg:aaroncc":"HR",
    "qs_pg:gn_country":"HR",
    "qs_pg:gn_fcode":"PPL",
    "qs_pg:gn_pop":0,
    "qs_pg:name":"Podobu\u010de",
    "qs_pg:name_adm0":"Hrvatska",
    "qs_pg:name_adm1":"Dubrova\u010dko-neretvanska",
    "qs_pg:photos":35,
    "qs_pg:photos_1k":7,
    "qs_pg:photos_9k":1,
    "qs_pg:photos_9r":2,
    "qs_pg:photos_all":35,
    "qs_pg:photos_sr":2,
    "qs_pg:pop_sr":0,
    "qs_pg:qs_pg_placetype":"locality",
    "qs_pg:qs_pg_placetype_gp":"Town",
    "qs_pg:woe_adm0":23424843,
    "woe:adm0_id":23424843,
    "woe:name_adm0":"Hrvatska",
    "woe:name_adm1":"Dubrova\u010dko-neretvanska",
    "woe:placetype":"Town",
    "wof:name":"Podobu\u010de",
    "wof:placetype":"locality",
    "wof:population":34
},
  "geometry": {"coordinates":[17.28833,42.94861],"type":"Point"}
}