{
  "type": "Feature",
  "properties": {
    "gn:admin1_code":"8.0",
    "gn:asciiname":"Rujnica",
    "gn:country_code":"HR",
    "gn:dem":571,
    "gn:feature_class":"P",
    "gn:feature_code":"PPL",
    "gn:name":"Rujnica",
    "gn:population":0,
    "gn:timezone":"Europe/Zagreb",
    "iso:country":"HR",
    "wof:name":"Rujnica",
    "wof:placetype":"locality"
},
  "geometry": {"coordinates":[15.43056,44.58861],"type":"Point"}
}