{
  "type": "Feature",
  "properties": {
    "gn:admin1_code":"08",
    "gn:admin2_code":"11049288.0",
    "gn:asciiname":"Smokric",
    "gn:country_code":"HR",
    "gn:dem":618,
    "gn:feature_class":"P",
    "gn:feature_code":"PPL",
    "gn:name":"Smokri\u0107",
    "gn:population":23,
    "gn:timezone":"Europe/Zagreb",
    "iso:country":"HR",
    "wof:name":"Smokric",
    "wof:placetype":"locality",
    "wof:population":23
},
  "geometry": {"coordinates":[15.74306,44.38472],"type":"Point"}
}