{
  "type": "Feature",
  "properties": {
    "gn:admin1_code":"19",
    "gn:admin2_code":"11049512.0",
    "gn:asciiname":"Popovic",
    "gn:cc2":"HR",
    "gn:country_code":"HR",
    "gn:dem":251,
    "gn:feature_class":"P",
    "gn:feature_code":"PPL",
    "gn:name":"Popovi\u0107",
    "gn:population":0,
    "gn:timezone":"Europe/Zagreb",
    "iso:country":"HR",
    "name:und_x_variant":[
        "Popovici",
        "Popovi\u0107"
    ],
    "wof:name":"Popovic",
    "wof:placetype":"locality"
},
  "geometry": {"coordinates":[15.66861,44.07333],"type":"Point"}
}