{
  "type": "Feature",
  "properties": {
    "gn:admin1_code":"12.0",
    "gn:asciiname":"Glavotok",
    "gn:country_code":"HR",
    "gn:dem":94,
    "gn:feature_class":"P",
    "gn:feature_code":"PPL",
    "gn:name":"Glavotok",
    "gn:population":0,
    "gn:timezone":"Europe/Zagreb",
    "iso:country":"HR",
    "name:hrv_x_preferred":[
        "Glavotok"
    ],
    "name:nld_x_preferred":[
        "Glavotok"
    ],
    "name:slv_x_preferred":[
        "Glavotok"
    ],
    "wof:name":"Glavotok",
    "wof:placetype":"locality"
},
  "geometry": {"coordinates":[14.44247,45.08928],"type":"Point"}
}