{
  "type": "Feature",
  "properties": {
    "gn:admin1_code":"20",
    "gn:admin2_code":"3186602.0",
    "gn:asciiname":"Gornje Psarjevo",
    "gn:country_code":"HR",
    "gn:dem":197,
    "gn:feature_class":"P",
    "gn:feature_code":"PPL",
    "gn:name":"Gornje Psarjevo",
    "gn:population":467,
    "gn:timezone":"Europe/Zagreb",
    "iso:country":"HR",
    "wof:name":"Gornje Psarjevo",
    "wof:placetype":"locality",
    "wof:population":467
},
  "geometry": {"coordinates":[16.23333,45.95],"type":"Point"}
}