{
  "type": "Feature",
  "properties": {
    "gn:admin1_code":"20",
    "gn:admin2_code":"3186602.0",
    "gn:asciiname":"Gornje Psarjevo",
    "gn:country_code":"HR",
    "gn:dem":197,
    "gn:feature_class":"P",
    "gn:feature_code":"PPL",
    "gn:name":"Gornje Psarjevo",
    "gn:population":467,
    "gn:timezone":"Europe/Zagreb",
    "iso:country":"HR",
    "name:bos_x_preferred":[
        "Gornje Psarjevo"
    ],
    "name:hrv_x_preferred":[
        "Gornje Psarjevo"
    ],
    "name:hun_x_preferred":[
        "Gornje Psarjevo"
    ],
    "name:nld_x_preferred":[
        "Gornje Psarjevo"
    ],
    "name:slv_x_preferred":[
        "Gornje Psarjevo"
    ],
    "name:srp_x_preferred":[
        "\u0413\u043e\u0440\u045a\u0435 \u041f\u0441\u0430\u0440\u0458\u0435\u0432\u043e"
    ],
    "name:ukr_x_preferred":[
        "\u0413\u043e\u0440\u043d\u0454 \u041f\u0441\u0430\u0440'\u0454\u0432\u043e"
    ],
    "wof:name":"Gornje Psarjevo",
    "wof:placetype":"locality",
    "wof:population":467
},
  "geometry": {"coordinates":[16.23333,45.95],"type":"Point"}
}