{
  "type": "Feature",
  "properties": {
    "gn:admin1_code":"19",
    "gn:admin2_code":"11054319.0",
    "gn:asciiname":"Glogovo",
    "gn:country_code":"HR",
    "gn:dem":819,
    "gn:feature_class":"P",
    "gn:feature_code":"PPLL",
    "gn:name":"Glogovo",
    "gn:population":0,
    "gn:timezone":"Europe/Zagreb",
    "iso:country":"HR",
    "name:bul_x_preferred":[
        "\u0413\u043b\u043e\u0433\u043e\u0432\u043e"
    ],
    "name:fas_x_preferred":[
        "\u06af\u0644\u0648\u06af\u0648\u0648\u0648"
    ],
    "name:kaz_x_preferred":[
        "\u0413\u043b\u043e\u0433\u043e\u0432\u043e"
    ],
    "name:ron_x_preferred":[
        "Glogovo"
    ],
    "name:rus_x_preferred":[
        "\u0413\u043b\u043e\u0433\u043e\u0432\u043e"
    ],
    "name:ukr_x_preferred":[
        "\u0413\u043b\u043e\u0433\u043e\u0432\u043e"
    ],
    "wof:name":"Glogovo",
    "wof:placetype":"locality"
},
  "geometry": {"coordinates":[15.95028,44.31194],"type":"Point"}
}