{
  "type": "Feature",
  "properties": {
    "gn:admin1_code":"14",
    "gn:admin2_code":"11049231.0",
    "gn:asciiname":"Martinska Ves",
    "gn:country_code":"HR",
    "gn:dem":100,
    "gn:feature_class":"P",
    "gn:feature_code":"PPLA2",
    "gn:name":"Martinska Ves",
    "gn:population":0,
    "gn:timezone":"Europe/Zagreb",
    "iso:country":"HR",
    "name:bos_x_preferred":[
        "Martinska Ves"
    ],
    "name:fra_x_preferred":[
        "Martinska Ves"
    ],
    "name:hun_x_preferred":[
        "Martinska Ves"
    ],
    "name:nld_x_preferred":[
        "Martinska Ves"
    ],
    "name:srp_x_preferred":[
        "\u041c\u0430\u0440\u0442\u0438\u043d\u0441\u043a\u0430 \u0412\u0435\u0441"
    ],
    "name:und_x_variant":[
        "Martinska Ves Lijeva",
        "Lijeva Martinska Ves",
        "Martinska Ves",
        "Martinska Ves Desna",
        "Desna Martinska Ves"
    ],
    "wof:name":"Martinska Ves",
    "wof:placetype":"locality"
},
  "geometry": {"coordinates":[16.37617,45.58368],"type":"Point"}
}