{
  "type": "Feature",
  "properties": {
    "gn:admin1_code":"20",
    "gn:admin2_code":"3186602.0",
    "gn:asciiname":"Komin",
    "gn:country_code":"HR",
    "gn:dem":131,
    "gn:feature_class":"P",
    "gn:feature_code":"PPL",
    "gn:name":"Komin",
    "gn:population":250,
    "gn:timezone":"Europe/Zagreb",
    "iso:country":"HR",
    "name:bos_x_preferred":[
        "Komin"
    ],
    "name:ceb_x_preferred":[
        "Komin"
    ],
    "name:hrv_x_preferred":[
        "Komin"
    ],
    "name:hun_x_preferred":[
        "Komin"
    ],
    "name:nld_x_preferred":[
        "Komin"
    ],
    "name:slv_x_preferred":[
        "Komin"
    ],
    "name:srp_x_preferred":[
        "\u041a\u043e\u043c\u0438\u043d"
    ],
    "name:swe_x_preferred":[
        "Komin"
    ],
    "wof:name":"Komin",
    "wof:placetype":"locality",
    "wof:population":250
},
  "geometry": {"coordinates":[16.27972,46.00361],"type":"Point"}
}