{
  "type": "Feature",
  "properties": {
    "gn:admin1_code":"8.0",
    "gn:asciiname":"Buk",
    "gn:country_code":"HR",
    "gn:dem":464,
    "gn:feature_class":"P",
    "gn:feature_code":"PPL",
    "gn:name":"Buk",
    "gn:population":0,
    "gn:timezone":"Europe/Zagreb",
    "iso:country":"HR",
    "wof:name":"Buk",
    "wof:placetype":"locality"
},
  "geometry": {"coordinates":[15.1425,44.86806],"type":"Point"}
}