{
  "type": "Feature",
  "properties": {
    "gn:admin1_code":"12",
    "gn:asciiname":"Vele Srakane",
    "gn:cc2":"HR",
    "gn:country_code":"HR",
    "gn:dem":7,
    "gn:feature_class":"P",
    "gn:feature_code":"PPL",
    "gn:name":"Vele Srakane",
    "gn:population":3,
    "gn:timezone":"Europe/Zagreb",
    "iso:country":"HR",
    "name:und_x_variant":[
        "Can\u00eddole Grande",
        "Srakane Vele",
        "Velika Skrakana",
        "Vele Srakane"
    ],
    "wof:name":"Vele Srakane",
    "wof:placetype":"locality",
    "wof:population":3
},
  "geometry": {"coordinates":[14.31472,44.57667],"type":"Point"}
}