{
  "type": "Feature",
  "properties": {
    "gn:admin1_code":"12",
    "gn:asciiname":"Vele Srakane",
    "gn:cc2":"HR",
    "gn:country_code":"HR",
    "gn:dem":7,
    "gn:feature_class":"P",
    "gn:feature_code":"PPL",
    "gn:name":"Vele Srakane",
    "gn:population":3,
    "gn:timezone":"Europe/Zagreb",
    "iso:country":"HR",
    "name:deu_x_preferred":[
        "Vele Srakane"
    ],
    "name:hrv_x_preferred":[
        "Vele Srakane"
    ],
    "name:hun_x_preferred":[
        "Vele Srakane"
    ],
    "name:ind_x_preferred":[
        "Vele Srakane"
    ],
    "name:ita_x_preferred":[
        "Canidole Grande"
    ],
    "name:nno_x_preferred":[
        "Vele Srakane"
    ],
    "name:nor_x_preferred":[
        "Vele Srakane"
    ],
    "name:pol_x_preferred":[
        "Vele Srakane"
    ],
    "name:rus_x_preferred":[
        "\u0412\u0435\u043b\u0435-\u0421\u0440\u0430\u043a\u0430\u043d\u0435"
    ],
    "name:slv_x_preferred":[
        "Vele Srakane"
    ],
    "name:spa_x_preferred":[
        "Vele Srakane"
    ],
    "name:tur_x_preferred":[
        "Vele Srakane"
    ],
    "name:ukr_x_preferred":[
        "\u0412\u0435\u043b\u0435 \u0421\u0440\u0430\u043a\u0430\u043d\u0435"
    ],
    "name:und_x_variant":[
        "Can\u00eddole Grande",
        "Srakane Vele",
        "Velika Skrakana",
        "Vele Srakane"
    ],
    "name:vie_x_preferred":[
        "Vele Srakane"
    ],
    "wof:name":"Vele Srakane",
    "wof:placetype":"locality",
    "wof:population":3
},
  "geometry": {"coordinates":[14.31472,44.57667],"type":"Point"}
}