{
  "type": "Feature",
  "properties": {
    "gn:admin1_code":"08",
    "gn:admin2_code":"11049293.0",
    "gn:asciiname":"Krasno Polje",
    "gn:cc2":"HR",
    "gn:country_code":"HR",
    "gn:dem":790,
    "gn:feature_class":"P",
    "gn:feature_code":"PPL",
    "gn:name":"Krasno Polje",
    "gn:population":0,
    "gn:timezone":"Europe/Zagreb",
    "iso:country":"HR",
    "name:und_x_variant":[
        "Krasno",
        "Krasno Polje"
    ],
    "wof:name":"Krasno Polje",
    "wof:placetype":"locality"
},
  "geometry": {"coordinates":[15.05139,44.82306],"type":"Point"}
}