{
  "type": "Feature",
  "properties": {
    "gn:admin1_code":"19.0",
    "gn:asciiname":"Zupcici",
    "gn:country_code":"HR",
    "gn:dem":132,
    "gn:feature_class":"P",
    "gn:feature_code":"PPL",
    "gn:name":"Zup\u010di\u0107i",
    "gn:population":0,
    "gn:timezone":"Europe/Zagreb",
    "iso:country":"HR",
    "wof:name":"Zupcici",
    "wof:placetype":"locality"
},
  "geometry": {"coordinates":[15.58778,44.12639],"type":"Point"}
}