{
  "type": "Feature",
  "properties": {
    "gn:admin1_code":"3.0",
    "gn:admin2_code":"11054958.0",
    "gn:asciiname":"Klacina",
    "gn:country_code":"HR",
    "gn:dem":23,
    "gn:feature_class":"P",
    "gn:feature_code":"PPL",
    "gn:name":"Kla\u010dina",
    "gn:population":0,
    "gn:timezone":"Europe/Zagreb",
    "iso:country":"HR",
    "wof:name":"Klacina",
    "wof:placetype":"locality"
},
  "geometry": {"coordinates":[17.61028,42.98639],"type":"Point"}
}