{
  "type": "Feature",
  "properties": {
    "gn:admin1_code":"12.0",
    "gn:admin2_code":"11054902.0",
    "gn:asciiname":"Zbicina",
    "gn:country_code":"HR",
    "gn:dem":232,
    "gn:feature_class":"P",
    "gn:feature_code":"PPL",
    "gn:name":"Zbi\u010dina",
    "gn:population":5,
    "gn:timezone":"Europe/Zagreb",
    "iso:country":"HR",
    "wof:name":"Zbicina",
    "wof:placetype":"locality",
    "wof:population":5
},
  "geometry": {"coordinates":[14.34833,44.89861],"type":"Point"}
}