{
  "type": "Feature",
  "properties": {
    "gn:admin1_code":"12",
    "gn:admin2_code":"3202931.0",
    "gn:asciiname":"Hrib",
    "gn:cc2":"HR",
    "gn:country_code":"HR",
    "gn:dem":594,
    "gn:feature_class":"P",
    "gn:feature_code":"PPL",
    "gn:name":"Hrib",
    "gn:population":109,
    "gn:timezone":"Europe/Zagreb",
    "iso:country":"HR",
    "name:und_x_variant":[
        "Skednari",
        "Hrib-Skednari",
        "Hrib"
    ],
    "wof:name":"Hrib",
    "wof:placetype":"locality",
    "wof:population":109
},
  "geometry": {"coordinates":[14.68083,45.51722],"type":"Point"}
}