{
  "type": "Feature",
  "properties": {
    "gn:admin1_code":"12",
    "gn:admin2_code":"3202931.0",
    "gn:asciiname":"Hrib",
    "gn:cc2":"HR",
    "gn:country_code":"HR",
    "gn:dem":594,
    "gn:feature_class":"P",
    "gn:feature_code":"PPL",
    "gn:name":"Hrib",
    "gn:population":109,
    "gn:timezone":"Europe/Zagreb",
    "iso:country":"HR",
    "name:bos_x_preferred":[
        "Hrib"
    ],
    "name:fra_x_preferred":[
        "Hrib"
    ],
    "name:hrv_x_preferred":[
        "Hrib"
    ],
    "name:hun_x_preferred":[
        "Hrib"
    ],
    "name:nld_x_preferred":[
        "Hrib"
    ],
    "name:sco_x_preferred":[
        "Hrib"
    ],
    "name:slv_x_preferred":[
        "Hrib"
    ],
    "name:srp_x_preferred":[
        "\u0425\u0440\u0438\u0431"
    ],
    "name:und_x_variant":[
        "Skednari",
        "Hrib-Skednari"
    ],
    "wof:name":"Hrib",
    "wof:placetype":"locality",
    "wof:population":109
},
  "geometry": {"coordinates":[14.68083,45.51722],"type":"Point"}
}