{
  "type": "Feature",
  "properties": {
    "gn:admin1_code":"9.0",
    "gn:admin2_code":"11054886.0",
    "gn:asciiname":"Robadje",
    "gn:country_code":"HR",
    "gn:dem":293,
    "gn:feature_class":"P",
    "gn:feature_code":"PPL",
    "gn:name":"Robadje",
    "gn:population":0,
    "gn:timezone":"Europe/Zagreb",
    "iso:country":"HR",
    "wof:name":"Robadje",
    "wof:placetype":"locality"
},
  "geometry": {"coordinates":[16.25806,46.49556],"type":"Point"}
}