{
  "type": "Feature",
  "properties": {
    "gn:admin1_code":"05",
    "gn:admin2_code":"11049266.0",
    "gn:asciiname":"Perjasica",
    "gn:cc2":"HR",
    "gn:country_code":"HR",
    "gn:dem":211,
    "gn:feature_class":"P",
    "gn:feature_code":"PPL",
    "gn:name":"Perjasica",
    "gn:population":17,
    "gn:timezone":"Europe/Zagreb",
    "iso:country":"HR",
    "name:und_x_variant":[
        "Gornja Perjasica",
        "Perjasica Gornja",
        "Perjasica"
    ],
    "wof:name":"Perjasica",
    "wof:placetype":"locality",
    "wof:population":17
},
  "geometry": {"coordinates":[15.46722,45.29083],"type":"Point"}
}