{
  "type": "Feature",
  "properties": {
    "gn:admin1_code":"05",
    "gn:admin2_code":"11049266.0",
    "gn:asciiname":"Perjasica",
    "gn:cc2":"HR",
    "gn:country_code":"HR",
    "gn:dem":211,
    "gn:feature_class":"P",
    "gn:feature_code":"PPL",
    "gn:name":"Perjasica",
    "gn:population":17,
    "gn:timezone":"Europe/Zagreb",
    "iso:country":"HR",
    "name:bos_x_preferred":[
        "Perjasica"
    ],
    "name:cat_x_preferred":[
        "Perjasica"
    ],
    "name:hrv_x_preferred":[
        "Perjasica"
    ],
    "name:hun_x_preferred":[
        "Perjasica"
    ],
    "name:nld_x_preferred":[
        "Perjasica"
    ],
    "name:slv_x_preferred":[
        "Perjasica"
    ],
    "name:spa_x_preferred":[
        "Perjasica"
    ],
    "name:srp_x_preferred":[
        "\u041f\u0435\u0440\u0458\u0430\u0441\u0438\u0446\u0430"
    ],
    "name:ukr_x_preferred":[
        "\u041f\u0435\u0440'\u044f\u0441\u0438\u0446\u044f"
    ],
    "name:und_x_variant":[
        "Gornja Perjasica",
        "Perjasica Gornja"
    ],
    "wof:name":"Perjasica",
    "wof:placetype":"locality",
    "wof:population":17
},
  "geometry": {"coordinates":[15.46722,45.29083],"type":"Point"}
}