{
  "type": "Feature",
  "properties": {
    "gn:admin1_code":"12",
    "gn:asciiname":"Stivan",
    "gn:cc2":"HR",
    "gn:country_code":"HR",
    "gn:dem":120,
    "gn:feature_class":"P",
    "gn:feature_code":"PPL",
    "gn:name":"\u0160tivan",
    "gn:population":0,
    "gn:timezone":"Europe/Zagreb",
    "iso:country":"HR",
    "name:und_x_variant":[
        "San Giovanni",
        "San Giovanni di Cherso",
        "\u0160tivan"
    ],
    "wof:name":"Stivan",
    "wof:placetype":"locality"
},
  "geometry": {"coordinates":[14.38194,44.79083],"type":"Point"}
}