{
  "type": "Feature",
  "properties": {
    "gn:admin1_code":"5.0",
    "gn:admin2_code":"11049278.0",
    "gn:asciiname":"Brezovac",
    "gn:country_code":"HR",
    "gn:dem":353,
    "gn:feature_class":"P",
    "gn:feature_code":"PPL",
    "gn:name":"Brezovac",
    "gn:population":6,
    "gn:timezone":"Europe/Zagreb",
    "iso:country":"HR",
    "name:bos_x_preferred":[
        "Brezovac"
    ],
    "name:ceb_x_preferred":[
        "Brezovac"
    ],
    "name:fra_x_preferred":[
        "Brezovac"
    ],
    "name:hrv_x_preferred":[
        "Brezovac"
    ],
    "name:hun_x_preferred":[
        "Brezovac"
    ],
    "name:nld_x_preferred":[
        "Brezovac"
    ],
    "name:slv_x_preferred":[
        "Brezovac"
    ],
    "name:srp_x_preferred":[
        "\u0411\u0440\u0435\u0437\u043e\u0432\u0430\u0446"
    ],
    "name:swe_x_preferred":[
        "Brezovac"
    ],
    "wof:name":"Brezovac",
    "wof:placetype":"locality",
    "wof:population":6
},
  "geometry": {"coordinates":[15.65583,45.04694],"type":"Point"}
}