{
  "type": "Feature",
  "properties": {
    "gn:admin1_code":"5.0",
    "gn:admin2_code":"11049278.0",
    "gn:asciiname":"Brezovac",
    "gn:country_code":"HR",
    "gn:dem":353,
    "gn:feature_class":"P",
    "gn:feature_code":"PPL",
    "gn:name":"Brezovac",
    "gn:population":6,
    "gn:timezone":"Europe/Zagreb",
    "iso:country":"HR",
    "wof:name":"Brezovac",
    "wof:placetype":"locality",
    "wof:population":6
},
  "geometry": {"coordinates":[15.65583,45.04694],"type":"Point"}
}