{
  "type": "Feature",
  "properties": {
    "gn:admin1_code":"17.0",
    "gn:admin2_code":"11049464.0",
    "gn:asciiname":"Balinci",
    "gn:country_code":"HR",
    "gn:dem":136,
    "gn:feature_class":"P",
    "gn:feature_code":"PPL",
    "gn:name":"Balinci",
    "gn:population":70,
    "gn:timezone":"Europe/Zagreb",
    "iso:country":"HR",
    "wof:name":"Balinci",
    "wof:placetype":"locality",
    "wof:population":70
},
  "geometry": {"coordinates":[17.7475,45.61389000000001],"type":"Point"}
}