{
  "type": "Feature",
  "properties": {
    "gn:admin1_code":"15.0",
    "gn:asciiname":"Patrlji",
    "gn:country_code":"HR",
    "gn:dem":388,
    "gn:feature_class":"P",
    "gn:feature_code":"PPL",
    "gn:name":"Patrlji",
    "gn:population":0,
    "gn:timezone":"Europe/Zagreb",
    "iso:country":"HR",
    "wof:name":"Patrlji",
    "wof:placetype":"locality"
},
  "geometry": {"coordinates":[17.16861,43.39361],"type":"Point"}
}