{
  "type": "Feature",
  "properties": {
    "gn:admin1_code":"15.0",
    "gn:asciiname":"Sarici",
    "gn:country_code":"HR",
    "gn:dem":423,
    "gn:feature_class":"P",
    "gn:feature_code":"PPL",
    "gn:name":"\u0160ari\u0107i",
    "gn:population":0,
    "gn:timezone":"Europe/Zagreb",
    "iso:country":"HR",
    "wof:name":"Sarici",
    "wof:placetype":"locality"
},
  "geometry": {"coordinates":[16.78806,43.52917],"type":"Point"}
}