{
  "type": "Feature",
  "properties": {
    "gn:admin1_code":"15.0",
    "gn:asciiname":"Jarkoviste",
    "gn:country_code":"HR",
    "gn:dem":1102,
    "gn:feature_class":"P",
    "gn:feature_code":"PPL",
    "gn:name":"Jarkovi\u0161te",
    "gn:population":0,
    "gn:timezone":"Europe/Zagreb",
    "iso:country":"HR",
    "wof:name":"Jarkoviste",
    "wof:placetype":"locality"
},
  "geometry": {"coordinates":[16.89111,43.67083],"type":"Point"}
}