{
  "type": "Feature",
  "properties": {
    "gn:admin1_code":"5.0",
    "gn:asciiname":"Peurace",
    "gn:country_code":"HR",
    "gn:dem":206,
    "gn:feature_class":"P",
    "gn:feature_code":"PPL",
    "gn:name":"Peura\u010de",
    "gn:population":0,
    "gn:timezone":"Europe/Zagreb",
    "iso:country":"HR",
    "wof:name":"Peurace",
    "wof:placetype":"locality"
},
  "geometry": {"coordinates":[15.66639,45.24139],"type":"Point"}
}