{
  "type": "Feature",
  "properties": {
    "gn:admin1_code":"5.0",
    "gn:asciiname":"Bogunovici",
    "gn:country_code":"HR",
    "gn:dem":128,
    "gn:feature_class":"P",
    "gn:feature_code":"PPL",
    "gn:name":"Bogunovi\u0107i",
    "gn:population":0,
    "gn:timezone":"Europe/Zagreb",
    "iso:country":"HR",
    "wof:name":"Bogunovici",
    "wof:placetype":"locality"
},
  "geometry": {"coordinates":[15.66167,45.45444000000001],"type":"Point"}
}