{
  "type": "Feature",
  "properties": {
    "gn:admin1_code":"15.0",
    "gn:asciiname":"Roglici",
    "gn:country_code":"HR",
    "gn:dem":407,
    "gn:feature_class":"P",
    "gn:feature_code":"PPL",
    "gn:name":"Rogli\u0107i",
    "gn:population":0,
    "gn:timezone":"Europe/Zagreb",
    "iso:country":"HR",
    "wof:name":"Roglici",
    "wof:placetype":"locality"
},
  "geometry": {"coordinates":[17.13917,43.32139],"type":"Point"}
}