{
  "type": "Feature",
  "properties": {
    "gn:admin1_code":"3.0",
    "gn:admin2_code":"11054971.0",
    "gn:asciiname":"Prusci",
    "gn:country_code":"HR",
    "gn:dem":18,
    "gn:feature_class":"P",
    "gn:feature_code":"PPL",
    "gn:name":"Pru\u0161ci",
    "gn:population":0,
    "gn:timezone":"Europe/Zagreb",
    "iso:country":"HR",
    "name:bos_x_preferred":[
        "Prusci"
    ],
    "name:ceb_x_preferred":[
        "Prusci"
    ],
    "name:fra_x_preferred":[
        "Prusci"
    ],
    "name:hrv_x_preferred":[
        "Prusci"
    ],
    "name:srp_x_preferred":[
        "\u041f\u0440\u0443\u0441\u0446\u0438"
    ],
    "name:swe_x_preferred":[
        "Prusci"
    ],
    "wof:name":"Prusci",
    "wof:placetype":"locality"
},
  "geometry": {"coordinates":[17.58028,43.07472],"type":"Point"}
}