{
  "type": "Feature",
  "properties": {
    "gn:admin1_code":"15",
    "gn:admin2_code":"11054614.0",
    "gn:asciiname":"Sutina",
    "gn:country_code":"HR",
    "gn:dem":537,
    "gn:feature_class":"P",
    "gn:feature_code":"PPLL",
    "gn:name":"Sutina",
    "gn:population":0,
    "gn:timezone":"Europe/Zagreb",
    "iso:country":"HR",
    "name:bos_x_preferred":[
        "Sutina"
    ],
    "name:fra_x_preferred":[
        "Sutina"
    ],
    "name:hrv_x_preferred":[
        "Sutina"
    ],
    "name:srp_x_preferred":[
        "\u0421\u0443\u0442\u0438\u043d\u0430"
    ],
    "wof:name":"Sutina",
    "wof:placetype":"locality"
},
  "geometry": {"coordinates":[16.53374,43.69363],"type":"Point"}
}