{
  "type": "Feature",
  "properties": {
    "gn:admin1_code":"08",
    "gn:admin2_code":"11049293.0",
    "gn:asciiname":"Jurjevo",
    "gn:cc2":"HR",
    "gn:country_code":"HR",
    "gn:dem":30,
    "gn:feature_class":"P",
    "gn:feature_code":"PPL",
    "gn:name":"Jurjevo",
    "gn:population":0,
    "gn:timezone":"Europe/Zagreb",
    "iso:country":"HR",
    "name:bos_x_preferred":[
        "Sveti Juraj"
    ],
    "name:ceb_x_preferred":[
        "Jurjevo"
    ],
    "name:ces_x_preferred":[
        "Sveti Juraj"
    ],
    "name:deu_x_preferred":[
        "Sveti Juraj"
    ],
    "name:hrv_x_preferred":[
        "Sveti Juraj"
    ],
    "name:hun_x_preferred":[
        "Szentgy\u00f6rgy"
    ],
    "name:nld_x_preferred":[
        "Sveti Juraj"
    ],
    "name:slv_x_preferred":[
        "Sveti Juraj"
    ],
    "name:spa_x_preferred":[
        "Sveti Juraj"
    ],
    "name:srp_x_preferred":[
        "\u0421\u0432\u0435\u0442\u0438 \u0408\u0443\u0440\u0430\u0458"
    ],
    "name:swe_x_preferred":[
        "Jurjevo"
    ],
    "name:ukr_x_preferred":[
        "\u0421\u0432\u0435\u0442\u0438\u0439 \u042e\u0440\u0430\u0439"
    ],
    "name:und_x_variant":[
        "Szentgy\u00f6rgy",
        "San Giorgio",
        "Sveti Juraj",
        "Jurjevo"
    ],
    "wof:name":"Jurjevo",
    "wof:placetype":"locality"
},
  "geometry": {"coordinates":[14.92194,44.92833],"type":"Point"}
}