{
  "type": "Feature",
  "properties": {
    "gn:admin1_code":"08",
    "gn:admin2_code":"11049292.0",
    "gn:asciiname":"Novo Selo",
    "gn:cc2":"HR",
    "gn:country_code":"HR",
    "gn:dem":650,
    "gn:feature_class":"P",
    "gn:feature_code":"PPL",
    "gn:name":"Novo Selo",
    "gn:population":0,
    "gn:timezone":"Europe/Zagreb",
    "iso:country":"HR",
    "name:und_x_variant":[
        "Koreni\u010dko Novo Selo",
        "Novo Selo Koreni\u010dko",
        "Novo Selo"
    ],
    "wof:name":"Novo Selo",
    "wof:placetype":"locality"
},
  "geometry": {"coordinates":[15.71722,44.73861],"type":"Point"}
}