{
  "type": "Feature",
  "properties": {
    "gn:admin1_code":"15.0",
    "gn:asciiname":"Greda",
    "gn:country_code":"HR",
    "gn:dem":397,
    "gn:feature_class":"P",
    "gn:feature_code":"PPL",
    "gn:name":"Greda",
    "gn:population":1015,
    "gn:timezone":"Europe/Zagreb",
    "iso:country":"HR",
    "wof:name":"Greda",
    "wof:placetype":"locality",
    "wof:population":1015
},
  "geometry": {"coordinates":[16.69361,43.61528],"type":"Point"}
}