{
  "type": "Feature",
  "properties": {
    "gn:admin1_code":"21.0",
    "gn:asciiname":"Hobolici",
    "gn:country_code":"HR",
    "gn:dem":184,
    "gn:feature_class":"P",
    "gn:feature_code":"PPL",
    "gn:name":"Hoboli\u0107i",
    "gn:population":0,
    "gn:timezone":"Europe/Zagreb",
    "iso:country":"HR",
    "wof:name":"Hobolici",
    "wof:placetype":"locality"
},
  "geometry": {"coordinates":[15.87194,45.66306],"type":"Point"}
}