{
  "type": "Feature",
  "properties": {
    "gn:admin1_code":"15.0",
    "gn:asciiname":"Vujicici",
    "gn:country_code":"HR",
    "gn:dem":339,
    "gn:feature_class":"P",
    "gn:feature_code":"PPL",
    "gn:name":"Vuji\u010di\u0107i",
    "gn:population":0,
    "gn:timezone":"Europe/Zagreb",
    "iso:country":"HR",
    "wof:name":"Vujicici",
    "wof:placetype":"locality"
},
  "geometry": {"coordinates":[17.40583,43.22722],"type":"Point"}
}