{
  "type": "Feature",
  "properties": {
    "gn:admin1_code":"18.0",
    "gn:asciiname":"Staro Selo",
    "gn:country_code":"HR",
    "gn:dem":81,
    "gn:feature_class":"P",
    "gn:feature_code":"PPLL",
    "gn:name":"Staro Selo",
    "gn:population":0,
    "gn:timezone":"Europe/Zagreb",
    "iso:country":"HR",
    "wof:name":"Staro Selo",
    "wof:placetype":"locality"
},
  "geometry": {"coordinates":[18.63806,45.06417],"type":"Point"}
}