{
  "type": "Feature",
  "properties": {
    "gn:admin1_code":"14.0",
    "gn:asciiname":"Sukunde",
    "gn:country_code":"HR",
    "gn:dem":311,
    "gn:feature_class":"P",
    "gn:feature_code":"PPL",
    "gn:name":"\u0160ukunde",
    "gn:population":0,
    "gn:timezone":"Europe/Zagreb",
    "iso:country":"HR",
    "wof:name":"Sukunde",
    "wof:placetype":"locality"
},
  "geometry": {"coordinates":[16.21972,45.23917],"type":"Point"}
}