{
  "type": "Feature",
  "properties": {
    "gn:admin1_code":"03",
    "gn:admin2_code":"7577034.0",
    "gn:asciiname":"Sumet",
    "gn:country_code":"HR",
    "gn:dem":147,
    "gn:feature_class":"P",
    "gn:feature_code":"PPL",
    "gn:name":"\u0160umet",
    "gn:population":176,
    "gn:timezone":"Europe/Zagreb",
    "iso:country":"HR",
    "wof:name":"Sumet",
    "wof:placetype":"locality",
    "wof:population":176
},
  "geometry": {"coordinates":[18.1475,42.64611],"type":"Point"}
}