{
  "type": "Feature",
  "properties": {
    "gn:admin1_code":"10",
    "gn:admin2_code":"11054464.0",
    "gn:asciiname":"Divos",
    "gn:country_code":"HR",
    "gn:dem":83,
    "gn:feature_class":"P",
    "gn:feature_code":"PPL",
    "gn:name":"Divo\u0161",
    "gn:population":63,
    "gn:timezone":"Europe/Zagreb",
    "iso:country":"HR",
    "name:und_x_variant":[
        "Divo\u0161"
    ],
    "wof:name":"Divos",
    "wof:placetype":"locality",
    "wof:population":63
},
  "geometry": {"coordinates":[18.65639,45.46333],"type":"Point"}
}