{
  "type": "Feature",
  "properties": {
    "gn:admin1_code":"5.0",
    "gn:admin2_code":"11049268.0",
    "gn:asciiname":"Durin Potok",
    "gn:country_code":"HR",
    "gn:dem":211,
    "gn:feature_class":"P",
    "gn:feature_code":"PPLL",
    "gn:name":"\u00d0urin Potok",
    "gn:population":0,
    "gn:timezone":"Europe/Zagreb",
    "iso:country":"HR",
    "wof:name":"Durin Potok",
    "wof:placetype":"locality"
},
  "geometry": {"coordinates":[15.785,45.11417],"type":"Point"}
}