{
  "type": "Feature",
  "properties": {
    "gn:admin1_code":"5.0",
    "gn:asciiname":"Brodani",
    "gn:country_code":"HR",
    "gn:dem":108,
    "gn:feature_class":"P",
    "gn:feature_code":"PPL",
    "gn:name":"Brodani",
    "gn:population":0,
    "gn:timezone":"Europe/Zagreb",
    "iso:country":"HR",
    "wof:name":"Brodani",
    "wof:placetype":"locality"
},
  "geometry": {"coordinates":[15.66306,45.47639],"type":"Point"}
}