{
  "type": "Feature",
  "properties": {
    "gn:admin1_code":"15.0",
    "gn:asciiname":"Akrap",
    "gn:country_code":"HR",
    "gn:dem":879,
    "gn:feature_class":"P",
    "gn:feature_code":"PPL",
    "gn:name":"Akrap",
    "gn:population":0,
    "gn:timezone":"Europe/Zagreb",
    "iso:country":"HR",
    "wof:name":"Akrap",
    "wof:placetype":"locality"
},
  "geometry": {"coordinates":[16.89944,43.65528],"type":"Point"}
}