{
  "type": "Feature",
  "properties": {
    "gn:admin1_code":"13",
    "gn:admin2_code":"11055025.0",
    "gn:asciiname":"Citluk",
    "gn:country_code":"HR",
    "gn:dem":255,
    "gn:feature_class":"P",
    "gn:feature_code":"PPL",
    "gn:name":"\u010citluk",
    "gn:population":112,
    "gn:timezone":"Europe/Zagreb",
    "iso:country":"HR",
    "wof:name":"Citluk",
    "wof:placetype":"locality",
    "wof:population":112
},
  "geometry": {"coordinates":[16.07611,43.96278],"type":"Point"}
}