{
  "type": "Feature",
  "properties": {
    "gn:admin1_code":"14",
    "gn:admin2_code":"11049235.0",
    "gn:asciiname":"Vidrenjak",
    "gn:cc2":"HR",
    "gn:country_code":"HR",
    "gn:dem":109,
    "gn:feature_class":"P",
    "gn:feature_code":"PPL",
    "gn:name":"Vidrenjak",
    "gn:population":552,
    "gn:timezone":"Europe/Zagreb",
    "iso:country":"HR",
    "name:und_x_variant":[
        "Vidrnjak",
        "Vidrenjak"
    ],
    "wof:name":"Vidrenjak",
    "wof:placetype":"locality",
    "wof:population":552
},
  "geometry": {"coordinates":[16.57444,45.61083],"type":"Point"}
}