{
  "type": "Feature",
  "properties": {
    "gn:admin1_code":"12",
    "gn:admin2_code":"3202931.0",
    "gn:asciiname":"Gerovski Kraj",
    "gn:cc2":"HR",
    "gn:country_code":"HR",
    "gn:dem":658,
    "gn:feature_class":"P",
    "gn:feature_code":"PPL",
    "gn:name":"Gerovski Kraj",
    "gn:population":95,
    "gn:timezone":"Europe/Zagreb",
    "iso:country":"HR",
    "name:bos_x_preferred":[
        "Gerovski Kraj"
    ],
    "name:fra_x_preferred":[
        "Gerovski Kraj"
    ],
    "name:hrv_x_preferred":[
        "Gerovski Kraj"
    ],
    "name:hun_x_preferred":[
        "Gerovski Kraj"
    ],
    "name:slv_x_preferred":[
        "Gerovski Kraj"
    ],
    "name:spa_x_preferred":[
        "Gerovski Kraj"
    ],
    "name:ukr_x_preferred":[
        "\u0413\u0435\u0440\u043e\u0432\u0435\u0446\u044c\u043a\u0438\u0439 \u041a\u0440\u0430\u0439"
    ],
    "name:und_x_variant":[
        "Kraj",
        "Gerovski Kraj"
    ],
    "wof:name":"Gerovski Kraj",
    "wof:placetype":"locality",
    "wof:population":95
},
  "geometry": {"coordinates":[14.64194,45.50028],"type":"Point"}
}