{
  "type": "Feature",
  "properties": {
    "gn:admin1_code":"16",
    "gn:admin2_code":"11049316.0",
    "gn:asciiname":"Donja Poljana",
    "gn:country_code":"HR",
    "gn:dem":206,
    "gn:feature_class":"P",
    "gn:feature_code":"PPL",
    "gn:name":"Donja Poljana",
    "gn:population":426,
    "gn:timezone":"Europe/Zagreb",
    "iso:country":"HR",
    "wof:name":"Donja Poljana",
    "wof:placetype":"locality",
    "wof:population":426
},
  "geometry": {"coordinates":[16.50194,46.22056],"type":"Point"}
}