{
  "type": "Feature",
  "properties": {
    "gn:admin1_code":"15.0",
    "gn:asciiname":"Kursani",
    "gn:country_code":"HR",
    "gn:dem":418,
    "gn:feature_class":"P",
    "gn:feature_code":"PPL",
    "gn:name":"Kursani",
    "gn:population":0,
    "gn:timezone":"Europe/Zagreb",
    "iso:country":"HR",
    "wof:name":"Kursani",
    "wof:placetype":"locality"
},
  "geometry": {"coordinates":[16.57139,43.57194000000001],"type":"Point"}
}