{
  "type": "Feature",
  "properties": {
    "gn:admin1_code":"19.0",
    "gn:asciiname":"Poznic",
    "gn:cc2":"HR",
    "gn:country_code":"HR",
    "gn:dem":801,
    "gn:feature_class":"P",
    "gn:feature_code":"PPL",
    "gn:name":"Pozni\u0107",
    "gn:population":0,
    "gn:timezone":"Europe/Zagreb",
    "iso:country":"HR",
    "name:und_x_variant":[
        "Pozni\u0107i",
        "Pozni\u0107"
    ],
    "wof:name":"Poznic",
    "wof:placetype":"locality"
},
  "geometry": {"coordinates":[15.95556,44.36361],"type":"Point"}
}