{
  "type": "Feature",
  "properties": {
    "gn:admin1_code":"19.0",
    "gn:asciiname":"Trtica",
    "gn:cc2":"HR",
    "gn:country_code":"HR",
    "gn:dem":714,
    "gn:feature_class":"P",
    "gn:feature_code":"PPL",
    "gn:name":"Trtica",
    "gn:population":0,
    "gn:timezone":"Europe/Zagreb",
    "iso:country":"HR",
    "name:und_x_variant":[
        "Trti\u0107i",
        "Trtica"
    ],
    "wof:name":"Trtica",
    "wof:placetype":"locality"
},
  "geometry": {"coordinates":[15.90139,44.35889],"type":"Point"}
}