{
  "type": "Feature",
  "properties": {
    "gn:admin1_code":"20",
    "gn:admin2_code":"11048985.0",
    "gn:asciiname":"Fuka",
    "gn:country_code":"HR",
    "gn:dem":160,
    "gn:feature_class":"P",
    "gn:feature_code":"PPL",
    "gn:name":"Fuka",
    "gn:population":99,
    "gn:timezone":"Europe/Zagreb",
    "iso:country":"HR",
    "name:ceb_x_preferred":[
        "Fuka"
    ],
    "name:ces_x_preferred":[
        "Fuka"
    ],
    "name:deu_x_preferred":[
        "Fuka"
    ],
    "name:swe_x_preferred":[
        "Fuka"
    ],
    "wof:name":"Fuka",
    "wof:placetype":"locality",
    "wof:population":99
},
  "geometry": {"coordinates":[16.53333,45.88333],"type":"Point"}
}