{
  "type": "Feature",
  "properties": {
    "gn:admin1_code":"19.0",
    "gn:asciiname":"Podvornice",
    "gn:country_code":"HR",
    "gn:dem":240,
    "gn:feature_class":"P",
    "gn:feature_code":"PPL",
    "gn:name":"Podvornice",
    "gn:population":0,
    "gn:timezone":"Europe/Zagreb",
    "iso:country":"HR",
    "wof:name":"Podvornice",
    "wof:placetype":"locality"
},
  "geometry": {"coordinates":[15.64306,44.02583],"type":"Point"}
}