{
  "type": "Feature",
  "properties": {
    "gn:admin1_code":"14.0",
    "gn:asciiname":"Komanda",
    "gn:country_code":"HR",
    "gn:dem":277,
    "gn:feature_class":"P",
    "gn:feature_code":"PPL",
    "gn:name":"Komanda",
    "gn:population":0,
    "gn:timezone":"Europe/Zagreb",
    "iso:country":"HR",
    "wof:name":"Komanda",
    "wof:placetype":"locality"
},
  "geometry": {"coordinates":[16.02222,45.21694],"type":"Point"}
}