{
  "type": "Feature",
  "properties": {
    "gn:admin1_code":"20.0",
    "gn:admin2_code":"3188243.0",
    "gn:asciiname":"Lazina Cicka",
    "gn:country_code":"HR",
    "gn:dem":99,
    "gn:feature_class":"P",
    "gn:feature_code":"PPL",
    "gn:name":"Lazina \u010ci\u010dka",
    "gn:population":566,
    "gn:timezone":"Europe/Zagreb",
    "iso:country":"HR",
    "name:bos_x_preferred":[
        "Lazina \u010ci\u010dka"
    ],
    "name:ceb_x_preferred":[
        "Lazina \u010ci\u010dka"
    ],
    "name:hrv_x_preferred":[
        "Lazina \u010ci\u010dka"
    ],
    "name:hun_x_preferred":[
        "Lazina \u010ci\u010dka"
    ],
    "name:nld_x_preferred":[
        "Lazina \u010ci\u010dka"
    ],
    "name:slv_x_preferred":[
        "Lazina \u010ci\u010dka"
    ],
    "name:srp_x_preferred":[
        "\u041b\u0430\u0437\u0438\u043d\u0430 \u0427\u0438\u0447\u043a\u0430"
    ],
    "name:swe_x_preferred":[
        "Lazina \u010ci\u010dka"
    ],
    "name:ukr_x_preferred":[
        "\u041b\u0430\u0437\u0438\u043d\u0430-\u0427\u0438\u0447\u043a\u0430"
    ],
    "wof:name":"Lazina Cicka",
    "wof:placetype":"locality",
    "wof:population":566
},
  "geometry": {"coordinates":[16.12544,45.72626],"type":"Point"}
}