{
  "type": "Feature",
  "properties": {
    "gn:admin1_code":"05",
    "gn:asciiname":"Trbovici",
    "gn:country_code":"HR",
    "gn:dem":510,
    "gn:feature_class":"P",
    "gn:feature_code":"PPL",
    "gn:name":"Trbovi\u0107i",
    "gn:population":0,
    "gn:timezone":"Europe/Zagreb",
    "iso:country":"HR",
    "name:und_x_variant":[
        "Dre\u017enica Srednja",
        "Srednja Dre\u017enica",
        "Trbovi\u0107i"
    ],
    "wof:name":"Trbovici",
    "wof:placetype":"locality"
},
  "geometry": {"coordinates":[15.08333,45.15],"type":"Point"}
}