{
  "type": "Feature",
  "properties": {
    "gn:admin1_code":"8.0",
    "gn:asciiname":"Cankovi Stan",
    "gn:country_code":"HR",
    "gn:dem":863,
    "gn:feature_class":"P",
    "gn:feature_code":"PPL",
    "gn:name":"Cankovi Stan",
    "gn:population":0,
    "gn:timezone":"Europe/Zagreb",
    "iso:country":"HR",
    "wof:name":"Cankovi Stan",
    "wof:placetype":"locality"
},
  "geometry": {"coordinates":[15.54611,44.61333],"type":"Point"}
}