{
  "type": "Feature",
  "properties": {
    "gn:admin1_code":"07",
    "gn:asciiname":"Donja Bedekovcina",
    "gn:cc2":"HR",
    "gn:country_code":"HR",
    "gn:dem":210,
    "gn:feature_class":"P",
    "gn:feature_code":"PPL",
    "gn:name":"Donja Bedekov\u010dina",
    "gn:population":0,
    "gn:timezone":"Europe/Zagreb",
    "iso:country":"HR",
    "name:und_x_variant":[
        "Bedekov\u010dina Donja",
        "Donja Bedekov\u010dina"
    ],
    "wof:name":"Donja Bedekovcina",
    "wof:placetype":"locality"
},
  "geometry": {"coordinates":[15.96389,46.04444],"type":"Point"}
}