{
  "type": "Feature",
  "properties": {
    "gn:admin1_code":"1.0",
    "gn:admin2_code":"11049414.0",
    "gn:asciiname":"Suplja Lipa",
    "gn:country_code":"HR",
    "gn:dem":154,
    "gn:feature_class":"P",
    "gn:feature_code":"PPL",
    "gn:name":"\u0160uplja Lipa",
    "gn:population":186,
    "gn:timezone":"Europe/Zagreb",
    "iso:country":"HR",
    "wof:name":"Suplja Lipa",
    "wof:placetype":"locality",
    "wof:population":186
},
  "geometry": {"coordinates":[17.22528,45.64722],"type":"Point"}
}