{
  "type": "Feature",
  "properties": {
    "gn:admin1_code":"10.0",
    "gn:asciiname":"Gusce Cepinsko",
    "gn:cc2":"HR",
    "gn:country_code":"HR",
    "gn:dem":90,
    "gn:feature_class":"P",
    "gn:feature_code":"PPL",
    "gn:name":"Gu\u0161\u0107e \u010cepinsko",
    "gn:population":0,
    "gn:timezone":"Europe/Zagreb",
    "iso:country":"HR",
    "name:und_x_variant":[
        "Gu\u0161\u0107e",
        "Gu\u0161\u0107e \u010cepinsko"
    ],
    "wof:name":"Gusce Cepinsko",
    "wof:placetype":"locality"
},
  "geometry": {"coordinates":[18.58472,45.52861],"type":"Point"}
}