{
  "type": "Feature",
  "properties": {
    "gn:admin1_code":"20",
    "gn:asciiname":"Pleso",
    "gn:country_code":"HR",
    "gn:dem":108,
    "gn:feature_class":"P",
    "gn:feature_code":"PPL",
    "gn:name":"Pleso",
    "gn:population":0,
    "gn:timezone":"Europe/Zagreb",
    "iso:country":"HR",
    "wof:name":"Pleso",
    "wof:placetype":"locality"
},
  "geometry": {"coordinates":[16.08333,45.73333],"type":"Point"}
}