{
  "type": "Feature",
  "properties": {
    "gn:admin1_code":"5.0",
    "gn:asciiname":"Devici",
    "gn:country_code":"HR",
    "gn:dem":267,
    "gn:feature_class":"P",
    "gn:feature_code":"PPL",
    "gn:name":"Devi\u0107i",
    "gn:population":0,
    "gn:timezone":"Europe/Zagreb",
    "iso:country":"HR",
    "wof:name":"Devici",
    "wof:placetype":"locality"
},
  "geometry": {"coordinates":[15.60472,45.24639000000001],"type":"Point"}
}