{
  "type": "Feature",
  "properties": {
    "gn:admin1_code":"13",
    "gn:admin2_code":"11054516.0",
    "gn:asciiname":"Polaca",
    "gn:country_code":"HR",
    "gn:dem":483,
    "gn:feature_class":"P",
    "gn:feature_code":"PPLL",
    "gn:name":"Pola\u010da",
    "gn:population":0,
    "gn:timezone":"Europe/Zagreb",
    "iso:country":"HR",
    "name:bos_x_preferred":[
        "Pola\u010da"
    ],
    "name:deu_x_preferred":[
        "Polaca"
    ],
    "name:fra_x_preferred":[
        "Pola\u010da"
    ],
    "name:hrv_x_preferred":[
        "Pola\u010da"
    ],
    "name:hun_x_preferred":[
        "Pola\u010da"
    ],
    "name:por_x_preferred":[
        "Polaca"
    ],
    "name:slv_x_preferred":[
        "Pola\u010da"
    ],
    "name:srp_x_preferred":[
        "\u041f\u043e\u043b\u0430\u0447\u0430"
    ],
    "wof:name":"Polaca",
    "wof:placetype":"locality"
},
  "geometry": {"coordinates":[16.31611,44.02111],"type":"Point"}
}