{
  "type": "Feature",
  "properties": {
    "gn:admin1_code":"13",
    "gn:admin2_code":"11054516.0",
    "gn:asciiname":"Polaca",
    "gn:country_code":"HR",
    "gn:dem":483,
    "gn:feature_class":"P",
    "gn:feature_code":"PPLL",
    "gn:name":"Pola\u010da",
    "gn:population":0,
    "gn:timezone":"Europe/Zagreb",
    "iso:country":"HR",
    "wof:name":"Polaca",
    "wof:placetype":"locality"
},
  "geometry": {"coordinates":[16.31611,44.02111],"type":"Point"}
}