{
  "type": "Feature",
  "properties": {
    "gn:admin1_code":"5.0",
    "gn:asciiname":"Bojanici",
    "gn:country_code":"HR",
    "gn:dem":258,
    "gn:feature_class":"P",
    "gn:feature_code":"PPL",
    "gn:name":"Bojanici",
    "gn:population":0,
    "gn:timezone":"Europe/Zagreb",
    "iso:country":"HR",
    "wof:name":"Bojanici",
    "wof:placetype":"locality"
},
  "geometry": {"coordinates":[15.50167,45.21361],"type":"Point"}
}