{
  "type": "Feature",
  "properties": {
    "gn:admin1_code":"15.0",
    "gn:asciiname":"Musinac",
    "gn:country_code":"HR",
    "gn:dem":684,
    "gn:feature_class":"P",
    "gn:feature_code":"PPL",
    "gn:name":"Musinac",
    "gn:population":0,
    "gn:timezone":"Europe/Zagreb",
    "iso:country":"HR",
    "wof:name":"Musinac",
    "wof:placetype":"locality"
},
  "geometry": {"coordinates":[17.02,43.53194000000001],"type":"Point"}
}