{
  "type": "Feature",
  "properties": {
    "gn:admin1_code":"15.0",
    "gn:asciiname":"Miocevici",
    "gn:country_code":"HR",
    "gn:dem":545,
    "gn:feature_class":"P",
    "gn:feature_code":"PPL",
    "gn:name":"Mio\u010devi\u0107i",
    "gn:population":0,
    "gn:timezone":"Europe/Zagreb",
    "iso:country":"HR",
    "wof:name":"Miocevici",
    "wof:placetype":"locality"
},
  "geometry": {"coordinates":[17.1575,43.23528],"type":"Point"}
}