{
  "type": "Feature",
  "properties": {
    "gn:admin1_code":"05",
    "gn:admin2_code":"3194182.0",
    "gn:asciiname":"Hreljin Ogulinski",
    "gn:cc2":"HR",
    "gn:country_code":"HR",
    "gn:dem":378,
    "gn:feature_class":"P",
    "gn:feature_code":"PPL",
    "gn:name":"Hreljin Ogulinski",
    "gn:population":549,
    "gn:timezone":"Europe/Zagreb",
    "iso:country":"HR",
    "name:und_x_variant":[
        "Ogulinski Hreljin",
        "Hreljin",
        "Hreljin Ogulinski"
    ],
    "wof:name":"Hreljin Ogulinski",
    "wof:placetype":"locality",
    "wof:population":549
},
  "geometry": {"coordinates":[15.18139,45.29667],"type":"Point"}
}