{
  "type": "Feature",
  "properties": {
    "gn:admin1_code":"05",
    "gn:admin2_code":"3194182.0",
    "gn:asciiname":"Hreljin Ogulinski",
    "gn:cc2":"HR",
    "gn:country_code":"HR",
    "gn:dem":378,
    "gn:feature_class":"P",
    "gn:feature_code":"PPL",
    "gn:name":"Hreljin Ogulinski",
    "gn:population":549,
    "gn:timezone":"Europe/Zagreb",
    "iso:country":"HR",
    "name:bos_x_preferred":[
        "Hreljin Ogulinski"
    ],
    "name:hrv_x_preferred":[
        "Hreljin Ogulinski"
    ],
    "name:hun_x_preferred":[
        "Hreljin Ogulinski"
    ],
    "name:nld_x_preferred":[
        "Hreljin Ogulinski"
    ],
    "name:slv_x_preferred":[
        "Hreljin Ogulinski"
    ],
    "name:spa_x_preferred":[
        "Hreljin Ogulinski"
    ],
    "name:srp_x_preferred":[
        "\u0425\u0440\u0435\u0459\u0438\u043d \u041e\u0433\u0443\u043b\u0438\u043d\u0441\u043a\u0438"
    ],
    "name:ukr_x_preferred":[
        "\u0425\u0440\u0435\u043b\u0456\u043d-\u041e\u0433\u0443\u043b\u0438\u043d\u0441\u044c\u043a\u0438\u0439"
    ],
    "name:und_x_variant":[
        "Ogulinski Hreljin",
        "Hreljin",
        "Hreljin Ogulinski"
    ],
    "wof:name":"Hreljin Ogulinski",
    "wof:placetype":"locality",
    "wof:population":549
},
  "geometry": {"coordinates":[15.18139,45.29667],"type":"Point"}
}