{
  "type": "Feature",
  "properties": {
    "gn:admin1_code":"12",
    "gn:admin2_code":"3202102.0",
    "gn:asciiname":"Marija Trost",
    "gn:country_code":"HR",
    "gn:dem":515,
    "gn:feature_class":"P",
    "gn:feature_code":"PPL",
    "gn:name":"Marija Tro\u0161t",
    "gn:population":46,
    "gn:timezone":"Europe/Zagreb",
    "iso:country":"HR",
    "name:und_x_variant":[
        "Marija Tro\u0161t"
    ],
    "wof:name":"Marija Trost",
    "wof:placetype":"locality",
    "wof:population":46
},
  "geometry": {"coordinates":[14.81889,45.41778],"type":"Point"}
}