{
  "type": "Feature",
  "properties": {
    "gn:admin1_code":"5.0",
    "gn:asciiname":"Skipine",
    "gn:cc2":"HR",
    "gn:country_code":"HR",
    "gn:dem":506,
    "gn:feature_class":"P",
    "gn:feature_code":"PPL",
    "gn:name":"\u0160kipine",
    "gn:population":0,
    "gn:timezone":"Europe/Zagreb",
    "iso:country":"HR",
    "name:und_x_variant":[
        "Tatalovi\u0107i",
        "\u0160kipine"
    ],
    "wof:name":"Skipine",
    "wof:placetype":"locality"
},
  "geometry": {"coordinates":[15.10444,45.13722],"type":"Point"}
}