{
  "type": "Feature",
  "properties": {
    "gn:admin1_code":"8.0",
    "gn:admin2_code":"11049284.0",
    "gn:asciiname":"Vranici",
    "gn:country_code":"HR",
    "gn:dem":460,
    "gn:feature_class":"P",
    "gn:feature_code":"PPL",
    "gn:name":"Vrani\u0107i",
    "gn:population":0,
    "gn:timezone":"Europe/Zagreb",
    "iso:country":"HR",
    "wof:name":"Vranici",
    "wof:placetype":"locality"
},
  "geometry": {"coordinates":[15.10917,44.99389],"type":"Point"}
}