{
  "type": "Feature",
  "properties": {
    "gn:admin1_code":"1.0",
    "gn:admin2_code":"3202819.0",
    "gn:asciiname":"Bojana",
    "gn:country_code":"HR",
    "gn:dem":151,
    "gn:feature_class":"P",
    "gn:feature_code":"PPL",
    "gn:name":"Bojana",
    "gn:population":158,
    "gn:timezone":"Europe/Zagreb",
    "iso:country":"HR",
    "name:ara_x_preferred":[
        "\u0628\u0648\u062c\u0627\u0646\u0627"
    ],
    "name:ben_x_preferred":[
        "\u09ac\u09cb\u099c\u09be\u09a8\u09be"
    ],
    "name:bos_x_preferred":[
        "Bojana"
    ],
    "name:ceb_x_preferred":[
        "Bojana"
    ],
    "name:ces_x_preferred":[
        "Bojana"
    ],
    "name:deu_x_preferred":[
        "Bojana"
    ],
    "name:fra_x_preferred":[
        "Bojana"
    ],
    "name:hin_x_preferred":[
        "\u092c\u094b\u091c\u093e\u0928\u093e"
    ],
    "name:hun_x_preferred":[
        "Bojana"
    ],
    "name:ind_x_preferred":[
        "Bojana"
    ],
    "name:jpn_x_preferred":[
        "\u30dc\u30b8\u30e3\u30ca\u5ddd"
    ],
    "name:kor_x_preferred":[
        "\ubcf4\uc790\ub098"
    ],
    "name:nld_x_preferred":[
        "Bojana"
    ],
    "name:pol_x_preferred":[
        "Bojana"
    ],
    "name:por_x_preferred":[
        "Bojana"
    ],
    "name:slv_x_preferred":[
        "Bojana"
    ],
    "name:srp_x_preferred":[
        "\u0411\u043e\u0458\u0430\u043d\u0430"
    ],
    "name:swe_x_preferred":[
        "Bojana"
    ],
    "name:urd_x_preferred":[
        "\u0628\u0648\u062c\u0627\u0646\u0627"
    ],
    "name:vie_x_preferred":[
        "S\u00f4ng Bojana"
    ],
    "wof:name":"Bojana",
    "wof:placetype":"locality",
    "wof:population":158
},
  "geometry": {"coordinates":[16.68162,45.75674],"type":"Point"}
}