{
  "type": "Feature",
  "properties": {
    "gn:admin1_code":"1.0",
    "gn:admin2_code":"3202819.0",
    "gn:asciiname":"Bojana",
    "gn:country_code":"HR",
    "gn:dem":151,
    "gn:feature_class":"P",
    "gn:feature_code":"PPL",
    "gn:name":"Bojana",
    "gn:population":158,
    "gn:timezone":"Europe/Zagreb",
    "iso:country":"HR",
    "wof:name":"Bojana",
    "wof:placetype":"locality",
    "wof:population":158
},
  "geometry": {"coordinates":[16.68162,45.75674],"type":"Point"}
}