{
  "type": "Feature",
  "properties": {
    "gn:asciiname":"Kanica",
    "gn:country_code":"HR",
    "gn:dem":17,
    "gn:feature_class":"P",
    "gn:feature_code":"PPL",
    "gn:name":"Kanica",
    "gn:population":129,
    "gn:timezone":"Europe/Zagreb",
    "iso:country":"HR",
    "wof:name":"Kanica",
    "wof:placetype":"locality",
    "wof:population":129
},
  "geometry": {"coordinates":[16.00103,43.49745],"type":"Point"}
}