{
  "type": "Feature",
  "properties": {
    "gn:admin1_code":"19",
    "gn:asciiname":"Gornji Srb",
    "gn:country_code":"HR",
    "gn:dem":463,
    "gn:feature_class":"P",
    "gn:feature_code":"PPL",
    "gn:name":"Gornji Srb",
    "gn:population":0,
    "gn:timezone":"Europe/Zagreb",
    "iso:country":"HR",
    "wof:name":"Gornji Srb",
    "wof:placetype":"locality"
},
  "geometry": {"coordinates":[16.11639,44.35167],"type":"Point"}
}