{
  "type": "Feature",
  "properties": {
    "gn:admin1_code":"14.0",
    "gn:asciiname":"Gnjatovici",
    "gn:country_code":"HR",
    "gn:dem":283,
    "gn:feature_class":"P",
    "gn:feature_code":"PPL",
    "gn:name":"Gnjatovi\u0107i",
    "gn:population":0,
    "gn:timezone":"Europe/Zagreb",
    "iso:country":"HR",
    "wof:name":"Gnjatovici",
    "wof:placetype":"locality"
},
  "geometry": {"coordinates":[16.10389,45.23639],"type":"Point"}
}