{
  "type": "Feature",
  "properties": {
    "gn:admin1_code":"8.0",
    "gn:asciiname":"Skorici",
    "gn:country_code":"HR",
    "gn:dem":419,
    "gn:feature_class":"P",
    "gn:feature_code":"PPL",
    "gn:name":"\u0160kori\u0107i",
    "gn:population":0,
    "gn:timezone":"Europe/Zagreb",
    "iso:country":"HR",
    "wof:name":"Skorici",
    "wof:placetype":"locality"
},
  "geometry": {"coordinates":[15.11056,44.90028],"type":"Point"}
}