{
  "type": "Feature",
  "properties": {
    "gn:admin1_code":"15.0",
    "gn:asciiname":"Vulete",
    "gn:country_code":"HR",
    "gn:dem":352,
    "gn:feature_class":"P",
    "gn:feature_code":"PPL",
    "gn:name":"Vulete",
    "gn:population":0,
    "gn:timezone":"Europe/Zagreb",
    "iso:country":"HR",
    "wof:name":"Vulete",
    "wof:placetype":"locality"
},
  "geometry": {"coordinates":[17.22917,43.23306],"type":"Point"}
}