{
  "type": "Feature",
  "properties": {
    "gn:admin1_code":"3.0",
    "gn:admin2_code":"3193146.0",
    "gn:asciiname":"Peracko Blato",
    "gn:country_code":"HR",
    "gn:dem":10,
    "gn:feature_class":"P",
    "gn:feature_code":"PPL",
    "gn:name":"Pera\u010dko Blato",
    "gn:population":288,
    "gn:timezone":"Europe/Zagreb",
    "iso:country":"HR",
    "wof:name":"Peracko Blato",
    "wof:placetype":"locality",
    "wof:population":288
},
  "geometry": {"coordinates":[17.43944,43.07667],"type":"Point"}
}