{
  "type": "Feature",
  "properties": {
    "gn:admin1_code":"14",
    "gn:admin2_code":"3190812.0",
    "gn:asciiname":"Sela",
    "gn:country_code":"HR",
    "gn:dem":101,
    "gn:feature_class":"P",
    "gn:feature_code":"PPL",
    "gn:name":"Sela",
    "gn:population":963,
    "gn:timezone":"Europe/Zagreb",
    "iso:country":"HR",
    "wof:name":"Sela",
    "wof:placetype":"locality",
    "wof:population":963
},
  "geometry": {"coordinates":[16.30474,45.50833],"type":"Point"}
}