{
  "type": "Feature",
  "properties": {
    "gn:admin1_code":"14",
    "gn:admin2_code":"3200597.0",
    "gn:asciiname":"Donje Seliste",
    "gn:country_code":"HR",
    "gn:dem":111,
    "gn:feature_class":"P",
    "gn:feature_code":"PPL",
    "gn:name":"Donje Seli\u0161te",
    "gn:population":109,
    "gn:timezone":"Europe/Zagreb",
    "iso:country":"HR",
    "wof:name":"Donje Seliste",
    "wof:placetype":"locality",
    "wof:population":109
},
  "geometry": {"coordinates":[16.06667,45.33333],"type":"Point"}
}