{
  "type": "Feature",
  "properties": {
    "gn:admin1_code":"06",
    "gn:admin2_code":"11049397.0",
    "gn:asciiname":"Donje Zdelice",
    "gn:country_code":"HR",
    "gn:dem":184,
    "gn:feature_class":"P",
    "gn:feature_code":"PPL",
    "gn:name":"Donje Zdelice",
    "gn:population":0,
    "gn:timezone":"Europe/Zagreb",
    "iso:country":"HR",
    "wof:name":"Donje Zdelice",
    "wof:placetype":"locality"
},
  "geometry": {"coordinates":[16.91167,46.02639],"type":"Point"}
}