{
  "type": "Feature",
  "properties": {
    "gn:admin1_code":"3.0",
    "gn:admin2_code":"11054963.0",
    "gn:asciiname":"Vlaka",
    "gn:country_code":"HR",
    "gn:dem":0,
    "gn:feature_class":"P",
    "gn:feature_code":"PPLA2",
    "gn:name":"Vlaka",
    "gn:population":0,
    "gn:timezone":"Europe/Zagreb",
    "iso:country":"HR",
    "name:bos_x_preferred":[
        "Vlaka"
    ],
    "name:ceb_x_preferred":[
        "Vlaka"
    ],
    "name:fra_x_preferred":[
        "Vlaka"
    ],
    "name:hrv_x_preferred":[
        "Vlaka"
    ],
    "name:hun_x_preferred":[
        "Vlaka"
    ],
    "name:nld_x_preferred":[
        "Vlaka"
    ],
    "name:slv_x_preferred":[
        "Vlaka"
    ],
    "name:srp_x_preferred":[
        "\u0412\u043b\u0430\u043a\u0430"
    ],
    "name:swe_x_preferred":[
        "Vlaka"
    ],
    "name:ukr_x_preferred":[
        "\u0412\u043b\u0430\u043a\u0430"
    ],
    "wof:name":"Vlaka",
    "wof:placetype":"locality"
},
  "geometry": {"coordinates":[17.52417,42.99917],"type":"Point"}
}