{
  "type": "Feature",
  "properties": {
    "gn:admin1_code":"3.0",
    "gn:admin2_code":"11054963.0",
    "gn:asciiname":"Vlaka",
    "gn:country_code":"HR",
    "gn:dem":0,
    "gn:feature_class":"P",
    "gn:feature_code":"PPLA2",
    "gn:name":"Vlaka",
    "gn:population":0,
    "gn:timezone":"Europe/Zagreb",
    "iso:country":"HR",
    "wof:name":"Vlaka",
    "wof:placetype":"locality"
},
  "geometry": {"coordinates":[17.52417,42.99917],"type":"Point"}
}