{
  "type": "Feature",
  "properties": {
    "gn:admin1_code":"8.0",
    "gn:admin2_code":"11049285.0",
    "gn:asciiname":"Krnete",
    "gn:country_code":"HR",
    "gn:dem":626,
    "gn:feature_class":"P",
    "gn:feature_code":"PPL",
    "gn:name":"Krnete",
    "gn:population":0,
    "gn:timezone":"Europe/Zagreb",
    "iso:country":"HR",
    "wof:name":"Krnete",
    "wof:placetype":"locality"
},
  "geometry": {"coordinates":[16.10389,44.50806],"type":"Point"}
}