{
  "type": "Feature",
  "properties": {
    "gn:admin1_code":"15.0",
    "gn:asciiname":"Mlatinje",
    "gn:country_code":"HR",
    "gn:dem":10,
    "gn:feature_class":"P",
    "gn:feature_code":"PPL",
    "gn:name":"Mlatinje",
    "gn:population":0,
    "gn:timezone":"Europe/Zagreb",
    "iso:country":"HR",
    "wof:name":"Mlatinje",
    "wof:placetype":"locality"
},
  "geometry": {"coordinates":[17.3475,43.10194],"type":"Point"}
}