{
  "type": "Feature",
  "properties": {
    "gn:admin1_code":"19.0",
    "gn:asciiname":"Pecina",
    "gn:country_code":"HR",
    "gn:dem":186,
    "gn:feature_class":"P",
    "gn:feature_code":"PPL",
    "gn:name":"Pe\u010dina",
    "gn:population":0,
    "gn:timezone":"Europe/Zagreb",
    "iso:country":"HR",
    "wof:name":"Pecina",
    "wof:placetype":"locality"
},
  "geometry": {"coordinates":[15.73417,44.18528],"type":"Point"}
}