{
  "type": "Feature",
  "properties": {
    "gn:admin1_code":"12",
    "gn:admin2_code":"3187256.0",
    "gn:asciiname":"Ljubosina",
    "gn:country_code":"HR",
    "gn:dem":422,
    "gn:feature_class":"P",
    "gn:feature_code":"PPL",
    "gn:name":"Ljubo\u0161ina",
    "gn:population":173,
    "gn:timezone":"Europe/Zagreb",
    "iso:country":"HR",
    "wof:name":"Ljubosina",
    "wof:placetype":"locality",
    "wof:population":173
},
  "geometry": {"coordinates":[15.16667,45.31667],"type":"Point"}
}