{
  "type": "Feature",
  "properties": {
    "gn:admin1_code":"8.0",
    "gn:asciiname":"Roncevici",
    "gn:country_code":"HR",
    "gn:dem":479,
    "gn:feature_class":"P",
    "gn:feature_code":"PPL",
    "gn:name":"Ron\u010devi\u0107i",
    "gn:population":0,
    "gn:timezone":"Europe/Zagreb",
    "iso:country":"HR",
    "wof:name":"Roncevici",
    "wof:placetype":"locality"
},
  "geometry": {"coordinates":[15.14861,44.82083],"type":"Point"}
}