{
  "type": "Feature",
  "properties": {
    "gn:admin1_code":"15.0",
    "gn:asciiname":"Prolosici",
    "gn:country_code":"HR",
    "gn:dem":456,
    "gn:feature_class":"P",
    "gn:feature_code":"PPL",
    "gn:name":"Prolo\u0161i\u0107i",
    "gn:population":0,
    "gn:timezone":"Europe/Zagreb",
    "iso:country":"HR",
    "wof:name":"Prolosici",
    "wof:placetype":"locality"
},
  "geometry": {"coordinates":[16.58111,43.83222],"type":"Point"}
}