{
  "type": "Feature",
  "properties": {
    "gn:admin1_code":"12",
    "gn:admin2_code":"11072235.0",
    "gn:asciiname":"Tribalj",
    "gn:cc2":"HR",
    "gn:country_code":"HR",
    "gn:dem":55,
    "gn:feature_class":"P",
    "gn:feature_code":"PPL",
    "gn:name":"Tribalj",
    "gn:population":621,
    "gn:timezone":"Europe/Zagreb",
    "iso:country":"HR",
    "name:und_x_variant":[
        "Tribanj",
        "Tribalj"
    ],
    "wof:name":"Tribalj",
    "wof:placetype":"locality",
    "wof:population":621
},
  "geometry": {"coordinates":[14.67861,45.22139],"type":"Point"}
}