{
  "type": "Feature",
  "properties": {
    "gn:admin1_code":"05",
    "gn:admin2_code":"3194182.0",
    "gn:asciiname":"Trosmarija",
    "gn:cc2":"HR",
    "gn:country_code":"HR",
    "gn:dem":228,
    "gn:feature_class":"P",
    "gn:feature_code":"PPL",
    "gn:name":"Tro\u0161marija",
    "gn:population":127,
    "gn:timezone":"Europe/Zagreb",
    "iso:country":"HR",
    "name:und_x_variant":[
        "Trosmairja",
        "Tro\u0161marija"
    ],
    "wof:name":"Trosmarija",
    "wof:placetype":"locality",
    "wof:population":127
},
  "geometry": {"coordinates":[15.27237,45.32548],"type":"Point"}
}