{
  "type": "Feature",
  "properties": {
    "gn:admin1_code":"12.0",
    "gn:asciiname":"Praprot",
    "gn:cc2":"HR",
    "gn:country_code":"HR",
    "gn:dem":873,
    "gn:feature_class":"P",
    "gn:feature_code":"PPL",
    "gn:name":"Praprot",
    "gn:population":0,
    "gn:timezone":"Europe/Zagreb",
    "iso:country":"HR",
    "name:bos_x_preferred":[
        "Praprot"
    ],
    "name:hrv_x_preferred":[
        "Praprot"
    ],
    "name:nld_x_preferred":[
        "Praprot"
    ],
    "name:pol_x_preferred":[
        "Praprot"
    ],
    "name:ron_x_preferred":[
        "Praprot"
    ],
    "name:slv_x_preferred":[
        "Praprot"
    ],
    "name:ukr_x_preferred":[
        "\u041f\u0440\u0430\u043f\u0440\u043e\u0442"
    ],
    "name:und_x_variant":[
        "\u0160umarija Praprot",
        "Praprot"
    ],
    "wof:name":"Praprot",
    "wof:placetype":"locality"
},
  "geometry": {"coordinates":[14.73583,45.47417],"type":"Point"}
}