{
  "type": "Feature",
  "properties": {
    "gn:admin1_code":"05",
    "gn:asciiname":"Utinja",
    "gn:country_code":"HR",
    "gn:dem":216,
    "gn:feature_class":"P",
    "gn:feature_code":"PPL",
    "gn:name":"Utinja",
    "gn:population":5,
    "gn:timezone":"Europe/Zagreb",
    "iso:country":"HR",
    "wof:name":"Utinja",
    "wof:placetype":"locality",
    "wof:population":5
},
  "geometry": {"coordinates":[15.73028,45.39917],"type":"Point"}
}