{
  "type": "Feature",
  "properties": {
    "gn:admin1_code":"20",
    "gn:admin2_code":"3191315.0",
    "gn:asciiname":"Rakov Potok",
    "gn:country_code":"HR",
    "gn:dem":146,
    "gn:feature_class":"P",
    "gn:feature_code":"PPL",
    "gn:name":"Rakov Potok",
    "gn:population":1134,
    "gn:timezone":"Europe/Zagreb",
    "iso:country":"HR",
    "name:bos_x_preferred":[
        "Rakov Potok"
    ],
    "name:hrv_x_preferred":[
        "Rakov Potok"
    ],
    "name:hun_x_preferred":[
        "Rakov Potok"
    ],
    "name:nld_x_preferred":[
        "Rakov Potok"
    ],
    "name:slv_x_preferred":[
        "Rakov Potok"
    ],
    "name:srp_x_preferred":[
        "\u0420\u0430\u043a\u043e\u0432 \u041f\u043e\u0442\u043e\u043a"
    ],
    "name:ukr_x_preferred":[
        "\u0420\u0430\u043a\u043e\u0432 \u041f\u043e\u0442\u043e\u043a"
    ],
    "wof:name":"Rakov Potok",
    "wof:placetype":"locality",
    "wof:population":1134
},
  "geometry": {"coordinates":[15.79722,45.73806],"type":"Point"}
}