{
  "type": "Feature",
  "properties": {
    "gn:admin1_code":"20",
    "gn:admin2_code":"3191315.0",
    "gn:asciiname":"Rakov Potok",
    "gn:country_code":"HR",
    "gn:dem":146,
    "gn:feature_class":"P",
    "gn:feature_code":"PPL",
    "gn:name":"Rakov Potok",
    "gn:population":1134,
    "gn:timezone":"Europe/Zagreb",
    "iso:country":"HR",
    "wof:name":"Rakov Potok",
    "wof:placetype":"locality",
    "wof:population":1134
},
  "geometry": {"coordinates":[15.79722,45.73806],"type":"Point"}
}