{
  "type": "Feature",
  "properties": {
    "gn:admin1_code":"4.0",
    "gn:admin2_code":"11054818.0",
    "gn:asciiname":"Stranici kod Lovreca",
    "gn:cc2":"HR",
    "gn:country_code":"HR",
    "gn:dem":138,
    "gn:feature_class":"P",
    "gn:feature_code":"PPL",
    "gn:name":"Strani\u0107i kod Lovre\u010da",
    "gn:population":41,
    "gn:timezone":"Europe/Zagreb",
    "iso:country":"HR",
    "name:und_x_variant":[
        "Strani\u0107i",
        "Strani\u0107i kod Lovre\u010da"
    ],
    "wof:name":"Stranici kod Lovreca",
    "wof:placetype":"locality",
    "wof:population":41
},
  "geometry": {"coordinates":[13.73361,45.15944],"type":"Point"}
}