{
  "type": "Feature",
  "properties": {
    "gn:admin1_code":"04",
    "gn:admin2_code":"11054805.0",
    "gn:asciiname":"Brdo",
    "gn:country_code":"HR",
    "gn:dem":140,
    "gn:feature_class":"P",
    "gn:feature_code":"PPL",
    "gn:name":"Brdo",
    "gn:population":0,
    "gn:timezone":"Europe/Zagreb",
    "iso:country":"HR",
    "wof:name":"Brdo",
    "wof:placetype":"locality"
},
  "geometry": {"coordinates":[14.11806,45.23444],"type":"Point"}
}