{
  "type": "Feature",
  "properties": {
    "gn:admin1_code":"15.0",
    "gn:asciiname":"Zizica Strazbenica",
    "gn:country_code":"HR",
    "gn:dem":546,
    "gn:feature_class":"P",
    "gn:feature_code":"PPL",
    "gn:name":"\u017di\u017ei\u0107a Stra\u017ebenica",
    "gn:population":0,
    "gn:timezone":"Europe/Zagreb",
    "iso:country":"HR",
    "wof:name":"Zizica Strazbenica",
    "wof:placetype":"locality"
},
  "geometry": {"coordinates":[16.77361,43.70167],"type":"Point"}
}