{
  "type": "Feature",
  "properties": {
    "gn:admin1_code":"3.0",
    "gn:admin2_code":"11055009.0",
    "gn:asciiname":"Kunja Ljut",
    "gn:country_code":"HR",
    "gn:dem":166,
    "gn:feature_class":"P",
    "gn:feature_code":"PPL",
    "gn:name":"Kunja Ljut",
    "gn:population":0,
    "gn:timezone":"Europe/Zagreb",
    "iso:country":"HR",
    "wof:name":"Kunja Ljut",
    "wof:placetype":"locality"
},
  "geometry": {"coordinates":[17.89306000000001,42.75944000000001],"type":"Point"}
}