{
  "type": "Feature",
  "properties": {
    "gn:admin1_code":"10",
    "gn:admin2_code":"11054483.0",
    "gn:asciiname":"Hrkanovci Dakovacki",
    "gn:cc2":"HR",
    "gn:country_code":"HR",
    "gn:dem":146,
    "gn:feature_class":"P",
    "gn:feature_code":"PPL",
    "gn:name":"Hrkanovci \u00d0akova\u010dki",
    "gn:population":0,
    "gn:timezone":"Europe/Zagreb",
    "iso:country":"HR",
    "name:und_x_variant":[
        "Hrkanovci Djakova\u010dki",
        "Hrkanovci",
        "Hrkanovci \u00d0akova\u010dki"
    ],
    "wof:name":"Hrkanovci Dakovacki",
    "wof:placetype":"locality"
},
  "geometry": {"coordinates":[18.18694,45.26667],"type":"Point"}
}