{
  "type": "Feature",
  "properties": {
    "gn:admin1_code":"07",
    "gn:admin2_code":"11049219.0",
    "gn:asciiname":"Velika Erpenja",
    "gn:cc2":"HR",
    "gn:country_code":"HR",
    "gn:dem":233,
    "gn:feature_class":"P",
    "gn:feature_code":"PPL",
    "gn:name":"Velika Erpenja",
    "gn:population":111,
    "gn:timezone":"Europe/Zagreb",
    "iso:country":"HR",
    "name:und_x_variant":[
        "Erpenye",
        "Nagy Erpenye",
        "Velika Erpenye",
        "Velika Erpenja"
    ],
    "wof:name":"Velika Erpenja",
    "wof:placetype":"locality",
    "wof:population":111
},
  "geometry": {"coordinates":[15.80924,46.06543],"type":"Point"}
}