{
  "type": "Feature",
  "properties": {
    "gn:admin1_code":"11.0",
    "gn:admin2_code":"3190588.0",
    "gn:asciiname":"Marin Dvor",
    "gn:cc2":"HR",
    "gn:country_code":"HR",
    "gn:dem":212,
    "gn:feature_class":"P",
    "gn:feature_code":"PPL",
    "gn:name":"Marin Dvor",
    "gn:population":0,
    "gn:timezone":"Europe/Zagreb",
    "iso:country":"HR",
    "name:und_x_variant":[
        "Marm Dvor",
        "Marin Dvor"
    ],
    "wof:name":"Marin Dvor",
    "wof:placetype":"locality"
},
  "geometry": {"coordinates":[17.64167,45.37194],"type":"Point"}
}