{
  "type": "Feature",
  "properties": {
    "gn:admin1_code":"15",
    "gn:admin2_code":"11054603.0",
    "gn:asciiname":"Drvenik",
    "gn:country_code":"HR",
    "gn:dem":3,
    "gn:feature_class":"P",
    "gn:feature_code":"PPLL",
    "gn:name":"Drvenik",
    "gn:population":0,
    "gn:timezone":"Europe/Zagreb",
    "iso:country":"HR",
    "name:bos_x_preferred":[
        "Drvenik"
    ],
    "name:cat_x_preferred":[
        "Drvenik"
    ],
    "name:ceb_x_preferred":[
        "Drvenik"
    ],
    "name:ces_x_preferred":[
        "Drvenik"
    ],
    "name:deu_x_preferred":[
        "Drvenik"
    ],
    "name:eng_x_preferred":[
        "Drvenik"
    ],
    "name:fra_x_preferred":[
        "Drvenik"
    ],
    "name:hrv_x_preferred":[
        "Drvenik"
    ],
    "name:hun_x_preferred":[
        "Drvenik"
    ],
    "name:nld_x_preferred":[
        "Drvenik"
    ],
    "name:pol_x_preferred":[
        "Drvenik"
    ],
    "name:ron_x_preferred":[
        "Drvenik"
    ],
    "name:rus_x_preferred":[
        "\u0414\u0440\u0432\u0435\u043d\u0438\u043a"
    ],
    "name:slv_x_preferred":[
        "Drvenik"
    ],
    "name:srp_x_preferred":[
        "\u0414\u0440\u0432\u0435\u043d\u0438\u043a"
    ],
    "name:swe_x_preferred":[
        "Drvenik"
    ],
    "name:ukr_x_preferred":[
        "\u0414\u0440\u0432\u0435\u043d\u0438\u043a"
    ],
    "wof:name":"Drvenik",
    "wof:placetype":"locality"
},
  "geometry": {"coordinates":[17.24854,43.15573],"type":"Point"}
}