{
  "type": "Feature",
  "properties": {
    "gn:admin1_code":"8.0",
    "gn:asciiname":"Sveti Tranjo",
    "gn:country_code":"HR",
    "gn:dem":469,
    "gn:feature_class":"P",
    "gn:feature_code":"PPL",
    "gn:name":"Sveti Tranjo",
    "gn:population":0,
    "gn:timezone":"Europe/Zagreb",
    "iso:country":"HR",
    "wof:name":"Sveti Tranjo",
    "wof:placetype":"locality"
},
  "geometry": {"coordinates":[15.36694,44.78694],"type":"Point"}
}