{
  "type": "Feature",
  "properties": {
    "gn:admin1_code":"8.0",
    "gn:asciiname":"Podkraj",
    "gn:country_code":"HR",
    "gn:dem":424,
    "gn:feature_class":"P",
    "gn:feature_code":"PPL",
    "gn:name":"Podkraj",
    "gn:population":0,
    "gn:timezone":"Europe/Zagreb",
    "iso:country":"HR",
    "name:bos_x_preferred":[
        "Podkraj"
    ],
    "name:ceb_x_preferred":[
        "Podkraj"
    ],
    "name:fra_x_preferred":[
        "Podkraj"
    ],
    "name:hrv_x_preferred":[
        "Podkraj"
    ],
    "name:nld_x_preferred":[
        "Podkraj"
    ],
    "name:sco_x_preferred":[
        "Podkraj"
    ],
    "name:slv_x_preferred":[
        "Podkraj"
    ],
    "name:srp_x_preferred":[
        "\u041f\u043e\u0434\u043a\u0440\u0430\u0458"
    ],
    "wof:name":"Podkraj",
    "wof:placetype":"locality"
},
  "geometry": {"coordinates":[15.15528,44.90472000000001],"type":"Point"}
}