{
  "type": "Feature",
  "properties": {
    "gn:gn_country":"HR",
    "gn:gn_fcode":"PPL",
    "gn:gn_pop":0,
    "gn:population":594,
    "iso:country":"HR",
    "name:unk_x_variant":[
        "Dubravica"
    ],
    "qs_pg:aaroncc":"HR",
    "qs_pg:gn_country":"HR",
    "qs_pg:gn_fcode":"PPL",
    "qs_pg:gn_pop":0,
    "qs_pg:name":"Dubravice",
    "qs_pg:name_adm0":"Hrvatska",
    "qs_pg:name_adm1":"Sibenska",
    "qs_pg:photos":66,
    "qs_pg:photos_1k":13,
    "qs_pg:photos_9k":1,
    "qs_pg:photos_9r":2,
    "qs_pg:photos_all":66,
    "qs_pg:photos_sr":2,
    "qs_pg:pop_sr":0,
    "qs_pg:qs_pg_placetype":"locality",
    "qs_pg:qs_pg_placetype_gp":"Town",
    "qs_pg:woe_adm0":23424843,
    "woe:adm0_id":23424843,
    "woe:name_adm0":"Hrvatska",
    "woe:name_adm1":"Sibenska",
    "woe:placetype":"Town",
    "wof:name":"Dubravice",
    "wof:placetype":"locality",
    "wof:population":594
},
  "geometry": {"coordinates":[15.93889,43.85306],"type":"Point"}
}