{
  "type": "Feature",
  "properties": {
    "gn:admin1_code":"16",
    "gn:admin2_code":"11049311.0",
    "gn:asciiname":"Novaki Marusevecki",
    "gn:cc2":"HR",
    "gn:country_code":"HR",
    "gn:dem":220,
    "gn:feature_class":"P",
    "gn:feature_code":"PPL",
    "gn:name":"Novaki Maru\u0161eve\u010dki",
    "gn:population":0,
    "gn:timezone":"Europe/Zagreb",
    "iso:country":"HR",
    "name:und_x_variant":[
        "Maru\u0161eve\u010dki Novaki",
        "Novaki",
        "Novaki Maru\u0161eve\u010dki"
    ],
    "wof:name":"Novaki Marusevecki",
    "wof:placetype":"locality"
},
  "geometry": {"coordinates":[16.1325,46.26722],"type":"Point"}
}