{
  "type": "Feature",
  "properties": {
    "gn:admin1_code":"8.0",
    "gn:asciiname":"Ilinac",
    "gn:country_code":"HR",
    "gn:dem":596,
    "gn:feature_class":"P",
    "gn:feature_code":"PPL",
    "gn:name":"Ilinac",
    "gn:population":0,
    "gn:timezone":"Europe/Zagreb",
    "iso:country":"HR",
    "wof:name":"Ilinac",
    "wof:placetype":"locality"
},
  "geometry": {"coordinates":[15.58611,44.48861],"type":"Point"}
}