{
  "type": "Feature",
  "properties": {
    "gn:admin1_code":"04",
    "gn:asciiname":"Donji Bratovici",
    "gn:cc2":"HR",
    "gn:country_code":"HR",
    "gn:dem":224,
    "gn:feature_class":"P",
    "gn:feature_code":"PPL",
    "gn:name":"Donji Bratovi\u0107i",
    "gn:population":0,
    "gn:timezone":"Europe/Zagreb",
    "iso:country":"HR",
    "name:und_x_variant":[
        "Bratovi\u0107i",
        "Brattovi",
        "Donji Bratovi\u0107i"
    ],
    "wof:name":"Donji Bratovici",
    "wof:placetype":"locality"
},
  "geometry": {"coordinates":[13.75417,45.22056],"type":"Point"}
}