{
  "type": "Feature",
  "properties": {
    "gn:admin1_code":"10",
    "gn:admin2_code":"11054476.0",
    "gn:asciiname":"Razbojiste",
    "gn:country_code":"HR",
    "gn:dem":122,
    "gn:feature_class":"P",
    "gn:feature_code":"PPL",
    "gn:name":"Razboji\u0161te",
    "gn:population":283,
    "gn:timezone":"Europe/Zagreb",
    "iso:country":"HR",
    "name:bos_x_preferred":[
        "Razboji\u0161te"
    ],
    "name:hrv_x_preferred":[
        "Razboji\u0161te"
    ],
    "name:slv_x_preferred":[
        "Razboji\u0161te"
    ],
    "name:srp_x_preferred":[
        "\u0420\u0430\u0437\u0431\u043e\u0458\u0438\u0448\u0442\u0435"
    ],
    "name:ukr_x_preferred":[
        "\u0420\u0430\u0437\u0431\u043e\u0457\u0449\u0435"
    ],
    "name:und_x_variant":[
        "Razboji\u0161te"
    ],
    "wof:name":"Razbojiste",
    "wof:placetype":"locality",
    "wof:population":283
},
  "geometry": {"coordinates":[18.24917,45.44056],"type":"Point"}
}