{
  "type": "Feature",
  "properties": {
    "gn:admin1_code":"12.0",
    "gn:asciiname":"Podrvanj",
    "gn:country_code":"HR",
    "gn:dem":307,
    "gn:feature_class":"P",
    "gn:feature_code":"PPL",
    "gn:name":"Podrvanj",
    "gn:population":461,
    "gn:timezone":"Europe/Zagreb",
    "iso:country":"HR",
    "wof:name":"Podrvanj",
    "wof:placetype":"locality",
    "wof:population":461
},
  "geometry": {"coordinates":[14.48,45.36083],"type":"Point"}
}