{
  "type": "Feature",
  "properties": {
    "gn:admin1_code":"8.0",
    "gn:admin2_code":"11049292.0",
    "gn:asciiname":"Kalebovac",
    "gn:country_code":"HR",
    "gn:dem":695,
    "gn:feature_class":"P",
    "gn:feature_code":"PPL",
    "gn:name":"Kalebovac",
    "gn:population":35,
    "gn:timezone":"Europe/Zagreb",
    "iso:country":"HR",
    "wof:name":"Kalebovac",
    "wof:placetype":"locality",
    "wof:population":35
},
  "geometry": {"coordinates":[15.70528,44.74028],"type":"Point"}
}