{
  "type": "Feature",
  "properties": {
    "gn:country":"HR",
    "gn:fcode":"PPL",
    "gn:population":377,
    "iso:country":"HR",
    "name:bos_x_preferred":[
        "Sedlarica"
    ],
    "name:ceb_x_preferred":[
        "Sedlarica"
    ],
    "name:eng_x_preferred":[
        "Sedlarica"
    ],
    "name:fra_x_preferred":[
        "Sedlarica"
    ],
    "name:hrv_x_preferred":[
        "Sedlarica"
    ],
    "name:hun_x_preferred":[
        "Sedlarica"
    ],
    "name:nld_x_preferred":[
        "Sedlarica"
    ],
    "name:pol_x_preferred":[
        "Sedlarica"
    ],
    "name:slv_x_preferred":[
        "Sedlarica"
    ],
    "name:spa_x_preferred":[
        "Sedlarica"
    ],
    "name:srp_x_preferred":[
        "\u0421\u0435\u0434\u043b\u0430\u0440\u0438\u0446\u0430"
    ],
    "name:swe_x_preferred":[
        "Sedlarica"
    ],
    "name:ukr_x_preferred":[
        "\u0421\u0435\u0434\u043b\u0430\u0440\u0438\u0446\u044f"
    ],
    "qs_pg:aaroncc":"HR",
    "qs_pg:gn_country":"HR",
    "qs_pg:gn_fcode":"PPL",
    "qs_pg:gn_pop":377,
    "qs_pg:name":"Sedlarica",
    "qs_pg:name_adm0":"Hrvatska",
    "qs_pg:name_adm1":"Viroviti\u010dko-podravska",
    "qs_pg:photos_9r":0,
    "qs_pg:photos_sr":0,
    "qs_pg:pop_sr":2,
    "qs_pg:qs_pg_placetype":"locality",
    "qs_pg:qs_pg_placetype_gp":"Town",
    "qs_pg:woe_adm0":23424843,
    "woe:adm0_id":23424843,
    "woe:name_adm0":"Hrvatska",
    "woe:name_adm1":"Viroviti\u010dko-podravska",
    "woe:placetype":"Town",
    "wof:name":"Sedlarica",
    "wof:placetype":"locality",
    "wof:population":363
},
  "geometry": {"coordinates":[17.19639,45.89528],"type":"Point"}
}