{
  "type": "Feature",
  "properties": {
    "gn:admin1_code":"10.0",
    "gn:asciiname":"Mala Branjevina",
    "gn:country_code":"HR",
    "gn:dem":84,
    "gn:feature_class":"P",
    "gn:feature_code":"PPL",
    "gn:name":"Mala Branjevina",
    "gn:population":0,
    "gn:timezone":"Europe/Zagreb",
    "iso:country":"HR",
    "wof:name":"Mala Branjevina",
    "wof:placetype":"locality"
},
  "geometry": {"coordinates":[18.52444,45.46972],"type":"Point"}
}