{
  "type": "Feature",
  "properties": {
    "gn:admin1_code":"12.0",
    "gn:admin2_code":"3202931.0",
    "gn:asciiname":"Mandli",
    "gn:country_code":"HR",
    "gn:dem":345,
    "gn:feature_class":"P",
    "gn:feature_code":"PPL",
    "gn:name":"Mandli",
    "gn:population":39,
    "gn:timezone":"Europe/Zagreb",
    "iso:country":"HR",
    "wof:name":"Mandli",
    "wof:placetype":"locality",
    "wof:population":39
},
  "geometry": {"coordinates":[14.69472,45.56],"type":"Point"}
}