{
  "type": "Feature",
  "properties": {
    "gn:admin1_code":"14.0",
    "gn:asciiname":"Bijelnik",
    "gn:cc2":"HR",
    "gn:country_code":"HR",
    "gn:dem":170,
    "gn:feature_class":"P",
    "gn:feature_code":"PPL",
    "gn:name":"Bijelnik",
    "gn:population":47,
    "gn:timezone":"Europe/Zagreb",
    "iso:country":"HR",
    "name:und_x_variant":[
        "Bednik",
        "Bijelnik"
    ],
    "wof:name":"Bijelnik",
    "wof:placetype":"locality",
    "wof:population":47
},
  "geometry": {"coordinates":[16.38332999999999,45.35],"type":"Point"}
}