{
  "type": "Feature",
  "properties": {
    "gn:admin1_code":"5.0",
    "gn:asciiname":"Jagrovac",
    "gn:country_code":"HR",
    "gn:dem":151,
    "gn:feature_class":"P",
    "gn:feature_code":"PPL",
    "gn:name":"Jagrovac",
    "gn:population":44,
    "gn:timezone":"Europe/Zagreb",
    "iso:country":"HR",
    "name:bos_x_preferred":[
        "Jagrovac"
    ],
    "name:cat_x_preferred":[
        "Jagrovac"
    ],
    "name:hrv_x_preferred":[
        "Jagrovac"
    ],
    "name:hun_x_preferred":[
        "Jagrovac"
    ],
    "name:nld_x_preferred":[
        "Jagrovac"
    ],
    "name:slv_x_preferred":[
        "Jagrovac"
    ],
    "name:spa_x_preferred":[
        "Jagrovac"
    ],
    "name:srp_x_preferred":[
        "\u0408\u0430\u0433\u0440\u043e\u0432\u0430\u0446"
    ],
    "name:ukr_x_preferred":[
        "\u042f\u0433\u0440\u043e\u0432\u0430\u0446\u044c"
    ],
    "name:urd_x_preferred":[
        "\u062c\u06af\u0631\u0648\u0648\u0627\u06a9"
    ],
    "wof:name":"Jagrovac",
    "wof:placetype":"locality",
    "wof:population":44
},
  "geometry": {"coordinates":[15.75,45.21833],"type":"Point"}
}