{
  "type": "Feature",
  "properties": {
    "gn:admin1_code":"20",
    "gn:admin2_code":"3186602.0",
    "gn:asciiname":"Novo Mjesto",
    "gn:country_code":"HR",
    "gn:dem":125,
    "gn:feature_class":"P",
    "gn:feature_code":"PPL",
    "gn:name":"Novo Mjesto",
    "gn:population":147,
    "gn:timezone":"Europe/Zagreb",
    "iso:country":"HR",
    "wof:name":"Novo Mjesto",
    "wof:placetype":"locality",
    "wof:population":147
},
  "geometry": {"coordinates":[16.28333,45.95],"type":"Point"}
}