{
  "type": "Feature",
  "properties": {
    "gn:admin1_code":"15.0",
    "gn:asciiname":"Zekulici",
    "gn:country_code":"HR",
    "gn:dem":421,
    "gn:feature_class":"P",
    "gn:feature_code":"PPL",
    "gn:name":"Zekuli\u0107i",
    "gn:population":0,
    "gn:timezone":"Europe/Zagreb",
    "iso:country":"HR",
    "wof:name":"Zekulici",
    "wof:placetype":"locality"
},
  "geometry": {"coordinates":[17.29111,43.23111],"type":"Point"}
}