{
  "type": "Feature",
  "properties": {
    "gn:admin1_code":"14.0",
    "gn:asciiname":"Ljubisici",
    "gn:country_code":"HR",
    "gn:dem":222,
    "gn:feature_class":"P",
    "gn:feature_code":"PPL",
    "gn:name":"Ljubi\u0161i\u0107i",
    "gn:population":0,
    "gn:timezone":"Europe/Zagreb",
    "iso:country":"HR",
    "wof:name":"Ljubisici",
    "wof:placetype":"locality"
},
  "geometry": {"coordinates":[16.2725,45.15556],"type":"Point"}
}