{
  "type": "Feature",
  "properties": {
    "gn:admin1_code":"20",
    "gn:admin2_code":"3186602.0",
    "gn:asciiname":"Laktec",
    "gn:country_code":"HR",
    "gn:dem":119,
    "gn:feature_class":"P",
    "gn:feature_code":"PPL",
    "gn:name":"Laktec",
    "gn:population":175,
    "gn:timezone":"Europe/Zagreb",
    "iso:country":"HR",
    "name:bos_x_preferred":[
        "Laktec"
    ],
    "name:hrv_x_preferred":[
        "Laktec"
    ],
    "name:hun_x_preferred":[
        "Laktec"
    ],
    "name:nld_x_preferred":[
        "Laktec"
    ],
    "name:slv_x_preferred":[
        "Laktec"
    ],
    "name:ukr_x_preferred":[
        "\u041b\u0430\u043a\u0442\u0435\u0446\u044c"
    ],
    "wof:name":"Laktec",
    "wof:placetype":"locality",
    "wof:population":175
},
  "geometry": {"coordinates":[16.23194,45.86],"type":"Point"}
}