{
  "type": "Feature",
  "properties": {
    "gn:admin1_code":"15.0",
    "gn:asciiname":"Jelasi",
    "gn:country_code":"HR",
    "gn:dem":385,
    "gn:feature_class":"P",
    "gn:feature_code":"PPL",
    "gn:name":"Jelasi",
    "gn:population":0,
    "gn:timezone":"Europe/Zagreb",
    "iso:country":"HR",
    "wof:name":"Jelasi",
    "wof:placetype":"locality"
},
  "geometry": {"coordinates":[17.24389,43.25056],"type":"Point"}
}