{
  "type": "Feature",
  "properties": {
    "gn:admin1_code":"19.0",
    "gn:asciiname":"Provalija",
    "gn:country_code":"HR",
    "gn:dem":43,
    "gn:feature_class":"P",
    "gn:feature_code":"PPL",
    "gn:name":"Provalija",
    "gn:population":0,
    "gn:timezone":"Europe/Zagreb",
    "iso:country":"HR",
    "wof:name":"Provalija",
    "wof:placetype":"locality"
},
  "geometry": {"coordinates":[15.51944,44.27222],"type":"Point"}
}