{
  "type": "Feature",
  "properties": {
    "gn:admin1_code":"07",
    "gn:admin2_code":"11049195.0",
    "gn:asciiname":"Petrovsko",
    "gn:country_code":"HR",
    "gn:dem":341,
    "gn:feature_class":"P",
    "gn:feature_code":"PPLA2",
    "gn:name":"Petrovsko",
    "gn:population":0,
    "gn:timezone":"Europe/Zagreb",
    "iso:country":"HR",
    "wof:name":"Petrovsko",
    "wof:placetype":"locality"
},
  "geometry": {"coordinates":[15.84083,46.16806],"type":"Point"}
}