{
  "type": "Feature",
  "properties": {
    "gn:admin1_code":"07",
    "gn:admin2_code":"11049195.0",
    "gn:asciiname":"Petrovsko",
    "gn:country_code":"HR",
    "gn:dem":341,
    "gn:feature_class":"P",
    "gn:feature_code":"PPLA2",
    "gn:name":"Petrovsko",
    "gn:population":0,
    "gn:timezone":"Europe/Zagreb",
    "iso:country":"HR",
    "name:bos_x_preferred":[
        "Petrovsko"
    ],
    "name:fra_x_preferred":[
        "Petrovsko"
    ],
    "name:hrv_x_preferred":[
        "Petrovsko"
    ],
    "name:hun_x_preferred":[
        "Petrovsko"
    ],
    "name:ita_x_preferred":[
        "Petrovsko"
    ],
    "name:nld_x_preferred":[
        "Petrovsko"
    ],
    "name:pol_x_preferred":[
        "Gmina Petrovsko"
    ],
    "name:ron_x_preferred":[
        "Comuna Petrovsko"
    ],
    "name:rus_x_preferred":[
        "\u041f\u0435\u0442\u0440\u043e\u0432\u0441\u043a\u043e"
    ],
    "name:slv_x_preferred":[
        "Petrovsko"
    ],
    "name:spa_x_preferred":[
        "Petrovsko"
    ],
    "name:srp_x_preferred":[
        "\u041f\u0435\u0442\u0440\u043e\u0432\u0441\u043a\u043e"
    ],
    "name:ukr_x_preferred":[
        "\u041f\u0435\u0442\u0440\u043e\u0432\u0441\u044c\u043a\u043e"
    ],
    "name:war_x_preferred":[
        "Petrovsko"
    ],
    "wof:name":"Petrovsko",
    "wof:placetype":"locality"
},
  "geometry": {"coordinates":[15.84083,46.16806],"type":"Point"}
}