{
  "type": "Feature",
  "properties": {
    "gn:admin1_code":"16.0",
    "gn:admin2_code":"11049296.0",
    "gn:asciiname":"Trakoscansko Jezero",
    "gn:country_code":"HR",
    "gn:dem":270,
    "gn:feature_class":"P",
    "gn:feature_code":"PPL",
    "gn:name":"Trako\u0161\u010dansko Jezero",
    "gn:population":0,
    "gn:timezone":"Europe/Zagreb",
    "iso:country":"HR",
    "wof:name":"Trakoscansko Jezero",
    "wof:placetype":"locality"
},
  "geometry": {"coordinates":[15.93917,46.25917000000001],"type":"Point"}
}