{
  "type": "Feature",
  "properties": {
    "gn:admin1_code":"21",
    "gn:asciiname":"Kucilovina",
    "gn:country_code":"HR",
    "gn:dem":424,
    "gn:feature_class":"P",
    "gn:feature_code":"PPL",
    "gn:name":"Ku\u010dilovina",
    "gn:population":0,
    "gn:timezone":"Europe/Zagreb",
    "iso:country":"HR",
    "name:und_x_variant":[
        "Ku\u010dilovina"
    ],
    "wof:name":"Kucilovina",
    "wof:placetype":"locality"
},
  "geometry": {"coordinates":[16.08333,45.91667],"type":"Point"}
}