{
  "type": "Feature",
  "properties": {
    "gn:admin1_code":"01",
    "gn:admin2_code":"3203981.0",
    "gn:asciiname":"Prgomelje",
    "gn:country_code":"HR",
    "gn:dem":111,
    "gn:feature_class":"P",
    "gn:feature_code":"PPL",
    "gn:name":"Prgomelje",
    "gn:population":696,
    "gn:timezone":"Europe/Zagreb",
    "iso:country":"HR",
    "wof:name":"Prgomelje",
    "wof:placetype":"locality",
    "wof:population":696
},
  "geometry": {"coordinates":[16.75222,45.89083],"type":"Point"}
}