{
  "type": "Feature",
  "properties": {
    "gn:admin1_code":"10",
    "gn:admin2_code":"11054484.0",
    "gn:asciiname":"Cret Viljevski",
    "gn:cc2":"HR",
    "gn:country_code":"HR",
    "gn:dem":93,
    "gn:feature_class":"P",
    "gn:feature_code":"PPL",
    "gn:name":"Cret Viljevski",
    "gn:population":80,
    "gn:timezone":"Europe/Zagreb",
    "iso:country":"HR",
    "name:und_x_variant":[
        "Viljevski \u010cret",
        "\u010cret Pustara",
        "Cret Viljevski"
    ],
    "wof:name":"Cret Viljevski",
    "wof:placetype":"locality",
    "wof:population":80
},
  "geometry": {"coordinates":[18.06167,45.725],"type":"Point"}
}