{
  "type": "Feature",
  "properties": {
    "gn:admin1_code":"19.0",
    "gn:asciiname":"Jovanici",
    "gn:country_code":"HR",
    "gn:dem":503,
    "gn:feature_class":"P",
    "gn:feature_code":"PPL",
    "gn:name":"Jovani\u0107i",
    "gn:population":0,
    "gn:timezone":"Europe/Zagreb",
    "iso:country":"HR",
    "wof:name":"Jovanici",
    "wof:placetype":"locality"
},
  "geometry": {"coordinates":[16.09528,44.40444],"type":"Point"}
}