{
  "type": "Feature",
  "properties": {
    "gn:admin1_code":"5.0",
    "gn:asciiname":"Gracac",
    "gn:country_code":"HR",
    "gn:dem":657,
    "gn:feature_class":"P",
    "gn:feature_code":"PPL",
    "gn:name":"Gra\u010dac",
    "gn:population":0,
    "gn:timezone":"Europe/Zagreb",
    "iso:country":"HR",
    "wof:name":"Gracac",
    "wof:placetype":"locality"
},
  "geometry": {"coordinates":[15.1325,45.20861],"type":"Point"}
}