{
  "type": "Feature",
  "properties": {
    "gn:admin1_code":"06",
    "gn:admin2_code":"11049397.0",
    "gn:asciiname":"Semovci",
    "gn:country_code":"HR",
    "gn:dem":179,
    "gn:feature_class":"P",
    "gn:feature_code":"PPL",
    "gn:name":"\u0160emovci",
    "gn:population":0,
    "gn:timezone":"Europe/Zagreb",
    "iso:country":"HR",
    "name:bos_x_preferred":[
        "\u0160emovci"
    ],
    "name:hrv_x_preferred":[
        "\u0160emovci"
    ],
    "name:hun_x_preferred":[
        "\u0160emovci"
    ],
    "name:nld_x_preferred":[
        "\u0160emovci"
    ],
    "name:slv_x_preferred":[
        "\u0160emovci"
    ],
    "name:spa_x_preferred":[
        "\u0160emovci"
    ],
    "name:srp_x_preferred":[
        "\u0428\u0435\u043c\u043e\u0432\u0446\u0438"
    ],
    "name:ukr_x_preferred":[
        "\u0428\u0435\u043c\u043e\u0432\u0446\u0456"
    ],
    "name:und_x_variant":[
        "\u0160emovci"
    ],
    "wof:name":"Semovci",
    "wof:placetype":"locality"
},
  "geometry": {"coordinates":[16.99194,46.02361],"type":"Point"}
}