{
  "type": "Feature",
  "properties": {
    "gn:admin1_code":"3.0",
    "gn:admin2_code":"11054963.0",
    "gn:asciiname":"Rosni Do",
    "gn:country_code":"HR",
    "gn:dem":325,
    "gn:feature_class":"P",
    "gn:feature_code":"PPL",
    "gn:name":"Rosni Do",
    "gn:population":0,
    "gn:timezone":"Europe/Zagreb",
    "iso:country":"HR",
    "wof:name":"Rosni Do",
    "wof:placetype":"locality"
},
  "geometry": {"coordinates":[17.56528,42.96917],"type":"Point"}
}