{
  "type": "Feature",
  "properties": {
    "gn:admin1_code":"03",
    "gn:admin2_code":"11054963.0",
    "gn:asciiname":"Zavala",
    "gn:country_code":"HR",
    "gn:dem":169,
    "gn:feature_class":"P",
    "gn:feature_code":"PPL",
    "gn:name":"Zavala",
    "gn:population":1,
    "gn:timezone":"Europe/Zagreb",
    "iso:country":"HR",
    "name:bos_x_preferred":[
        "Zavala"
    ],
    "name:ceb_x_preferred":[
        "Zavala"
    ],
    "name:deu_x_preferred":[
        "Zavala"
    ],
    "name:est_x_preferred":[
        "Zavala"
    ],
    "name:fra_x_preferred":[
        "Zavala"
    ],
    "name:hrv_x_preferred":[
        "Zavala"
    ],
    "name:hun_x_preferred":[
        "Zavala"
    ],
    "name:ita_x_preferred":[
        "Zavala"
    ],
    "name:nld_x_preferred":[
        "Zavala"
    ],
    "name:rus_x_preferred":[
        "\u0417\u0430\u0432\u0430\u043b\u0430"
    ],
    "name:slv_x_preferred":[
        "Zavala"
    ],
    "name:spa_x_preferred":[
        "Zavala"
    ],
    "name:srp_x_preferred":[
        "\u0417\u0430\u0432\u0430\u043b\u0430"
    ],
    "name:swe_x_preferred":[
        "Zavala"
    ],
    "name:ukr_x_preferred":[
        "\u0417\u0430\u0432\u0430\u043b\u0430"
    ],
    "wof:name":"Zavala",
    "wof:placetype":"locality",
    "wof:population":1
},
  "geometry": {"coordinates":[17.58361,42.95028],"type":"Point"}
}