{
  "type": "Feature",
  "properties": {
    "gn:admin1_code":"8.0",
    "gn:asciiname":"Uzelci",
    "gn:country_code":"HR",
    "gn:dem":566,
    "gn:feature_class":"P",
    "gn:feature_code":"PPL",
    "gn:name":"Uzelci",
    "gn:population":0,
    "gn:timezone":"Europe/Zagreb",
    "iso:country":"HR",
    "wof:name":"Uzelci",
    "wof:placetype":"locality"
},
  "geometry": {"coordinates":[15.42389,44.46583],"type":"Point"}
}