{
  "type": "Feature",
  "properties": {
    "gn:admin1_code":"19.0",
    "gn:asciiname":"Kojic",
    "gn:country_code":"HR",
    "gn:dem":72,
    "gn:feature_class":"P",
    "gn:feature_code":"PPL",
    "gn:name":"Koji\u0107",
    "gn:population":0,
    "gn:timezone":"Europe/Zagreb",
    "iso:country":"HR",
    "wof:name":"Kojic",
    "wof:placetype":"locality"
},
  "geometry": {"coordinates":[15.42222,44.31361],"type":"Point"}
}