{
  "type": "Feature",
  "properties": {
    "gn:admin1_code":"14",
    "gn:admin2_code":"3194318.0",
    "gn:asciiname":"Kozarice",
    "gn:cc2":"HR",
    "gn:country_code":"HR",
    "gn:dem":126,
    "gn:feature_class":"P",
    "gn:feature_code":"PPL",
    "gn:name":"Kozarice",
    "gn:population":433,
    "gn:timezone":"Europe/Zagreb",
    "iso:country":"HR",
    "name:und_x_variant":[
        "Kozarica",
        "Kozarice"
    ],
    "wof:name":"Kozarice",
    "wof:placetype":"locality",
    "wof:population":433
},
  "geometry": {"coordinates":[16.96583,45.38667],"type":"Point"}
}