{
  "type": "Feature",
  "properties": {
    "gn:admin1_code":"04",
    "gn:admin2_code":"11054807.0",
    "gn:asciiname":"Vranja",
    "gn:cc2":"HR",
    "gn:country_code":"HR",
    "gn:dem":265,
    "gn:feature_class":"P",
    "gn:feature_code":"PPL",
    "gn:name":"Vranja",
    "gn:population":98,
    "gn:timezone":"Europe/Zagreb",
    "iso:country":"HR",
    "name:und_x_variant":[
        "Aurania",
        "Vranje",
        "Vragna",
        "Vranja"
    ],
    "wof:name":"Vranja",
    "wof:placetype":"locality",
    "wof:population":98
},
  "geometry": {"coordinates":[14.14528,45.31972],"type":"Point"}
}