{
  "type": "Feature",
  "properties": {
    "gn:admin1_code":"04",
    "gn:admin2_code":"11054807.0",
    "gn:asciiname":"Vranja",
    "gn:cc2":"HR",
    "gn:country_code":"HR",
    "gn:dem":265,
    "gn:feature_class":"P",
    "gn:feature_code":"PPL",
    "gn:name":"Vranja",
    "gn:population":98,
    "gn:timezone":"Europe/Zagreb",
    "iso:country":"HR",
    "name:bos_x_preferred":[
        "Vranja"
    ],
    "name:fra_x_preferred":[
        "Vranja"
    ],
    "name:hrv_x_preferred":[
        "Vranja"
    ],
    "name:hun_x_preferred":[
        "Vranja"
    ],
    "name:nld_x_preferred":[
        "Vranja"
    ],
    "name:pol_x_preferred":[
        "Vranja"
    ],
    "name:slv_x_preferred":[
        "Vranja"
    ],
    "name:srp_x_preferred":[
        "\u0412\u0440\u0430\u045a\u0430"
    ],
    "name:ukr_x_preferred":[
        "\u0412\u0440\u0430\u043d\u044f"
    ],
    "name:und_x_variant":[
        "Aurania",
        "Vranje",
        "Vragna",
        "Vranja"
    ],
    "wof:name":"Vranja",
    "wof:placetype":"locality",
    "wof:population":98
},
  "geometry": {"coordinates":[14.14528,45.31972],"type":"Point"}
}