{
  "type": "Feature",
  "properties": {
    "iso:country":"HR",
    "name:hrv_x_preferred":[
        "Gornji grad-Medve\u0161\u010dak"
    ],
    "wof:name":"Gornji grad-Medvescak",
    "wof:placetype":"neighbourhood"
},
  "geometry": {"coordinates":[15.9772866537747,45.82746929045692],"type":"Point"}
}