{
  "type": "Feature",
  "properties": {
    "gn:admin1_code":"15.0",
    "gn:admin2_code":"3194113.0",
    "gn:asciiname":"Nemira",
    "gn:country_code":"HR",
    "gn:dem":26,
    "gn:feature_class":"P",
    "gn:feature_code":"PPL",
    "gn:name":"Nemira",
    "gn:population":0,
    "gn:timezone":"Europe/Zagreb",
    "iso:country":"HR",
    "wof:name":"Nemira",
    "wof:placetype":"locality"
},
  "geometry": {"coordinates":[16.71133,43.42121],"type":"Point"}
}