{
  "type": "Feature",
  "properties": {
    "gn:admin1_code":"8.0",
    "gn:asciiname":"Blazevici",
    "gn:country_code":"HR",
    "gn:dem":578,
    "gn:feature_class":"P",
    "gn:feature_code":"PPL",
    "gn:name":"Bla\u017eevi\u0107i",
    "gn:population":0,
    "gn:timezone":"Europe/Zagreb",
    "iso:country":"HR",
    "wof:name":"Blazevici",
    "wof:placetype":"locality"
},
  "geometry": {"coordinates":[15.23333,44.58194],"type":"Point"}
}