{
  "type": "Feature",
  "properties": {
    "gn:admin1_code":"18",
    "gn:admin2_code":"11054545.0",
    "gn:asciiname":"Marinci",
    "gn:country_code":"HR",
    "gn:dem":87,
    "gn:feature_class":"P",
    "gn:feature_code":"PPL",
    "gn:name":"Marinci",
    "gn:population":670,
    "gn:timezone":"Europe/Zagreb",
    "iso:country":"HR",
    "name:bos_x_preferred":[
        "Marinci"
    ],
    "name:ceb_x_preferred":[
        "Marinci"
    ],
    "name:hrv_x_preferred":[
        "Marinci"
    ],
    "name:nld_x_preferred":[
        "Marinci"
    ],
    "name:ron_x_preferred":[
        "Marinci"
    ],
    "name:slv_x_preferred":[
        "Marinci"
    ],
    "name:spa_x_preferred":[
        "Marinci"
    ],
    "name:srp_x_preferred":[
        "\u041c\u0430\u0440\u0438\u043d\u0446\u0438"
    ],
    "name:swe_x_preferred":[
        "Marinci"
    ],
    "name:ukr_x_preferred":[
        "\u041c\u0430\u0440\u0438\u043d\u0446\u0456"
    ],
    "wof:name":"Marinci",
    "wof:placetype":"locality",
    "wof:population":670
},
  "geometry": {"coordinates":[18.89944,45.34],"type":"Point"}
}