{
  "type": "Feature",
  "properties": {
    "gn:admin1_code":"18",
    "gn:admin2_code":"11054545.0",
    "gn:asciiname":"Marinci",
    "gn:country_code":"HR",
    "gn:dem":87,
    "gn:feature_class":"P",
    "gn:feature_code":"PPL",
    "gn:name":"Marinci",
    "gn:population":670,
    "gn:timezone":"Europe/Zagreb",
    "iso:country":"HR",
    "wof:name":"Marinci",
    "wof:placetype":"locality",
    "wof:population":670
},
  "geometry": {"coordinates":[18.89944,45.34],"type":"Point"}
}