{
  "type": "Feature",
  "properties": {
    "gn:admin1_code":"3.0",
    "gn:asciiname":"Strizevo",
    "gn:country_code":"HR",
    "gn:dem":210,
    "gn:feature_class":"P",
    "gn:feature_code":"PPL",
    "gn:name":"Stri\u017eevo",
    "gn:population":0,
    "gn:timezone":"Europe/Zagreb",
    "iso:country":"HR",
    "wof:name":"Strizevo",
    "wof:placetype":"locality"
},
  "geometry": {"coordinates":[17.40444,43.06556],"type":"Point"}
}