{
  "type": "Feature",
  "properties": {
    "gn:admin1_code":"8.0",
    "gn:admin2_code":"11049294.0",
    "gn:asciiname":"Svilari",
    "gn:country_code":"HR",
    "gn:dem":639,
    "gn:feature_class":"P",
    "gn:feature_code":"PPL",
    "gn:name":"Svilari",
    "gn:population":0,
    "gn:timezone":"Europe/Zagreb",
    "iso:country":"HR",
    "wof:name":"Svilari",
    "wof:placetype":"locality"
},
  "geometry": {"coordinates":[15.72583,44.64],"type":"Point"}
}