{
  "type": "Feature",
  "properties": {
    "gn:admin1_code":"15.0",
    "gn:asciiname":"Tolici",
    "gn:country_code":"HR",
    "gn:dem":95,
    "gn:feature_class":"P",
    "gn:feature_code":"PPL",
    "gn:name":"Toli\u0107i",
    "gn:population":0,
    "gn:timezone":"Europe/Zagreb",
    "iso:country":"HR",
    "wof:name":"Tolici",
    "wof:placetype":"locality"
},
  "geometry": {"coordinates":[17.37694,43.22139],"type":"Point"}
}