{
  "type": "Feature",
  "properties": {
    "iso:country":"HR",
    "name:bos_x_preferred":[
        "Humac"
    ],
    "name:ceb_x_preferred":[
        "Humac"
    ],
    "name:fra_x_preferred":[
        "Humac"
    ],
    "name:hrv_x_preferred":[
        "Humac"
    ],
    "name:hun_x_preferred":[
        "Humac"
    ],
    "name:srp_x_preferred":[
        "\u0425\u0443\u043c\u0430\u0446"
    ],
    "name:swe_x_preferred":[
        "Humac"
    ],
    "qs_pg:aaroncc":"HR",
    "qs_pg:name":"Humac",
    "qs_pg:name_adm0":"Hrvatska",
    "qs_pg:name_adm1":"Splitsko-Dalmatinska",
    "qs_pg:photos":46,
    "qs_pg:photos_1k":9,
    "qs_pg:photos_9k":1,
    "qs_pg:photos_9r":2,
    "qs_pg:photos_all":46,
    "qs_pg:photos_sr":2,
    "qs_pg:pop_sr":0,
    "qs_pg:qs_pg_placetype":"locality",
    "qs_pg:qs_pg_placetype_gp":"Town",
    "qs_pg:woe_adm0":23424843,
    "woe:adm0_id":23424843,
    "woe:name_adm0":"Hrvatska",
    "woe:name_adm1":"Splitsko-Dalmatinska",
    "woe:placetype":"Town",
    "wof:name":"Humac",
    "wof:placetype":"locality"
},
  "geometry": {"coordinates":[16.7571965,43.147232],"type":"Point"}
}