{
  "type": "Feature",
  "properties": {
    "gn:admin1_code":"8.0",
    "gn:asciiname":"Radakovici",
    "gn:country_code":"HR",
    "gn:dem":560,
    "gn:feature_class":"P",
    "gn:feature_code":"PPL",
    "gn:name":"Radakovi\u0107i",
    "gn:population":0,
    "gn:timezone":"Europe/Zagreb",
    "iso:country":"HR",
    "wof:name":"Radakovici",
    "wof:placetype":"locality"
},
  "geometry": {"coordinates":[15.35639,44.50278],"type":"Point"}
}