{
  "type": "Feature",
  "properties": {
    "gn:admin1_code":"5.0",
    "gn:admin2_code":"11049273.0",
    "gn:asciiname":"Durici",
    "gn:country_code":"HR",
    "gn:dem":129,
    "gn:feature_class":"P",
    "gn:feature_code":"PPL",
    "gn:name":"Duri\u0107i",
    "gn:population":0,
    "gn:timezone":"Europe/Zagreb",
    "iso:country":"HR",
    "wof:name":"Durici",
    "wof:placetype":"locality"
},
  "geometry": {"coordinates":[15.60444,45.37083],"type":"Point"}
}