{
  "type": "Feature",
  "properties": {
    "gn:admin1_code":"10",
    "gn:admin2_code":"11054394.0",
    "gn:asciiname":"Mitrovac",
    "gn:cc2":"HR",
    "gn:country_code":"HR",
    "gn:dem":86,
    "gn:feature_class":"P",
    "gn:feature_code":"PPL",
    "gn:name":"Mitrovac",
    "gn:population":20,
    "gn:timezone":"Europe/Zagreb",
    "iso:country":"HR",
    "name:und_x_variant":[
        "Mitrovac Pustara",
        "Mitrovac"
    ],
    "wof:name":"Mitrovac",
    "wof:placetype":"locality",
    "wof:population":20
},
  "geometry": {"coordinates":[18.7225,45.71111],"type":"Point"}
}