{
  "type": "Feature",
  "properties": {
    "gn:admin1_code":"10",
    "gn:admin2_code":"11054394.0",
    "gn:asciiname":"Mitrovac",
    "gn:cc2":"HR",
    "gn:country_code":"HR",
    "gn:dem":86,
    "gn:feature_class":"P",
    "gn:feature_code":"PPL",
    "gn:name":"Mitrovac",
    "gn:population":20,
    "gn:timezone":"Europe/Zagreb",
    "iso:country":"HR",
    "name:bos_x_preferred":[
        "Mitrovac"
    ],
    "name:fra_x_preferred":[
        "Mitrovac"
    ],
    "name:hrv_x_preferred":[
        "Mitrovac"
    ],
    "name:nld_x_preferred":[
        "Mitrovac"
    ],
    "name:slv_x_preferred":[
        "Mitrovac"
    ],
    "name:srp_x_preferred":[
        "\u041c\u0438\u0442\u0440\u043e\u0432\u0430\u0446"
    ],
    "name:und_x_variant":[
        "Mitrovac Pustara"
    ],
    "wof:name":"Mitrovac",
    "wof:placetype":"locality",
    "wof:population":20
},
  "geometry": {"coordinates":[18.7225,45.71111],"type":"Point"}
}