{
  "type": "Feature",
  "properties": {
    "gn:admin1_code":"15.0",
    "gn:asciiname":"Rudezi",
    "gn:country_code":"HR",
    "gn:dem":687,
    "gn:feature_class":"P",
    "gn:feature_code":"PPL",
    "gn:name":"Rude\u017ei",
    "gn:population":0,
    "gn:timezone":"Europe/Zagreb",
    "iso:country":"HR",
    "wof:name":"Rudezi",
    "wof:placetype":"locality"
},
  "geometry": {"coordinates":[17.25639,43.31306],"type":"Point"}
}