{
  "type": "Feature",
  "properties": {
    "gn:admin1_code":"16",
    "gn:admin2_code":"3188382.0",
    "gn:asciiname":"Zbelava",
    "gn:country_code":"HR",
    "gn:dem":164,
    "gn:feature_class":"P",
    "gn:feature_code":"PPL",
    "gn:name":"Zbelava",
    "gn:population":504,
    "gn:timezone":"Europe/Zagreb",
    "iso:country":"HR",
    "wof:name":"Zbelava",
    "wof:placetype":"locality",
    "wof:population":504
},
  "geometry": {"coordinates":[16.40917,46.28444],"type":"Point"}
}