{
  "type": "Feature",
  "properties": {
    "gn:admin1_code":"16",
    "gn:admin2_code":"3188382.0",
    "gn:asciiname":"Zbelava",
    "gn:country_code":"HR",
    "gn:dem":164,
    "gn:feature_class":"P",
    "gn:feature_code":"PPL",
    "gn:name":"Zbelava",
    "gn:population":504,
    "gn:timezone":"Europe/Zagreb",
    "iso:country":"HR",
    "name:bos_x_preferred":[
        "Zbelava"
    ],
    "name:hrv_x_preferred":[
        "Zbelava"
    ],
    "name:hun_x_preferred":[
        "Zbelava"
    ],
    "name:nld_x_preferred":[
        "Zbelava"
    ],
    "name:slv_x_preferred":[
        "Zbelava"
    ],
    "name:spa_x_preferred":[
        "Zbelava"
    ],
    "name:srp_x_preferred":[
        "\u0417\u0431\u0435\u043b\u0430\u0432\u0430"
    ],
    "name:ukr_x_preferred":[
        "\u0417\u0431\u0435\u043b\u0430\u0432\u0430"
    ],
    "wof:name":"Zbelava",
    "wof:placetype":"locality",
    "wof:population":504
},
  "geometry": {"coordinates":[16.40917,46.28444],"type":"Point"}
}