{
  "type": "Feature",
  "properties": {
    "gn:admin1_code":"03",
    "gn:admin2_code":"11054961.0",
    "gn:asciiname":"Prapratna",
    "gn:cc2":"HR",
    "gn:country_code":"HR",
    "gn:dem":52,
    "gn:feature_class":"P",
    "gn:feature_code":"PPL",
    "gn:name":"Prapratna",
    "gn:population":0,
    "gn:timezone":"Europe/Zagreb",
    "iso:country":"HR",
    "name:und_x_variant":[
        "Prapratno",
        "Prapatno",
        "Prapratna"
    ],
    "wof:name":"Prapratna",
    "wof:placetype":"locality"
},
  "geometry": {"coordinates":[17.67611,42.81889],"type":"Point"}
}