{
  "type": "Feature",
  "properties": {
    "gn:country":"HR",
    "gn:fcode":"PPL",
    "gn:population":989,
    "iso:country":"HR",
    "qs_pg:aaroncc":"HR",
    "qs_pg:gn_country":"HR",
    "qs_pg:gn_fcode":"PPL",
    "qs_pg:gn_pop":989,
    "qs_pg:name":"Bresta\u010da",
    "qs_pg:name_adm0":"Hrvatska",
    "qs_pg:name_adm1":"Sisa\u010dko-moslava\u010dka",
    "qs_pg:photos_9r":0,
    "qs_pg:photos_sr":0,
    "qs_pg:pop_sr":2,
    "qs_pg:qs_pg_placetype":"locality",
    "qs_pg:qs_pg_placetype_gp":"Town",
    "qs_pg:woe_adm0":23424843,
    "woe:adm0_id":23424843,
    "woe:name_adm0":"Hrvatska",
    "woe:name_adm1":"Sisa\u010dko-moslava\u010dka",
    "woe:placetype":"Town",
    "wof:name":"Bresta\u010da",
    "wof:placetype":"locality",
    "wof:population":913
},
  "geometry": {"coordinates":[16.95861,45.35639],"type":"Point"}
}