{
  "type": "Feature",
  "properties": {
    "gn:admin1_code":"5.0",
    "gn:admin2_code":"3190522.0",
    "gn:asciiname":"Salopek Luke",
    "gn:country_code":"HR",
    "gn:dem":270,
    "gn:feature_class":"P",
    "gn:feature_code":"PPL",
    "gn:name":"Salopek Luke",
    "gn:population":0,
    "gn:timezone":"Europe/Zagreb",
    "iso:country":"HR",
    "wof:name":"Salopek Luke",
    "wof:placetype":"locality"
},
  "geometry": {"coordinates":[15.69694,45.09917],"type":"Point"}
}