{
  "type": "Feature",
  "properties": {
    "gn:admin1_code":"5.0",
    "gn:admin2_code":"3190522.0",
    "gn:asciiname":"Salopek Luke",
    "gn:country_code":"HR",
    "gn:dem":270,
    "gn:feature_class":"P",
    "gn:feature_code":"PPL",
    "gn:name":"Salopek Luke",
    "gn:population":0,
    "gn:timezone":"Europe/Zagreb",
    "iso:country":"HR",
    "name:bos_x_preferred":[
        "Salopek Luke"
    ],
    "name:hrv_x_preferred":[
        "Salopek Luke"
    ],
    "name:hun_x_preferred":[
        "Salopek Luke"
    ],
    "name:nld_x_preferred":[
        "Salopek Luke"
    ],
    "name:slv_x_preferred":[
        "Salopek Luke"
    ],
    "name:spa_x_preferred":[
        "Salopek Luke"
    ],
    "name:srp_x_preferred":[
        "\u0421\u0430\u043b\u043e\u043f\u0435\u043a \u041b\u0443\u043a\u0435"
    ],
    "name:ukr_x_preferred":[
        "\u0421\u0430\u043b\u043e\u043f\u0435\u043a-\u041b\u0443\u043a\u0435"
    ],
    "wof:name":"Salopek Luke",
    "wof:placetype":"locality"
},
  "geometry": {"coordinates":[15.69694,45.09917],"type":"Point"}
}