{
  "type": "Feature",
  "properties": {
    "gn:admin1_code":"4.0",
    "gn:admin2_code":"11054810.0",
    "gn:asciiname":"Sveti Bartol",
    "gn:country_code":"HR",
    "gn:dem":156,
    "gn:elevation":"0.0",
    "gn:feature_class":"P",
    "gn:feature_code":"PPL",
    "gn:name":"Sveti Bartol",
    "gn:population":0,
    "gn:timezone":"Europe/Zagreb",
    "iso:country":"HR",
    "wof:name":"Sveti Bartol",
    "wof:placetype":"locality"
},
  "geometry": {"coordinates":[13.85934,45.33723],"type":"Point"}
}