{
  "type": "Feature",
  "properties": {
    "gn:gn_country":"HR",
    "gn:gn_fcode":"PPL",
    "gn:gn_pop":0,
    "iso:country":"HR",
    "name:bos_x_preferred":[
        "Kolan"
    ],
    "name:dut_x_preferred":[
        "Kolan"
    ],
    "name:eng_x_preferred":[
        "Kolan"
    ],
    "name:fre_x_preferred":[
        "Kolan"
    ],
    "name:ger_x_preferred":[
        "Kolan"
    ],
    "name:hrv_x_preferred":[
        "Kolan"
    ],
    "name:hun_x_preferred":[
        "Kolan"
    ],
    "name:ita_x_preferred":[
        "Colane"
    ],
    "name:rum_x_preferred":[
        "Comuna Kolan"
    ],
    "name:slv_x_preferred":[
        "Kolan"
    ],
    "name:spa_x_preferred":[
        "Kolan"
    ],
    "name:srp_x_preferred":[
        "\u041a\u043e\u043b\u0430\u043d"
    ],
    "name:unk_x_variant":[
        "Kolane"
    ],
    "qs_pg:aaroncc":"HR",
    "qs_pg:gn_country":"HR",
    "qs_pg:gn_fcode":"PPL",
    "qs_pg:gn_pop":0,
    "qs_pg:name":"Kolan",
    "qs_pg:name_adm0":"Hrvatska",
    "qs_pg:name_adm1":"Zadarsko-Kninska",
    "qs_pg:photos":216,
    "qs_pg:photos_1k":44,
    "qs_pg:photos_9k":1,
    "qs_pg:photos_9r":4,
    "qs_pg:photos_all":216,
    "qs_pg:photos_sr":4,
    "qs_pg:pop_sr":0,
    "qs_pg:qs_pg_placetype":"locality",
    "qs_pg:qs_pg_placetype_gp":"Town",
    "qs_pg:woe_adm0":23424843,
    "woe:adm0_id":23424843,
    "woe:name_adm0":"Hrvatska",
    "woe:name_adm1":"Zadarsko-Kninska",
    "woe:placetype":"Town",
    "wof:name":"Kolan",
    "wof:placetype":"locality"
},
  "geometry": {"coordinates":[14.96139,44.49417],"type":"Point"}
}