{
  "type": "Feature",
  "properties": {
    "gn:admin1_code":"12.0",
    "gn:admin2_code":"3187256.0",
    "gn:asciiname":"Mlinari Vucinci",
    "gn:country_code":"HR",
    "gn:dem":425,
    "gn:feature_class":"P",
    "gn:feature_code":"PPL",
    "gn:name":"Mlinari Vu\u010dinci",
    "gn:population":0,
    "gn:timezone":"Europe/Zagreb",
    "iso:country":"HR",
    "wof:name":"Mlinari Vucinci",
    "wof:placetype":"locality"
},
  "geometry": {"coordinates":[15.03333,45.41306],"type":"Point"}
}