{
  "type": "Feature",
  "properties": {
    "gn:admin1_code":"15.0",
    "gn:asciiname":"Grgetici",
    "gn:country_code":"HR",
    "gn:dem":304,
    "gn:feature_class":"P",
    "gn:feature_code":"PPL",
    "gn:name":"Grgeti\u0107i",
    "gn:population":0,
    "gn:timezone":"Europe/Zagreb",
    "iso:country":"HR",
    "wof:name":"Grgetici",
    "wof:placetype":"locality"
},
  "geometry": {"coordinates":[16.74111,43.67833],"type":"Point"}
}