{
  "type": "Feature",
  "properties": {
    "gn:admin1_code":"8.0",
    "gn:asciiname":"Karavla",
    "gn:country_code":"HR",
    "gn:dem":248,
    "gn:feature_class":"P",
    "gn:feature_code":"PPL",
    "gn:name":"Karavla",
    "gn:population":0,
    "gn:timezone":"Europe/Zagreb",
    "iso:country":"HR",
    "wof:name":"Karavla",
    "wof:placetype":"locality"
},
  "geometry": {"coordinates":[14.99,44.59972],"type":"Point"}
}