{
  "type": "Feature",
  "properties": {
    "gn:admin1_code":"07",
    "gn:asciiname":"Vrbovo",
    "gn:country_code":"HR",
    "gn:dem":203,
    "gn:feature_class":"P",
    "gn:feature_code":"PPL",
    "gn:name":"Vrbovo",
    "gn:population":292,
    "gn:timezone":"Europe/Zagreb",
    "iso:country":"HR",
    "name:bos_x_preferred":[
        "Vrbovo"
    ],
    "name:ceb_x_preferred":[
        "Vrbovo"
    ],
    "name:hrv_x_preferred":[
        "Vrbovo"
    ],
    "name:nld_x_preferred":[
        "Vrbovo"
    ],
    "name:pol_x_preferred":[
        "Vrbovo"
    ],
    "name:ron_x_preferred":[
        "Vrbovo"
    ],
    "name:slv_x_preferred":[
        "Vrbovo"
    ],
    "name:ukr_x_preferred":[
        "\u0412\u0440\u0431\u043e\u0432\u043e"
    ],
    "wof:name":"Vrbovo",
    "wof:placetype":"locality",
    "wof:population":292
},
  "geometry": {"coordinates":[16.06667,46.08333],"type":"Point"}
}