{
  "type": "Feature",
  "properties": {
    "gn:admin1_code":"07",
    "gn:asciiname":"Vrbovo",
    "gn:country_code":"HR",
    "gn:dem":203,
    "gn:feature_class":"P",
    "gn:feature_code":"PPL",
    "gn:name":"Vrbovo",
    "gn:population":292,
    "gn:timezone":"Europe/Zagreb",
    "iso:country":"HR",
    "wof:name":"Vrbovo",
    "wof:placetype":"locality",
    "wof:population":292
},
  "geometry": {"coordinates":[16.06667,46.08333],"type":"Point"}
}