{
  "type": "Feature",
  "properties": {
    "gn:admin1_code":"15.0",
    "gn:asciiname":"Poduba",
    "gn:country_code":"HR",
    "gn:dem":1036,
    "gn:feature_class":"P",
    "gn:feature_code":"PPL",
    "gn:name":"Poduba",
    "gn:population":0,
    "gn:timezone":"Europe/Zagreb",
    "iso:country":"HR",
    "wof:name":"Poduba",
    "wof:placetype":"locality"
},
  "geometry": {"coordinates":[16.90556,43.66639],"type":"Point"}
}