{
  "type": "Feature",
  "properties": {
    "gn:admin1_code":"19.0",
    "gn:asciiname":"Gornja Omsica",
    "gn:country_code":"HR",
    "gn:dem":812,
    "gn:feature_class":"P",
    "gn:feature_code":"PPL",
    "gn:name":"Gornja Omsica",
    "gn:population":0,
    "gn:timezone":"Europe/Zagreb",
    "iso:country":"HR",
    "wof:name":"Gornja Omsica",
    "wof:placetype":"locality"
},
  "geometry": {"coordinates":[15.93778,44.36889],"type":"Point"}
}