{
  "type": "Feature",
  "properties": {
    "gn:admin1_code":"15.0",
    "gn:asciiname":"Graborac",
    "gn:country_code":"HR",
    "gn:dem":485,
    "gn:feature_class":"P",
    "gn:feature_code":"PPL",
    "gn:name":"Graborac",
    "gn:population":0,
    "gn:timezone":"Europe/Zagreb",
    "iso:country":"HR",
    "wof:name":"Graborac",
    "wof:placetype":"locality"
},
  "geometry": {"coordinates":[17.03139,43.455],"type":"Point"}
}