{
  "type": "Feature",
  "properties": {
    "gn:admin1_code":"8.0",
    "gn:admin2_code":"11049295.0",
    "gn:asciiname":"Zivulja",
    "gn:country_code":"HR",
    "gn:dem":927,
    "gn:feature_class":"P",
    "gn:feature_code":"PPL",
    "gn:name":"\u017divulja",
    "gn:population":0,
    "gn:timezone":"Europe/Zagreb",
    "iso:country":"HR",
    "wof:name":"Zivulja",
    "wof:placetype":"locality"
},
  "geometry": {"coordinates":[15.52917,44.76194],"type":"Point"}
}