{
  "type": "Feature",
  "properties": {
    "gn:admin1_code":"15.0",
    "gn:asciiname":"Vrcani",
    "gn:country_code":"HR",
    "gn:dem":377,
    "gn:feature_class":"P",
    "gn:feature_code":"PPL",
    "gn:name":"Vrcani",
    "gn:population":0,
    "gn:timezone":"Europe/Zagreb",
    "iso:country":"HR",
    "wof:name":"Vrcani",
    "wof:placetype":"locality"
},
  "geometry": {"coordinates":[16.7625,43.56444000000001],"type":"Point"}
}