{
  "type": "Feature",
  "properties": {
    "gn:admin1_code":"4.0",
    "gn:admin2_code":"11054818.0",
    "gn:asciiname":"Heraki",
    "gn:country_code":"HR",
    "gn:dem":257,
    "gn:elevation":"0.0",
    "gn:feature_class":"P",
    "gn:feature_code":"PPL",
    "gn:name":"Heraki",
    "gn:population":18,
    "gn:timezone":"Europe/Zagreb",
    "iso:country":"HR",
    "wof:name":"Heraki",
    "wof:placetype":"locality",
    "wof:population":18
},
  "geometry": {"coordinates":[13.76143,45.1899],"type":"Point"}
}