{
  "type": "Feature",
  "properties": {
    "gn:admin1_code":"17",
    "gn:admin2_code":"11049467.0",
    "gn:asciiname":"Grabic",
    "gn:country_code":"HR",
    "gn:dem":103,
    "gn:feature_class":"P",
    "gn:feature_code":"PPL",
    "gn:name":"Grabi\u0107",
    "gn:population":122,
    "gn:timezone":"Europe/Zagreb",
    "iso:country":"HR",
    "wof:name":"Grabic",
    "wof:placetype":"locality",
    "wof:population":122
},
  "geometry": {"coordinates":[17.7275,45.74778],"type":"Point"}
}