{
  "type": "Feature",
  "properties": {
    "gn:gn_country":"HR",
    "gn:gn_fcode":"PPL",
    "gn:gn_pop":0,
    "gn:population":164,
    "iso:country":"HR",
    "qs_pg:aaroncc":"HR",
    "qs_pg:gn_country":"HR",
    "qs_pg:gn_fcode":"PPL",
    "qs_pg:gn_pop":0,
    "qs_pg:name":"Drinovci",
    "qs_pg:name_adm0":"Hrvatska",
    "qs_pg:name_adm1":"Sibenska",
    "qs_pg:photos":193,
    "qs_pg:photos_1k":39,
    "qs_pg:photos_9k":1,
    "qs_pg:photos_9r":4,
    "qs_pg:photos_all":193,
    "qs_pg:photos_sr":4,
    "qs_pg:pop_sr":0,
    "qs_pg:qs_pg_placetype":"locality",
    "qs_pg:qs_pg_placetype_gp":"Town",
    "qs_pg:woe_adm0":23424843,
    "woe:adm0_id":23424843,
    "woe:name_adm0":"Hrvatska",
    "woe:name_adm1":"Sibenska",
    "woe:placetype":"Town",
    "wof:name":"Drinovci",
    "wof:placetype":"locality",
    "wof:population":164
},
  "geometry": {"coordinates":[16.01806,43.85278],"type":"Point"}
}