{
  "type": "Feature",
  "properties": {
    "gn:admin1_code":"15.0",
    "gn:asciiname":"Corici",
    "gn:country_code":"HR",
    "gn:dem":370,
    "gn:feature_class":"P",
    "gn:feature_code":"PPL",
    "gn:name":"\u010cori\u0107i",
    "gn:population":0,
    "gn:timezone":"Europe/Zagreb",
    "iso:country":"HR",
    "wof:name":"Corici",
    "wof:placetype":"locality"
},
  "geometry": {"coordinates":[16.76333,43.52917],"type":"Point"}
}