{
  "type": "Feature",
  "properties": {
    "gn:admin1_code":"8.0",
    "gn:asciiname":"Mala Kapela",
    "gn:country_code":"HR",
    "gn:dem":804,
    "gn:feature_class":"P",
    "gn:feature_code":"PPL",
    "gn:name":"Mala Kapela",
    "gn:population":0,
    "gn:timezone":"Europe/Zagreb",
    "iso:country":"HR",
    "name:ceb_x_preferred":[
        "Mala Kapela"
    ],
    "name:deu_x_preferred":[
        "Kapela"
    ],
    "name:fra_x_preferred":[
        "Mala Kapela"
    ],
    "name:hrv_x_preferred":[
        "Mala Kapela"
    ],
    "name:nld_x_preferred":[
        "Kleine Kapela"
    ],
    "name:nor_x_preferred":[
        "Mala Kapela"
    ],
    "name:pol_x_preferred":[
        "Ma\u0142a Kapela"
    ],
    "name:slv_x_preferred":[
        "Mala Kapela"
    ],
    "name:srp_x_preferred":[
        "\u041c\u0430\u043b\u0430 \u041a\u0430\u043f\u0435\u043b\u0430"
    ],
    "name:swe_x_preferred":[
        "Mala Kapela"
    ],
    "wof:name":"Mala Kapela",
    "wof:placetype":"locality"
},
  "geometry": {"coordinates":[15.39833,44.97528],"type":"Point"}
}