{
  "type": "Feature",
  "properties": {
    "gn:admin1_code":"8.0",
    "gn:asciiname":"Mala Kapela",
    "gn:country_code":"HR",
    "gn:dem":804,
    "gn:feature_class":"P",
    "gn:feature_code":"PPL",
    "gn:name":"Mala Kapela",
    "gn:population":0,
    "gn:timezone":"Europe/Zagreb",
    "iso:country":"HR",
    "wof:name":"Mala Kapela",
    "wof:placetype":"locality"
},
  "geometry": {"coordinates":[15.39833,44.97528],"type":"Point"}
}