{
  "type": "Feature",
  "properties": {
    "gn:admin1_code":"04",
    "gn:asciiname":"Brdo",
    "gn:cc2":"HR",
    "gn:country_code":"HR",
    "gn:dem":369,
    "gn:feature_class":"P",
    "gn:feature_code":"PPL",
    "gn:name":"Brdo",
    "gn:population":0,
    "gn:timezone":"Europe/Zagreb",
    "iso:country":"HR",
    "name:und_x_variant":[
        "Collalto",
        "Brda",
        "Brdo"
    ],
    "wof:name":"Brdo",
    "wof:placetype":"locality"
},
  "geometry": {"coordinates":[13.76111,45.44722],"type":"Point"}
}