{
  "type": "Feature",
  "properties": {
    "gn:admin1_code":"15.0",
    "gn:asciiname":"Krzanici",
    "gn:country_code":"HR",
    "gn:dem":190,
    "gn:feature_class":"P",
    "gn:feature_code":"PPL",
    "gn:name":"Kr\u017eani\u0107i",
    "gn:population":0,
    "gn:timezone":"Europe/Zagreb",
    "iso:country":"HR",
    "wof:name":"Krzanici",
    "wof:placetype":"locality"
},
  "geometry": {"coordinates":[17.08902,43.23798],"type":"Point"}
}