{
  "type": "Feature",
  "properties": {
    "gn:admin1_code":"13.0",
    "gn:asciiname":"Kurajice",
    "gn:country_code":"HR",
    "gn:dem":890,
    "gn:feature_class":"P",
    "gn:feature_code":"PPL",
    "gn:name":"Kurajice",
    "gn:population":0,
    "gn:timezone":"Europe/Zagreb",
    "iso:country":"HR",
    "wof:name":"Kurajice",
    "wof:placetype":"locality"
},
  "geometry": {"coordinates":[16.22556,44.18806],"type":"Point"}
}