{
  "type": "Feature",
  "properties": {
    "gn:country":"HR",
    "gn:fcode":"PPL",
    "gn:population":993,
    "iso:country":"HR",
    "name:bos_x_preferred":[
        "Zadubravlje"
    ],
    "name:ceb_x_preferred":[
        "Zadubravlje"
    ],
    "name:eng_x_preferred":[
        "Zadubravlje"
    ],
    "name:hrv_x_preferred":[
        "Zadubravlje"
    ],
    "name:nld_x_preferred":[
        "Zadubravlje"
    ],
    "name:slv_x_preferred":[
        "Zadubravlje"
    ],
    "name:srp_x_preferred":[
        "\u0417\u0430\u0434\u0443\u0431\u0440\u0430\u0432\u0459\u0435"
    ],
    "name:swe_x_preferred":[
        "Zadubravlje"
    ],
    "name:ukr_x_preferred":[
        "\u0417\u0430\u0434\u0443\u0431\u0440\u0430\u0432\u043b\u0454"
    ],
    "name:und_x_variant":[
        "Zadubravje"
    ],
    "qs_pg:aaroncc":"HR",
    "qs_pg:gn_country":"HR",
    "qs_pg:gn_fcode":"PPL",
    "qs_pg:gn_pop":993,
    "qs_pg:name":"Zadubravlje",
    "qs_pg:name_adm0":"Hrvatska",
    "qs_pg:name_adm1":"Brodsko-Posavska",
    "qs_pg:photos_9r":0,
    "qs_pg:photos_sr":0,
    "qs_pg:pop_sr":2,
    "qs_pg:qs_pg_placetype":"locality",
    "qs_pg:qs_pg_placetype_gp":"Town",
    "qs_pg:woe_adm0":23424843,
    "woe:adm0_id":23424843,
    "woe:name_adm0":"Hrvatska",
    "woe:name_adm1":"Brodsko-Posavska",
    "woe:placetype":"Town",
    "wof:name":"Zadubravlje",
    "wof:placetype":"locality",
    "wof:population":912
},
  "geometry": {"coordinates":[18.15444,45.16361],"type":"Point"}
}