{
  "type": "Feature",
  "properties": {
    "gn:admin1_code":"15.0",
    "gn:asciiname":"Zivulje",
    "gn:country_code":"HR",
    "gn:dem":612,
    "gn:feature_class":"P",
    "gn:feature_code":"PPL",
    "gn:name":"\u017divulje",
    "gn:population":0,
    "gn:timezone":"Europe/Zagreb",
    "iso:country":"HR",
    "wof:name":"Zivulje",
    "wof:placetype":"locality"
},
  "geometry": {"coordinates":[16.77972,43.70528],"type":"Point"}
}