{
  "type": "Feature",
  "properties": {
    "gn:admin1_code":"15.0",
    "gn:asciiname":"Basici",
    "gn:country_code":"HR",
    "gn:dem":431,
    "gn:feature_class":"P",
    "gn:feature_code":"PPL",
    "gn:name":"Basi\u0107i",
    "gn:population":0,
    "gn:timezone":"Europe/Zagreb",
    "iso:country":"HR",
    "wof:name":"Basici",
    "wof:placetype":"locality"
},
  "geometry": {"coordinates":[16.52194,43.57528],"type":"Point"}
}