{
  "type": "Feature",
  "properties": {
    "gn:admin1_code":"11.0",
    "gn:admin2_code":"11049475.0",
    "gn:asciiname":"Besinci",
    "gn:country_code":"HR",
    "gn:dem":321,
    "gn:feature_class":"P",
    "gn:feature_code":"PPL",
    "gn:name":"Be\u0161inci",
    "gn:population":88,
    "gn:timezone":"Europe/Zagreb",
    "iso:country":"HR",
    "wof:name":"Besinci",
    "wof:placetype":"locality",
    "wof:population":88
},
  "geometry": {"coordinates":[17.75639,45.44444],"type":"Point"}
}