{
  "type": "Feature",
  "properties": {
    "gn:admin1_code":"08",
    "gn:admin2_code":"11049290.0",
    "gn:asciiname":"Covici",
    "gn:country_code":"HR",
    "gn:dem":456,
    "gn:feature_class":"P",
    "gn:feature_code":"PPL",
    "gn:name":"\u010covi\u0107i",
    "gn:population":560,
    "gn:timezone":"Europe/Zagreb",
    "iso:country":"HR",
    "name:bos_x_preferred":[
        "\u010covi\u0107i"
    ],
    "name:hrv_x_preferred":[
        "\u010covi\u0107i"
    ],
    "name:hun_x_preferred":[
        "\u010covi\u0107i"
    ],
    "name:nld_x_preferred":[
        "\u010covi\u0107i"
    ],
    "name:slv_x_preferred":[
        "\u010covi\u0107i"
    ],
    "name:spa_x_preferred":[
        "\u010covi\u0107i"
    ],
    "name:srp_x_preferred":[
        "\u0427\u043e\u0432\u0438\u045b\u0438"
    ],
    "name:ukr_x_preferred":[
        "\u0413\u043e\u0432\u0438\u0447\u0456"
    ],
    "wof:name":"Covici",
    "wof:placetype":"locality",
    "wof:population":560
},
  "geometry": {"coordinates":[15.30111,44.82778],"type":"Point"}
}