{
  "type": "Feature",
  "properties": {
    "gn:admin1_code":"08",
    "gn:admin2_code":"11049290.0",
    "gn:asciiname":"Covici",
    "gn:country_code":"HR",
    "gn:dem":456,
    "gn:feature_class":"P",
    "gn:feature_code":"PPL",
    "gn:name":"\u010covi\u0107i",
    "gn:population":560,
    "gn:timezone":"Europe/Zagreb",
    "iso:country":"HR",
    "name:und_x_variant":[
        "\u010covi\u0107i"
    ],
    "wof:name":"Covici",
    "wof:placetype":"locality",
    "wof:population":560
},
  "geometry": {"coordinates":[15.30111,44.82778],"type":"Point"}
}