{
  "type": "Feature",
  "properties": {
    "gn:country":"HR",
    "gn:fcode":"PPL",
    "gn:population":816,
    "iso:country":"HR",
    "name:bos_x_preferred":[
        "Hrastovsko"
    ],
    "name:bul_x_preferred":[
        "\u0425\u0440\u0430\u0441\u0442\u043e\u0432\u0441\u043a\u043e"
    ],
    "name:ceb_x_preferred":[
        "Hrastovsko"
    ],
    "name:eng_x_preferred":[
        "Hrastovsko"
    ],
    "name:hrv_x_preferred":[
        "Hrastovsko"
    ],
    "name:hun_x_preferred":[
        "Hrastovsko"
    ],
    "name:nld_x_preferred":[
        "Hrastovsko"
    ],
    "name:slv_x_preferred":[
        "Hrastovsko"
    ],
    "name:spa_x_preferred":[
        "Hrastovsko"
    ],
    "name:srp_x_preferred":[
        "\u0425\u0440\u0430\u0441\u0442\u043e\u0432\u0441\u043a\u043e"
    ],
    "name:swe_x_preferred":[
        "Hrastovsko"
    ],
    "name:ukr_x_preferred":[
        "\u0425\u0440\u0430\u0441\u0442\u043e\u0432\u0441\u044c\u043a\u043e"
    ],
    "qs_pg:aaroncc":"HR",
    "qs_pg:gn_country":"HR",
    "qs_pg:gn_fcode":"PPL",
    "qs_pg:gn_pop":816,
    "qs_pg:name":"Hrastovsko",
    "qs_pg:name_adm0":"Hrvatska",
    "qs_pg:name_adm1":"Vara\u017edinska",
    "qs_pg:photos_9r":0,
    "qs_pg:photos_sr":0,
    "qs_pg:pop_sr":2,
    "qs_pg:qs_pg_placetype":"locality",
    "qs_pg:qs_pg_placetype_gp":"Town",
    "qs_pg:woe_adm0":23424843,
    "woe:adm0_id":23424843,
    "woe:name_adm0":"Hrvatska",
    "woe:name_adm1":"Vara\u017edinska",
    "woe:placetype":"Town",
    "wof:name":"Hrastovsko",
    "wof:placetype":"locality",
    "wof:population":760
},
  "geometry": {"coordinates":[16.58444,46.24917],"type":"Point"}
}