{
  "type": "Feature",
  "properties": {
    "gn:admin1_code":"05",
    "gn:admin2_code":"11049267.0",
    "gn:asciiname":"Umol",
    "gn:country_code":"HR",
    "gn:dem":234,
    "gn:feature_class":"P",
    "gn:feature_code":"PPL",
    "gn:name":"Umol",
    "gn:population":37,
    "gn:timezone":"Europe/Zagreb",
    "iso:country":"HR",
    "wof:name":"Umol",
    "wof:placetype":"locality",
    "wof:population":37
},
  "geometry": {"coordinates":[15.31667,45.36667],"type":"Point"}
}