{
  "type": "Feature",
  "properties": {
    "gn:admin1_code":"14.0",
    "gn:admin2_code":"3193419.0",
    "gn:asciiname":"Donja Pastusa",
    "gn:country_code":"HR",
    "gn:dem":282,
    "gn:feature_class":"P",
    "gn:feature_code":"PPL",
    "gn:name":"Donja Pastu\u0161a",
    "gn:population":11,
    "gn:timezone":"Europe/Zagreb",
    "iso:country":"HR",
    "wof:name":"Donja Pastusa",
    "wof:placetype":"locality",
    "wof:population":11
},
  "geometry": {"coordinates":[16.35861,45.3125],"type":"Point"}
}