{
  "type": "Feature",
  "properties": {
    "gn:country":"HR",
    "gn:fcode":"PPL",
    "gn:population":2366,
    "iso:country":"HR",
    "name:afr_x_preferred":[
        "Brodarica"
    ],
    "name:bos_x_preferred":[
        "Brodarica"
    ],
    "name:cat_x_preferred":[
        "Brodarica"
    ],
    "name:ceb_x_preferred":[
        "Brodarica"
    ],
    "name:ces_x_preferred":[
        "Brodarica"
    ],
    "name:deu_x_preferred":[
        "Brodarica"
    ],
    "name:eng_x_preferred":[
        "Brodarica"
    ],
    "name:fra_x_preferred":[
        "Brodarica"
    ],
    "name:hrv_x_preferred":[
        "Brodarica"
    ],
    "name:hun_x_preferred":[
        "Brodarica"
    ],
    "name:nld_x_preferred":[
        "Brodarica"
    ],
    "name:pol_x_preferred":[
        "Brodarica"
    ],
    "name:slk_x_preferred":[
        "Brodarica"
    ],
    "name:slv_x_preferred":[
        "Brodarica"
    ],
    "name:spa_x_preferred":[
        "Brodarica"
    ],
    "name:sqi_x_preferred":[
        "Brodarica"
    ],
    "name:srp_x_preferred":[
        "\u0411\u0440\u043e\u0434\u0430\u0440\u0438\u0446\u0430"
    ],
    "name:swe_x_preferred":[
        "Brodarica"
    ],
    "name:ukr_x_preferred":[
        "\u0411\u0440\u043e\u0434\u0430\u0440\u0438\u0446\u044f"
    ],
    "name:und_x_variant":[
        "Lusa"
    ],
    "qs_pg:aaroncc":"HR",
    "qs_pg:gn_country":"HR",
    "qs_pg:gn_fcode":"PPL",
    "qs_pg:gn_pop":2366,
    "qs_pg:name":"Brodarica",
    "qs_pg:name_adm0":"Hrvatska",
    "qs_pg:name_adm1":"Sibenska",
    "qs_pg:photos":109,
    "qs_pg:photos_1k":22,
    "qs_pg:photos_9k":1,
    "qs_pg:photos_9r":3,
    "qs_pg:photos_all":109,
    "qs_pg:photos_sr":3,
    "qs_pg:pop_sr":4,
    "qs_pg:qs_pg_placetype":"locality",
    "qs_pg:qs_pg_placetype_gp":"Town",
    "qs_pg:woe_adm0":23424843,
    "woe:adm0_id":23424843,
    "woe:name_adm0":"Hrvatska",
    "woe:name_adm1":"Sibenska",
    "woe:placetype":"Town",
    "wof:name":"Brodarica",
    "wof:placetype":"locality",
    "wof:population":2534
},
  "geometry": {"coordinates":[15.91972,43.68],"type":"Point"}
}