{
  "type": "Feature",
  "properties": {
    "gn:admin1_code":"13",
    "gn:admin2_code":"3190938.0",
    "gn:asciiname":"Radonic",
    "gn:country_code":"HR",
    "gn:dem":227,
    "gn:feature_class":"P",
    "gn:feature_code":"PPL",
    "gn:name":"Radoni\u0107",
    "gn:population":0,
    "gn:timezone":"Europe/Zagreb",
    "iso:country":"HR",
    "wof:name":"Radonic",
    "wof:placetype":"locality"
},
  "geometry": {"coordinates":[16.06667,43.76667],"type":"Point"}
}