{
  "type": "Feature",
  "properties": {
    "gn:admin1_code":"07",
    "gn:admin2_code":"11049222.0",
    "gn:asciiname":"Ervenik",
    "gn:country_code":"HR",
    "gn:dem":209,
    "gn:feature_class":"P",
    "gn:feature_code":"PPL",
    "gn:name":"Ervenik",
    "gn:population":0,
    "gn:timezone":"Europe/Zagreb",
    "iso:country":"HR",
    "name:bos_x_preferred":[
        "Ervenik"
    ],
    "name:cat_x_preferred":[
        "Ervenik"
    ],
    "name:fra_x_preferred":[
        "Ervenik"
    ],
    "name:hrv_x_preferred":[
        "Ervenik"
    ],
    "name:hun_x_preferred":[
        "Ervenik"
    ],
    "name:ita_x_preferred":[
        "Ervenico"
    ],
    "name:nld_x_preferred":[
        "Ervenik"
    ],
    "name:pol_x_preferred":[
        "Gmina Ervenik"
    ],
    "name:ron_x_preferred":[
        "Comuna Ervenik"
    ],
    "name:slv_x_preferred":[
        "Ervenik"
    ],
    "name:srp_x_preferred":[
        "\u0415\u0440\u0432\u0435\u043d\u0438\u043a"
    ],
    "name:ukr_x_preferred":[
        "\u0415\u0440\u0432\u0435\u043d\u0438\u043a"
    ],
    "name:war_x_preferred":[
        "Ervenik"
    ],
    "wof:name":"Ervenik",
    "wof:placetype":"locality"
},
  "geometry": {"coordinates":[16.11909,46.08174],"type":"Point"}
}