{
  "type": "Feature",
  "properties": {
    "gn:admin1_code":"07",
    "gn:admin2_code":"11049222.0",
    "gn:asciiname":"Ervenik",
    "gn:country_code":"HR",
    "gn:dem":209,
    "gn:feature_class":"P",
    "gn:feature_code":"PPL",
    "gn:name":"Ervenik",
    "gn:population":0,
    "gn:timezone":"Europe/Zagreb",
    "iso:country":"HR",
    "wof:name":"Ervenik",
    "wof:placetype":"locality"
},
  "geometry": {"coordinates":[16.11909,46.08174],"type":"Point"}
}