{
  "type": "Feature",
  "properties": {
    "gn:gn_country":"HR",
    "gn:gn_fcode":"PPL",
    "gn:gn_pop":970,
    "gn:population":970,
    "iso:country":"HR",
    "name:bos_x_preferred":[
        "Zagvozd"
    ],
    "name:bul_x_preferred":[
        "\u0417\u0430\u0433\u0432\u043e\u0437\u0434"
    ],
    "name:cat_x_preferred":[
        "Zagvozd"
    ],
    "name:ceb_x_preferred":[
        "Zagvozd"
    ],
    "name:ces_x_preferred":[
        "Zagvozd"
    ],
    "name:deu_x_preferred":[
        "Zagvozd"
    ],
    "name:eng_x_preferred":[
        "Zagvozd"
    ],
    "name:fra_x_preferred":[
        "Zagvozd"
    ],
    "name:hrv_x_preferred":[
        "Zagvozd"
    ],
    "name:hsb_x_preferred":[
        "Zagvozd"
    ],
    "name:hun_x_preferred":[
        "Zagvozd"
    ],
    "name:ita_x_preferred":[
        "Zagvozd"
    ],
    "name:nld_x_preferred":[
        "Zagvozd"
    ],
    "name:oci_x_preferred":[
        "Zagvozd"
    ],
    "name:pol_x_preferred":[
        "Zagvozd"
    ],
    "name:ron_x_preferred":[
        "Comuna Zagvozd"
    ],
    "name:slv_x_preferred":[
        "Zagvozd"
    ],
    "name:spa_x_preferred":[
        "Zagvozd"
    ],
    "name:srp_x_preferred":[
        "\u0417\u0430\u0433\u0432\u043e\u0437\u0434"
    ],
    "name:swe_x_preferred":[
        "Zagvozd"
    ],
    "name:ukr_x_preferred":[
        "\u0417\u0430\u0433\u0432\u043e\u0437\u0434"
    ],
    "name:unk_x_variant":[
        "Zagost"
    ],
    "name:war_x_preferred":[
        "Zagvozd"
    ],
    "name:zho_x_preferred":[
        "\u624e\u683c\u6c83\u8332\u5fb7"
    ],
    "qs_pg:aaroncc":"HR",
    "qs_pg:gn_country":"HR",
    "qs_pg:gn_fcode":"PPL",
    "qs_pg:gn_pop":970,
    "qs_pg:name":"Zagvozd",
    "qs_pg:name_adm0":"Hrvatska",
    "qs_pg:name_adm1":"Splitsko-Dalmatinska",
    "qs_pg:photos_9k":1,
    "qs_pg:photos_9r":1,
    "qs_pg:photos_all":2,
    "qs_pg:photos_sr":0,
    "qs_pg:pop_sr":2,
    "qs_pg:qs_pg_placetype":"locality",
    "qs_pg:qs_pg_placetype_gp":"Town",
    "qs_pg:woe_adm0":23424843,
    "woe:adm0_id":23424843,
    "woe:name_adm0":"Hrvatska",
    "woe:name_adm1":"Splitsko-Dalmatinska",
    "woe:placetype":"Town",
    "wof:name":"Zagvozd",
    "wof:placetype":"locality",
    "wof:population":970
},
  "geometry": {"coordinates":[17.05694,43.3975],"type":"Point"}
}