{
  "type": "Feature",
  "properties": {
    "gn:admin1_code":"13",
    "gn:admin2_code":"11055025.0",
    "gn:asciiname":"Razvoge",
    "gn:country_code":"HR",
    "gn:dem":283,
    "gn:feature_class":"P",
    "gn:feature_code":"PPL",
    "gn:name":"Razvo\u0111e",
    "gn:population":170,
    "gn:timezone":"Europe/Zagreb",
    "iso:country":"HR",
    "wof:name":"Razvoge",
    "wof:placetype":"locality",
    "wof:population":170
},
  "geometry": {"coordinates":[16.10611,43.92639000000001],"type":"Point"}
}