{
  "type": "Feature",
  "properties": {
    "gn:admin1_code":"8.0",
    "gn:asciiname":"Jadovno",
    "gn:country_code":"HR",
    "gn:dem":817,
    "gn:feature_class":"P",
    "gn:feature_code":"PPL",
    "gn:name":"Jadovno",
    "gn:population":0,
    "gn:timezone":"Europe/Zagreb",
    "iso:country":"HR",
    "wof:name":"Jadovno",
    "wof:placetype":"locality"
},
  "geometry": {"coordinates":[15.23806,44.53861],"type":"Point"}
}