{
  "type": "Feature",
  "properties": {
    "gn:admin1_code":"14.0",
    "gn:asciiname":"Gornjani",
    "gn:country_code":"HR",
    "gn:dem":98,
    "gn:feature_class":"P",
    "gn:feature_code":"PPL",
    "gn:name":"Gornjani",
    "gn:population":0,
    "gn:timezone":"Europe/Zagreb",
    "iso:country":"HR",
    "wof:name":"Gornjani",
    "wof:placetype":"locality"
},
  "geometry": {"coordinates":[16.79444,45.19139000000001],"type":"Point"}
}