{
  "type": "Feature",
  "properties": {
    "gn:admin1_code":"11",
    "gn:asciiname":"Ivanin Dvor",
    "gn:country_code":"HR",
    "gn:dem":119,
    "gn:feature_class":"P",
    "gn:feature_code":"PPL",
    "gn:name":"Ivanin Dvor",
    "gn:population":0,
    "gn:timezone":"Europe/Zagreb",
    "iso:country":"HR",
    "wof:name":"Ivanin Dvor",
    "wof:placetype":"locality"
},
  "geometry": {"coordinates":[17.82611,45.30583],"type":"Point"}
}