{
  "type": "Feature",
  "properties": {
    "gn:admin1_code":"2.0",
    "gn:admin2_code":"11049493.0",
    "gn:asciiname":"Surevica",
    "gn:country_code":"HR",
    "gn:dem":118,
    "gn:feature_class":"P",
    "gn:feature_code":"PPL",
    "gn:name":"Surevica",
    "gn:population":0,
    "gn:timezone":"Europe/Zagreb",
    "iso:country":"HR",
    "wof:name":"Surevica",
    "wof:placetype":"locality"
},
  "geometry": {"coordinates":[18.18944,45.21222],"type":"Point"}
}