{
  "type": "Feature",
  "properties": {
    "gn:admin1_code":"19.0",
    "gn:asciiname":"Mecet",
    "gn:country_code":"HR",
    "gn:dem":381,
    "gn:feature_class":"P",
    "gn:feature_code":"PPL",
    "gn:name":"Me\u010det",
    "gn:population":0,
    "gn:timezone":"Europe/Zagreb",
    "iso:country":"HR",
    "wof:name":"Mecet",
    "wof:placetype":"locality"
},
  "geometry": {"coordinates":[16.11056,44.40111],"type":"Point"}
}