{
  "type": "Feature",
  "properties": {
    "gn:gn_country":"HR",
    "gn:gn_fcode":"PPL",
    "gn:gn_pop":1581,
    "gn:population":1581,
    "iso:country":"HR",
    "name:bos_x_preferred":[
        "Kalinovac"
    ],
    "name:eng_x_preferred":[
        "Kalinovac"
    ],
    "name:fra_x_preferred":[
        "Kalinovac"
    ],
    "name:hrv_x_preferred":[
        "Kalinovac"
    ],
    "name:hun_x_preferred":[
        "Kalin\u00f3c"
    ],
    "name:ita_x_preferred":[
        "Kalinovac"
    ],
    "name:nld_x_preferred":[
        "Kalinovac"
    ],
    "name:ron_x_preferred":[
        "Comuna Kalinovac"
    ],
    "name:rus_x_preferred":[
        "\u041a\u0430\u043b\u0438\u043d\u043e\u0432\u0430\u0446"
    ],
    "name:slv_x_preferred":[
        "Kalinovac"
    ],
    "name:spa_x_preferred":[
        "Kalinovac"
    ],
    "name:srp_x_preferred":[
        "\u041a\u0430\u043b\u0438\u043d\u043e\u0432\u0430\u0446"
    ],
    "name:swe_x_preferred":[
        "Kalinovac"
    ],
    "name:ukr_x_preferred":[
        "\u041a\u0430\u043b\u0456\u043d\u043e\u0432\u0430\u0446"
    ],
    "name:unk_x_variant":[
        "Kalinovac"
    ],
    "name:war_x_preferred":[
        "Kalinovac"
    ],
    "qs_pg:aaroncc":"HR",
    "qs_pg:gn_country":"HR",
    "qs_pg:gn_fcode":"PPL",
    "qs_pg:gn_pop":1581,
    "qs_pg:name":"Katinovac",
    "qs_pg:name_adm0":"Hrvatska",
    "qs_pg:name_adm1":"Sisa\u010dko-moslava\u010dka",
    "qs_pg:photos_9r":0,
    "qs_pg:photos_sr":0,
    "qs_pg:pop_sr":3,
    "qs_pg:qs_pg_placetype":"locality",
    "qs_pg:qs_pg_placetype_gp":"Town",
    "qs_pg:woe_adm0":23424843,
    "woe:adm0_id":23424843,
    "woe:name_adm0":"Hrvatska",
    "woe:name_adm1":"Sisa\u010dko-moslava\u010dka",
    "woe:placetype":"Town",
    "wof:name":"Katinovac",
    "wof:placetype":"locality",
    "wof:population":1581
},
  "geometry": {"coordinates":[17.11556,46.02944],"type":"Point"}
}