{
  "type": "Feature",
  "properties": {
    "gn:admin1_code":"19.0",
    "gn:asciiname":"Cukovi",
    "gn:country_code":"HR",
    "gn:dem":733,
    "gn:feature_class":"P",
    "gn:feature_code":"PPL",
    "gn:name":"Cukovi",
    "gn:population":0,
    "gn:timezone":"Europe/Zagreb",
    "iso:country":"HR",
    "wof:name":"Cukovi",
    "wof:placetype":"locality"
},
  "geometry": {"coordinates":[15.88333,44.39861],"type":"Point"}
}