{
  "type": "Feature",
  "properties": {
    "gn:admin1_code":"8.0",
    "gn:asciiname":"Grezina",
    "gn:country_code":"HR",
    "gn:dem":699,
    "gn:feature_class":"P",
    "gn:feature_code":"PPL",
    "gn:name":"Grezina",
    "gn:population":0,
    "gn:timezone":"Europe/Zagreb",
    "iso:country":"HR",
    "wof:name":"Grezina",
    "wof:placetype":"locality"
},
  "geometry": {"coordinates":[15.11861,44.82611],"type":"Point"}
}