{
  "type": "Feature",
  "properties": {
    "gn:admin1_code":"12",
    "gn:admin2_code":"3202931.0",
    "gn:asciiname":"Kozji Vrh",
    "gn:country_code":"HR",
    "gn:dem":897,
    "gn:feature_class":"P",
    "gn:feature_code":"PPL",
    "gn:name":"Kozji Vrh",
    "gn:population":60,
    "gn:timezone":"Europe/Zagreb",
    "iso:country":"HR",
    "name:bos_x_preferred":[
        "Kozji Vrh"
    ],
    "name:fra_x_preferred":[
        "Kozji Vrh"
    ],
    "name:hrv_x_preferred":[
        "Kozji Vrh"
    ],
    "name:hun_x_preferred":[
        "Kozji Vrh"
    ],
    "name:slv_x_preferred":[
        "Kozji Vrh"
    ],
    "name:spa_x_preferred":[
        "Kozji Vrh"
    ],
    "name:ukr_x_preferred":[
        "\u041a\u043e\u0437\u0456\u0439 \u0412\u0440\u0445"
    ],
    "wof:name":"Kozji Vrh",
    "wof:placetype":"locality",
    "wof:population":60
},
  "geometry": {"coordinates":[14.59388,45.6174],"type":"Point"}
}