{
  "type": "Feature",
  "properties": {
    "gn:admin1_code":"12",
    "gn:admin2_code":"3202931.0",
    "gn:asciiname":"Kozji Vrh",
    "gn:country_code":"HR",
    "gn:dem":897,
    "gn:feature_class":"P",
    "gn:feature_code":"PPL",
    "gn:name":"Kozji Vrh",
    "gn:population":60,
    "gn:timezone":"Europe/Zagreb",
    "iso:country":"HR",
    "wof:name":"Kozji Vrh",
    "wof:placetype":"locality",
    "wof:population":60
},
  "geometry": {"coordinates":[14.59388,45.6174],"type":"Point"}
}