{
  "type": "Feature",
  "properties": {
    "gn:admin1_code":"12.0",
    "gn:asciiname":"Antovo",
    "gn:country_code":"HR",
    "gn:dem":592,
    "gn:feature_class":"P",
    "gn:feature_code":"PPL",
    "gn:name":"Antovo",
    "gn:population":0,
    "gn:timezone":"Europe/Zagreb",
    "iso:country":"HR",
    "wof:name":"Antovo",
    "wof:placetype":"locality"
},
  "geometry": {"coordinates":[14.71667,45.21667],"type":"Point"}
}