{
  "type": "Feature",
  "properties": {
    "gn:gn_country":"HR",
    "gn:gn_fcode":"PPL",
    "gn:gn_pop":0,
    "gn:population":474,
    "iso:country":"HR",
    "name:bos_x_preferred":[
        "Sumartin"
    ],
    "name:cat_x_preferred":[
        "Sumartin"
    ],
    "name:cze_x_preferred":[
        "Sumartin"
    ],
    "name:dut_x_preferred":[
        "Sumartin"
    ],
    "name:eng_x_preferred":[
        "Sumartin"
    ],
    "name:fre_x_preferred":[
        "Sumartin"
    ],
    "name:ger_x_preferred":[
        "Sumartin"
    ],
    "name:hrv_x_preferred":[
        "Sumartin"
    ],
    "name:hun_x_preferred":[
        "Sumartin"
    ],
    "name:ita_x_preferred":[
        "Sumartin"
    ],
    "name:oci_x_preferred":[
        "Sumartin"
    ],
    "name:pol_x_preferred":[
        "Sumartin"
    ],
    "name:slo_x_preferred":[
        "Sumartin"
    ],
    "name:slv_x_preferred":[
        "Sumartin"
    ],
    "name:spa_x_preferred":[
        "Sumartin"
    ],
    "name:srp_x_preferred":[
        "\u0421\u0443\u043c\u0430\u0440\u0442\u0438\u043d"
    ],
    "name:swe_x_preferred":[
        "Sumartin"
    ],
    "qs_pg:aaroncc":"HR",
    "qs_pg:gn_country":"HR",
    "qs_pg:gn_fcode":"PPL",
    "qs_pg:gn_pop":0,
    "qs_pg:name":"Sumartin",
    "qs_pg:name_adm0":"Hrvatska",
    "qs_pg:name_adm1":"Splitsko-Dalmatinska",
    "qs_pg:photos":347,
    "qs_pg:photos_1k":70,
    "qs_pg:photos_9k":2,
    "qs_pg:photos_9r":5,
    "qs_pg:photos_all":347,
    "qs_pg:photos_sr":5,
    "qs_pg:pop_sr":0,
    "qs_pg:qs_pg_placetype":"locality",
    "qs_pg:qs_pg_placetype_gp":"Town",
    "qs_pg:woe_adm0":23424843,
    "woe:adm0_id":23424843,
    "woe:name_adm0":"Hrvatska",
    "woe:name_adm1":"Splitsko-Dalmatinska",
    "woe:placetype":"Town",
    "wof:name":"Sumartin",
    "wof:placetype":"locality",
    "wof:population":474
},
  "geometry": {"coordinates":[16.87556,43.285],"type":"Point"}
}