{
  "type": "Feature",
  "properties": {
    "iso:country":"HR",
    "name:hrv_x_preferred":[
        "Tre\u0161njevka - sjever"
    ],
    "wof:name":"Tresnjevka-sjever",
    "wof:placetype":"neighbourhood"
},
  "geometry": {"coordinates":[15.93952113184322,45.80114724923637],"type":"Point"}
}