{
  "type": "Feature",
  "properties": {
    "gn:admin1_code":"5.0",
    "gn:asciiname":"Smrzlic",
    "gn:country_code":"HR",
    "gn:dem":298,
    "gn:feature_class":"P",
    "gn:feature_code":"PPL",
    "gn:name":"Smrzlic",
    "gn:population":0,
    "gn:timezone":"Europe/Zagreb",
    "iso:country":"HR",
    "wof:name":"Smrzlic",
    "wof:placetype":"locality"
},
  "geometry": {"coordinates":[15.65389,45.12667],"type":"Point"}
}