{
  "type": "Feature",
  "properties": {
    "gn:admin1_code":"3.0",
    "gn:admin2_code":"11054971.0",
    "gn:asciiname":"Sibcine",
    "gn:country_code":"HR",
    "gn:dem":85,
    "gn:feature_class":"P",
    "gn:feature_code":"PPL",
    "gn:name":"\u0160ib\u010dine",
    "gn:population":0,
    "gn:timezone":"Europe/Zagreb",
    "iso:country":"HR",
    "wof:name":"Sibcine",
    "wof:placetype":"locality"
},
  "geometry": {"coordinates":[17.53389,43.10444],"type":"Point"}
}