{
  "type": "Feature",
  "properties": {
    "gn:admin1_code":"15.0",
    "gn:asciiname":"Kute",
    "gn:country_code":"HR",
    "gn:dem":273,
    "gn:feature_class":"P",
    "gn:feature_code":"PPL",
    "gn:name":"Kute",
    "gn:population":0,
    "gn:timezone":"Europe/Zagreb",
    "iso:country":"HR",
    "name:bos_x_preferred":[
        "Kute"
    ],
    "name:ceb_x_preferred":[
        "Kute"
    ],
    "name:fra_x_preferred":[
        "Kute"
    ],
    "name:hrv_x_preferred":[
        "Kute"
    ],
    "name:srp_x_preferred":[
        "\u041a\u0443\u0442\u0435"
    ],
    "name:swe_x_preferred":[
        "Kute"
    ],
    "wof:name":"Kute",
    "wof:placetype":"locality"
},
  "geometry": {"coordinates":[16.60778,43.57944000000001],"type":"Point"}
}