{
  "type": "Feature",
  "properties": {
    "gn:admin1_code":"01",
    "gn:admin2_code":"11055019.0",
    "gn:asciiname":"Removac",
    "gn:cc2":"HR",
    "gn:country_code":"HR",
    "gn:dem":200,
    "gn:feature_class":"P",
    "gn:feature_code":"PPL",
    "gn:name":"Removac",
    "gn:population":19,
    "gn:timezone":"Europe/Zagreb",
    "iso:country":"HR",
    "name:und_x_variant":[
        "Removacz",
        "Removac"
    ],
    "wof:name":"Removac",
    "wof:placetype":"locality",
    "wof:population":19
},
  "geometry": {"coordinates":[17.41306,45.70944],"type":"Point"}
}