{
  "type": "Feature",
  "properties": {
    "gn:admin1_code":"21",
    "gn:asciiname":"Brebernica",
    "gn:country_code":"HR",
    "gn:dem":180,
    "gn:feature_class":"P",
    "gn:feature_code":"PPL",
    "gn:name":"Brebernica",
    "gn:population":0,
    "gn:timezone":"Europe/Zagreb",
    "iso:country":"HR",
    "wof:name":"Brebernica",
    "wof:placetype":"locality"
},
  "geometry": {"coordinates":[15.89121,45.66763],"type":"Point"}
}