{
  "type": "Feature",
  "properties": {
    "gn:admin1_code":"21",
    "gn:asciiname":"Brebernica",
    "gn:country_code":"HR",
    "gn:dem":180,
    "gn:feature_class":"P",
    "gn:feature_code":"PPL",
    "gn:name":"Brebernica",
    "gn:population":0,
    "gn:timezone":"Europe/Zagreb",
    "iso:country":"HR",
    "name:bos_x_preferred":[
        "Brebernica"
    ],
    "name:hrv_x_preferred":[
        "Brebernica"
    ],
    "name:nld_x_preferred":[
        "Brebernica"
    ],
    "name:slv_x_preferred":[
        "Brebernica"
    ],
    "name:ukr_x_preferred":[
        "\u0411\u0440\u0435\u0431\u0435\u0440\u043d\u0438\u0446\u044f"
    ],
    "wof:name":"Brebernica",
    "wof:placetype":"locality"
},
  "geometry": {"coordinates":[15.89121,45.66763],"type":"Point"}
}