{
  "type": "Feature",
  "properties": {
    "gn:admin1_code":"19.0",
    "gn:asciiname":"Arbanasi",
    "gn:cc2":"HR",
    "gn:country_code":"HR",
    "gn:dem":176,
    "gn:feature_class":"P",
    "gn:feature_code":"PPL",
    "gn:name":"Arbanasi",
    "gn:population":0,
    "gn:timezone":"Europe/Zagreb",
    "iso:country":"HR",
    "name:und_x_variant":[
        "Arbanasia",
        "Arbanasi"
    ],
    "wof:name":"Arbanasi",
    "wof:placetype":"locality"
},
  "geometry": {"coordinates":[15.51139,44.13528],"type":"Point"}
}