{
  "type": "Feature",
  "properties": {
    "gn:admin1_code":"19.0",
    "gn:asciiname":"Arbanasi",
    "gn:cc2":"HR",
    "gn:country_code":"HR",
    "gn:dem":176,
    "gn:feature_class":"P",
    "gn:feature_code":"PPL",
    "gn:name":"Arbanasi",
    "gn:population":0,
    "gn:timezone":"Europe/Zagreb",
    "iso:country":"HR",
    "name:bul_x_preferred":[
        "\u0410\u0440\u0431\u0430\u043d\u0430\u0441\u0438"
    ],
    "name:deu_x_preferred":[
        "Arbanasi"
    ],
    "name:fra_x_preferred":[
        "Arbanasi"
    ],
    "name:ita_x_preferred":[
        "Arbanasi"
    ],
    "name:sqi_x_preferred":[
        "Arbanasi"
    ],
    "name:srp_x_preferred":[
        "\u0410\u0440\u0431\u0430\u043d\u0430\u0441\u0438"
    ],
    "name:und_x_variant":[
        "Arbanasia"
    ],
    "wof:name":"Arbanasi",
    "wof:placetype":"locality"
},
  "geometry": {"coordinates":[15.51139,44.13528],"type":"Point"}
}