{
  "type": "Feature",
  "properties": {
    "gn:admin1_code":"3.0",
    "gn:asciiname":"Soline",
    "gn:country_code":"HR",
    "gn:dem":7,
    "gn:feature_class":"P",
    "gn:feature_code":"PPL",
    "gn:name":"Soline",
    "gn:population":0,
    "gn:timezone":"Europe/Zagreb",
    "iso:country":"HR",
    "name:bos_x_preferred":[
        "Soline"
    ],
    "name:ceb_x_preferred":[
        "Soline"
    ],
    "name:deu_x_preferred":[
        "Soline"
    ],
    "name:fra_x_preferred":[
        "Soline"
    ],
    "name:hrv_x_preferred":[
        "Soline"
    ],
    "name:hun_x_preferred":[
        "Soline"
    ],
    "name:nld_x_preferred":[
        "Soline"
    ],
    "name:slv_x_preferred":[
        "Soline"
    ],
    "name:srp_x_preferred":[
        "\u0421\u043e\u043b\u0438\u043d\u0435"
    ],
    "name:swe_x_preferred":[
        "Soline"
    ],
    "name:ukr_x_preferred":[
        "\u0421\u043e\u043b\u0438\u043d\u0435"
    ],
    "wof:name":"Soline",
    "wof:placetype":"locality"
},
  "geometry": {"coordinates":[18.04056,42.69806],"type":"Point"}
}