{
  "type": "Feature",
  "properties": {
    "gn:admin1_code":"3.0",
    "gn:asciiname":"Soline",
    "gn:country_code":"HR",
    "gn:dem":7,
    "gn:feature_class":"P",
    "gn:feature_code":"PPL",
    "gn:name":"Soline",
    "gn:population":0,
    "gn:timezone":"Europe/Zagreb",
    "iso:country":"HR",
    "wof:name":"Soline",
    "wof:placetype":"locality"
},
  "geometry": {"coordinates":[18.04056,42.69806],"type":"Point"}
}