{
  "type": "Feature",
  "properties": {
    "gn:gn_country":"HR",
    "gn:gn_fcode":"PPL",
    "gn:gn_pop":2714,
    "gn:population":2714,
    "iso:country":"HR",
    "name:bos_x_preferred":[
        "Pag"
    ],
    "name:ces_x_preferred":[
        "Pag"
    ],
    "name:ckb_x_preferred":[
        "\u067e\u0627\u06af"
    ],
    "name:deu_x_preferred":[
        "Pag"
    ],
    "name:eng_x_preferred":[
        "Pag"
    ],
    "name:fas_x_preferred":[
        "\u067e\u0627\u06af"
    ],
    "name:fra_x_preferred":[
        "Pag"
    ],
    "name:hrv_x_preferred":[
        "Pag"
    ],
    "name:hun_x_preferred":[
        "Pag"
    ],
    "name:hye_x_preferred":[
        "\u054a\u0561\u0563"
    ],
    "name:ita_x_preferred":[
        "Isola di Pago"
    ],
    "name:jpn_x_preferred":[
        "\u30d1\u30b0"
    ],
    "name:kor_x_preferred":[
        "\ud30c\uadf8"
    ],
    "name:lit_x_preferred":[
        "Pagas"
    ],
    "name:nld_x_preferred":[
        "Pag"
    ],
    "name:nor_x_preferred":[
        "Pag"
    ],
    "name:pol_x_preferred":[
        "Pag"
    ],
    "name:por_x_preferred":[
        "Pag"
    ],
    "name:ron_x_preferred":[
        "Pag"
    ],
    "name:rus_x_preferred":[
        "\u041f\u0430\u0433"
    ],
    "name:slk_x_preferred":[
        "Pag"
    ],
    "name:slv_x_preferred":[
        "Pag"
    ],
    "name:srp_x_preferred":[
        "\u041f\u0430\u0433"
    ],
    "name:srp_x_variant":[
        "Pag"
    ],
    "name:swe_x_preferred":[
        "Pag"
    ],
    "name:tat_x_preferred":[
        "\u041f\u0430\u0433"
    ],
    "name:ukr_x_preferred":[
        "\u041f\u0430\u0433"
    ],
    "name:unk_x_variant":[
        "Pago"
    ],
    "name:war_x_preferred":[
        "Pag"
    ],
    "name:zho_x_preferred":[
        "\u5e15\u683c"
    ],
    "qs_pg:aaroncc":"HR",
    "qs_pg:gn_country":"HR",
    "qs_pg:gn_fcode":"PPL",
    "qs_pg:gn_pop":2714,
    "qs_pg:name":"Parg",
    "qs_pg:name_adm0":"Hrvatska",
    "qs_pg:name_adm1":"Primorsko-Goranska",
    "qs_pg:photos_9r":0,
    "qs_pg:photos_sr":0,
    "qs_pg:pop_sr":4,
    "qs_pg:qs_pg_placetype":"locality",
    "qs_pg:qs_pg_placetype_gp":"Town",
    "qs_pg:woe_adm0":23424843,
    "woe:adm0_id":23424843,
    "woe:name_adm0":"Hrvatska",
    "woe:name_adm1":"Primorsko-Goranska",
    "woe:placetype":"Town",
    "wof:name":"Parg",
    "wof:placetype":"locality",
    "wof:population":2714
},
  "geometry": {"coordinates":[15.0575,44.445],"type":"Point"}
}