{
  "type": "Feature",
  "properties": {
    "gn:gn_country":"HR",
    "gn:gn_fcode":"PPL",
    "gn:gn_pop":919,
    "gn:population":924,
    "iso:country":"HR",
    "qs_pg:aaroncc":"HR",
    "qs_pg:gn_country":"HR",
    "qs_pg:gn_fcode":"PPL",
    "qs_pg:gn_pop":919,
    "qs_pg:name":"Glogovac",
    "qs_pg:name_adm0":"Hrvatska",
    "qs_pg:name_adm1":"Koprivni\u010dko-kri\u017eeva\u010dka",
    "qs_pg:photos_9k":1,
    "qs_pg:photos_9r":1,
    "qs_pg:photos_all":1,
    "qs_pg:photos_sr":0,
    "qs_pg:pop_sr":2,
    "qs_pg:qs_pg_placetype":"locality",
    "qs_pg:qs_pg_placetype_gp":"Town",
    "qs_pg:woe_adm0":23424843,
    "woe:adm0_id":23424843,
    "woe:name_adm0":"Hrvatska",
    "woe:name_adm1":"Koprivni\u010dko-kri\u017eeva\u010dka",
    "woe:placetype":"Town",
    "wof:name":"Glogovac",
    "wof:placetype":"locality",
    "wof:population":924
},
  "geometry": {"coordinates":[16.87444,46.11556],"type":"Point"}
}