{
  "type": "Feature",
  "properties": {
    "gn:country":"HR",
    "gn:fcode":"PPL",
    "gn:population":919,
    "iso:country":"HR",
    "name:ceb_x_preferred":[
        "Glogovac"
    ],
    "name:ces_x_preferred":[
        "Glogovac"
    ],
    "name:cym_x_preferred":[
        "Drenas"
    ],
    "name:deu_x_preferred":[
        "Drenas"
    ],
    "name:fas_x_preferred":[
        "\u06af\u0644\u0648\u06af\u0648\u0648\u0627\u0633"
    ],
    "name:fra_x_preferred":[
        "Gllogoc"
    ],
    "name:hrv_x_preferred":[
        "Glogovac"
    ],
    "name:ile_x_preferred":[
        "Gllogoc"
    ],
    "name:ita_x_preferred":[
        "Glogovac"
    ],
    "name:kor_x_preferred":[
        "\ub4dc\ub808\ub098\uc2a4"
    ],
    "name:lit_x_preferred":[
        "Glogovacas"
    ],
    "name:mkd_x_preferred":[
        "\u0413\u043b\u043e\u0433\u043e\u0432\u0430\u0446"
    ],
    "name:nld_x_preferred":[
        "Gllogovc"
    ],
    "name:nor_x_preferred":[
        "Gllogoc"
    ],
    "name:pol_x_preferred":[
        "Glogovac"
    ],
    "name:por_x_preferred":[
        "Glogovac"
    ],
    "name:ron_x_preferred":[
        "Glogovac"
    ],
    "name:sqi_x_preferred":[
        "Drenasi"
    ],
    "name:srp_x_preferred":[
        "\u0413\u043b\u043e\u0433\u043e\u0432\u0430\u0446"
    ],
    "name:swe_x_preferred":[
        "Glogovac"
    ],
    "name:tur_x_preferred":[
        "Glogova\u00e7"
    ],
    "name:ukr_x_preferred":[
        "\u0413\u043b\u043e\u0433\u043e\u0432\u0430\u0446"
    ],
    "name:zho_x_preferred":[
        "\u683c\u6d1b\u6208\u74e6\u8328"
    ],
    "qs_pg:aaroncc":"HR",
    "qs_pg:gn_country":"HR",
    "qs_pg:gn_fcode":"PPL",
    "qs_pg:gn_pop":919,
    "qs_pg:name":"Glogovac",
    "qs_pg:name_adm0":"Hrvatska",
    "qs_pg:name_adm1":"Koprivni\u010dko-kri\u017eeva\u010dka",
    "qs_pg:photos_9k":1,
    "qs_pg:photos_9r":1,
    "qs_pg:photos_all":1,
    "qs_pg:photos_sr":0,
    "qs_pg:pop_sr":2,
    "qs_pg:qs_pg_placetype":"locality",
    "qs_pg:qs_pg_placetype_gp":"Town",
    "qs_pg:woe_adm0":23424843,
    "woe:adm0_id":23424843,
    "woe:name_adm0":"Hrvatska",
    "woe:name_adm1":"Koprivni\u010dko-kri\u017eeva\u010dka",
    "woe:placetype":"Town",
    "wof:name":"Glogovac",
    "wof:placetype":"locality",
    "wof:population":924
},
  "geometry": {"coordinates":[16.87444,46.11556],"type":"Point"}
}