{
  "type": "Feature",
  "properties": {
    "gn:admin1_code":"8.0",
    "gn:asciiname":"Bogdanic",
    "gn:country_code":"HR",
    "gn:dem":573,
    "gn:feature_class":"P",
    "gn:feature_code":"PPL",
    "gn:name":"Bogdani\u0107",
    "gn:population":0,
    "gn:timezone":"Europe/Zagreb",
    "iso:country":"HR",
    "wof:name":"Bogdanic",
    "wof:placetype":"locality"
},
  "geometry": {"coordinates":[15.31222,44.55472],"type":"Point"}
}