{
  "type": "Feature",
  "properties": {
    "gn:admin1_code":"19.0",
    "gn:asciiname":"Petrovici",
    "gn:country_code":"HR",
    "gn:dem":681,
    "gn:feature_class":"P",
    "gn:feature_code":"PPL",
    "gn:name":"Petrovi\u0107i",
    "gn:population":0,
    "gn:timezone":"Europe/Zagreb",
    "iso:country":"HR",
    "wof:name":"Petrovici",
    "wof:placetype":"locality"
},
  "geometry": {"coordinates":[15.91056,44.35528],"type":"Point"}
}