{
  "type": "Feature",
  "properties": {
    "gn:admin1_code":"01",
    "gn:admin2_code":"3200709.0",
    "gn:asciiname":"Uljanik",
    "gn:cc2":"HR",
    "gn:country_code":"HR",
    "gn:dem":128,
    "gn:feature_class":"P",
    "gn:feature_code":"PPL",
    "gn:name":"Uljanik",
    "gn:population":287,
    "gn:timezone":"Europe/Zagreb",
    "iso:country":"HR",
    "name:und_x_variant":[
        "Ullinjak",
        "Ullinyak",
        "Uljanik"
    ],
    "wof:name":"Uljanik",
    "wof:placetype":"locality",
    "wof:population":287
},
  "geometry": {"coordinates":[17.01833,45.53028],"type":"Point"}
}