{
  "type": "Feature",
  "properties": {
    "gn:admin1_code":"13.0",
    "gn:asciiname":"Kravljacica",
    "gn:country_code":"HR",
    "gn:dem":54,
    "gn:feature_class":"P",
    "gn:feature_code":"PPL",
    "gn:name":"Kravlja\u010dica",
    "gn:population":0,
    "gn:timezone":"Europe/Zagreb",
    "iso:country":"HR",
    "wof:name":"Kravljacica",
    "wof:placetype":"locality"
},
  "geometry": {"coordinates":[15.27722,43.83056],"type":"Point"}
}