{
  "type": "Feature",
  "properties": {
    "gn:admin1_code":"15.0",
    "gn:asciiname":"Sokici",
    "gn:country_code":"HR",
    "gn:dem":468,
    "gn:feature_class":"P",
    "gn:feature_code":"PPL",
    "gn:name":"Soki\u0107i",
    "gn:population":0,
    "gn:timezone":"Europe/Zagreb",
    "iso:country":"HR",
    "wof:name":"Sokici",
    "wof:placetype":"locality"
},
  "geometry": {"coordinates":[16.83472,43.53722],"type":"Point"}
}