{
  "type": "Feature",
  "properties": {
    "gn:admin1_code":"08",
    "gn:admin2_code":"11049286.0",
    "gn:asciiname":"Licki Ribnik",
    "gn:cc2":"HR",
    "gn:country_code":"HR",
    "gn:dem":569,
    "gn:feature_class":"P",
    "gn:feature_code":"PPL",
    "gn:name":"Li\u010dki Ribnik",
    "gn:population":93,
    "gn:timezone":"Europe/Zagreb",
    "iso:country":"HR",
    "name:und_x_variant":[
        "Ribnik",
        "Li\u010dki Ribnik"
    ],
    "wof:name":"Licki Ribnik",
    "wof:placetype":"locality",
    "wof:population":93
},
  "geometry": {"coordinates":[15.45111,44.48583],"type":"Point"}
}