{
  "type": "Feature",
  "properties": {
    "gn:gn_country":"HR",
    "gn:gn_fcode":"PPL",
    "gn:gn_pop":856,
    "gn:population":933,
    "iso:country":"HR",
    "name:bos_x_preferred":[
        "\u010cilipi"
    ],
    "name:ceb_x_preferred":[
        "\u010cilipi"
    ],
    "name:eng_x_preferred":[
        "\u010cilipi"
    ],
    "name:fra_x_preferred":[
        "\u010cilipi"
    ],
    "name:hrv_x_preferred":[
        "\u010cilipi"
    ],
    "name:hun_x_preferred":[
        "\u010cilipi"
    ],
    "name:ita_x_preferred":[
        "Cilippi"
    ],
    "name:nld_x_preferred":[
        "\u010cilipi"
    ],
    "name:rus_x_preferred":[
        "\u0427\u0438\u043b\u0438\u043f\u0438"
    ],
    "name:slv_x_preferred":[
        "\u010cilipi"
    ],
    "name:srp_x_preferred":[
        "\u0427\u0438\u043b\u0438\u043f\u0438"
    ],
    "name:swe_x_preferred":[
        "\u010cilipi"
    ],
    "name:ukr_x_preferred":[
        "\u0427\u0456\u043b\u0456\u043f\u0456"
    ],
    "qs_pg:aaroncc":"HR",
    "qs_pg:gn_country":"HR",
    "qs_pg:gn_fcode":"PPL",
    "qs_pg:gn_pop":856,
    "qs_pg:name":"\u010cilipi",
    "qs_pg:photos_9r":0,
    "qs_pg:photos_sr":0,
    "qs_pg:pop_sr":2,
    "qs_pg:qs_pg_placetype":"locality",
    "wof:name":"\u010cilipi",
    "wof:placetype":"locality",
    "wof:population":933
},
  "geometry": {"coordinates":[18.28472,42.54972],"type":"Point"}
}