{
  "type": "Feature",
  "properties": {
    "gn:admin1_code":"3.0",
    "gn:admin2_code":"11054968.0",
    "gn:asciiname":"Radulici",
    "gn:country_code":"HR",
    "gn:dem":257,
    "gn:feature_class":"P",
    "gn:feature_code":"PPL",
    "gn:name":"Radulici",
    "gn:population":0,
    "gn:timezone":"Europe/Zagreb",
    "iso:country":"HR",
    "wof:name":"Radulici",
    "wof:placetype":"locality"
},
  "geometry": {"coordinates":[17.54028,42.74083],"type":"Point"}
}