{
  "type": "Feature",
  "properties": {
    "gn:admin1_code":"20",
    "gn:admin2_code":"3198798.0",
    "gn:asciiname":"Tihocaj",
    "gn:country_code":"HR",
    "gn:dem":728,
    "gn:feature_class":"P",
    "gn:feature_code":"PPL",
    "gn:name":"Tiho\u010daj",
    "gn:population":3,
    "gn:timezone":"Europe/Zagreb",
    "iso:country":"HR",
    "wof:name":"Tihocaj",
    "wof:placetype":"locality",
    "wof:population":3
},
  "geometry": {"coordinates":[15.55,45.75],"type":"Point"}
}