{
  "type": "Feature",
  "properties": {
    "gn:admin1_code":"5.0",
    "gn:asciiname":"Cindrici",
    "gn:country_code":"HR",
    "gn:dem":360,
    "gn:feature_class":"P",
    "gn:feature_code":"PPL",
    "gn:name":"Cindri\u0107i",
    "gn:population":0,
    "gn:timezone":"Europe/Zagreb",
    "iso:country":"HR",
    "wof:name":"Cindrici",
    "wof:placetype":"locality"
},
  "geometry": {"coordinates":[15.73528,45.10056],"type":"Point"}
}