{
  "type": "Feature",
  "properties": {
    "gn:admin1_code":"14",
    "gn:asciiname":"Kosna",
    "gn:country_code":"HR",
    "gn:dem":254,
    "gn:feature_class":"P",
    "gn:feature_code":"PPLL",
    "gn:name":"Kosna",
    "gn:population":0,
    "gn:timezone":"Europe/Zagreb",
    "iso:country":"HR",
    "wof:name":"Kosna",
    "wof:placetype":"locality"
},
  "geometry": {"coordinates":[16.25861,45.09222000000001],"type":"Point"}
}