{
  "type": "Feature",
  "properties": {
    "gn:admin1_code":"10.0",
    "gn:asciiname":"Ada",
    "gn:country_code":"HR",
    "gn:dem":85,
    "gn:feature_class":"P",
    "gn:feature_code":"PPL",
    "gn:name":"Ada",
    "gn:population":200,
    "gn:timezone":"Europe/Zagreb",
    "iso:country":"HR",
    "wof:name":"Ada",
    "wof:placetype":"locality",
    "wof:population":200
},
  "geometry": {"coordinates":[18.68361,45.40556],"type":"Point"}
}