{
  "type": "Feature",
  "properties": {
    "gn:admin1_code":"15.0",
    "gn:asciiname":"Gizdici",
    "gn:country_code":"HR",
    "gn:dem":132,
    "gn:feature_class":"P",
    "gn:feature_code":"PPL",
    "gn:name":"Gizdi\u0107i",
    "gn:population":0,
    "gn:timezone":"Europe/Zagreb",
    "iso:country":"HR",
    "wof:name":"Gizdici",
    "wof:placetype":"locality"
},
  "geometry": {"coordinates":[16.5025,43.55472],"type":"Point"}
}