{
  "type": "Feature",
  "properties": {
    "gn:admin1_code":"15.0",
    "gn:asciiname":"Carici",
    "gn:country_code":"HR",
    "gn:dem":347,
    "gn:feature_class":"P",
    "gn:feature_code":"PPL",
    "gn:name":"\u010cari\u0107i",
    "gn:population":0,
    "gn:timezone":"Europe/Zagreb",
    "iso:country":"HR",
    "wof:name":"Carici",
    "wof:placetype":"locality"
},
  "geometry": {"coordinates":[16.64917,43.67583],"type":"Point"}
}