{
  "type": "Feature",
  "properties": {
    "gn:admin1_code":"19.0",
    "gn:asciiname":"Pilje",
    "gn:country_code":"HR",
    "gn:dem":512,
    "gn:feature_class":"P",
    "gn:feature_code":"PPL",
    "gn:name":"Pilje",
    "gn:population":0,
    "gn:timezone":"Europe/Zagreb",
    "iso:country":"HR",
    "wof:name":"Pilje",
    "wof:placetype":"locality"
},
  "geometry": {"coordinates":[16.12444,44.44806],"type":"Point"}
}