{
  "type": "Feature",
  "properties": {
    "gn:admin1_code":"4.0",
    "gn:admin2_code":"11054816.0",
    "gn:asciiname":"Valhova",
    "gn:country_code":"HR",
    "gn:dem":160,
    "gn:feature_class":"P",
    "gn:feature_code":"PPL",
    "gn:name":"Valhova",
    "gn:population":0,
    "gn:timezone":"Europe/Zagreb",
    "iso:country":"HR",
    "wof:name":"Valhova",
    "wof:placetype":"locality"
},
  "geometry": {"coordinates":[14.09972,44.99806],"type":"Point"}
}