{
  "type": "Feature",
  "properties": {
    "gn:admin1_code":"18.0",
    "gn:asciiname":"Novi Cakovci",
    "gn:country_code":"HR",
    "gn:dem":110,
    "gn:feature_class":"P",
    "gn:feature_code":"PPL",
    "gn:name":"Novi \u010cakovci",
    "gn:population":0,
    "gn:timezone":"Europe/Zagreb",
    "iso:country":"HR",
    "wof:name":"Novi Cakovci",
    "wof:placetype":"locality"
},
  "geometry": {"coordinates":[19.0375,45.20917],"type":"Point"}
}