{
  "type": "Feature",
  "properties": {
    "gn:admin1_code":"7.0",
    "gn:admin2_code":"11049214.0",
    "gn:asciiname":"Donja Pila",
    "gn:country_code":"HR",
    "gn:dem":244,
    "gn:feature_class":"P",
    "gn:feature_code":"PPL",
    "gn:name":"Donja Pila",
    "gn:population":0,
    "gn:timezone":"Europe/Zagreb",
    "iso:country":"HR",
    "wof:name":"Donja Pila",
    "wof:placetype":"locality"
},
  "geometry": {"coordinates":[15.93306,45.94778],"type":"Point"}
}