{
  "type": "Feature",
  "properties": {
    "gn:admin1_code":"19.0",
    "gn:asciiname":"Bogatnik",
    "gn:country_code":"HR",
    "gn:dem":69,
    "gn:feature_class":"P",
    "gn:feature_code":"PPL",
    "gn:name":"Bogatnik",
    "gn:population":0,
    "gn:timezone":"Europe/Zagreb",
    "iso:country":"HR",
    "wof:name":"Bogatnik",
    "wof:placetype":"locality"
},
  "geometry": {"coordinates":[15.81667,44.18333],"type":"Point"}
}