{
  "type": "Feature",
  "properties": {
    "gn:admin1_code":"5.0",
    "gn:asciiname":"Sarejevo",
    "gn:country_code":"HR",
    "gn:dem":277,
    "gn:feature_class":"P",
    "gn:feature_code":"PPL",
    "gn:name":"Sarejevo",
    "gn:population":0,
    "gn:timezone":"Europe/Zagreb",
    "iso:country":"HR",
    "wof:name":"Sarejevo",
    "wof:placetype":"locality"
},
  "geometry": {"coordinates":[15.77694,45.10167],"type":"Point"}
}