{
  "type": "Feature",
  "properties": {
    "gn:admin1_code":"8.0",
    "gn:asciiname":"Stara Pila",
    "gn:country_code":"HR",
    "gn:dem":645,
    "gn:feature_class":"P",
    "gn:feature_code":"PPL",
    "gn:name":"Stara Pila",
    "gn:population":0,
    "gn:timezone":"Europe/Zagreb",
    "iso:country":"HR",
    "wof:name":"Stara Pila",
    "wof:placetype":"locality"
},
  "geometry": {"coordinates":[15.23583,44.50556],"type":"Point"}
}