{
  "type": "Feature",
  "properties": {
    "gn:admin1_code":"15.0",
    "gn:asciiname":"Gudelji",
    "gn:country_code":"HR",
    "gn:dem":670,
    "gn:feature_class":"P",
    "gn:feature_code":"PPL",
    "gn:name":"Gudelji",
    "gn:population":0,
    "gn:timezone":"Europe/Zagreb",
    "iso:country":"HR",
    "wof:name":"Gudelji",
    "wof:placetype":"locality"
},
  "geometry": {"coordinates":[17.11806,43.39306],"type":"Point"}
}