{
  "type": "Feature",
  "properties": {
    "gn:admin1_code":"10",
    "gn:admin2_code":"3201431.0",
    "gn:asciiname":"Golinci",
    "gn:country_code":"HR",
    "gn:dem":91,
    "gn:feature_class":"P",
    "gn:feature_code":"PPL",
    "gn:name":"Golinci",
    "gn:population":431,
    "gn:timezone":"Europe/Zagreb",
    "iso:country":"HR",
    "wof:name":"Golinci",
    "wof:placetype":"locality",
    "wof:population":431
},
  "geometry": {"coordinates":[18.16583,45.68944000000001],"type":"Point"}
}