{
  "type": "Feature",
  "properties": {
    "gn:admin1_code":"18",
    "gn:admin2_code":"11054556.0",
    "gn:asciiname":"Strosinci",
    "gn:cc2":"HR",
    "gn:country_code":"HR",
    "gn:dem":80,
    "gn:feature_class":"P",
    "gn:feature_code":"PPL",
    "gn:name":"Stro\u0161inci",
    "gn:population":492,
    "gn:timezone":"Europe/Zagreb",
    "iso:country":"HR",
    "name:und_x_variant":[
        "Stra\u0161inci",
        "Stro\u0161inci"
    ],
    "wof:name":"Strosinci",
    "wof:placetype":"locality",
    "wof:population":492
},
  "geometry": {"coordinates":[19.065,44.91639],"type":"Point"}
}