{
  "type": "Feature",
  "properties": {
    "gn:admin1_code":"18",
    "gn:admin2_code":"11054556.0",
    "gn:asciiname":"Strosinci",
    "gn:cc2":"HR",
    "gn:country_code":"HR",
    "gn:dem":80,
    "gn:feature_class":"P",
    "gn:feature_code":"PPL",
    "gn:name":"Stro\u0161inci",
    "gn:population":492,
    "gn:timezone":"Europe/Zagreb",
    "iso:country":"HR",
    "name:bos_x_preferred":[
        "Stro\u0161inci"
    ],
    "name:hrv_x_preferred":[
        "Stro\u0161inci"
    ],
    "name:nld_x_preferred":[
        "Stro\u0161inci"
    ],
    "name:ron_x_preferred":[
        "Stro\u0161inci"
    ],
    "name:slv_x_preferred":[
        "Stro\u0161inci"
    ],
    "name:srp_x_preferred":[
        "\u0421\u0442\u0440\u043e\u0448\u0438\u043d\u0446\u0438"
    ],
    "name:ukr_x_preferred":[
        "\u0421\u0442\u0440\u043e\u0448\u0438\u043d\u0446\u0456"
    ],
    "name:und_x_variant":[
        "Stra\u0161inci",
        "Stro\u0161inci"
    ],
    "wof:name":"Strosinci",
    "wof:placetype":"locality",
    "wof:population":492
},
  "geometry": {"coordinates":[19.065,44.91639],"type":"Point"}
}