{
  "type": "Feature",
  "properties": {
    "gn:admin1_code":"8.0",
    "gn:asciiname":"Brevozo Polje",
    "gn:country_code":"HR",
    "gn:dem":563,
    "gn:feature_class":"P",
    "gn:feature_code":"PPL",
    "gn:name":"Brevozo Polje",
    "gn:population":0,
    "gn:timezone":"Europe/Zagreb",
    "iso:country":"HR",
    "wof:name":"Brevozo Polje",
    "wof:placetype":"locality"
},
  "geometry": {"coordinates":[15.31,44.59889],"type":"Point"}
}