{
  "type": "Feature",
  "properties": {
    "gn:admin1_code":"01",
    "gn:admin2_code":"3200709.0",
    "gn:asciiname":"Disnik",
    "gn:cc2":"HR",
    "gn:country_code":"HR",
    "gn:dem":123,
    "gn:feature_class":"P",
    "gn:feature_code":"PPLL",
    "gn:name":"Di\u0161nik",
    "gn:population":0,
    "gn:timezone":"Europe/Zagreb",
    "iso:country":"HR",
    "name:und_x_variant":[
        "Dissnik",
        "Di\u0161nik"
    ],
    "wof:name":"Disnik",
    "wof:placetype":"locality"
},
  "geometry": {"coordinates":[16.90139,45.60056],"type":"Point"}
}