{
  "type": "Feature",
  "properties": {
    "gn:admin1_code":"01",
    "gn:admin2_code":"3200709.0",
    "gn:asciiname":"Disnik",
    "gn:cc2":"HR",
    "gn:country_code":"HR",
    "gn:dem":123,
    "gn:feature_class":"P",
    "gn:feature_code":"PPLL",
    "gn:name":"Di\u0161nik",
    "gn:population":0,
    "gn:timezone":"Europe/Zagreb",
    "iso:country":"HR",
    "name:bos_x_preferred":[
        "Di\u0161nik"
    ],
    "name:fra_x_preferred":[
        "Di\u0161nik"
    ],
    "name:hrv_x_preferred":[
        "Di\u0161nik"
    ],
    "name:hun_x_preferred":[
        "Di\u0161nik"
    ],
    "name:nld_x_preferred":[
        "Di\u0161nik"
    ],
    "name:slv_x_preferred":[
        "Di\u0161nik"
    ],
    "name:spa_x_preferred":[
        "Di\u0161nik"
    ],
    "name:srp_x_preferred":[
        "\u0414\u0438\u0448\u043d\u0438\u043a"
    ],
    "name:ukr_x_preferred":[
        "\u0414\u0438\u0448\u043d\u0438\u043a"
    ],
    "name:und_x_variant":[
        "Dissnik"
    ],
    "wof:name":"Disnik",
    "wof:placetype":"locality"
},
  "geometry": {"coordinates":[16.90139,45.60056],"type":"Point"}
}