{
  "type": "Feature",
  "properties": {
    "gn:admin1_code":"2.0",
    "gn:admin2_code":"11049508.0",
    "gn:asciiname":"Blazevica Dol",
    "gn:country_code":"HR",
    "gn:dem":162,
    "gn:feature_class":"P",
    "gn:feature_code":"PPLL",
    "gn:name":"Bla\u017eevi\u0107a Dol",
    "gn:population":0,
    "gn:timezone":"Europe/Zagreb",
    "iso:country":"HR",
    "wof:name":"Blazevica Dol",
    "wof:placetype":"locality"
},
  "geometry": {"coordinates":[17.58222,45.23667],"type":"Point"}
}