{
  "type": "Feature",
  "properties": {
    "gn:admin1_code":"04",
    "gn:asciiname":"Vranici",
    "gn:country_code":"HR",
    "gn:dem":54,
    "gn:feature_class":"P",
    "gn:feature_code":"PPL",
    "gn:name":"Vrani\u0107i",
    "gn:population":0,
    "gn:timezone":"Europe/Zagreb",
    "iso:country":"HR",
    "wof:name":"Vranici",
    "wof:placetype":"locality"
},
  "geometry": {"coordinates":[13.61667,45.24556],"type":"Point"}
}