{
  "type": "Feature",
  "properties": {
    "gn:admin1_code":"15.0",
    "gn:asciiname":"Skore",
    "gn:country_code":"HR",
    "gn:dem":389,
    "gn:feature_class":"P",
    "gn:feature_code":"PPL",
    "gn:name":"\u0160kore",
    "gn:population":0,
    "gn:timezone":"Europe/Zagreb",
    "iso:country":"HR",
    "wof:name":"Skore",
    "wof:placetype":"locality"
},
  "geometry": {"coordinates":[17.25639,43.36333],"type":"Point"}
}