{
  "type": "Feature",
  "properties": {
    "gn:admin1_code":"15.0",
    "gn:asciiname":"Skore",
    "gn:country_code":"HR",
    "gn:dem":389,
    "gn:feature_class":"P",
    "gn:feature_code":"PPL",
    "gn:name":"\u0160kore",
    "gn:population":0,
    "gn:timezone":"Europe/Zagreb",
    "iso:country":"HR",
    "name:ell_x_preferred":[
        "\u03a3\u03c7\u03c9\u03c1\u03b9\u03ac\u03b4\u03b5\u03c2"
    ],
    "name:sqi_x_preferred":[
        "Skore"
    ],
    "wof:name":"Skore",
    "wof:placetype":"locality"
},
  "geometry": {"coordinates":[17.25639,43.36333],"type":"Point"}
}