{
  "type": "Feature",
  "properties": {
    "gn:admin1_code":"13.0",
    "gn:asciiname":"Krcic",
    "gn:country_code":"HR",
    "gn:dem":323,
    "gn:feature_class":"P",
    "gn:feature_code":"PPL",
    "gn:name":"Kr\u010di\u0107",
    "gn:population":0,
    "gn:timezone":"Europe/Zagreb",
    "iso:country":"HR",
    "wof:name":"Krcic",
    "wof:placetype":"locality"
},
  "geometry": {"coordinates":[16.27944,44.04],"type":"Point"}
}