{
  "type": "Feature",
  "properties": {
    "gn:admin1_code":"16",
    "gn:admin2_code":"11055013.0",
    "gn:asciiname":"Struga",
    "gn:country_code":"HR",
    "gn:dem":144,
    "gn:feature_class":"P",
    "gn:feature_code":"PPL",
    "gn:name":"Struga",
    "gn:population":461,
    "gn:timezone":"Europe/Zagreb",
    "iso:country":"HR",
    "wof:name":"Struga",
    "wof:placetype":"locality",
    "wof:population":461
},
  "geometry": {"coordinates":[16.64861,46.29889],"type":"Point"}
}