{
  "type": "Feature",
  "properties": {
    "gn:admin1_code":"5.0",
    "gn:asciiname":"Cicin Most",
    "gn:cc2":"HR",
    "gn:country_code":"HR",
    "gn:dem":283,
    "gn:feature_class":"P",
    "gn:feature_code":"PPL",
    "gn:name":"\u010ci\u010din Most",
    "gn:population":0,
    "gn:timezone":"Europe/Zagreb",
    "iso:country":"HR",
    "name:und_x_variant":[
        "\u010ci\u010da",
        "\u010ci\u010din Most"
    ],
    "wof:name":"Cicin Most",
    "wof:placetype":"locality"
},
  "geometry": {"coordinates":[15.46444,45.16194],"type":"Point"}
}