{
  "type": "Feature",
  "properties": {
    "gn:admin1_code":"11",
    "gn:admin2_code":"11049477.0",
    "gn:asciiname":"Seovica",
    "gn:country_code":"HR",
    "gn:dem":219,
    "gn:feature_class":"P",
    "gn:feature_code":"PPL",
    "gn:name":"\u0160eovica",
    "gn:population":307,
    "gn:timezone":"Europe/Zagreb",
    "iso:country":"HR",
    "name:bos_x_preferred":[
        "\u0160eovica"
    ],
    "name:hrv_x_preferred":[
        "\u0160eovica"
    ],
    "name:hun_x_preferred":[
        "\u0160eovica"
    ],
    "name:nld_x_preferred":[
        "\u0160eovica"
    ],
    "name:slv_x_preferred":[
        "\u0160eovica"
    ],
    "name:spa_x_preferred":[
        "\u0160eovica"
    ],
    "name:srp_x_preferred":[
        "\u0428\u0435\u043e\u0432\u0438\u0446\u0430"
    ],
    "name:ukr_x_preferred":[
        "\u0428\u0435\u043e\u0432\u0438\u0446\u044f"
    ],
    "name:und_x_variant":[
        "\u0160eovica"
    ],
    "wof:name":"Seovica",
    "wof:placetype":"locality",
    "wof:population":307
},
  "geometry": {"coordinates":[17.21667,45.41667],"type":"Point"}
}