{
  "type": "Feature",
  "properties": {
    "gn:admin1_code":"8.0",
    "gn:admin2_code":"11049287.0",
    "gn:asciiname":"Rukavina",
    "gn:country_code":"HR",
    "gn:dem":201,
    "gn:feature_class":"P",
    "gn:feature_code":"PPL",
    "gn:name":"Rukavina",
    "gn:population":0,
    "gn:timezone":"Europe/Zagreb",
    "iso:country":"HR",
    "wof:name":"Rukavina",
    "wof:placetype":"locality"
},
  "geometry": {"coordinates":[15.15528,44.47083],"type":"Point"}
}