{
  "type": "Feature",
  "properties": {
    "gn:admin1_code":"5.0",
    "gn:asciiname":"Obrovci",
    "gn:country_code":"HR",
    "gn:dem":263,
    "gn:feature_class":"P",
    "gn:feature_code":"PPL",
    "gn:name":"Obrovci",
    "gn:population":0,
    "gn:timezone":"Europe/Zagreb",
    "iso:country":"HR",
    "wof:name":"Obrovci",
    "wof:placetype":"locality"
},
  "geometry": {"coordinates":[15.66861,45.17611],"type":"Point"}
}