{
  "type": "Feature",
  "properties": {
    "gn:admin1_code":"11",
    "gn:admin2_code":"3193705.0",
    "gn:asciiname":"Gornja Obrijez",
    "gn:cc2":"HR",
    "gn:country_code":"HR",
    "gn:dem":190,
    "gn:feature_class":"P",
    "gn:feature_code":"PPL",
    "gn:name":"Gornja Obrije\u017e",
    "gn:population":81,
    "gn:timezone":"Europe/Zagreb",
    "iso:country":"HR",
    "name:bos_x_preferred":[
        "Gornja Obrije\u017e"
    ],
    "name:fra_x_preferred":[
        "Gornja Obrije\u017e"
    ],
    "name:hrv_x_preferred":[
        "Gornja Obrije\u017e"
    ],
    "name:hun_x_preferred":[
        "Gornja Obrije\u017e"
    ],
    "name:nld_x_preferred":[
        "Gornja Obrije\u017e"
    ],
    "name:slv_x_preferred":[
        "Gornja Obrije\u017e"
    ],
    "name:spa_x_preferred":[
        "Gornja Obrije\u017e"
    ],
    "name:srp_x_preferred":[
        "\u0413\u043e\u0440\u045a\u0430 \u041e\u0431\u0440\u0438\u0458\u0435\u0436"
    ],
    "name:ukr_x_preferred":[
        "\u0413\u043e\u0440\u043d\u044f \u041e\u0431\u0440\u0456\u0454\u0436"
    ],
    "name:und_x_variant":[
        "Gornja Obrie\u017e"
    ],
    "wof:name":"Gornja Obrijez",
    "wof:placetype":"locality",
    "wof:population":81
},
  "geometry": {"coordinates":[17.17083,45.47889],"type":"Point"}
}