{
  "type": "Feature",
  "properties": {
    "gn:admin1_code":"11",
    "gn:admin2_code":"3193705.0",
    "gn:asciiname":"Gornja Obrijez",
    "gn:cc2":"HR",
    "gn:country_code":"HR",
    "gn:dem":190,
    "gn:feature_class":"P",
    "gn:feature_code":"PPL",
    "gn:name":"Gornja Obrije\u017e",
    "gn:population":81,
    "gn:timezone":"Europe/Zagreb",
    "iso:country":"HR",
    "name:und_x_variant":[
        "Gornja Obrie\u017e",
        "Gornja Obrije\u017e"
    ],
    "wof:name":"Gornja Obrijez",
    "wof:placetype":"locality",
    "wof:population":81
},
  "geometry": {"coordinates":[17.17083,45.47889],"type":"Point"}
}