{
  "type": "Feature",
  "properties": {
    "gn:admin1_code":"15.0",
    "gn:asciiname":"Sokoli",
    "gn:country_code":"HR",
    "gn:dem":563,
    "gn:feature_class":"P",
    "gn:feature_code":"PPL",
    "gn:name":"Sokoli",
    "gn:population":0,
    "gn:timezone":"Europe/Zagreb",
    "iso:country":"HR",
    "wof:name":"Sokoli",
    "wof:placetype":"locality"
},
  "geometry": {"coordinates":[17.18444,43.30806],"type":"Point"}
}