{
  "type": "Feature",
  "properties": {
    "gn:admin1_code":"16",
    "gn:admin2_code":"11049303.0",
    "gn:asciiname":"Imbrijovec Jalzabetski",
    "gn:cc2":"HR",
    "gn:country_code":"HR",
    "gn:dem":177,
    "gn:feature_class":"P",
    "gn:feature_code":"PPL",
    "gn:name":"Imbrijovec Jal\u017eabetski",
    "gn:population":0,
    "gn:timezone":"Europe/Zagreb",
    "iso:country":"HR",
    "name:und_x_variant":[
        "Imbriovec",
        "Jal\u017eabetski Imbriovec",
        "Imbrijovec Jal\u017eabetski"
    ],
    "wof:name":"Imbrijovec Jalzabetski",
    "wof:placetype":"locality"
},
  "geometry": {"coordinates":[16.46027999999999,46.25694],"type":"Point"}
}