{
  "type": "Feature",
  "properties": {
    "gn:admin1_code":"18.0",
    "gn:asciiname":"Borinci",
    "gn:country_code":"HR",
    "gn:dem":85,
    "gn:feature_class":"P",
    "gn:feature_code":"PPL",
    "gn:name":"Borinci",
    "gn:population":0,
    "gn:timezone":"Europe/Zagreb",
    "iso:country":"HR",
    "wof:name":"Borinci",
    "wof:placetype":"locality"
},
  "geometry": {"coordinates":[18.76694,45.30778],"type":"Point"}
}