{
  "type": "Feature",
  "properties": {
    "gn:gn_country":"HR",
    "gn:gn_fcode":"PPL",
    "gn:gn_pop":1400,
    "gn:population":1173,
    "iso:country":"HR",
    "qs_pg:aaroncc":"HR",
    "qs_pg:gn_country":"HR",
    "qs_pg:gn_fcode":"PPL",
    "qs_pg:gn_pop":1400,
    "qs_pg:name":"Kru\u00b5evica",
    "qs_pg:name_adm0":"Hrvatska",
    "qs_pg:name_adm1":"Brodsko-Posavska",
    "qs_pg:photos_9r":0,
    "qs_pg:photos_sr":0,
    "qs_pg:pop_sr":3,
    "qs_pg:qs_pg_placetype":"locality",
    "qs_pg:qs_pg_placetype_gp":"Town",
    "qs_pg:woe_adm0":23424843,
    "woe:adm0_id":23424843,
    "woe:name_adm0":"Hrvatska",
    "woe:name_adm1":"Brodsko-Posavska",
    "woe:placetype":"Town",
    "wof:name":"Kru\u00b5evica",
    "wof:placetype":"locality",
    "wof:population":1173
},
  "geometry": {"coordinates":[18.48278,45.0775],"type":"Point"}
}