{
  "type": "Feature",
  "properties": {
    "gn:admin1_code":"8.0",
    "gn:asciiname":"Tomljenovici",
    "gn:country_code":"HR",
    "gn:dem":576,
    "gn:feature_class":"P",
    "gn:feature_code":"PPL",
    "gn:name":"Tomljenovi\u0107i",
    "gn:population":0,
    "gn:timezone":"Europe/Zagreb",
    "iso:country":"HR",
    "wof:name":"Tomljenovici",
    "wof:placetype":"locality"
},
  "geometry": {"coordinates":[15.23056,44.58889],"type":"Point"}
}