{
  "type": "Feature",
  "properties": {
    "gn:admin1_code":"19",
    "gn:admin2_code":"11049512.0",
    "gn:asciiname":"Donje Ceranje",
    "gn:cc2":"HR",
    "gn:country_code":"HR",
    "gn:dem":140,
    "gn:feature_class":"P",
    "gn:feature_code":"PPL",
    "gn:name":"Donje Ceranje",
    "gn:population":22,
    "gn:timezone":"Europe/Zagreb",
    "iso:country":"HR",
    "name:bos_x_preferred":[
        "Donje Ceranje"
    ],
    "name:fra_x_preferred":[
        "Donje Ceranje"
    ],
    "name:hrv_x_preferred":[
        "Donje Ceranje"
    ],
    "name:hun_x_preferred":[
        "Donje Ceranje"
    ],
    "name:nld_x_preferred":[
        "Donje Ceranje"
    ],
    "name:slv_x_preferred":[
        "Donje Ceranje"
    ],
    "name:srp_x_preferred":[
        "\u0414\u043e\u045a\u0435 \u0426\u0435\u0440\u0430\u045a\u0435"
    ],
    "name:ukr_x_preferred":[
        "\u0414\u043e\u043d\u0454 \u0426\u0435\u0440\u0430\u043d\u0454"
    ],
    "name:und_x_variant":[
        "Ceranje-Donje",
        "Cerane-Donje"
    ],
    "wof:name":"Donje Ceranje",
    "wof:placetype":"locality",
    "wof:population":22
},
  "geometry": {"coordinates":[15.59667,43.96417],"type":"Point"}
}