{
  "type": "Feature",
  "properties": {
    "gn:admin1_code":"19",
    "gn:admin2_code":"11049512.0",
    "gn:asciiname":"Donje Ceranje",
    "gn:cc2":"HR",
    "gn:country_code":"HR",
    "gn:dem":140,
    "gn:feature_class":"P",
    "gn:feature_code":"PPL",
    "gn:name":"Donje Ceranje",
    "gn:population":22,
    "gn:timezone":"Europe/Zagreb",
    "iso:country":"HR",
    "name:und_x_variant":[
        "Ceranje-Donje",
        "Cerane-Donje",
        "Donje Ceranje"
    ],
    "wof:name":"Donje Ceranje",
    "wof:placetype":"locality",
    "wof:population":22
},
  "geometry": {"coordinates":[15.59667,43.96417],"type":"Point"}
}