{
  "type": "Feature",
  "properties": {
    "gn:admin1_code":"05",
    "gn:admin2_code":"3187450.0",
    "gn:asciiname":"Kljucar",
    "gn:country_code":"HR",
    "gn:dem":262,
    "gn:feature_class":"P",
    "gn:feature_code":"PPL",
    "gn:name":"Klju\u010dar",
    "gn:population":86,
    "gn:timezone":"Europe/Zagreb",
    "iso:country":"HR",
    "wof:name":"Kljucar",
    "wof:placetype":"locality",
    "wof:population":86
},
  "geometry": {"coordinates":[15.76092,45.32982],"type":"Point"}
}