{
  "type": "Feature",
  "properties": {
    "gn:admin1_code":"14",
    "gn:admin2_code":"3196862.0",
    "gn:asciiname":"Gojlo",
    "gn:cc2":"HR",
    "gn:country_code":"HR",
    "gn:dem":189,
    "gn:feature_class":"P",
    "gn:feature_code":"PPLL",
    "gn:name":"Gojlo",
    "gn:population":0,
    "gn:timezone":"Europe/Zagreb",
    "iso:country":"HR",
    "name:und_x_variant":[
        "Gojilo",
        "Goilo",
        "Gojlo"
    ],
    "wof:name":"Gojlo",
    "wof:placetype":"locality"
},
  "geometry": {"coordinates":[16.8625,45.49056],"type":"Point"}
}