{
  "type": "Feature",
  "properties": {
    "gn:admin1_code":"8.0",
    "gn:asciiname":"Kastel",
    "gn:country_code":"HR",
    "gn:dem":34,
    "gn:feature_class":"P",
    "gn:feature_code":"PPL",
    "gn:name":"Ka\u0161tel",
    "gn:population":0,
    "gn:timezone":"Europe/Zagreb",
    "iso:country":"HR",
    "wof:name":"Kastel",
    "wof:placetype":"locality"
},
  "geometry": {"coordinates":[14.87972,44.59278],"type":"Point"}
}