{
  "type": "Feature",
  "properties": {
    "gn:admin1_code":"8.0",
    "gn:asciiname":"Kastel",
    "gn:country_code":"HR",
    "gn:dem":34,
    "gn:feature_class":"P",
    "gn:feature_code":"PPL",
    "gn:name":"Ka\u0161tel",
    "gn:population":0,
    "gn:timezone":"Europe/Zagreb",
    "iso:country":"HR",
    "name:ceb_x_preferred":[
        "Kastel"
    ],
    "name:deu_x_preferred":[
        "Kastel"
    ],
    "name:fra_x_preferred":[
        "Kastel"
    ],
    "name:pol_x_preferred":[
        "Kastel"
    ],
    "name:rus_x_preferred":[
        "\u041a\u0430\u0441\u0442\u0435\u043b\u044c"
    ],
    "name:slk_x_preferred":[
        "Kastel"
    ],
    "name:swe_x_preferred":[
        "Kastel"
    ],
    "name:ukr_x_preferred":[
        "\u041a\u0430\u0441\u0442\u0435\u043b\u044c"
    ],
    "wof:name":"Kastel",
    "wof:placetype":"locality"
},
  "geometry": {"coordinates":[14.87972,44.59278],"type":"Point"}
}