{
  "type": "Feature",
  "properties": {
    "gn:country":"HR",
    "gn:fcode":"PPL",
    "gn:population":0,
    "iso:country":"HR",
    "name:bos_x_preferred":[
        "Svetvin\u010denat"
    ],
    "name:ces_x_preferred":[
        "Svetvin\u010denat"
    ],
    "name:deu_x_preferred":[
        "Svetvin\u010denat"
    ],
    "name:eng_x_preferred":[
        "Svetvin\u010denat"
    ],
    "name:fra_x_preferred":[
        "Svetvin\u010denat"
    ],
    "name:hrv_x_preferred":[
        "Svetvin\u010denat"
    ],
    "name:hun_x_preferred":[
        "Svetvin\u010denat"
    ],
    "name:ita_x_preferred":[
        "Sanvincenti"
    ],
    "name:lat_x_preferred":[
        "Fanum Sancti Vincentii"
    ],
    "name:nld_x_preferred":[
        "Svetvin\u010denat"
    ],
    "name:pol_x_preferred":[
        "Gmina Svetvin\u010denat"
    ],
    "name:por_x_preferred":[
        "Svetvin\u010denat"
    ],
    "name:ron_x_preferred":[
        "Comuna Svetvin\u010denat"
    ],
    "name:rus_x_preferred":[
        "\u0421\u0432\u0435\u0442\u0432\u0438\u043d\u0447\u0435\u043d\u0430\u0442"
    ],
    "name:slv_x_preferred":[
        "Svetvin\u010denat"
    ],
    "name:spa_x_preferred":[
        "Svetvin\u010denat"
    ],
    "name:srp_x_preferred":[
        "\u0421\u0432\u0435\u0442\u0432\u0438\u043d\u0447\u0435\u043d\u0430\u0442"
    ],
    "name:ukr_x_preferred":[
        "\u0421\u0432\u0435\u0442\u0432\u0438\u043d\u0447\u0435\u043d\u0430\u0442"
    ],
    "name:vec_x_preferred":[
        "Sanvin\u00e7enti"
    ],
    "name:war_x_preferred":[
        "Svetvin\u010denat"
    ],
    "qs_pg:aaroncc":"HR",
    "qs_pg:gn_country":"HR",
    "qs_pg:gn_fcode":"PPL",
    "qs_pg:gn_pop":0,
    "qs_pg:name":"Svetvin\u010denat",
    "qs_pg:name_adm0":"Hrvatska",
    "qs_pg:name_adm1":"Istarska",
    "qs_pg:photos":687,
    "qs_pg:photos_1k":139,
    "qs_pg:photos_9k":3,
    "qs_pg:photos_9r":5,
    "qs_pg:photos_all":687,
    "qs_pg:photos_sr":8,
    "qs_pg:pop_sr":0,
    "qs_pg:qs_pg_placetype":"locality",
    "qs_pg:qs_pg_placetype_gp":"Town",
    "qs_pg:woe_adm0":23424843,
    "woe:adm0_id":23424843,
    "woe:name_adm0":"Hrvatska",
    "woe:name_adm1":"Istarska",
    "woe:placetype":"Town",
    "wof:name":"Svetvin\u010denat",
    "wof:placetype":"locality"
},
  "geometry": {"coordinates":[13.88361,45.08806],"type":"Point"}
}