{
  "type": "Feature",
  "properties": {
    "gn:admin1_code":"20.0",
    "gn:admin2_code":"3186602.0",
    "gn:asciiname":"Biskupec Zelinski",
    "gn:cc2":"HR",
    "gn:country_code":"HR",
    "gn:dem":212,
    "gn:feature_class":"P",
    "gn:feature_code":"PPL",
    "gn:name":"Bi\u0161kupec Zelinski",
    "gn:population":988,
    "gn:timezone":"Europe/Zagreb",
    "iso:country":"HR",
    "name:bos_x_preferred":[
        "Bi\u0161kupec Zelinski"
    ],
    "name:ceb_x_preferred":[
        "Bi\u0161kupec Zelinski"
    ],
    "name:hrv_x_preferred":[
        "Bi\u0161kupec Zelinski"
    ],
    "name:hun_x_preferred":[
        "Bi\u0161kupec Zelinski"
    ],
    "name:nld_x_preferred":[
        "Bi\u0161kupec Zelinski"
    ],
    "name:slv_x_preferred":[
        "Bi\u0161kupec Zelinski"
    ],
    "name:srp_x_preferred":[
        "\u0411\u0438\u0448\u043a\u0443\u043f\u0435\u0446 \u0417\u0435\u043b\u0438\u043d\u0441\u043a\u0438"
    ],
    "name:swe_x_preferred":[
        "Bi\u0161kupec Zelinski"
    ],
    "name:ukr_x_preferred":[
        "\u0411\u0438\u0448\u043a\u0443\u043f\u0435\u0446\u044c-\u0417\u0435\u043b\u0438\u043d\u0441\u044c\u043a\u0438\u0439"
    ],
    "name:und_x_variant":[
        "Zelinski Bi\u0161kupec",
        "Bi\u0161kupec",
        "Bi\u0161kupec Zelinski"
    ],
    "wof:name":"Biskupec Zelinski",
    "wof:placetype":"locality",
    "wof:population":988
},
  "geometry": {"coordinates":[16.2425,45.96194000000001],"type":"Point"}
}