{
  "type": "Feature",
  "properties": {
    "gn:admin1_code":"01",
    "gn:admin2_code":"3203981.0",
    "gn:asciiname":"Rajic Gudovacki",
    "gn:cc2":"HR",
    "gn:country_code":"HR",
    "gn:dem":111,
    "gn:feature_class":"P",
    "gn:feature_code":"PPL",
    "gn:name":"Raji\u0107 Gudova\u010dki",
    "gn:population":0,
    "gn:timezone":"Europe/Zagreb",
    "iso:country":"HR",
    "name:und_x_variant":[
        "Rai\u0107",
        "Rai\u0107i",
        "Raji\u0107i",
        "Ria\u0107",
        "Raji\u0107 Gudova\u010dki"
    ],
    "wof:name":"Rajic Gudovacki",
    "wof:placetype":"locality"
},
  "geometry": {"coordinates":[16.71444,45.90028],"type":"Point"}
}