{
  "type": "Feature",
  "properties": {
    "gn:country":"HR",
    "iso:country":"HR",
    "qs_pg:aaroncc":"HR",
    "qs_pg:gn_country":"HR",
    "qs_pg:name":"Lokva Rogoznica",
    "qs_pg:name_adm0":"Hrvatska",
    "qs_pg:name_adm1":"Splitsko-Dalmatinska",
    "qs_pg:photos":39,
    "qs_pg:photos_1k":8,
    "qs_pg:photos_9k":1,
    "qs_pg:photos_9r":2,
    "qs_pg:photos_all":39,
    "qs_pg:photos_sr":2,
    "qs_pg:pop_sr":0,
    "qs_pg:qs_pg_placetype":"locality",
    "qs_pg:qs_pg_placetype_gp":"Town",
    "qs_pg:woe_adm0":23424843,
    "woe:adm0_id":23424843,
    "woe:name_adm0":"Hrvatska",
    "woe:name_adm1":"Splitsko-Dalmatinska",
    "woe:placetype":"Town",
    "wof:name":"Lokva Rogoznica",
    "wof:placetype":"locality"
},
  "geometry": {"coordinates":[16.766853,43.408461],"type":"Point"}
}