{
  "type": "Feature",
  "properties": {
    "gn:admin1_code":"5.0",
    "gn:admin2_code":"11049270.0",
    "gn:asciiname":"Radocaj",
    "gn:country_code":"HR",
    "gn:dem":190,
    "gn:feature_class":"P",
    "gn:feature_code":"PPL",
    "gn:name":"Radocaj",
    "gn:population":0,
    "gn:timezone":"Europe/Zagreb",
    "iso:country":"HR",
    "wof:name":"Radocaj",
    "wof:placetype":"locality"
},
  "geometry": {"coordinates":[15.36111,45.39],"type":"Point"}
}