{
  "type": "Feature",
  "properties": {
    "iso:country":"HR",
    "name:bos_x_preferred":[
        "Zaklopatica"
    ],
    "name:eng_x_preferred":[
        "Zaklopatica"
    ],
    "name:hrv_x_preferred":[
        "Zaklopatica"
    ],
    "name:hun_x_preferred":[
        "Zaklopatica"
    ],
    "name:nld_x_preferred":[
        "Zaklopatica"
    ],
    "name:slv_x_preferred":[
        "Zaklopatica"
    ],
    "name:srp_x_preferred":[
        "\u0417\u0430\u043a\u043b\u043e\u043f\u0430\u0442\u0438\u0446\u0430"
    ],
    "name:ukr_x_preferred":[
        "\u0417\u0430\u043a\u043b\u043e\u043f\u0430\u0442\u0438\u0446\u044f"
    ],
    "qs_pg:aaroncc":"HR",
    "qs_pg:name":"Zaklopatica",
    "qs_pg:name_adm0":"Hrvatska",
    "qs_pg:name_adm1":"Dubrova\u010dko-neretvanska",
    "qs_pg:photos":40,
    "qs_pg:photos_1k":8,
    "qs_pg:photos_9k":1,
    "qs_pg:photos_9r":2,
    "qs_pg:photos_all":40,
    "qs_pg:photos_sr":2,
    "qs_pg:pop_sr":0,
    "qs_pg:qs_pg_placetype":"locality",
    "qs_pg:qs_pg_placetype_gp":"Town",
    "qs_pg:woe_adm0":23424843,
    "woe:adm0_id":23424843,
    "woe:name_adm0":"Hrvatska",
    "woe:name_adm1":"Dubrova\u010dko-neretvanska",
    "woe:placetype":"Town",
    "wof:name":"Zaklopatica",
    "wof:placetype":"locality"
},
  "geometry": {"coordinates":[16.874707,42.771825],"type":"Point"}
}