{
  "type": "Feature",
  "properties": {
    "gn:admin1_code":"07",
    "gn:admin2_code":"11049012.0",
    "gn:asciiname":"Prislin",
    "gn:country_code":"HR",
    "gn:dem":253,
    "gn:feature_class":"P",
    "gn:feature_code":"PPL",
    "gn:name":"Pri\u0161lin",
    "gn:population":430,
    "gn:timezone":"Europe/Zagreb",
    "iso:country":"HR",
    "wof:name":"Prislin",
    "wof:placetype":"locality",
    "wof:population":430
},
  "geometry": {"coordinates":[15.6617,46.21078],"type":"Point"}
}