{
  "type": "Feature",
  "properties": {
    "gn:admin1_code":"19.0",
    "gn:asciiname":"Krajnovici",
    "gn:country_code":"HR",
    "gn:dem":757,
    "gn:feature_class":"P",
    "gn:feature_code":"PPL",
    "gn:name":"Krajnovi\u0107i",
    "gn:population":0,
    "gn:timezone":"Europe/Zagreb",
    "iso:country":"HR",
    "wof:name":"Krajnovici",
    "wof:placetype":"locality"
},
  "geometry": {"coordinates":[15.92778,44.39306],"type":"Point"}
}