{
  "type": "Feature",
  "properties": {
    "gn:admin1_code":"8.0",
    "gn:asciiname":"Srdelj",
    "gn:country_code":"HR",
    "gn:dem":555,
    "gn:feature_class":"P",
    "gn:feature_code":"PPL",
    "gn:name":"Srdelj",
    "gn:population":0,
    "gn:timezone":"Europe/Zagreb",
    "iso:country":"HR",
    "wof:name":"Srdelj",
    "wof:placetype":"locality"
},
  "geometry": {"coordinates":[15.33056,44.55056],"type":"Point"}
}