{
  "type": "Feature",
  "properties": {
    "gn:admin1_code":"20",
    "gn:admin2_code":"3198798.0",
    "gn:asciiname":"Gracac Slaveticki",
    "gn:cc2":"HR",
    "gn:country_code":"HR",
    "gn:dem":493,
    "gn:feature_class":"P",
    "gn:feature_code":"PPL",
    "gn:name":"Gra\u010dac Slaveti\u0107ki",
    "gn:population":5,
    "gn:timezone":"Europe/Zagreb",
    "iso:country":"HR",
    "name:und_x_variant":[
        "Gra\u010dac",
        "Gra\u010dac Slaveti\u0107ki"
    ],
    "wof:name":"Gracac Slaveticki",
    "wof:placetype":"locality",
    "wof:population":5
},
  "geometry": {"coordinates":[15.51667,45.73333],"type":"Point"}
}