{
  "type": "Feature",
  "properties": {
    "gn:admin1_code":"14.0",
    "gn:asciiname":"Kamenik",
    "gn:country_code":"HR",
    "gn:dem":147,
    "gn:feature_class":"P",
    "gn:feature_code":"PPL",
    "gn:name":"Kamenik",
    "gn:population":0,
    "gn:timezone":"Europe/Zagreb",
    "iso:country":"HR",
    "name:ceb_x_preferred":[
        "Kamenik"
    ],
    "name:deu_x_preferred":[
        "Kamenik"
    ],
    "name:ron_x_preferred":[
        "Kamenik"
    ],
    "name:slv_x_preferred":[
        "Kamenik"
    ],
    "name:swe_x_preferred":[
        "Kamenik"
    ],
    "wof:name":"Kamenik",
    "wof:placetype":"locality"
},
  "geometry": {"coordinates":[16.78889,45.2025],"type":"Point"}
}