{
  "type": "Feature",
  "properties": {
    "gn:country":"HR",
    "gn:fcode":"PPL",
    "gn:population":0,
    "iso:country":"HR",
    "name:ara_x_preferred":[
        "\u0645\u0648\u062f\u0631\u064a\u0643\u0634\u0627"
    ],
    "name:bos_x_preferred":[
        "Modri\u010da"
    ],
    "name:bul_x_preferred":[
        "\u041c\u043e\u0434\u0440\u0438\u0447\u0430"
    ],
    "name:cat_x_preferred":[
        "Modri\u010da"
    ],
    "name:ces_x_preferred":[
        "Modri\u010da"
    ],
    "name:deu_x_preferred":[
        "Modri\u010da"
    ],
    "name:fas_x_preferred":[
        "\u0645\u0648\u062f\u0631\u06cc\u0686\u0627"
    ],
    "name:fra_x_preferred":[
        "Modri\u010da"
    ],
    "name:hrv_x_preferred":[
        "Modri\u010da"
    ],
    "name:hye_x_preferred":[
        "\u0544\u0578\u0564\u0580\u056b\u0579\u0561"
    ],
    "name:ita_x_preferred":[
        "Modri\u010da"
    ],
    "name:jpn_x_preferred":[
        "\u30e2\u30c9\u30ea\u30c1\u30e3"
    ],
    "name:lit_x_preferred":[
        "Modri\u010da"
    ],
    "name:mwl_x_preferred":[
        "Modri\u010da"
    ],
    "name:nld_x_preferred":[
        "Modri\u010da"
    ],
    "name:nor_x_preferred":[
        "Modri\u010da"
    ],
    "name:pol_x_preferred":[
        "Modri\u010da"
    ],
    "name:por_x_preferred":[
        "Modri\u010da"
    ],
    "name:rus_x_preferred":[
        "\u041c\u043e\u0434\u0440\u0438\u0447\u0430"
    ],
    "name:spa_x_preferred":[
        "Modri\u010da"
    ],
    "name:sqi_x_preferred":[
        "Modri\u00e7a"
    ],
    "name:srp_x_preferred":[
        "\u041c\u043e\u0434\u0440\u0438\u0447\u0430"
    ],
    "name:tur_x_preferred":[
        "Modri\u010da"
    ],
    "name:ukr_x_preferred":[
        "\u041c\u043e\u0434\u0440\u0438\u0447\u0430"
    ],
    "name:urd_x_preferred":[
        "\u0645\u0648\u062f\u0631\u06cc\u0686\u0627"
    ],
    "name:zho_x_preferred":[
        "\u83ab\u5fb7\u91cc\u67e5"
    ],
    "qs_pg:aaroncc":"HR",
    "qs_pg:gn_country":"HR",
    "qs_pg:gn_fcode":"PPL",
    "qs_pg:gn_pop":0,
    "qs_pg:name":"Modri\u010da",
    "qs_pg:name_adm0":"Bosna i Hercegovina",
    "qs_pg:name_adm1":"Republika Srpska",
    "qs_pg:photos":34,
    "qs_pg:photos_1k":7,
    "qs_pg:photos_9k":1,
    "qs_pg:photos_9r":2,
    "qs_pg:photos_all":34,
    "qs_pg:photos_sr":2,
    "qs_pg:pop_sr":0,
    "qs_pg:qs_pg_placetype":"locality",
    "qs_pg:qs_pg_placetype_gp":"Town",
    "qs_pg:woe_adm0":23424761,
    "woe:adm0_id":23424761,
    "woe:name_adm0":"Bosna i Hercegovina",
    "woe:name_adm1":"Republika Srpska",
    "woe:placetype":"Town",
    "wof:name":"Modri\u010da",
    "wof:placetype":"locality",
    "wof:population":188
},
  "geometry": {"coordinates":[17.72722,45.23972],"type":"Point"}
}