{
  "type": "Feature",
  "properties": {
    "gn:gn_country":"HR",
    "gn:gn_fcode":"PPL",
    "gn:gn_pop":0,
    "gn:population":188,
    "iso:country":"HR",
    "qs_pg:aaroncc":"HR",
    "qs_pg:gn_country":"HR",
    "qs_pg:gn_fcode":"PPL",
    "qs_pg:gn_pop":0,
    "qs_pg:name":"Modri\u010da",
    "qs_pg:name_adm0":"Bosna i Hercegovina",
    "qs_pg:name_adm1":"Republika Srpska",
    "qs_pg:photos":34,
    "qs_pg:photos_1k":7,
    "qs_pg:photos_9k":1,
    "qs_pg:photos_9r":2,
    "qs_pg:photos_all":34,
    "qs_pg:photos_sr":2,
    "qs_pg:pop_sr":0,
    "qs_pg:qs_pg_placetype":"locality",
    "qs_pg:qs_pg_placetype_gp":"Town",
    "qs_pg:woe_adm0":23424761,
    "woe:adm0_id":23424761,
    "woe:name_adm0":"Bosna i Hercegovina",
    "woe:name_adm1":"Republika Srpska",
    "woe:placetype":"Town",
    "wof:name":"Modri\u010da",
    "wof:placetype":"locality",
    "wof:population":188
},
  "geometry": {"coordinates":[17.72722,45.23972],"type":"Point"}
}