{
  "type": "Feature",
  "properties": {
    "gn:admin1_code":"3.0",
    "gn:admin2_code":"3196753.0",
    "gn:asciiname":"Krucica",
    "gn:country_code":"HR",
    "gn:dem":73,
    "gn:feature_class":"P",
    "gn:feature_code":"PPL",
    "gn:name":"Kru\u010dica",
    "gn:population":34,
    "gn:timezone":"Europe/Zagreb",
    "iso:country":"HR",
    "wof:name":"Krucica",
    "wof:placetype":"locality",
    "wof:population":34
},
  "geometry": {"coordinates":[16.84944,42.76639],"type":"Point"}
}