{
  "type": "Feature",
  "properties": {
    "gn:admin1_code":"15.0",
    "gn:asciiname":"Gubavica",
    "gn:country_code":"HR",
    "gn:dem":311,
    "gn:feature_class":"P",
    "gn:feature_code":"PPL",
    "gn:name":"Gubavica",
    "gn:population":0,
    "gn:timezone":"Europe/Zagreb",
    "iso:country":"HR",
    "name:bos_x_preferred":[
        "Gubavica"
    ],
    "name:ceb_x_preferred":[
        "Gubavica"
    ],
    "name:ell_x_preferred":[
        "\u0393\u03ba\u03bf\u03c5\u03bc\u03c0\u03ac\u03b2\u03b9\u03c4\u03c3\u03b1"
    ],
    "name:fra_x_preferred":[
        "Gubavica"
    ],
    "name:hrv_x_preferred":[
        "Gubavica"
    ],
    "name:srp_x_preferred":[
        "\u0413\u0443\u0431\u0430\u0432\u0438\u0446\u0430"
    ],
    "name:swe_x_preferred":[
        "Gubavica"
    ],
    "wof:name":"Gubavica",
    "wof:placetype":"locality"
},
  "geometry": {"coordinates":[16.74056,43.62806],"type":"Point"}
}