{
  "type": "Feature",
  "properties": {
    "gn:admin1_code":"08",
    "gn:admin2_code":"11049286.0",
    "gn:asciiname":"Medak",
    "gn:country_code":"HR",
    "gn:dem":576,
    "gn:feature_class":"P",
    "gn:feature_code":"PPL",
    "gn:name":"Medak",
    "gn:population":62,
    "gn:timezone":"Europe/Zagreb",
    "iso:country":"HR",
    "name:ara_x_preferred":[
        "\u0645\u064a\u062f\u0627\u0643"
    ],
    "name:bpy_x_preferred":[
        "\u09ae\u09c7\u09a6\u0995"
    ],
    "name:cat_x_preferred":[
        "Medak"
    ],
    "name:ceb_x_preferred":[
        "Medak"
    ],
    "name:hin_x_preferred":[
        "\u092e\u0947\u0926\u0915"
    ],
    "name:ita_x_preferred":[
        "Medak"
    ],
    "name:mlg_x_preferred":[
        "Medak"
    ],
    "name:msa_x_preferred":[
        "Medak"
    ],
    "name:nep_x_preferred":[
        "\u092e\u0947\u0902\u0921\u0915"
    ],
    "name:new_x_preferred":[
        "\u092e\u0947\u0921\u0915"
    ],
    "name:ori_x_preferred":[
        "\u0b2e\u0b47\u0b26\u0b3e\u0b15\u0b4d"
    ],
    "name:swe_x_preferred":[
        "Medak"
    ],
    "name:tam_x_preferred":[
        "\u0bae\u0bc7\u0ba4\u0b95\u0bcd"
    ],
    "name:urd_x_preferred":[
        "\u0645\u06cc\u0688\u06a9"
    ],
    "name:vie_x_preferred":[
        "Medak"
    ],
    "name:zho_x_preferred":[
        "\u6885\u8fbe\u514b"
    ],
    "wof:name":"Medak",
    "wof:placetype":"locality",
    "wof:population":62
},
  "geometry": {"coordinates":[15.50776,44.45541],"type":"Point"}
}