{
  "type": "Feature",
  "properties": {
    "gn:admin1_code":"08",
    "gn:admin2_code":"11049286.0",
    "gn:asciiname":"Medak",
    "gn:country_code":"HR",
    "gn:dem":576,
    "gn:feature_class":"P",
    "gn:feature_code":"PPL",
    "gn:name":"Medak",
    "gn:population":62,
    "gn:timezone":"Europe/Zagreb",
    "iso:country":"HR",
    "wof:name":"Medak",
    "wof:placetype":"locality",
    "wof:population":62
},
  "geometry": {"coordinates":[15.50776,44.45541],"type":"Point"}
}